Workbook

Sheet Invoice Template
K1: This is X spend (Aleph to invoice the clients) - Cost to pay X in column CS | CS1: Cost to pay the partner
L5: IO Attributes | S5: Local Gross Revenue (Net of LOI) | Y5: Local Direct Tax | AE5: Local Commission | AK5: Local Withholding Tax | AQ5: Local Regulatory Complexity Fee | AW5: Local Currency Complexity Fee | BC5: Local Total Commission and Tax | BI5: Entered Currency Direct Tax | BO5: Entered Currency Commission | BU5: Entered Currency Withholding Tax | CA5: Entered Currency Regulatory Complexity Fee | CG5: Entered Currency Currency Complexity Fee | CM5: Entered Currency Total Commission and Tax | CS5: Entered Currency | DF5: Update from Monthly FX File as of Jan'26(Corp.rate)
A6: Campaign ID | B6: IO# | C6: Salesforce IO ID | D6: Currency | E6: Amplify Sponsorship | F6: Twitter Takeover | G6: Promoted Ads | H6: Twitter Publisher Network | I6: Amplify Instream Pre-Roll | J6: Commission Rate | K6: Revenue Net of LOI | L6: Currency | M6: IO FX Rate | N6: Country Billed from | O6: Direct Tax Rate | P6: W/H Tax rate | Q6: Regulatory Complexity Fee | R6: Currency Complexity Fee | S6: Local PAc | T6: Local PTr | U6: Local PTw | V6: Local TPN | W6: Local Amplify | X6: Local Gross Revenue (Net of LOI) Total | Y6: Local PAc Direct Tax | Z6: Local PTr Direct Tax | AA6: Local PTw Direct Tax | AB6: Local TPN Direct Tax | AC6: Local Amplify Direct Tax | AD6: Local Direct Tax Total | AE6: Local PAc Commission | AF6: Local PTr Commission | AG6: Local PTw Commission | AH6: Local TPN Commission | AI6: Local Amplify Commission | AJ6: Local Commission Total | AK6: Local PAc W/H Tax | AL6: Local PTr W/H Tax | AM6: Local PTw W/H Tax | AN6: Local TPN W/H Tax | AO6: Local Amplify W/H Tax | AP6: Local Withholding Tax Total | AQ6: Local PAc Reg Fee | AR6: Local PTr Reg Fee | AS6: Local PTw Reg Fee | AT6: Local TPN Reg Fee | AU6: Local Amplify Reg Fee | AV6: Local Reg Fee Total | AW6: Local PAc Curr. Complex Fee | AX6: Local PTr Curr. Complex Fee | AY6: Local PTw Curr. Complex Fee | AZ6: Local TPN Curr. Complex Fee | BA6: Local Amplify Curr. Complex Fee | BB6: Local Curr. Complex Fee Total | BC6: Local PAc Total | BD6: Local PTr Total | BE6: Local PTw Total | BF6: Local TPN Total | BG6: Local Amplify Total | BH6: Local Total Comm & Tax | BI6: PAc Total | BJ6: PTr Total | BK6: PTw Total | BL6: TPN Total | BM6: Amplify Total | BN6: Direct Tax Total | BO6: PAc Total | BP6: PTr Total | BQ6: PTw Total | BR6: TPN Total | BS6: Amplify Total | BT6: Commission Total | BU6: PAc Total | BV6: PTr Total | BW6: PTw Total | BX6: TPN Total | BY6: Amplify Total | BZ6: Withholding Tax Total | CA6: PAc Total | CB6: PTr Total | CC6: PTw Total | CD6: TPN Total | CE6: Amplify Total | CF6: Regulatory Complexity Fee Total | CG6: PAc Total | CH6: PTr Total | CI6: PTw Total | CJ6: TPN Total | CK6: Amplify Total | CL6: Currency Complexity Fee Total | CM6: PAc Consol Total | CN6: PTr Consol Total | CO6: PTw Consol Total | CP6: TPN Consol Total | CQ6: Amplify Consol Total | CR6: Consol Total Comm & Tax | CS6: Total Invoiced amount | CT6: Comments for 0% Direct tax | CU6: Billed Currency | CV6: FX Rate to USD | CW6: USD Revenue Net of LOI | CX6: USD Total Direct Tax | CY6: USD Total Commission | CZ6: USD Total W/H Tax | DA6: USD Total Regulatory Complexity Fee | DB6: USD Total Currency Complexity Fee | DC6: USD Total Invoiced Amt | DD6: Campaign Name | DF6: Billed Currency | DG6: Fx Rate to USD
A7: 40459084 | B7: T2694837 | C7: 269483701 | D7: ARS | G7: 911867.62 | J7: =VLOOKUP($B7,'IMS Commission List'!E:CE,79,0)/100 -> 0.15 | K7: =SUM(E7:I7) -> 911867.62 | L7: =VLOOKUP($B7,'IMS Commission List'!E:V,18,0) -> ARS | M7: 1 | N7: =VLOOKUP($B7,'IMS Commission List'!E:T,16,0) -> MX | O7: =VLOOKUP($B7,'IMS Commission List'!E:CF,80,0) -> 0.049 | P7: =VLOOKUP($B7,'IMS Commission List'!E:CG,81,0) -> 0.1575 | Q7: =VLOOKUP($B7,'IMS Commission List'!E:CP,90,0) -> 0.03 | R7: =VLOOKUP($B7,'IMS Commission List'!E:CQ,91,0) -> 0.04 | S7: =$E7*$M7 -> 0 | T7: =$F7*$M7 -> 0 | U7: =$G7*$M7 -> 911867.62 | V7: =$H7*$M7 -> 0 | W7: =$I7*$M7 -> 0 | X7: =$K7*$M7 -> 911867.62 | Y7: =(S7*$O7)*(1-J7) -> 0 | Z7: =(T7*$O7)*(1-J7) -> 0 | AA7: =(U7*$O7)*(1-J7) -> 37979.286 | AB7: =(V7*$O7)*(1-J7) -> 0 | AC7: =(W7*$O7)*(1-J7) -> 0 | AD7: =SUM(Y7:AC7) -> 37979.286 | AE7: =S7*$J7 -> 0 | AF7: =T7*$J7 -> 0 | AG7: =U7*$J7 -> 136780.14 | AH7: =V7*$J7 -> 0 | AI7: =W7*$J7 -> 0 | AJ7: =SUM(AE7:AI7) -> 136780.14 | AK7: =($P7*S7)*(1-$J7) -> 0 | AL7: =($P7*T7)*(1-$J7) -> 0 | AM7: =($P7*U7)*(1-$J7) -> 122076.28 | AN7: =($P7*V7)*(1-$J7) -> 0 | AO7: =($P7*W7)*(1-$J7) -> 0 | AP7: =SUM(AK7:AO7) -> 122076.28 | AQ7: =S7*$Q7 -> 0 | AR7: =T7*$Q7 -> 0 | AS7: =U7*$Q7 -> 27356.029 | AT7: =V7*$Q7 -> 0 | AU7: =W7*$Q7 -> 0 | AV7: =SUM(AQ7:AU7) -> 27356.029 | AW7: =S7*$R7 -> 0 | AX7: =T7*$R7 -> 0 | AY7: =U7*$R7 -> 36474.705 | AZ7: =V7*$R7 -> 0 | BA7: =W7*$R7 -> 0 | BB7: =SUM(AW7:BA7) -> 36474.705 | BC7: =$Y7+$AE7+$AK7+$AQ7+AW7 -> 0 | BD7: =$Z7+$AF7+$AL7+AR7+AX7 -> 0 | BE7: =$AA7+$AG7+$AM7+AS7+AY7 -> 360666.44 | BF7: =$AB7+$AH7+$AN7+AT7+AZ7 -> 0 | BG7: =$AC7+$AI7+$AO7+AU7+BA7 -> 0 | BH7: =SUM(BC7:BG7) -> 360666.44 | BI7: =$Y7/$M7 -> 0 | BJ7: =$Z7/$M7 -> 0 | BK7: =$AA7/$M7 -> 37979.286 | BL7: =$AB7/$M7 -> 0 | BM7: =$AC7/$M7 -> 0 | BN7: =$AD7/$M7 -> 37979.286 | BO7: =$AE7/$M7 -> 0 | BP7: =$AF7/$M7 -> 0 | BQ7: =$AG7/$M7 -> 136780.14 | BR7: =$AH7/$M7 -> 0 | BS7: =$AI7/$M7 -> 0 | BT7: =$AJ7/$M7 -> 136780.14 | BU7: =$AK7/$M7 -> 0 | BV7: =$AL7/$M7 -> 0 | BW7: =$AM7/$M7 -> 122076.28 | BX7: =$AN7/$M7 -> 0 | BY7: =$AO7/$M7 -> 0 | BZ7: =$AP7/$M7 -> 122076.28 | CA7: =AQ7/$M7 -> 0 | CB7: =AR7/$M7 -> 0 | CC7: =AS7/$M7 -> 27356.029 | CD7: =AT7/$M7 -> 0 | CE7: =AU7/$M7 -> 0 | CF7: =AV7/$M7 -> 27356.029 | CG7: =AW7/$M7 -> 0 | CH7: =AX7/$M7 -> 0 | ... CL7: =BB7/$M7 -> 36474.705 | CM7: =$BC7/$M7 -> 0 | CN7: =$BD7/$M7 -> 0 | CO7: =$BE7/$M7 -> 360666.44 | CP7: =$BF7/$M7 -> 0 | CQ7: =$BG7/$M7 -> 0 | CR7: =SUM(CM7:CQ7) -> 360666.44 | CS7: =K7-CR7 -> 551201.18 | CU7: =D7 -> ARS | CV7: =VLOOKUP(CU7,DF:DG,2,0) -> 0.0006918517 | CW7: =K7*CV7 -> 630.87716 | CX7: =BN7*CV7 -> 26.276034 | CY7: =BT7*CV7 -> 94.631574 | CZ7: =BZ7*CV7 -> 84.45868 | DA7: =CF7*CV7 -> 18.926315 | DB7: =CL7*CV7 -> 25.235087 | DC7: =CS7*CV7 -> 381.34947 | DD7: =VLOOKUP(A7,'Billing Report'!H:I,2,FALSE) -> BULL_LEMON_AR_INTERACCION_TW_ALL_BROAD_AO_NEW | DF7: AED | DG7: 0.27227703
A8: 40931692 | B8: T2751490 | C8: 275149001 | D8: ARS | G8: 900539.44 | J8: =VLOOKUP($B8,'IMS Commission List'!E:CE,79,0)/100 -> 0.15 | K8: =SUM(E8:I8) -> 900539.44 | L8: =VLOOKUP($B8,'IMS Commission List'!E:V,18,0) -> ARS | M8: 1 | N8: =VLOOKUP($B8,'IMS Commission List'!E:T,16,0) -> MX | O8: =VLOOKUP($B8,'IMS Commission List'!E:CF,80,0) -> 0.049 | P8: =VLOOKUP($B8,'IMS Commission List'!E:CG,81,0) -> 0.1575 | Q8: =VLOOKUP($B8,'IMS Commission List'!E:CP,90,0) -> 0.03 | R8: =VLOOKUP($B8,'IMS Commission List'!E:CQ,91,0) -> 0.04 | S8: =$E8*$M8 -> 0 | T8: =$F8*$M8 -> 0 | U8: =$G8*$M8 -> 900539.44 | V8: =$H8*$M8 -> 0 | W8: =$I8*$M8 -> 0 | X8: =$K8*$M8 -> 900539.44 | Y8: =(S8*$O8)*(1-J8) -> 0 | Z8: =(T8*$O8)*(1-J8) -> 0 | AA8: =(U8*$O8)*(1-J8) -> 37507.468 | AB8: =(V8*$O8)*(1-J8) -> 0 | AC8: =(W8*$O8)*(1-J8) -> 0 | AD8: =SUM(Y8:AC8) -> 37507.468 | AE8: =S8*$J8 -> 0 | AF8: =T8*$J8 -> 0 | AG8: =U8*$J8 -> 135080.92 | AH8: =V8*$J8 -> 0 | AI8: =W8*$J8 -> 0 | AJ8: =SUM(AE8:AI8) -> 135080.92 | AK8: =($P8*S8)*(1-$J8) -> 0 | AL8: =($P8*T8)*(1-$J8) -> 0 | AM8: =($P8*U8)*(1-$J8) -> 120559.72 | AN8: =($P8*V8)*(1-$J8) -> 0 | AO8: =($P8*W8)*(1-$J8) -> 0 | AP8: =SUM(AK8:AO8) -> 120559.72 | AQ8: =S8*$Q8 -> 0 | AR8: =T8*$Q8 -> 0 | AS8: =U8*$Q8 -> 27016.183 | AT8: =V8*$Q8 -> 0 | AU8: =W8*$Q8 -> 0 | AV8: =SUM(AQ8:AU8) -> 27016.183 | AW8: =S8*$R8 -> 0 | AX8: =T8*$R8 -> 0 | AY8: =U8*$R8 -> 36021.578 | AZ8: =V8*$R8 -> 0 | BA8: =W8*$R8 -> 0 | BB8: =SUM(AW8:BA8) -> 36021.578 | BC8: =$Y8+$AE8+$AK8+$AQ8+AW8 -> 0 | BD8: =$Z8+$AF8+$AL8+AR8+AX8 -> 0 | BE8: =$AA8+$AG8+$AM8+AS8+AY8 -> 356185.86 | BF8: =$AB8+$AH8+$AN8+AT8+AZ8 -> 0 | BG8: =$AC8+$AI8+$AO8+AU8+BA8 -> 0 | BH8: =SUM(BC8:BG8) -> 356185.86 | BI8: =$Y8/$M8 -> 0 | BJ8: =$Z8/$M8 -> 0 | BK8: =$AA8/$M8 -> 37507.468 | BL8: =$AB8/$M8 -> 0 | BM8: =$AC8/$M8 -> 0 | BN8: =$AD8/$M8 -> 37507.468 | BO8: =$AE8/$M8 -> 0 | BP8: =$AF8/$M8 -> 0 | BQ8: =$AG8/$M8 -> 135080.92 | BR8: =$AH8/$M8 -> 0 | BS8: =$AI8/$M8 -> 0 | BT8: =$AJ8/$M8 -> 135080.92 | BU8: =$AK8/$M8 -> 0 | BV8: =$AL8/$M8 -> 0 | BW8: =$AM8/$M8 -> 120559.72 | BX8: =$AN8/$M8 -> 0 | BY8: =$AO8/$M8 -> 0 | BZ8: =$AP8/$M8 -> 120559.72 | CA8: =AQ8/$M8 -> 0 | CB8: =AR8/$M8 -> 0 | CC8: =AS8/$M8 -> 27016.183 | CD8: =AT8/$M8 -> 0 | CE8: =AU8/$M8 -> 0 | CF8: =AV8/$M8 -> 27016.183 | CG8: =AW8/$M8 -> 0 | CH8: =AX8/$M8 -> 0 | ... CL8: =BB8/$M8 -> 36021.578 | CM8: =$BC8/$M8 -> 0 | CN8: =$BD8/$M8 -> 0 | CO8: =$BE8/$M8 -> 356185.86 | CP8: =$BF8/$M8 -> 0 | CQ8: =$BG8/$M8 -> 0 | CR8: =SUM(CM8:CQ8) -> 356185.86 | CS8: =K8-CR8 -> 544353.58 | CU8: =D8 -> ARS | CV8: =VLOOKUP(CU8,DF:DG,2,0) -> 0.0006918517 | CW8: =K8*CV8 -> 623.03974 | CX8: =BN8*CV8 -> 25.949605 | CY8: =BT8*CV8 -> 93.455961 | CZ8: =BZ8*CV8 -> 83.409446 | DA8: =CF8*CV8 -> 18.691192 | DB8: =CL8*CV8 -> 24.92159 | DC8: =CS8*CV8 -> 376.61195 | DD8: =VLOOKUP(A8,'Billing Report'!H:I,2,FALSE) -> OT467 Vuelta al cole - Alcance - TWITTER | DF8: ALL | DG8: 0.012329646
A9: 40888664 | B9: T2751490 | C9: 275149001 | D9: ARS | G9: 162996.65 | J9: =VLOOKUP($B9,'IMS Commission List'!E:CE,79,0)/100 -> 0.15 | K9: =SUM(E9:I9) -> 162996.65 | L9: =VLOOKUP($B9,'IMS Commission List'!E:V,18,0) -> ARS | M9: 1 | N9: =VLOOKUP($B9,'IMS Commission List'!E:T,16,0) -> MX | O9: =VLOOKUP($B9,'IMS Commission List'!E:CF,80,0) -> 0.049 | P9: =VLOOKUP($B9,'IMS Commission List'!E:CG,81,0) -> 0.1575 | Q9: =VLOOKUP($B9,'IMS Commission List'!E:CP,90,0) -> 0.03 | R9: =VLOOKUP($B9,'IMS Commission List'!E:CQ,91,0) -> 0.04 | S9: =$E9*$M9 -> 0 | T9: =$F9*$M9 -> 0 | U9: =$G9*$M9 -> 162996.65 | V9: =$H9*$M9 -> 0 | W9: =$I9*$M9 -> 0 | X9: =$K9*$M9 -> 162996.65 | Y9: =(S9*$O9)*(1-J9) -> 0 | Z9: =(T9*$O9)*(1-J9) -> 0 | AA9: =(U9*$O9)*(1-J9) -> 6788.8105 | AB9: =(V9*$O9)*(1-J9) -> 0 | AC9: =(W9*$O9)*(1-J9) -> 0 | AD9: =SUM(Y9:AC9) -> 6788.8105 | AE9: =S9*$J9 -> 0 | AF9: =T9*$J9 -> 0 | AG9: =U9*$J9 -> 24449.498 | AH9: =V9*$J9 -> 0 | AI9: =W9*$J9 -> 0 | AJ9: =SUM(AE9:AI9) -> 24449.498 | AK9: =($P9*S9)*(1-$J9) -> 0 | AL9: =($P9*T9)*(1-$J9) -> 0 | AM9: =($P9*U9)*(1-$J9) -> 21821.177 | AN9: =($P9*V9)*(1-$J9) -> 0 | AO9: =($P9*W9)*(1-$J9) -> 0 | AP9: =SUM(AK9:AO9) -> 21821.177 | AQ9: =S9*$Q9 -> 0 | AR9: =T9*$Q9 -> 0 | AS9: =U9*$Q9 -> 4889.8995 | AT9: =V9*$Q9 -> 0 | AU9: =W9*$Q9 -> 0 | AV9: =SUM(AQ9:AU9) -> 4889.8995 | AW9: =S9*$R9 -> 0 | AX9: =T9*$R9 -> 0 | AY9: =U9*$R9 -> 6519.866 | AZ9: =V9*$R9 -> 0 | BA9: =W9*$R9 -> 0 | BB9: =SUM(AW9:BA9) -> 6519.866 | BC9: =$Y9+$AE9+$AK9+$AQ9+AW9 -> 0 | BD9: =$Z9+$AF9+$AL9+AR9+AX9 -> 0 | BE9: =$AA9+$AG9+$AM9+AS9+AY9 -> 64469.25 | BF9: =$AB9+$AH9+$AN9+AT9+AZ9 -> 0 | BG9: =$AC9+$AI9+$AO9+AU9+BA9 -> 0 | BH9: =SUM(BC9:BG9) -> 64469.25 | BI9: =$Y9/$M9 -> 0 | BJ9: =$Z9/$M9 -> 0 | BK9: =$AA9/$M9 -> 6788.8105 | BL9: =$AB9/$M9 -> 0 | BM9: =$AC9/$M9 -> 0 | BN9: =$AD9/$M9 -> 6788.8105 | BO9: =$AE9/$M9 -> 0 | BP9: =$AF9/$M9 -> 0 | BQ9: =$AG9/$M9 -> 24449.498 | BR9: =$AH9/$M9 -> 0 | BS9: =$AI9/$M9 -> 0 | BT9: =$AJ9/$M9 -> 24449.498 | BU9: =$AK9/$M9 -> 0 | BV9: =$AL9/$M9 -> 0 | BW9: =$AM9/$M9 -> 21821.177 | BX9: =$AN9/$M9 -> 0 | BY9: =$AO9/$M9 -> 0 | BZ9: =$AP9/$M9 -> 21821.177 | CA9: =AQ9/$M9 -> 0 | CB9: =AR9/$M9 -> 0 | CC9: =AS9/$M9 -> 4889.8995 | CD9: =AT9/$M9 -> 0 | CE9: =AU9/$M9 -> 0 | CF9: =AV9/$M9 -> 4889.8995 | CG9: =AW9/$M9 -> 0 | CH9: =AX9/$M9 -> 0 | ... CL9: =BB9/$M9 -> 6519.866 | CM9: =$BC9/$M9 -> 0 | CN9: =$BD9/$M9 -> 0 | CO9: =$BE9/$M9 -> 64469.25 | CP9: =$BF9/$M9 -> 0 | CQ9: =$BG9/$M9 -> 0 | CR9: =SUM(CM9:CQ9) -> 64469.25 | CS9: =K9-CR9 -> 98527.4 | CU9: =D9 -> ARS | CV9: =VLOOKUP(CU9,DF:DG,2,0) -> 0.0006918517 | CW9: =K9*CV9 -> 112.76951 | CX9: =BN9*CV9 -> 4.6968501 | CY9: =BT9*CV9 -> 16.915426 | CZ9: =BZ9*CV9 -> 15.097018 | DA9: =CF9*CV9 -> 3.3830853 | DB9: =CL9*CV9 -> 4.5107804 | DC9: =CS9*CV9 -> 68.166349 | DD9: =VLOOKUP(A9,'Billing Report'!H:I,2,FALSE) -> OT470 Inversiones Feb26 - Tráfico - TWITTER | DF9: ARS | DG9: 0.0006918517
A10: 40888662 | B10: T2751490 | C10: 275149001 | D10: ARS | G10: 102565.52 | J10: =VLOOKUP($B10,'IMS Commission List'!E:CE,79,0)/100 -> 0.15 | K10: =SUM(E10:I10) -> 102565.52 | L10: =VLOOKUP($B10,'IMS Commission List'!E:V,18,0) -> ARS | M10: 1 | N10: =VLOOKUP($B10,'IMS Commission List'!E:T,16,0) -> MX | O10: =VLOOKUP($B10,'IMS Commission List'!E:CF,80,0) -> 0.049 | P10: =VLOOKUP($B10,'IMS Commission List'!E:CG,81,0) -> 0.1575 | Q10: =VLOOKUP($B10,'IMS Commission List'!E:CP,90,0) -> 0.03 | R10: =VLOOKUP($B10,'IMS Commission List'!E:CQ,91,0) -> 0.04 | S10: =$E10*$M10 -> 0 | T10: =$F10*$M10 -> 0 | U10: =$G10*$M10 -> 102565.52 | V10: =$H10*$M10 -> 0 | W10: =$I10*$M10 -> 0 | X10: =$K10*$M10 -> 102565.52 | Y10: =(S10*$O10)*(1-J10) -> 0 | Z10: =(T10*$O10)*(1-J10) -> 0 | AA10: =(U10*$O10)*(1-J10) -> 4271.8539 | AB10: =(V10*$O10)*(1-J10) -> 0 | AC10: =(W10*$O10)*(1-J10) -> 0 | AD10: =SUM(Y10:AC10) -> 4271.8539 | AE10: =S10*$J10 -> 0 | AF10: =T10*$J10 -> 0 | AG10: =U10*$J10 -> 15384.828 | AH10: =V10*$J10 -> 0 | AI10: =W10*$J10 -> 0 | AJ10: =SUM(AE10:AI10) -> 15384.828 | AK10: =($P10*S10)*(1-$J10) -> 0 | AL10: =($P10*T10)*(1-$J10) -> 0 | AM10: =($P10*U10)*(1-$J10) -> 13730.959 | AN10: =($P10*V10)*(1-$J10) -> 0 | AO10: =($P10*W10)*(1-$J10) -> 0 | AP10: =SUM(AK10:AO10) -> 13730.959 | AQ10: =S10*$Q10 -> 0 | AR10: =T10*$Q10 -> 0 | AS10: =U10*$Q10 -> 3076.9656 | AT10: =V10*$Q10 -> 0 | AU10: =W10*$Q10 -> 0 | AV10: =SUM(AQ10:AU10) -> 3076.9656 | AW10: =S10*$R10 -> 0 | AX10: =T10*$R10 -> 0 | AY10: =U10*$R10 -> 4102.6208 | AZ10: =V10*$R10 -> 0 | BA10: =W10*$R10 -> 0 | BB10: =SUM(AW10:BA10) -> 4102.6208 | BC10: =$Y10+$AE10+$AK10+$AQ10+AW10 -> 0 | BD10: =$Z10+$AF10+$AL10+AR10+AX10 -> 0 | BE10: =$AA10+$AG10+$AM10+AS10+AY10 -> 40567.227 | BF10: =$AB10+$AH10+$AN10+AT10+AZ10 -> 0 | BG10: =$AC10+$AI10+$AO10+AU10+BA10 -> 0 | BH10: =SUM(BC10:BG10) -> 40567.227 | BI10: =$Y10/$M10 -> 0 | BJ10: =$Z10/$M10 -> 0 | BK10: =$AA10/$M10 -> 4271.8539 | BL10: =$AB10/$M10 -> 0 | BM10: =$AC10/$M10 -> 0 | BN10: =$AD10/$M10 -> 4271.8539 | BO10: =$AE10/$M10 -> 0 | BP10: =$AF10/$M10 -> 0 | BQ10: =$AG10/$M10 -> 15384.828 | BR10: =$AH10/$M10 -> 0 | BS10: =$AI10/$M10 -> 0 | BT10: =$AJ10/$M10 -> 15384.828 | BU10: =$AK10/$M10 -> 0 | BV10: =$AL10/$M10 -> 0 | BW10: =$AM10/$M10 -> 13730.959 | BX10: =$AN10/$M10 -> 0 | BY10: =$AO10/$M10 -> 0 | BZ10: =$AP10/$M10 -> 13730.959 | CA10: =AQ10/$M10 -> 0 | CB10: =AR10/$M10 -> 0 | CC10: =AS10/$M10 -> 3076.9656 | CD10: =AT10/$M10 -> 0 | CE10: =AU10/$M10 -> 0 | CF10: =AV10/$M10 -> 3076.9656 | CG10: =AW10/$M10 -> 0 | CH10: =AX10/$M10 -> 0 | ... CL10: =BB10/$M10 -> 4102.6208 | CM10: =$BC10/$M10 -> 0 | CN10: =$BD10/$M10 -> 0 | CO10: =$BE10/$M10 -> 40567.227 | CP10: =$BF10/$M10 -> 0 | CQ10: =$BG10/$M10 -> 0 | CR10: =SUM(CM10:CQ10) -> 40567.227 | CS10: =K10-CR10 -> 61998.293 | CU10: =D10 -> ARS | CV10: =VLOOKUP(CU10,DF:DG,2,0) -> 0.0006918517 | CW10: =K10*CV10 -> 70.960129 | CX10: =BN10*CV10 -> 2.9554894 | CY10: =BT10*CV10 -> 10.644019 | CZ10: =BZ10*CV10 -> 9.4997873 | DA10: =CF10*CV10 -> 2.1288039 | DB10: =CL10*CV10 -> 2.8384052 | DC10: =CS10*CV10 -> 42.893624 | DD10: =VLOOKUP(A10,'Billing Report'!H:I,2,FALSE) -> OT470 Inversiones Feb26 - Alcance - TWITTER | DF10: AUD | DG10: 0.69938873
A11: 40888605 | B11: T2751490 | C11: 275149001 | D11: ARS | G11: 413581.86 | J11: =VLOOKUP($B11,'IMS Commission List'!E:CE,79,0)/100 -> 0.15 | K11: =SUM(E11:I11) -> 413581.86 | L11: =VLOOKUP($B11,'IMS Commission List'!E:V,18,0) -> ARS | M11: 1 | N11: =VLOOKUP($B11,'IMS Commission List'!E:T,16,0) -> MX | O11: =VLOOKUP($B11,'IMS Commission List'!E:CF,80,0) -> 0.049 | P11: =VLOOKUP($B11,'IMS Commission List'!E:CG,81,0) -> 0.1575 | Q11: =VLOOKUP($B11,'IMS Commission List'!E:CP,90,0) -> 0.03 | R11: =VLOOKUP($B11,'IMS Commission List'!E:CQ,91,0) -> 0.04 | S11: =$E11*$M11 -> 0 | T11: =$F11*$M11 -> 0 | U11: =$G11*$M11 -> 413581.86 | V11: =$H11*$M11 -> 0 | W11: =$I11*$M11 -> 0 | X11: =$K11*$M11 -> 413581.86 | Y11: =(S11*$O11)*(1-J11) -> 0 | Z11: =(T11*$O11)*(1-J11) -> 0 | AA11: =(U11*$O11)*(1-J11) -> 17225.684 | AB11: =(V11*$O11)*(1-J11) -> 0 | AC11: =(W11*$O11)*(1-J11) -> 0 | AD11: =SUM(Y11:AC11) -> 17225.684 | AE11: =S11*$J11 -> 0 | AF11: =T11*$J11 -> 0 | AG11: =U11*$J11 -> 62037.279 | AH11: =V11*$J11 -> 0 | AI11: =W11*$J11 -> 0 | AJ11: =SUM(AE11:AI11) -> 62037.279 | AK11: =($P11*S11)*(1-$J11) -> 0 | AL11: =($P11*T11)*(1-$J11) -> 0 | AM11: =($P11*U11)*(1-$J11) -> 55368.272 | AN11: =($P11*V11)*(1-$J11) -> 0 | AO11: =($P11*W11)*(1-$J11) -> 0 | AP11: =SUM(AK11:AO11) -> 55368.272 | AQ11: =S11*$Q11 -> 0 | AR11: =T11*$Q11 -> 0 | AS11: =U11*$Q11 -> 12407.456 | AT11: =V11*$Q11 -> 0 | AU11: =W11*$Q11 -> 0 | AV11: =SUM(AQ11:AU11) -> 12407.456 | AW11: =S11*$R11 -> 0 | AX11: =T11*$R11 -> 0 | AY11: =U11*$R11 -> 16543.274 | AZ11: =V11*$R11 -> 0 | BA11: =W11*$R11 -> 0 | BB11: =SUM(AW11:BA11) -> 16543.274 | BC11: =$Y11+$AE11+$AK11+$AQ11+AW11 -> 0 | BD11: =$Z11+$AF11+$AL11+AR11+AX11 -> 0 | BE11: =$AA11+$AG11+$AM11+AS11+AY11 -> 163581.97 | BF11: =$AB11+$AH11+$AN11+AT11+AZ11 -> 0 | BG11: =$AC11+$AI11+$AO11+AU11+BA11 -> 0 | BH11: =SUM(BC11:BG11) -> 163581.97 | BI11: =$Y11/$M11 -> 0 | BJ11: =$Z11/$M11 -> 0 | BK11: =$AA11/$M11 -> 17225.684 | BL11: =$AB11/$M11 -> 0 | BM11: =$AC11/$M11 -> 0 | BN11: =$AD11/$M11 -> 17225.684 | BO11: =$AE11/$M11 -> 0 | BP11: =$AF11/$M11 -> 0 | BQ11: =$AG11/$M11 -> 62037.279 | BR11: =$AH11/$M11 -> 0 | BS11: =$AI11/$M11 -> 0 | BT11: =$AJ11/$M11 -> 62037.279 | BU11: =$AK11/$M11 -> 0 | BV11: =$AL11/$M11 -> 0 | BW11: =$AM11/$M11 -> 55368.272 | BX11: =$AN11/$M11 -> 0 | BY11: =$AO11/$M11 -> 0 | BZ11: =$AP11/$M11 -> 55368.272 | CA11: =AQ11/$M11 -> 0 | CB11: =AR11/$M11 -> 0 | CC11: =AS11/$M11 -> 12407.456 | CD11: =AT11/$M11 -> 0 | CE11: =AU11/$M11 -> 0 | CF11: =AV11/$M11 -> 12407.456 | CG11: =AW11/$M11 -> 0 | CH11: =AX11/$M11 -> 0 | ... CL11: =BB11/$M11 -> 16543.274 | CM11: =$BC11/$M11 -> 0 | CN11: =$BD11/$M11 -> 0 | CO11: =$BE11/$M11 -> 163581.97 | CP11: =$BF11/$M11 -> 0 | CQ11: =$BG11/$M11 -> 0 | CR11: =SUM(CM11:CQ11) -> 163581.97 | CS11: =K11-CR11 -> 249999.89 | CU11: =D11 -> ARS | CV11: =VLOOKUP(CU11,DF:DG,2,0) -> 0.0006918517 | CW11: =K11*CV11 -> 286.13731 | CX11: =BN11*CV11 -> 11.917619 | CY11: =BT11*CV11 -> 42.920597 | CZ11: =BZ11*CV11 -> 38.306633 | DA11: =CF11*CV11 -> 8.5841194 | DB11: =CL11*CV11 -> 11.445493 | DC11: =CS11*CV11 -> 172.96285 | DD11: =VLOOKUP(A11,'Billing Report'!H:I,2,FALSE) -> OT473 Ciberdelito Feb26 - Alcance - TWITTER | DF11: BAM | DG11: 0.60864087
A12: 40855406 | B12: T2751490 | C12: 275149001 | D12: ARS | G12: 1389582.7 | J12: =VLOOKUP($B12,'IMS Commission List'!E:CE,79,0)/100 -> 0.15 | K12: =SUM(E12:I12) -> 1389582.7 | L12: =VLOOKUP($B12,'IMS Commission List'!E:V,18,0) -> ARS | M12: 1 | N12: =VLOOKUP($B12,'IMS Commission List'!E:T,16,0) -> MX | O12: =VLOOKUP($B12,'IMS Commission List'!E:CF,80,0) -> 0.049 | P12: =VLOOKUP($B12,'IMS Commission List'!E:CG,81,0) -> 0.1575 | Q12: =VLOOKUP($B12,'IMS Commission List'!E:CP,90,0) -> 0.03 | R12: =VLOOKUP($B12,'IMS Commission List'!E:CQ,91,0) -> 0.04 | S12: =$E12*$M12 -> 0 | T12: =$F12*$M12 -> 0 | U12: =$G12*$M12 -> 1389582.7 | V12: =$H12*$M12 -> 0 | W12: =$I12*$M12 -> 0 | X12: =$K12*$M12 -> 1389582.7 | Y12: =(S12*$O12)*(1-J12) -> 0 | Z12: =(T12*$O12)*(1-J12) -> 0 | AA12: =(U12*$O12)*(1-J12) -> 57876.117 | AB12: =(V12*$O12)*(1-J12) -> 0 | AC12: =(W12*$O12)*(1-J12) -> 0 | AD12: =SUM(Y12:AC12) -> 57876.117 | AE12: =S12*$J12 -> 0 | AF12: =T12*$J12 -> 0 | AG12: =U12*$J12 -> 208437.4 | AH12: =V12*$J12 -> 0 | AI12: =W12*$J12 -> 0 | AJ12: =SUM(AE12:AI12) -> 208437.4 | AK12: =($P12*S12)*(1-$J12) -> 0 | AL12: =($P12*T12)*(1-$J12) -> 0 | AM12: =($P12*U12)*(1-$J12) -> 186030.38 | AN12: =($P12*V12)*(1-$J12) -> 0 | AO12: =($P12*W12)*(1-$J12) -> 0 | AP12: =SUM(AK12:AO12) -> 186030.38 | AQ12: =S12*$Q12 -> 0 | AR12: =T12*$Q12 -> 0 | AS12: =U12*$Q12 -> 41687.48 | AT12: =V12*$Q12 -> 0 | AU12: =W12*$Q12 -> 0 | AV12: =SUM(AQ12:AU12) -> 41687.48 | AW12: =S12*$R12 -> 0 | AX12: =T12*$R12 -> 0 | AY12: =U12*$R12 -> 55583.306 | AZ12: =V12*$R12 -> 0 | BA12: =W12*$R12 -> 0 | BB12: =SUM(AW12:BA12) -> 55583.306 | BC12: =$Y12+$AE12+$AK12+$AQ12+AW12 -> 0 | BD12: =$Z12+$AF12+$AL12+AR12+AX12 -> 0 | BE12: =$AA12+$AG12+$AM12+AS12+AY12 -> 549614.68 | BF12: =$AB12+$AH12+$AN12+AT12+AZ12 -> 0 | BG12: =$AC12+$AI12+$AO12+AU12+BA12 -> 0 | BH12: =SUM(BC12:BG12) -> 549614.68 | BI12: =$Y12/$M12 -> 0 | BJ12: =$Z12/$M12 -> 0 | BK12: =$AA12/$M12 -> 57876.117 | BL12: =$AB12/$M12 -> 0 | BM12: =$AC12/$M12 -> 0 | BN12: =$AD12/$M12 -> 57876.117 | BO12: =$AE12/$M12 -> 0 | BP12: =$AF12/$M12 -> 0 | BQ12: =$AG12/$M12 -> 208437.4 | BR12: =$AH12/$M12 -> 0 | BS12: =$AI12/$M12 -> 0 | BT12: =$AJ12/$M12 -> 208437.4 | BU12: =$AK12/$M12 -> 0 | BV12: =$AL12/$M12 -> 0 | BW12: =$AM12/$M12 -> 186030.38 | BX12: =$AN12/$M12 -> 0 | BY12: =$AO12/$M12 -> 0 | BZ12: =$AP12/$M12 -> 186030.38 | CA12: =AQ12/$M12 -> 0 | CB12: =AR12/$M12 -> 0 | CC12: =AS12/$M12 -> 41687.48 | CD12: =AT12/$M12 -> 0 | CE12: =AU12/$M12 -> 0 | CF12: =AV12/$M12 -> 41687.48 | CG12: =AW12/$M12 -> 0 | CH12: =AX12/$M12 -> 0 | ... CL12: =BB12/$M12 -> 55583.306 | CM12: =$BC12/$M12 -> 0 | CN12: =$BD12/$M12 -> 0 | CO12: =$BE12/$M12 -> 549614.68 | CP12: =$BF12/$M12 -> 0 | CQ12: =$BG12/$M12 -> 0 | CR12: =SUM(CM12:CQ12) -> 549614.68 | CS12: =K12-CR12 -> 839967.97 | CU12: =D12 -> ARS | CV12: =VLOOKUP(CU12,DF:DG,2,0) -> 0.0006918517 | CW12: =K12*CV12 -> 961.38512 | CX12: =BN12*CV12 -> 40.04169 | CY12: =BT12*CV12 -> 144.20777 | CZ12: =BZ12*CV12 -> 128.70543 | DA12: =CF12*CV12 -> 28.841554 | DB12: =CL12*CV12 -> 38.455405 | DC12: =CS12*CV12 -> 581.13327 | DD12: =VLOOKUP(A12,'Billing Report'!H:I,2,FALSE) -> OT466 Rentas - Alcance - Twitter | DF12: BGN | DG12: 0.60864087
A13: 40789966 | B13: T2751490 | C13: 275149001 | D13: ARS | G13: 443772.08 | J13: =VLOOKUP($B13,'IMS Commission List'!E:CE,79,0)/100 -> 0.15 | K13: =SUM(E13:I13) -> 443772.08 | L13: =VLOOKUP($B13,'IMS Commission List'!E:V,18,0) -> ARS | M13: 1 | N13: =VLOOKUP($B13,'IMS Commission List'!E:T,16,0) -> MX | O13: =VLOOKUP($B13,'IMS Commission List'!E:CF,80,0) -> 0.049 | P13: =VLOOKUP($B13,'IMS Commission List'!E:CG,81,0) -> 0.1575 | Q13: =VLOOKUP($B13,'IMS Commission List'!E:CP,90,0) -> 0.03 | R13: =VLOOKUP($B13,'IMS Commission List'!E:CQ,91,0) -> 0.04 | S13: =$E13*$M13 -> 0 | T13: =$F13*$M13 -> 0 | U13: =$G13*$M13 -> 443772.08 | V13: =$H13*$M13 -> 0 | W13: =$I13*$M13 -> 0 | X13: =$K13*$M13 -> 443772.08 | Y13: =(S13*$O13)*(1-J13) -> 0 | Z13: =(T13*$O13)*(1-J13) -> 0 | AA13: =(U13*$O13)*(1-J13) -> 18483.107 | AB13: =(V13*$O13)*(1-J13) -> 0 | AC13: =(W13*$O13)*(1-J13) -> 0 | AD13: =SUM(Y13:AC13) -> 18483.107 | AE13: =S13*$J13 -> 0 | AF13: =T13*$J13 -> 0 | AG13: =U13*$J13 -> 66565.812 | AH13: =V13*$J13 -> 0 | AI13: =W13*$J13 -> 0 | AJ13: =SUM(AE13:AI13) -> 66565.812 | AK13: =($P13*S13)*(1-$J13) -> 0 | AL13: =($P13*T13)*(1-$J13) -> 0 | AM13: =($P13*U13)*(1-$J13) -> 59409.987 | AN13: =($P13*V13)*(1-$J13) -> 0 | AO13: =($P13*W13)*(1-$J13) -> 0 | AP13: =SUM(AK13:AO13) -> 59409.987 | AQ13: =S13*$Q13 -> 0 | AR13: =T13*$Q13 -> 0 | AS13: =U13*$Q13 -> 13313.162 | AT13: =V13*$Q13 -> 0 | AU13: =W13*$Q13 -> 0 | AV13: =SUM(AQ13:AU13) -> 13313.162 | AW13: =S13*$R13 -> 0 | AX13: =T13*$R13 -> 0 | AY13: =U13*$R13 -> 17750.883 | AZ13: =V13*$R13 -> 0 | BA13: =W13*$R13 -> 0 | BB13: =SUM(AW13:BA13) -> 17750.883 | BC13: =$Y13+$AE13+$AK13+$AQ13+AW13 -> 0 | BD13: =$Z13+$AF13+$AL13+AR13+AX13 -> 0 | BE13: =$AA13+$AG13+$AM13+AS13+AY13 -> 175522.95 | BF13: =$AB13+$AH13+$AN13+AT13+AZ13 -> 0 | BG13: =$AC13+$AI13+$AO13+AU13+BA13 -> 0 | BH13: =SUM(BC13:BG13) -> 175522.95 | BI13: =$Y13/$M13 -> 0 | BJ13: =$Z13/$M13 -> 0 | BK13: =$AA13/$M13 -> 18483.107 | BL13: =$AB13/$M13 -> 0 | BM13: =$AC13/$M13 -> 0 | BN13: =$AD13/$M13 -> 18483.107 | BO13: =$AE13/$M13 -> 0 | BP13: =$AF13/$M13 -> 0 | BQ13: =$AG13/$M13 -> 66565.812 | BR13: =$AH13/$M13 -> 0 | BS13: =$AI13/$M13 -> 0 | BT13: =$AJ13/$M13 -> 66565.812 | BU13: =$AK13/$M13 -> 0 | BV13: =$AL13/$M13 -> 0 | BW13: =$AM13/$M13 -> 59409.987 | BX13: =$AN13/$M13 -> 0 | BY13: =$AO13/$M13 -> 0 | BZ13: =$AP13/$M13 -> 59409.987 | CA13: =AQ13/$M13 -> 0 | CB13: =AR13/$M13 -> 0 | CC13: =AS13/$M13 -> 13313.162 | CD13: =AT13/$M13 -> 0 | CE13: =AU13/$M13 -> 0 | CF13: =AV13/$M13 -> 13313.162 | CG13: =AW13/$M13 -> 0 | CH13: =AX13/$M13 -> 0 | ... CL13: =BB13/$M13 -> 17750.883 | CM13: =$BC13/$M13 -> 0 | CN13: =$BD13/$M13 -> 0 | CO13: =$BE13/$M13 -> 175522.95 | CP13: =$BF13/$M13 -> 0 | CQ13: =$BG13/$M13 -> 0 | CR13: =SUM(CM13:CQ13) -> 175522.95 | CS13: =K13-CR13 -> 268249.13 | CU13: =D13 -> ARS | CV13: =VLOOKUP(CU13,DF:DG,2,0) -> 0.0006918517 | CW13: =K13*CV13 -> 307.02447 | CX13: =BN13*CV13 -> 12.787569 | CY13: =BT13*CV13 -> 46.05367 | CZ13: =BZ13*CV13 -> 41.102901 | DA13: =CF13*CV13 -> 9.210734 | DB13: =CL13*CV13 -> 12.280979 | DC13: =CS13*CV13 -> 185.58862 | DD13: =VLOOKUP(A13,'Billing Report'!H:I,2,FALSE) -> OT429-V3 Cordobesa Verano - Alcance - Twitter - Capsulas de Video (MALEVO) | DF13: BHD | DG13: 2.6525903
A14: 40789854 | B14: T2751490 | C14: 275149001 | D14: ARS | G14: 61583.81 | J14: =VLOOKUP($B14,'IMS Commission List'!E:CE,79,0)/100 -> 0.15 | K14: =SUM(E14:I14) -> 61583.81 | L14: =VLOOKUP($B14,'IMS Commission List'!E:V,18,0) -> ARS | M14: 1 | N14: =VLOOKUP($B14,'IMS Commission List'!E:T,16,0) -> MX | O14: =VLOOKUP($B14,'IMS Commission List'!E:CF,80,0) -> 0.049 | P14: =VLOOKUP($B14,'IMS Commission List'!E:CG,81,0) -> 0.1575 | Q14: =VLOOKUP($B14,'IMS Commission List'!E:CP,90,0) -> 0.03 | R14: =VLOOKUP($B14,'IMS Commission List'!E:CQ,91,0) -> 0.04 | S14: =$E14*$M14 -> 0 | T14: =$F14*$M14 -> 0 | U14: =$G14*$M14 -> 61583.81 | V14: =$H14*$M14 -> 0 | W14: =$I14*$M14 -> 0 | X14: =$K14*$M14 -> 61583.81 | Y14: =(S14*$O14)*(1-J14) -> 0 | Z14: =(T14*$O14)*(1-J14) -> 0 | AA14: =(U14*$O14)*(1-J14) -> 2564.9657 | AB14: =(V14*$O14)*(1-J14) -> 0 | AC14: =(W14*$O14)*(1-J14) -> 0 | AD14: =SUM(Y14:AC14) -> 2564.9657 | AE14: =S14*$J14 -> 0 | AF14: =T14*$J14 -> 0 | AG14: =U14*$J14 -> 9237.5715 | AH14: =V14*$J14 -> 0 | AI14: =W14*$J14 -> 0 | AJ14: =SUM(AE14:AI14) -> 9237.5715 | AK14: =($P14*S14)*(1-$J14) -> 0 | AL14: =($P14*T14)*(1-$J14) -> 0 | AM14: =($P14*U14)*(1-$J14) -> 8244.5326 | AN14: =($P14*V14)*(1-$J14) -> 0 | AO14: =($P14*W14)*(1-$J14) -> 0 | AP14: =SUM(AK14:AO14) -> 8244.5326 | AQ14: =S14*$Q14 -> 0 | AR14: =T14*$Q14 -> 0 | AS14: =U14*$Q14 -> 1847.5143 | AT14: =V14*$Q14 -> 0 | AU14: =W14*$Q14 -> 0 | AV14: =SUM(AQ14:AU14) -> 1847.5143 | AW14: =S14*$R14 -> 0 | AX14: =T14*$R14 -> 0 | AY14: =U14*$R14 -> 2463.3524 | AZ14: =V14*$R14 -> 0 | BA14: =W14*$R14 -> 0 | BB14: =SUM(AW14:BA14) -> 2463.3524 | BC14: =$Y14+$AE14+$AK14+$AQ14+AW14 -> 0 | BD14: =$Z14+$AF14+$AL14+AR14+AX14 -> 0 | BE14: =$AA14+$AG14+$AM14+AS14+AY14 -> 24357.936 | BF14: =$AB14+$AH14+$AN14+AT14+AZ14 -> 0 | BG14: =$AC14+$AI14+$AO14+AU14+BA14 -> 0 | BH14: =SUM(BC14:BG14) -> 24357.936 | BI14: =$Y14/$M14 -> 0 | BJ14: =$Z14/$M14 -> 0 | BK14: =$AA14/$M14 -> 2564.9657 | BL14: =$AB14/$M14 -> 0 | BM14: =$AC14/$M14 -> 0 | BN14: =$AD14/$M14 -> 2564.9657 | BO14: =$AE14/$M14 -> 0 | BP14: =$AF14/$M14 -> 0 | BQ14: =$AG14/$M14 -> 9237.5715 | BR14: =$AH14/$M14 -> 0 | BS14: =$AI14/$M14 -> 0 | BT14: =$AJ14/$M14 -> 9237.5715 | BU14: =$AK14/$M14 -> 0 | BV14: =$AL14/$M14 -> 0 | BW14: =$AM14/$M14 -> 8244.5326 | BX14: =$AN14/$M14 -> 0 | BY14: =$AO14/$M14 -> 0 | BZ14: =$AP14/$M14 -> 8244.5326 | CA14: =AQ14/$M14 -> 0 | CB14: =AR14/$M14 -> 0 | CC14: =AS14/$M14 -> 1847.5143 | CD14: =AT14/$M14 -> 0 | CE14: =AU14/$M14 -> 0 | CF14: =AV14/$M14 -> 1847.5143 | CG14: =AW14/$M14 -> 0 | CH14: =AX14/$M14 -> 0 | ... CL14: =BB14/$M14 -> 2463.3524 | CM14: =$BC14/$M14 -> 0 | CN14: =$BD14/$M14 -> 0 | CO14: =$BE14/$M14 -> 24357.936 | CP14: =$BF14/$M14 -> 0 | CQ14: =$BG14/$M14 -> 0 | CR14: =SUM(CM14:CQ14) -> 24357.936 | CS14: =K14-CR14 -> 37225.874 | CU14: =D14 -> ARS | CV14: =VLOOKUP(CU14,DF:DG,2,0) -> 0.0006918517 | CW14: =K14*CV14 -> 42.606864 | CX14: =BN14*CV14 -> 1.7745759 | CY14: =BT14*CV14 -> 6.3910295 | CZ14: =BZ14*CV14 -> 5.7039939 | DA14: =CF14*CV14 -> 1.2782059 | DB14: =CL14*CV14 -> 1.7042745 | DC14: =CS14*CV14 -> 25.754784 | DD14: =VLOOKUP(A14,'Billing Report'!H:I,2,FALSE) -> OT429-V3 Cordobesa Verano - Alcance - Twitter - PROMO PEAJE | DF14: BRL | DG14: 0.19166396
A15: 40789845 | B15: T2751490 | C15: 275149001 | D15: ARS | G15: 319263.44 | J15: =VLOOKUP($B15,'IMS Commission List'!E:CE,79,0)/100 -> 0.15 | K15: =SUM(E15:I15) -> 319263.44 | L15: =VLOOKUP($B15,'IMS Commission List'!E:V,18,0) -> ARS | M15: 1 | N15: =VLOOKUP($B15,'IMS Commission List'!E:T,16,0) -> MX | O15: =VLOOKUP($B15,'IMS Commission List'!E:CF,80,0) -> 0.049 | P15: =VLOOKUP($B15,'IMS Commission List'!E:CG,81,0) -> 0.1575 | Q15: =VLOOKUP($B15,'IMS Commission List'!E:CP,90,0) -> 0.03 | R15: =VLOOKUP($B15,'IMS Commission List'!E:CQ,91,0) -> 0.04 | S15: =$E15*$M15 -> 0 | T15: =$F15*$M15 -> 0 | U15: =$G15*$M15 -> 319263.44 | V15: =$H15*$M15 -> 0 | W15: =$I15*$M15 -> 0 | X15: =$K15*$M15 -> 319263.44 | Y15: =(S15*$O15)*(1-J15) -> 0 | Z15: =(T15*$O15)*(1-J15) -> 0 | AA15: =(U15*$O15)*(1-J15) -> 13297.322 | AB15: =(V15*$O15)*(1-J15) -> 0 | AC15: =(W15*$O15)*(1-J15) -> 0 | AD15: =SUM(Y15:AC15) -> 13297.322 | AE15: =S15*$J15 -> 0 | AF15: =T15*$J15 -> 0 | AG15: =U15*$J15 -> 47889.516 | AH15: =V15*$J15 -> 0 | AI15: =W15*$J15 -> 0 | AJ15: =SUM(AE15:AI15) -> 47889.516 | AK15: =($P15*S15)*(1-$J15) -> 0 | AL15: =($P15*T15)*(1-$J15) -> 0 | AM15: =($P15*U15)*(1-$J15) -> 42741.393 | AN15: =($P15*V15)*(1-$J15) -> 0 | AO15: =($P15*W15)*(1-$J15) -> 0 | AP15: =SUM(AK15:AO15) -> 42741.393 | AQ15: =S15*$Q15 -> 0 | AR15: =T15*$Q15 -> 0 | AS15: =U15*$Q15 -> 9577.9032 | AT15: =V15*$Q15 -> 0 | AU15: =W15*$Q15 -> 0 | AV15: =SUM(AQ15:AU15) -> 9577.9032 | AW15: =S15*$R15 -> 0 | AX15: =T15*$R15 -> 0 | AY15: =U15*$R15 -> 12770.538 | AZ15: =V15*$R15 -> 0 | BA15: =W15*$R15 -> 0 | BB15: =SUM(AW15:BA15) -> 12770.538 | BC15: =$Y15+$AE15+$AK15+$AQ15+AW15 -> 0 | BD15: =$Z15+$AF15+$AL15+AR15+AX15 -> 0 | BE15: =$AA15+$AG15+$AM15+AS15+AY15 -> 126276.67 | BF15: =$AB15+$AH15+$AN15+AT15+AZ15 -> 0 | BG15: =$AC15+$AI15+$AO15+AU15+BA15 -> 0 | BH15: =SUM(BC15:BG15) -> 126276.67 | BI15: =$Y15/$M15 -> 0 | BJ15: =$Z15/$M15 -> 0 | BK15: =$AA15/$M15 -> 13297.322 | BL15: =$AB15/$M15 -> 0 | BM15: =$AC15/$M15 -> 0 | BN15: =$AD15/$M15 -> 13297.322 | BO15: =$AE15/$M15 -> 0 | BP15: =$AF15/$M15 -> 0 | BQ15: =$AG15/$M15 -> 47889.516 | BR15: =$AH15/$M15 -> 0 | BS15: =$AI15/$M15 -> 0 | BT15: =$AJ15/$M15 -> 47889.516 | BU15: =$AK15/$M15 -> 0 | BV15: =$AL15/$M15 -> 0 | BW15: =$AM15/$M15 -> 42741.393 | BX15: =$AN15/$M15 -> 0 | BY15: =$AO15/$M15 -> 0 | BZ15: =$AP15/$M15 -> 42741.393 | CA15: =AQ15/$M15 -> 0 | CB15: =AR15/$M15 -> 0 | CC15: =AS15/$M15 -> 9577.9032 | CD15: =AT15/$M15 -> 0 | CE15: =AU15/$M15 -> 0 | CF15: =AV15/$M15 -> 9577.9032 | CG15: =AW15/$M15 -> 0 | CH15: =AX15/$M15 -> 0 | ... CL15: =BB15/$M15 -> 12770.538 | CM15: =$BC15/$M15 -> 0 | CN15: =$BD15/$M15 -> 0 | CO15: =$BE15/$M15 -> 126276.67 | CP15: =$BF15/$M15 -> 0 | CQ15: =$BG15/$M15 -> 0 | CR15: =SUM(CM15:CQ15) -> 126276.67 | CS15: =K15-CR15 -> 192986.77 | CU15: =D15 -> ARS | CV15: =VLOOKUP(CU15,DF:DG,2,0) -> 0.0006918517 | CW15: =K15*CV15 -> 220.88295 | CX15: =BN15*CV15 -> 9.199775 | CY15: =BT15*CV15 -> 33.132443 | CZ15: =BZ15*CV15 -> 29.570705 | DA15: =CF15*CV15 -> 6.6264886 | DB15: =CL15*CV15 -> 8.8353181 | DC15: =CS15*CV15 -> 133.51822 | DD15: =VLOOKUP(A15,'Billing Report'!H:I,2,FALSE) -> OT429-V3 Cordobesa Verano - Alcance - Twitter - PROMO Festivales y Espectáculos | DF15: BYR | DG15: 3.51832e-05
A16: 40789826 | B16: T2751490 | C16: 275149001 | D16: ARS | G16: 61670.34 | J16: =VLOOKUP($B16,'IMS Commission List'!E:CE,79,0)/100 -> 0.15 | K16: =SUM(E16:I16) -> 61670.34 | L16: =VLOOKUP($B16,'IMS Commission List'!E:V,18,0) -> ARS | M16: 1 | N16: =VLOOKUP($B16,'IMS Commission List'!E:T,16,0) -> MX | O16: =VLOOKUP($B16,'IMS Commission List'!E:CF,80,0) -> 0.049 | P16: =VLOOKUP($B16,'IMS Commission List'!E:CG,81,0) -> 0.1575 | Q16: =VLOOKUP($B16,'IMS Commission List'!E:CP,90,0) -> 0.03 | R16: =VLOOKUP($B16,'IMS Commission List'!E:CQ,91,0) -> 0.04 | S16: =$E16*$M16 -> 0 | T16: =$F16*$M16 -> 0 | U16: =$G16*$M16 -> 61670.34 | V16: =$H16*$M16 -> 0 | W16: =$I16*$M16 -> 0 | X16: =$K16*$M16 -> 61670.34 | Y16: =(S16*$O16)*(1-J16) -> 0 | Z16: =(T16*$O16)*(1-J16) -> 0 | AA16: =(U16*$O16)*(1-J16) -> 2568.5697 | AB16: =(V16*$O16)*(1-J16) -> 0 | AC16: =(W16*$O16)*(1-J16) -> 0 | AD16: =SUM(Y16:AC16) -> 2568.5697 | AE16: =S16*$J16 -> 0 | AF16: =T16*$J16 -> 0 | AG16: =U16*$J16 -> 9250.551 | AH16: =V16*$J16 -> 0 | AI16: =W16*$J16 -> 0 | AJ16: =SUM(AE16:AI16) -> 9250.551 | AK16: =($P16*S16)*(1-$J16) -> 0 | AL16: =($P16*T16)*(1-$J16) -> 0 | AM16: =($P16*U16)*(1-$J16) -> 8256.1168 | AN16: =($P16*V16)*(1-$J16) -> 0 | AO16: =($P16*W16)*(1-$J16) -> 0 | AP16: =SUM(AK16:AO16) -> 8256.1168 | AQ16: =S16*$Q16 -> 0 | AR16: =T16*$Q16 -> 0 | AS16: =U16*$Q16 -> 1850.1102 | AT16: =V16*$Q16 -> 0 | AU16: =W16*$Q16 -> 0 | AV16: =SUM(AQ16:AU16) -> 1850.1102 | AW16: =S16*$R16 -> 0 | AX16: =T16*$R16 -> 0 | AY16: =U16*$R16 -> 2466.8136 | AZ16: =V16*$R16 -> 0 | BA16: =W16*$R16 -> 0 | BB16: =SUM(AW16:BA16) -> 2466.8136 | BC16: =$Y16+$AE16+$AK16+$AQ16+AW16 -> 0 | BD16: =$Z16+$AF16+$AL16+AR16+AX16 -> 0 | BE16: =$AA16+$AG16+$AM16+AS16+AY16 -> 24392.161 | BF16: =$AB16+$AH16+$AN16+AT16+AZ16 -> 0 | BG16: =$AC16+$AI16+$AO16+AU16+BA16 -> 0 | BH16: =SUM(BC16:BG16) -> 24392.161 | BI16: =$Y16/$M16 -> 0 | BJ16: =$Z16/$M16 -> 0 | BK16: =$AA16/$M16 -> 2568.5697 | BL16: =$AB16/$M16 -> 0 | BM16: =$AC16/$M16 -> 0 | BN16: =$AD16/$M16 -> 2568.5697 | BO16: =$AE16/$M16 -> 0 | BP16: =$AF16/$M16 -> 0 | BQ16: =$AG16/$M16 -> 9250.551 | BR16: =$AH16/$M16 -> 0 | BS16: =$AI16/$M16 -> 0 | BT16: =$AJ16/$M16 -> 9250.551 | BU16: =$AK16/$M16 -> 0 | BV16: =$AL16/$M16 -> 0 | BW16: =$AM16/$M16 -> 8256.1168 | BX16: =$AN16/$M16 -> 0 | BY16: =$AO16/$M16 -> 0 | BZ16: =$AP16/$M16 -> 8256.1168 | CA16: =AQ16/$M16 -> 0 | CB16: =AR16/$M16 -> 0 | CC16: =AS16/$M16 -> 1850.1102 | CD16: =AT16/$M16 -> 0 | CE16: =AU16/$M16 -> 0 | CF16: =AV16/$M16 -> 1850.1102 | CG16: =AW16/$M16 -> 0 | CH16: =AX16/$M16 -> 0 | ... CL16: =BB16/$M16 -> 2466.8136 | CM16: =$BC16/$M16 -> 0 | CN16: =$BD16/$M16 -> 0 | CO16: =$BE16/$M16 -> 24392.161 | CP16: =$BF16/$M16 -> 0 | CQ16: =$BG16/$M16 -> 0 | CR16: =SUM(CM16:CQ16) -> 24392.161 | CS16: =K16-CR16 -> 37278.179 | CU16: =D16 -> ARS | CV16: =VLOOKUP(CU16,DF:DG,2,0) -> 0.0006918517 | CW16: =K16*CV16 -> 42.66673 | CX16: =BN16*CV16 -> 1.7770693 | CY16: =BT16*CV16 -> 6.4000094 | CZ16: =BZ16*CV16 -> 5.7120084 | DA16: =CF16*CV16 -> 1.2800019 | DB16: =CL16*CV16 -> 1.7066692 | DC16: =CS16*CV16 -> 25.790971 | DD16: =VLOOKUP(A16,'Billing Report'!H:I,2,FALSE) -> OT429-V3 Cordobesa Verano - Alcance - Twitter - PROMO SUPERMERCADO | DF16: CAD | DG16: 0.73817354
A17: 37183205 | B17: T2767832 | C17: 276783201 | D17: ARS | G17: 3113913.1 | J17: =VLOOKUP($B17,'IMS Commission List'!E:CE,79,0)/100 -> 0.15 | K17: =SUM(E17:I17) -> 3113913.1 | L17: =VLOOKUP($B17,'IMS Commission List'!E:V,18,0) -> ARS | M17: 1 | N17: =VLOOKUP($B17,'IMS Commission List'!E:T,16,0) -> MX | O17: =VLOOKUP($B17,'IMS Commission List'!E:CF,80,0) -> 0.049 | P17: =VLOOKUP($B17,'IMS Commission List'!E:CG,81,0) -> 0.1575 | Q17: =VLOOKUP($B17,'IMS Commission List'!E:CP,90,0) -> 0.03 | R17: =VLOOKUP($B17,'IMS Commission List'!E:CQ,91,0) -> 0.04 | S17: =$E17*$M17 -> 0 | T17: =$F17*$M17 -> 0 | U17: =$G17*$M17 -> 3113913.1 | V17: =$H17*$M17 -> 0 | W17: =$I17*$M17 -> 0 | X17: =$K17*$M17 -> 3113913.1 | Y17: =(S17*$O17)*(1-J17) -> 0 | Z17: =(T17*$O17)*(1-J17) -> 0 | AA17: =(U17*$O17)*(1-J17) -> 129694.48 | AB17: =(V17*$O17)*(1-J17) -> 0 | AC17: =(W17*$O17)*(1-J17) -> 0 | AD17: =SUM(Y17:AC17) -> 129694.48 | AE17: =S17*$J17 -> 0 | AF17: =T17*$J17 -> 0 | AG17: =U17*$J17 -> 467086.96 | AH17: =V17*$J17 -> 0 | AI17: =W17*$J17 -> 0 | AJ17: =SUM(AE17:AI17) -> 467086.96 | AK17: =($P17*S17)*(1-$J17) -> 0 | AL17: =($P17*T17)*(1-$J17) -> 0 | AM17: =($P17*U17)*(1-$J17) -> 416875.11 | AN17: =($P17*V17)*(1-$J17) -> 0 | AO17: =($P17*W17)*(1-$J17) -> 0 | AP17: =SUM(AK17:AO17) -> 416875.11 | AQ17: =S17*$Q17 -> 0 | AR17: =T17*$Q17 -> 0 | AS17: =U17*$Q17 -> 93417.392 | AT17: =V17*$Q17 -> 0 | AU17: =W17*$Q17 -> 0 | AV17: =SUM(AQ17:AU17) -> 93417.392 | AW17: =S17*$R17 -> 0 | AX17: =T17*$R17 -> 0 | AY17: =U17*$R17 -> 124556.52 | AZ17: =V17*$R17 -> 0 | BA17: =W17*$R17 -> 0 | BB17: =SUM(AW17:BA17) -> 124556.52 | BC17: =$Y17+$AE17+$AK17+$AQ17+AW17 -> 0 | BD17: =$Z17+$AF17+$AL17+AR17+AX17 -> 0 | BE17: =$AA17+$AG17+$AM17+AS17+AY17 -> 1231630.5 | BF17: =$AB17+$AH17+$AN17+AT17+AZ17 -> 0 | BG17: =$AC17+$AI17+$AO17+AU17+BA17 -> 0 | BH17: =SUM(BC17:BG17) -> 1231630.5 | BI17: =$Y17/$M17 -> 0 | BJ17: =$Z17/$M17 -> 0 | BK17: =$AA17/$M17 -> 129694.48 | BL17: =$AB17/$M17 -> 0 | BM17: =$AC17/$M17 -> 0 | BN17: =$AD17/$M17 -> 129694.48 | BO17: =$AE17/$M17 -> 0 | BP17: =$AF17/$M17 -> 0 | BQ17: =$AG17/$M17 -> 467086.96 | BR17: =$AH17/$M17 -> 0 | BS17: =$AI17/$M17 -> 0 | BT17: =$AJ17/$M17 -> 467086.96 | BU17: =$AK17/$M17 -> 0 | BV17: =$AL17/$M17 -> 0 | BW17: =$AM17/$M17 -> 416875.11 | BX17: =$AN17/$M17 -> 0 | BY17: =$AO17/$M17 -> 0 | BZ17: =$AP17/$M17 -> 416875.11 | CA17: =AQ17/$M17 -> 0 | CB17: =AR17/$M17 -> 0 | CC17: =AS17/$M17 -> 93417.392 | CD17: =AT17/$M17 -> 0 | CE17: =AU17/$M17 -> 0 | CF17: =AV17/$M17 -> 93417.392 | CG17: =AW17/$M17 -> 0 | CH17: =AX17/$M17 -> 0 | ... CL17: =BB17/$M17 -> 124556.52 | CM17: =$BC17/$M17 -> 0 | CN17: =$BD17/$M17 -> 0 | CO17: =$BE17/$M17 -> 1231630.5 | CP17: =$BF17/$M17 -> 0 | CQ17: =$BG17/$M17 -> 0 | CR17: =SUM(CM17:CQ17) -> 1231630.5 | CS17: =K17-CR17 -> 1882282.6 | CU17: =D17 -> ARS | CV17: =VLOOKUP(CU17,DF:DG,2,0) -> 0.0006918517 | CW17: =K17*CV17 -> 2154.3661 | CX17: =BN17*CV17 -> 89.729346 | CY17: =BT17*CV17 -> 323.15491 | CZ17: =BZ17*CV17 -> 288.41576 | DA17: =CF17*CV17 -> 64.630982 | DB17: =CL17*CV17 -> 86.174642 | DC17: =CS17*CV17 -> 1302.2604 | DD17: =VLOOKUP(A17,'Billing Report'!H:I,2,FALSE) -> Banco Galicia 6 y 12 cuotas | DF17: CHF | DG17: 1.2994523
A18: 40860429 | B18: T2834460 | C18: 283446001 | D18: ARS | G18: 1208044.6 | J18: =VLOOKUP($B18,'IMS Commission List'!E:CE,79,0)/100 -> 0.15 | K18: =SUM(E18:I18) -> 1208044.6 | L18: =VLOOKUP($B18,'IMS Commission List'!E:V,18,0) -> ARS | M18: 1 | N18: =VLOOKUP($B18,'IMS Commission List'!E:T,16,0) -> MX | O18: =VLOOKUP($B18,'IMS Commission List'!E:CF,80,0) -> 0.049 | P18: =VLOOKUP($B18,'IMS Commission List'!E:CG,81,0) -> 0.1575 | Q18: =VLOOKUP($B18,'IMS Commission List'!E:CP,90,0) -> 0.03 | R18: =VLOOKUP($B18,'IMS Commission List'!E:CQ,91,0) -> 0.04 | S18: =$E18*$M18 -> 0 | T18: =$F18*$M18 -> 0 | U18: =$G18*$M18 -> 1208044.6 | V18: =$H18*$M18 -> 0 | W18: =$I18*$M18 -> 0 | X18: =$K18*$M18 -> 1208044.6 | Y18: =(S18*$O18)*(1-J18) -> 0 | Z18: =(T18*$O18)*(1-J18) -> 0 | AA18: =(U18*$O18)*(1-J18) -> 50315.059 | AB18: =(V18*$O18)*(1-J18) -> 0 | AC18: =(W18*$O18)*(1-J18) -> 0 | AD18: =SUM(Y18:AC18) -> 50315.059 | AE18: =S18*$J18 -> 0 | AF18: =T18*$J18 -> 0 | AG18: =U18*$J18 -> 181206.69 | AH18: =V18*$J18 -> 0 | AI18: =W18*$J18 -> 0 | AJ18: =SUM(AE18:AI18) -> 181206.69 | AK18: =($P18*S18)*(1-$J18) -> 0 | AL18: =($P18*T18)*(1-$J18) -> 0 | AM18: =($P18*U18)*(1-$J18) -> 161726.97 | AN18: =($P18*V18)*(1-$J18) -> 0 | AO18: =($P18*W18)*(1-$J18) -> 0 | AP18: =SUM(AK18:AO18) -> 161726.97 | AQ18: =S18*$Q18 -> 0 | AR18: =T18*$Q18 -> 0 | AS18: =U18*$Q18 -> 36241.339 | AT18: =V18*$Q18 -> 0 | AU18: =W18*$Q18 -> 0 | AV18: =SUM(AQ18:AU18) -> 36241.339 | AW18: =S18*$R18 -> 0 | AX18: =T18*$R18 -> 0 | AY18: =U18*$R18 -> 48321.785 | AZ18: =V18*$R18 -> 0 | BA18: =W18*$R18 -> 0 | BB18: =SUM(AW18:BA18) -> 48321.785 | BC18: =$Y18+$AE18+$AK18+$AQ18+AW18 -> 0 | BD18: =$Z18+$AF18+$AL18+AR18+AX18 -> 0 | BE18: =$AA18+$AG18+$AM18+AS18+AY18 -> 477811.85 | BF18: =$AB18+$AH18+$AN18+AT18+AZ18 -> 0 | BG18: =$AC18+$AI18+$AO18+AU18+BA18 -> 0 | BH18: =SUM(BC18:BG18) -> 477811.85 | BI18: =$Y18/$M18 -> 0 | BJ18: =$Z18/$M18 -> 0 | BK18: =$AA18/$M18 -> 50315.059 | BL18: =$AB18/$M18 -> 0 | BM18: =$AC18/$M18 -> 0 | BN18: =$AD18/$M18 -> 50315.059 | BO18: =$AE18/$M18 -> 0 | BP18: =$AF18/$M18 -> 0 | BQ18: =$AG18/$M18 -> 181206.69 | BR18: =$AH18/$M18 -> 0 | BS18: =$AI18/$M18 -> 0 | BT18: =$AJ18/$M18 -> 181206.69 | BU18: =$AK18/$M18 -> 0 | BV18: =$AL18/$M18 -> 0 | BW18: =$AM18/$M18 -> 161726.97 | BX18: =$AN18/$M18 -> 0 | BY18: =$AO18/$M18 -> 0 | BZ18: =$AP18/$M18 -> 161726.97 | CA18: =AQ18/$M18 -> 0 | CB18: =AR18/$M18 -> 0 | CC18: =AS18/$M18 -> 36241.339 | CD18: =AT18/$M18 -> 0 | CE18: =AU18/$M18 -> 0 | CF18: =AV18/$M18 -> 36241.339 | CG18: =AW18/$M18 -> 0 | CH18: =AX18/$M18 -> 0 | ... CL18: =BB18/$M18 -> 48321.785 | CM18: =$BC18/$M18 -> 0 | CN18: =$BD18/$M18 -> 0 | CO18: =$BE18/$M18 -> 477811.85 | CP18: =$BF18/$M18 -> 0 | CQ18: =$BG18/$M18 -> 0 | CR18: =SUM(CM18:CQ18) -> 477811.85 | CS18: =K18-CR18 -> 730232.78 | CU18: =D18 -> ARS | CV18: =VLOOKUP(CU18,DF:DG,2,0) -> 0.0006918517 | CW18: =K18*CV18 -> 835.78773 | CX18: =BN18*CV18 -> 34.810559 | CY18: =BT18*CV18 -> 125.36816 | CZ18: =BZ18*CV18 -> 111.89108 | DA18: =CF18*CV18 -> 25.073632 | DB18: =CL18*CV18 -> 33.431509 | DC18: =CS18*CV18 -> 505.21279 | DD18: =VLOOKUP(A18,'Billing Report'!H:I,2,FALSE) -> BULL_FLYBONDI_AR_TWITTER_TRAF_ALWAYSON_PRUEBA | DF18: CLP | DG18: 0.0011587177
... A35: 40045288 | B35: T3025948 | C35: 302594801 | D35: ARS | G35: 523174.23 | J35: =VLOOKUP($B35,'IMS Commission List'!E:CE,79,0)/100 -> 0.08 | K35: =SUM(E35:I35) -> 523174.23 | L35: =VLOOKUP($B35,'IMS Commission List'!E:V,18,0) -> ARS | M35: 1 | N35: =VLOOKUP($B35,'IMS Commission List'!E:T,16,0) -> MX | O35: =VLOOKUP($B35,'IMS Commission List'!E:CF,80,0) -> 0.049 | P35: =VLOOKUP($B35,'IMS Commission List'!E:CG,81,0) -> 0.1575 | Q35: =VLOOKUP($B35,'IMS Commission List'!E:CP,90,0) -> 0.03 | R35: =VLOOKUP($B35,'IMS Commission List'!E:CQ,91,0) -> 0.04 | S35: =$E35*$M35 -> 0 | T35: =$F35*$M35 -> 0 | U35: =$G35*$M35 -> 523174.23 | V35: =$H35*$M35 -> 0 | W35: =$I35*$M35 -> 0 | X35: =$K35*$M35 -> 523174.23 | Y35: =(S35*$O35)*(1-J35) -> 0 | Z35: =(T35*$O35)*(1-J35) -> 0 | AA35: =(U35*$O35)*(1-J35) -> 23584.694 | AB35: =(V35*$O35)*(1-J35) -> 0 | AC35: =(W35*$O35)*(1-J35) -> 0 | AD35: =SUM(Y35:AC35) -> 23584.694 | AE35: =S35*$J35 -> 0 | AF35: =T35*$J35 -> 0 | AG35: =U35*$J35 -> 41853.938 | AH35: =V35*$J35 -> 0 | AI35: =W35*$J35 -> 0 | AJ35: =SUM(AE35:AI35) -> 41853.938 | AK35: =($P35*S35)*(1-$J35) -> 0 | AL35: =($P35*T35)*(1-$J35) -> 0 | AM35: =($P35*U35)*(1-$J35) -> 75807.946 | AN35: =($P35*V35)*(1-$J35) -> 0 | AO35: =($P35*W35)*(1-$J35) -> 0 | AP35: =SUM(AK35:AO35) -> 75807.946 | AQ35: =S35*$Q35 -> 0 | AR35: =T35*$Q35 -> 0 | AS35: =U35*$Q35 -> 15695.227 | AT35: =V35*$Q35 -> 0 | AU35: =W35*$Q35 -> 0 | AV35: =SUM(AQ35:AU35) -> 15695.227 | AW35: =S35*$R35 -> 0 | AX35: =T35*$R35 -> 0 | AY35: =U35*$R35 -> 20926.969 | AZ35: =V35*$R35 -> 0 | BA35: =W35*$R35 -> 0 | BB35: =SUM(AW35:BA35) -> 20926.969 | BC35: =$Y35+$AE35+$AK35+$AQ35+AW35 -> 0 | BD35: =$Z35+$AF35+$AL35+AR35+AX35 -> 0 | BE35: =$AA35+$AG35+$AM35+AS35+AY35 -> 177868.77 | BF35: =$AB35+$AH35+$AN35+AT35+AZ35 -> 0 | BG35: =$AC35+$AI35+$AO35+AU35+BA35 -> 0 | BH35: =SUM(BC35:BG35) -> 177868.77 | BI35: =$Y35/$M35 -> 0 | BJ35: =$Z35/$M35 -> 0 | BK35: =$AA35/$M35 -> 23584.694 | BL35: =$AB35/$M35 -> 0 | BM35: =$AC35/$M35 -> 0 | BN35: =$AD35/$M35 -> 23584.694 | BO35: =$AE35/$M35 -> 0 | BP35: =$AF35/$M35 -> 0 | BQ35: =$AG35/$M35 -> 41853.938 | BR35: =$AH35/$M35 -> 0 | BS35: =$AI35/$M35 -> 0 | BT35: =$AJ35/$M35 -> 41853.938 | BU35: =$AK35/$M35 -> 0 | BV35: =$AL35/$M35 -> 0 | BW35: =$AM35/$M35 -> 75807.946 | BX35: =$AN35/$M35 -> 0 | BY35: =$AO35/$M35 -> 0 | BZ35: =$AP35/$M35 -> 75807.946 | CA35: =AQ35/$M35 -> 0 | CB35: =AR35/$M35 -> 0 | CC35: =AS35/$M35 -> 15695.227 | CD35: =AT35/$M35 -> 0 | CE35: =AU35/$M35 -> 0 | CF35: =AV35/$M35 -> 15695.227 | CG35: =AW35/$M35 -> 0 | CH35: =AX35/$M35 -> 0 | ... CL35: =BB35/$M35 -> 20926.969 | CM35: =$BC35/$M35 -> 0 | CN35: =$BD35/$M35 -> 0 | CO35: =$BE35/$M35 -> 177868.77 | CP35: =$BF35/$M35 -> 0 | CQ35: =$BG35/$M35 -> 0 | CR35: =SUM(CM35:CQ35) -> 177868.77 | CS35: =K35-CR35 -> 345305.46 | CU35: =D35 -> ARS | CV35: =VLOOKUP(CU35,DF:DG,2,0) -> 0.0006918517 | CW35: =K35*CV35 -> 361.95898 | CX35: =BN35*CV35 -> 16.317111 | CY35: =BT35*CV35 -> 28.956718 | CZ35: =BZ35*CV35 -> 52.447856 | DA35: =CF35*CV35 -> 10.858769 | DB35: =CL35*CV35 -> 14.478359 | DC35: =CS35*CV35 -> 238.90017 | DD35: =VLOOKUP(A35,'Billing Report'!H:I,2,FALSE) -> CX_AR_PR_PS_TW_TWI_AND_ALL_RAP_ALL_NA_00000_TAC_INS_INS | DF35: IQD | DG35: 0.0007629998
A36: (blank) | B36: T3094969 | C36: 309496901 | D36: ARS | G36: -31.88 | J36: =VLOOKUP($B36,'IMS Commission List'!E:CE,79,0)/100 -> 0.15 | K36: =SUM(E36:I36) -> -31.88 | L36: =VLOOKUP($B36,'IMS Commission List'!E:V,18,0) -> ARS | M36: 1 | N36: =VLOOKUP($B36,'IMS Commission List'!E:T,16,0) -> MX | O36: =VLOOKUP($B36,'IMS Commission List'!E:CF,80,0) -> 0.049 | P36: =VLOOKUP($B36,'IMS Commission List'!E:CG,81,0) -> 0.1575 | Q36: =VLOOKUP($B36,'IMS Commission List'!E:CP,90,0) -> 0.03 | R36: =VLOOKUP($B36,'IMS Commission List'!E:CQ,91,0) -> 0.04 | S36: =$E36*$M36 -> 0 | T36: =$F36*$M36 -> 0 | U36: =$G36*$M36 -> -31.88 | V36: =$H36*$M36 -> 0 | W36: =$I36*$M36 -> 0 | X36: =$K36*$M36 -> -31.88 | Y36: =(S36*$O36)*(1-J36) -> 0 | Z36: =(T36*$O36)*(1-J36) -> 0 | AA36: =(U36*$O36)*(1-J36) -> -1.327802 | AB36: =(V36*$O36)*(1-J36) -> 0 | AC36: =(W36*$O36)*(1-J36) -> 0 | AD36: =SUM(Y36:AC36) -> -1.327802 | AE36: =S36*$J36 -> 0 | AF36: =T36*$J36 -> 0 | AG36: =U36*$J36 -> -4.782 | AH36: =V36*$J36 -> 0 | AI36: =W36*$J36 -> 0 | AJ36: =SUM(AE36:AI36) -> -4.782 | AK36: =($P36*S36)*(1-$J36) -> 0 | AL36: =($P36*T36)*(1-$J36) -> 0 | AM36: =($P36*U36)*(1-$J36) -> -4.267935 | AN36: =($P36*V36)*(1-$J36) -> 0 | AO36: =($P36*W36)*(1-$J36) -> 0 | AP36: =SUM(AK36:AO36) -> -4.267935 | AQ36: =S36*$Q36 -> 0 | AR36: =T36*$Q36 -> 0 | AS36: =U36*$Q36 -> -0.9564 | AT36: =V36*$Q36 -> 0 | AU36: =W36*$Q36 -> 0 | AV36: =SUM(AQ36:AU36) -> -0.9564 | AW36: =S36*$R36 -> 0 | AX36: =T36*$R36 -> 0 | AY36: =U36*$R36 -> -1.2752 | AZ36: =V36*$R36 -> 0 | BA36: =W36*$R36 -> 0 | BB36: =SUM(AW36:BA36) -> -1.2752 | BC36: =$Y36+$AE36+$AK36+$AQ36+AW36 -> 0 | BD36: =$Z36+$AF36+$AL36+AR36+AX36 -> 0 | BE36: =$AA36+$AG36+$AM36+AS36+AY36 -> -12.609337 | BF36: =$AB36+$AH36+$AN36+AT36+AZ36 -> 0 | BG36: =$AC36+$AI36+$AO36+AU36+BA36 -> 0 | BH36: =SUM(BC36:BG36) -> -12.609337 | BI36: =$Y36/$M36 -> 0 | BJ36: =$Z36/$M36 -> 0 | BK36: =$AA36/$M36 -> -1.327802 | BL36: =$AB36/$M36 -> 0 | BM36: =$AC36/$M36 -> 0 | BN36: =$AD36/$M36 -> -1.327802 | BO36: =$AE36/$M36 -> 0 | BP36: =$AF36/$M36 -> 0 | BQ36: =$AG36/$M36 -> -4.782 | BR36: =$AH36/$M36 -> 0 | BS36: =$AI36/$M36 -> 0 | BT36: =$AJ36/$M36 -> -4.782 | BU36: =$AK36/$M36 -> 0 | BV36: =$AL36/$M36 -> 0 | BW36: =$AM36/$M36 -> -4.267935 | BX36: =$AN36/$M36 -> 0 | BY36: =$AO36/$M36 -> 0 | BZ36: =$AP36/$M36 -> -4.267935 | CA36: =AQ36/$M36 -> 0 | CB36: =AR36/$M36 -> 0 | CC36: =AS36/$M36 -> -0.9564 | CD36: =AT36/$M36 -> 0 | CE36: =AU36/$M36 -> 0 | CF36: =AV36/$M36 -> -0.9564 | CG36: =AW36/$M36 -> 0 | CH36: =AX36/$M36 -> 0 | ... CL36: =BB36/$M36 -> -1.2752 | CM36: =$BC36/$M36 -> 0 | CN36: =$BD36/$M36 -> 0 | CO36: =$BE36/$M36 -> -12.609337 | CP36: =$BF36/$M36 -> 0 | CQ36: =$BG36/$M36 -> 0 | CR36: =SUM(CM36:CQ36) -> -12.609337 | CS36: =K36-CR36 -> -19.270663 | CU36: =D36 -> ARS | CV36: =VLOOKUP(CU36,DF:DG,2,0) -> 0.0006918517 | CW36: =K36*CV36 -> -0.022056232 | CX36: =BN36*CV36 -> -0.00091864207 | CY36: =BT36*CV36 -> -0.0033084348 | CZ36: =BZ36*CV36 -> -0.0029527781 | DA36: =CF36*CV36 -> -0.00066168697 | DB36: =CL36*CV36 -> -0.00088224929 | DC36: =CS36*CV36 -> -0.013332441 | DD36: =VLOOKUP(A36,'Billing Report'!H:I,2,FALSE) -> #N/A | DF36: ISK | DG36: 0.0082094881
A37: 40930072 | B37: T3094969 | C37: 309496901 | D37: ARS | G37: 298461.32 | J37: =VLOOKUP($B37,'IMS Commission List'!E:CE,79,0)/100 -> 0.15 | K37: =SUM(E37:I37) -> 298461.32 | L37: =VLOOKUP($B37,'IMS Commission List'!E:V,18,0) -> ARS | M37: 1 | N37: =VLOOKUP($B37,'IMS Commission List'!E:T,16,0) -> MX | O37: =VLOOKUP($B37,'IMS Commission List'!E:CF,80,0) -> 0.049 | P37: =VLOOKUP($B37,'IMS Commission List'!E:CG,81,0) -> 0.1575 | Q37: =VLOOKUP($B37,'IMS Commission List'!E:CP,90,0) -> 0.03 | R37: =VLOOKUP($B37,'IMS Commission List'!E:CQ,91,0) -> 0.04 | S37: =$E37*$M37 -> 0 | T37: =$F37*$M37 -> 0 | U37: =$G37*$M37 -> 298461.32 | V37: =$H37*$M37 -> 0 | W37: =$I37*$M37 -> 0 | X37: =$K37*$M37 -> 298461.32 | Y37: =(S37*$O37)*(1-J37) -> 0 | Z37: =(T37*$O37)*(1-J37) -> 0 | AA37: =(U37*$O37)*(1-J37) -> 12430.914 | AB37: =(V37*$O37)*(1-J37) -> 0 | AC37: =(W37*$O37)*(1-J37) -> 0 | AD37: =SUM(Y37:AC37) -> 12430.914 | AE37: =S37*$J37 -> 0 | AF37: =T37*$J37 -> 0 | AG37: =U37*$J37 -> 44769.198 | AH37: =V37*$J37 -> 0 | AI37: =W37*$J37 -> 0 | AJ37: =SUM(AE37:AI37) -> 44769.198 | AK37: =($P37*S37)*(1-$J37) -> 0 | AL37: =($P37*T37)*(1-$J37) -> 0 | AM37: =($P37*U37)*(1-$J37) -> 39956.509 | AN37: =($P37*V37)*(1-$J37) -> 0 | AO37: =($P37*W37)*(1-$J37) -> 0 | AP37: =SUM(AK37:AO37) -> 39956.509 | AQ37: =S37*$Q37 -> 0 | AR37: =T37*$Q37 -> 0 | AS37: =U37*$Q37 -> 8953.8396 | AT37: =V37*$Q37 -> 0 | AU37: =W37*$Q37 -> 0 | AV37: =SUM(AQ37:AU37) -> 8953.8396 | AW37: =S37*$R37 -> 0 | AX37: =T37*$R37 -> 0 | AY37: =U37*$R37 -> 11938.453 | AZ37: =V37*$R37 -> 0 | BA37: =W37*$R37 -> 0 | BB37: =SUM(AW37:BA37) -> 11938.453 | BC37: =$Y37+$AE37+$AK37+$AQ37+AW37 -> 0 | BD37: =$Z37+$AF37+$AL37+AR37+AX37 -> 0 | BE37: =$AA37+$AG37+$AM37+AS37+AY37 -> 118048.91 | BF37: =$AB37+$AH37+$AN37+AT37+AZ37 -> 0 | BG37: =$AC37+$AI37+$AO37+AU37+BA37 -> 0 | BH37: =SUM(BC37:BG37) -> 118048.91 | BI37: =$Y37/$M37 -> 0 | BJ37: =$Z37/$M37 -> 0 | BK37: =$AA37/$M37 -> 12430.914 | BL37: =$AB37/$M37 -> 0 | BM37: =$AC37/$M37 -> 0 | BN37: =$AD37/$M37 -> 12430.914 | BO37: =$AE37/$M37 -> 0 | BP37: =$AF37/$M37 -> 0 | BQ37: =$AG37/$M37 -> 44769.198 | BR37: =$AH37/$M37 -> 0 | BS37: =$AI37/$M37 -> 0 | BT37: =$AJ37/$M37 -> 44769.198 | BU37: =$AK37/$M37 -> 0 | BV37: =$AL37/$M37 -> 0 | BW37: =$AM37/$M37 -> 39956.509 | BX37: =$AN37/$M37 -> 0 | BY37: =$AO37/$M37 -> 0 | BZ37: =$AP37/$M37 -> 39956.509 | CA37: =AQ37/$M37 -> 0 | CB37: =AR37/$M37 -> 0 | CC37: =AS37/$M37 -> 8953.8396 | CD37: =AT37/$M37 -> 0 | CE37: =AU37/$M37 -> 0 | CF37: =AV37/$M37 -> 8953.8396 | CG37: =AW37/$M37 -> 0 | CH37: =AX37/$M37 -> 0 | ... CL37: =BB37/$M37 -> 11938.453 | CM37: =$BC37/$M37 -> 0 | CN37: =$BD37/$M37 -> 0 | CO37: =$BE37/$M37 -> 118048.91 | CP37: =$BF37/$M37 -> 0 | CQ37: =$BG37/$M37 -> 0 | CR37: =SUM(CM37:CQ37) -> 118048.91 | CS37: =K37-CR37 -> 180412.41 | CU37: =D37 -> ARS | CV37: =VLOOKUP(CU37,DF:DG,2,0) -> 0.0006918517 | CW37: =K37*CV37 -> 206.49097 | CX37: =BN37*CV37 -> 8.600349 | CY37: =BT37*CV37 -> 30.973646 | CZ37: =BZ37*CV37 -> 27.643979 | DA37: =CF37*CV37 -> 6.1947291 | DB37: =CL37*CV37 -> 8.2596389 | DC37: =CS37*CV37 -> 124.81863 | DD37: =VLOOKUP(A37,'Billing Report'!H:I,2,FALSE) -> yoy-sv-brandformance-alcance | DF37: JPY | DG37: 0.0064860528
A38: 40775999 | B38: T3094969 | C38: 309496901 | D38: ARS | G38: 311760.77 | J38: =VLOOKUP($B38,'IMS Commission List'!E:CE,79,0)/100 -> 0.15 | K38: =SUM(E38:I38) -> 311760.77 | L38: =VLOOKUP($B38,'IMS Commission List'!E:V,18,0) -> ARS | M38: 1 | N38: =VLOOKUP($B38,'IMS Commission List'!E:T,16,0) -> MX | O38: =VLOOKUP($B38,'IMS Commission List'!E:CF,80,0) -> 0.049 | P38: =VLOOKUP($B38,'IMS Commission List'!E:CG,81,0) -> 0.1575 | Q38: =VLOOKUP($B38,'IMS Commission List'!E:CP,90,0) -> 0.03 | R38: =VLOOKUP($B38,'IMS Commission List'!E:CQ,91,0) -> 0.04 | S38: =$E38*$M38 -> 0 | T38: =$F38*$M38 -> 0 | U38: =$G38*$M38 -> 311760.77 | V38: =$H38*$M38 -> 0 | W38: =$I38*$M38 -> 0 | X38: =$K38*$M38 -> 311760.77 | Y38: =(S38*$O38)*(1-J38) -> 0 | Z38: =(T38*$O38)*(1-J38) -> 0 | AA38: =(U38*$O38)*(1-J38) -> 12984.836 | AB38: =(V38*$O38)*(1-J38) -> 0 | AC38: =(W38*$O38)*(1-J38) -> 0 | AD38: =SUM(Y38:AC38) -> 12984.836 | AE38: =S38*$J38 -> 0 | AF38: =T38*$J38 -> 0 | AG38: =U38*$J38 -> 46764.115 | AH38: =V38*$J38 -> 0 | AI38: =W38*$J38 -> 0 | AJ38: =SUM(AE38:AI38) -> 46764.115 | AK38: =($P38*S38)*(1-$J38) -> 0 | AL38: =($P38*T38)*(1-$J38) -> 0 | AM38: =($P38*U38)*(1-$J38) -> 41736.973 | AN38: =($P38*V38)*(1-$J38) -> 0 | AO38: =($P38*W38)*(1-$J38) -> 0 | AP38: =SUM(AK38:AO38) -> 41736.973 | AQ38: =S38*$Q38 -> 0 | AR38: =T38*$Q38 -> 0 | AS38: =U38*$Q38 -> 9352.8231 | AT38: =V38*$Q38 -> 0 | AU38: =W38*$Q38 -> 0 | AV38: =SUM(AQ38:AU38) -> 9352.8231 | AW38: =S38*$R38 -> 0 | AX38: =T38*$R38 -> 0 | AY38: =U38*$R38 -> 12470.431 | AZ38: =V38*$R38 -> 0 | BA38: =W38*$R38 -> 0 | BB38: =SUM(AW38:BA38) -> 12470.431 | BC38: =$Y38+$AE38+$AK38+$AQ38+AW38 -> 0 | BD38: =$Z38+$AF38+$AL38+AR38+AX38 -> 0 | BE38: =$AA38+$AG38+$AM38+AS38+AY38 -> 123309.18 | BF38: =$AB38+$AH38+$AN38+AT38+AZ38 -> 0 | BG38: =$AC38+$AI38+$AO38+AU38+BA38 -> 0 | BH38: =SUM(BC38:BG38) -> 123309.18 | BI38: =$Y38/$M38 -> 0 | BJ38: =$Z38/$M38 -> 0 | BK38: =$AA38/$M38 -> 12984.836 | BL38: =$AB38/$M38 -> 0 | BM38: =$AC38/$M38 -> 0 | BN38: =$AD38/$M38 -> 12984.836 | BO38: =$AE38/$M38 -> 0 | BP38: =$AF38/$M38 -> 0 | BQ38: =$AG38/$M38 -> 46764.115 | BR38: =$AH38/$M38 -> 0 | BS38: =$AI38/$M38 -> 0 | BT38: =$AJ38/$M38 -> 46764.115 | BU38: =$AK38/$M38 -> 0 | BV38: =$AL38/$M38 -> 0 | BW38: =$AM38/$M38 -> 41736.973 | BX38: =$AN38/$M38 -> 0 | BY38: =$AO38/$M38 -> 0 | BZ38: =$AP38/$M38 -> 41736.973 | CA38: =AQ38/$M38 -> 0 | CB38: =AR38/$M38 -> 0 | CC38: =AS38/$M38 -> 9352.8231 | CD38: =AT38/$M38 -> 0 | CE38: =AU38/$M38 -> 0 | CF38: =AV38/$M38 -> 9352.8231 | CG38: =AW38/$M38 -> 0 | CH38: =AX38/$M38 -> 0 | ... CL38: =BB38/$M38 -> 12470.431 | CM38: =$BC38/$M38 -> 0 | CN38: =$BD38/$M38 -> 0 | CO38: =$BE38/$M38 -> 123309.18 | CP38: =$BF38/$M38 -> 0 | CQ38: =$BG38/$M38 -> 0 | CR38: =SUM(CM38:CQ38) -> 123309.18 | CS38: =K38-CR38 -> 188451.59 | CU38: =D38 -> ARS | CV38: =VLOOKUP(CU38,DF:DG,2,0) -> 0.0006918517 | CW38: =K38*CV38 -> 215.69222 | CX38: =BN38*CV38 -> 8.9835809 | CY38: =BT38*CV38 -> 32.353833 | CZ38: =BZ38*CV38 -> 28.875796 | DA38: =CF38*CV38 -> 6.4707666 | DB38: =CL38*CV38 -> 8.6276887 | DC38: =CS38*CV38 -> 130.38055 | DD38: =VLOOKUP(A38,'Billing Report'!H:I,2,FALSE) -> yoy-brandformance-alcance | DF38: KES | DG38: 0.0077470997
A39: 39718034 | B39: T3101174 | C39: 310117401 | D39: ARS | G39: 2007664.5 | J39: =VLOOKUP($B39,'IMS Commission List'!E:CE,79,0)/100 -> 0.15 | K39: =SUM(E39:I39) -> 2007664.5 | L39: =VLOOKUP($B39,'IMS Commission List'!E:V,18,0) -> ARS | M39: 1 | N39: =VLOOKUP($B39,'IMS Commission List'!E:T,16,0) -> MX | O39: =VLOOKUP($B39,'IMS Commission List'!E:CF,80,0) -> 0.049 | P39: =VLOOKUP($B39,'IMS Commission List'!E:CG,81,0) -> 0.1575 | Q39: =VLOOKUP($B39,'IMS Commission List'!E:CP,90,0) -> 0.03 | R39: =VLOOKUP($B39,'IMS Commission List'!E:CQ,91,0) -> 0.04 | S39: =$E39*$M39 -> 0 | T39: =$F39*$M39 -> 0 | U39: =$G39*$M39 -> 2007664.5 | V39: =$H39*$M39 -> 0 | W39: =$I39*$M39 -> 0 | X39: =$K39*$M39 -> 2007664.5 | Y39: =(S39*$O39)*(1-J39) -> 0 | Z39: =(T39*$O39)*(1-J39) -> 0 | AA39: =(U39*$O39)*(1-J39) -> 83619.226 | AB39: =(V39*$O39)*(1-J39) -> 0 | AC39: =(W39*$O39)*(1-J39) -> 0 | AD39: =SUM(Y39:AC39) -> 83619.226 | AE39: =S39*$J39 -> 0 | AF39: =T39*$J39 -> 0 | AG39: =U39*$J39 -> 301149.67 | AH39: =V39*$J39 -> 0 | AI39: =W39*$J39 -> 0 | AJ39: =SUM(AE39:AI39) -> 301149.67 | AK39: =($P39*S39)*(1-$J39) -> 0 | AL39: =($P39*T39)*(1-$J39) -> 0 | AM39: =($P39*U39)*(1-$J39) -> 268776.08 | AN39: =($P39*V39)*(1-$J39) -> 0 | AO39: =($P39*W39)*(1-$J39) -> 0 | AP39: =SUM(AK39:AO39) -> 268776.08 | AQ39: =S39*$Q39 -> 0 | AR39: =T39*$Q39 -> 0 | AS39: =U39*$Q39 -> 60229.934 | AT39: =V39*$Q39 -> 0 | AU39: =W39*$Q39 -> 0 | AV39: =SUM(AQ39:AU39) -> 60229.934 | AW39: =S39*$R39 -> 0 | AX39: =T39*$R39 -> 0 | AY39: =U39*$R39 -> 80306.579 | AZ39: =V39*$R39 -> 0 | BA39: =W39*$R39 -> 0 | BB39: =SUM(AW39:BA39) -> 80306.579 | BC39: =$Y39+$AE39+$AK39+$AQ39+AW39 -> 0 | BD39: =$Z39+$AF39+$AL39+AR39+AX39 -> 0 | BE39: =$AA39+$AG39+$AM39+AS39+AY39 -> 794081.49 | BF39: =$AB39+$AH39+$AN39+AT39+AZ39 -> 0 | BG39: =$AC39+$AI39+$AO39+AU39+BA39 -> 0 | BH39: =SUM(BC39:BG39) -> 794081.49 | BI39: =$Y39/$M39 -> 0 | BJ39: =$Z39/$M39 -> 0 | BK39: =$AA39/$M39 -> 83619.226 | BL39: =$AB39/$M39 -> 0 | BM39: =$AC39/$M39 -> 0 | BN39: =$AD39/$M39 -> 83619.226 | BO39: =$AE39/$M39 -> 0 | BP39: =$AF39/$M39 -> 0 | BQ39: =$AG39/$M39 -> 301149.67 | BR39: =$AH39/$M39 -> 0 | BS39: =$AI39/$M39 -> 0 | BT39: =$AJ39/$M39 -> 301149.67 | BU39: =$AK39/$M39 -> 0 | BV39: =$AL39/$M39 -> 0 | BW39: =$AM39/$M39 -> 268776.08 | BX39: =$AN39/$M39 -> 0 | BY39: =$AO39/$M39 -> 0 | BZ39: =$AP39/$M39 -> 268776.08 | CA39: =AQ39/$M39 -> 0 | CB39: =AR39/$M39 -> 0 | CC39: =AS39/$M39 -> 60229.934 | CD39: =AT39/$M39 -> 0 | CE39: =AU39/$M39 -> 0 | CF39: =AV39/$M39 -> 60229.934 | CG39: =AW39/$M39 -> 0 | CH39: =AX39/$M39 -> 0 | ... CL39: =BB39/$M39 -> 80306.579 | CM39: =$BC39/$M39 -> 0 | CN39: =$BD39/$M39 -> 0 | CO39: =$BE39/$M39 -> 794081.49 | CP39: =$BF39/$M39 -> 0 | CQ39: =$BG39/$M39 -> 0 | CR39: =SUM(CM39:CQ39) -> 794081.49 | CS39: =K39-CR39 -> 1213583 | CU39: =D39 -> ARS | CV39: =VLOOKUP(CU39,DF:DG,2,0) -> 0.0006918517 | CW39: =K39*CV39 -> 1389.0061 | CX39: =BN39*CV39 -> 57.852103 | CY39: =BT39*CV39 -> 208.35091 | CZ39: =BZ39*CV39 -> 185.95319 | DA39: =CF39*CV39 -> 41.670183 | DB39: =CL39*CV39 -> 55.560243 | DC39: =CS39*CV39 -> 839.61945 | DD39: =VLOOKUP(A39,'Billing Report'!H:I,2,FALSE) -> 2025_MODO_BRANDING_PROMO_PROMO-DIAV2_TOTAL-PAIS_TWITTER_NU_AW_JUN-JUL | DF39: KRW | DG39: 0.0006930595
A40: 40884286 | B40: T3163143 | C40: 316314309 | D40: ARS | F40: 801900 | J40: =VLOOKUP($B40,'IMS Commission List'!E:CE,79,0)/100 -> 0.15 | K40: =SUM(E40:I40) -> 801900 | L40: =VLOOKUP($B40,'IMS Commission List'!E:V,18,0) -> ARS | M40: 1 | N40: =VLOOKUP($B40,'IMS Commission List'!E:T,16,0) -> MX | O40: =VLOOKUP($B40,'IMS Commission List'!E:CF,80,0) -> 0.049 | P40: =VLOOKUP($B40,'IMS Commission List'!E:CG,81,0) -> 0.1575 | Q40: =VLOOKUP($B40,'IMS Commission List'!E:CP,90,0) -> 0.03 | R40: =VLOOKUP($B40,'IMS Commission List'!E:CQ,91,0) -> 0.04 | S40: =$E40*$M40 -> 0 | T40: =$F40*$M40 -> 801900 | U40: =$G40*$M40 -> 0 | V40: =$H40*$M40 -> 0 | W40: =$I40*$M40 -> 0 | X40: =$K40*$M40 -> 801900 | Y40: =(S40*$O40)*(1-J40) -> 0 | Z40: =(T40*$O40)*(1-J40) -> 33399.135 | AA40: =(U40*$O40)*(1-J40) -> 0 | AB40: =(V40*$O40)*(1-J40) -> 0 | AC40: =(W40*$O40)*(1-J40) -> 0 | AD40: =SUM(Y40:AC40) -> 33399.135 | AE40: =S40*$J40 -> 0 | AF40: =T40*$J40 -> 120285 | AG40: =U40*$J40 -> 0 | AH40: =V40*$J40 -> 0 | AI40: =W40*$J40 -> 0 | AJ40: =SUM(AE40:AI40) -> 120285 | AK40: =($P40*S40)*(1-$J40) -> 0 | AL40: =($P40*T40)*(1-$J40) -> 107354.36 | AM40: =($P40*U40)*(1-$J40) -> 0 | AN40: =($P40*V40)*(1-$J40) -> 0 | AO40: =($P40*W40)*(1-$J40) -> 0 | AP40: =SUM(AK40:AO40) -> 107354.36 | AQ40: =S40*$Q40 -> 0 | AR40: =T40*$Q40 -> 24057 | AS40: =U40*$Q40 -> 0 | AT40: =V40*$Q40 -> 0 | AU40: =W40*$Q40 -> 0 | AV40: =SUM(AQ40:AU40) -> 24057 | AW40: =S40*$R40 -> 0 | AX40: =T40*$R40 -> 32076 | AY40: =U40*$R40 -> 0 | AZ40: =V40*$R40 -> 0 | BA40: =W40*$R40 -> 0 | BB40: =SUM(AW40:BA40) -> 32076 | BC40: =$Y40+$AE40+$AK40+$AQ40+AW40 -> 0 | BD40: =$Z40+$AF40+$AL40+AR40+AX40 -> 317171.5 | BE40: =$AA40+$AG40+$AM40+AS40+AY40 -> 0 | BF40: =$AB40+$AH40+$AN40+AT40+AZ40 -> 0 | BG40: =$AC40+$AI40+$AO40+AU40+BA40 -> 0 | BH40: =SUM(BC40:BG40) -> 317171.5 | BI40: =$Y40/$M40 -> 0 | BJ40: =$Z40/$M40 -> 33399.135 | BK40: =$AA40/$M40 -> 0 | BL40: =$AB40/$M40 -> 0 | BM40: =$AC40/$M40 -> 0 | BN40: =$AD40/$M40 -> 33399.135 | BO40: =$AE40/$M40 -> 0 | BP40: =$AF40/$M40 -> 120285 | BQ40: =$AG40/$M40 -> 0 | BR40: =$AH40/$M40 -> 0 | BS40: =$AI40/$M40 -> 0 | BT40: =$AJ40/$M40 -> 120285 | BU40: =$AK40/$M40 -> 0 | BV40: =$AL40/$M40 -> 107354.36 | BW40: =$AM40/$M40 -> 0 | BX40: =$AN40/$M40 -> 0 | BY40: =$AO40/$M40 -> 0 | BZ40: =$AP40/$M40 -> 107354.36 | CA40: =AQ40/$M40 -> 0 | CB40: =AR40/$M40 -> 24057 | CC40: =AS40/$M40 -> 0 | CD40: =AT40/$M40 -> 0 | CE40: =AU40/$M40 -> 0 | CF40: =AV40/$M40 -> 24057 | CG40: =AW40/$M40 -> 0 | CH40: =AX40/$M40 -> 32076 | ... CL40: =BB40/$M40 -> 32076 | CM40: =$BC40/$M40 -> 0 | CN40: =$BD40/$M40 -> 317171.5 | CO40: =$BE40/$M40 -> 0 | CP40: =$BF40/$M40 -> 0 | CQ40: =$BG40/$M40 -> 0 | CR40: =SUM(CM40:CQ40) -> 317171.5 | CS40: =K40-CR40 -> 484728.5 | CU40: =D40 -> ARS | CV40: =VLOOKUP(CU40,DF:DG,2,0) -> 0.0006918517 | CW40: =K40*CV40 -> 554.79588 | CX40: =BN40*CV40 -> 23.107248 | CY40: =BT40*CV40 -> 83.219382 | CZ40: =BZ40*CV40 -> 74.273298 | DA40: =CF40*CV40 -> 16.643876 | DB40: =CL40*CV40 -> 22.191835 | DC40: =CS40*CV40 -> 335.36024 | DD40: =VLOOKUP(A40,'Billing Report'!H:I,2,FALSE) -> Betfunok Estándar 2026-02-03 | DF40: KWD | DG40: 3.2607278
A41: 40884277 | B41: T3163143 | C41: 3163143010 | D41: ARS | F41: 2308500 | J41: =VLOOKUP($B41,'IMS Commission List'!E:CE,79,0)/100 -> 0.15 | K41: =SUM(E41:I41) -> 2308500 | L41: =VLOOKUP($B41,'IMS Commission List'!E:V,18,0) -> ARS | M41: 1 | N41: =VLOOKUP($B41,'IMS Commission List'!E:T,16,0) -> MX | O41: =VLOOKUP($B41,'IMS Commission List'!E:CF,80,0) -> 0.049 | P41: =VLOOKUP($B41,'IMS Commission List'!E:CG,81,0) -> 0.1575 | Q41: =VLOOKUP($B41,'IMS Commission List'!E:CP,90,0) -> 0.03 | R41: =VLOOKUP($B41,'IMS Commission List'!E:CQ,91,0) -> 0.04 | S41: =$E41*$M41 -> 0 | T41: =$F41*$M41 -> 2308500 | U41: =$G41*$M41 -> 0 | V41: =$H41*$M41 -> 0 | W41: =$I41*$M41 -> 0 | X41: =$K41*$M41 -> 2308500 | Y41: =(S41*$O41)*(1-J41) -> 0 | Z41: =(T41*$O41)*(1-J41) -> 96149.025 | AA41: =(U41*$O41)*(1-J41) -> 0 | AB41: =(V41*$O41)*(1-J41) -> 0 | AC41: =(W41*$O41)*(1-J41) -> 0 | AD41: =SUM(Y41:AC41) -> 96149.025 | AE41: =S41*$J41 -> 0 | AF41: =T41*$J41 -> 346275 | AG41: =U41*$J41 -> 0 | AH41: =V41*$J41 -> 0 | AI41: =W41*$J41 -> 0 | AJ41: =SUM(AE41:AI41) -> 346275 | AK41: =($P41*S41)*(1-$J41) -> 0 | AL41: =($P41*T41)*(1-$J41) -> 309050.44 | AM41: =($P41*U41)*(1-$J41) -> 0 | AN41: =($P41*V41)*(1-$J41) -> 0 | AO41: =($P41*W41)*(1-$J41) -> 0 | AP41: =SUM(AK41:AO41) -> 309050.44 | AQ41: =S41*$Q41 -> 0 | AR41: =T41*$Q41 -> 69255 | AS41: =U41*$Q41 -> 0 | AT41: =V41*$Q41 -> 0 | AU41: =W41*$Q41 -> 0 | AV41: =SUM(AQ41:AU41) -> 69255 | AW41: =S41*$R41 -> 0 | AX41: =T41*$R41 -> 92340 | AY41: =U41*$R41 -> 0 | AZ41: =V41*$R41 -> 0 | BA41: =W41*$R41 -> 0 | BB41: =SUM(AW41:BA41) -> 92340 | BC41: =$Y41+$AE41+$AK41+$AQ41+AW41 -> 0 | BD41: =$Z41+$AF41+$AL41+AR41+AX41 -> 913069.46 | BE41: =$AA41+$AG41+$AM41+AS41+AY41 -> 0 | BF41: =$AB41+$AH41+$AN41+AT41+AZ41 -> 0 | BG41: =$AC41+$AI41+$AO41+AU41+BA41 -> 0 | BH41: =SUM(BC41:BG41) -> 913069.46 | BI41: =$Y41/$M41 -> 0 | BJ41: =$Z41/$M41 -> 96149.025 | BK41: =$AA41/$M41 -> 0 | BL41: =$AB41/$M41 -> 0 | BM41: =$AC41/$M41 -> 0 | BN41: =$AD41/$M41 -> 96149.025 | BO41: =$AE41/$M41 -> 0 | BP41: =$AF41/$M41 -> 346275 | BQ41: =$AG41/$M41 -> 0 | BR41: =$AH41/$M41 -> 0 | BS41: =$AI41/$M41 -> 0 | BT41: =$AJ41/$M41 -> 346275 | BU41: =$AK41/$M41 -> 0 | BV41: =$AL41/$M41 -> 309050.44 | BW41: =$AM41/$M41 -> 0 | BX41: =$AN41/$M41 -> 0 | BY41: =$AO41/$M41 -> 0 | BZ41: =$AP41/$M41 -> 309050.44 | CA41: =AQ41/$M41 -> 0 | CB41: =AR41/$M41 -> 69255 | CC41: =AS41/$M41 -> 0 | CD41: =AT41/$M41 -> 0 | CE41: =AU41/$M41 -> 0 | CF41: =AV41/$M41 -> 69255 | CG41: =AW41/$M41 -> 0 | CH41: =AX41/$M41 -> 92340 | ... CL41: =BB41/$M41 -> 92340 | CM41: =$BC41/$M41 -> 0 | CN41: =$BD41/$M41 -> 913069.46 | CO41: =$BE41/$M41 -> 0 | CP41: =$BF41/$M41 -> 0 | CQ41: =$BG41/$M41 -> 0 | CR41: =SUM(CM41:CQ41) -> 913069.46 | CS41: =K41-CR41 -> 1395430.5 | CU41: =D41 -> ARS | CV41: =VLOOKUP(CU41,DF:DG,2,0) -> 0.0006918517 | CW41: =K41*CV41 -> 1597.1396 | CX41: =BN41*CV41 -> 66.520866 | CY41: =BT41*CV41 -> 239.57095 | CZ41: =BZ41*CV41 -> 213.81707 | DA41: =CF41*CV41 -> 47.914189 | DB41: =CL41*CV41 -> 63.885586 | DC41: =CS41*CV41 -> 965.43099 | DD41: =VLOOKUP(A41,'Billing Report'!H:I,2,FALSE) -> Betfunok Timeline Takeover Nivel 1 2026-02-03 | DF41: KYD | DG41: 1.2000048
A42: 40921482 | B42: T3163157 | C42: 316315701 | D42: ARS | F42: 801900 | J42: =VLOOKUP($B42,'IMS Commission List'!E:CE,79,0)/100 -> 0.15 | K42: =SUM(E42:I42) -> 801900 | L42: =VLOOKUP($B42,'IMS Commission List'!E:V,18,0) -> ARS | M42: 1 | N42: =VLOOKUP($B42,'IMS Commission List'!E:T,16,0) -> MX | O42: =VLOOKUP($B42,'IMS Commission List'!E:CF,80,0) -> 0.049 | P42: =VLOOKUP($B42,'IMS Commission List'!E:CG,81,0) -> 0.1575 | Q42: =VLOOKUP($B42,'IMS Commission List'!E:CP,90,0) -> 0.03 | R42: =VLOOKUP($B42,'IMS Commission List'!E:CQ,91,0) -> 0.04 | S42: =$E42*$M42 -> 0 | T42: =$F42*$M42 -> 801900 | U42: =$G42*$M42 -> 0 | V42: =$H42*$M42 -> 0 | W42: =$I42*$M42 -> 0 | X42: =$K42*$M42 -> 801900 | Y42: =(S42*$O42)*(1-J42) -> 0 | Z42: =(T42*$O42)*(1-J42) -> 33399.135 | AA42: =(U42*$O42)*(1-J42) -> 0 | AB42: =(V42*$O42)*(1-J42) -> 0 | AC42: =(W42*$O42)*(1-J42) -> 0 | AD42: =SUM(Y42:AC42) -> 33399.135 | AE42: =S42*$J42 -> 0 | AF42: =T42*$J42 -> 120285 | AG42: =U42*$J42 -> 0 | AH42: =V42*$J42 -> 0 | AI42: =W42*$J42 -> 0 | AJ42: =SUM(AE42:AI42) -> 120285 | AK42: =($P42*S42)*(1-$J42) -> 0 | AL42: =($P42*T42)*(1-$J42) -> 107354.36 | AM42: =($P42*U42)*(1-$J42) -> 0 | AN42: =($P42*V42)*(1-$J42) -> 0 | AO42: =($P42*W42)*(1-$J42) -> 0 | AP42: =SUM(AK42:AO42) -> 107354.36 | AQ42: =S42*$Q42 -> 0 | AR42: =T42*$Q42 -> 24057 | AS42: =U42*$Q42 -> 0 | AT42: =V42*$Q42 -> 0 | AU42: =W42*$Q42 -> 0 | AV42: =SUM(AQ42:AU42) -> 24057 | AW42: =S42*$R42 -> 0 | AX42: =T42*$R42 -> 32076 | AY42: =U42*$R42 -> 0 | AZ42: =V42*$R42 -> 0 | BA42: =W42*$R42 -> 0 | BB42: =SUM(AW42:BA42) -> 32076 | BC42: =$Y42+$AE42+$AK42+$AQ42+AW42 -> 0 | BD42: =$Z42+$AF42+$AL42+AR42+AX42 -> 317171.5 | BE42: =$AA42+$AG42+$AM42+AS42+AY42 -> 0 | BF42: =$AB42+$AH42+$AN42+AT42+AZ42 -> 0 | BG42: =$AC42+$AI42+$AO42+AU42+BA42 -> 0 | BH42: =SUM(BC42:BG42) -> 317171.5 | BI42: =$Y42/$M42 -> 0 | BJ42: =$Z42/$M42 -> 33399.135 | BK42: =$AA42/$M42 -> 0 | BL42: =$AB42/$M42 -> 0 | BM42: =$AC42/$M42 -> 0 | BN42: =$AD42/$M42 -> 33399.135 | BO42: =$AE42/$M42 -> 0 | BP42: =$AF42/$M42 -> 120285 | BQ42: =$AG42/$M42 -> 0 | BR42: =$AH42/$M42 -> 0 | BS42: =$AI42/$M42 -> 0 | BT42: =$AJ42/$M42 -> 120285 | BU42: =$AK42/$M42 -> 0 | BV42: =$AL42/$M42 -> 107354.36 | BW42: =$AM42/$M42 -> 0 | BX42: =$AN42/$M42 -> 0 | BY42: =$AO42/$M42 -> 0 | BZ42: =$AP42/$M42 -> 107354.36 | CA42: =AQ42/$M42 -> 0 | CB42: =AR42/$M42 -> 24057 | CC42: =AS42/$M42 -> 0 | CD42: =AT42/$M42 -> 0 | CE42: =AU42/$M42 -> 0 | CF42: =AV42/$M42 -> 24057 | CG42: =AW42/$M42 -> 0 | CH42: =AX42/$M42 -> 32076 | ... CL42: =BB42/$M42 -> 32076 | CM42: =$BC42/$M42 -> 0 | CN42: =$BD42/$M42 -> 317171.5 | CO42: =$BE42/$M42 -> 0 | CP42: =$BF42/$M42 -> 0 | CQ42: =$BG42/$M42 -> 0 | CR42: =SUM(CM42:CQ42) -> 317171.5 | CS42: =K42-CR42 -> 484728.5 | CU42: =D42 -> ARS | CV42: =VLOOKUP(CU42,DF:DG,2,0) -> 0.0006918517 | CW42: =K42*CV42 -> 554.79588 | CX42: =BN42*CV42 -> 23.107248 | CY42: =BT42*CV42 -> 83.219382 | CZ42: =BZ42*CV42 -> 74.273298 | DA42: =CF42*CV42 -> 16.643876 | DB42: =CL42*CV42 -> 22.191835 | DC42: =CS42*CV42 -> 335.36024 | DD42: =VLOOKUP(A42,'Billing Report'!H:I,2,FALSE) -> HipodromoArgPal Estándar 2026-02-13 | DF42: LBP | DG42: 1.12766e-05
A43: 40921478 | B43: T3163157 | C43: 316315702 | D43: ARS | F43: 2308500 | J43: =VLOOKUP($B43,'IMS Commission List'!E:CE,79,0)/100 -> 0.15 | K43: =SUM(E43:I43) -> 2308500 | L43: =VLOOKUP($B43,'IMS Commission List'!E:V,18,0) -> ARS | M43: 1 | N43: =VLOOKUP($B43,'IMS Commission List'!E:T,16,0) -> MX | O43: =VLOOKUP($B43,'IMS Commission List'!E:CF,80,0) -> 0.049 | P43: =VLOOKUP($B43,'IMS Commission List'!E:CG,81,0) -> 0.1575 | Q43: =VLOOKUP($B43,'IMS Commission List'!E:CP,90,0) -> 0.03 | R43: =VLOOKUP($B43,'IMS Commission List'!E:CQ,91,0) -> 0.04 | S43: =$E43*$M43 -> 0 | T43: =$F43*$M43 -> 2308500 | U43: =$G43*$M43 -> 0 | V43: =$H43*$M43 -> 0 | W43: =$I43*$M43 -> 0 | X43: =$K43*$M43 -> 2308500 | Y43: =(S43*$O43)*(1-J43) -> 0 | Z43: =(T43*$O43)*(1-J43) -> 96149.025 | AA43: =(U43*$O43)*(1-J43) -> 0 | AB43: =(V43*$O43)*(1-J43) -> 0 | AC43: =(W43*$O43)*(1-J43) -> 0 | AD43: =SUM(Y43:AC43) -> 96149.025 | AE43: =S43*$J43 -> 0 | AF43: =T43*$J43 -> 346275 | AG43: =U43*$J43 -> 0 | AH43: =V43*$J43 -> 0 | AI43: =W43*$J43 -> 0 | AJ43: =SUM(AE43:AI43) -> 346275 | AK43: =($P43*S43)*(1-$J43) -> 0 | AL43: =($P43*T43)*(1-$J43) -> 309050.44 | AM43: =($P43*U43)*(1-$J43) -> 0 | AN43: =($P43*V43)*(1-$J43) -> 0 | AO43: =($P43*W43)*(1-$J43) -> 0 | AP43: =SUM(AK43:AO43) -> 309050.44 | AQ43: =S43*$Q43 -> 0 | AR43: =T43*$Q43 -> 69255 | AS43: =U43*$Q43 -> 0 | AT43: =V43*$Q43 -> 0 | AU43: =W43*$Q43 -> 0 | AV43: =SUM(AQ43:AU43) -> 69255 | AW43: =S43*$R43 -> 0 | AX43: =T43*$R43 -> 92340 | AY43: =U43*$R43 -> 0 | AZ43: =V43*$R43 -> 0 | BA43: =W43*$R43 -> 0 | BB43: =SUM(AW43:BA43) -> 92340 | BC43: =$Y43+$AE43+$AK43+$AQ43+AW43 -> 0 | BD43: =$Z43+$AF43+$AL43+AR43+AX43 -> 913069.46 | BE43: =$AA43+$AG43+$AM43+AS43+AY43 -> 0 | BF43: =$AB43+$AH43+$AN43+AT43+AZ43 -> 0 | BG43: =$AC43+$AI43+$AO43+AU43+BA43 -> 0 | BH43: =SUM(BC43:BG43) -> 913069.46 | BI43: =$Y43/$M43 -> 0 | BJ43: =$Z43/$M43 -> 96149.025 | BK43: =$AA43/$M43 -> 0 | BL43: =$AB43/$M43 -> 0 | BM43: =$AC43/$M43 -> 0 | BN43: =$AD43/$M43 -> 96149.025 | BO43: =$AE43/$M43 -> 0 | BP43: =$AF43/$M43 -> 346275 | BQ43: =$AG43/$M43 -> 0 | BR43: =$AH43/$M43 -> 0 | BS43: =$AI43/$M43 -> 0 | BT43: =$AJ43/$M43 -> 346275 | BU43: =$AK43/$M43 -> 0 | BV43: =$AL43/$M43 -> 309050.44 | BW43: =$AM43/$M43 -> 0 | BX43: =$AN43/$M43 -> 0 | BY43: =$AO43/$M43 -> 0 | BZ43: =$AP43/$M43 -> 309050.44 | CA43: =AQ43/$M43 -> 0 | CB43: =AR43/$M43 -> 69255 | CC43: =AS43/$M43 -> 0 | CD43: =AT43/$M43 -> 0 | CE43: =AU43/$M43 -> 0 | CF43: =AV43/$M43 -> 69255 | CG43: =AW43/$M43 -> 0 | CH43: =AX43/$M43 -> 92340 | ... CL43: =BB43/$M43 -> 92340 | CM43: =$BC43/$M43 -> 0 | CN43: =$BD43/$M43 -> 913069.46 | CO43: =$BE43/$M43 -> 0 | CP43: =$BF43/$M43 -> 0 | CQ43: =$BG43/$M43 -> 0 | CR43: =SUM(CM43:CQ43) -> 913069.46 | CS43: =K43-CR43 -> 1395430.5 | CU43: =D43 -> ARS | CV43: =VLOOKUP(CU43,DF:DG,2,0) -> 0.0006918517 | CW43: =K43*CV43 -> 1597.1396 | CX43: =BN43*CV43 -> 66.520866 | CY43: =BT43*CV43 -> 239.57095 | CZ43: =BZ43*CV43 -> 213.81707 | DA43: =CF43*CV43 -> 47.914189 | DB43: =CL43*CV43 -> 63.885586 | DC43: =CS43*CV43 -> 965.43099 | DD43: =VLOOKUP(A43,'Billing Report'!H:I,2,FALSE) -> HipodromoArgPal Timeline Takeover Nivel 1 2026-02-13 | DF43: MAD | DG43: 0.11004024
A44: 40855286 | B44: T3163161 | C44: 316316103 | D44: ARS | F44: 1710000 | J44: =VLOOKUP($B44,'IMS Commission List'!E:CE,79,0)/100 -> 0.08 | K44: =SUM(E44:I44) -> 1710000 | L44: =VLOOKUP($B44,'IMS Commission List'!E:V,18,0) -> ARS | M44: 1 | N44: =VLOOKUP($B44,'IMS Commission List'!E:T,16,0) -> MX | O44: =VLOOKUP($B44,'IMS Commission List'!E:CF,80,0) -> 0.049 | P44: =VLOOKUP($B44,'IMS Commission List'!E:CG,81,0) -> 0.1575 | Q44: =VLOOKUP($B44,'IMS Commission List'!E:CP,90,0) -> 0.03 | R44: =VLOOKUP($B44,'IMS Commission List'!E:CQ,91,0) -> 0.04 | S44: =$E44*$M44 -> 0 | T44: =$F44*$M44 -> 1710000 | U44: =$G44*$M44 -> 0 | V44: =$H44*$M44 -> 0 | W44: =$I44*$M44 -> 0 | X44: =$K44*$M44 -> 1710000 | Y44: =(S44*$O44)*(1-J44) -> 0 | Z44: =(T44*$O44)*(1-J44) -> 77086.8 | AA44: =(U44*$O44)*(1-J44) -> 0 | AB44: =(V44*$O44)*(1-J44) -> 0 | AC44: =(W44*$O44)*(1-J44) -> 0 | AD44: =SUM(Y44:AC44) -> 77086.8 | AE44: =S44*$J44 -> 0 | AF44: =T44*$J44 -> 136800 | AG44: =U44*$J44 -> 0 | AH44: =V44*$J44 -> 0 | AI44: =W44*$J44 -> 0 | AJ44: =SUM(AE44:AI44) -> 136800 | AK44: =($P44*S44)*(1-$J44) -> 0 | AL44: =($P44*T44)*(1-$J44) -> 247779 | AM44: =($P44*U44)*(1-$J44) -> 0 | AN44: =($P44*V44)*(1-$J44) -> 0 | AO44: =($P44*W44)*(1-$J44) -> 0 | AP44: =SUM(AK44:AO44) -> 247779 | AQ44: =S44*$Q44 -> 0 | AR44: =T44*$Q44 -> 51300 | AS44: =U44*$Q44 -> 0 | AT44: =V44*$Q44 -> 0 | AU44: =W44*$Q44 -> 0 | AV44: =SUM(AQ44:AU44) -> 51300 | AW44: =S44*$R44 -> 0 | AX44: =T44*$R44 -> 68400 | AY44: =U44*$R44 -> 0 | AZ44: =V44*$R44 -> 0 | BA44: =W44*$R44 -> 0 | BB44: =SUM(AW44:BA44) -> 68400 | BC44: =$Y44+$AE44+$AK44+$AQ44+AW44 -> 0 | BD44: =$Z44+$AF44+$AL44+AR44+AX44 -> 581365.8 | BE44: =$AA44+$AG44+$AM44+AS44+AY44 -> 0 | BF44: =$AB44+$AH44+$AN44+AT44+AZ44 -> 0 | BG44: =$AC44+$AI44+$AO44+AU44+BA44 -> 0 | BH44: =SUM(BC44:BG44) -> 581365.8 | BI44: =$Y44/$M44 -> 0 | BJ44: =$Z44/$M44 -> 77086.8 | BK44: =$AA44/$M44 -> 0 | BL44: =$AB44/$M44 -> 0 | BM44: =$AC44/$M44 -> 0 | BN44: =$AD44/$M44 -> 77086.8 | BO44: =$AE44/$M44 -> 0 | BP44: =$AF44/$M44 -> 136800 | BQ44: =$AG44/$M44 -> 0 | BR44: =$AH44/$M44 -> 0 | BS44: =$AI44/$M44 -> 0 | BT44: =$AJ44/$M44 -> 136800 | BU44: =$AK44/$M44 -> 0 | BV44: =$AL44/$M44 -> 247779 | BW44: =$AM44/$M44 -> 0 | BX44: =$AN44/$M44 -> 0 | BY44: =$AO44/$M44 -> 0 | BZ44: =$AP44/$M44 -> 247779 | CA44: =AQ44/$M44 -> 0 | CB44: =AR44/$M44 -> 51300 | CC44: =AS44/$M44 -> 0 | CD44: =AT44/$M44 -> 0 | CE44: =AU44/$M44 -> 0 | CF44: =AV44/$M44 -> 51300 | CG44: =AW44/$M44 -> 0 | CH44: =AX44/$M44 -> 68400 | ... CL44: =BB44/$M44 -> 68400 | CM44: =$BC44/$M44 -> 0 | CN44: =$BD44/$M44 -> 581365.8 | CO44: =$BE44/$M44 -> 0 | CP44: =$BF44/$M44 -> 0 | CQ44: =$BG44/$M44 -> 0 | CR44: =SUM(CM44:CQ44) -> 581365.8 | CS44: =K44-CR44 -> 1128634.2 | CU44: =D44 -> ARS | CV44: =VLOOKUP(CU44,DF:DG,2,0) -> 0.0006918517 | CW44: =K44*CV44 -> 1183.0664 | CX44: =BN44*CV44 -> 53.332634 | CY44: =BT44*CV44 -> 94.645313 | CZ44: =BZ44*CV44 -> 171.42632 | DA44: =CF44*CV44 -> 35.491992 | DB44: =CL44*CV44 -> 47.322656 | DC44: =CS44*CV44 -> 780.84749 | DD44: =VLOOKUP(A44,'Billing Report'!H:I,2,FALSE) -> MLA DD2 Timeline- 2/2 | DF44: MKD | DG44: 0.019317801
A45: 40850980 | B45: T3163161 | C45: 316316102 | D45: ARS | F45: 594000 | J45: =VLOOKUP($B45,'IMS Commission List'!E:CE,79,0)/100 -> 0.08 | K45: =SUM(E45:I45) -> 594000 | L45: =VLOOKUP($B45,'IMS Commission List'!E:V,18,0) -> ARS | M45: 1 | N45: =VLOOKUP($B45,'IMS Commission List'!E:T,16,0) -> MX | O45: =VLOOKUP($B45,'IMS Commission List'!E:CF,80,0) -> 0.049 | P45: =VLOOKUP($B45,'IMS Commission List'!E:CG,81,0) -> 0.1575 | Q45: =VLOOKUP($B45,'IMS Commission List'!E:CP,90,0) -> 0.03 | R45: =VLOOKUP($B45,'IMS Commission List'!E:CQ,91,0) -> 0.04 | S45: =$E45*$M45 -> 0 | T45: =$F45*$M45 -> 594000 | U45: =$G45*$M45 -> 0 | V45: =$H45*$M45 -> 0 | W45: =$I45*$M45 -> 0 | X45: =$K45*$M45 -> 594000 | Y45: =(S45*$O45)*(1-J45) -> 0 | Z45: =(T45*$O45)*(1-J45) -> 26777.52 | AA45: =(U45*$O45)*(1-J45) -> 0 | AB45: =(V45*$O45)*(1-J45) -> 0 | AC45: =(W45*$O45)*(1-J45) -> 0 | AD45: =SUM(Y45:AC45) -> 26777.52 | AE45: =S45*$J45 -> 0 | AF45: =T45*$J45 -> 47520 | AG45: =U45*$J45 -> 0 | AH45: =V45*$J45 -> 0 | AI45: =W45*$J45 -> 0 | AJ45: =SUM(AE45:AI45) -> 47520 | AK45: =($P45*S45)*(1-$J45) -> 0 | AL45: =($P45*T45)*(1-$J45) -> 86070.6 | AM45: =($P45*U45)*(1-$J45) -> 0 | AN45: =($P45*V45)*(1-$J45) -> 0 | AO45: =($P45*W45)*(1-$J45) -> 0 | AP45: =SUM(AK45:AO45) -> 86070.6 | AQ45: =S45*$Q45 -> 0 | AR45: =T45*$Q45 -> 17820 | AS45: =U45*$Q45 -> 0 | AT45: =V45*$Q45 -> 0 | AU45: =W45*$Q45 -> 0 | AV45: =SUM(AQ45:AU45) -> 17820 | AW45: =S45*$R45 -> 0 | AX45: =T45*$R45 -> 23760 | AY45: =U45*$R45 -> 0 | AZ45: =V45*$R45 -> 0 | BA45: =W45*$R45 -> 0 | BB45: =SUM(AW45:BA45) -> 23760 | BC45: =$Y45+$AE45+$AK45+$AQ45+AW45 -> 0 | BD45: =$Z45+$AF45+$AL45+AR45+AX45 -> 201948.12 | BE45: =$AA45+$AG45+$AM45+AS45+AY45 -> 0 | BF45: =$AB45+$AH45+$AN45+AT45+AZ45 -> 0 | BG45: =$AC45+$AI45+$AO45+AU45+BA45 -> 0 | BH45: =SUM(BC45:BG45) -> 201948.12 | BI45: =$Y45/$M45 -> 0 | BJ45: =$Z45/$M45 -> 26777.52 | BK45: =$AA45/$M45 -> 0 | BL45: =$AB45/$M45 -> 0 | BM45: =$AC45/$M45 -> 0 | BN45: =$AD45/$M45 -> 26777.52 | BO45: =$AE45/$M45 -> 0 | BP45: =$AF45/$M45 -> 47520 | BQ45: =$AG45/$M45 -> 0 | BR45: =$AH45/$M45 -> 0 | BS45: =$AI45/$M45 -> 0 | BT45: =$AJ45/$M45 -> 47520 | BU45: =$AK45/$M45 -> 0 | BV45: =$AL45/$M45 -> 86070.6 | BW45: =$AM45/$M45 -> 0 | BX45: =$AN45/$M45 -> 0 | BY45: =$AO45/$M45 -> 0 | BZ45: =$AP45/$M45 -> 86070.6 | CA45: =AQ45/$M45 -> 0 | CB45: =AR45/$M45 -> 17820 | CC45: =AS45/$M45 -> 0 | CD45: =AT45/$M45 -> 0 | CE45: =AU45/$M45 -> 0 | CF45: =AV45/$M45 -> 17820 | CG45: =AW45/$M45 -> 0 | CH45: =AX45/$M45 -> 23760 | ... CL45: =BB45/$M45 -> 23760 | CM45: =$BC45/$M45 -> 0 | CN45: =$BD45/$M45 -> 201948.12 | CO45: =$BE45/$M45 -> 0 | CP45: =$BF45/$M45 -> 0 | CQ45: =$BG45/$M45 -> 0 | CR45: =SUM(CM45:CQ45) -> 201948.12 | CS45: =K45-CR45 -> 392051.88 | CU45: =D45 -> ARS | CV45: =VLOOKUP(CU45,DF:DG,2,0) -> 0.0006918517 | CW45: =K45*CV45 -> 410.95991 | CX45: =BN45*CV45 -> 18.526073 | CY45: =BT45*CV45 -> 32.876793 | CZ45: =BZ45*CV45 -> 59.548091 | DA45: =CF45*CV45 -> 12.328797 | DB45: =CL45*CV45 -> 16.438396 | DC45: =CS45*CV45 -> 271.24176 | DD45: =VLOOKUP(A45,'Billing Report'!H:I,2,FALSE) -> MLA DD2 Spotlight- 2/2 | DF45: MXN | DG45: 0.057707417
A46: 40459480 | B46: T3184062 | C46: 318406201 | D46: ARS | G46: 718276.95 | J46: =VLOOKUP($B46,'IMS Commission List'!E:CE,79,0)/100 -> 0.15 | K46: =SUM(E46:I46) -> 718276.95 | L46: =VLOOKUP($B46,'IMS Commission List'!E:V,18,0) -> ARS | M46: 1 | N46: =VLOOKUP($B46,'IMS Commission List'!E:T,16,0) -> MX | O46: =VLOOKUP($B46,'IMS Commission List'!E:CF,80,0) -> 0.049 | P46: =VLOOKUP($B46,'IMS Commission List'!E:CG,81,0) -> 0.1575 | Q46: =VLOOKUP($B46,'IMS Commission List'!E:CP,90,0) -> 0.03 | R46: =VLOOKUP($B46,'IMS Commission List'!E:CQ,91,0) -> 0.04 | S46: =$E46*$M46 -> 0 | T46: =$F46*$M46 -> 0 | U46: =$G46*$M46 -> 718276.95 | V46: =$H46*$M46 -> 0 | W46: =$I46*$M46 -> 0 | X46: =$K46*$M46 -> 718276.95 | Y46: =(S46*$O46)*(1-J46) -> 0 | Z46: =(T46*$O46)*(1-J46) -> 0 | AA46: =(U46*$O46)*(1-J46) -> 29916.235 | AB46: =(V46*$O46)*(1-J46) -> 0 | AC46: =(W46*$O46)*(1-J46) -> 0 | AD46: =SUM(Y46:AC46) -> 29916.235 | AE46: =S46*$J46 -> 0 | AF46: =T46*$J46 -> 0 | AG46: =U46*$J46 -> 107741.54 | AH46: =V46*$J46 -> 0 | AI46: =W46*$J46 -> 0 | AJ46: =SUM(AE46:AI46) -> 107741.54 | AK46: =($P46*S46)*(1-$J46) -> 0 | AL46: =($P46*T46)*(1-$J46) -> 0 | AM46: =($P46*U46)*(1-$J46) -> 96159.327 | AN46: =($P46*V46)*(1-$J46) -> 0 | AO46: =($P46*W46)*(1-$J46) -> 0 | AP46: =SUM(AK46:AO46) -> 96159.327 | AQ46: =S46*$Q46 -> 0 | AR46: =T46*$Q46 -> 0 | AS46: =U46*$Q46 -> 21548.308 | AT46: =V46*$Q46 -> 0 | AU46: =W46*$Q46 -> 0 | AV46: =SUM(AQ46:AU46) -> 21548.308 | AW46: =S46*$R46 -> 0 | AX46: =T46*$R46 -> 0 | AY46: =U46*$R46 -> 28731.078 | AZ46: =V46*$R46 -> 0 | BA46: =W46*$R46 -> 0 | BB46: =SUM(AW46:BA46) -> 28731.078 | BC46: =$Y46+$AE46+$AK46+$AQ46+AW46 -> 0 | BD46: =$Z46+$AF46+$AL46+AR46+AX46 -> 0 | BE46: =$AA46+$AG46+$AM46+AS46+AY46 -> 284096.49 | BF46: =$AB46+$AH46+$AN46+AT46+AZ46 -> 0 | BG46: =$AC46+$AI46+$AO46+AU46+BA46 -> 0 | BH46: =SUM(BC46:BG46) -> 284096.49 | BI46: =$Y46/$M46 -> 0 | BJ46: =$Z46/$M46 -> 0 | BK46: =$AA46/$M46 -> 29916.235 | BL46: =$AB46/$M46 -> 0 | BM46: =$AC46/$M46 -> 0 | BN46: =$AD46/$M46 -> 29916.235 | BO46: =$AE46/$M46 -> 0 | BP46: =$AF46/$M46 -> 0 | BQ46: =$AG46/$M46 -> 107741.54 | BR46: =$AH46/$M46 -> 0 | BS46: =$AI46/$M46 -> 0 | BT46: =$AJ46/$M46 -> 107741.54 | BU46: =$AK46/$M46 -> 0 | BV46: =$AL46/$M46 -> 0 | BW46: =$AM46/$M46 -> 96159.327 | BX46: =$AN46/$M46 -> 0 | BY46: =$AO46/$M46 -> 0 | BZ46: =$AP46/$M46 -> 96159.327 | CA46: =AQ46/$M46 -> 0 | CB46: =AR46/$M46 -> 0 | CC46: =AS46/$M46 -> 21548.308 | CD46: =AT46/$M46 -> 0 | CE46: =AU46/$M46 -> 0 | CF46: =AV46/$M46 -> 21548.308 | CG46: =AW46/$M46 -> 0 | CH46: =AX46/$M46 -> 0 | ... CL46: =BB46/$M46 -> 28731.078 | CM46: =$BC46/$M46 -> 0 | CN46: =$BD46/$M46 -> 0 | CO46: =$BE46/$M46 -> 284096.49 | CP46: =$BF46/$M46 -> 0 | CQ46: =$BG46/$M46 -> 0 | CR46: =SUM(CM46:CQ46) -> 284096.49 | CS46: =K46-CR46 -> 434180.46 | CU46: =D46 -> ARS | CV46: =VLOOKUP(CU46,DF:DG,2,0) -> 0.0006918517 | CW46: =K46*CV46 -> 496.94113 | CX46: =BN46*CV46 -> 20.697598 | CY46: =BT46*CV46 -> 74.541169 | CZ46: =BZ46*CV46 -> 66.527994 | DA46: =CF46*CV46 -> 14.908234 | DB46: =CL46*CV46 -> 19.877645 | DC46: =CS46*CV46 -> 300.38849 | DD46: =VLOOKUP(A46,'Billing Report'!H:I,2,FALSE) -> 2025_MODO_BRANDING_PROMO_DIARCO_GEO_TWITTER_NU_AW_NOV | DF46: MYR | DG46: 0.25375011
A47: 40968095 | B47: T3184279 | C47: 318427901 | D47: ARS | G47: 1206718.5 | J47: =VLOOKUP($B47,'IMS Commission List'!E:CE,79,0)/100 -> 0.15 | K47: =SUM(E47:I47) -> 1206718.5 | L47: =VLOOKUP($B47,'IMS Commission List'!E:V,18,0) -> ARS | M47: 1 | N47: =VLOOKUP($B47,'IMS Commission List'!E:T,16,0) -> MX | O47: =VLOOKUP($B47,'IMS Commission List'!E:CF,80,0) -> 0.049 | P47: =VLOOKUP($B47,'IMS Commission List'!E:CG,81,0) -> 0.1575 | Q47: =VLOOKUP($B47,'IMS Commission List'!E:CP,90,0) -> 0.03 | R47: =VLOOKUP($B47,'IMS Commission List'!E:CQ,91,0) -> 0.04 | S47: =$E47*$M47 -> 0 | T47: =$F47*$M47 -> 0 | U47: =$G47*$M47 -> 1206718.5 | V47: =$H47*$M47 -> 0 | W47: =$I47*$M47 -> 0 | X47: =$K47*$M47 -> 1206718.5 | Y47: =(S47*$O47)*(1-J47) -> 0 | Z47: =(T47*$O47)*(1-J47) -> 0 | AA47: =(U47*$O47)*(1-J47) -> 50259.825 | AB47: =(V47*$O47)*(1-J47) -> 0 | AC47: =(W47*$O47)*(1-J47) -> 0 | AD47: =SUM(Y47:AC47) -> 50259.825 | AE47: =S47*$J47 -> 0 | AF47: =T47*$J47 -> 0 | AG47: =U47*$J47 -> 181007.77 | AH47: =V47*$J47 -> 0 | AI47: =W47*$J47 -> 0 | AJ47: =SUM(AE47:AI47) -> 181007.77 | AK47: =($P47*S47)*(1-$J47) -> 0 | AL47: =($P47*T47)*(1-$J47) -> 0 | AM47: =($P47*U47)*(1-$J47) -> 161549.44 | AN47: =($P47*V47)*(1-$J47) -> 0 | AO47: =($P47*W47)*(1-$J47) -> 0 | AP47: =SUM(AK47:AO47) -> 161549.44 | AQ47: =S47*$Q47 -> 0 | AR47: =T47*$Q47 -> 0 | AS47: =U47*$Q47 -> 36201.554 | AT47: =V47*$Q47 -> 0 | AU47: =W47*$Q47 -> 0 | AV47: =SUM(AQ47:AU47) -> 36201.554 | AW47: =S47*$R47 -> 0 | AX47: =T47*$R47 -> 0 | AY47: =U47*$R47 -> 48268.739 | AZ47: =V47*$R47 -> 0 | BA47: =W47*$R47 -> 0 | BB47: =SUM(AW47:BA47) -> 48268.739 | BC47: =$Y47+$AE47+$AK47+$AQ47+AW47 -> 0 | BD47: =$Z47+$AF47+$AL47+AR47+AX47 -> 0 | BE47: =$AA47+$AG47+$AM47+AS47+AY47 -> 477287.33 | BF47: =$AB47+$AH47+$AN47+AT47+AZ47 -> 0 | BG47: =$AC47+$AI47+$AO47+AU47+BA47 -> 0 | BH47: =SUM(BC47:BG47) -> 477287.33 | BI47: =$Y47/$M47 -> 0 | BJ47: =$Z47/$M47 -> 0 | BK47: =$AA47/$M47 -> 50259.825 | BL47: =$AB47/$M47 -> 0 | BM47: =$AC47/$M47 -> 0 | BN47: =$AD47/$M47 -> 50259.825 | BO47: =$AE47/$M47 -> 0 | BP47: =$AF47/$M47 -> 0 | BQ47: =$AG47/$M47 -> 181007.77 | BR47: =$AH47/$M47 -> 0 | BS47: =$AI47/$M47 -> 0 | BT47: =$AJ47/$M47 -> 181007.77 | BU47: =$AK47/$M47 -> 0 | BV47: =$AL47/$M47 -> 0 | BW47: =$AM47/$M47 -> 161549.44 | BX47: =$AN47/$M47 -> 0 | BY47: =$AO47/$M47 -> 0 | BZ47: =$AP47/$M47 -> 161549.44 | CA47: =AQ47/$M47 -> 0 | CB47: =AR47/$M47 -> 0 | CC47: =AS47/$M47 -> 36201.554 | CD47: =AT47/$M47 -> 0 | CE47: =AU47/$M47 -> 0 | CF47: =AV47/$M47 -> 36201.554 | CG47: =AW47/$M47 -> 0 | CH47: =AX47/$M47 -> 0 | ... CL47: =BB47/$M47 -> 48268.739 | CM47: =$BC47/$M47 -> 0 | CN47: =$BD47/$M47 -> 0 | CO47: =$BE47/$M47 -> 477287.33 | CP47: =$BF47/$M47 -> 0 | CQ47: =$BG47/$M47 -> 0 | CR47: =SUM(CM47:CQ47) -> 477287.33 | CS47: =K47-CR47 -> 729431.15 | CU47: =D47 -> ARS | CV47: =VLOOKUP(CU47,DF:DG,2,0) -> 0.0006918517 | CW47: =K47*CV47 -> 834.87023 | CX47: =BN47*CV47 -> 34.772345 | CY47: =BT47*CV47 -> 125.23053 | CZ47: =BZ47*CV47 -> 111.76825 | DA47: =CF47*CV47 -> 25.046107 | DB47: =CL47*CV47 -> 33.394809 | DC47: =CS47*CV47 -> 504.65818 | DD47: =VLOOKUP(A47,'Billing Report'!H:I,2,FALSE) -> EJE_Clics_Institucional_FEB/MAR26 (Inscripciones) | DF47: NGN | DG47: 0.000720119
A48: 40497612 | B48: T3186988 | C48: 318698801 | D48: ARS | G48: 1216795.6 | J48: =VLOOKUP($B48,'IMS Commission List'!E:CE,79,0)/100 -> 0.15 | K48: =SUM(E48:I48) -> 1216795.6 | L48: =VLOOKUP($B48,'IMS Commission List'!E:V,18,0) -> ARS | M48: 1 | N48: =VLOOKUP($B48,'IMS Commission List'!E:T,16,0) -> MX | O48: =VLOOKUP($B48,'IMS Commission List'!E:CF,80,0) -> 0.049 | P48: =VLOOKUP($B48,'IMS Commission List'!E:CG,81,0) -> 0.1575 | Q48: =VLOOKUP($B48,'IMS Commission List'!E:CP,90,0) -> 0.03 | R48: =VLOOKUP($B48,'IMS Commission List'!E:CQ,91,0) -> 0.04 | S48: =$E48*$M48 -> 0 | T48: =$F48*$M48 -> 0 | U48: =$G48*$M48 -> 1216795.6 | V48: =$H48*$M48 -> 0 | W48: =$I48*$M48 -> 0 | X48: =$K48*$M48 -> 1216795.6 | Y48: =(S48*$O48)*(1-J48) -> 0 | Z48: =(T48*$O48)*(1-J48) -> 0 | AA48: =(U48*$O48)*(1-J48) -> 50679.538 | AB48: =(V48*$O48)*(1-J48) -> 0 | AC48: =(W48*$O48)*(1-J48) -> 0 | AD48: =SUM(Y48:AC48) -> 50679.538 | AE48: =S48*$J48 -> 0 | AF48: =T48*$J48 -> 0 | AG48: =U48*$J48 -> 182519.34 | AH48: =V48*$J48 -> 0 | AI48: =W48*$J48 -> 0 | AJ48: =SUM(AE48:AI48) -> 182519.34 | AK48: =($P48*S48)*(1-$J48) -> 0 | AL48: =($P48*T48)*(1-$J48) -> 0 | AM48: =($P48*U48)*(1-$J48) -> 162898.51 | AN48: =($P48*V48)*(1-$J48) -> 0 | AO48: =($P48*W48)*(1-$J48) -> 0 | AP48: =SUM(AK48:AO48) -> 162898.51 | AQ48: =S48*$Q48 -> 0 | AR48: =T48*$Q48 -> 0 | AS48: =U48*$Q48 -> 36503.869 | AT48: =V48*$Q48 -> 0 | AU48: =W48*$Q48 -> 0 | AV48: =SUM(AQ48:AU48) -> 36503.869 | AW48: =S48*$R48 -> 0 | AX48: =T48*$R48 -> 0 | AY48: =U48*$R48 -> 48671.825 | AZ48: =V48*$R48 -> 0 | BA48: =W48*$R48 -> 0 | BB48: =SUM(AW48:BA48) -> 48671.825 | BC48: =$Y48+$AE48+$AK48+$AQ48+AW48 -> 0 | BD48: =$Z48+$AF48+$AL48+AR48+AX48 -> 0 | BE48: =$AA48+$AG48+$AM48+AS48+AY48 -> 481273.09 | BF48: =$AB48+$AH48+$AN48+AT48+AZ48 -> 0 | BG48: =$AC48+$AI48+$AO48+AU48+BA48 -> 0 | BH48: =SUM(BC48:BG48) -> 481273.09 | BI48: =$Y48/$M48 -> 0 | BJ48: =$Z48/$M48 -> 0 | BK48: =$AA48/$M48 -> 50679.538 | BL48: =$AB48/$M48 -> 0 | BM48: =$AC48/$M48 -> 0 | BN48: =$AD48/$M48 -> 50679.538 | BO48: =$AE48/$M48 -> 0 | BP48: =$AF48/$M48 -> 0 | BQ48: =$AG48/$M48 -> 182519.34 | BR48: =$AH48/$M48 -> 0 | BS48: =$AI48/$M48 -> 0 | BT48: =$AJ48/$M48 -> 182519.34 | BU48: =$AK48/$M48 -> 0 | BV48: =$AL48/$M48 -> 0 | BW48: =$AM48/$M48 -> 162898.51 | BX48: =$AN48/$M48 -> 0 | BY48: =$AO48/$M48 -> 0 | BZ48: =$AP48/$M48 -> 162898.51 | CA48: =AQ48/$M48 -> 0 | CB48: =AR48/$M48 -> 0 | CC48: =AS48/$M48 -> 36503.869 | CD48: =AT48/$M48 -> 0 | CE48: =AU48/$M48 -> 0 | CF48: =AV48/$M48 -> 36503.869 | CG48: =AW48/$M48 -> 0 | CH48: =AX48/$M48 -> 0 | ... CL48: =BB48/$M48 -> 48671.825 | CM48: =$BC48/$M48 -> 0 | CN48: =$BD48/$M48 -> 0 | CO48: =$BE48/$M48 -> 481273.09 | CP48: =$BF48/$M48 -> 0 | CQ48: =$BG48/$M48 -> 0 | CR48: =SUM(CM48:CQ48) -> 481273.09 | CS48: =K48-CR48 -> 735522.54 | CU48: =D48 -> ARS | CV48: =VLOOKUP(CU48,DF:DG,2,0) -> 0.0006918517 | CW48: =K48*CV48 -> 841.84213 | CX48: =BN48*CV48 -> 35.062725 | CY48: =BT48*CV48 -> 126.27632 | CZ48: =BZ48*CV48 -> 112.70161 | DA48: =CF48*CV48 -> 25.255264 | DB48: =CL48*CV48 -> 33.673685 | DC48: =CS48*CV48 -> 508.87252 | DD48: =VLOOKUP(A48,'Billing Report'!H:I,2,FALSE) -> bull_cnmk_all_trafico_X_all_broad_gene_ticket_ao | DF48: NOK | DG48: 0.10420737
A49: 40497187 | B49: T3186988 | C49: 318698801 | D49: ARS | G49: 1214635.5 | J49: =VLOOKUP($B49,'IMS Commission List'!E:CE,79,0)/100 -> 0.15 | K49: =SUM(E49:I49) -> 1214635.5 | L49: =VLOOKUP($B49,'IMS Commission List'!E:V,18,0) -> ARS | M49: 1 | N49: =VLOOKUP($B49,'IMS Commission List'!E:T,16,0) -> MX | O49: =VLOOKUP($B49,'IMS Commission List'!E:CF,80,0) -> 0.049 | P49: =VLOOKUP($B49,'IMS Commission List'!E:CG,81,0) -> 0.1575 | Q49: =VLOOKUP($B49,'IMS Commission List'!E:CP,90,0) -> 0.03 | R49: =VLOOKUP($B49,'IMS Commission List'!E:CQ,91,0) -> 0.04 | S49: =$E49*$M49 -> 0 | T49: =$F49*$M49 -> 0 | U49: =$G49*$M49 -> 1214635.5 | V49: =$H49*$M49 -> 0 | W49: =$I49*$M49 -> 0 | X49: =$K49*$M49 -> 1214635.5 | Y49: =(S49*$O49)*(1-J49) -> 0 | Z49: =(T49*$O49)*(1-J49) -> 0 | AA49: =(U49*$O49)*(1-J49) -> 50589.568 | AB49: =(V49*$O49)*(1-J49) -> 0 | AC49: =(W49*$O49)*(1-J49) -> 0 | AD49: =SUM(Y49:AC49) -> 50589.568 | AE49: =S49*$J49 -> 0 | AF49: =T49*$J49 -> 0 | AG49: =U49*$J49 -> 182195.32 | AH49: =V49*$J49 -> 0 | AI49: =W49*$J49 -> 0 | AJ49: =SUM(AE49:AI49) -> 182195.32 | AK49: =($P49*S49)*(1-$J49) -> 0 | AL49: =($P49*T49)*(1-$J49) -> 0 | AM49: =($P49*U49)*(1-$J49) -> 162609.33 | AN49: =($P49*V49)*(1-$J49) -> 0 | AO49: =($P49*W49)*(1-$J49) -> 0 | AP49: =SUM(AK49:AO49) -> 162609.33 | AQ49: =S49*$Q49 -> 0 | AR49: =T49*$Q49 -> 0 | AS49: =U49*$Q49 -> 36439.065 | AT49: =V49*$Q49 -> 0 | AU49: =W49*$Q49 -> 0 | AV49: =SUM(AQ49:AU49) -> 36439.065 | AW49: =S49*$R49 -> 0 | AX49: =T49*$R49 -> 0 | AY49: =U49*$R49 -> 48585.42 | AZ49: =V49*$R49 -> 0 | BA49: =W49*$R49 -> 0 | BB49: =SUM(AW49:BA49) -> 48585.42 | BC49: =$Y49+$AE49+$AK49+$AQ49+AW49 -> 0 | BD49: =$Z49+$AF49+$AL49+AR49+AX49 -> 0 | BE49: =$AA49+$AG49+$AM49+AS49+AY49 -> 480418.7 | BF49: =$AB49+$AH49+$AN49+AT49+AZ49 -> 0 | BG49: =$AC49+$AI49+$AO49+AU49+BA49 -> 0 | BH49: =SUM(BC49:BG49) -> 480418.7 | BI49: =$Y49/$M49 -> 0 | BJ49: =$Z49/$M49 -> 0 | BK49: =$AA49/$M49 -> 50589.568 | BL49: =$AB49/$M49 -> 0 | BM49: =$AC49/$M49 -> 0 | BN49: =$AD49/$M49 -> 50589.568 | BO49: =$AE49/$M49 -> 0 | BP49: =$AF49/$M49 -> 0 | BQ49: =$AG49/$M49 -> 182195.32 | BR49: =$AH49/$M49 -> 0 | BS49: =$AI49/$M49 -> 0 | BT49: =$AJ49/$M49 -> 182195.32 | BU49: =$AK49/$M49 -> 0 | BV49: =$AL49/$M49 -> 0 | BW49: =$AM49/$M49 -> 162609.33 | BX49: =$AN49/$M49 -> 0 | BY49: =$AO49/$M49 -> 0 | BZ49: =$AP49/$M49 -> 162609.33 | CA49: =AQ49/$M49 -> 0 | CB49: =AR49/$M49 -> 0 | CC49: =AS49/$M49 -> 36439.065 | CD49: =AT49/$M49 -> 0 | CE49: =AU49/$M49 -> 0 | CF49: =AV49/$M49 -> 36439.065 | CG49: =AW49/$M49 -> 0 | CH49: =AX49/$M49 -> 0 | ... CL49: =BB49/$M49 -> 48585.42 | CM49: =$BC49/$M49 -> 0 | CN49: =$BD49/$M49 -> 0 | CO49: =$BE49/$M49 -> 480418.7 | CP49: =$BF49/$M49 -> 0 | CQ49: =$BG49/$M49 -> 0 | CR49: =SUM(CM49:CQ49) -> 480418.7 | CS49: =K49-CR49 -> 734216.79 | CU49: =D49 -> ARS | CV49: =VLOOKUP(CU49,DF:DG,2,0) -> 0.0006918517 | CW49: =K49*CV49 -> 840.34763 | CX49: =BN49*CV49 -> 35.000479 | CY49: =BT49*CV49 -> 126.05214 | CZ49: =BZ49*CV49 -> 112.50154 | DA49: =CF49*CV49 -> 25.210429 | DB49: =CL49*CV49 -> 33.613905 | DC49: =CS49*CV49 -> 507.96913 | DD49: =VLOOKUP(A49,'Billing Report'!H:I,2,FALSE) -> bull_cnmk_all_venta_X_all_broad_gene_ticket_ao | DF49: NZD | DG49: 0.60458213
A50: 40926151 | B50: T3203120 | C50: 320312002 | D50: ARS | G50: 643873.17 | J50: =VLOOKUP($B50,'IMS Commission List'!E:CE,79,0)/100 -> 0.08 | K50: =SUM(E50:I50) -> 643873.17 | L50: =VLOOKUP($B50,'IMS Commission List'!E:V,18,0) -> ARS | M50: 1 | N50: =VLOOKUP($B50,'IMS Commission List'!E:T,16,0) -> MX | O50: =VLOOKUP($B50,'IMS Commission List'!E:CF,80,0) -> 0.049 | P50: =VLOOKUP($B50,'IMS Commission List'!E:CG,81,0) -> 0.1575 | Q50: =VLOOKUP($B50,'IMS Commission List'!E:CP,90,0) -> 0.03 | R50: =VLOOKUP($B50,'IMS Commission List'!E:CQ,91,0) -> 0.04 | S50: =$E50*$M50 -> 0 | T50: =$F50*$M50 -> 0 | U50: =$G50*$M50 -> 643873.17 | V50: =$H50*$M50 -> 0 | W50: =$I50*$M50 -> 0 | X50: =$K50*$M50 -> 643873.17 | Y50: =(S50*$O50)*(1-J50) -> 0 | Z50: =(T50*$O50)*(1-J50) -> 0 | AA50: =(U50*$O50)*(1-J50) -> 29025.803 | AB50: =(V50*$O50)*(1-J50) -> 0 | AC50: =(W50*$O50)*(1-J50) -> 0 | AD50: =SUM(Y50:AC50) -> 29025.803 | AE50: =S50*$J50 -> 0 | AF50: =T50*$J50 -> 0 | AG50: =U50*$J50 -> 51509.854 | AH50: =V50*$J50 -> 0 | AI50: =W50*$J50 -> 0 | AJ50: =SUM(AE50:AI50) -> 51509.854 | AK50: =($P50*S50)*(1-$J50) -> 0 | AL50: =($P50*T50)*(1-$J50) -> 0 | AM50: =($P50*U50)*(1-$J50) -> 93297.222 | AN50: =($P50*V50)*(1-$J50) -> 0 | AO50: =($P50*W50)*(1-$J50) -> 0 | AP50: =SUM(AK50:AO50) -> 93297.222 | AQ50: =S50*$Q50 -> 0 | AR50: =T50*$Q50 -> 0 | AS50: =U50*$Q50 -> 19316.195 | AT50: =V50*$Q50 -> 0 | AU50: =W50*$Q50 -> 0 | AV50: =SUM(AQ50:AU50) -> 19316.195 | AW50: =S50*$R50 -> 0 | AX50: =T50*$R50 -> 0 | AY50: =U50*$R50 -> 25754.927 | AZ50: =V50*$R50 -> 0 | BA50: =W50*$R50 -> 0 | BB50: =SUM(AW50:BA50) -> 25754.927 | BC50: =$Y50+$AE50+$AK50+$AQ50+AW50 -> 0 | BD50: =$Z50+$AF50+$AL50+AR50+AX50 -> 0 | BE50: =$AA50+$AG50+$AM50+AS50+AY50 -> 218904 | BF50: =$AB50+$AH50+$AN50+AT50+AZ50 -> 0 | BG50: =$AC50+$AI50+$AO50+AU50+BA50 -> 0 | BH50: =SUM(BC50:BG50) -> 218904 | BI50: =$Y50/$M50 -> 0 | BJ50: =$Z50/$M50 -> 0 | BK50: =$AA50/$M50 -> 29025.803 | BL50: =$AB50/$M50 -> 0 | BM50: =$AC50/$M50 -> 0 | BN50: =$AD50/$M50 -> 29025.803 | BO50: =$AE50/$M50 -> 0 | BP50: =$AF50/$M50 -> 0 | BQ50: =$AG50/$M50 -> 51509.854 | BR50: =$AH50/$M50 -> 0 | BS50: =$AI50/$M50 -> 0 | BT50: =$AJ50/$M50 -> 51509.854 | BU50: =$AK50/$M50 -> 0 | BV50: =$AL50/$M50 -> 0 | BW50: =$AM50/$M50 -> 93297.222 | BX50: =$AN50/$M50 -> 0 | BY50: =$AO50/$M50 -> 0 | BZ50: =$AP50/$M50 -> 93297.222 | CA50: =AQ50/$M50 -> 0 | CB50: =AR50/$M50 -> 0 | CC50: =AS50/$M50 -> 19316.195 | CD50: =AT50/$M50 -> 0 | CE50: =AU50/$M50 -> 0 | CF50: =AV50/$M50 -> 19316.195 | CG50: =AW50/$M50 -> 0 | CH50: =AX50/$M50 -> 0 | ... CL50: =BB50/$M50 -> 25754.927 | CM50: =$BC50/$M50 -> 0 | CN50: =$BD50/$M50 -> 0 | CO50: =$BE50/$M50 -> 218904 | CP50: =$BF50/$M50 -> 0 | CQ50: =$BG50/$M50 -> 0 | CR50: =SUM(CM50:CQ50) -> 218904 | CS50: =K50-CR50 -> 424969.17 | CU50: =D50 -> ARS | CV50: =VLOOKUP(CU50,DF:DG,2,0) -> 0.0006918517 | CW50: =K50*CV50 -> 445.46475 | CX50: =BN50*CV50 -> 20.081551 | CY50: =BT50*CV50 -> 35.63718 | CZ50: =BZ50*CV50 -> 64.547842 | DA50: =CF50*CV50 -> 13.363942 | DB50: =CL50*CV50 -> 17.81859 | DC50: =CS50*CV50 -> 294.01564 | DD50: =VLOOKUP(A50,'Billing Report'!H:I,2,FALSE) -> WLA_ARG CUMBRES BORRASCOSAS Launch-X CPI Q1_2026 | DF50: PEN | DG50: 0.29853821
A51: 40921344 | B51: T3203120 | C51: 320312001 | D51: ARS | F51: 1755000 | J51: =VLOOKUP($B51,'IMS Commission List'!E:CE,79,0)/100 -> 0.08 | K51: =SUM(E51:I51) -> 1755000 | L51: =VLOOKUP($B51,'IMS Commission List'!E:V,18,0) -> ARS | M51: 1 | N51: =VLOOKUP($B51,'IMS Commission List'!E:T,16,0) -> MX | O51: =VLOOKUP($B51,'IMS Commission List'!E:CF,80,0) -> 0.049 | P51: =VLOOKUP($B51,'IMS Commission List'!E:CG,81,0) -> 0.1575 | Q51: =VLOOKUP($B51,'IMS Commission List'!E:CP,90,0) -> 0.03 | R51: =VLOOKUP($B51,'IMS Commission List'!E:CQ,91,0) -> 0.04 | S51: =$E51*$M51 -> 0 | T51: =$F51*$M51 -> 1755000 | U51: =$G51*$M51 -> 0 | V51: =$H51*$M51 -> 0 | W51: =$I51*$M51 -> 0 | X51: =$K51*$M51 -> 1755000 | Y51: =(S51*$O51)*(1-J51) -> 0 | Z51: =(T51*$O51)*(1-J51) -> 79115.4 | AA51: =(U51*$O51)*(1-J51) -> 0 | AB51: =(V51*$O51)*(1-J51) -> 0 | AC51: =(W51*$O51)*(1-J51) -> 0 | AD51: =SUM(Y51:AC51) -> 79115.4 | AE51: =S51*$J51 -> 0 | AF51: =T51*$J51 -> 140400 | AG51: =U51*$J51 -> 0 | AH51: =V51*$J51 -> 0 | AI51: =W51*$J51 -> 0 | AJ51: =SUM(AE51:AI51) -> 140400 | AK51: =($P51*S51)*(1-$J51) -> 0 | AL51: =($P51*T51)*(1-$J51) -> 254299.5 | AM51: =($P51*U51)*(1-$J51) -> 0 | AN51: =($P51*V51)*(1-$J51) -> 0 | AO51: =($P51*W51)*(1-$J51) -> 0 | AP51: =SUM(AK51:AO51) -> 254299.5 | AQ51: =S51*$Q51 -> 0 | AR51: =T51*$Q51 -> 52650 | AS51: =U51*$Q51 -> 0 | AT51: =V51*$Q51 -> 0 | AU51: =W51*$Q51 -> 0 | AV51: =SUM(AQ51:AU51) -> 52650 | AW51: =S51*$R51 -> 0 | AX51: =T51*$R51 -> 70200 | AY51: =U51*$R51 -> 0 | AZ51: =V51*$R51 -> 0 | BA51: =W51*$R51 -> 0 | BB51: =SUM(AW51:BA51) -> 70200 | BC51: =$Y51+$AE51+$AK51+$AQ51+AW51 -> 0 | BD51: =$Z51+$AF51+$AL51+AR51+AX51 -> 596664.9 | BE51: =$AA51+$AG51+$AM51+AS51+AY51 -> 0 | BF51: =$AB51+$AH51+$AN51+AT51+AZ51 -> 0 | BG51: =$AC51+$AI51+$AO51+AU51+BA51 -> 0 | BH51: =SUM(BC51:BG51) -> 596664.9 | BI51: =$Y51/$M51 -> 0 | BJ51: =$Z51/$M51 -> 79115.4 | BK51: =$AA51/$M51 -> 0 | BL51: =$AB51/$M51 -> 0 | BM51: =$AC51/$M51 -> 0 | BN51: =$AD51/$M51 -> 79115.4 | BO51: =$AE51/$M51 -> 0 | BP51: =$AF51/$M51 -> 140400 | BQ51: =$AG51/$M51 -> 0 | BR51: =$AH51/$M51 -> 0 | BS51: =$AI51/$M51 -> 0 | BT51: =$AJ51/$M51 -> 140400 | BU51: =$AK51/$M51 -> 0 | BV51: =$AL51/$M51 -> 254299.5 | BW51: =$AM51/$M51 -> 0 | BX51: =$AN51/$M51 -> 0 | BY51: =$AO51/$M51 -> 0 | BZ51: =$AP51/$M51 -> 254299.5 | CA51: =AQ51/$M51 -> 0 | CB51: =AR51/$M51 -> 52650 | CC51: =AS51/$M51 -> 0 | CD51: =AT51/$M51 -> 0 | CE51: =AU51/$M51 -> 0 | CF51: =AV51/$M51 -> 52650 | CG51: =AW51/$M51 -> 0 | CH51: =AX51/$M51 -> 70200 | ... CL51: =BB51/$M51 -> 70200 | CM51: =$BC51/$M51 -> 0 | CN51: =$BD51/$M51 -> 596664.9 | CO51: =$BE51/$M51 -> 0 | CP51: =$BF51/$M51 -> 0 | CQ51: =$BG51/$M51 -> 0 | CR51: =SUM(CM51:CQ51) -> 596664.9 | CS51: =K51-CR51 -> 1158335.1 | CU51: =D51 -> ARS | CV51: =VLOOKUP(CU51,DF:DG,2,0) -> 0.0006918517 | CW51: =K51*CV51 -> 1214.1997 | CX51: =BN51*CV51 -> 54.736124 | CY51: =BT51*CV51 -> 97.135979 | CZ51: =BZ51*CV51 -> 175.93754 | DA51: =CF51*CV51 -> 36.425992 | DB51: =CL51*CV51 -> 48.567989 | DC51: =CS51*CV51 -> 801.39611 | DD51: =VLOOKUP(A51,'Billing Report'!H:I,2,FALSE) -> Warner Argentina CUMBRES BORRASCOSAS Trend Takeover 2/11 | DF51: PHP | DG51: 0.016970348
A52: 40872593 | B52: T3203120 | C52: 320312002 | D52: ARS | G52: 770437.75 | J52: =VLOOKUP($B52,'IMS Commission List'!E:CE,79,0)/100 -> 0.08 | K52: =SUM(E52:I52) -> 770437.75 | L52: =VLOOKUP($B52,'IMS Commission List'!E:V,18,0) -> ARS | M52: 1 | N52: =VLOOKUP($B52,'IMS Commission List'!E:T,16,0) -> MX | O52: =VLOOKUP($B52,'IMS Commission List'!E:CF,80,0) -> 0.049 | P52: =VLOOKUP($B52,'IMS Commission List'!E:CG,81,0) -> 0.1575 | Q52: =VLOOKUP($B52,'IMS Commission List'!E:CP,90,0) -> 0.03 | R52: =VLOOKUP($B52,'IMS Commission List'!E:CQ,91,0) -> 0.04 | S52: =$E52*$M52 -> 0 | T52: =$F52*$M52 -> 0 | U52: =$G52*$M52 -> 770437.75 | V52: =$H52*$M52 -> 0 | W52: =$I52*$M52 -> 0 | X52: =$K52*$M52 -> 770437.75 | Y52: =(S52*$O52)*(1-J52) -> 0 | Z52: =(T52*$O52)*(1-J52) -> 0 | AA52: =(U52*$O52)*(1-J52) -> 34731.334 | AB52: =(V52*$O52)*(1-J52) -> 0 | AC52: =(W52*$O52)*(1-J52) -> 0 | AD52: =SUM(Y52:AC52) -> 34731.334 | AE52: =S52*$J52 -> 0 | AF52: =T52*$J52 -> 0 | AG52: =U52*$J52 -> 61635.02 | AH52: =V52*$J52 -> 0 | AI52: =W52*$J52 -> 0 | AJ52: =SUM(AE52:AI52) -> 61635.02 | AK52: =($P52*S52)*(1-$J52) -> 0 | AL52: =($P52*T52)*(1-$J52) -> 0 | AM52: =($P52*U52)*(1-$J52) -> 111636.43 | AN52: =($P52*V52)*(1-$J52) -> 0 | AO52: =($P52*W52)*(1-$J52) -> 0 | AP52: =SUM(AK52:AO52) -> 111636.43 | AQ52: =S52*$Q52 -> 0 | AR52: =T52*$Q52 -> 0 | AS52: =U52*$Q52 -> 23113.132 | AT52: =V52*$Q52 -> 0 | AU52: =W52*$Q52 -> 0 | AV52: =SUM(AQ52:AU52) -> 23113.132 | AW52: =S52*$R52 -> 0 | AX52: =T52*$R52 -> 0 | AY52: =U52*$R52 -> 30817.51 | AZ52: =V52*$R52 -> 0 | BA52: =W52*$R52 -> 0 | BB52: =SUM(AW52:BA52) -> 30817.51 | BC52: =$Y52+$AE52+$AK52+$AQ52+AW52 -> 0 | BD52: =$Z52+$AF52+$AL52+AR52+AX52 -> 0 | BE52: =$AA52+$AG52+$AM52+AS52+AY52 -> 261933.43 | BF52: =$AB52+$AH52+$AN52+AT52+AZ52 -> 0 | BG52: =$AC52+$AI52+$AO52+AU52+BA52 -> 0 | BH52: =SUM(BC52:BG52) -> 261933.43 | BI52: =$Y52/$M52 -> 0 | BJ52: =$Z52/$M52 -> 0 | BK52: =$AA52/$M52 -> 34731.334 | BL52: =$AB52/$M52 -> 0 | BM52: =$AC52/$M52 -> 0 | BN52: =$AD52/$M52 -> 34731.334 | BO52: =$AE52/$M52 -> 0 | BP52: =$AF52/$M52 -> 0 | BQ52: =$AG52/$M52 -> 61635.02 | BR52: =$AH52/$M52 -> 0 | BS52: =$AI52/$M52 -> 0 | BT52: =$AJ52/$M52 -> 61635.02 | BU52: =$AK52/$M52 -> 0 | BV52: =$AL52/$M52 -> 0 | BW52: =$AM52/$M52 -> 111636.43 | BX52: =$AN52/$M52 -> 0 | BY52: =$AO52/$M52 -> 0 | BZ52: =$AP52/$M52 -> 111636.43 | CA52: =AQ52/$M52 -> 0 | CB52: =AR52/$M52 -> 0 | CC52: =AS52/$M52 -> 23113.132 | CD52: =AT52/$M52 -> 0 | CE52: =AU52/$M52 -> 0 | CF52: =AV52/$M52 -> 23113.132 | CG52: =AW52/$M52 -> 0 | CH52: =AX52/$M52 -> 0 | ... CL52: =BB52/$M52 -> 30817.51 | CM52: =$BC52/$M52 -> 0 | CN52: =$BD52/$M52 -> 0 | CO52: =$BE52/$M52 -> 261933.43 | CP52: =$BF52/$M52 -> 0 | CQ52: =$BG52/$M52 -> 0 | CR52: =SUM(CM52:CQ52) -> 261933.43 | CS52: =K52-CR52 -> 508504.32 | CU52: =D52 -> ARS | CV52: =VLOOKUP(CU52,DF:DG,2,0) -> 0.0006918517 | CW52: =K52*CV52 -> 533.02867 | CX52: =BN52*CV52 -> 24.028932 | CY52: =BT52*CV52 -> 42.642293 | CZ52: =BZ52*CV52 -> 77.235854 | DA52: =CF52*CV52 -> 15.99086 | DB52: =CL52*CV52 -> 21.321147 | DC52: =CS52*CV52 -> 351.80958 | DD52: =VLOOKUP(A52,'Billing Report'!H:I,2,FALSE) -> WLA_ARG CUMBRES BORRASCOSAS Prelaunch-X CPI Q1_2026 | DF52: PKR | DG52: 0.0035726437
A53: 40872434 | B53: T3203120 | C53: 320312002 | D53: ARS | G53: 1285324.1 | J53: =VLOOKUP($B53,'IMS Commission List'!E:CE,79,0)/100 -> 0.08 | K53: =SUM(E53:I53) -> 1285324.1 | L53: =VLOOKUP($B53,'IMS Commission List'!E:V,18,0) -> ARS | M53: 1 | N53: =VLOOKUP($B53,'IMS Commission List'!E:T,16,0) -> MX | O53: =VLOOKUP($B53,'IMS Commission List'!E:CF,80,0) -> 0.049 | P53: =VLOOKUP($B53,'IMS Commission List'!E:CG,81,0) -> 0.1575 | Q53: =VLOOKUP($B53,'IMS Commission List'!E:CP,90,0) -> 0.03 | R53: =VLOOKUP($B53,'IMS Commission List'!E:CQ,91,0) -> 0.04 | S53: =$E53*$M53 -> 0 | T53: =$F53*$M53 -> 0 | U53: =$G53*$M53 -> 1285324.1 | V53: =$H53*$M53 -> 0 | W53: =$I53*$M53 -> 0 | X53: =$K53*$M53 -> 1285324.1 | Y53: =(S53*$O53)*(1-J53) -> 0 | Z53: =(T53*$O53)*(1-J53) -> 0 | AA53: =(U53*$O53)*(1-J53) -> 57942.412 | AB53: =(V53*$O53)*(1-J53) -> 0 | AC53: =(W53*$O53)*(1-J53) -> 0 | AD53: =SUM(Y53:AC53) -> 57942.412 | AE53: =S53*$J53 -> 0 | AF53: =T53*$J53 -> 0 | AG53: =U53*$J53 -> 102825.93 | AH53: =V53*$J53 -> 0 | AI53: =W53*$J53 -> 0 | AJ53: =SUM(AE53:AI53) -> 102825.93 | AK53: =($P53*S53)*(1-$J53) -> 0 | AL53: =($P53*T53)*(1-$J53) -> 0 | AM53: =($P53*U53)*(1-$J53) -> 186243.47 | AN53: =($P53*V53)*(1-$J53) -> 0 | AO53: =($P53*W53)*(1-$J53) -> 0 | AP53: =SUM(AK53:AO53) -> 186243.47 | AQ53: =S53*$Q53 -> 0 | AR53: =T53*$Q53 -> 0 | AS53: =U53*$Q53 -> 38559.724 | AT53: =V53*$Q53 -> 0 | AU53: =W53*$Q53 -> 0 | AV53: =SUM(AQ53:AU53) -> 38559.724 | AW53: =S53*$R53 -> 0 | AX53: =T53*$R53 -> 0 | AY53: =U53*$R53 -> 51412.965 | AZ53: =V53*$R53 -> 0 | BA53: =W53*$R53 -> 0 | BB53: =SUM(AW53:BA53) -> 51412.965 | BC53: =$Y53+$AE53+$AK53+$AQ53+AW53 -> 0 | BD53: =$Z53+$AF53+$AL53+AR53+AX53 -> 0 | BE53: =$AA53+$AG53+$AM53+AS53+AY53 -> 436984.5 | BF53: =$AB53+$AH53+$AN53+AT53+AZ53 -> 0 | BG53: =$AC53+$AI53+$AO53+AU53+BA53 -> 0 | BH53: =SUM(BC53:BG53) -> 436984.5 | BI53: =$Y53/$M53 -> 0 | BJ53: =$Z53/$M53 -> 0 | BK53: =$AA53/$M53 -> 57942.412 | BL53: =$AB53/$M53 -> 0 | BM53: =$AC53/$M53 -> 0 | BN53: =$AD53/$M53 -> 57942.412 | BO53: =$AE53/$M53 -> 0 | BP53: =$AF53/$M53 -> 0 | BQ53: =$AG53/$M53 -> 102825.93 | BR53: =$AH53/$M53 -> 0 | BS53: =$AI53/$M53 -> 0 | BT53: =$AJ53/$M53 -> 102825.93 | BU53: =$AK53/$M53 -> 0 | BV53: =$AL53/$M53 -> 0 | BW53: =$AM53/$M53 -> 186243.47 | BX53: =$AN53/$M53 -> 0 | BY53: =$AO53/$M53 -> 0 | BZ53: =$AP53/$M53 -> 186243.47 | CA53: =AQ53/$M53 -> 0 | CB53: =AR53/$M53 -> 0 | CC53: =AS53/$M53 -> 38559.724 | CD53: =AT53/$M53 -> 0 | CE53: =AU53/$M53 -> 0 | CF53: =AV53/$M53 -> 38559.724 | CG53: =AW53/$M53 -> 0 | CH53: =AX53/$M53 -> 0 | ... CL53: =BB53/$M53 -> 51412.965 | CM53: =$BC53/$M53 -> 0 | CN53: =$BD53/$M53 -> 0 | CO53: =$BE53/$M53 -> 436984.5 | CP53: =$BF53/$M53 -> 0 | CQ53: =$BG53/$M53 -> 0 | CR53: =SUM(CM53:CQ53) -> 436984.5 | CS53: =K53-CR53 -> 848339.63 | CU53: =D53 -> ARS | CV53: =VLOOKUP(CU53,DF:DG,2,0) -> 0.0006918517 | CW53: =K53*CV53 -> 889.25368 | CX53: =BN53*CV53 -> 40.087556 | CY53: =BT53*CV53 -> 71.140295 | CZ53: =BZ53*CV53 -> 128.85286 | DA53: =CF53*CV53 -> 26.677611 | DB53: =CL53*CV53 -> 35.570147 | DC53: =CS53*CV53 -> 586.92522 | DD53: =VLOOKUP(A53,'Billing Report'!H:I,2,FALSE) -> WLA_ARG CUMBRES BORRASCOSAS PreLaunch-X CPM Q1_2026 | DF53: PLN | DG53: 0.28275625
A54: 40790186 | B54: T3203811 | C54: 320381103 | D54: ARS | F54: 594000 | J54: =VLOOKUP($B54,'IMS Commission List'!E:CE,79,0)/100 -> 0.08 | K54: =SUM(E54:I54) -> 594000 | L54: =VLOOKUP($B54,'IMS Commission List'!E:V,18,0) -> ARS | M54: 1 | N54: =VLOOKUP($B54,'IMS Commission List'!E:T,16,0) -> MX | O54: =VLOOKUP($B54,'IMS Commission List'!E:CF,80,0) -> 0.049 | P54: =VLOOKUP($B54,'IMS Commission List'!E:CG,81,0) -> 0.1575 | Q54: =VLOOKUP($B54,'IMS Commission List'!E:CP,90,0) -> 0.03 | R54: =VLOOKUP($B54,'IMS Commission List'!E:CQ,91,0) -> 0.04 | S54: =$E54*$M54 -> 0 | T54: =$F54*$M54 -> 594000 | U54: =$G54*$M54 -> 0 | V54: =$H54*$M54 -> 0 | W54: =$I54*$M54 -> 0 | X54: =$K54*$M54 -> 594000 | Y54: =(S54*$O54)*(1-J54) -> 0 | Z54: =(T54*$O54)*(1-J54) -> 26777.52 | AA54: =(U54*$O54)*(1-J54) -> 0 | AB54: =(V54*$O54)*(1-J54) -> 0 | AC54: =(W54*$O54)*(1-J54) -> 0 | AD54: =SUM(Y54:AC54) -> 26777.52 | AE54: =S54*$J54 -> 0 | AF54: =T54*$J54 -> 47520 | AG54: =U54*$J54 -> 0 | AH54: =V54*$J54 -> 0 | AI54: =W54*$J54 -> 0 | AJ54: =SUM(AE54:AI54) -> 47520 | AK54: =($P54*S54)*(1-$J54) -> 0 | AL54: =($P54*T54)*(1-$J54) -> 86070.6 | AM54: =($P54*U54)*(1-$J54) -> 0 | AN54: =($P54*V54)*(1-$J54) -> 0 | AO54: =($P54*W54)*(1-$J54) -> 0 | AP54: =SUM(AK54:AO54) -> 86070.6 | AQ54: =S54*$Q54 -> 0 | AR54: =T54*$Q54 -> 17820 | AS54: =U54*$Q54 -> 0 | AT54: =V54*$Q54 -> 0 | AU54: =W54*$Q54 -> 0 | AV54: =SUM(AQ54:AU54) -> 17820 | AW54: =S54*$R54 -> 0 | AX54: =T54*$R54 -> 23760 | AY54: =U54*$R54 -> 0 | AZ54: =V54*$R54 -> 0 | BA54: =W54*$R54 -> 0 | BB54: =SUM(AW54:BA54) -> 23760 | BC54: =$Y54+$AE54+$AK54+$AQ54+AW54 -> 0 | BD54: =$Z54+$AF54+$AL54+AR54+AX54 -> 201948.12 | BE54: =$AA54+$AG54+$AM54+AS54+AY54 -> 0 | BF54: =$AB54+$AH54+$AN54+AT54+AZ54 -> 0 | BG54: =$AC54+$AI54+$AO54+AU54+BA54 -> 0 | BH54: =SUM(BC54:BG54) -> 201948.12 | BI54: =$Y54/$M54 -> 0 | BJ54: =$Z54/$M54 -> 26777.52 | BK54: =$AA54/$M54 -> 0 | BL54: =$AB54/$M54 -> 0 | BM54: =$AC54/$M54 -> 0 | BN54: =$AD54/$M54 -> 26777.52 | BO54: =$AE54/$M54 -> 0 | BP54: =$AF54/$M54 -> 47520 | BQ54: =$AG54/$M54 -> 0 | BR54: =$AH54/$M54 -> 0 | BS54: =$AI54/$M54 -> 0 | BT54: =$AJ54/$M54 -> 47520 | BU54: =$AK54/$M54 -> 0 | BV54: =$AL54/$M54 -> 86070.6 | BW54: =$AM54/$M54 -> 0 | BX54: =$AN54/$M54 -> 0 | BY54: =$AO54/$M54 -> 0 | BZ54: =$AP54/$M54 -> 86070.6 | CA54: =AQ54/$M54 -> 0 | CB54: =AR54/$M54 -> 17820 | CC54: =AS54/$M54 -> 0 | CD54: =AT54/$M54 -> 0 | CE54: =AU54/$M54 -> 0 | CF54: =AV54/$M54 -> 17820 | CG54: =AW54/$M54 -> 0 | CH54: =AX54/$M54 -> 23760 | ... CL54: =BB54/$M54 -> 23760 | CM54: =$BC54/$M54 -> 0 | CN54: =$BD54/$M54 -> 201948.12 | CO54: =$BE54/$M54 -> 0 | CP54: =$BF54/$M54 -> 0 | CQ54: =$BG54/$M54 -> 0 | CR54: =SUM(CM54:CQ54) -> 201948.12 | CS54: =K54-CR54 -> 392051.88 | CU54: =D54 -> ARS | CV54: =VLOOKUP(CU54,DF:DG,2,0) -> 0.0006918517 | CW54: =K54*CV54 -> 410.95991 | CX54: =BN54*CV54 -> 18.526073 | CY54: =BT54*CV54 -> 32.876793 | CZ54: =BZ54*CV54 -> 59.548091 | DA54: =CF54*CV54 -> 12.328797 | DB54: =CL54*CV54 -> 16.438396 | DC54: =CS54*CV54 -> 271.24176 | DD54: =VLOOKUP(A54,'Billing Report'!H:I,2,FALSE) -> MLA Campaña Verano Spotlight- 4/Feb | DF54: QAR | DG54: 0.27436573
A55: 40790180 | B55: T3203811 | C55: 320381104 | D55: ARS | F55: 1710000 | J55: =VLOOKUP($B55,'IMS Commission List'!E:CE,79,0)/100 -> 0.08 | K55: =SUM(E55:I55) -> 1710000 | L55: =VLOOKUP($B55,'IMS Commission List'!E:V,18,0) -> ARS | M55: 1 | N55: =VLOOKUP($B55,'IMS Commission List'!E:T,16,0) -> MX | O55: =VLOOKUP($B55,'IMS Commission List'!E:CF,80,0) -> 0.049 | P55: =VLOOKUP($B55,'IMS Commission List'!E:CG,81,0) -> 0.1575 | Q55: =VLOOKUP($B55,'IMS Commission List'!E:CP,90,0) -> 0.03 | R55: =VLOOKUP($B55,'IMS Commission List'!E:CQ,91,0) -> 0.04 | S55: =$E55*$M55 -> 0 | T55: =$F55*$M55 -> 1710000 | U55: =$G55*$M55 -> 0 | V55: =$H55*$M55 -> 0 | W55: =$I55*$M55 -> 0 | X55: =$K55*$M55 -> 1710000 | Y55: =(S55*$O55)*(1-J55) -> 0 | Z55: =(T55*$O55)*(1-J55) -> 77086.8 | AA55: =(U55*$O55)*(1-J55) -> 0 | AB55: =(V55*$O55)*(1-J55) -> 0 | AC55: =(W55*$O55)*(1-J55) -> 0 | AD55: =SUM(Y55:AC55) -> 77086.8 | AE55: =S55*$J55 -> 0 | AF55: =T55*$J55 -> 136800 | AG55: =U55*$J55 -> 0 | AH55: =V55*$J55 -> 0 | AI55: =W55*$J55 -> 0 | AJ55: =SUM(AE55:AI55) -> 136800 | AK55: =($P55*S55)*(1-$J55) -> 0 | AL55: =($P55*T55)*(1-$J55) -> 247779 | AM55: =($P55*U55)*(1-$J55) -> 0 | AN55: =($P55*V55)*(1-$J55) -> 0 | AO55: =($P55*W55)*(1-$J55) -> 0 | AP55: =SUM(AK55:AO55) -> 247779 | AQ55: =S55*$Q55 -> 0 | AR55: =T55*$Q55 -> 51300 | AS55: =U55*$Q55 -> 0 | AT55: =V55*$Q55 -> 0 | AU55: =W55*$Q55 -> 0 | AV55: =SUM(AQ55:AU55) -> 51300 | AW55: =S55*$R55 -> 0 | AX55: =T55*$R55 -> 68400 | AY55: =U55*$R55 -> 0 | AZ55: =V55*$R55 -> 0 | BA55: =W55*$R55 -> 0 | BB55: =SUM(AW55:BA55) -> 68400 | BC55: =$Y55+$AE55+$AK55+$AQ55+AW55 -> 0 | BD55: =$Z55+$AF55+$AL55+AR55+AX55 -> 581365.8 | BE55: =$AA55+$AG55+$AM55+AS55+AY55 -> 0 | BF55: =$AB55+$AH55+$AN55+AT55+AZ55 -> 0 | BG55: =$AC55+$AI55+$AO55+AU55+BA55 -> 0 | BH55: =SUM(BC55:BG55) -> 581365.8 | BI55: =$Y55/$M55 -> 0 | BJ55: =$Z55/$M55 -> 77086.8 | BK55: =$AA55/$M55 -> 0 | BL55: =$AB55/$M55 -> 0 | BM55: =$AC55/$M55 -> 0 | BN55: =$AD55/$M55 -> 77086.8 | BO55: =$AE55/$M55 -> 0 | BP55: =$AF55/$M55 -> 136800 | BQ55: =$AG55/$M55 -> 0 | BR55: =$AH55/$M55 -> 0 | BS55: =$AI55/$M55 -> 0 | BT55: =$AJ55/$M55 -> 136800 | BU55: =$AK55/$M55 -> 0 | BV55: =$AL55/$M55 -> 247779 | BW55: =$AM55/$M55 -> 0 | BX55: =$AN55/$M55 -> 0 | BY55: =$AO55/$M55 -> 0 | BZ55: =$AP55/$M55 -> 247779 | CA55: =AQ55/$M55 -> 0 | CB55: =AR55/$M55 -> 51300 | CC55: =AS55/$M55 -> 0 | CD55: =AT55/$M55 -> 0 | CE55: =AU55/$M55 -> 0 | CF55: =AV55/$M55 -> 51300 | CG55: =AW55/$M55 -> 0 | CH55: =AX55/$M55 -> 68400 | ... CL55: =BB55/$M55 -> 68400 | CM55: =$BC55/$M55 -> 0 | CN55: =$BD55/$M55 -> 581365.8 | CO55: =$BE55/$M55 -> 0 | CP55: =$BF55/$M55 -> 0 | CQ55: =$BG55/$M55 -> 0 | CR55: =SUM(CM55:CQ55) -> 581365.8 | CS55: =K55-CR55 -> 1128634.2 | CU55: =D55 -> ARS | CV55: =VLOOKUP(CU55,DF:DG,2,0) -> 0.0006918517 | CW55: =K55*CV55 -> 1183.0664 | CX55: =BN55*CV55 -> 53.332634 | CY55: =BT55*CV55 -> 94.645313 | CZ55: =BZ55*CV55 -> 171.42632 | DA55: =CF55*CV55 -> 35.491992 | DB55: =CL55*CV55 -> 47.322656 | DC55: =CS55*CV55 -> 780.84749 | DD55: =VLOOKUP(A55,'Billing Report'!H:I,2,FALSE) -> MLA Campaña Verano Timeline- 4/Feb | DF55: RON | DG55: 0.23360638
A56: 40980211 | B56: T3207502 | C56: 320750202 | D56: ARS | G56: 534603.53 | J56: =VLOOKUP($B56,'IMS Commission List'!E:CE,79,0)/100 -> 0.15 | K56: =SUM(E56:I56) -> 534603.53 | L56: =VLOOKUP($B56,'IMS Commission List'!E:V,18,0) -> ARS | M56: 1 | N56: =VLOOKUP($B56,'IMS Commission List'!E:T,16,0) -> MX | O56: =VLOOKUP($B56,'IMS Commission List'!E:CF,80,0) -> 0 | P56: =VLOOKUP($B56,'IMS Commission List'!E:CG,81,0) -> 0 | Q56: =VLOOKUP($B56,'IMS Commission List'!E:CP,90,0) -> 0.03 | R56: =VLOOKUP($B56,'IMS Commission List'!E:CQ,91,0) -> 0.04 | S56: =$E56*$M56 -> 0 | T56: =$F56*$M56 -> 0 | U56: =$G56*$M56 -> 534603.53 | V56: =$H56*$M56 -> 0 | W56: =$I56*$M56 -> 0 | X56: =$K56*$M56 -> 534603.53 | Y56: =(S56*$O56)*(1-J56) -> 0 | Z56: =(T56*$O56)*(1-J56) -> 0 | AA56: =(U56*$O56)*(1-J56) -> 0 | AB56: =(V56*$O56)*(1-J56) -> 0 | AC56: =(W56*$O56)*(1-J56) -> 0 | AD56: =SUM(Y56:AC56) -> 0 | AE56: =S56*$J56 -> 0 | AF56: =T56*$J56 -> 0 | AG56: =U56*$J56 -> 80190.53 | AH56: =V56*$J56 -> 0 | AI56: =W56*$J56 -> 0 | AJ56: =SUM(AE56:AI56) -> 80190.53 | AK56: =($P56*S56)*(1-$J56) -> 0 | AL56: =($P56*T56)*(1-$J56) -> 0 | AM56: =($P56*U56)*(1-$J56) -> 0 | AN56: =($P56*V56)*(1-$J56) -> 0 | AO56: =($P56*W56)*(1-$J56) -> 0 | AP56: =SUM(AK56:AO56) -> 0 | AQ56: =S56*$Q56 -> 0 | AR56: =T56*$Q56 -> 0 | AS56: =U56*$Q56 -> 16038.106 | AT56: =V56*$Q56 -> 0 | AU56: =W56*$Q56 -> 0 | AV56: =SUM(AQ56:AU56) -> 16038.106 | AW56: =S56*$R56 -> 0 | AX56: =T56*$R56 -> 0 | AY56: =U56*$R56 -> 21384.141 | AZ56: =V56*$R56 -> 0 | BA56: =W56*$R56 -> 0 | BB56: =SUM(AW56:BA56) -> 21384.141 | BC56: =$Y56+$AE56+$AK56+$AQ56+AW56 -> 0 | BD56: =$Z56+$AF56+$AL56+AR56+AX56 -> 0 | BE56: =$AA56+$AG56+$AM56+AS56+AY56 -> 117612.78 | BF56: =$AB56+$AH56+$AN56+AT56+AZ56 -> 0 | BG56: =$AC56+$AI56+$AO56+AU56+BA56 -> 0 | BH56: =SUM(BC56:BG56) -> 117612.78 | BI56: =$Y56/$M56 -> 0 | BJ56: =$Z56/$M56 -> 0 | BK56: =$AA56/$M56 -> 0 | BL56: =$AB56/$M56 -> 0 | BM56: =$AC56/$M56 -> 0 | BN56: =$AD56/$M56 -> 0 | BO56: =$AE56/$M56 -> 0 | BP56: =$AF56/$M56 -> 0 | BQ56: =$AG56/$M56 -> 80190.53 | BR56: =$AH56/$M56 -> 0 | BS56: =$AI56/$M56 -> 0 | BT56: =$AJ56/$M56 -> 80190.53 | BU56: =$AK56/$M56 -> 0 | BV56: =$AL56/$M56 -> 0 | BW56: =$AM56/$M56 -> 0 | BX56: =$AN56/$M56 -> 0 | BY56: =$AO56/$M56 -> 0 | BZ56: =$AP56/$M56 -> 0 | CA56: =AQ56/$M56 -> 0 | CB56: =AR56/$M56 -> 0 | CC56: =AS56/$M56 -> 16038.106 | CD56: =AT56/$M56 -> 0 | CE56: =AU56/$M56 -> 0 | CF56: =AV56/$M56 -> 16038.106 | CG56: =AW56/$M56 -> 0 | CH56: =AX56/$M56 -> 0 | ... CL56: =BB56/$M56 -> 21384.141 | CM56: =$BC56/$M56 -> 0 | CN56: =$BD56/$M56 -> 0 | CO56: =$BE56/$M56 -> 117612.78 | CP56: =$BF56/$M56 -> 0 | CQ56: =$BG56/$M56 -> 0 | CR56: =SUM(CM56:CQ56) -> 117612.78 | CS56: =K56-CR56 -> 416990.75 | CU56: =D56 -> ARS | CV56: =VLOOKUP(CU56,DF:DG,2,0) -> 0.0006918517 | CW56: =K56*CV56 -> 369.86636 | CX56: =BN56*CV56 -> 0 | CY56: =BT56*CV56 -> 55.479954 | CZ56: =BZ56*CV56 -> 0 | DA56: =CF56*CV56 -> 11.095991 | DB56: =CL56*CV56 -> 14.794654 | DC56: =CS56*CV56 -> 288.49576 | DD56: =VLOOKUP(A56,'Billing Report'!H:I,2,FALSE) -> WLA_ARG LA NOVIA Prelaunch-X CPI Q1_2026 | DF56: RSD | DG56: 0.010139098
A57: 40980003 | B57: T3207502 | C57: 320750202 | D57: ARS | G57: 658331.65 | J57: =VLOOKUP($B57,'IMS Commission List'!E:CE,79,0)/100 -> 0.15 | K57: =SUM(E57:I57) -> 658331.65 | L57: =VLOOKUP($B57,'IMS Commission List'!E:V,18,0) -> ARS | M57: 1 | N57: =VLOOKUP($B57,'IMS Commission List'!E:T,16,0) -> MX | O57: =VLOOKUP($B57,'IMS Commission List'!E:CF,80,0) -> 0 | P57: =VLOOKUP($B57,'IMS Commission List'!E:CG,81,0) -> 0 | Q57: =VLOOKUP($B57,'IMS Commission List'!E:CP,90,0) -> 0.03 | R57: =VLOOKUP($B57,'IMS Commission List'!E:CQ,91,0) -> 0.04 | S57: =$E57*$M57 -> 0 | T57: =$F57*$M57 -> 0 | U57: =$G57*$M57 -> 658331.65 | V57: =$H57*$M57 -> 0 | W57: =$I57*$M57 -> 0 | X57: =$K57*$M57 -> 658331.65 | Y57: =(S57*$O57)*(1-J57) -> 0 | Z57: =(T57*$O57)*(1-J57) -> 0 | AA57: =(U57*$O57)*(1-J57) -> 0 | AB57: =(V57*$O57)*(1-J57) -> 0 | AC57: =(W57*$O57)*(1-J57) -> 0 | AD57: =SUM(Y57:AC57) -> 0 | AE57: =S57*$J57 -> 0 | AF57: =T57*$J57 -> 0 | AG57: =U57*$J57 -> 98749.747 | AH57: =V57*$J57 -> 0 | AI57: =W57*$J57 -> 0 | AJ57: =SUM(AE57:AI57) -> 98749.747 | AK57: =($P57*S57)*(1-$J57) -> 0 | AL57: =($P57*T57)*(1-$J57) -> 0 | AM57: =($P57*U57)*(1-$J57) -> 0 | AN57: =($P57*V57)*(1-$J57) -> 0 | AO57: =($P57*W57)*(1-$J57) -> 0 | AP57: =SUM(AK57:AO57) -> 0 | AQ57: =S57*$Q57 -> 0 | AR57: =T57*$Q57 -> 0 | AS57: =U57*$Q57 -> 19749.949 | AT57: =V57*$Q57 -> 0 | AU57: =W57*$Q57 -> 0 | AV57: =SUM(AQ57:AU57) -> 19749.949 | AW57: =S57*$R57 -> 0 | AX57: =T57*$R57 -> 0 | AY57: =U57*$R57 -> 26333.266 | AZ57: =V57*$R57 -> 0 | BA57: =W57*$R57 -> 0 | BB57: =SUM(AW57:BA57) -> 26333.266 | BC57: =$Y57+$AE57+$AK57+$AQ57+AW57 -> 0 | BD57: =$Z57+$AF57+$AL57+AR57+AX57 -> 0 | BE57: =$AA57+$AG57+$AM57+AS57+AY57 -> 144832.96 | BF57: =$AB57+$AH57+$AN57+AT57+AZ57 -> 0 | BG57: =$AC57+$AI57+$AO57+AU57+BA57 -> 0 | BH57: =SUM(BC57:BG57) -> 144832.96 | BI57: =$Y57/$M57 -> 0 | BJ57: =$Z57/$M57 -> 0 | BK57: =$AA57/$M57 -> 0 | BL57: =$AB57/$M57 -> 0 | BM57: =$AC57/$M57 -> 0 | BN57: =$AD57/$M57 -> 0 | BO57: =$AE57/$M57 -> 0 | BP57: =$AF57/$M57 -> 0 | BQ57: =$AG57/$M57 -> 98749.747 | BR57: =$AH57/$M57 -> 0 | BS57: =$AI57/$M57 -> 0 | BT57: =$AJ57/$M57 -> 98749.747 | BU57: =$AK57/$M57 -> 0 | BV57: =$AL57/$M57 -> 0 | BW57: =$AM57/$M57 -> 0 | BX57: =$AN57/$M57 -> 0 | BY57: =$AO57/$M57 -> 0 | BZ57: =$AP57/$M57 -> 0 | CA57: =AQ57/$M57 -> 0 | CB57: =AR57/$M57 -> 0 | CC57: =AS57/$M57 -> 19749.949 | CD57: =AT57/$M57 -> 0 | CE57: =AU57/$M57 -> 0 | CF57: =AV57/$M57 -> 19749.949 | CG57: =AW57/$M57 -> 0 | CH57: =AX57/$M57 -> 0 | ... CL57: =BB57/$M57 -> 26333.266 | CM57: =$BC57/$M57 -> 0 | CN57: =$BD57/$M57 -> 0 | CO57: =$BE57/$M57 -> 144832.96 | CP57: =$BF57/$M57 -> 0 | CQ57: =$BG57/$M57 -> 0 | CR57: =SUM(CM57:CQ57) -> 144832.96 | CS57: =K57-CR57 -> 513498.69 | CU57: =D57 -> ARS | CV57: =VLOOKUP(CU57,DF:DG,2,0) -> 0.0006918517 | CW57: =K57*CV57 -> 455.46787 | CX57: =BN57*CV57 -> 0 | CY57: =BT57*CV57 -> 68.320181 | CZ57: =BZ57*CV57 -> 0 | DA57: =CF57*CV57 -> 13.664036 | DB57: =CL57*CV57 -> 18.218715 | DC57: =CS57*CV57 -> 355.26494 | DD57: =VLOOKUP(A57,'Billing Report'!H:I,2,FALSE) -> WLA_ARG LA NOVIA PreLaunch-X CPM Q1_2026 | DF57: RUB | DG57: 0.013218644
A58: 40636269 | B58: T3209384 | C58: 320938401 | D58: ARS | G58: 1642612 | J58: =VLOOKUP($B58,'IMS Commission List'!E:CE,79,0)/100 -> 0.15 | K58: =SUM(E58:I58) -> 1642612 | L58: =VLOOKUP($B58,'IMS Commission List'!E:V,18,0) -> ARS | M58: 1 | N58: =VLOOKUP($B58,'IMS Commission List'!E:T,16,0) -> MX | O58: =VLOOKUP($B58,'IMS Commission List'!E:CF,80,0) -> 0.049 | P58: =VLOOKUP($B58,'IMS Commission List'!E:CG,81,0) -> 0.1575 | Q58: =VLOOKUP($B58,'IMS Commission List'!E:CP,90,0) -> 0.03 | R58: =VLOOKUP($B58,'IMS Commission List'!E:CQ,91,0) -> 0.04 | S58: =$E58*$M58 -> 0 | T58: =$F58*$M58 -> 0 | U58: =$G58*$M58 -> 1642612 | V58: =$H58*$M58 -> 0 | W58: =$I58*$M58 -> 0 | X58: =$K58*$M58 -> 1642612 | Y58: =(S58*$O58)*(1-J58) -> 0 | Z58: =(T58*$O58)*(1-J58) -> 0 | AA58: =(U58*$O58)*(1-J58) -> 68414.789 | AB58: =(V58*$O58)*(1-J58) -> 0 | AC58: =(W58*$O58)*(1-J58) -> 0 | AD58: =SUM(Y58:AC58) -> 68414.789 | AE58: =S58*$J58 -> 0 | AF58: =T58*$J58 -> 0 | AG58: =U58*$J58 -> 246391.8 | AH58: =V58*$J58 -> 0 | AI58: =W58*$J58 -> 0 | AJ58: =SUM(AE58:AI58) -> 246391.8 | AK58: =($P58*S58)*(1-$J58) -> 0 | AL58: =($P58*T58)*(1-$J58) -> 0 | AM58: =($P58*U58)*(1-$J58) -> 219904.68 | AN58: =($P58*V58)*(1-$J58) -> 0 | AO58: =($P58*W58)*(1-$J58) -> 0 | AP58: =SUM(AK58:AO58) -> 219904.68 | AQ58: =S58*$Q58 -> 0 | AR58: =T58*$Q58 -> 0 | AS58: =U58*$Q58 -> 49278.359 | AT58: =V58*$Q58 -> 0 | AU58: =W58*$Q58 -> 0 | AV58: =SUM(AQ58:AU58) -> 49278.359 | AW58: =S58*$R58 -> 0 | AX58: =T58*$R58 -> 0 | AY58: =U58*$R58 -> 65704.479 | AZ58: =V58*$R58 -> 0 | BA58: =W58*$R58 -> 0 | BB58: =SUM(AW58:BA58) -> 65704.479 | BC58: =$Y58+$AE58+$AK58+$AQ58+AW58 -> 0 | BD58: =$Z58+$AF58+$AL58+AR58+AX58 -> 0 | BE58: =$AA58+$AG58+$AM58+AS58+AY58 -> 649694.1 | BF58: =$AB58+$AH58+$AN58+AT58+AZ58 -> 0 | BG58: =$AC58+$AI58+$AO58+AU58+BA58 -> 0 | BH58: =SUM(BC58:BG58) -> 649694.1 | BI58: =$Y58/$M58 -> 0 | BJ58: =$Z58/$M58 -> 0 | BK58: =$AA58/$M58 -> 68414.789 | BL58: =$AB58/$M58 -> 0 | BM58: =$AC58/$M58 -> 0 | BN58: =$AD58/$M58 -> 68414.789 | BO58: =$AE58/$M58 -> 0 | BP58: =$AF58/$M58 -> 0 | BQ58: =$AG58/$M58 -> 246391.8 | BR58: =$AH58/$M58 -> 0 | BS58: =$AI58/$M58 -> 0 | BT58: =$AJ58/$M58 -> 246391.8 | BU58: =$AK58/$M58 -> 0 | BV58: =$AL58/$M58 -> 0 | BW58: =$AM58/$M58 -> 219904.68 | BX58: =$AN58/$M58 -> 0 | BY58: =$AO58/$M58 -> 0 | BZ58: =$AP58/$M58 -> 219904.68 | CA58: =AQ58/$M58 -> 0 | CB58: =AR58/$M58 -> 0 | CC58: =AS58/$M58 -> 49278.359 | CD58: =AT58/$M58 -> 0 | CE58: =AU58/$M58 -> 0 | CF58: =AV58/$M58 -> 49278.359 | CG58: =AW58/$M58 -> 0 | CH58: =AX58/$M58 -> 0 | ... CL58: =BB58/$M58 -> 65704.479 | CM58: =$BC58/$M58 -> 0 | CN58: =$BD58/$M58 -> 0 | CO58: =$BE58/$M58 -> 649694.1 | CP58: =$BF58/$M58 -> 0 | CQ58: =$BG58/$M58 -> 0 | CR58: =SUM(CM58:CQ58) -> 649694.1 | CS58: =K58-CR58 -> 992917.88 | CU58: =D58 -> ARS | CV58: =VLOOKUP(CU58,DF:DG,2,0) -> 0.0006918517 | CW58: =K58*CV58 -> 1136.4439 | CX58: =BN58*CV58 -> 47.332888 | CY58: =BT58*CV58 -> 170.46658 | CZ58: =BZ58*CV58 -> 152.14143 | DA58: =CF58*CV58 -> 34.093317 | DB58: =CL58*CV58 -> 45.457756 | DC58: =CS58*CV58 -> 686.95192 | DD58: =VLOOKUP(A58,'Billing Report'!H:I,2,FALSE) -> 2025_MODO_BRANDING_PROMO_MAKRO_GEO_TWITTER_NU_AW_DIC | DF58: SAR | DG58: 0.26661477
A59: 40617267 | B59: T3209384 | C59: 320938401 | D59: ARS | G59: 2515517.3 | J59: =VLOOKUP($B59,'IMS Commission List'!E:CE,79,0)/100 -> 0.15 | K59: =SUM(E59:I59) -> 2515517.3 | L59: =VLOOKUP($B59,'IMS Commission List'!E:V,18,0) -> ARS | M59: 1 | N59: =VLOOKUP($B59,'IMS Commission List'!E:T,16,0) -> MX | O59: =VLOOKUP($B59,'IMS Commission List'!E:CF,80,0) -> 0.049 | P59: =VLOOKUP($B59,'IMS Commission List'!E:CG,81,0) -> 0.1575 | Q59: =VLOOKUP($B59,'IMS Commission List'!E:CP,90,0) -> 0.03 | R59: =VLOOKUP($B59,'IMS Commission List'!E:CQ,91,0) -> 0.04 | S59: =$E59*$M59 -> 0 | T59: =$F59*$M59 -> 0 | U59: =$G59*$M59 -> 2515517.3 | V59: =$H59*$M59 -> 0 | W59: =$I59*$M59 -> 0 | X59: =$K59*$M59 -> 2515517.3 | Y59: =(S59*$O59)*(1-J59) -> 0 | Z59: =(T59*$O59)*(1-J59) -> 0 | AA59: =(U59*$O59)*(1-J59) -> 104771.3 | AB59: =(V59*$O59)*(1-J59) -> 0 | AC59: =(W59*$O59)*(1-J59) -> 0 | AD59: =SUM(Y59:AC59) -> 104771.3 | AE59: =S59*$J59 -> 0 | AF59: =T59*$J59 -> 0 | AG59: =U59*$J59 -> 377327.6 | AH59: =V59*$J59 -> 0 | AI59: =W59*$J59 -> 0 | AJ59: =SUM(AE59:AI59) -> 377327.6 | AK59: =($P59*S59)*(1-$J59) -> 0 | AL59: =($P59*T59)*(1-$J59) -> 0 | AM59: =($P59*U59)*(1-$J59) -> 336764.88 | AN59: =($P59*V59)*(1-$J59) -> 0 | AO59: =($P59*W59)*(1-$J59) -> 0 | AP59: =SUM(AK59:AO59) -> 336764.88 | AQ59: =S59*$Q59 -> 0 | AR59: =T59*$Q59 -> 0 | AS59: =U59*$Q59 -> 75465.52 | AT59: =V59*$Q59 -> 0 | AU59: =W59*$Q59 -> 0 | AV59: =SUM(AQ59:AU59) -> 75465.52 | AW59: =S59*$R59 -> 0 | AX59: =T59*$R59 -> 0 | AY59: =U59*$R59 -> 100620.69 | AZ59: =V59*$R59 -> 0 | BA59: =W59*$R59 -> 0 | BB59: =SUM(AW59:BA59) -> 100620.69 | BC59: =$Y59+$AE59+$AK59+$AQ59+AW59 -> 0 | BD59: =$Z59+$AF59+$AL59+AR59+AX59 -> 0 | BE59: =$AA59+$AG59+$AM59+AS59+AY59 -> 994950 | BF59: =$AB59+$AH59+$AN59+AT59+AZ59 -> 0 | BG59: =$AC59+$AI59+$AO59+AU59+BA59 -> 0 | BH59: =SUM(BC59:BG59) -> 994950 | BI59: =$Y59/$M59 -> 0 | BJ59: =$Z59/$M59 -> 0 | BK59: =$AA59/$M59 -> 104771.3 | BL59: =$AB59/$M59 -> 0 | BM59: =$AC59/$M59 -> 0 | BN59: =$AD59/$M59 -> 104771.3 | BO59: =$AE59/$M59 -> 0 | BP59: =$AF59/$M59 -> 0 | BQ59: =$AG59/$M59 -> 377327.6 | BR59: =$AH59/$M59 -> 0 | BS59: =$AI59/$M59 -> 0 | BT59: =$AJ59/$M59 -> 377327.6 | BU59: =$AK59/$M59 -> 0 | BV59: =$AL59/$M59 -> 0 | BW59: =$AM59/$M59 -> 336764.88 | BX59: =$AN59/$M59 -> 0 | BY59: =$AO59/$M59 -> 0 | BZ59: =$AP59/$M59 -> 336764.88 | CA59: =AQ59/$M59 -> 0 | CB59: =AR59/$M59 -> 0 | CC59: =AS59/$M59 -> 75465.52 | CD59: =AT59/$M59 -> 0 | CE59: =AU59/$M59 -> 0 | CF59: =AV59/$M59 -> 75465.52 | CG59: =AW59/$M59 -> 0 | CH59: =AX59/$M59 -> 0 | ... CL59: =BB59/$M59 -> 100620.69 | CM59: =$BC59/$M59 -> 0 | CN59: =$BD59/$M59 -> 0 | CO59: =$BE59/$M59 -> 994950 | CP59: =$BF59/$M59 -> 0 | CQ59: =$BG59/$M59 -> 0 | CR59: =SUM(CM59:CQ59) -> 994950 | CS59: =K59-CR59 -> 1520567.3 | CU59: =D59 -> ARS | CV59: =VLOOKUP(CU59,DF:DG,2,0) -> 0.0006918517 | CW59: =K59*CV59 -> 1740.3649 | CX59: =BN59*CV59 -> 72.4862 | CY59: =BT59*CV59 -> 261.05474 | CZ59: =BZ59*CV59 -> 232.99136 | DA59: =CF59*CV59 -> 52.210948 | DB59: =CL59*CV59 -> 69.614598 | DC59: =CS59*CV59 -> 1052.0071 | DD59: =VLOOKUP(A59,'Billing Report'!H:I,2,FALSE) -> 2025_MODO_BRANDING_PROMO_VEA&DISCO_GEO_TWITTER_NU_AW_DIC | DF59: SEK | DG59: 0.11285172
A60: 40613189 | B60: T3209384 | C60: 320938401 | D60: ARS | G60: 2052055 | J60: =VLOOKUP($B60,'IMS Commission List'!E:CE,79,0)/100 -> 0.15 | K60: =SUM(E60:I60) -> 2052055 | L60: =VLOOKUP($B60,'IMS Commission List'!E:V,18,0) -> ARS | M60: 1 | N60: =VLOOKUP($B60,'IMS Commission List'!E:T,16,0) -> MX | O60: =VLOOKUP($B60,'IMS Commission List'!E:CF,80,0) -> 0.049 | P60: =VLOOKUP($B60,'IMS Commission List'!E:CG,81,0) -> 0.1575 | Q60: =VLOOKUP($B60,'IMS Commission List'!E:CP,90,0) -> 0.03 | R60: =VLOOKUP($B60,'IMS Commission List'!E:CQ,91,0) -> 0.04 | S60: =$E60*$M60 -> 0 | T60: =$F60*$M60 -> 0 | U60: =$G60*$M60 -> 2052055 | V60: =$H60*$M60 -> 0 | W60: =$I60*$M60 -> 0 | X60: =$K60*$M60 -> 2052055 | Y60: =(S60*$O60)*(1-J60) -> 0 | Z60: =(T60*$O60)*(1-J60) -> 0 | AA60: =(U60*$O60)*(1-J60) -> 85468.091 | AB60: =(V60*$O60)*(1-J60) -> 0 | AC60: =(W60*$O60)*(1-J60) -> 0 | AD60: =SUM(Y60:AC60) -> 85468.091 | AE60: =S60*$J60 -> 0 | AF60: =T60*$J60 -> 0 | AG60: =U60*$J60 -> 307808.25 | AH60: =V60*$J60 -> 0 | AI60: =W60*$J60 -> 0 | AJ60: =SUM(AE60:AI60) -> 307808.25 | AK60: =($P60*S60)*(1-$J60) -> 0 | AL60: =($P60*T60)*(1-$J60) -> 0 | AM60: =($P60*U60)*(1-$J60) -> 274718.86 | AN60: =($P60*V60)*(1-$J60) -> 0 | AO60: =($P60*W60)*(1-$J60) -> 0 | AP60: =SUM(AK60:AO60) -> 274718.86 | AQ60: =S60*$Q60 -> 0 | AR60: =T60*$Q60 -> 0 | AS60: =U60*$Q60 -> 61561.65 | AT60: =V60*$Q60 -> 0 | AU60: =W60*$Q60 -> 0 | AV60: =SUM(AQ60:AU60) -> 61561.65 | AW60: =S60*$R60 -> 0 | AX60: =T60*$R60 -> 0 | AY60: =U60*$R60 -> 82082.2 | AZ60: =V60*$R60 -> 0 | BA60: =W60*$R60 -> 0 | BB60: =SUM(AW60:BA60) -> 82082.2 | BC60: =$Y60+$AE60+$AK60+$AQ60+AW60 -> 0 | BD60: =$Z60+$AF60+$AL60+AR60+AX60 -> 0 | BE60: =$AA60+$AG60+$AM60+AS60+AY60 -> 811639.05 | BF60: =$AB60+$AH60+$AN60+AT60+AZ60 -> 0 | BG60: =$AC60+$AI60+$AO60+AU60+BA60 -> 0 | BH60: =SUM(BC60:BG60) -> 811639.05 | BI60: =$Y60/$M60 -> 0 | BJ60: =$Z60/$M60 -> 0 | BK60: =$AA60/$M60 -> 85468.091 | BL60: =$AB60/$M60 -> 0 | BM60: =$AC60/$M60 -> 0 | BN60: =$AD60/$M60 -> 85468.091 | BO60: =$AE60/$M60 -> 0 | BP60: =$AF60/$M60 -> 0 | BQ60: =$AG60/$M60 -> 307808.25 | BR60: =$AH60/$M60 -> 0 | BS60: =$AI60/$M60 -> 0 | BT60: =$AJ60/$M60 -> 307808.25 | BU60: =$AK60/$M60 -> 0 | BV60: =$AL60/$M60 -> 0 | BW60: =$AM60/$M60 -> 274718.86 | BX60: =$AN60/$M60 -> 0 | BY60: =$AO60/$M60 -> 0 | BZ60: =$AP60/$M60 -> 274718.86 | CA60: =AQ60/$M60 -> 0 | CB60: =AR60/$M60 -> 0 | CC60: =AS60/$M60 -> 61561.65 | CD60: =AT60/$M60 -> 0 | CE60: =AU60/$M60 -> 0 | CF60: =AV60/$M60 -> 61561.65 | CG60: =AW60/$M60 -> 0 | CH60: =AX60/$M60 -> 0 | ... CL60: =BB60/$M60 -> 82082.2 | CM60: =$BC60/$M60 -> 0 | CN60: =$BD60/$M60 -> 0 | CO60: =$BE60/$M60 -> 811639.05 | CP60: =$BF60/$M60 -> 0 | CQ60: =$BG60/$M60 -> 0 | CR60: =SUM(CM60:CQ60) -> 811639.05 | CS60: =K60-CR60 -> 1240415.9 | CU60: =D60 -> ARS | CV60: =VLOOKUP(CU60,DF:DG,2,0) -> 0.0006918517 | CW60: =K60*CV60 -> 1419.7177 | CX60: =BN60*CV60 -> 59.131244 | CY60: =BT60*CV60 -> 212.95766 | CZ60: =BZ60*CV60 -> 190.06471 | DA60: =CF60*CV60 -> 42.591532 | DB60: =CL60*CV60 -> 56.78871 | DC60: =CS60*CV60 -> 858.18388 | DD60: =VLOOKUP(A60,'Billing Report'!H:I,2,FALSE) -> 2025_MODO_BRANDING_PROMO_JUMBO_GEO_TWITTER_NU_AW_DIC | DF60: SGD | DG60: 0.78825811
A61: 40866465 | B61: T3210360 | C61: 321036001 | D61: ARS | G61: 4134155.9 | J61: =VLOOKUP($B61,'IMS Commission List'!E:CE,79,0)/100 -> 0.15 | K61: =SUM(E61:I61) -> 4134155.9 | L61: =VLOOKUP($B61,'IMS Commission List'!E:V,18,0) -> ARS | M61: 1 | N61: =VLOOKUP($B61,'IMS Commission List'!E:T,16,0) -> MX | O61: =VLOOKUP($B61,'IMS Commission List'!E:CF,80,0) -> 0.049 | P61: =VLOOKUP($B61,'IMS Commission List'!E:CG,81,0) -> 0.1575 | Q61: =VLOOKUP($B61,'IMS Commission List'!E:CP,90,0) -> 0.03 | R61: =VLOOKUP($B61,'IMS Commission List'!E:CQ,91,0) -> 0.04 | S61: =$E61*$M61 -> 0 | T61: =$F61*$M61 -> 0 | U61: =$G61*$M61 -> 4134155.9 | V61: =$H61*$M61 -> 0 | W61: =$I61*$M61 -> 0 | X61: =$K61*$M61 -> 4134155.9 | Y61: =(S61*$O61)*(1-J61) -> 0 | Z61: =(T61*$O61)*(1-J61) -> 0 | AA61: =(U61*$O61)*(1-J61) -> 172187.59 | AB61: =(V61*$O61)*(1-J61) -> 0 | AC61: =(W61*$O61)*(1-J61) -> 0 | AD61: =SUM(Y61:AC61) -> 172187.59 | AE61: =S61*$J61 -> 0 | AF61: =T61*$J61 -> 0 | AG61: =U61*$J61 -> 620123.38 | AH61: =V61*$J61 -> 0 | AI61: =W61*$J61 -> 0 | AJ61: =SUM(AE61:AI61) -> 620123.38 | AK61: =($P61*S61)*(1-$J61) -> 0 | AL61: =($P61*T61)*(1-$J61) -> 0 | AM61: =($P61*U61)*(1-$J61) -> 553460.12 | AN61: =($P61*V61)*(1-$J61) -> 0 | AO61: =($P61*W61)*(1-$J61) -> 0 | AP61: =SUM(AK61:AO61) -> 553460.12 | AQ61: =S61*$Q61 -> 0 | AR61: =T61*$Q61 -> 0 | AS61: =U61*$Q61 -> 124024.68 | AT61: =V61*$Q61 -> 0 | AU61: =W61*$Q61 -> 0 | AV61: =SUM(AQ61:AU61) -> 124024.68 | AW61: =S61*$R61 -> 0 | AX61: =T61*$R61 -> 0 | AY61: =U61*$R61 -> 165366.24 | AZ61: =V61*$R61 -> 0 | BA61: =W61*$R61 -> 0 | BB61: =SUM(AW61:BA61) -> 165366.24 | BC61: =$Y61+$AE61+$AK61+$AQ61+AW61 -> 0 | BD61: =$Z61+$AF61+$AL61+AR61+AX61 -> 0 | BE61: =$AA61+$AG61+$AM61+AS61+AY61 -> 1635162 | BF61: =$AB61+$AH61+$AN61+AT61+AZ61 -> 0 | BG61: =$AC61+$AI61+$AO61+AU61+BA61 -> 0 | BH61: =SUM(BC61:BG61) -> 1635162 | BI61: =$Y61/$M61 -> 0 | BJ61: =$Z61/$M61 -> 0 | BK61: =$AA61/$M61 -> 172187.59 | BL61: =$AB61/$M61 -> 0 | BM61: =$AC61/$M61 -> 0 | BN61: =$AD61/$M61 -> 172187.59 | BO61: =$AE61/$M61 -> 0 | BP61: =$AF61/$M61 -> 0 | BQ61: =$AG61/$M61 -> 620123.38 | BR61: =$AH61/$M61 -> 0 | BS61: =$AI61/$M61 -> 0 | BT61: =$AJ61/$M61 -> 620123.38 | BU61: =$AK61/$M61 -> 0 | BV61: =$AL61/$M61 -> 0 | BW61: =$AM61/$M61 -> 553460.12 | BX61: =$AN61/$M61 -> 0 | BY61: =$AO61/$M61 -> 0 | BZ61: =$AP61/$M61 -> 553460.12 | CA61: =AQ61/$M61 -> 0 | CB61: =AR61/$M61 -> 0 | CC61: =AS61/$M61 -> 124024.68 | CD61: =AT61/$M61 -> 0 | CE61: =AU61/$M61 -> 0 | CF61: =AV61/$M61 -> 124024.68 | CG61: =AW61/$M61 -> 0 | CH61: =AX61/$M61 -> 0 | ... CL61: =BB61/$M61 -> 165366.24 | CM61: =$BC61/$M61 -> 0 | CN61: =$BD61/$M61 -> 0 | CO61: =$BE61/$M61 -> 1635162 | CP61: =$BF61/$M61 -> 0 | CQ61: =$BG61/$M61 -> 0 | CR61: =SUM(CM61:CQ61) -> 1635162 | CS61: =K61-CR61 -> 2498993.9 | CU61: =D61 -> ARS | CV61: =VLOOKUP(CU61,DF:DG,2,0) -> 0.0006918517 | CW61: =K61*CV61 -> 2860.2228 | CX61: =BN61*CV61 -> 119.12828 | CY61: =BT61*CV61 -> 429.03342 | CZ61: =BZ61*CV61 -> 382.91232 | DA61: =CF61*CV61 -> 85.806683 | DB61: =CL61*CV61 -> 114.40891 | DC61: =CS61*CV61 -> 1728.9332 | DD61: =VLOOKUP(A61,'Billing Report'!H:I,2,FALSE) -> 17802_V3_P_2026_ARG_ISEDITION_TOTDIGOTH | DF61: THB | DG61: 0.031795173
A62: 40676315 | B62: T3210360 | C62: 321036001 | D62: ARS | G62: 1412281.8 | J62: =VLOOKUP($B62,'IMS Commission List'!E:CE,79,0)/100 -> 0.15 | K62: =SUM(E62:I62) -> 1412281.8 | L62: =VLOOKUP($B62,'IMS Commission List'!E:V,18,0) -> ARS | M62: 1 | N62: =VLOOKUP($B62,'IMS Commission List'!E:T,16,0) -> MX | O62: =VLOOKUP($B62,'IMS Commission List'!E:CF,80,0) -> 0.049 | P62: =VLOOKUP($B62,'IMS Commission List'!E:CG,81,0) -> 0.1575 | Q62: =VLOOKUP($B62,'IMS Commission List'!E:CP,90,0) -> 0.03 | R62: =VLOOKUP($B62,'IMS Commission List'!E:CQ,91,0) -> 0.04 | S62: =$E62*$M62 -> 0 | T62: =$F62*$M62 -> 0 | U62: =$G62*$M62 -> 1412281.8 | V62: =$H62*$M62 -> 0 | W62: =$I62*$M62 -> 0 | X62: =$K62*$M62 -> 1412281.8 | Y62: =(S62*$O62)*(1-J62) -> 0 | Z62: =(T62*$O62)*(1-J62) -> 0 | AA62: =(U62*$O62)*(1-J62) -> 58821.538 | AB62: =(V62*$O62)*(1-J62) -> 0 | AC62: =(W62*$O62)*(1-J62) -> 0 | AD62: =SUM(Y62:AC62) -> 58821.538 | AE62: =S62*$J62 -> 0 | AF62: =T62*$J62 -> 0 | AG62: =U62*$J62 -> 211842.27 | AH62: =V62*$J62 -> 0 | AI62: =W62*$J62 -> 0 | AJ62: =SUM(AE62:AI62) -> 211842.27 | AK62: =($P62*S62)*(1-$J62) -> 0 | AL62: =($P62*T62)*(1-$J62) -> 0 | AM62: =($P62*U62)*(1-$J62) -> 189069.23 | AN62: =($P62*V62)*(1-$J62) -> 0 | AO62: =($P62*W62)*(1-$J62) -> 0 | AP62: =SUM(AK62:AO62) -> 189069.23 | AQ62: =S62*$Q62 -> 0 | AR62: =T62*$Q62 -> 0 | AS62: =U62*$Q62 -> 42368.455 | AT62: =V62*$Q62 -> 0 | AU62: =W62*$Q62 -> 0 | AV62: =SUM(AQ62:AU62) -> 42368.455 | AW62: =S62*$R62 -> 0 | AX62: =T62*$R62 -> 0 | AY62: =U62*$R62 -> 56491.273 | AZ62: =V62*$R62 -> 0 | BA62: =W62*$R62 -> 0 | BB62: =SUM(AW62:BA62) -> 56491.273 | BC62: =$Y62+$AE62+$AK62+$AQ62+AW62 -> 0 | BD62: =$Z62+$AF62+$AL62+AR62+AX62 -> 0 | BE62: =$AA62+$AG62+$AM62+AS62+AY62 -> 558592.77 | BF62: =$AB62+$AH62+$AN62+AT62+AZ62 -> 0 | BG62: =$AC62+$AI62+$AO62+AU62+BA62 -> 0 | BH62: =SUM(BC62:BG62) -> 558592.77 | BI62: =$Y62/$M62 -> 0 | BJ62: =$Z62/$M62 -> 0 | BK62: =$AA62/$M62 -> 58821.538 | BL62: =$AB62/$M62 -> 0 | BM62: =$AC62/$M62 -> 0 | BN62: =$AD62/$M62 -> 58821.538 | BO62: =$AE62/$M62 -> 0 | BP62: =$AF62/$M62 -> 0 | BQ62: =$AG62/$M62 -> 211842.27 | BR62: =$AH62/$M62 -> 0 | BS62: =$AI62/$M62 -> 0 | BT62: =$AJ62/$M62 -> 211842.27 | BU62: =$AK62/$M62 -> 0 | BV62: =$AL62/$M62 -> 0 | BW62: =$AM62/$M62 -> 189069.23 | BX62: =$AN62/$M62 -> 0 | BY62: =$AO62/$M62 -> 0 | BZ62: =$AP62/$M62 -> 189069.23 | CA62: =AQ62/$M62 -> 0 | CB62: =AR62/$M62 -> 0 | CC62: =AS62/$M62 -> 42368.455 | CD62: =AT62/$M62 -> 0 | CE62: =AU62/$M62 -> 0 | CF62: =AV62/$M62 -> 42368.455 | CG62: =AW62/$M62 -> 0 | CH62: =AX62/$M62 -> 0 | ... CL62: =BB62/$M62 -> 56491.273 | CM62: =$BC62/$M62 -> 0 | CN62: =$BD62/$M62 -> 0 | CO62: =$BE62/$M62 -> 558592.77 | CP62: =$BF62/$M62 -> 0 | CQ62: =$BG62/$M62 -> 0 | CR62: =SUM(CM62:CQ62) -> 558592.77 | CS62: =K62-CR62 -> 853689.05 | CU62: =D62 -> ARS | CV62: =VLOOKUP(CU62,DF:DG,2,0) -> 0.0006918517 | CW62: =K62*CV62 -> 977.08958 | CX62: =BN62*CV62 -> 40.695781 | CY62: =BT62*CV62 -> 146.56344 | CZ62: =BZ62*CV62 -> 130.80787 | DA62: =CF62*CV62 -> 29.312687 | DB62: =CL62*CV62 -> 39.083583 | DC62: =CS62*CV62 -> 590.62622 | DD62: =VLOOKUP(A62,'Billing Report'!H:I,2,FALSE) -> 17802_V3_P_2026_ARG_ISEDITION_TOTDIGOTH | DF62: TND | DG62: 0.35120683
A63: 40888510 | B63: T3217930 | C63: 321793002 | D63: ARS | F63: 891000 | J63: =VLOOKUP($B63,'IMS Commission List'!E:CE,79,0)/100 -> 0.15 | K63: =SUM(E63:I63) -> 891000 | L63: =VLOOKUP($B63,'IMS Commission List'!E:V,18,0) -> ARS | M63: 1 | N63: =VLOOKUP($B63,'IMS Commission List'!E:T,16,0) -> MX | O63: =VLOOKUP($B63,'IMS Commission List'!E:CF,80,0) -> 0.049 | P63: =VLOOKUP($B63,'IMS Commission List'!E:CG,81,0) -> 0.1575 | Q63: =VLOOKUP($B63,'IMS Commission List'!E:CP,90,0) -> 0.03 | R63: =VLOOKUP($B63,'IMS Commission List'!E:CQ,91,0) -> 0.04 | S63: =$E63*$M63 -> 0 | T63: =$F63*$M63 -> 891000 | U63: =$G63*$M63 -> 0 | V63: =$H63*$M63 -> 0 | W63: =$I63*$M63 -> 0 | X63: =$K63*$M63 -> 891000 | Y63: =(S63*$O63)*(1-J63) -> 0 | Z63: =(T63*$O63)*(1-J63) -> 37110.15 | AA63: =(U63*$O63)*(1-J63) -> 0 | AB63: =(V63*$O63)*(1-J63) -> 0 | AC63: =(W63*$O63)*(1-J63) -> 0 | AD63: =SUM(Y63:AC63) -> 37110.15 | AE63: =S63*$J63 -> 0 | AF63: =T63*$J63 -> 133650 | AG63: =U63*$J63 -> 0 | AH63: =V63*$J63 -> 0 | AI63: =W63*$J63 -> 0 | AJ63: =SUM(AE63:AI63) -> 133650 | AK63: =($P63*S63)*(1-$J63) -> 0 | AL63: =($P63*T63)*(1-$J63) -> 119282.62 | AM63: =($P63*U63)*(1-$J63) -> 0 | AN63: =($P63*V63)*(1-$J63) -> 0 | AO63: =($P63*W63)*(1-$J63) -> 0 | AP63: =SUM(AK63:AO63) -> 119282.62 | AQ63: =S63*$Q63 -> 0 | AR63: =T63*$Q63 -> 26730 | AS63: =U63*$Q63 -> 0 | AT63: =V63*$Q63 -> 0 | AU63: =W63*$Q63 -> 0 | AV63: =SUM(AQ63:AU63) -> 26730 | AW63: =S63*$R63 -> 0 | AX63: =T63*$R63 -> 35640 | AY63: =U63*$R63 -> 0 | AZ63: =V63*$R63 -> 0 | BA63: =W63*$R63 -> 0 | BB63: =SUM(AW63:BA63) -> 35640 | BC63: =$Y63+$AE63+$AK63+$AQ63+AW63 -> 0 | BD63: =$Z63+$AF63+$AL63+AR63+AX63 -> 352412.78 | BE63: =$AA63+$AG63+$AM63+AS63+AY63 -> 0 | BF63: =$AB63+$AH63+$AN63+AT63+AZ63 -> 0 | BG63: =$AC63+$AI63+$AO63+AU63+BA63 -> 0 | BH63: =SUM(BC63:BG63) -> 352412.78 | BI63: =$Y63/$M63 -> 0 | BJ63: =$Z63/$M63 -> 37110.15 | BK63: =$AA63/$M63 -> 0 | BL63: =$AB63/$M63 -> 0 | BM63: =$AC63/$M63 -> 0 | BN63: =$AD63/$M63 -> 37110.15 | BO63: =$AE63/$M63 -> 0 | BP63: =$AF63/$M63 -> 133650 | BQ63: =$AG63/$M63 -> 0 | BR63: =$AH63/$M63 -> 0 | BS63: =$AI63/$M63 -> 0 | BT63: =$AJ63/$M63 -> 133650 | BU63: =$AK63/$M63 -> 0 | BV63: =$AL63/$M63 -> 119282.62 | BW63: =$AM63/$M63 -> 0 | BX63: =$AN63/$M63 -> 0 | BY63: =$AO63/$M63 -> 0 | BZ63: =$AP63/$M63 -> 119282.62 | CA63: =AQ63/$M63 -> 0 | CB63: =AR63/$M63 -> 26730 | CC63: =AS63/$M63 -> 0 | CD63: =AT63/$M63 -> 0 | CE63: =AU63/$M63 -> 0 | CF63: =AV63/$M63 -> 26730 | CG63: =AW63/$M63 -> 0 | CH63: =AX63/$M63 -> 35640 | ... CL63: =BB63/$M63 -> 35640 | CM63: =$BC63/$M63 -> 0 | CN63: =$BD63/$M63 -> 352412.78 | CO63: =$BE63/$M63 -> 0 | CP63: =$BF63/$M63 -> 0 | CQ63: =$BG63/$M63 -> 0 | CR63: =SUM(CM63:CQ63) -> 352412.78 | CS63: =K63-CR63 -> 538587.22 | CU63: =D63 -> ARS | CV63: =VLOOKUP(CU63,DF:DG,2,0) -> 0.0006918517 | CW63: =K63*CV63 -> 616.43986 | CX63: =BN63*CV63 -> 25.67472 | CY63: =BT63*CV63 -> 92.46598 | CZ63: =BZ63*CV63 -> 82.525887 | DA63: =CF63*CV63 -> 18.493196 | DB63: =CL63*CV63 -> 24.657595 | DC63: =CS63*CV63 -> 372.62249 | DD63: =VLOOKUP(A63,'Billing Report'!H:I,2,FALSE) -> pedidosya Estándar 2026-02-08 | DF63: TRY | DG63: 0.02300095
A64: 40888507 | B64: T3217930 | C64: 321793003 | D64: ARS | F64: 2565000 | J64: =VLOOKUP($B64,'IMS Commission List'!E:CE,79,0)/100 -> 0.15 | K64: =SUM(E64:I64) -> 2565000 | L64: =VLOOKUP($B64,'IMS Commission List'!E:V,18,0) -> ARS | M64: 1 | N64: =VLOOKUP($B64,'IMS Commission List'!E:T,16,0) -> MX | O64: =VLOOKUP($B64,'IMS Commission List'!E:CF,80,0) -> 0.049 | P64: =VLOOKUP($B64,'IMS Commission List'!E:CG,81,0) -> 0.1575 | Q64: =VLOOKUP($B64,'IMS Commission List'!E:CP,90,0) -> 0.03 | R64: =VLOOKUP($B64,'IMS Commission List'!E:CQ,91,0) -> 0.04 | S64: =$E64*$M64 -> 0 | T64: =$F64*$M64 -> 2565000 | U64: =$G64*$M64 -> 0 | V64: =$H64*$M64 -> 0 | W64: =$I64*$M64 -> 0 | X64: =$K64*$M64 -> 2565000 | Y64: =(S64*$O64)*(1-J64) -> 0 | Z64: =(T64*$O64)*(1-J64) -> 106832.25 | AA64: =(U64*$O64)*(1-J64) -> 0 | AB64: =(V64*$O64)*(1-J64) -> 0 | AC64: =(W64*$O64)*(1-J64) -> 0 | AD64: =SUM(Y64:AC64) -> 106832.25 | AE64: =S64*$J64 -> 0 | AF64: =T64*$J64 -> 384750 | AG64: =U64*$J64 -> 0 | AH64: =V64*$J64 -> 0 | AI64: =W64*$J64 -> 0 | AJ64: =SUM(AE64:AI64) -> 384750 | AK64: =($P64*S64)*(1-$J64) -> 0 | AL64: =($P64*T64)*(1-$J64) -> 343389.38 | AM64: =($P64*U64)*(1-$J64) -> 0 | AN64: =($P64*V64)*(1-$J64) -> 0 | AO64: =($P64*W64)*(1-$J64) -> 0 | AP64: =SUM(AK64:AO64) -> 343389.38 | AQ64: =S64*$Q64 -> 0 | AR64: =T64*$Q64 -> 76950 | AS64: =U64*$Q64 -> 0 | AT64: =V64*$Q64 -> 0 | AU64: =W64*$Q64 -> 0 | AV64: =SUM(AQ64:AU64) -> 76950 | AW64: =S64*$R64 -> 0 | AX64: =T64*$R64 -> 102600 | AY64: =U64*$R64 -> 0 | AZ64: =V64*$R64 -> 0 | BA64: =W64*$R64 -> 0 | BB64: =SUM(AW64:BA64) -> 102600 | BC64: =$Y64+$AE64+$AK64+$AQ64+AW64 -> 0 | BD64: =$Z64+$AF64+$AL64+AR64+AX64 -> 1014521.6 | BE64: =$AA64+$AG64+$AM64+AS64+AY64 -> 0 | BF64: =$AB64+$AH64+$AN64+AT64+AZ64 -> 0 | BG64: =$AC64+$AI64+$AO64+AU64+BA64 -> 0 | BH64: =SUM(BC64:BG64) -> 1014521.6 | BI64: =$Y64/$M64 -> 0 | BJ64: =$Z64/$M64 -> 106832.25 | BK64: =$AA64/$M64 -> 0 | BL64: =$AB64/$M64 -> 0 | BM64: =$AC64/$M64 -> 0 | BN64: =$AD64/$M64 -> 106832.25 | BO64: =$AE64/$M64 -> 0 | BP64: =$AF64/$M64 -> 384750 | BQ64: =$AG64/$M64 -> 0 | BR64: =$AH64/$M64 -> 0 | BS64: =$AI64/$M64 -> 0 | BT64: =$AJ64/$M64 -> 384750 | BU64: =$AK64/$M64 -> 0 | BV64: =$AL64/$M64 -> 343389.38 | BW64: =$AM64/$M64 -> 0 | BX64: =$AN64/$M64 -> 0 | BY64: =$AO64/$M64 -> 0 | BZ64: =$AP64/$M64 -> 343389.38 | CA64: =AQ64/$M64 -> 0 | CB64: =AR64/$M64 -> 76950 | CC64: =AS64/$M64 -> 0 | CD64: =AT64/$M64 -> 0 | CE64: =AU64/$M64 -> 0 | CF64: =AV64/$M64 -> 76950 | CG64: =AW64/$M64 -> 0 | CH64: =AX64/$M64 -> 102600 | ... CL64: =BB64/$M64 -> 102600 | CM64: =$BC64/$M64 -> 0 | CN64: =$BD64/$M64 -> 1014521.6 | CO64: =$BE64/$M64 -> 0 | CP64: =$BF64/$M64 -> 0 | CQ64: =$BG64/$M64 -> 0 | CR64: =SUM(CM64:CQ64) -> 1014521.6 | CS64: =K64-CR64 -> 1550478.4 | CU64: =D64 -> ARS | CV64: =VLOOKUP(CU64,DF:DG,2,0) -> 0.0006918517 | CW64: =K64*CV64 -> 1774.5996 | CX64: =BN64*CV64 -> 73.912074 | CY64: =BT64*CV64 -> 266.18994 | CZ64: =BZ64*CV64 -> 237.57452 | DA64: =CF64*CV64 -> 53.237988 | DB64: =CL64*CV64 -> 70.983984 | DC64: =CS64*CV64 -> 1072.7011 | DD64: =VLOOKUP(A64,'Billing Report'!H:I,2,FALSE) -> pedidosya Timeline Takeover Nivel 1 2026-02-08 | DF64: TWD | DG64: 0.031761973
A65: 40888463 | B65: T3217930 | C65: 321793004 | D65: ARS | F65: 891000 | J65: =VLOOKUP($B65,'IMS Commission List'!E:CE,79,0)/100 -> 0.15 | K65: =SUM(E65:I65) -> 891000 | L65: =VLOOKUP($B65,'IMS Commission List'!E:V,18,0) -> ARS | M65: 1 | N65: =VLOOKUP($B65,'IMS Commission List'!E:T,16,0) -> MX | O65: =VLOOKUP($B65,'IMS Commission List'!E:CF,80,0) -> 0.049 | P65: =VLOOKUP($B65,'IMS Commission List'!E:CG,81,0) -> 0.1575 | Q65: =VLOOKUP($B65,'IMS Commission List'!E:CP,90,0) -> 0.03 | R65: =VLOOKUP($B65,'IMS Commission List'!E:CQ,91,0) -> 0.04 | S65: =$E65*$M65 -> 0 | T65: =$F65*$M65 -> 891000 | U65: =$G65*$M65 -> 0 | V65: =$H65*$M65 -> 0 | W65: =$I65*$M65 -> 0 | X65: =$K65*$M65 -> 891000 | Y65: =(S65*$O65)*(1-J65) -> 0 | Z65: =(T65*$O65)*(1-J65) -> 37110.15 | AA65: =(U65*$O65)*(1-J65) -> 0 | AB65: =(V65*$O65)*(1-J65) -> 0 | AC65: =(W65*$O65)*(1-J65) -> 0 | AD65: =SUM(Y65:AC65) -> 37110.15 | AE65: =S65*$J65 -> 0 | AF65: =T65*$J65 -> 133650 | AG65: =U65*$J65 -> 0 | AH65: =V65*$J65 -> 0 | AI65: =W65*$J65 -> 0 | AJ65: =SUM(AE65:AI65) -> 133650 | AK65: =($P65*S65)*(1-$J65) -> 0 | AL65: =($P65*T65)*(1-$J65) -> 119282.62 | AM65: =($P65*U65)*(1-$J65) -> 0 | AN65: =($P65*V65)*(1-$J65) -> 0 | AO65: =($P65*W65)*(1-$J65) -> 0 | AP65: =SUM(AK65:AO65) -> 119282.62 | AQ65: =S65*$Q65 -> 0 | AR65: =T65*$Q65 -> 26730 | AS65: =U65*$Q65 -> 0 | AT65: =V65*$Q65 -> 0 | AU65: =W65*$Q65 -> 0 | AV65: =SUM(AQ65:AU65) -> 26730 | AW65: =S65*$R65 -> 0 | AX65: =T65*$R65 -> 35640 | AY65: =U65*$R65 -> 0 | AZ65: =V65*$R65 -> 0 | BA65: =W65*$R65 -> 0 | BB65: =SUM(AW65:BA65) -> 35640 | BC65: =$Y65+$AE65+$AK65+$AQ65+AW65 -> 0 | BD65: =$Z65+$AF65+$AL65+AR65+AX65 -> 352412.78 | BE65: =$AA65+$AG65+$AM65+AS65+AY65 -> 0 | BF65: =$AB65+$AH65+$AN65+AT65+AZ65 -> 0 | BG65: =$AC65+$AI65+$AO65+AU65+BA65 -> 0 | BH65: =SUM(BC65:BG65) -> 352412.78 | BI65: =$Y65/$M65 -> 0 | BJ65: =$Z65/$M65 -> 37110.15 | BK65: =$AA65/$M65 -> 0 | BL65: =$AB65/$M65 -> 0 | BM65: =$AC65/$M65 -> 0 | BN65: =$AD65/$M65 -> 37110.15 | BO65: =$AE65/$M65 -> 0 | BP65: =$AF65/$M65 -> 133650 | BQ65: =$AG65/$M65 -> 0 | BR65: =$AH65/$M65 -> 0 | BS65: =$AI65/$M65 -> 0 | BT65: =$AJ65/$M65 -> 133650 | BU65: =$AK65/$M65 -> 0 | BV65: =$AL65/$M65 -> 119282.62 | BW65: =$AM65/$M65 -> 0 | BX65: =$AN65/$M65 -> 0 | BY65: =$AO65/$M65 -> 0 | BZ65: =$AP65/$M65 -> 119282.62 | CA65: =AQ65/$M65 -> 0 | CB65: =AR65/$M65 -> 26730 | CC65: =AS65/$M65 -> 0 | CD65: =AT65/$M65 -> 0 | CE65: =AU65/$M65 -> 0 | CF65: =AV65/$M65 -> 26730 | CG65: =AW65/$M65 -> 0 | CH65: =AX65/$M65 -> 35640 | ... CL65: =BB65/$M65 -> 35640 | CM65: =$BC65/$M65 -> 0 | CN65: =$BD65/$M65 -> 352412.78 | CO65: =$BE65/$M65 -> 0 | CP65: =$BF65/$M65 -> 0 | CQ65: =$BG65/$M65 -> 0 | CR65: =SUM(CM65:CQ65) -> 352412.78 | CS65: =K65-CR65 -> 538587.22 | CU65: =D65 -> ARS | CV65: =VLOOKUP(CU65,DF:DG,2,0) -> 0.0006918517 | CW65: =K65*CV65 -> 616.43986 | CX65: =BN65*CV65 -> 25.67472 | CY65: =BT65*CV65 -> 92.46598 | CZ65: =BZ65*CV65 -> 82.525887 | DA65: =CF65*CV65 -> 18.493196 | DB65: =CL65*CV65 -> 24.657595 | DC65: =CS65*CV65 -> 372.62249 | DD65: =VLOOKUP(A65,'Billing Report'!H:I,2,FALSE) -> pedidosya Estándar 2026-02-05 | DF65: TZS | DG65: 0.0003897862
A66: 40887941 | B66: T3217930 | C66: 321793001 | D66: ARS | F66: 2565000 | J66: =VLOOKUP($B66,'IMS Commission List'!E:CE,79,0)/100 -> 0.15 | K66: =SUM(E66:I66) -> 2565000 | L66: =VLOOKUP($B66,'IMS Commission List'!E:V,18,0) -> ARS | M66: 1 | N66: =VLOOKUP($B66,'IMS Commission List'!E:T,16,0) -> MX | O66: =VLOOKUP($B66,'IMS Commission List'!E:CF,80,0) -> 0.049 | P66: =VLOOKUP($B66,'IMS Commission List'!E:CG,81,0) -> 0.1575 | Q66: =VLOOKUP($B66,'IMS Commission List'!E:CP,90,0) -> 0.03 | R66: =VLOOKUP($B66,'IMS Commission List'!E:CQ,91,0) -> 0.04 | S66: =$E66*$M66 -> 0 | T66: =$F66*$M66 -> 2565000 | U66: =$G66*$M66 -> 0 | V66: =$H66*$M66 -> 0 | W66: =$I66*$M66 -> 0 | X66: =$K66*$M66 -> 2565000 | Y66: =(S66*$O66)*(1-J66) -> 0 | Z66: =(T66*$O66)*(1-J66) -> 106832.25 | AA66: =(U66*$O66)*(1-J66) -> 0 | AB66: =(V66*$O66)*(1-J66) -> 0 | AC66: =(W66*$O66)*(1-J66) -> 0 | AD66: =SUM(Y66:AC66) -> 106832.25 | AE66: =S66*$J66 -> 0 | AF66: =T66*$J66 -> 384750 | AG66: =U66*$J66 -> 0 | AH66: =V66*$J66 -> 0 | AI66: =W66*$J66 -> 0 | AJ66: =SUM(AE66:AI66) -> 384750 | AK66: =($P66*S66)*(1-$J66) -> 0 | AL66: =($P66*T66)*(1-$J66) -> 343389.38 | AM66: =($P66*U66)*(1-$J66) -> 0 | AN66: =($P66*V66)*(1-$J66) -> 0 | AO66: =($P66*W66)*(1-$J66) -> 0 | AP66: =SUM(AK66:AO66) -> 343389.38 | AQ66: =S66*$Q66 -> 0 | AR66: =T66*$Q66 -> 76950 | AS66: =U66*$Q66 -> 0 | AT66: =V66*$Q66 -> 0 | AU66: =W66*$Q66 -> 0 | AV66: =SUM(AQ66:AU66) -> 76950 | AW66: =S66*$R66 -> 0 | AX66: =T66*$R66 -> 102600 | AY66: =U66*$R66 -> 0 | AZ66: =V66*$R66 -> 0 | BA66: =W66*$R66 -> 0 | BB66: =SUM(AW66:BA66) -> 102600 | BC66: =$Y66+$AE66+$AK66+$AQ66+AW66 -> 0 | BD66: =$Z66+$AF66+$AL66+AR66+AX66 -> 1014521.6 | BE66: =$AA66+$AG66+$AM66+AS66+AY66 -> 0 | BF66: =$AB66+$AH66+$AN66+AT66+AZ66 -> 0 | BG66: =$AC66+$AI66+$AO66+AU66+BA66 -> 0 | BH66: =SUM(BC66:BG66) -> 1014521.6 | BI66: =$Y66/$M66 -> 0 | BJ66: =$Z66/$M66 -> 106832.25 | BK66: =$AA66/$M66 -> 0 | BL66: =$AB66/$M66 -> 0 | BM66: =$AC66/$M66 -> 0 | BN66: =$AD66/$M66 -> 106832.25 | BO66: =$AE66/$M66 -> 0 | BP66: =$AF66/$M66 -> 384750 | BQ66: =$AG66/$M66 -> 0 | BR66: =$AH66/$M66 -> 0 | BS66: =$AI66/$M66 -> 0 | BT66: =$AJ66/$M66 -> 384750 | BU66: =$AK66/$M66 -> 0 | BV66: =$AL66/$M66 -> 343389.38 | BW66: =$AM66/$M66 -> 0 | BX66: =$AN66/$M66 -> 0 | BY66: =$AO66/$M66 -> 0 | BZ66: =$AP66/$M66 -> 343389.38 | CA66: =AQ66/$M66 -> 0 | CB66: =AR66/$M66 -> 76950 | CC66: =AS66/$M66 -> 0 | CD66: =AT66/$M66 -> 0 | CE66: =AU66/$M66 -> 0 | CF66: =AV66/$M66 -> 76950 | CG66: =AW66/$M66 -> 0 | CH66: =AX66/$M66 -> 102600 | ... CL66: =BB66/$M66 -> 102600 | CM66: =$BC66/$M66 -> 0 | CN66: =$BD66/$M66 -> 1014521.6 | CO66: =$BE66/$M66 -> 0 | CP66: =$BF66/$M66 -> 0 | CQ66: =$BG66/$M66 -> 0 | CR66: =SUM(CM66:CQ66) -> 1014521.6 | CS66: =K66-CR66 -> 1550478.4 | CU66: =D66 -> ARS | CV66: =VLOOKUP(CU66,DF:DG,2,0) -> 0.0006918517 | CW66: =K66*CV66 -> 1774.5996 | CX66: =BN66*CV66 -> 73.912074 | CY66: =BT66*CV66 -> 266.18994 | CZ66: =BZ66*CV66 -> 237.57452 | DA66: =CF66*CV66 -> 53.237988 | DB66: =CL66*CV66 -> 70.983984 | DC66: =CS66*CV66 -> 1072.7011 | DD66: =VLOOKUP(A66,'Billing Report'!H:I,2,FALSE) -> pedidosya Timeline Takeover Nivel 1 2026-02-05 | DF66: UAH | DG66: 0.023318111
A67: 40700854 | B67: T3218190 | C67: 321819001 | D67: ARS | G67: 9005104.1 | J67: =VLOOKUP($B67,'IMS Commission List'!E:CE,79,0)/100 -> 0.15 | K67: =SUM(E67:I67) -> 9005104.1 | L67: =VLOOKUP($B67,'IMS Commission List'!E:V,18,0) -> ARS | M67: 1 | N67: =VLOOKUP($B67,'IMS Commission List'!E:T,16,0) -> MX | O67: =VLOOKUP($B67,'IMS Commission List'!E:CF,80,0) -> 0.049 | P67: =VLOOKUP($B67,'IMS Commission List'!E:CG,81,0) -> 0.1575 | Q67: =VLOOKUP($B67,'IMS Commission List'!E:CP,90,0) -> 0.03 | R67: =VLOOKUP($B67,'IMS Commission List'!E:CQ,91,0) -> 0.04 | S67: =$E67*$M67 -> 0 | T67: =$F67*$M67 -> 0 | U67: =$G67*$M67 -> 9005104.1 | V67: =$H67*$M67 -> 0 | W67: =$I67*$M67 -> 0 | X67: =$K67*$M67 -> 9005104.1 | Y67: =(S67*$O67)*(1-J67) -> 0 | Z67: =(T67*$O67)*(1-J67) -> 0 | AA67: =(U67*$O67)*(1-J67) -> 375062.59 | AB67: =(V67*$O67)*(1-J67) -> 0 | AC67: =(W67*$O67)*(1-J67) -> 0 | AD67: =SUM(Y67:AC67) -> 375062.59 | AE67: =S67*$J67 -> 0 | AF67: =T67*$J67 -> 0 | AG67: =U67*$J67 -> 1350765.6 | AH67: =V67*$J67 -> 0 | AI67: =W67*$J67 -> 0 | AJ67: =SUM(AE67:AI67) -> 1350765.6 | AK67: =($P67*S67)*(1-$J67) -> 0 | AL67: =($P67*T67)*(1-$J67) -> 0 | AM67: =($P67*U67)*(1-$J67) -> 1205558.3 | AN67: =($P67*V67)*(1-$J67) -> 0 | AO67: =($P67*W67)*(1-$J67) -> 0 | AP67: =SUM(AK67:AO67) -> 1205558.3 | AQ67: =S67*$Q67 -> 0 | AR67: =T67*$Q67 -> 0 | AS67: =U67*$Q67 -> 270153.12 | AT67: =V67*$Q67 -> 0 | AU67: =W67*$Q67 -> 0 | AV67: =SUM(AQ67:AU67) -> 270153.12 | AW67: =S67*$R67 -> 0 | AX67: =T67*$R67 -> 0 | AY67: =U67*$R67 -> 360204.17 | AZ67: =V67*$R67 -> 0 | BA67: =W67*$R67 -> 0 | BB67: =SUM(AW67:BA67) -> 360204.17 | BC67: =$Y67+$AE67+$AK67+$AQ67+AW67 -> 0 | BD67: =$Z67+$AF67+$AL67+AR67+AX67 -> 0 | BE67: =$AA67+$AG67+$AM67+AS67+AY67 -> 3561743.8 | BF67: =$AB67+$AH67+$AN67+AT67+AZ67 -> 0 | BG67: =$AC67+$AI67+$AO67+AU67+BA67 -> 0 | BH67: =SUM(BC67:BG67) -> 3561743.8 | BI67: =$Y67/$M67 -> 0 | BJ67: =$Z67/$M67 -> 0 | BK67: =$AA67/$M67 -> 375062.59 | BL67: =$AB67/$M67 -> 0 | BM67: =$AC67/$M67 -> 0 | BN67: =$AD67/$M67 -> 375062.59 | BO67: =$AE67/$M67 -> 0 | BP67: =$AF67/$M67 -> 0 | BQ67: =$AG67/$M67 -> 1350765.6 | BR67: =$AH67/$M67 -> 0 | BS67: =$AI67/$M67 -> 0 | BT67: =$AJ67/$M67 -> 1350765.6 | BU67: =$AK67/$M67 -> 0 | BV67: =$AL67/$M67 -> 0 | BW67: =$AM67/$M67 -> 1205558.3 | BX67: =$AN67/$M67 -> 0 | BY67: =$AO67/$M67 -> 0 | BZ67: =$AP67/$M67 -> 1205558.3 | CA67: =AQ67/$M67 -> 0 | CB67: =AR67/$M67 -> 0 | CC67: =AS67/$M67 -> 270153.12 | CD67: =AT67/$M67 -> 0 | CE67: =AU67/$M67 -> 0 | CF67: =AV67/$M67 -> 270153.12 | CG67: =AW67/$M67 -> 0 | CH67: =AX67/$M67 -> 0 | ... CL67: =BB67/$M67 -> 360204.17 | CM67: =$BC67/$M67 -> 0 | CN67: =$BD67/$M67 -> 0 | CO67: =$BE67/$M67 -> 3561743.8 | CP67: =$BF67/$M67 -> 0 | CQ67: =$BG67/$M67 -> 0 | CR67: =SUM(CM67:CQ67) -> 3561743.8 | CS67: =K67-CR67 -> 5443360.3 | CU67: =D67 -> ARS | CV67: =VLOOKUP(CU67,DF:DG,2,0) -> 0.0006918517 | CW67: =K67*CV67 -> 6230.1966 | CX67: =BN67*CV67 -> 259.48769 | CY67: =BT67*CV67 -> 934.52949 | CZ67: =BZ67*CV67 -> 834.06757 | DA67: =CF67*CV67 -> 186.9059 | DB67: =CL67*CV67 -> 249.20786 | DC67: =CS67*CV67 -> 3765.9981 | DD67: =VLOOKUP(A67,'Billing Report'!H:I,2,FALSE) -> AR_DCB_OTH_OINV_FY25Q3_SSN_VERANO-2026_BAW_BRA_PSOC_TW_ALI-NA_AWA_B0005T5S | DF67: UGX | DG67: 0.0002802621
A68: 40983659 | B68: T3218548 | C68: 321854805 | D68: ARS | G68: 241926.19 | J68: =VLOOKUP($B68,'IMS Commission List'!E:CE,79,0)/100 -> 0.15 | K68: =SUM(E68:I68) -> 241926.19 | L68: =VLOOKUP($B68,'IMS Commission List'!E:V,18,0) -> ARS | M68: 1 | N68: =VLOOKUP($B68,'IMS Commission List'!E:T,16,0) -> MX | O68: =VLOOKUP($B68,'IMS Commission List'!E:CF,80,0) -> 0 | P68: =VLOOKUP($B68,'IMS Commission List'!E:CG,81,0) -> 0 | Q68: =VLOOKUP($B68,'IMS Commission List'!E:CP,90,0) -> 0.03 | R68: =VLOOKUP($B68,'IMS Commission List'!E:CQ,91,0) -> 0.04 | S68: =$E68*$M68 -> 0 | T68: =$F68*$M68 -> 0 | U68: =$G68*$M68 -> 241926.19 | V68: =$H68*$M68 -> 0 | W68: =$I68*$M68 -> 0 | X68: =$K68*$M68 -> 241926.19 | Y68: =(S68*$O68)*(1-J68) -> 0 | Z68: =(T68*$O68)*(1-J68) -> 0 | AA68: =(U68*$O68)*(1-J68) -> 0 | AB68: =(V68*$O68)*(1-J68) -> 0 | AC68: =(W68*$O68)*(1-J68) -> 0 | AD68: =SUM(Y68:AC68) -> 0 | AE68: =S68*$J68 -> 0 | AF68: =T68*$J68 -> 0 | AG68: =U68*$J68 -> 36288.929 | AH68: =V68*$J68 -> 0 | AI68: =W68*$J68 -> 0 | AJ68: =SUM(AE68:AI68) -> 36288.929 | AK68: =($P68*S68)*(1-$J68) -> 0 | AL68: =($P68*T68)*(1-$J68) -> 0 | AM68: =($P68*U68)*(1-$J68) -> 0 | AN68: =($P68*V68)*(1-$J68) -> 0 | AO68: =($P68*W68)*(1-$J68) -> 0 | AP68: =SUM(AK68:AO68) -> 0 | AQ68: =S68*$Q68 -> 0 | AR68: =T68*$Q68 -> 0 | AS68: =U68*$Q68 -> 7257.7857 | AT68: =V68*$Q68 -> 0 | AU68: =W68*$Q68 -> 0 | AV68: =SUM(AQ68:AU68) -> 7257.7857 | AW68: =S68*$R68 -> 0 | AX68: =T68*$R68 -> 0 | AY68: =U68*$R68 -> 9677.0476 | AZ68: =V68*$R68 -> 0 | BA68: =W68*$R68 -> 0 | BB68: =SUM(AW68:BA68) -> 9677.0476 | BC68: =$Y68+$AE68+$AK68+$AQ68+AW68 -> 0 | BD68: =$Z68+$AF68+$AL68+AR68+AX68 -> 0 | BE68: =$AA68+$AG68+$AM68+AS68+AY68 -> 53223.762 | BF68: =$AB68+$AH68+$AN68+AT68+AZ68 -> 0 | BG68: =$AC68+$AI68+$AO68+AU68+BA68 -> 0 | BH68: =SUM(BC68:BG68) -> 53223.762 | BI68: =$Y68/$M68 -> 0 | BJ68: =$Z68/$M68 -> 0 | BK68: =$AA68/$M68 -> 0 | BL68: =$AB68/$M68 -> 0 | BM68: =$AC68/$M68 -> 0 | BN68: =$AD68/$M68 -> 0 | BO68: =$AE68/$M68 -> 0 | BP68: =$AF68/$M68 -> 0 | BQ68: =$AG68/$M68 -> 36288.929 | BR68: =$AH68/$M68 -> 0 | BS68: =$AI68/$M68 -> 0 | BT68: =$AJ68/$M68 -> 36288.929 | BU68: =$AK68/$M68 -> 0 | BV68: =$AL68/$M68 -> 0 | BW68: =$AM68/$M68 -> 0 | BX68: =$AN68/$M68 -> 0 | BY68: =$AO68/$M68 -> 0 | BZ68: =$AP68/$M68 -> 0 | CA68: =AQ68/$M68 -> 0 | CB68: =AR68/$M68 -> 0 | CC68: =AS68/$M68 -> 7257.7857 | CD68: =AT68/$M68 -> 0 | CE68: =AU68/$M68 -> 0 | CF68: =AV68/$M68 -> 7257.7857 | CG68: =AW68/$M68 -> 0 | CH68: =AX68/$M68 -> 0 | ... CL68: =BB68/$M68 -> 9677.0476 | CM68: =$BC68/$M68 -> 0 | CN68: =$BD68/$M68 -> 0 | CO68: =$BE68/$M68 -> 53223.762 | CP68: =$BF68/$M68 -> 0 | CQ68: =$BG68/$M68 -> 0 | CR68: =SUM(CM68:CQ68) -> 53223.762 | CS68: =K68-CR68 -> 188702.43 | CU68: =D68 -> ARS | CV68: =VLOOKUP(CU68,DF:DG,2,0) -> 0.0006918517 | CW68: =K68*CV68 -> 167.37705 | CX68: =BN68*CV68 -> 0 | CY68: =BT68*CV68 -> 25.106557 | CZ68: =BZ68*CV68 -> 0 | DA68: =CF68*CV68 -> 5.0213114 | DB68: =CL68*CV68 -> 6.6950818 | DC68: =CS68*CV68 -> 130.5541 | DD68: =VLOOKUP(A68,'Billing Report'!H:I,2,FALSE) -> FW_MSC_LOLLA_EXBRD_BRD_NAC_REACH_X | DF68: VEF | DG68: 2.74e-08
A69: 40734151 | B69: T3219252 | C69: 321925201 | D69: ARS | G69: 296060.78 | J69: =VLOOKUP($B69,'IMS Commission List'!E:CE,79,0)/100 -> 0.15 | K69: =SUM(E69:I69) -> 296060.78 | L69: =VLOOKUP($B69,'IMS Commission List'!E:V,18,0) -> ARS | M69: 1 | N69: =VLOOKUP($B69,'IMS Commission List'!E:T,16,0) -> MX | O69: =VLOOKUP($B69,'IMS Commission List'!E:CF,80,0) -> 0.049 | P69: =VLOOKUP($B69,'IMS Commission List'!E:CG,81,0) -> 0.1575 | Q69: =VLOOKUP($B69,'IMS Commission List'!E:CP,90,0) -> 0.03 | R69: =VLOOKUP($B69,'IMS Commission List'!E:CQ,91,0) -> 0.04 | S69: =$E69*$M69 -> 0 | T69: =$F69*$M69 -> 0 | U69: =$G69*$M69 -> 296060.78 | V69: =$H69*$M69 -> 0 | W69: =$I69*$M69 -> 0 | X69: =$K69*$M69 -> 296060.78 | Y69: =(S69*$O69)*(1-J69) -> 0 | Z69: =(T69*$O69)*(1-J69) -> 0 | AA69: =(U69*$O69)*(1-J69) -> 12330.931 | AB69: =(V69*$O69)*(1-J69) -> 0 | AC69: =(W69*$O69)*(1-J69) -> 0 | AD69: =SUM(Y69:AC69) -> 12330.931 | AE69: =S69*$J69 -> 0 | AF69: =T69*$J69 -> 0 | AG69: =U69*$J69 -> 44409.117 | AH69: =V69*$J69 -> 0 | AI69: =W69*$J69 -> 0 | AJ69: =SUM(AE69:AI69) -> 44409.117 | AK69: =($P69*S69)*(1-$J69) -> 0 | AL69: =($P69*T69)*(1-$J69) -> 0 | AM69: =($P69*U69)*(1-$J69) -> 39635.137 | AN69: =($P69*V69)*(1-$J69) -> 0 | AO69: =($P69*W69)*(1-$J69) -> 0 | AP69: =SUM(AK69:AO69) -> 39635.137 | AQ69: =S69*$Q69 -> 0 | AR69: =T69*$Q69 -> 0 | AS69: =U69*$Q69 -> 8881.8234 | AT69: =V69*$Q69 -> 0 | AU69: =W69*$Q69 -> 0 | AV69: =SUM(AQ69:AU69) -> 8881.8234 | AW69: =S69*$R69 -> 0 | AX69: =T69*$R69 -> 0 | AY69: =U69*$R69 -> 11842.431 | AZ69: =V69*$R69 -> 0 | BA69: =W69*$R69 -> 0 | BB69: =SUM(AW69:BA69) -> 11842.431 | BC69: =$Y69+$AE69+$AK69+$AQ69+AW69 -> 0 | BD69: =$Z69+$AF69+$AL69+AR69+AX69 -> 0 | BE69: =$AA69+$AG69+$AM69+AS69+AY69 -> 117099.44 | BF69: =$AB69+$AH69+$AN69+AT69+AZ69 -> 0 | BG69: =$AC69+$AI69+$AO69+AU69+BA69 -> 0 | BH69: =SUM(BC69:BG69) -> 117099.44 | BI69: =$Y69/$M69 -> 0 | BJ69: =$Z69/$M69 -> 0 | BK69: =$AA69/$M69 -> 12330.931 | BL69: =$AB69/$M69 -> 0 | BM69: =$AC69/$M69 -> 0 | BN69: =$AD69/$M69 -> 12330.931 | BO69: =$AE69/$M69 -> 0 | BP69: =$AF69/$M69 -> 0 | BQ69: =$AG69/$M69 -> 44409.117 | BR69: =$AH69/$M69 -> 0 | BS69: =$AI69/$M69 -> 0 | BT69: =$AJ69/$M69 -> 44409.117 | BU69: =$AK69/$M69 -> 0 | BV69: =$AL69/$M69 -> 0 | BW69: =$AM69/$M69 -> 39635.137 | BX69: =$AN69/$M69 -> 0 | BY69: =$AO69/$M69 -> 0 | BZ69: =$AP69/$M69 -> 39635.137 | CA69: =AQ69/$M69 -> 0 | CB69: =AR69/$M69 -> 0 | CC69: =AS69/$M69 -> 8881.8234 | CD69: =AT69/$M69 -> 0 | CE69: =AU69/$M69 -> 0 | CF69: =AV69/$M69 -> 8881.8234 | CG69: =AW69/$M69 -> 0 | CH69: =AX69/$M69 -> 0 | ... CL69: =BB69/$M69 -> 11842.431 | CM69: =$BC69/$M69 -> 0 | CN69: =$BD69/$M69 -> 0 | CO69: =$BE69/$M69 -> 117099.44 | CP69: =$BF69/$M69 -> 0 | CQ69: =$BG69/$M69 -> 0 | CR69: =SUM(CM69:CQ69) -> 117099.44 | CS69: =K69-CR69 -> 178961.34 | CU69: =D69 -> ARS | CV69: =VLOOKUP(CU69,DF:DG,2,0) -> 0.0006918517 | CW69: =K69*CV69 -> 204.83015 | CX69: =BN69*CV69 -> 8.5311759 | CY69: =BT69*CV69 -> 30.724523 | CZ69: =BZ69*CV69 -> 27.421637 | DA69: =CF69*CV69 -> 6.1449046 | DB69: =CL69*CV69 -> 8.1932062 | DC69: =CS69*CV69 -> 123.81471 | DD69: =VLOOKUP(A69,'Billing Report'!H:I,2,FALSE) -> ypf_combustibles-tw-alcance-season-verano2026_bdd-2025-dic | DF69: VND | DG69: 3.85582e-05
A70: 40734032 | B70: T3219252 | C70: 321925201 | D70: ARS | G70: 1381796.4 | J70: =VLOOKUP($B70,'IMS Commission List'!E:CE,79,0)/100 -> 0.15 | K70: =SUM(E70:I70) -> 1381796.4 | L70: =VLOOKUP($B70,'IMS Commission List'!E:V,18,0) -> ARS | M70: 1 | N70: =VLOOKUP($B70,'IMS Commission List'!E:T,16,0) -> MX | O70: =VLOOKUP($B70,'IMS Commission List'!E:CF,80,0) -> 0.049 | P70: =VLOOKUP($B70,'IMS Commission List'!E:CG,81,0) -> 0.1575 | Q70: =VLOOKUP($B70,'IMS Commission List'!E:CP,90,0) -> 0.03 | R70: =VLOOKUP($B70,'IMS Commission List'!E:CQ,91,0) -> 0.04 | S70: =$E70*$M70 -> 0 | T70: =$F70*$M70 -> 0 | U70: =$G70*$M70 -> 1381796.4 | V70: =$H70*$M70 -> 0 | W70: =$I70*$M70 -> 0 | X70: =$K70*$M70 -> 1381796.4 | Y70: =(S70*$O70)*(1-J70) -> 0 | Z70: =(T70*$O70)*(1-J70) -> 0 | AA70: =(U70*$O70)*(1-J70) -> 57551.819 | AB70: =(V70*$O70)*(1-J70) -> 0 | AC70: =(W70*$O70)*(1-J70) -> 0 | AD70: =SUM(Y70:AC70) -> 57551.819 | AE70: =S70*$J70 -> 0 | AF70: =T70*$J70 -> 0 | AG70: =U70*$J70 -> 207269.46 | AH70: =V70*$J70 -> 0 | AI70: =W70*$J70 -> 0 | AJ70: =SUM(AE70:AI70) -> 207269.46 | AK70: =($P70*S70)*(1-$J70) -> 0 | AL70: =($P70*T70)*(1-$J70) -> 0 | AM70: =($P70*U70)*(1-$J70) -> 184987.99 | AN70: =($P70*V70)*(1-$J70) -> 0 | AO70: =($P70*W70)*(1-$J70) -> 0 | AP70: =SUM(AK70:AO70) -> 184987.99 | AQ70: =S70*$Q70 -> 0 | AR70: =T70*$Q70 -> 0 | AS70: =U70*$Q70 -> 41453.891 | AT70: =V70*$Q70 -> 0 | AU70: =W70*$Q70 -> 0 | AV70: =SUM(AQ70:AU70) -> 41453.891 | AW70: =S70*$R70 -> 0 | AX70: =T70*$R70 -> 0 | AY70: =U70*$R70 -> 55271.855 | AZ70: =V70*$R70 -> 0 | BA70: =W70*$R70 -> 0 | BB70: =SUM(AW70:BA70) -> 55271.855 | BC70: =$Y70+$AE70+$AK70+$AQ70+AW70 -> 0 | BD70: =$Z70+$AF70+$AL70+AR70+AX70 -> 0 | BE70: =$AA70+$AG70+$AM70+AS70+AY70 -> 546535.01 | BF70: =$AB70+$AH70+$AN70+AT70+AZ70 -> 0 | BG70: =$AC70+$AI70+$AO70+AU70+BA70 -> 0 | BH70: =SUM(BC70:BG70) -> 546535.01 | BI70: =$Y70/$M70 -> 0 | BJ70: =$Z70/$M70 -> 0 | BK70: =$AA70/$M70 -> 57551.819 | BL70: =$AB70/$M70 -> 0 | BM70: =$AC70/$M70 -> 0 | BN70: =$AD70/$M70 -> 57551.819 | BO70: =$AE70/$M70 -> 0 | BP70: =$AF70/$M70 -> 0 | BQ70: =$AG70/$M70 -> 207269.46 | BR70: =$AH70/$M70 -> 0 | BS70: =$AI70/$M70 -> 0 | BT70: =$AJ70/$M70 -> 207269.46 | BU70: =$AK70/$M70 -> 0 | BV70: =$AL70/$M70 -> 0 | BW70: =$AM70/$M70 -> 184987.99 | BX70: =$AN70/$M70 -> 0 | BY70: =$AO70/$M70 -> 0 | BZ70: =$AP70/$M70 -> 184987.99 | CA70: =AQ70/$M70 -> 0 | CB70: =AR70/$M70 -> 0 | CC70: =AS70/$M70 -> 41453.891 | CD70: =AT70/$M70 -> 0 | CE70: =AU70/$M70 -> 0 | CF70: =AV70/$M70 -> 41453.891 | CG70: =AW70/$M70 -> 0 | CH70: =AX70/$M70 -> 0 | ... CL70: =BB70/$M70 -> 55271.855 | CM70: =$BC70/$M70 -> 0 | CN70: =$BD70/$M70 -> 0 | CO70: =$BE70/$M70 -> 546535.01 | CP70: =$BF70/$M70 -> 0 | CQ70: =$BG70/$M70 -> 0 | CR70: =SUM(CM70:CQ70) -> 546535.01 | CS70: =K70-CR70 -> 835261.37 | CU70: =D70 -> ARS | CV70: =VLOOKUP(CU70,DF:DG,2,0) -> 0.0006918517 | CW70: =K70*CV70 -> 955.99817 | CX70: =BN70*CV70 -> 39.817324 | CY70: =BT70*CV70 -> 143.39973 | CZ70: =BZ70*CV70 -> 127.98426 | DA70: =CF70*CV70 -> 28.679945 | DB70: =CL70*CV70 -> 38.239927 | DC70: =CS70*CV70 -> 577.877 | DD70: =VLOOKUP(A70,'Billing Report'!H:I,2,FALSE) -> ypf_combustibles-tw-alcance-season-verano2026_intereses-2025-dic | DF70: ZAR | DG70: 0.062622348
A71: 40734874 | B71: T3219531 | C71: 321953101 | D71: ARS | G71: 1952420.4 | J71: =VLOOKUP($B71,'IMS Commission List'!E:CE,79,0)/100 -> 0.08 | K71: =SUM(E71:I71) -> 1952420.4 | L71: =VLOOKUP($B71,'IMS Commission List'!E:V,18,0) -> ARS | M71: 1 | N71: =VLOOKUP($B71,'IMS Commission List'!E:T,16,0) -> MX | O71: =VLOOKUP($B71,'IMS Commission List'!E:CF,80,0) -> 0.049 | P71: =VLOOKUP($B71,'IMS Commission List'!E:CG,81,0) -> 0.1575 | Q71: =VLOOKUP($B71,'IMS Commission List'!E:CP,90,0) -> 0.03 | R71: =VLOOKUP($B71,'IMS Commission List'!E:CQ,91,0) -> 0.04 | S71: =$E71*$M71 -> 0 | T71: =$F71*$M71 -> 0 | U71: =$G71*$M71 -> 1952420.4 | V71: =$H71*$M71 -> 0 | W71: =$I71*$M71 -> 0 | X71: =$K71*$M71 -> 1952420.4 | Y71: =(S71*$O71)*(1-J71) -> 0 | Z71: =(T71*$O71)*(1-J71) -> 0 | AA71: =(U71*$O71)*(1-J71) -> 88015.113 | AB71: =(V71*$O71)*(1-J71) -> 0 | AC71: =(W71*$O71)*(1-J71) -> 0 | AD71: =SUM(Y71:AC71) -> 88015.113 | AE71: =S71*$J71 -> 0 | AF71: =T71*$J71 -> 0 | AG71: =U71*$J71 -> 156193.64 | AH71: =V71*$J71 -> 0 | AI71: =W71*$J71 -> 0 | AJ71: =SUM(AE71:AI71) -> 156193.64 | AK71: =($P71*S71)*(1-$J71) -> 0 | AL71: =($P71*T71)*(1-$J71) -> 0 | AM71: =($P71*U71)*(1-$J71) -> 282905.72 | AN71: =($P71*V71)*(1-$J71) -> 0 | AO71: =($P71*W71)*(1-$J71) -> 0 | AP71: =SUM(AK71:AO71) -> 282905.72 | AQ71: =S71*$Q71 -> 0 | AR71: =T71*$Q71 -> 0 | AS71: =U71*$Q71 -> 58572.613 | AT71: =V71*$Q71 -> 0 | AU71: =W71*$Q71 -> 0 | AV71: =SUM(AQ71:AU71) -> 58572.613 | AW71: =S71*$R71 -> 0 | AX71: =T71*$R71 -> 0 | AY71: =U71*$R71 -> 78096.818 | AZ71: =V71*$R71 -> 0 | BA71: =W71*$R71 -> 0 | BB71: =SUM(AW71:BA71) -> 78096.818 | BC71: =$Y71+$AE71+$AK71+$AQ71+AW71 -> 0 | BD71: =$Z71+$AF71+$AL71+AR71+AX71 -> 0 | BE71: =$AA71+$AG71+$AM71+AS71+AY71 -> 663783.9 | BF71: =$AB71+$AH71+$AN71+AT71+AZ71 -> 0 | BG71: =$AC71+$AI71+$AO71+AU71+BA71 -> 0 | BH71: =SUM(BC71:BG71) -> 663783.9 | BI71: =$Y71/$M71 -> 0 | BJ71: =$Z71/$M71 -> 0 | BK71: =$AA71/$M71 -> 88015.113 | BL71: =$AB71/$M71 -> 0 | BM71: =$AC71/$M71 -> 0 | BN71: =$AD71/$M71 -> 88015.113 | BO71: =$AE71/$M71 -> 0 | BP71: =$AF71/$M71 -> 0 | BQ71: =$AG71/$M71 -> 156193.64 | BR71: =$AH71/$M71 -> 0 | BS71: =$AI71/$M71 -> 0 | BT71: =$AJ71/$M71 -> 156193.64 | BU71: =$AK71/$M71 -> 0 | BV71: =$AL71/$M71 -> 0 | BW71: =$AM71/$M71 -> 282905.72 | BX71: =$AN71/$M71 -> 0 | BY71: =$AO71/$M71 -> 0 | BZ71: =$AP71/$M71 -> 282905.72 | CA71: =AQ71/$M71 -> 0 | CB71: =AR71/$M71 -> 0 | CC71: =AS71/$M71 -> 58572.613 | CD71: =AT71/$M71 -> 0 | CE71: =AU71/$M71 -> 0 | CF71: =AV71/$M71 -> 58572.613 | CG71: =AW71/$M71 -> 0 | CH71: =AX71/$M71 -> 0 | ... CL71: =BB71/$M71 -> 78096.818 | CM71: =$BC71/$M71 -> 0 | CN71: =$BD71/$M71 -> 0 | CO71: =$BE71/$M71 -> 663783.9 | CP71: =$BF71/$M71 -> 0 | CQ71: =$BG71/$M71 -> 0 | CR71: =SUM(CM71:CQ71) -> 663783.9 | CS71: =K71-CR71 -> 1288636.5 | CU71: =D71 -> ARS | CV71: =VLOOKUP(CU71,DF:DG,2,0) -> 0.0006918517 | CW71: =K71*CV71 -> 1350.7854 | CX71: =BN71*CV71 -> 60.893406 | CY71: =BT71*CV71 -> 108.06283 | CZ71: =BZ71*CV71 -> 195.7288 | DA71: =CF71*CV71 -> 40.523562 | DB71: =CL71*CV71 -> 54.031416 | DC71: =CS71*CV71 -> 891.54538 | DD71: =VLOOKUP(A71,'Billing Report'!H:I,2,FALSE) -> MLA_ML_TW-TWT_GEN_X_BRD-F-GEN-X_ALL_REACH_SUMMER-26_X_36235263 | DF71: ZMW | DG71: 0.050676904
A72: 40788989 | B72: T3221498 | C72: 322149801 | D72: ARS | G72: 474511.63 | J72: =VLOOKUP($B72,'IMS Commission List'!E:CE,79,0)/100 -> 0.15 | K72: =SUM(E72:I72) -> 474511.63 | L72: =VLOOKUP($B72,'IMS Commission List'!E:V,18,0) -> ARS | M72: 1 | N72: =VLOOKUP($B72,'IMS Commission List'!E:T,16,0) -> MX | O72: =VLOOKUP($B72,'IMS Commission List'!E:CF,80,0) -> 0.049 | P72: =VLOOKUP($B72,'IMS Commission List'!E:CG,81,0) -> 0.1575 | Q72: =VLOOKUP($B72,'IMS Commission List'!E:CP,90,0) -> 0.03 | R72: =VLOOKUP($B72,'IMS Commission List'!E:CQ,91,0) -> 0.04 | S72: =$E72*$M72 -> 0 | T72: =$F72*$M72 -> 0 | U72: =$G72*$M72 -> 474511.63 | V72: =$H72*$M72 -> 0 | W72: =$I72*$M72 -> 0 | X72: =$K72*$M72 -> 474511.63 | Y72: =(S72*$O72)*(1-J72) -> 0 | Z72: =(T72*$O72)*(1-J72) -> 0 | AA72: =(U72*$O72)*(1-J72) -> 19763.409 | AB72: =(V72*$O72)*(1-J72) -> 0 | AC72: =(W72*$O72)*(1-J72) -> 0 | AD72: =SUM(Y72:AC72) -> 19763.409 | AE72: =S72*$J72 -> 0 | AF72: =T72*$J72 -> 0 | AG72: =U72*$J72 -> 71176.745 | AH72: =V72*$J72 -> 0 | AI72: =W72*$J72 -> 0 | AJ72: =SUM(AE72:AI72) -> 71176.745 | AK72: =($P72*S72)*(1-$J72) -> 0 | AL72: =($P72*T72)*(1-$J72) -> 0 | AM72: =($P72*U72)*(1-$J72) -> 63525.244 | AN72: =($P72*V72)*(1-$J72) -> 0 | AO72: =($P72*W72)*(1-$J72) -> 0 | AP72: =SUM(AK72:AO72) -> 63525.244 | AQ72: =S72*$Q72 -> 0 | AR72: =T72*$Q72 -> 0 | AS72: =U72*$Q72 -> 14235.349 | AT72: =V72*$Q72 -> 0 | AU72: =W72*$Q72 -> 0 | AV72: =SUM(AQ72:AU72) -> 14235.349 | AW72: =S72*$R72 -> 0 | AX72: =T72*$R72 -> 0 | AY72: =U72*$R72 -> 18980.465 | AZ72: =V72*$R72 -> 0 | BA72: =W72*$R72 -> 0 | BB72: =SUM(AW72:BA72) -> 18980.465 | BC72: =$Y72+$AE72+$AK72+$AQ72+AW72 -> 0 | BD72: =$Z72+$AF72+$AL72+AR72+AX72 -> 0 | BE72: =$AA72+$AG72+$AM72+AS72+AY72 -> 187681.21 | BF72: =$AB72+$AH72+$AN72+AT72+AZ72 -> 0 | BG72: =$AC72+$AI72+$AO72+AU72+BA72 -> 0 | BH72: =SUM(BC72:BG72) -> 187681.21 | BI72: =$Y72/$M72 -> 0 | BJ72: =$Z72/$M72 -> 0 | BK72: =$AA72/$M72 -> 19763.409 | BL72: =$AB72/$M72 -> 0 | BM72: =$AC72/$M72 -> 0 | BN72: =$AD72/$M72 -> 19763.409 | BO72: =$AE72/$M72 -> 0 | BP72: =$AF72/$M72 -> 0 | BQ72: =$AG72/$M72 -> 71176.745 | BR72: =$AH72/$M72 -> 0 | BS72: =$AI72/$M72 -> 0 | BT72: =$AJ72/$M72 -> 71176.745 | BU72: =$AK72/$M72 -> 0 | BV72: =$AL72/$M72 -> 0 | BW72: =$AM72/$M72 -> 63525.244 | BX72: =$AN72/$M72 -> 0 | BY72: =$AO72/$M72 -> 0 | BZ72: =$AP72/$M72 -> 63525.244 | CA72: =AQ72/$M72 -> 0 | CB72: =AR72/$M72 -> 0 | CC72: =AS72/$M72 -> 14235.349 | CD72: =AT72/$M72 -> 0 | CE72: =AU72/$M72 -> 0 | CF72: =AV72/$M72 -> 14235.349 | CG72: =AW72/$M72 -> 0 | CH72: =AX72/$M72 -> 0 | ... CL72: =BB72/$M72 -> 18980.465 | CM72: =$BC72/$M72 -> 0 | CN72: =$BD72/$M72 -> 0 | CO72: =$BE72/$M72 -> 187681.21 | CP72: =$BF72/$M72 -> 0 | CQ72: =$BG72/$M72 -> 0 | CR72: =SUM(CM72:CQ72) -> 187681.21 | CS72: =K72-CR72 -> 286830.42 | CU72: =D72 -> ARS | CV72: =VLOOKUP(CU72,DF:DG,2,0) -> 0.0006918517 | CW72: =K72*CV72 -> 328.29168 | CX72: =BN72*CV72 -> 13.673348 | CY72: =BT72*CV72 -> 49.243752 | CZ72: =BZ72*CV72 -> 43.950048 | DA72: =CF72*CV72 -> 9.8487503 | DB72: =CL72*CV72 -> 13.131667 | DC72: =CS72*CV72 -> 198.44411 | DD72: =VLOOKUP(A72,'Billing Report'!H:I,2,FALSE) -> ARG_BRD_BRA_SEDDEBRAHMA_VERANO_NON_ENG_BEY_2026_NOA | DF72: USD | DG72: 1
A73: 40745375 | B73: T3221498 | C73: 322149801 | D73: ARS | G73: 3703283.4 | J73: =VLOOKUP($B73,'IMS Commission List'!E:CE,79,0)/100 -> 0.15 | K73: =SUM(E73:I73) -> 3703283.4 | L73: =VLOOKUP($B73,'IMS Commission List'!E:V,18,0) -> ARS | M73: 1 | N73: =VLOOKUP($B73,'IMS Commission List'!E:T,16,0) -> MX | O73: =VLOOKUP($B73,'IMS Commission List'!E:CF,80,0) -> 0.049 | P73: =VLOOKUP($B73,'IMS Commission List'!E:CG,81,0) -> 0.1575 | Q73: =VLOOKUP($B73,'IMS Commission List'!E:CP,90,0) -> 0.03 | R73: =VLOOKUP($B73,'IMS Commission List'!E:CQ,91,0) -> 0.04 | S73: =$E73*$M73 -> 0 | T73: =$F73*$M73 -> 0 | U73: =$G73*$M73 -> 3703283.4 | V73: =$H73*$M73 -> 0 | W73: =$I73*$M73 -> 0 | X73: =$K73*$M73 -> 3703283.4 | Y73: =(S73*$O73)*(1-J73) -> 0 | Z73: =(T73*$O73)*(1-J73) -> 0 | AA73: =(U73*$O73)*(1-J73) -> 154241.75 | AB73: =(V73*$O73)*(1-J73) -> 0 | AC73: =(W73*$O73)*(1-J73) -> 0 | AD73: =SUM(Y73:AC73) -> 154241.75 | AE73: =S73*$J73 -> 0 | AF73: =T73*$J73 -> 0 | AG73: =U73*$J73 -> 555492.5 | AH73: =V73*$J73 -> 0 | AI73: =W73*$J73 -> 0 | AJ73: =SUM(AE73:AI73) -> 555492.5 | AK73: =($P73*S73)*(1-$J73) -> 0 | AL73: =($P73*T73)*(1-$J73) -> 0 | AM73: =($P73*U73)*(1-$J73) -> 495777.06 | AN73: =($P73*V73)*(1-$J73) -> 0 | AO73: =($P73*W73)*(1-$J73) -> 0 | AP73: =SUM(AK73:AO73) -> 495777.06 | AQ73: =S73*$Q73 -> 0 | AR73: =T73*$Q73 -> 0 | AS73: =U73*$Q73 -> 111098.5 | AT73: =V73*$Q73 -> 0 | AU73: =W73*$Q73 -> 0 | AV73: =SUM(AQ73:AU73) -> 111098.5 | AW73: =S73*$R73 -> 0 | AX73: =T73*$R73 -> 0 | AY73: =U73*$R73 -> 148131.33 | AZ73: =V73*$R73 -> 0 | BA73: =W73*$R73 -> 0 | BB73: =SUM(AW73:BA73) -> 148131.33 | BC73: =$Y73+$AE73+$AK73+$AQ73+AW73 -> 0 | BD73: =$Z73+$AF73+$AL73+AR73+AX73 -> 0 | BE73: =$AA73+$AG73+$AM73+AS73+AY73 -> 1464741.1 | BF73: =$AB73+$AH73+$AN73+AT73+AZ73 -> 0 | BG73: =$AC73+$AI73+$AO73+AU73+BA73 -> 0 | BH73: =SUM(BC73:BG73) -> 1464741.1 | BI73: =$Y73/$M73 -> 0 | BJ73: =$Z73/$M73 -> 0 | BK73: =$AA73/$M73 -> 154241.75 | BL73: =$AB73/$M73 -> 0 | BM73: =$AC73/$M73 -> 0 | BN73: =$AD73/$M73 -> 154241.75 | BO73: =$AE73/$M73 -> 0 | BP73: =$AF73/$M73 -> 0 | BQ73: =$AG73/$M73 -> 555492.5 | BR73: =$AH73/$M73 -> 0 | BS73: =$AI73/$M73 -> 0 | BT73: =$AJ73/$M73 -> 555492.5 | BU73: =$AK73/$M73 -> 0 | BV73: =$AL73/$M73 -> 0 | BW73: =$AM73/$M73 -> 495777.06 | BX73: =$AN73/$M73 -> 0 | BY73: =$AO73/$M73 -> 0 | BZ73: =$AP73/$M73 -> 495777.06 | CA73: =AQ73/$M73 -> 0 | CB73: =AR73/$M73 -> 0 | CC73: =AS73/$M73 -> 111098.5 | CD73: =AT73/$M73 -> 0 | CE73: =AU73/$M73 -> 0 | CF73: =AV73/$M73 -> 111098.5 | CG73: =AW73/$M73 -> 0 | CH73: =AX73/$M73 -> 0 | ... CL73: =BB73/$M73 -> 148131.33 | CM73: =$BC73/$M73 -> 0 | CN73: =$BD73/$M73 -> 0 | CO73: =$BE73/$M73 -> 1464741.1 | CP73: =$BF73/$M73 -> 0 | CQ73: =$BG73/$M73 -> 0 | CR73: =SUM(CM73:CQ73) -> 1464741.1 | CS73: =K73-CR73 -> 2238542.2 | CU73: =D73 -> ARS | CV73: =VLOOKUP(CU73,DF:DG,2,0) -> 0.0006918517 | CW73: =K73*CV73 -> 2562.1229 | CX73: =BN73*CV73 -> 106.71242 | CY73: =BT73*CV73 -> 384.31843 | CZ73: =BZ73*CV73 -> 343.0042 | DA73: =CF73*CV73 -> 76.863686 | DB73: =CL73*CV73 -> 102.48492 | DC73: =CS73*CV73 -> 1548.7392 | DD73: =VLOOKUP(A73,'Billing Report'!H:I,2,FALSE) -> ARG_BRD_BRA_SEDDEBRAHMA_VERANO_NON_ENG_BEY_2026_AMBA_COSTA_CBA
A74: 40745359 | B74: T3221498 | C74: 322149801 | D74: ARS | G74: 1293559.9 | J74: =VLOOKUP($B74,'IMS Commission List'!E:CE,79,0)/100 -> 0.15 | K74: =SUM(E74:I74) -> 1293559.9 | L74: =VLOOKUP($B74,'IMS Commission List'!E:V,18,0) -> ARS | M74: 1 | N74: =VLOOKUP($B74,'IMS Commission List'!E:T,16,0) -> MX | O74: =VLOOKUP($B74,'IMS Commission List'!E:CF,80,0) -> 0.049 | P74: =VLOOKUP($B74,'IMS Commission List'!E:CG,81,0) -> 0.1575 | Q74: =VLOOKUP($B74,'IMS Commission List'!E:CP,90,0) -> 0.03 | R74: =VLOOKUP($B74,'IMS Commission List'!E:CQ,91,0) -> 0.04 | S74: =$E74*$M74 -> 0 | T74: =$F74*$M74 -> 0 | U74: =$G74*$M74 -> 1293559.9 | V74: =$H74*$M74 -> 0 | W74: =$I74*$M74 -> 0 | X74: =$K74*$M74 -> 1293559.9 | Y74: =(S74*$O74)*(1-J74) -> 0 | Z74: =(T74*$O74)*(1-J74) -> 0 | AA74: =(U74*$O74)*(1-J74) -> 53876.772 | AB74: =(V74*$O74)*(1-J74) -> 0 | AC74: =(W74*$O74)*(1-J74) -> 0 | AD74: =SUM(Y74:AC74) -> 53876.772 | AE74: =S74*$J74 -> 0 | AF74: =T74*$J74 -> 0 | AG74: =U74*$J74 -> 194033.99 | AH74: =V74*$J74 -> 0 | AI74: =W74*$J74 -> 0 | AJ74: =SUM(AE74:AI74) -> 194033.99 | AK74: =($P74*S74)*(1-$J74) -> 0 | AL74: =($P74*T74)*(1-$J74) -> 0 | AM74: =($P74*U74)*(1-$J74) -> 173175.34 | AN74: =($P74*V74)*(1-$J74) -> 0 | AO74: =($P74*W74)*(1-$J74) -> 0 | AP74: =SUM(AK74:AO74) -> 173175.34 | AQ74: =S74*$Q74 -> 0 | AR74: =T74*$Q74 -> 0 | AS74: =U74*$Q74 -> 38806.798 | AT74: =V74*$Q74 -> 0 | AU74: =W74*$Q74 -> 0 | AV74: =SUM(AQ74:AU74) -> 38806.798 | AW74: =S74*$R74 -> 0 | AX74: =T74*$R74 -> 0 | AY74: =U74*$R74 -> 51742.398 | AZ74: =V74*$R74 -> 0 | BA74: =W74*$R74 -> 0 | BB74: =SUM(AW74:BA74) -> 51742.398 | BC74: =$Y74+$AE74+$AK74+$AQ74+AW74 -> 0 | BD74: =$Z74+$AF74+$AL74+AR74+AX74 -> 0 | BE74: =$AA74+$AG74+$AM74+AS74+AY74 -> 511635.3 | BF74: =$AB74+$AH74+$AN74+AT74+AZ74 -> 0 | BG74: =$AC74+$AI74+$AO74+AU74+BA74 -> 0 | BH74: =SUM(BC74:BG74) -> 511635.3 | BI74: =$Y74/$M74 -> 0 | BJ74: =$Z74/$M74 -> 0 | BK74: =$AA74/$M74 -> 53876.772 | BL74: =$AB74/$M74 -> 0 | BM74: =$AC74/$M74 -> 0 | BN74: =$AD74/$M74 -> 53876.772 | BO74: =$AE74/$M74 -> 0 | BP74: =$AF74/$M74 -> 0 | BQ74: =$AG74/$M74 -> 194033.99 | BR74: =$AH74/$M74 -> 0 | BS74: =$AI74/$M74 -> 0 | BT74: =$AJ74/$M74 -> 194033.99 | BU74: =$AK74/$M74 -> 0 | BV74: =$AL74/$M74 -> 0 | BW74: =$AM74/$M74 -> 173175.34 | BX74: =$AN74/$M74 -> 0 | BY74: =$AO74/$M74 -> 0 | BZ74: =$AP74/$M74 -> 173175.34 | CA74: =AQ74/$M74 -> 0 | CB74: =AR74/$M74 -> 0 | CC74: =AS74/$M74 -> 38806.798 | CD74: =AT74/$M74 -> 0 | CE74: =AU74/$M74 -> 0 | CF74: =AV74/$M74 -> 38806.798 | CG74: =AW74/$M74 -> 0 | CH74: =AX74/$M74 -> 0 | ... CL74: =BB74/$M74 -> 51742.398 | CM74: =$BC74/$M74 -> 0 | CN74: =$BD74/$M74 -> 0 | CO74: =$BE74/$M74 -> 511635.3 | CP74: =$BF74/$M74 -> 0 | CQ74: =$BG74/$M74 -> 0 | CR74: =SUM(CM74:CQ74) -> 511635.3 | CS74: =K74-CR74 -> 781924.64 | CU74: =D74 -> ARS | CV74: =VLOOKUP(CU74,DF:DG,2,0) -> 0.0006918517 | CW74: =K74*CV74 -> 894.95164 | CX74: =BN74*CV74 -> 37.274736 | CY74: =BT74*CV74 -> 134.24275 | CZ74: =BZ74*CV74 -> 119.81165 | DA74: =CF74*CV74 -> 26.848549 | DB74: =CL74*CV74 -> 35.798066 | DC74: =CS74*CV74 -> 540.97589 | DD74: =VLOOKUP(A74,'Billing Report'!H:I,2,FALSE) -> ARG_BRD_BRA_SEDDEBRAHMA_VERANO_NON_ENG_BEY_2026_STAFE_LAPAMPA_ER
A75: 40745354 | B75: T3221498 | C75: 322149801 | D75: ARS | G75: 2735581.6 | J75: =VLOOKUP($B75,'IMS Commission List'!E:CE,79,0)/100 -> 0.15 | K75: =SUM(E75:I75) -> 2735581.6 | L75: =VLOOKUP($B75,'IMS Commission List'!E:V,18,0) -> ARS | M75: 1 | N75: =VLOOKUP($B75,'IMS Commission List'!E:T,16,0) -> MX | O75: =VLOOKUP($B75,'IMS Commission List'!E:CF,80,0) -> 0.049 | P75: =VLOOKUP($B75,'IMS Commission List'!E:CG,81,0) -> 0.1575 | Q75: =VLOOKUP($B75,'IMS Commission List'!E:CP,90,0) -> 0.03 | R75: =VLOOKUP($B75,'IMS Commission List'!E:CQ,91,0) -> 0.04 | S75: =$E75*$M75 -> 0 | T75: =$F75*$M75 -> 0 | U75: =$G75*$M75 -> 2735581.6 | V75: =$H75*$M75 -> 0 | W75: =$I75*$M75 -> 0 | X75: =$K75*$M75 -> 2735581.6 | Y75: =(S75*$O75)*(1-J75) -> 0 | Z75: =(T75*$O75)*(1-J75) -> 0 | AA75: =(U75*$O75)*(1-J75) -> 113936.97 | AB75: =(V75*$O75)*(1-J75) -> 0 | AC75: =(W75*$O75)*(1-J75) -> 0 | AD75: =SUM(Y75:AC75) -> 113936.97 | AE75: =S75*$J75 -> 0 | AF75: =T75*$J75 -> 0 | AG75: =U75*$J75 -> 410337.23 | AH75: =V75*$J75 -> 0 | AI75: =W75*$J75 -> 0 | AJ75: =SUM(AE75:AI75) -> 410337.23 | AK75: =($P75*S75)*(1-$J75) -> 0 | AL75: =($P75*T75)*(1-$J75) -> 0 | AM75: =($P75*U75)*(1-$J75) -> 366225.98 | AN75: =($P75*V75)*(1-$J75) -> 0 | AO75: =($P75*W75)*(1-$J75) -> 0 | AP75: =SUM(AK75:AO75) -> 366225.98 | AQ75: =S75*$Q75 -> 0 | AR75: =T75*$Q75 -> 0 | AS75: =U75*$Q75 -> 82067.447 | AT75: =V75*$Q75 -> 0 | AU75: =W75*$Q75 -> 0 | AV75: =SUM(AQ75:AU75) -> 82067.447 | AW75: =S75*$R75 -> 0 | AX75: =T75*$R75 -> 0 | AY75: =U75*$R75 -> 109423.26 | AZ75: =V75*$R75 -> 0 | BA75: =W75*$R75 -> 0 | BB75: =SUM(AW75:BA75) -> 109423.26 | BC75: =$Y75+$AE75+$AK75+$AQ75+AW75 -> 0 | BD75: =$Z75+$AF75+$AL75+AR75+AX75 -> 0 | BE75: =$AA75+$AG75+$AM75+AS75+AY75 -> 1081990.9 | BF75: =$AB75+$AH75+$AN75+AT75+AZ75 -> 0 | BG75: =$AC75+$AI75+$AO75+AU75+BA75 -> 0 | BH75: =SUM(BC75:BG75) -> 1081990.9 | BI75: =$Y75/$M75 -> 0 | BJ75: =$Z75/$M75 -> 0 | BK75: =$AA75/$M75 -> 113936.97 | BL75: =$AB75/$M75 -> 0 | BM75: =$AC75/$M75 -> 0 | BN75: =$AD75/$M75 -> 113936.97 | BO75: =$AE75/$M75 -> 0 | BP75: =$AF75/$M75 -> 0 | BQ75: =$AG75/$M75 -> 410337.23 | BR75: =$AH75/$M75 -> 0 | BS75: =$AI75/$M75 -> 0 | BT75: =$AJ75/$M75 -> 410337.23 | BU75: =$AK75/$M75 -> 0 | BV75: =$AL75/$M75 -> 0 | BW75: =$AM75/$M75 -> 366225.98 | BX75: =$AN75/$M75 -> 0 | BY75: =$AO75/$M75 -> 0 | BZ75: =$AP75/$M75 -> 366225.98 | CA75: =AQ75/$M75 -> 0 | CB75: =AR75/$M75 -> 0 | CC75: =AS75/$M75 -> 82067.447 | CD75: =AT75/$M75 -> 0 | CE75: =AU75/$M75 -> 0 | CF75: =AV75/$M75 -> 82067.447 | CG75: =AW75/$M75 -> 0 | CH75: =AX75/$M75 -> 0 | ... CL75: =BB75/$M75 -> 109423.26 | CM75: =$BC75/$M75 -> 0 | CN75: =$BD75/$M75 -> 0 | CO75: =$BE75/$M75 -> 1081990.9 | CP75: =$BF75/$M75 -> 0 | CQ75: =$BG75/$M75 -> 0 | CR75: =SUM(CM75:CQ75) -> 1081990.9 | CS75: =K75-CR75 -> 1653590.7 | CU75: =D75 -> ARS | CV75: =VLOOKUP(CU75,DF:DG,2,0) -> 0.0006918517 | CW75: =K75*CV75 -> 1892.6168 | CX75: =BN75*CV75 -> 78.827488 | CY75: =BT75*CV75 -> 283.89251 | CZ75: =BZ75*CV75 -> 253.37407 | DA75: =CF75*CV75 -> 56.778503 | DB75: =CL75*CV75 -> 75.70467 | DC75: =CS75*CV75 -> 1144.0395 | DD75: =VLOOKUP(A75,'Billing Report'!H:I,2,FALSE) -> ARG_BRD_BRA_SEDDEBRAHMA_VERANO_NON_AWA_BEY_2026_AMBA_COSTA_CBA
A76: 40745349 | B76: T3221498 | C76: 322149801 | D76: ARS | G76: 74846.17 | J76: =VLOOKUP($B76,'IMS Commission List'!E:CE,79,0)/100 -> 0.15 | K76: =SUM(E76:I76) -> 74846.17 | L76: =VLOOKUP($B76,'IMS Commission List'!E:V,18,0) -> ARS | M76: 1 | N76: =VLOOKUP($B76,'IMS Commission List'!E:T,16,0) -> MX | O76: =VLOOKUP($B76,'IMS Commission List'!E:CF,80,0) -> 0.049 | P76: =VLOOKUP($B76,'IMS Commission List'!E:CG,81,0) -> 0.1575 | Q76: =VLOOKUP($B76,'IMS Commission List'!E:CP,90,0) -> 0.03 | R76: =VLOOKUP($B76,'IMS Commission List'!E:CQ,91,0) -> 0.04 | S76: =$E76*$M76 -> 0 | T76: =$F76*$M76 -> 0 | U76: =$G76*$M76 -> 74846.17 | V76: =$H76*$M76 -> 0 | W76: =$I76*$M76 -> 0 | X76: =$K76*$M76 -> 74846.17 | Y76: =(S76*$O76)*(1-J76) -> 0 | Z76: =(T76*$O76)*(1-J76) -> 0 | AA76: =(U76*$O76)*(1-J76) -> 3117.343 | AB76: =(V76*$O76)*(1-J76) -> 0 | AC76: =(W76*$O76)*(1-J76) -> 0 | AD76: =SUM(Y76:AC76) -> 3117.343 | AE76: =S76*$J76 -> 0 | AF76: =T76*$J76 -> 0 | AG76: =U76*$J76 -> 11226.925 | AH76: =V76*$J76 -> 0 | AI76: =W76*$J76 -> 0 | AJ76: =SUM(AE76:AI76) -> 11226.925 | AK76: =($P76*S76)*(1-$J76) -> 0 | AL76: =($P76*T76)*(1-$J76) -> 0 | AM76: =($P76*U76)*(1-$J76) -> 10020.031 | AN76: =($P76*V76)*(1-$J76) -> 0 | AO76: =($P76*W76)*(1-$J76) -> 0 | AP76: =SUM(AK76:AO76) -> 10020.031 | AQ76: =S76*$Q76 -> 0 | AR76: =T76*$Q76 -> 0 | AS76: =U76*$Q76 -> 2245.3851 | AT76: =V76*$Q76 -> 0 | AU76: =W76*$Q76 -> 0 | AV76: =SUM(AQ76:AU76) -> 2245.3851 | AW76: =S76*$R76 -> 0 | AX76: =T76*$R76 -> 0 | AY76: =U76*$R76 -> 2993.8468 | AZ76: =V76*$R76 -> 0 | BA76: =W76*$R76 -> 0 | BB76: =SUM(AW76:BA76) -> 2993.8468 | BC76: =$Y76+$AE76+$AK76+$AQ76+AW76 -> 0 | BD76: =$Z76+$AF76+$AL76+AR76+AX76 -> 0 | BE76: =$AA76+$AG76+$AM76+AS76+AY76 -> 29603.531 | BF76: =$AB76+$AH76+$AN76+AT76+AZ76 -> 0 | BG76: =$AC76+$AI76+$AO76+AU76+BA76 -> 0 | BH76: =SUM(BC76:BG76) -> 29603.531 | BI76: =$Y76/$M76 -> 0 | BJ76: =$Z76/$M76 -> 0 | BK76: =$AA76/$M76 -> 3117.343 | BL76: =$AB76/$M76 -> 0 | BM76: =$AC76/$M76 -> 0 | BN76: =$AD76/$M76 -> 3117.343 | BO76: =$AE76/$M76 -> 0 | BP76: =$AF76/$M76 -> 0 | BQ76: =$AG76/$M76 -> 11226.925 | BR76: =$AH76/$M76 -> 0 | BS76: =$AI76/$M76 -> 0 | BT76: =$AJ76/$M76 -> 11226.925 | BU76: =$AK76/$M76 -> 0 | BV76: =$AL76/$M76 -> 0 | BW76: =$AM76/$M76 -> 10020.031 | BX76: =$AN76/$M76 -> 0 | BY76: =$AO76/$M76 -> 0 | BZ76: =$AP76/$M76 -> 10020.031 | CA76: =AQ76/$M76 -> 0 | CB76: =AR76/$M76 -> 0 | CC76: =AS76/$M76 -> 2245.3851 | CD76: =AT76/$M76 -> 0 | CE76: =AU76/$M76 -> 0 | CF76: =AV76/$M76 -> 2245.3851 | CG76: =AW76/$M76 -> 0 | CH76: =AX76/$M76 -> 0 | ... CL76: =BB76/$M76 -> 2993.8468 | CM76: =$BC76/$M76 -> 0 | CN76: =$BD76/$M76 -> 0 | CO76: =$BE76/$M76 -> 29603.531 | CP76: =$BF76/$M76 -> 0 | CQ76: =$BG76/$M76 -> 0 | CR76: =SUM(CM76:CQ76) -> 29603.531 | CS76: =K76-CR76 -> 45242.639 | CU76: =D76 -> ARS | CV76: =VLOOKUP(CU76,DF:DG,2,0) -> 0.0006918517 | CW76: =K76*CV76 -> 51.78245 | CX76: =BN76*CV76 -> 2.156739 | CY76: =BT76*CV76 -> 7.7673675 | CZ76: =BZ76*CV76 -> 6.9323755 | DA76: =CF76*CV76 -> 1.5534735 | DB76: =CL76*CV76 -> 2.071298 | DC76: =CS76*CV76 -> 31.301196 | DD76: =VLOOKUP(A76,'Billing Report'!H:I,2,FALSE) -> ARG_BRD_BRA_SEDDEBRAHMA_VERANO_NON_AWA_BEY_2026_NOA
A77: 40745339 | B77: T3221498 | C77: 322149801 | D77: ARS | G77: 480031.53 | J77: =VLOOKUP($B77,'IMS Commission List'!E:CE,79,0)/100 -> 0.15 | K77: =SUM(E77:I77) -> 480031.53 | L77: =VLOOKUP($B77,'IMS Commission List'!E:V,18,0) -> ARS | M77: 1 | N77: =VLOOKUP($B77,'IMS Commission List'!E:T,16,0) -> MX | O77: =VLOOKUP($B77,'IMS Commission List'!E:CF,80,0) -> 0.049 | P77: =VLOOKUP($B77,'IMS Commission List'!E:CG,81,0) -> 0.1575 | Q77: =VLOOKUP($B77,'IMS Commission List'!E:CP,90,0) -> 0.03 | R77: =VLOOKUP($B77,'IMS Commission List'!E:CQ,91,0) -> 0.04 | S77: =$E77*$M77 -> 0 | T77: =$F77*$M77 -> 0 | U77: =$G77*$M77 -> 480031.53 | V77: =$H77*$M77 -> 0 | W77: =$I77*$M77 -> 0 | X77: =$K77*$M77 -> 480031.53 | Y77: =(S77*$O77)*(1-J77) -> 0 | Z77: =(T77*$O77)*(1-J77) -> 0 | AA77: =(U77*$O77)*(1-J77) -> 19993.313 | AB77: =(V77*$O77)*(1-J77) -> 0 | AC77: =(W77*$O77)*(1-J77) -> 0 | AD77: =SUM(Y77:AC77) -> 19993.313 | AE77: =S77*$J77 -> 0 | AF77: =T77*$J77 -> 0 | AG77: =U77*$J77 -> 72004.73 | AH77: =V77*$J77 -> 0 | AI77: =W77*$J77 -> 0 | AJ77: =SUM(AE77:AI77) -> 72004.73 | AK77: =($P77*S77)*(1-$J77) -> 0 | AL77: =($P77*T77)*(1-$J77) -> 0 | AM77: =($P77*U77)*(1-$J77) -> 64264.221 | AN77: =($P77*V77)*(1-$J77) -> 0 | AO77: =($P77*W77)*(1-$J77) -> 0 | AP77: =SUM(AK77:AO77) -> 64264.221 | AQ77: =S77*$Q77 -> 0 | AR77: =T77*$Q77 -> 0 | AS77: =U77*$Q77 -> 14400.946 | AT77: =V77*$Q77 -> 0 | AU77: =W77*$Q77 -> 0 | AV77: =SUM(AQ77:AU77) -> 14400.946 | AW77: =S77*$R77 -> 0 | AX77: =T77*$R77 -> 0 | AY77: =U77*$R77 -> 19201.261 | AZ77: =V77*$R77 -> 0 | BA77: =W77*$R77 -> 0 | BB77: =SUM(AW77:BA77) -> 19201.261 | BC77: =$Y77+$AE77+$AK77+$AQ77+AW77 -> 0 | BD77: =$Z77+$AF77+$AL77+AR77+AX77 -> 0 | BE77: =$AA77+$AG77+$AM77+AS77+AY77 -> 189864.47 | BF77: =$AB77+$AH77+$AN77+AT77+AZ77 -> 0 | BG77: =$AC77+$AI77+$AO77+AU77+BA77 -> 0 | BH77: =SUM(BC77:BG77) -> 189864.47 | BI77: =$Y77/$M77 -> 0 | BJ77: =$Z77/$M77 -> 0 | BK77: =$AA77/$M77 -> 19993.313 | BL77: =$AB77/$M77 -> 0 | BM77: =$AC77/$M77 -> 0 | BN77: =$AD77/$M77 -> 19993.313 | BO77: =$AE77/$M77 -> 0 | BP77: =$AF77/$M77 -> 0 | BQ77: =$AG77/$M77 -> 72004.73 | BR77: =$AH77/$M77 -> 0 | BS77: =$AI77/$M77 -> 0 | BT77: =$AJ77/$M77 -> 72004.73 | BU77: =$AK77/$M77 -> 0 | BV77: =$AL77/$M77 -> 0 | BW77: =$AM77/$M77 -> 64264.221 | BX77: =$AN77/$M77 -> 0 | BY77: =$AO77/$M77 -> 0 | BZ77: =$AP77/$M77 -> 64264.221 | CA77: =AQ77/$M77 -> 0 | CB77: =AR77/$M77 -> 0 | CC77: =AS77/$M77 -> 14400.946 | CD77: =AT77/$M77 -> 0 | CE77: =AU77/$M77 -> 0 | CF77: =AV77/$M77 -> 14400.946 | CG77: =AW77/$M77 -> 0 | CH77: =AX77/$M77 -> 0 | ... CL77: =BB77/$M77 -> 19201.261 | CM77: =$BC77/$M77 -> 0 | CN77: =$BD77/$M77 -> 0 | CO77: =$BE77/$M77 -> 189864.47 | CP77: =$BF77/$M77 -> 0 | CQ77: =$BG77/$M77 -> 0 | CR77: =SUM(CM77:CQ77) -> 189864.47 | CS77: =K77-CR77 -> 290167.06 | CU77: =D77 -> ARS | CV77: =VLOOKUP(CU77,DF:DG,2,0) -> 0.0006918517 | CW77: =K77*CV77 -> 332.11063 | CX77: =BN77*CV77 -> 13.832408 | CY77: =BT77*CV77 -> 49.816595 | CZ77: =BZ77*CV77 -> 44.461311 | DA77: =CF77*CV77 -> 9.9633189 | DB77: =CL77*CV77 -> 13.284425 | DC77: =CS77*CV77 -> 200.75257 | DD77: =VLOOKUP(A77,'Billing Report'!H:I,2,FALSE) -> ARG_BRD_BRA_SEDDEBRAHMA_VERANO_NON_AWA_BEY_2026_STAFE_LAPAMPA_ER
A78: 40745273 | B78: T3221498 | C78: 322149801 | D78: ARS | G78: 815704.5 | J78: =VLOOKUP($B78,'IMS Commission List'!E:CE,79,0)/100 -> 0.15 | K78: =SUM(E78:I78) -> 815704.5 | L78: =VLOOKUP($B78,'IMS Commission List'!E:V,18,0) -> ARS | M78: 1 | N78: =VLOOKUP($B78,'IMS Commission List'!E:T,16,0) -> MX | O78: =VLOOKUP($B78,'IMS Commission List'!E:CF,80,0) -> 0.049 | P78: =VLOOKUP($B78,'IMS Commission List'!E:CG,81,0) -> 0.1575 | Q78: =VLOOKUP($B78,'IMS Commission List'!E:CP,90,0) -> 0.03 | R78: =VLOOKUP($B78,'IMS Commission List'!E:CQ,91,0) -> 0.04 | S78: =$E78*$M78 -> 0 | T78: =$F78*$M78 -> 0 | U78: =$G78*$M78 -> 815704.5 | V78: =$H78*$M78 -> 0 | W78: =$I78*$M78 -> 0 | X78: =$K78*$M78 -> 815704.5 | Y78: =(S78*$O78)*(1-J78) -> 0 | Z78: =(T78*$O78)*(1-J78) -> 0 | AA78: =(U78*$O78)*(1-J78) -> 33974.092 | AB78: =(V78*$O78)*(1-J78) -> 0 | AC78: =(W78*$O78)*(1-J78) -> 0 | AD78: =SUM(Y78:AC78) -> 33974.092 | AE78: =S78*$J78 -> 0 | AF78: =T78*$J78 -> 0 | AG78: =U78*$J78 -> 122355.67 | AH78: =V78*$J78 -> 0 | AI78: =W78*$J78 -> 0 | AJ78: =SUM(AE78:AI78) -> 122355.67 | AK78: =($P78*S78)*(1-$J78) -> 0 | AL78: =($P78*T78)*(1-$J78) -> 0 | AM78: =($P78*U78)*(1-$J78) -> 109202.44 | AN78: =($P78*V78)*(1-$J78) -> 0 | AO78: =($P78*W78)*(1-$J78) -> 0 | AP78: =SUM(AK78:AO78) -> 109202.44 | AQ78: =S78*$Q78 -> 0 | AR78: =T78*$Q78 -> 0 | AS78: =U78*$Q78 -> 24471.135 | AT78: =V78*$Q78 -> 0 | AU78: =W78*$Q78 -> 0 | AV78: =SUM(AQ78:AU78) -> 24471.135 | AW78: =S78*$R78 -> 0 | AX78: =T78*$R78 -> 0 | AY78: =U78*$R78 -> 32628.18 | AZ78: =V78*$R78 -> 0 | BA78: =W78*$R78 -> 0 | BB78: =SUM(AW78:BA78) -> 32628.18 | BC78: =$Y78+$AE78+$AK78+$AQ78+AW78 -> 0 | BD78: =$Z78+$AF78+$AL78+AR78+AX78 -> 0 | BE78: =$AA78+$AG78+$AM78+AS78+AY78 -> 322631.52 | BF78: =$AB78+$AH78+$AN78+AT78+AZ78 -> 0 | BG78: =$AC78+$AI78+$AO78+AU78+BA78 -> 0 | BH78: =SUM(BC78:BG78) -> 322631.52 | BI78: =$Y78/$M78 -> 0 | BJ78: =$Z78/$M78 -> 0 | BK78: =$AA78/$M78 -> 33974.092 | BL78: =$AB78/$M78 -> 0 | BM78: =$AC78/$M78 -> 0 | BN78: =$AD78/$M78 -> 33974.092 | BO78: =$AE78/$M78 -> 0 | BP78: =$AF78/$M78 -> 0 | BQ78: =$AG78/$M78 -> 122355.67 | BR78: =$AH78/$M78 -> 0 | BS78: =$AI78/$M78 -> 0 | BT78: =$AJ78/$M78 -> 122355.67 | BU78: =$AK78/$M78 -> 0 | BV78: =$AL78/$M78 -> 0 | BW78: =$AM78/$M78 -> 109202.44 | BX78: =$AN78/$M78 -> 0 | BY78: =$AO78/$M78 -> 0 | BZ78: =$AP78/$M78 -> 109202.44 | CA78: =AQ78/$M78 -> 0 | CB78: =AR78/$M78 -> 0 | CC78: =AS78/$M78 -> 24471.135 | CD78: =AT78/$M78 -> 0 | CE78: =AU78/$M78 -> 0 | CF78: =AV78/$M78 -> 24471.135 | CG78: =AW78/$M78 -> 0 | CH78: =AX78/$M78 -> 0 | ... CL78: =BB78/$M78 -> 32628.18 | CM78: =$BC78/$M78 -> 0 | CN78: =$BD78/$M78 -> 0 | CO78: =$BE78/$M78 -> 322631.52 | CP78: =$BF78/$M78 -> 0 | CQ78: =$BG78/$M78 -> 0 | CR78: =SUM(CM78:CQ78) -> 322631.52 | CS78: =K78-CR78 -> 493072.98 | CU78: =D78 -> ARS | CV78: =VLOOKUP(CU78,DF:DG,2,0) -> 0.0006918517 | CW78: =K78*CV78 -> 564.34655 | CX78: =BN78*CV78 -> 23.505034 | CY78: =BT78*CV78 -> 84.651982 | CZ78: =BZ78*CV78 -> 75.551894 | DA78: =CF78*CV78 -> 16.930396 | DB78: =CL78*CV78 -> 22.573862 | DC78: =CS78*CV78 -> 341.13338 | DD78: =VLOOKUP(A78,'Billing Report'!H:I,2,FALSE) -> ARG_BRD_BRA_SEDDEBRAHMA_VERANO_NON_AWA_BEY_2026_LDA
A79: 40776297 | B79: T3221499 | C79: 322149901 | D79: ARS | G79: 158098.96 | J79: =VLOOKUP($B79,'IMS Commission List'!E:CE,79,0)/100 -> 0.15 | K79: =SUM(E79:I79) -> 158098.96 | L79: =VLOOKUP($B79,'IMS Commission List'!E:V,18,0) -> ARS | M79: 1 | N79: =VLOOKUP($B79,'IMS Commission List'!E:T,16,0) -> MX | O79: =VLOOKUP($B79,'IMS Commission List'!E:CF,80,0) -> 0.049 | P79: =VLOOKUP($B79,'IMS Commission List'!E:CG,81,0) -> 0.1575 | Q79: =VLOOKUP($B79,'IMS Commission List'!E:CP,90,0) -> 0.03 | R79: =VLOOKUP($B79,'IMS Commission List'!E:CQ,91,0) -> 0.04 | S79: =$E79*$M79 -> 0 | T79: =$F79*$M79 -> 0 | U79: =$G79*$M79 -> 158098.96 | V79: =$H79*$M79 -> 0 | W79: =$I79*$M79 -> 0 | X79: =$K79*$M79 -> 158098.96 | Y79: =(S79*$O79)*(1-J79) -> 0 | Z79: =(T79*$O79)*(1-J79) -> 0 | AA79: =(U79*$O79)*(1-J79) -> 6584.8217 | AB79: =(V79*$O79)*(1-J79) -> 0 | AC79: =(W79*$O79)*(1-J79) -> 0 | AD79: =SUM(Y79:AC79) -> 6584.8217 | AE79: =S79*$J79 -> 0 | AF79: =T79*$J79 -> 0 | AG79: =U79*$J79 -> 23714.844 | AH79: =V79*$J79 -> 0 | AI79: =W79*$J79 -> 0 | AJ79: =SUM(AE79:AI79) -> 23714.844 | AK79: =($P79*S79)*(1-$J79) -> 0 | AL79: =($P79*T79)*(1-$J79) -> 0 | AM79: =($P79*U79)*(1-$J79) -> 21165.498 | AN79: =($P79*V79)*(1-$J79) -> 0 | AO79: =($P79*W79)*(1-$J79) -> 0 | AP79: =SUM(AK79:AO79) -> 21165.498 | AQ79: =S79*$Q79 -> 0 | AR79: =T79*$Q79 -> 0 | AS79: =U79*$Q79 -> 4742.9688 | AT79: =V79*$Q79 -> 0 | AU79: =W79*$Q79 -> 0 | AV79: =SUM(AQ79:AU79) -> 4742.9688 | AW79: =S79*$R79 -> 0 | AX79: =T79*$R79 -> 0 | AY79: =U79*$R79 -> 6323.9584 | AZ79: =V79*$R79 -> 0 | BA79: =W79*$R79 -> 0 | BB79: =SUM(AW79:BA79) -> 6323.9584 | BC79: =$Y79+$AE79+$AK79+$AQ79+AW79 -> 0 | BD79: =$Z79+$AF79+$AL79+AR79+AX79 -> 0 | BE79: =$AA79+$AG79+$AM79+AS79+AY79 -> 62532.091 | BF79: =$AB79+$AH79+$AN79+AT79+AZ79 -> 0 | BG79: =$AC79+$AI79+$AO79+AU79+BA79 -> 0 | BH79: =SUM(BC79:BG79) -> 62532.091 | BI79: =$Y79/$M79 -> 0 | BJ79: =$Z79/$M79 -> 0 | BK79: =$AA79/$M79 -> 6584.8217 | BL79: =$AB79/$M79 -> 0 | BM79: =$AC79/$M79 -> 0 | BN79: =$AD79/$M79 -> 6584.8217 | BO79: =$AE79/$M79 -> 0 | BP79: =$AF79/$M79 -> 0 | BQ79: =$AG79/$M79 -> 23714.844 | BR79: =$AH79/$M79 -> 0 | BS79: =$AI79/$M79 -> 0 | BT79: =$AJ79/$M79 -> 23714.844 | BU79: =$AK79/$M79 -> 0 | BV79: =$AL79/$M79 -> 0 | BW79: =$AM79/$M79 -> 21165.498 | BX79: =$AN79/$M79 -> 0 | BY79: =$AO79/$M79 -> 0 | BZ79: =$AP79/$M79 -> 21165.498 | CA79: =AQ79/$M79 -> 0 | CB79: =AR79/$M79 -> 0 | CC79: =AS79/$M79 -> 4742.9688 | CD79: =AT79/$M79 -> 0 | CE79: =AU79/$M79 -> 0 | CF79: =AV79/$M79 -> 4742.9688 | CG79: =AW79/$M79 -> 0 | CH79: =AX79/$M79 -> 0 | ... CL79: =BB79/$M79 -> 6323.9584 | CM79: =$BC79/$M79 -> 0 | CN79: =$BD79/$M79 -> 0 | CO79: =$BE79/$M79 -> 62532.091 | CP79: =$BF79/$M79 -> 0 | CQ79: =$BG79/$M79 -> 0 | CR79: =SUM(CM79:CQ79) -> 62532.091 | CS79: =K79-CR79 -> 95566.869 | CU79: =D79 -> ARS | CV79: =VLOOKUP(CU79,DF:DG,2,0) -> 0.0006918517 | CW79: =K79*CV79 -> 109.38103 | CX79: =BN79*CV79 -> 4.5557201 | CY79: =BT79*CV79 -> 16.407155 | CZ79: =BZ79*CV79 -> 14.643386 | DA79: =CF79*CV79 -> 3.281431 | DB79: =CL79*CV79 -> 4.3752414 | DC79: =CS79*CV79 -> 66.118101 | DD79: =VLOOKUP(A79,'Billing Report'!H:I,2,FALSE) -> ARG_BRD_BRA_SEDDEBRAHMA_CARNAVAL_NON_RCH_BEY_2026_LDA
A80: 40776264 | B80: T3221499 | C80: 322149901 | D80: ARS | G80: 221426.17 | J80: =VLOOKUP($B80,'IMS Commission List'!E:CE,79,0)/100 -> 0.15 | K80: =SUM(E80:I80) -> 221426.17 | L80: =VLOOKUP($B80,'IMS Commission List'!E:V,18,0) -> ARS | M80: 1 | N80: =VLOOKUP($B80,'IMS Commission List'!E:T,16,0) -> MX | O80: =VLOOKUP($B80,'IMS Commission List'!E:CF,80,0) -> 0.049 | P80: =VLOOKUP($B80,'IMS Commission List'!E:CG,81,0) -> 0.1575 | Q80: =VLOOKUP($B80,'IMS Commission List'!E:CP,90,0) -> 0.03 | R80: =VLOOKUP($B80,'IMS Commission List'!E:CQ,91,0) -> 0.04 | S80: =$E80*$M80 -> 0 | T80: =$F80*$M80 -> 0 | U80: =$G80*$M80 -> 221426.17 | V80: =$H80*$M80 -> 0 | W80: =$I80*$M80 -> 0 | X80: =$K80*$M80 -> 221426.17 | Y80: =(S80*$O80)*(1-J80) -> 0 | Z80: =(T80*$O80)*(1-J80) -> 0 | AA80: =(U80*$O80)*(1-J80) -> 9222.4 | AB80: =(V80*$O80)*(1-J80) -> 0 | AC80: =(W80*$O80)*(1-J80) -> 0 | AD80: =SUM(Y80:AC80) -> 9222.4 | AE80: =S80*$J80 -> 0 | AF80: =T80*$J80 -> 0 | AG80: =U80*$J80 -> 33213.925 | AH80: =V80*$J80 -> 0 | AI80: =W80*$J80 -> 0 | AJ80: =SUM(AE80:AI80) -> 33213.925 | AK80: =($P80*S80)*(1-$J80) -> 0 | AL80: =($P80*T80)*(1-$J80) -> 0 | AM80: =($P80*U80)*(1-$J80) -> 29643.429 | AN80: =($P80*V80)*(1-$J80) -> 0 | AO80: =($P80*W80)*(1-$J80) -> 0 | AP80: =SUM(AK80:AO80) -> 29643.429 | AQ80: =S80*$Q80 -> 0 | AR80: =T80*$Q80 -> 0 | AS80: =U80*$Q80 -> 6642.7851 | AT80: =V80*$Q80 -> 0 | AU80: =W80*$Q80 -> 0 | AV80: =SUM(AQ80:AU80) -> 6642.7851 | AW80: =S80*$R80 -> 0 | AX80: =T80*$R80 -> 0 | AY80: =U80*$R80 -> 8857.0468 | AZ80: =V80*$R80 -> 0 | BA80: =W80*$R80 -> 0 | BB80: =SUM(AW80:BA80) -> 8857.0468 | BC80: =$Y80+$AE80+$AK80+$AQ80+AW80 -> 0 | BD80: =$Z80+$AF80+$AL80+AR80+AX80 -> 0 | BE80: =$AA80+$AG80+$AM80+AS80+AY80 -> 87579.586 | BF80: =$AB80+$AH80+$AN80+AT80+AZ80 -> 0 | BG80: =$AC80+$AI80+$AO80+AU80+BA80 -> 0 | BH80: =SUM(BC80:BG80) -> 87579.586 | BI80: =$Y80/$M80 -> 0 | BJ80: =$Z80/$M80 -> 0 | BK80: =$AA80/$M80 -> 9222.4 | BL80: =$AB80/$M80 -> 0 | BM80: =$AC80/$M80 -> 0 | BN80: =$AD80/$M80 -> 9222.4 | BO80: =$AE80/$M80 -> 0 | BP80: =$AF80/$M80 -> 0 | BQ80: =$AG80/$M80 -> 33213.925 | BR80: =$AH80/$M80 -> 0 | BS80: =$AI80/$M80 -> 0 | BT80: =$AJ80/$M80 -> 33213.925 | BU80: =$AK80/$M80 -> 0 | BV80: =$AL80/$M80 -> 0 | BW80: =$AM80/$M80 -> 29643.429 | BX80: =$AN80/$M80 -> 0 | BY80: =$AO80/$M80 -> 0 | BZ80: =$AP80/$M80 -> 29643.429 | CA80: =AQ80/$M80 -> 0 | CB80: =AR80/$M80 -> 0 | CC80: =AS80/$M80 -> 6642.7851 | CD80: =AT80/$M80 -> 0 | CE80: =AU80/$M80 -> 0 | CF80: =AV80/$M80 -> 6642.7851 | CG80: =AW80/$M80 -> 0 | CH80: =AX80/$M80 -> 0 | ... CL80: =BB80/$M80 -> 8857.0468 | CM80: =$BC80/$M80 -> 0 | CN80: =$BD80/$M80 -> 0 | CO80: =$BE80/$M80 -> 87579.586 | CP80: =$BF80/$M80 -> 0 | CQ80: =$BG80/$M80 -> 0 | CR80: =SUM(CM80:CQ80) -> 87579.586 | CS80: =K80-CR80 -> 133846.58 | CU80: =D80 -> ARS | CV80: =VLOOKUP(CU80,DF:DG,2,0) -> 0.0006918517 | CW80: =K80*CV80 -> 153.19407 | CX80: =BN80*CV80 -> 6.3805331 | CY80: =BT80*CV80 -> 22.979111 | CZ80: =BZ80*CV80 -> 20.508856 | DA80: =CF80*CV80 -> 4.5958222 | DB80: =CL80*CV80 -> 6.1277629 | DC80: =CS80*CV80 -> 92.601987 | DD80: =VLOOKUP(A80,'Billing Report'!H:I,2,FALSE) -> ARG_BRD_BRA_SEDDEBRAHMA_CARNAVAL_NON_RCH_BEY_2026_BARRIALES
A81: 40776253 | B81: T3221499 | C81: 322149901 | D81: ARS | G81: 213624.01 | J81: =VLOOKUP($B81,'IMS Commission List'!E:CE,79,0)/100 -> 0.15 | K81: =SUM(E81:I81) -> 213624.01 | L81: =VLOOKUP($B81,'IMS Commission List'!E:V,18,0) -> ARS | M81: 1 | N81: =VLOOKUP($B81,'IMS Commission List'!E:T,16,0) -> MX | O81: =VLOOKUP($B81,'IMS Commission List'!E:CF,80,0) -> 0.049 | P81: =VLOOKUP($B81,'IMS Commission List'!E:CG,81,0) -> 0.1575 | Q81: =VLOOKUP($B81,'IMS Commission List'!E:CP,90,0) -> 0.03 | R81: =VLOOKUP($B81,'IMS Commission List'!E:CQ,91,0) -> 0.04 | S81: =$E81*$M81 -> 0 | T81: =$F81*$M81 -> 0 | U81: =$G81*$M81 -> 213624.01 | V81: =$H81*$M81 -> 0 | W81: =$I81*$M81 -> 0 | X81: =$K81*$M81 -> 213624.01 | Y81: =(S81*$O81)*(1-J81) -> 0 | Z81: =(T81*$O81)*(1-J81) -> 0 | AA81: =(U81*$O81)*(1-J81) -> 8897.44 | AB81: =(V81*$O81)*(1-J81) -> 0 | AC81: =(W81*$O81)*(1-J81) -> 0 | AD81: =SUM(Y81:AC81) -> 8897.44 | AE81: =S81*$J81 -> 0 | AF81: =T81*$J81 -> 0 | AG81: =U81*$J81 -> 32043.602 | AH81: =V81*$J81 -> 0 | AI81: =W81*$J81 -> 0 | AJ81: =SUM(AE81:AI81) -> 32043.602 | AK81: =($P81*S81)*(1-$J81) -> 0 | AL81: =($P81*T81)*(1-$J81) -> 0 | AM81: =($P81*U81)*(1-$J81) -> 28598.914 | AN81: =($P81*V81)*(1-$J81) -> 0 | AO81: =($P81*W81)*(1-$J81) -> 0 | AP81: =SUM(AK81:AO81) -> 28598.914 | AQ81: =S81*$Q81 -> 0 | AR81: =T81*$Q81 -> 0 | AS81: =U81*$Q81 -> 6408.7203 | AT81: =V81*$Q81 -> 0 | AU81: =W81*$Q81 -> 0 | AV81: =SUM(AQ81:AU81) -> 6408.7203 | AW81: =S81*$R81 -> 0 | AX81: =T81*$R81 -> 0 | AY81: =U81*$R81 -> 8544.9604 | AZ81: =V81*$R81 -> 0 | BA81: =W81*$R81 -> 0 | BB81: =SUM(AW81:BA81) -> 8544.9604 | BC81: =$Y81+$AE81+$AK81+$AQ81+AW81 -> 0 | BD81: =$Z81+$AF81+$AL81+AR81+AX81 -> 0 | BE81: =$AA81+$AG81+$AM81+AS81+AY81 -> 84493.637 | BF81: =$AB81+$AH81+$AN81+AT81+AZ81 -> 0 | BG81: =$AC81+$AI81+$AO81+AU81+BA81 -> 0 | BH81: =SUM(BC81:BG81) -> 84493.637 | BI81: =$Y81/$M81 -> 0 | BJ81: =$Z81/$M81 -> 0 | BK81: =$AA81/$M81 -> 8897.44 | BL81: =$AB81/$M81 -> 0 | BM81: =$AC81/$M81 -> 0 | BN81: =$AD81/$M81 -> 8897.44 | BO81: =$AE81/$M81 -> 0 | BP81: =$AF81/$M81 -> 0 | BQ81: =$AG81/$M81 -> 32043.602 | BR81: =$AH81/$M81 -> 0 | BS81: =$AI81/$M81 -> 0 | BT81: =$AJ81/$M81 -> 32043.602 | BU81: =$AK81/$M81 -> 0 | BV81: =$AL81/$M81 -> 0 | BW81: =$AM81/$M81 -> 28598.914 | BX81: =$AN81/$M81 -> 0 | BY81: =$AO81/$M81 -> 0 | BZ81: =$AP81/$M81 -> 28598.914 | CA81: =AQ81/$M81 -> 0 | CB81: =AR81/$M81 -> 0 | CC81: =AS81/$M81 -> 6408.7203 | CD81: =AT81/$M81 -> 0 | CE81: =AU81/$M81 -> 0 | CF81: =AV81/$M81 -> 6408.7203 | CG81: =AW81/$M81 -> 0 | CH81: =AX81/$M81 -> 0 | ... CL81: =BB81/$M81 -> 8544.9604 | CM81: =$BC81/$M81 -> 0 | CN81: =$BD81/$M81 -> 0 | CO81: =$BE81/$M81 -> 84493.637 | CP81: =$BF81/$M81 -> 0 | CQ81: =$BG81/$M81 -> 0 | CR81: =SUM(CM81:CQ81) -> 84493.637 | CS81: =K81-CR81 -> 129130.37 | CU81: =D81 -> ARS | CV81: =VLOOKUP(CU81,DF:DG,2,0) -> 0.0006918517 | CW81: =K81*CV81 -> 147.79613 | CX81: =BN81*CV81 -> 6.155709 | CY81: =BT81*CV81 -> 22.16942 | CZ81: =BZ81*CV81 -> 19.786208 | DA81: =CF81*CV81 -> 4.433884 | DB81: =CL81*CV81 -> 5.9118454 | DC81: =CS81*CV81 -> 89.339068 | DD81: =VLOOKUP(A81,'Billing Report'!H:I,2,FALSE) -> ARG_BRD_BRA_SEDDEBRAHMA_CARNAVAL_NON_RCH_BEY_2026_GUALEGUAYCHU
A82: 40776231 | B82: T3221499 | C82: 322149901 | D82: ARS | G82: 301607.77 | J82: =VLOOKUP($B82,'IMS Commission List'!E:CE,79,0)/100 -> 0.15 | K82: =SUM(E82:I82) -> 301607.77 | L82: =VLOOKUP($B82,'IMS Commission List'!E:V,18,0) -> ARS | M82: 1 | N82: =VLOOKUP($B82,'IMS Commission List'!E:T,16,0) -> MX | O82: =VLOOKUP($B82,'IMS Commission List'!E:CF,80,0) -> 0.049 | P82: =VLOOKUP($B82,'IMS Commission List'!E:CG,81,0) -> 0.1575 | Q82: =VLOOKUP($B82,'IMS Commission List'!E:CP,90,0) -> 0.03 | R82: =VLOOKUP($B82,'IMS Commission List'!E:CQ,91,0) -> 0.04 | S82: =$E82*$M82 -> 0 | T82: =$F82*$M82 -> 0 | U82: =$G82*$M82 -> 301607.77 | V82: =$H82*$M82 -> 0 | W82: =$I82*$M82 -> 0 | X82: =$K82*$M82 -> 301607.77 | Y82: =(S82*$O82)*(1-J82) -> 0 | Z82: =(T82*$O82)*(1-J82) -> 0 | AA82: =(U82*$O82)*(1-J82) -> 12561.964 | AB82: =(V82*$O82)*(1-J82) -> 0 | AC82: =(W82*$O82)*(1-J82) -> 0 | AD82: =SUM(Y82:AC82) -> 12561.964 | AE82: =S82*$J82 -> 0 | AF82: =T82*$J82 -> 0 | AG82: =U82*$J82 -> 45241.166 | AH82: =V82*$J82 -> 0 | AI82: =W82*$J82 -> 0 | AJ82: =SUM(AE82:AI82) -> 45241.166 | AK82: =($P82*S82)*(1-$J82) -> 0 | AL82: =($P82*T82)*(1-$J82) -> 0 | AM82: =($P82*U82)*(1-$J82) -> 40377.74 | AN82: =($P82*V82)*(1-$J82) -> 0 | AO82: =($P82*W82)*(1-$J82) -> 0 | AP82: =SUM(AK82:AO82) -> 40377.74 | AQ82: =S82*$Q82 -> 0 | AR82: =T82*$Q82 -> 0 | AS82: =U82*$Q82 -> 9048.2331 | AT82: =V82*$Q82 -> 0 | AU82: =W82*$Q82 -> 0 | AV82: =SUM(AQ82:AU82) -> 9048.2331 | AW82: =S82*$R82 -> 0 | AX82: =T82*$R82 -> 0 | AY82: =U82*$R82 -> 12064.311 | AZ82: =V82*$R82 -> 0 | BA82: =W82*$R82 -> 0 | BB82: =SUM(AW82:BA82) -> 12064.311 | BC82: =$Y82+$AE82+$AK82+$AQ82+AW82 -> 0 | BD82: =$Z82+$AF82+$AL82+AR82+AX82 -> 0 | BE82: =$AA82+$AG82+$AM82+AS82+AY82 -> 119293.41 | BF82: =$AB82+$AH82+$AN82+AT82+AZ82 -> 0 | BG82: =$AC82+$AI82+$AO82+AU82+BA82 -> 0 | BH82: =SUM(BC82:BG82) -> 119293.41 | BI82: =$Y82/$M82 -> 0 | BJ82: =$Z82/$M82 -> 0 | BK82: =$AA82/$M82 -> 12561.964 | BL82: =$AB82/$M82 -> 0 | BM82: =$AC82/$M82 -> 0 | BN82: =$AD82/$M82 -> 12561.964 | BO82: =$AE82/$M82 -> 0 | BP82: =$AF82/$M82 -> 0 | BQ82: =$AG82/$M82 -> 45241.166 | BR82: =$AH82/$M82 -> 0 | BS82: =$AI82/$M82 -> 0 | BT82: =$AJ82/$M82 -> 45241.166 | BU82: =$AK82/$M82 -> 0 | BV82: =$AL82/$M82 -> 0 | BW82: =$AM82/$M82 -> 40377.74 | BX82: =$AN82/$M82 -> 0 | BY82: =$AO82/$M82 -> 0 | BZ82: =$AP82/$M82 -> 40377.74 | CA82: =AQ82/$M82 -> 0 | CB82: =AR82/$M82 -> 0 | CC82: =AS82/$M82 -> 9048.2331 | CD82: =AT82/$M82 -> 0 | CE82: =AU82/$M82 -> 0 | CF82: =AV82/$M82 -> 9048.2331 | CG82: =AW82/$M82 -> 0 | CH82: =AX82/$M82 -> 0 | ... CL82: =BB82/$M82 -> 12064.311 | CM82: =$BC82/$M82 -> 0 | CN82: =$BD82/$M82 -> 0 | CO82: =$BE82/$M82 -> 119293.41 | CP82: =$BF82/$M82 -> 0 | CQ82: =$BG82/$M82 -> 0 | CR82: =SUM(CM82:CQ82) -> 119293.41 | CS82: =K82-CR82 -> 182314.36 | CU82: =D82 -> ARS | CV82: =VLOOKUP(CU82,DF:DG,2,0) -> 0.0006918517 | CW82: =K82*CV82 -> 208.66785 | CX82: =BN82*CV82 -> 8.6910159 | CY82: =BT82*CV82 -> 31.300177 | CZ82: =BZ82*CV82 -> 27.935408 | DA82: =CF82*CV82 -> 6.2600355 | DB82: =CL82*CV82 -> 8.3467139 | DC82: =CS82*CV82 -> 126.1345 | DD82: =VLOOKUP(A82,'Billing Report'!H:I,2,FALSE) -> ARG_BRD_BRA_SEDDEBRAHMA_CARNAVAL_NON_RCH_BEY_2026_CORRIENTES
A83: 40881967 | B83: T3221580 | C83: 322158001 | D83: ARS | G83: 1185638.2 | J83: =VLOOKUP($B83,'IMS Commission List'!E:CE,79,0)/100 -> 0.08 | K83: =SUM(E83:I83) -> 1185638.2 | L83: =VLOOKUP($B83,'IMS Commission List'!E:V,18,0) -> ARS | M83: 1 | N83: =VLOOKUP($B83,'IMS Commission List'!E:T,16,0) -> MX | O83: =VLOOKUP($B83,'IMS Commission List'!E:CF,80,0) -> 0.049 | P83: =VLOOKUP($B83,'IMS Commission List'!E:CG,81,0) -> 0.1575 | Q83: =VLOOKUP($B83,'IMS Commission List'!E:CP,90,0) -> 0.03 | R83: =VLOOKUP($B83,'IMS Commission List'!E:CQ,91,0) -> 0.04 | S83: =$E83*$M83 -> 0 | T83: =$F83*$M83 -> 0 | U83: =$G83*$M83 -> 1185638.2 | V83: =$H83*$M83 -> 0 | W83: =$I83*$M83 -> 0 | X83: =$K83*$M83 -> 1185638.2 | Y83: =(S83*$O83)*(1-J83) -> 0 | Z83: =(T83*$O83)*(1-J83) -> 0 | AA83: =(U83*$O83)*(1-J83) -> 53448.569 | AB83: =(V83*$O83)*(1-J83) -> 0 | AC83: =(W83*$O83)*(1-J83) -> 0 | AD83: =SUM(Y83:AC83) -> 53448.569 | AE83: =S83*$J83 -> 0 | AF83: =T83*$J83 -> 0 | AG83: =U83*$J83 -> 94851.054 | AH83: =V83*$J83 -> 0 | AI83: =W83*$J83 -> 0 | AJ83: =SUM(AE83:AI83) -> 94851.054 | AK83: =($P83*S83)*(1-$J83) -> 0 | AL83: =($P83*T83)*(1-$J83) -> 0 | AM83: =($P83*U83)*(1-$J83) -> 171798.97 | AN83: =($P83*V83)*(1-$J83) -> 0 | AO83: =($P83*W83)*(1-$J83) -> 0 | AP83: =SUM(AK83:AO83) -> 171798.97 | AQ83: =S83*$Q83 -> 0 | AR83: =T83*$Q83 -> 0 | AS83: =U83*$Q83 -> 35569.145 | AT83: =V83*$Q83 -> 0 | AU83: =W83*$Q83 -> 0 | AV83: =SUM(AQ83:AU83) -> 35569.145 | AW83: =S83*$R83 -> 0 | AX83: =T83*$R83 -> 0 | AY83: =U83*$R83 -> 47425.527 | AZ83: =V83*$R83 -> 0 | BA83: =W83*$R83 -> 0 | BB83: =SUM(AW83:BA83) -> 47425.527 | BC83: =$Y83+$AE83+$AK83+$AQ83+AW83 -> 0 | BD83: =$Z83+$AF83+$AL83+AR83+AX83 -> 0 | BE83: =$AA83+$AG83+$AM83+AS83+AY83 -> 403093.27 | BF83: =$AB83+$AH83+$AN83+AT83+AZ83 -> 0 | BG83: =$AC83+$AI83+$AO83+AU83+BA83 -> 0 | BH83: =SUM(BC83:BG83) -> 403093.27 | BI83: =$Y83/$M83 -> 0 | BJ83: =$Z83/$M83 -> 0 | BK83: =$AA83/$M83 -> 53448.569 | BL83: =$AB83/$M83 -> 0 | BM83: =$AC83/$M83 -> 0 | BN83: =$AD83/$M83 -> 53448.569 | BO83: =$AE83/$M83 -> 0 | BP83: =$AF83/$M83 -> 0 | BQ83: =$AG83/$M83 -> 94851.054 | BR83: =$AH83/$M83 -> 0 | BS83: =$AI83/$M83 -> 0 | BT83: =$AJ83/$M83 -> 94851.054 | BU83: =$AK83/$M83 -> 0 | BV83: =$AL83/$M83 -> 0 | BW83: =$AM83/$M83 -> 171798.97 | BX83: =$AN83/$M83 -> 0 | BY83: =$AO83/$M83 -> 0 | BZ83: =$AP83/$M83 -> 171798.97 | CA83: =AQ83/$M83 -> 0 | CB83: =AR83/$M83 -> 0 | CC83: =AS83/$M83 -> 35569.145 | CD83: =AT83/$M83 -> 0 | CE83: =AU83/$M83 -> 0 | CF83: =AV83/$M83 -> 35569.145 | CG83: =AW83/$M83 -> 0 | CH83: =AX83/$M83 -> 0 | ... CL83: =BB83/$M83 -> 47425.527 | CM83: =$BC83/$M83 -> 0 | CN83: =$BD83/$M83 -> 0 | CO83: =$BE83/$M83 -> 403093.27 | CP83: =$BF83/$M83 -> 0 | CQ83: =$BG83/$M83 -> 0 | CR83: =SUM(CM83:CQ83) -> 403093.27 | CS83: =K83-CR83 -> 782544.91 | CU83: =D83 -> ARS | CV83: =VLOOKUP(CU83,DF:DG,2,0) -> 0.0006918517 | CW83: =K83*CV83 -> 820.28579 | CX83: =BN83*CV83 -> 36.978483 | CY83: =BT83*CV83 -> 65.622863 | CZ83: =BZ83*CV83 -> 118.85941 | DA83: =CF83*CV83 -> 24.608574 | DB83: =CL83*CV83 -> 32.811432 | DC83: =CS83*CV83 -> 541.40503 | DD83: =VLOOKUP(A83,'Billing Report'!H:I,2,FALSE) -> UIP_UNIVERSAL-HAMNET-SOLOENCINES-TWITTER-TOTAL-TRAFICO-INTERESES-CLICKS-OP_504180
