Workbook

Sheet con 1
A1: Use your private filters OR Download file as Excel | AE1: Miss | AS1: Miss | BA1: Miss | BE1: =COLUMN((BE1)) -> 57 | CH1: =COLUMN(CH1) -> 86 | CI1: 46087.744
AE2: Incorrect | AS2: Incorrect | BA2: Incorrect | BG2: =er!A3 -> 46054 | CH2: Minutes until refresh: | CI2: =30-MINUTE(NOW()-CI1) -> 24
AF3: C3-Curr | AI3: C4-Diff | AK3: C5-Diff | AW3: C6-Curr | AX3: C7-Diff | BB3: C8-Curr | BC3: C9-Diff | CH3: Comment columns get hidden during the refresh.
A5: Account ID | B5: BU Name | C5: Division | D5: Structured Name | E5: SO Status | F5: PO Status | G5: Reporting Country | H5: Billing Entity | I5: Billing Country | J5: Revenue (Net Budget Delivered (Billing Currency)) | K5: Revenue (Net Budget Delivered (Billing Currency)) w/o deals | L5: Bill Curr | M5: Total Net Budget (Delivered) | N5: Account Curr | O5: Qualified Purch Qty | P5: Costs | Q5: Purch Curr | R5: Purch Country | S5: Deal Name | T5: Expected Discount % | U5: Real Discount % | V5: Year Month | W5: Posting Period | X5: Division | Y5: Quota Country | Z5: Purchase Country | AA5: Account Curr | AB5: Revenue | AC5: Purch Curr | AD5: Cost | AE5: Commision percentage | AF5: Purch Curr (SF-Bil) | AG5: Rev Dif (SF-Bil) | AH5: Rev Dif (SF-Bil) USD | AI5: Cost Dif (SF-Bil) | AJ5: Cost Dif (SF-Bil) USD | AK5: Margin (SF Rev-Cogs) | AL5: Purch Country (SF-Bil) | AM5: Invoice Number | AN5: Action Point | AO5: Bill To | AP5: Account Curr | AQ5: Account Spend Net | AR5: Purch Curr | AS5: Purch Spend Net | AT5: Account Curr (inv-SF) | AU5: Rev Dif (Inv - SF) | AV5: Rev Dif (Inv - SF) USD | AW5: Purch Curr (SF-Inv) | AX5: Cost Dif (SF-Inv) | AY5: Cost Dif (SF-Inv) USD | AZ5: Purch Curr | BA5: Spend Amount | BB5: Curr (SF-Stat) | BC5: Dif (SF-Stat) | BD5: Dif (SF-Stat) USD | BE5: Comm Percent | BF5: Comm Purch Curr | BG5: Comm USD Curr | BH5: Net Interco | BI5: Direct Tax Percent | BJ5: Direct Tax Purch Curr | BK5: Direct Tax USD Curr | BL5: With Tax Percent | BM5: With Tax Purch Curr | BN5: With Tax USD Curr | BO5: Fee | BP5: Fee Purch Curr | BQ5: Fee USD Curr | BR5: Direct Tax Percent | BS5: Direct Tax Purch Curr | BT5: Direct Tax USD Curr | BU5: With Tax Percent | BV5: With Tax Purch Curr | BW5: With Tax USD Curr | BX5: Fee | BY5: Fee Purch Curr | BZ5: Fee USD Curr | CA5: Margin SF Rev vs. SF Costs | CB5: Margin Bil Rev vs. Bil Costs | CC5: Margin SF - Margin Bil | CD5: Tax - Tax Bil | CE5: Tax - Tax Bil in USD | CF5: (Cost Dif (SF-Bil) USD) - (Tax - Tax Bil in USD) | CG5: Check (Comm Percent - Bil Commision percentage) | CH5: Comments for Operations | CI5: Comments for Rev&Cogs team | CK5: TAX AMMOUNT TWITTER | CL5: DIFF IN COGS WITHOUT TAX ERR | CN5: TAX AMMOUNT TWITTER USD
A6: T2694837 | B6: Twitter Rep | C6: IMS | D6: AR_Media Company_!Blocked Nessy LLC USA_AR00310258 TW - Lemon - US 2025 | G6: Argentina | H6: Aleph USA | I6: United States | J6: 902.75 | K6: 902.74894 | L6: USD | M6: 911867.62 | N6: ARS | O6: 911867.62 | P6: 711256.74 | Q6: ARS | R6: Mexico | U6: 0 | V6: 2026-02 | W6: February/2026 | X6: IMS | Y6: Argentina | Z6: Mexico | AA6: ARS | AB6: 911867.62 | AC6: ARS | AD6: 551201.18 | AE6: 39.55 | AF6: OK | AG6: 0 | AH6: 0 | AI6: 160055.56 | AJ6: 114.57 | AK6: 0.43602157 | AL6: OK | AM6: 10573708 | AO6: Miss | AP6: Miss | AR6: Miss | AT6: Miss | AU6: 911867.62 | AV6: 651 | AW6: Miss | AX6: 911867.62 | AY6: 652.73 | AZ6: ARS | BA6: 551201.18 | BB6: OK | BC6: 160055.56 | BD6: 114.57 | BE6: {=IFERROR(INDEX('Com&tax'!$E$2:$E$5, MATCH(1, ('Com&tax'!$A$2:$A$5=B6)*('Com&tax'!$B$2:$B$5=G6), 0)),"")} -> 0.15 | BF6: =IF(A6="","",( IFERROR(O6*BE6,""))) -> 136780.14 | BG6: {=IF(A6="","",( IFERROR((O6/ INDEX(er!$D$3:$D$75,MATCH(1, (er!$A$3:$A$75=$BG$2)*(er!$C$3:$C$75=Q6), 0)))*BE6,"")))} -> 97.909909 | BH6: =IF(A6="","",( IF(B6="Snapchat Rep", IF(A6="","",(P6-BF6)),-BF6))) -> -136780.14 | BI6: {=IFERROR(INDEX('Com&tax'!$F$2:$F$5, MATCH(1, ('Com&tax'!$A$2:$A$5=B6)*('Com&tax'!$B$2:$B$5=Y6), 0)),0)} -> 0.049 | BJ6: =IF(A6="","",( IFERROR((J6*(1-BE6))*BI6,0))) -> 37.599538 | BK6: {=IF(A6="","",( IFERROR((J6*(1-BE6))*BI6/INDEX(er!D:D, MATCH(Q6,er!C:C,0),1),0)))} -> 0.026914486 | BL6: {=IFERROR(INDEX('Com&tax'!$G$2:$G$5, MATCH(1, ('Com&tax'!$A$2:$A$5=B6)*('Com&tax'!$B$2:$B$5=Y6), 0)),0)} -> 0.1575 | BM6: =IF(A6="","",( IFERROR((J6*(1-BE6))*BL6,0))) -> 120.85566 | BN6: {=IF(A6="","",( IFERROR((J6*(1-BE6))*BL6/INDEX(er!D:D, MATCH(Q6,er!C:C,0),1),0)))} -> 0.086510849 | BO6: {=IFERROR(INDEX('Com&tax'!$H$2:$H$5, MATCH(1, ('Com&tax'!$A$2:$A$5=B6)*('Com&tax'!$B$2:$B$5=Y6), 0)),0)} -> 0.07 | BP6: =IF(A6="","",( IFERROR(J6*BO6,0))) -> 63.1925 | BQ6: {=IF(A6="","",( IFERROR(J6*BO6/INDEX(er!D:D, MATCH(Q6,er!C:C,0),1),0)))} -> 0.045234431 | BR6: {=IFERROR(INDEX('Com&tax'!$F$2:$F$5, MATCH(1, ('Com&tax'!$A$2:$A$5=B6)*('Com&tax'!$D$2:$D$5=H6), 0)),0)} -> 0 | BS6: =IF(A6="","",( IFERROR((J6*(1-BE6))*BR6,0))) -> 0 | BT6: {=IF(A6="","",( IFERROR((J6*(1-BE6))*BR6/INDEX(er!D:D, MATCH(Q6,er!C:C,0),1),0)))} -> 0 | BU6: {=IFERROR(INDEX('Com&tax'!$G$2:$G$5, MATCH(1, ('Com&tax'!$A$2:$A$5=B6)*('Com&tax'!$D$2:$D$5=H6), 0)),0)} -> 0 | BV6: =IF(A6="","",( IFERROR((J6*(1-BE6))*BU6,0))) -> 0 | BW6: {=IF(A6="","",( IFERROR((J6*(1-BE6))*BU6/INDEX(er!D:D, MATCH(Q6,er!C:C,0),1),0)))} -> 0 | BX6: {=IFERROR(INDEX('Com&tax'!$H$2:$H$5, MATCH(1, ('Com&tax'!$A$2:$A$5=B6)*('Com&tax'!$D$2:$D$5=H6), 0)),0)} -> 0 | BY6: =IF(A6="","",( IFERROR(J6*BX6,0))) -> 0 | BZ6: {=IF(A6="","",( IFERROR(J6*BX6/INDEX(er!D:D, MATCH(Q6,er!C:C,0),1),0)))} -> 0 | CA6: {=IF(A6="","",( IFERROR(1-((P6/ INDEX(er!$D$3:$D$75,MATCH(1, (er!$A$3:$A$75=$BG$2)*(er!$C$3:$C$75=Q6), 0)) / (J6/ INDEX(er!$D$3:$D$75,MATCH(1, (er!$A$3:$A$75=$BG$2)*(er!$C$3:$C$75=L6), 0))))),"")))} -> 0.43602157 | CB6: =IF(AB6="","",1-AD6/AB6) -> 0.395525 | CC6: =IF(AND(CA6="", CB6=""), "", CA6-CB6) -> 0.040496574 | CD6: =BJ6+BM6-BS6-BV6 -> 158.45519 | CE6: =BK6+BN6-BT6-BW6 -> 0.11342534 | CF6: =AJ6-CE6 -> 114.45657 | CG6: =IF(OR(BE6="", AE6=""), "Miss", IF(ABS(AE6/100-AK6)<0.005, "OK", "Incorrect")) -> Incorrect | CI6: OK. Diff. Bill. / Adv. Country | CK6: 0 | CL6: =(AI6+CK6)/INDEX(er!D:D,MATCH(AC6,er!C:C,0),1) -> 114.57091 | CN6: =CK6/INDEX(er!D:D,MATCH(AC6,er!C:C,0),1) -> 0
A7: T2751490 | B7: Twitter Rep | C7: IMS | D7: AR_Media Company_BANCO DE LA PROVINCIA DE CORDOBA ARGENTINA_SMB-X ARG - Banco de Cordoba - Ene - abril 24 UPSELL 5 | G7: Argentina | H7: Aleph Argentina | I7: Argentina | J7: 3855555.8 | K7: 3855555.8 | L7: ARS | M7: 3855555.8 | N7: ARS | O7: 3855555.8 | P7: 2330587.2 | Q7: ARS | R7: Mexico | U7: 0 | V7: 2026-02 | W7: February/2026 | X7: IMS | Y7: Argentina | Z7: Mexico | AA7: ARS | AB7: 3855555.8 | AC7: ARS | AD7: 2330587.1 | AE7: 39.55 | AF7: OK | AG7: 0 | AH7: 0 | AI7: 0.15 | AJ7: 0 | AK7: 0.39552496 | AL7: OK | AM7: 10573709 | AO7: Miss | AP7: Miss | AR7: Miss | AT7: Miss | AU7: 3855555.8 | AV7: 2758 | AW7: Miss | AX7: 3855555.8 | AY7: 2759.88 | AZ7: ARS | BA7: 2330587.1 | BB7: OK | BC7: 0.16 | BD7: 0 | BE7: {=IFERROR(INDEX('Com&tax'!$E$2:$E$5, MATCH(1, ('Com&tax'!$A$2:$A$5=B7)*('Com&tax'!$B$2:$B$5=G7), 0)),"")} -> 0.15 | BF7: =IF(A7="","",( IFERROR(O7*BE7,""))) -> 578333.37 | BG7: {=IF(A7="","",( IFERROR((O7/ INDEX(er!$D$3:$D$75,MATCH(1, (er!$A$3:$A$75=$BG$2)*(er!$C$3:$C$75=Q7), 0)))*BE7,"")))} -> 413.98237 | BH7: =IF(A7="","",( IF(B7="Snapchat Rep", IF(A7="","",(P7-BF7)),-BF7))) -> -578333.37 | BI7: {=IFERROR(INDEX('Com&tax'!$F$2:$F$5, MATCH(1, ('Com&tax'!$A$2:$A$5=B7)*('Com&tax'!$B$2:$B$5=Y7), 0)),0)} -> 0.049 | BJ7: =IF(A7="","",( IFERROR((J7*(1-BE7))*BI7,0))) -> 160583.9 | BK7: {=IF(A7="","",( IFERROR((J7*(1-BE7))*BI7/INDEX(er!D:D, MATCH(Q7,er!C:C,0),1),0)))} -> 114.9491 | BL7: {=IFERROR(INDEX('Com&tax'!$G$2:$G$5, MATCH(1, ('Com&tax'!$A$2:$A$5=B7)*('Com&tax'!$B$2:$B$5=Y7), 0)),0)} -> 0.1575 | BM7: =IF(A7="","",( IFERROR((J7*(1-BE7))*BL7,0))) -> 516162.53 | BN7: {=IF(A7="","",( IFERROR((J7*(1-BE7))*BL7/INDEX(er!D:D, MATCH(Q7,er!C:C,0),1),0)))} -> 369.47926 | BO7: {=IFERROR(INDEX('Com&tax'!$H$2:$H$5, MATCH(1, ('Com&tax'!$A$2:$A$5=B7)*('Com&tax'!$B$2:$B$5=Y7), 0)),0)} -> 0.07 | BP7: =IF(A7="","",( IFERROR(J7*BO7,0))) -> 269888.91 | BQ7: {=IF(A7="","",( IFERROR(J7*BO7/INDEX(er!D:D, MATCH(Q7,er!C:C,0),1),0)))} -> 193.19177 | BR7: {=IFERROR(INDEX('Com&tax'!$F$2:$F$5, MATCH(1, ('Com&tax'!$A$2:$A$5=B7)*('Com&tax'!$D$2:$D$5=H7), 0)),0)} -> 0.049 | BS7: =IF(A7="","",( IFERROR((J7*(1-BE7))*BR7,0))) -> 160583.9 | BT7: {=IF(A7="","",( IFERROR((J7*(1-BE7))*BR7/INDEX(er!D:D, MATCH(Q7,er!C:C,0),1),0)))} -> 114.9491 | BU7: {=IFERROR(INDEX('Com&tax'!$G$2:$G$5, MATCH(1, ('Com&tax'!$A$2:$A$5=B7)*('Com&tax'!$D$2:$D$5=H7), 0)),0)} -> 0.1575 | BV7: =IF(A7="","",( IFERROR((J7*(1-BE7))*BU7,0))) -> 516162.53 | BW7: {=IF(A7="","",( IFERROR((J7*(1-BE7))*BU7/INDEX(er!D:D, MATCH(Q7,er!C:C,0),1),0)))} -> 369.47926 | BX7: {=IFERROR(INDEX('Com&tax'!$H$2:$H$5, MATCH(1, ('Com&tax'!$A$2:$A$5=B7)*('Com&tax'!$D$2:$D$5=H7), 0)),0)} -> 0.07 | BY7: =IF(A7="","",( IFERROR(J7*BX7,0))) -> 269888.91 | BZ7: {=IF(A7="","",( IFERROR(J7*BX7/INDEX(er!D:D, MATCH(Q7,er!C:C,0),1),0)))} -> 193.19177 | CA7: {=IF(A7="","",( IFERROR(1-((P7/ INDEX(er!$D$3:$D$75,MATCH(1, (er!$A$3:$A$75=$BG$2)*(er!$C$3:$C$75=Q7), 0)) / (J7/ INDEX(er!$D$3:$D$75,MATCH(1, (er!$A$3:$A$75=$BG$2)*(er!$C$3:$C$75=L7), 0))))),"")))} -> 0.39552496 | CB7: =IF(AB7="","",1-AD7/AB7) -> 0.395525 | CC7: =IF(AND(CA7="", CB7=""), "", CA7-CB7) -> -3.8904897e-08 | CD7: =BJ7+BM7-BS7-BV7 -> 0 | CE7: =BK7+BN7-BT7-BW7 -> 0 | CF7: =AJ7-CE7 -> 0 | CG7: =IF(OR(BE7="", AE7=""), "Miss", IF(ABS(AE7/100-AK7)<0.005, "OK", "Incorrect")) -> OK | CI7: OK | CK7: 0 | CL7: =(AI7+CK7)/INDEX(er!D:D,MATCH(AC7,er!C:C,0),1) -> 0.00010737294 | CN7: =CK7/INDEX(er!D:D,MATCH(AC7,er!C:C,0),1) -> 0
A8: T2767832 | B8: Twitter Rep | C8: IMS | D8: AR_Media Company_Almundo.com SRL_X - almundo- 2025 | G8: Argentina | H8: Aleph Argentina | I8: Argentina | J8: 3113913.1 | K8: 3113913.1 | L8: ARS | M8: 3113913.1 | N8: ARS | O8: 3113913.1 | P8: 1882282.7 | Q8: ARS | R8: Mexico | U8: 0 | V8: 2026-02 | W8: February/2026 | X8: IMS | Y8: Argentina | Z8: Mexico | AA8: ARS | AB8: 3113913.1 | AC8: ARS | AD8: 1882282.6 | AE8: 39.55 | AF8: OK | AG8: 0 | AH8: 0 | AI8: 0.12 | AJ8: 0 | AK8: 0.39552496 | AL8: OK | AM8: 10573710 | AO8: Miss | AP8: Miss | AR8: Miss | AT8: Miss | AU8: 3113913.1 | AV8: 2227 | AW8: Miss | AX8: 3113913.1 | AY8: 2229 | AZ8: ARS | BA8: 1882282.6 | BB8: OK | BC8: 0.12 | BD8: 0 | BE8: {=IFERROR(INDEX('Com&tax'!$E$2:$E$5, MATCH(1, ('Com&tax'!$A$2:$A$5=B8)*('Com&tax'!$B$2:$B$5=G8), 0)),"")} -> 0.15 | BF8: =IF(A8="","",( IFERROR(O8*BE8,""))) -> 467086.96 | BG8: {=IF(A8="","",( IFERROR((O8/ INDEX(er!$D$3:$D$75,MATCH(1, (er!$A$3:$A$75=$BG$2)*(er!$C$3:$C$75=Q8), 0)))*BE8,"")))} -> 334.35001 | BH8: =IF(A8="","",( IF(B8="Snapchat Rep", IF(A8="","",(P8-BF8)),-BF8))) -> -467086.96 | BI8: {=IFERROR(INDEX('Com&tax'!$F$2:$F$5, MATCH(1, ('Com&tax'!$A$2:$A$5=B8)*('Com&tax'!$B$2:$B$5=Y8), 0)),0)} -> 0.049 | BJ8: =IF(A8="","",( IFERROR((J8*(1-BE8))*BI8,0))) -> 129694.48 | BK8: {=IF(A8="","",( IFERROR((J8*(1-BE8))*BI8/INDEX(er!D:D, MATCH(Q8,er!C:C,0),1),0)))} -> 92.837852 | BL8: {=IFERROR(INDEX('Com&tax'!$G$2:$G$5, MATCH(1, ('Com&tax'!$A$2:$A$5=B8)*('Com&tax'!$B$2:$B$5=Y8), 0)),0)} -> 0.1575 | BM8: =IF(A8="","",( IFERROR((J8*(1-BE8))*BL8,0))) -> 416875.11 | BN8: {=IF(A8="","",( IFERROR((J8*(1-BE8))*BL8/INDEX(er!D:D, MATCH(Q8,er!C:C,0),1),0)))} -> 298.40738 | BO8: {=IFERROR(INDEX('Com&tax'!$H$2:$H$5, MATCH(1, ('Com&tax'!$A$2:$A$5=B8)*('Com&tax'!$B$2:$B$5=Y8), 0)),0)} -> 0.07 | BP8: =IF(A8="","",( IFERROR(J8*BO8,0))) -> 217973.92 | BQ8: {=IF(A8="","",( IFERROR(J8*BO8/INDEX(er!D:D, MATCH(Q8,er!C:C,0),1),0)))} -> 156.03 | BR8: {=IFERROR(INDEX('Com&tax'!$F$2:$F$5, MATCH(1, ('Com&tax'!$A$2:$A$5=B8)*('Com&tax'!$D$2:$D$5=H8), 0)),0)} -> 0.049 | BS8: =IF(A8="","",( IFERROR((J8*(1-BE8))*BR8,0))) -> 129694.48 | BT8: {=IF(A8="","",( IFERROR((J8*(1-BE8))*BR8/INDEX(er!D:D, MATCH(Q8,er!C:C,0),1),0)))} -> 92.837852 | BU8: {=IFERROR(INDEX('Com&tax'!$G$2:$G$5, MATCH(1, ('Com&tax'!$A$2:$A$5=B8)*('Com&tax'!$D$2:$D$5=H8), 0)),0)} -> 0.1575 | BV8: =IF(A8="","",( IFERROR((J8*(1-BE8))*BU8,0))) -> 416875.11 | BW8: {=IF(A8="","",( IFERROR((J8*(1-BE8))*BU8/INDEX(er!D:D, MATCH(Q8,er!C:C,0),1),0)))} -> 298.40738 | BX8: {=IFERROR(INDEX('Com&tax'!$H$2:$H$5, MATCH(1, ('Com&tax'!$A$2:$A$5=B8)*('Com&tax'!$D$2:$D$5=H8), 0)),0)} -> 0.07 | BY8: =IF(A8="","",( IFERROR(J8*BX8,0))) -> 217973.92 | BZ8: {=IF(A8="","",( IFERROR(J8*BX8/INDEX(er!D:D, MATCH(Q8,er!C:C,0),1),0)))} -> 156.03 | CA8: {=IF(A8="","",( IFERROR(1-((P8/ INDEX(er!$D$3:$D$75,MATCH(1, (er!$A$3:$A$75=$BG$2)*(er!$C$3:$C$75=Q8), 0)) / (J8/ INDEX(er!$D$3:$D$75,MATCH(1, (er!$A$3:$A$75=$BG$2)*(er!$C$3:$C$75=L8), 0))))),"")))} -> 0.39552496 | CB8: =IF(AB8="","",1-AD8/AB8) -> 0.395525 | CC8: =IF(AND(CA8="", CB8=""), "", CA8-CB8) -> -3.8536721e-08 | CD8: =BJ8+BM8-BS8-BV8 -> 0 | CE8: =BK8+BN8-BT8-BW8 -> 0 | CF8: =AJ8-CE8 -> 0 | CG8: =IF(OR(BE8="", AE8=""), "Miss", IF(ABS(AE8/100-AK8)<0.005, "OK", "Incorrect")) -> OK | CI8: OK | CK8: 0 | CL8: =(AI8+CK8)/INDEX(er!D:D,MATCH(AC8,er!C:C,0),1) -> 8.5898354e-05 | CN8: =CK8/INDEX(er!D:D,MATCH(AC8,er!C:C,0),1) -> 0
A9: T2834460 | B9: Twitter Rep | C9: IMS | D9: AR_Media Company_Flybondi_SMB-X ARG - Flybondi (may - jun 24) | G9: Argentina | H9: Aleph Argentina | I9: Argentina | J9: 2687841.5 | K9: 2687841.5 | L9: ARS | M9: 2687841.5 | N9: ARS | O9: 2687841.5 | P9: 1624733.1 | Q9: ARS | R9: Mexico | U9: 0 | V9: 2026-02 | W9: February/2026 | X9: IMS | Y9: Argentina | Z9: Mexico | AA9: ARS | AB9: 2687841.5 | AC9: ARS | AD9: 1624733 | AE9: 39.55 | AF9: OK | AG9: 0 | AH9: 0 | AI9: 0.1 | AJ9: 0 | AK9: 0.39552496 | AL9: OK | AM9: 10573711 | AO9: Miss | AP9: Miss | AR9: Miss | AT9: Miss | AU9: 2687841.5 | AV9: 1922 | AW9: Miss | AX9: 2687841.5 | AY9: 1924.01 | AZ9: ARS | BA9: 1624733 | BB9: OK | BC9: 0.11 | BD9: 0 | BE9: {=IFERROR(INDEX('Com&tax'!$E$2:$E$5, MATCH(1, ('Com&tax'!$A$2:$A$5=B9)*('Com&tax'!$B$2:$B$5=G9), 0)),"")} -> 0.15 | BF9: =IF(A9="","",( IFERROR(O9*BE9,""))) -> 403176.22 | BG9: {=IF(A9="","",( IFERROR((O9/ INDEX(er!$D$3:$D$75,MATCH(1, (er!$A$3:$A$75=$BG$2)*(er!$C$3:$C$75=Q9), 0)))*BE9,"")))} -> 288.60145 | BH9: =IF(A9="","",( IF(B9="Snapchat Rep", IF(A9="","",(P9-BF9)),-BF9))) -> -403176.22 | BI9: {=IFERROR(INDEX('Com&tax'!$F$2:$F$5, MATCH(1, ('Com&tax'!$A$2:$A$5=B9)*('Com&tax'!$B$2:$B$5=Y9), 0)),0)} -> 0.049 | BJ9: =IF(A9="","",( IFERROR((J9*(1-BE9))*BI9,0))) -> 111948.6 | BK9: {=IF(A9="","",( IFERROR((J9*(1-BE9))*BI9/INDEX(er!D:D, MATCH(Q9,er!C:C,0),1),0)))} -> 80.135001 | BL9: {=IFERROR(INDEX('Com&tax'!$G$2:$G$5, MATCH(1, ('Com&tax'!$A$2:$A$5=B9)*('Com&tax'!$B$2:$B$5=Y9), 0)),0)} -> 0.1575 | BM9: =IF(A9="","",( IFERROR((J9*(1-BE9))*BL9,0))) -> 359834.78 | BN9: {=IF(A9="","",( IFERROR((J9*(1-BE9))*BL9/INDEX(er!D:D, MATCH(Q9,er!C:C,0),1),0)))} -> 257.57679 | BO9: {=IFERROR(INDEX('Com&tax'!$H$2:$H$5, MATCH(1, ('Com&tax'!$A$2:$A$5=B9)*('Com&tax'!$B$2:$B$5=Y9), 0)),0)} -> 0.07 | BP9: =IF(A9="","",( IFERROR(J9*BO9,0))) -> 188148.9 | BQ9: {=IF(A9="","",( IFERROR(J9*BO9/INDEX(er!D:D, MATCH(Q9,er!C:C,0),1),0)))} -> 134.68067 | BR9: {=IFERROR(INDEX('Com&tax'!$F$2:$F$5, MATCH(1, ('Com&tax'!$A$2:$A$5=B9)*('Com&tax'!$D$2:$D$5=H9), 0)),0)} -> 0.049 | BS9: =IF(A9="","",( IFERROR((J9*(1-BE9))*BR9,0))) -> 111948.6 | BT9: {=IF(A9="","",( IFERROR((J9*(1-BE9))*BR9/INDEX(er!D:D, MATCH(Q9,er!C:C,0),1),0)))} -> 80.135001 | BU9: {=IFERROR(INDEX('Com&tax'!$G$2:$G$5, MATCH(1, ('Com&tax'!$A$2:$A$5=B9)*('Com&tax'!$D$2:$D$5=H9), 0)),0)} -> 0.1575 | BV9: =IF(A9="","",( IFERROR((J9*(1-BE9))*BU9,0))) -> 359834.78 | BW9: {=IF(A9="","",( IFERROR((J9*(1-BE9))*BU9/INDEX(er!D:D, MATCH(Q9,er!C:C,0),1),0)))} -> 257.57679 | BX9: {=IFERROR(INDEX('Com&tax'!$H$2:$H$5, MATCH(1, ('Com&tax'!$A$2:$A$5=B9)*('Com&tax'!$D$2:$D$5=H9), 0)),0)} -> 0.07 | BY9: =IF(A9="","",( IFERROR(J9*BX9,0))) -> 188148.9 | BZ9: {=IF(A9="","",( IFERROR(J9*BX9/INDEX(er!D:D, MATCH(Q9,er!C:C,0),1),0)))} -> 134.68067 | CA9: {=IF(A9="","",( IFERROR(1-((P9/ INDEX(er!$D$3:$D$75,MATCH(1, (er!$A$3:$A$75=$BG$2)*(er!$C$3:$C$75=Q9), 0)) / (J9/ INDEX(er!$D$3:$D$75,MATCH(1, (er!$A$3:$A$75=$BG$2)*(er!$C$3:$C$75=L9), 0))))),"")))} -> 0.39552496 | CB9: =IF(AB9="","",1-AD9/AB9) -> 0.395525 | CC9: =IF(AND(CA9="", CB9=""), "", CA9-CB9) -> -3.7204575e-08 | CD9: =BJ9+BM9-BS9-BV9 -> 0 | CE9: =BK9+BN9-BT9-BW9 -> 0 | CF9: =AJ9-CE9 -> 0 | CG9: =IF(OR(BE9="", AE9=""), "Miss", IF(ABS(AE9/100-AK9)<0.005, "OK", "Incorrect")) -> OK | CI9: OK | CK9: 0 | CL9: =(AI9+CK9)/INDEX(er!D:D,MATCH(AC9,er!C:C,0),1) -> 7.1581961e-05 | CN9: =CK9/INDEX(er!D:D,MATCH(AC9,er!C:C,0),1) -> 0
A10: T2887099 | B10: Twitter Rep | C10: IMS | D10: AR_Media Company_FINTECH Argentina_TW - Satoshi Tango - Q3 | G10: Argentina | H10: Aleph Argentina | I10: Argentina | J10: 1055530.2 | K10: 1055530.2 | L10: ARS | M10: 1055530.2 | N10: ARS | O10: 1055530.2 | P10: 638041.67 | Q10: ARS | R10: Mexico | U10: 0 | V10: 2026-02 | W10: February/2026 | X10: IMS | Y10: Argentina | Z10: Mexico | AA10: ARS | AB10: 1055530.2 | AC10: ARS | AD10: 638041.63 | AE10: 39.55 | AF10: OK | AG10: 0 | AH10: 0 | AI10: 0.04 | AJ10: 0 | AK10: 0.39552496 | AL10: OK | AM10: 10573707 | AO10: Miss | AP10: Miss | AR10: Miss | AT10: Miss | AU10: 1055530.2 | AV10: 754 | AW10: Miss | AX10: 1055530.2 | AY10: 755.57 | AZ10: ARS | BA10: 638041.62 | BB10: OK | BC10: 0.05 | BD10: 0 | BE10: {=IFERROR(INDEX('Com&tax'!$E$2:$E$5, MATCH(1, ('Com&tax'!$A$2:$A$5=B10)*('Com&tax'!$B$2:$B$5=G10), 0)),"")} -> 0.15 | BF10: =IF(A10="","",( IFERROR(O10*BE10,""))) -> 158329.53 | BG10: {=IF(A10="","",( IFERROR((O10/ INDEX(er!$D$3:$D$75,MATCH(1, (er!$A$3:$A$75=$BG$2)*(er!$C$3:$C$75=Q10), 0)))*BE10,"")))} -> 113.33538 | BH10: =IF(A10="","",( IF(B10="Snapchat Rep", IF(A10="","",(P10-BF10)),-BF10))) -> -158329.53 | BI10: {=IFERROR(INDEX('Com&tax'!$F$2:$F$5, MATCH(1, ('Com&tax'!$A$2:$A$5=B10)*('Com&tax'!$B$2:$B$5=Y10), 0)),0)} -> 0.049 | BJ10: =IF(A10="","",( IFERROR((J10*(1-BE10))*BI10,0))) -> 43962.833 | BK10: {=IF(A10="","",( IFERROR((J10*(1-BE10))*BI10/INDEX(er!D:D, MATCH(Q10,er!C:C,0),1),0)))} -> 31.469458 | BL10: {=IFERROR(INDEX('Com&tax'!$G$2:$G$5, MATCH(1, ('Com&tax'!$A$2:$A$5=B10)*('Com&tax'!$B$2:$B$5=Y10), 0)),0)} -> 0.1575 | BM10: =IF(A10="","",( IFERROR((J10*(1-BE10))*BL10,0))) -> 141309.11 | BN10: {=IF(A10="","",( IFERROR((J10*(1-BE10))*BL10/INDEX(er!D:D, MATCH(Q10,er!C:C,0),1),0)))} -> 101.15183 | BO10: {=IFERROR(INDEX('Com&tax'!$H$2:$H$5, MATCH(1, ('Com&tax'!$A$2:$A$5=B10)*('Com&tax'!$B$2:$B$5=Y10), 0)),0)} -> 0.07 | BP10: =IF(A10="","",( IFERROR(J10*BO10,0))) -> 73887.115 | BQ10: {=IF(A10="","",( IFERROR(J10*BO10/INDEX(er!D:D, MATCH(Q10,er!C:C,0),1),0)))} -> 52.889846 | BR10: {=IFERROR(INDEX('Com&tax'!$F$2:$F$5, MATCH(1, ('Com&tax'!$A$2:$A$5=B10)*('Com&tax'!$D$2:$D$5=H10), 0)),0)} -> 0.049 | BS10: =IF(A10="","",( IFERROR((J10*(1-BE10))*BR10,0))) -> 43962.833 | BT10: {=IF(A10="","",( IFERROR((J10*(1-BE10))*BR10/INDEX(er!D:D, MATCH(Q10,er!C:C,0),1),0)))} -> 31.469458 | BU10: {=IFERROR(INDEX('Com&tax'!$G$2:$G$5, MATCH(1, ('Com&tax'!$A$2:$A$5=B10)*('Com&tax'!$D$2:$D$5=H10), 0)),0)} -> 0.1575 | BV10: =IF(A10="","",( IFERROR((J10*(1-BE10))*BU10,0))) -> 141309.11 | BW10: {=IF(A10="","",( IFERROR((J10*(1-BE10))*BU10/INDEX(er!D:D, MATCH(Q10,er!C:C,0),1),0)))} -> 101.15183 | BX10: {=IFERROR(INDEX('Com&tax'!$H$2:$H$5, MATCH(1, ('Com&tax'!$A$2:$A$5=B10)*('Com&tax'!$D$2:$D$5=H10), 0)),0)} -> 0.07 | BY10: =IF(A10="","",( IFERROR(J10*BX10,0))) -> 73887.115 | BZ10: {=IF(A10="","",( IFERROR(J10*BX10/INDEX(er!D:D, MATCH(Q10,er!C:C,0),1),0)))} -> 52.889846 | CA10: {=IF(A10="","",( IFERROR(1-((P10/ INDEX(er!$D$3:$D$75,MATCH(1, (er!$A$3:$A$75=$BG$2)*(er!$C$3:$C$75=Q10), 0)) / (J10/ INDEX(er!$D$3:$D$75,MATCH(1, (er!$A$3:$A$75=$BG$2)*(er!$C$3:$C$75=L10), 0))))),"")))} -> 0.39552496 | CB10: =IF(AB10="","",1-AD10/AB10) -> 0.39552499 | CC10: =IF(AND(CA10="", CB10=""), "", CA10-CB10) -> -3.7895647e-08 | CD10: =BJ10+BM10-BS10-BV10 -> 0 | CE10: =BK10+BN10-BT10-BW10 -> 0 | CF10: =AJ10-CE10 -> 0 | CG10: =IF(OR(BE10="", AE10=""), "Miss", IF(ABS(AE10/100-AK10)<0.005, "OK", "Incorrect")) -> OK | CI10: OK | CK10: 0 | CL10: =(AI10+CK10)/INDEX(er!D:D,MATCH(AC10,er!C:C,0),1) -> 2.8632785e-05 | CN10: =CK10/INDEX(er!D:D,MATCH(AC10,er!C:C,0),1) -> 0
A11: T2929648 | B11: Twitter Rep | C11: IMS | D11: AR_Media Company_Liliana SRL_SMB-X ARG - Liliana - Octubre 24 | G11: Argentina | H11: Aleph Argentina | I11: Argentina | J11: 1269863.2 | K11: 1269863.2 | L11: ARS | M11: 1269863.2 | N11: ARS | O11: 1269863.2 | P11: 767600.62 | Q11: ARS | R11: Mexico | U11: 0 | V11: 2026-02 | W11: February/2026 | X11: IMS | Y11: Argentina | Z11: Mexico | AA11: ARS | AB11: 1269863.2 | AC11: ARS | AD11: 767600.57 | AE11: 39.55 | AF11: OK | AG11: 0 | AH11: 0 | AI11: 0.05 | AJ11: 0 | AK11: 0.39552496 | AL11: OK | AM11: 10573619 | AO11: Miss | AP11: Miss | AR11: Miss | AT11: Miss | AU11: 1269863.2 | AV11: 907 | AW11: Miss | AX11: 1269863.2 | AY11: 908.99 | AZ11: ARS | BA11: 767600.57 | BB11: OK | BC11: 0.05 | BD11: 0 | BE11: {=IFERROR(INDEX('Com&tax'!$E$2:$E$5, MATCH(1, ('Com&tax'!$A$2:$A$5=B11)*('Com&tax'!$B$2:$B$5=G11), 0)),"")} -> 0.15 | BF11: =IF(A11="","",( IFERROR(O11*BE11,""))) -> 190479.48 | BG11: {=IF(A11="","",( IFERROR((O11/ INDEX(er!$D$3:$D$75,MATCH(1, (er!$A$3:$A$75=$BG$2)*(er!$C$3:$C$75=Q11), 0)))*BE11,"")))} -> 136.34895 | BH11: =IF(A11="","",( IF(B11="Snapchat Rep", IF(A11="","",(P11-BF11)),-BF11))) -> -190479.48 | BI11: {=IFERROR(INDEX('Com&tax'!$F$2:$F$5, MATCH(1, ('Com&tax'!$A$2:$A$5=B11)*('Com&tax'!$B$2:$B$5=Y11), 0)),0)} -> 0.049 | BJ11: =IF(A11="","",( IFERROR((J11*(1-BE11))*BI11,0))) -> 52889.803 | BK11: {=IF(A11="","",( IFERROR((J11*(1-BE11))*BI11/INDEX(er!D:D, MATCH(Q11,er!C:C,0),1),0)))} -> 37.859558 | BL11: {=IFERROR(INDEX('Com&tax'!$G$2:$G$5, MATCH(1, ('Com&tax'!$A$2:$A$5=B11)*('Com&tax'!$B$2:$B$5=Y11), 0)),0)} -> 0.1575 | BM11: =IF(A11="","",( IFERROR((J11*(1-BE11))*BL11,0))) -> 170002.94 | BN11: {=IF(A11="","",( IFERROR((J11*(1-BE11))*BL11/INDEX(er!D:D, MATCH(Q11,er!C:C,0),1),0)))} -> 121.69144 | BO11: {=IFERROR(INDEX('Com&tax'!$H$2:$H$5, MATCH(1, ('Com&tax'!$A$2:$A$5=B11)*('Com&tax'!$B$2:$B$5=Y11), 0)),0)} -> 0.07 | BP11: =IF(A11="","",( IFERROR(J11*BO11,0))) -> 88890.425 | BQ11: {=IF(A11="","",( IFERROR(J11*BO11/INDEX(er!D:D, MATCH(Q11,er!C:C,0),1),0)))} -> 63.62951 | BR11: {=IFERROR(INDEX('Com&tax'!$F$2:$F$5, MATCH(1, ('Com&tax'!$A$2:$A$5=B11)*('Com&tax'!$D$2:$D$5=H11), 0)),0)} -> 0.049 | BS11: =IF(A11="","",( IFERROR((J11*(1-BE11))*BR11,0))) -> 52889.803 | BT11: {=IF(A11="","",( IFERROR((J11*(1-BE11))*BR11/INDEX(er!D:D, MATCH(Q11,er!C:C,0),1),0)))} -> 37.859558 | BU11: {=IFERROR(INDEX('Com&tax'!$G$2:$G$5, MATCH(1, ('Com&tax'!$A$2:$A$5=B11)*('Com&tax'!$D$2:$D$5=H11), 0)),0)} -> 0.1575 | BV11: =IF(A11="","",( IFERROR((J11*(1-BE11))*BU11,0))) -> 170002.94 | BW11: {=IF(A11="","",( IFERROR((J11*(1-BE11))*BU11/INDEX(er!D:D, MATCH(Q11,er!C:C,0),1),0)))} -> 121.69144 | BX11: {=IFERROR(INDEX('Com&tax'!$H$2:$H$5, MATCH(1, ('Com&tax'!$A$2:$A$5=B11)*('Com&tax'!$D$2:$D$5=H11), 0)),0)} -> 0.07 | BY11: =IF(A11="","",( IFERROR(J11*BX11,0))) -> 88890.425 | BZ11: {=IF(A11="","",( IFERROR(J11*BX11/INDEX(er!D:D, MATCH(Q11,er!C:C,0),1),0)))} -> 63.62951 | CA11: {=IF(A11="","",( IFERROR(1-((P11/ INDEX(er!$D$3:$D$75,MATCH(1, (er!$A$3:$A$75=$BG$2)*(er!$C$3:$C$75=Q11), 0)) / (J11/ INDEX(er!$D$3:$D$75,MATCH(1, (er!$A$3:$A$75=$BG$2)*(er!$C$3:$C$75=L11), 0))))),"")))} -> 0.39552496 | CB11: =IF(AB11="","",1-AD11/AB11) -> 0.395525 | CC11: =IF(AND(CA11="", CB11=""), "", CA11-CB11) -> -3.9374319e-08 | CD11: =BJ11+BM11-BS11-BV11 -> 0 | CE11: =BK11+BN11-BT11-BW11 -> 0 | CF11: =AJ11-CE11 -> 0 | CG11: =IF(OR(BE11="", AE11=""), "Miss", IF(ABS(AE11/100-AK11)<0.005, "OK", "Incorrect")) -> OK | CI11: OK | CK11: 0 | CL11: =(AI11+CK11)/INDEX(er!D:D,MATCH(AC11,er!C:C,0),1) -> 3.5790981e-05 | CN11: =CK11/INDEX(er!D:D,MATCH(AC11,er!C:C,0),1) -> 0
A12: T2985381 | B12: Twitter Rep | C12: IMS | D12: AR_Media Company_Cocos Capital Argentina_AR00303899 | X | Cocos Cap | ENE 26 | G12: Argentina | H12: Aleph Argentina | I12: Argentina | J12: 1900327.9 | K12: 1900327.9 | L12: ARS | M12: 1900327.9 | N12: ARS | O12: 1900327.9 | P12: 1148700.8 | Q12: ARS | R12: Mexico | U12: 0 | V12: 2026-02 | W12: February/2026 | X12: IMS | Y12: Argentina | Z12: Mexico | AA12: ARS | AB12: 1900327.9 | AC12: ARS | AD12: 1148700.7 | AE12: 39.55 | AF12: OK | AG12: 0 | AH12: 0 | AI12: 0.07 | AJ12: 0 | AK12: 0.39552496 | AL12: OK | AM12: 10573629 | AO12: Miss | AP12: Miss | AR12: Miss | AT12: Miss | AU12: 1900327.9 | AV12: 1358 | AW12: Miss | AX12: 1900327.9 | AY12: 1360.29 | AZ12: ARS | BA12: 1148700.7 | BB12: OK | BC12: 0.08 | BD12: 0 | BE12: {=IFERROR(INDEX('Com&tax'!$E$2:$E$5, MATCH(1, ('Com&tax'!$A$2:$A$5=B12)*('Com&tax'!$B$2:$B$5=G12), 0)),"")} -> 0.15 | BF12: =IF(A12="","",( IFERROR(O12*BE12,""))) -> 285049.19 | BG12: {=IF(A12="","",( IFERROR((O12/ INDEX(er!$D$3:$D$75,MATCH(1, (er!$A$3:$A$75=$BG$2)*(er!$C$3:$C$75=Q12), 0)))*BE12,"")))} -> 204.0438 | BH12: =IF(A12="","",( IF(B12="Snapchat Rep", IF(A12="","",(P12-BF12)),-BF12))) -> -285049.19 | BI12: {=IFERROR(INDEX('Com&tax'!$F$2:$F$5, MATCH(1, ('Com&tax'!$A$2:$A$5=B12)*('Com&tax'!$B$2:$B$5=Y12), 0)),0)} -> 0.049 | BJ12: =IF(A12="","",( IFERROR((J12*(1-BE12))*BI12,0))) -> 79148.659 | BK12: {=IF(A12="","",( IFERROR((J12*(1-BE12))*BI12/INDEX(er!D:D, MATCH(Q12,er!C:C,0),1),0)))} -> 56.656163 | BL12: {=IFERROR(INDEX('Com&tax'!$G$2:$G$5, MATCH(1, ('Com&tax'!$A$2:$A$5=B12)*('Com&tax'!$B$2:$B$5=Y12), 0)),0)} -> 0.1575 | BM12: =IF(A12="","",( IFERROR((J12*(1-BE12))*BL12,0))) -> 254406.4 | BN12: {=IF(A12="","",( IFERROR((J12*(1-BE12))*BL12/INDEX(er!D:D, MATCH(Q12,er!C:C,0),1),0)))} -> 182.10909 | BO12: {=IFERROR(INDEX('Com&tax'!$H$2:$H$5, MATCH(1, ('Com&tax'!$A$2:$A$5=B12)*('Com&tax'!$B$2:$B$5=Y12), 0)),0)} -> 0.07 | BP12: =IF(A12="","",( IFERROR(J12*BO12,0))) -> 133022.96 | BQ12: {=IF(A12="","",( IFERROR(J12*BO12/INDEX(er!D:D, MATCH(Q12,er!C:C,0),1),0)))} -> 95.220441 | BR12: {=IFERROR(INDEX('Com&tax'!$F$2:$F$5, MATCH(1, ('Com&tax'!$A$2:$A$5=B12)*('Com&tax'!$D$2:$D$5=H12), 0)),0)} -> 0.049 | BS12: =IF(A12="","",( IFERROR((J12*(1-BE12))*BR12,0))) -> 79148.659 | BT12: {=IF(A12="","",( IFERROR((J12*(1-BE12))*BR12/INDEX(er!D:D, MATCH(Q12,er!C:C,0),1),0)))} -> 56.656163 | BU12: {=IFERROR(INDEX('Com&tax'!$G$2:$G$5, MATCH(1, ('Com&tax'!$A$2:$A$5=B12)*('Com&tax'!$D$2:$D$5=H12), 0)),0)} -> 0.1575 | BV12: =IF(A12="","",( IFERROR((J12*(1-BE12))*BU12,0))) -> 254406.4 | BW12: {=IF(A12="","",( IFERROR((J12*(1-BE12))*BU12/INDEX(er!D:D, MATCH(Q12,er!C:C,0),1),0)))} -> 182.10909 | BX12: {=IFERROR(INDEX('Com&tax'!$H$2:$H$5, MATCH(1, ('Com&tax'!$A$2:$A$5=B12)*('Com&tax'!$D$2:$D$5=H12), 0)),0)} -> 0.07 | BY12: =IF(A12="","",( IFERROR(J12*BX12,0))) -> 133022.96 | BZ12: {=IF(A12="","",( IFERROR(J12*BX12/INDEX(er!D:D, MATCH(Q12,er!C:C,0),1),0)))} -> 95.220441 | CA12: {=IF(A12="","",( IFERROR(1-((P12/ INDEX(er!$D$3:$D$75,MATCH(1, (er!$A$3:$A$75=$BG$2)*(er!$C$3:$C$75=Q12), 0)) / (J12/ INDEX(er!$D$3:$D$75,MATCH(1, (er!$A$3:$A$75=$BG$2)*(er!$C$3:$C$75=L12), 0))))),"")))} -> 0.39552496 | CB12: =IF(AB12="","",1-AD12/AB12) -> 0.395525 | CC12: =IF(AND(CA12="", CB12=""), "", CA12-CB12) -> -3.6835747e-08 | CD12: =BJ12+BM12-BS12-BV12 -> 0 | CE12: =BK12+BN12-BT12-BW12 -> 0 | CF12: =AJ12-CE12 -> 0 | CG12: =IF(OR(BE12="", AE12=""), "Miss", IF(ABS(AE12/100-AK12)<0.005, "OK", "Incorrect")) -> OK | CI12: OK | CK12: 0 | CL12: =(AI12+CK12)/INDEX(er!D:D,MATCH(AC12,er!C:C,0),1) -> 5.0107373e-05 | CN12: =CK12/INDEX(er!D:D,MATCH(AC12,er!C:C,0),1) -> 0
A13: T2993848 | B13: Twitter Rep | C13: IMS | D13: AR_Media Company_BALANZ CAPITAL VALORES Argentina_SMB-X ARG - Balanz - Enero 2025 | G13: Argentina | H13: Aleph Argentina | I13: Argentina | J13: 81926.99 | K13: 81926.99 | L13: ARS | M13: 81926.99 | N13: ARS | O13: 81926.99 | P13: 49522.82 | Q13: ARS | R13: Mexico | U13: 0 | V13: 2026-02 | W13: February/2026 | X13: IMS | Y13: Argentina | Z13: Mexico | AA13: ARS | AB13: 81926.99 | AC13: ARS | AD13: 49522.81 | AE13: 39.55 | AF13: OK | AG13: 0 | AH13: 0 | AI13: 0.01 | AJ13: 0 | AK13: 0.39552497 | AL13: OK | AM13: 10573656 | AO13: Miss | AP13: Miss | AR13: Miss | AT13: Miss | AU13: 81926.99 | AV13: 57 | AW13: Miss | AX13: 81926.99 | AY13: 58.64 | AZ13: ARS | BA13: 49522.81 | BB13: OK | BC13: 0.01 | BD13: 0 | BE13: {=IFERROR(INDEX('Com&tax'!$E$2:$E$5, MATCH(1, ('Com&tax'!$A$2:$A$5=B13)*('Com&tax'!$B$2:$B$5=G13), 0)),"")} -> 0.15 | BF13: =IF(A13="","",( IFERROR(O13*BE13,""))) -> 12289.049 | BG13: {=IF(A13="","",( IFERROR((O13/ INDEX(er!$D$3:$D$75,MATCH(1, (er!$A$3:$A$75=$BG$2)*(er!$C$3:$C$75=Q13), 0)))*BE13,"")))} -> 8.7967419 | BH13: =IF(A13="","",( IF(B13="Snapchat Rep", IF(A13="","",(P13-BF13)),-BF13))) -> -12289.049 | BI13: {=IFERROR(INDEX('Com&tax'!$F$2:$F$5, MATCH(1, ('Com&tax'!$A$2:$A$5=B13)*('Com&tax'!$B$2:$B$5=Y13), 0)),0)} -> 0.049 | BJ13: =IF(A13="","",( IFERROR((J13*(1-BE13))*BI13,0))) -> 3412.2591 | BK13: {=IF(A13="","",( IFERROR((J13*(1-BE13))*BI13/INDEX(er!D:D, MATCH(Q13,er!C:C,0),1),0)))} -> 2.442562 | BL13: {=IFERROR(INDEX('Com&tax'!$G$2:$G$5, MATCH(1, ('Com&tax'!$A$2:$A$5=B13)*('Com&tax'!$B$2:$B$5=Y13), 0)),0)} -> 0.1575 | BM13: =IF(A13="","",( IFERROR((J13*(1-BE13))*BL13,0))) -> 10967.976 | BN13: {=IF(A13="","",( IFERROR((J13*(1-BE13))*BL13/INDEX(er!D:D, MATCH(Q13,er!C:C,0),1),0)))} -> 7.8510922 | BO13: {=IFERROR(INDEX('Com&tax'!$H$2:$H$5, MATCH(1, ('Com&tax'!$A$2:$A$5=B13)*('Com&tax'!$B$2:$B$5=Y13), 0)),0)} -> 0.07 | BP13: =IF(A13="","",( IFERROR(J13*BO13,0))) -> 5734.8893 | BQ13: {=IF(A13="","",( IFERROR(J13*BO13/INDEX(er!D:D, MATCH(Q13,er!C:C,0),1),0)))} -> 4.1051462 | BR13: {=IFERROR(INDEX('Com&tax'!$F$2:$F$5, MATCH(1, ('Com&tax'!$A$2:$A$5=B13)*('Com&tax'!$D$2:$D$5=H13), 0)),0)} -> 0.049 | BS13: =IF(A13="","",( IFERROR((J13*(1-BE13))*BR13,0))) -> 3412.2591 | BT13: {=IF(A13="","",( IFERROR((J13*(1-BE13))*BR13/INDEX(er!D:D, MATCH(Q13,er!C:C,0),1),0)))} -> 2.442562 | BU13: {=IFERROR(INDEX('Com&tax'!$G$2:$G$5, MATCH(1, ('Com&tax'!$A$2:$A$5=B13)*('Com&tax'!$D$2:$D$5=H13), 0)),0)} -> 0.1575 | BV13: =IF(A13="","",( IFERROR((J13*(1-BE13))*BU13,0))) -> 10967.976 | BW13: {=IF(A13="","",( IFERROR((J13*(1-BE13))*BU13/INDEX(er!D:D, MATCH(Q13,er!C:C,0),1),0)))} -> 7.8510922 | BX13: {=IFERROR(INDEX('Com&tax'!$H$2:$H$5, MATCH(1, ('Com&tax'!$A$2:$A$5=B13)*('Com&tax'!$D$2:$D$5=H13), 0)),0)} -> 0.07 | BY13: =IF(A13="","",( IFERROR(J13*BX13,0))) -> 5734.8893 | BZ13: {=IF(A13="","",( IFERROR(J13*BX13/INDEX(er!D:D, MATCH(Q13,er!C:C,0),1),0)))} -> 4.1051462 | CA13: {=IF(A13="","",( IFERROR(1-((P13/ INDEX(er!$D$3:$D$75,MATCH(1, (er!$A$3:$A$75=$BG$2)*(er!$C$3:$C$75=Q13), 0)) / (J13/ INDEX(er!$D$3:$D$75,MATCH(1, (er!$A$3:$A$75=$BG$2)*(er!$C$3:$C$75=L13), 0))))),"")))} -> 0.39552497 | CB13: =IF(AB13="","",1-AD13/AB13) -> 0.39552509 | CC13: =IF(AND(CA13="", CB13=""), "", CA13-CB13) -> -1.220599e-07 | CD13: =BJ13+BM13-BS13-BV13 -> 0 | CE13: =BK13+BN13-BT13-BW13 -> 0 | CF13: =AJ13-CE13 -> 0 | CG13: =IF(OR(BE13="", AE13=""), "Miss", IF(ABS(AE13/100-AK13)<0.005, "OK", "Incorrect")) -> OK | CI13: OK | CK13: 0 | CL13: =(AI13+CK13)/INDEX(er!D:D,MATCH(AC13,er!C:C,0),1) -> 7.1581961e-06 | CN13: =CK13/INDEX(er!D:D,MATCH(AC13,er!C:C,0),1) -> 0
A14: T3025948 | B14: Twitter Billing | C14: IMS | D14: AR_Media Company_RAPPI ARG S.A.S._T3025948 - Rappi Argentina 2025 LInea de Credito - 19/02/2025 | G14: Argentina | H14: Aleph Argentina | I14: Argentina | J14: 16336338 | K14: 16336338 | L14: ARS | M14: 16336338 | N14: ARS | O14: 16336338 | P14: 10781901 | Q14: ARS | R14: Mexico | U14: 0 | V14: 2026-02 | W14: February/2026 | X14: IMS | Y14: Argentina | Z14: Mexico | AA14: ARS | AB14: 16336338 | AC14: ARS | AD14: 10782310 | AE14: 34 | AF14: OK | AG14: 0 | AH14: 0 | AI14: -408.41 | AJ14: -0.29 | AK14: 0.340005 | AL14: OK | AM14: 10573738 | AO14: Miss | AP14: Miss | AR14: Miss | AT14: Miss | AU14: 16336338 | AV14: 11692 | AW14: Miss | AX14: 16336338 | AY14: 11693.87 | AZ14: ARS | BA14: 10782310 | BB14: OK | BC14: -408.41 | BD14: -0.29 | BE14: {=IFERROR(INDEX('Com&tax'!$E$2:$E$5, MATCH(1, ('Com&tax'!$A$2:$A$5=B14)*('Com&tax'!$B$2:$B$5=G14), 0)),"")} -> 0.15 | BF14: =IF(A14="","",( IFERROR(O14*BE14,""))) -> 2450450.7 | BG14: {=IF(A14="","",( IFERROR((O14/ INDEX(er!$D$3:$D$75,MATCH(1, (er!$A$3:$A$75=$BG$2)*(er!$C$3:$C$75=Q14), 0)))*BE14,"")))} -> 1754.0807 | BH14: =IF(A14="","",( IF(B14="Snapchat Rep", IF(A14="","",(P14-BF14)),-BF14))) -> -2450450.7 | BI14: {=IFERROR(INDEX('Com&tax'!$F$2:$F$5, MATCH(1, ('Com&tax'!$A$2:$A$5=B14)*('Com&tax'!$B$2:$B$5=Y14), 0)),0)} -> 0.049 | BJ14: =IF(A14="","",( IFERROR((J14*(1-BE14))*BI14,0))) -> 680408.48 | BK14: {=IF(A14="","",( IFERROR((J14*(1-BE14))*BI14/INDEX(er!D:D, MATCH(Q14,er!C:C,0),1),0)))} -> 487.04973 | BL14: {=IFERROR(INDEX('Com&tax'!$G$2:$G$5, MATCH(1, ('Com&tax'!$A$2:$A$5=B14)*('Com&tax'!$B$2:$B$5=Y14), 0)),0)} -> 0.1575 | BM14: =IF(A14="","",( IFERROR((J14*(1-BE14))*BL14,0))) -> 2187027.2 | BN14: {=IF(A14="","",( IFERROR((J14*(1-BE14))*BL14/INDEX(er!D:D, MATCH(Q14,er!C:C,0),1),0)))} -> 1565.517 | BO14: {=IFERROR(INDEX('Com&tax'!$H$2:$H$5, MATCH(1, ('Com&tax'!$A$2:$A$5=B14)*('Com&tax'!$B$2:$B$5=Y14), 0)),0)} -> 0 | BP14: =IF(A14="","",( IFERROR(J14*BO14,0))) -> 0 | BQ14: {=IF(A14="","",( IFERROR(J14*BO14/INDEX(er!D:D, MATCH(Q14,er!C:C,0),1),0)))} -> 0 | BR14: {=IFERROR(INDEX('Com&tax'!$F$2:$F$5, MATCH(1, ('Com&tax'!$A$2:$A$5=B14)*('Com&tax'!$D$2:$D$5=H14), 0)),0)} -> 0.049 | BS14: =IF(A14="","",( IFERROR((J14*(1-BE14))*BR14,0))) -> 680408.48 | BT14: {=IF(A14="","",( IFERROR((J14*(1-BE14))*BR14/INDEX(er!D:D, MATCH(Q14,er!C:C,0),1),0)))} -> 487.04973 | BU14: {=IFERROR(INDEX('Com&tax'!$G$2:$G$5, MATCH(1, ('Com&tax'!$A$2:$A$5=B14)*('Com&tax'!$D$2:$D$5=H14), 0)),0)} -> 0.1575 | BV14: =IF(A14="","",( IFERROR((J14*(1-BE14))*BU14,0))) -> 2187027.2 | BW14: {=IF(A14="","",( IFERROR((J14*(1-BE14))*BU14/INDEX(er!D:D, MATCH(Q14,er!C:C,0),1),0)))} -> 1565.517 | BX14: {=IFERROR(INDEX('Com&tax'!$H$2:$H$5, MATCH(1, ('Com&tax'!$A$2:$A$5=B14)*('Com&tax'!$D$2:$D$5=H14), 0)),0)} -> 0 | BY14: =IF(A14="","",( IFERROR(J14*BX14,0))) -> 0 | BZ14: {=IF(A14="","",( IFERROR(J14*BX14/INDEX(er!D:D, MATCH(Q14,er!C:C,0),1),0)))} -> 0 | CA14: {=IF(A14="","",( IFERROR(1-((P14/ INDEX(er!$D$3:$D$75,MATCH(1, (er!$A$3:$A$75=$BG$2)*(er!$C$3:$C$75=Q14), 0)) / (J14/ INDEX(er!$D$3:$D$75,MATCH(1, (er!$A$3:$A$75=$BG$2)*(er!$C$3:$C$75=L14), 0))))),"")))} -> 0.340005 | CB14: =IF(AB14="","",1-AD14/AB14) -> 0.33998 | CC14: =IF(AND(CA14="", CB14=""), "", CA14-CB14) -> 2.5000095e-05 | CD14: =BJ14+BM14-BS14-BV14 -> 0 | CE14: =BK14+BN14-BT14-BW14 -> 0 | CF14: =AJ14-CE14 -> -0.29 | CG14: =IF(OR(BE14="", AE14=""), "Miss", IF(ABS(AE14/100-AK14)<0.005, "OK", "Incorrect")) -> OK | CI14: OK | CK14: 0 | CL14: =(AI14+CK14)/INDEX(er!D:D,MATCH(AC14,er!C:C,0),1) -> -0.29234789 | CN14: =CK14/INDEX(er!D:D,MATCH(AC14,er!C:C,0),1) -> 0
A15: T3094969 | B15: Twitter Rep | C15: IMS | D15: AR_Media Company_Industrial And Comercial Bank Of China - Argentina_X - YOY - Branding - Tácticos | G15: Argentina | H15: Aleph Argentina | I15: Argentina | J15: 610190.21 | K15: 610190.21 | L15: ARS | M15: 610190.21 | N15: ARS | O15: 610190.21 | P15: 368844.75 | Q15: ARS | R15: Mexico | U15: 0 | V15: 2026-02 | W15: February/2026 | X15: IMS | Y15: Argentina | Z15: Mexico | AA15: ARS | AB15: 610190.21 | AC15: ARS | AD15: 368844.72 | AE15: 39.55 | AF15: OK | AG15: 0 | AH15: 0 | AI15: 0.03 | AJ15: 0 | AK15: 0.39552496 | AL15: OK | AM15: 10573701 | AN15: Manually insert Revenue,Manually insert Cogs | AO15: Miss | AP15: Miss | AR15: Miss | AT15: Miss | AU15: 610190.21 | AV15: 435 | AW15: Miss | AX15: 610190.21 | AY15: 436.79 | AZ15: ARS | BA15: 368844.73 | BB15: OK | BC15: 0.02 | BD15: 0 | BE15: {=IFERROR(INDEX('Com&tax'!$E$2:$E$5, MATCH(1, ('Com&tax'!$A$2:$A$5=B15)*('Com&tax'!$B$2:$B$5=G15), 0)),"")} -> 0.15 | BF15: =IF(A15="","",( IFERROR(O15*BE15,""))) -> 91528.531 | BG15: {=IF(A15="","",( IFERROR((O15/ INDEX(er!$D$3:$D$75,MATCH(1, (er!$A$3:$A$75=$BG$2)*(er!$C$3:$C$75=Q15), 0)))*BE15,"")))} -> 65.517918 | BH15: =IF(A15="","",( IF(B15="Snapchat Rep", IF(A15="","",(P15-BF15)),-BF15))) -> -91528.531 | BI15: {=IFERROR(INDEX('Com&tax'!$F$2:$F$5, MATCH(1, ('Com&tax'!$A$2:$A$5=B15)*('Com&tax'!$B$2:$B$5=Y15), 0)),0)} -> 0.049 | BJ15: =IF(A15="","",( IFERROR((J15*(1-BE15))*BI15,0))) -> 25414.422 | BK15: {=IF(A15="","",( IFERROR((J15*(1-BE15))*BI15/INDEX(er!D:D, MATCH(Q15,er!C:C,0),1),0)))} -> 18.192142 | BL15: {=IFERROR(INDEX('Com&tax'!$G$2:$G$5, MATCH(1, ('Com&tax'!$A$2:$A$5=B15)*('Com&tax'!$B$2:$B$5=Y15), 0)),0)} -> 0.1575 | BM15: =IF(A15="","",( IFERROR((J15*(1-BE15))*BL15,0))) -> 81689.214 | BN15: {=IF(A15="","",( IFERROR((J15*(1-BE15))*BL15/INDEX(er!D:D, MATCH(Q15,er!C:C,0),1),0)))} -> 58.474742 | BO15: {=IFERROR(INDEX('Com&tax'!$H$2:$H$5, MATCH(1, ('Com&tax'!$A$2:$A$5=B15)*('Com&tax'!$B$2:$B$5=Y15), 0)),0)} -> 0.07 | BP15: =IF(A15="","",( IFERROR(J15*BO15,0))) -> 42713.315 | BQ15: {=IF(A15="","",( IFERROR(J15*BO15/INDEX(er!D:D, MATCH(Q15,er!C:C,0),1),0)))} -> 30.575028 | BR15: {=IFERROR(INDEX('Com&tax'!$F$2:$F$5, MATCH(1, ('Com&tax'!$A$2:$A$5=B15)*('Com&tax'!$D$2:$D$5=H15), 0)),0)} -> 0.049 | BS15: =IF(A15="","",( IFERROR((J15*(1-BE15))*BR15,0))) -> 25414.422 | BT15: {=IF(A15="","",( IFERROR((J15*(1-BE15))*BR15/INDEX(er!D:D, MATCH(Q15,er!C:C,0),1),0)))} -> 18.192142 | BU15: {=IFERROR(INDEX('Com&tax'!$G$2:$G$5, MATCH(1, ('Com&tax'!$A$2:$A$5=B15)*('Com&tax'!$D$2:$D$5=H15), 0)),0)} -> 0.1575 | BV15: =IF(A15="","",( IFERROR((J15*(1-BE15))*BU15,0))) -> 81689.214 | BW15: {=IF(A15="","",( IFERROR((J15*(1-BE15))*BU15/INDEX(er!D:D, MATCH(Q15,er!C:C,0),1),0)))} -> 58.474742 | BX15: {=IFERROR(INDEX('Com&tax'!$H$2:$H$5, MATCH(1, ('Com&tax'!$A$2:$A$5=B15)*('Com&tax'!$D$2:$D$5=H15), 0)),0)} -> 0.07 | BY15: =IF(A15="","",( IFERROR(J15*BX15,0))) -> 42713.315 | BZ15: {=IF(A15="","",( IFERROR(J15*BX15/INDEX(er!D:D, MATCH(Q15,er!C:C,0),1),0)))} -> 30.575028 | CA15: {=IF(A15="","",( IFERROR(1-((P15/ INDEX(er!$D$3:$D$75,MATCH(1, (er!$A$3:$A$75=$BG$2)*(er!$C$3:$C$75=Q15), 0)) / (J15/ INDEX(er!$D$3:$D$75,MATCH(1, (er!$A$3:$A$75=$BG$2)*(er!$C$3:$C$75=L15), 0))))),"")))} -> 0.39552496 | CB15: =IF(AB15="","",1-AD15/AB15) -> 0.39552501 | CC15: =IF(AND(CA15="", CB15=""), "", CA15-CB15) -> -4.9164997e-08 | CD15: =BJ15+BM15-BS15-BV15 -> 0 | CE15: =BK15+BN15-BT15-BW15 -> 0 | CF15: =AJ15-CE15 -> 0 | CG15: =IF(OR(BE15="", AE15=""), "Miss", IF(ABS(AE15/100-AK15)<0.005, "OK", "Incorrect")) -> OK | CI15: OK | CK15: 0 | CL15: =(AI15+CK15)/INDEX(er!D:D,MATCH(AC15,er!C:C,0),1) -> 2.1474588e-05 | CN15: =CK15/INDEX(er!D:D,MATCH(AC15,er!C:C,0),1) -> 0
A16: T3101174 | B16: Twitter Rep | C16: IMS | D16: AR_Media Company_Play Digital Argentina_TW - MODO - Promo Día | G16: Argentina | H16: Aleph Argentina | I16: Argentina | J16: 2007664.5 | K16: 2007664.5 | L16: ARS | M16: 2007664.5 | N16: ARS | O16: 2007664.5 | P16: 1213583.1 | Q16: ARS | R16: Mexico | U16: 0 | V16: 2026-02 | W16: February/2026 | X16: IMS | Y16: Argentina | Z16: Mexico | AA16: ARS | AB16: 2007664.5 | AC16: ARS | AD16: 1213583 | AE16: 39.55 | AF16: OK | AG16: 0 | AH16: 0 | AI16: 0.08 | AJ16: 0 | AK16: 0.39552496 | AL16: OK | AM16: 10573714 | AO16: Miss | AP16: Miss | AR16: Miss | AT16: Miss | AU16: 2007664.5 | AV16: 1435 | AW16: Miss | AX16: 2007664.5 | AY16: 1437.13 | AZ16: ARS | BA16: 1213583 | BB16: OK | BC16: 0.08 | BD16: 0 | BE16: {=IFERROR(INDEX('Com&tax'!$E$2:$E$5, MATCH(1, ('Com&tax'!$A$2:$A$5=B16)*('Com&tax'!$B$2:$B$5=G16), 0)),"")} -> 0.15 | BF16: =IF(A16="","",( IFERROR(O16*BE16,""))) -> 301149.67 | BG16: {=IF(A16="","",( IFERROR((O16/ INDEX(er!$D$3:$D$75,MATCH(1, (er!$A$3:$A$75=$BG$2)*(er!$C$3:$C$75=Q16), 0)))*BE16,"")))} -> 215.56884 | BH16: =IF(A16="","",( IF(B16="Snapchat Rep", IF(A16="","",(P16-BF16)),-BF16))) -> -301149.67 | BI16: {=IFERROR(INDEX('Com&tax'!$F$2:$F$5, MATCH(1, ('Com&tax'!$A$2:$A$5=B16)*('Com&tax'!$B$2:$B$5=Y16), 0)),0)} -> 0.049 | BJ16: =IF(A16="","",( IFERROR((J16*(1-BE16))*BI16,0))) -> 83619.226 | BK16: {=IF(A16="","",( IFERROR((J16*(1-BE16))*BI16/INDEX(er!D:D, MATCH(Q16,er!C:C,0),1),0)))} -> 59.856282 | BL16: {=IFERROR(INDEX('Com&tax'!$G$2:$G$5, MATCH(1, ('Com&tax'!$A$2:$A$5=B16)*('Com&tax'!$B$2:$B$5=Y16), 0)),0)} -> 0.1575 | BM16: =IF(A16="","",( IFERROR((J16*(1-BE16))*BL16,0))) -> 268776.08 | BN16: {=IF(A16="","",( IFERROR((J16*(1-BE16))*BL16/INDEX(er!D:D, MATCH(Q16,er!C:C,0),1),0)))} -> 192.39519 | BO16: {=IFERROR(INDEX('Com&tax'!$H$2:$H$5, MATCH(1, ('Com&tax'!$A$2:$A$5=B16)*('Com&tax'!$B$2:$B$5=Y16), 0)),0)} -> 0.07 | BP16: =IF(A16="","",( IFERROR(J16*BO16,0))) -> 140536.51 | BQ16: {=IF(A16="","",( IFERROR(J16*BO16/INDEX(er!D:D, MATCH(Q16,er!C:C,0),1),0)))} -> 100.59879 | BR16: {=IFERROR(INDEX('Com&tax'!$F$2:$F$5, MATCH(1, ('Com&tax'!$A$2:$A$5=B16)*('Com&tax'!$D$2:$D$5=H16), 0)),0)} -> 0.049 | BS16: =IF(A16="","",( IFERROR((J16*(1-BE16))*BR16,0))) -> 83619.226 | BT16: {=IF(A16="","",( IFERROR((J16*(1-BE16))*BR16/INDEX(er!D:D, MATCH(Q16,er!C:C,0),1),0)))} -> 59.856282 | BU16: {=IFERROR(INDEX('Com&tax'!$G$2:$G$5, MATCH(1, ('Com&tax'!$A$2:$A$5=B16)*('Com&tax'!$D$2:$D$5=H16), 0)),0)} -> 0.1575 | BV16: =IF(A16="","",( IFERROR((J16*(1-BE16))*BU16,0))) -> 268776.08 | BW16: {=IF(A16="","",( IFERROR((J16*(1-BE16))*BU16/INDEX(er!D:D, MATCH(Q16,er!C:C,0),1),0)))} -> 192.39519 | BX16: {=IFERROR(INDEX('Com&tax'!$H$2:$H$5, MATCH(1, ('Com&tax'!$A$2:$A$5=B16)*('Com&tax'!$D$2:$D$5=H16), 0)),0)} -> 0.07 | BY16: =IF(A16="","",( IFERROR(J16*BX16,0))) -> 140536.51 | BZ16: {=IF(A16="","",( IFERROR(J16*BX16/INDEX(er!D:D, MATCH(Q16,er!C:C,0),1),0)))} -> 100.59879 | CA16: {=IF(A16="","",( IFERROR(1-((P16/ INDEX(er!$D$3:$D$75,MATCH(1, (er!$A$3:$A$75=$BG$2)*(er!$C$3:$C$75=Q16), 0)) / (J16/ INDEX(er!$D$3:$D$75,MATCH(1, (er!$A$3:$A$75=$BG$2)*(er!$C$3:$C$75=L16), 0))))),"")))} -> 0.39552496 | CB16: =IF(AB16="","",1-AD16/AB16) -> 0.395525 | CC16: =IF(AND(CA16="", CB16=""), "", CA16-CB16) -> -3.9847296e-08 | CD16: =BJ16+BM16-BS16-BV16 -> 0 | CE16: =BK16+BN16-BT16-BW16 -> 0 | CF16: =AJ16-CE16 -> 0 | CG16: =IF(OR(BE16="", AE16=""), "Miss", IF(ABS(AE16/100-AK16)<0.005, "OK", "Incorrect")) -> OK | CI16: OK | CK16: 0 | CL16: =(AI16+CK16)/INDEX(er!D:D,MATCH(AC16,er!C:C,0),1) -> 5.7265569e-05 | CN16: =CK16/INDEX(er!D:D,MATCH(AC16,er!C:C,0),1) -> 0
A17: T3163143 | B17: Twitter Rep | C17: IMS | D17: AR_Media Company_Hipódromo Argentino de Palermo S.A_AR00380261-X-Betfun-Takeover-Q1 26 | G17: Argentina | H17: Aleph Argentina | I17: Argentina | J17: 3110400 | K17: 3110400 | L17: ARS | M17: 3110400 | N17: ARS | O17: 3110400 | P17: 1880159.2 | Q17: ARS | R17: Mexico | U17: 0 | V17: 2026-02 | W17: February/2026 | X17: IMS | Y17: Argentina | Z17: Mexico | AA17: ARS | AB17: 3110400 | AC17: ARS | AD17: 1880159 | AE17: 39.55 | AF17: OK | AG17: 0 | AH17: 0 | AI17: 0.12 | AJ17: 0 | AK17: 0.39552496 | AL17: OK | AM17: 10573720 | AO17: Miss | AP17: Miss | AR17: Miss | AT17: Miss | AU17: 3110400 | AV17: 2224 | AW17: Miss | AX17: 3110400 | AY17: 2226.49 | AZ17: ARS | BA17: 1880159 | BB17: OK | BC17: 0.12 | BD17: 0 | BE17: {=IFERROR(INDEX('Com&tax'!$E$2:$E$5, MATCH(1, ('Com&tax'!$A$2:$A$5=B17)*('Com&tax'!$B$2:$B$5=G17), 0)),"")} -> 0.15 | BF17: =IF(A17="","",( IFERROR(O17*BE17,""))) -> 466560 | BG17: {=IF(A17="","",( IFERROR((O17/ INDEX(er!$D$3:$D$75,MATCH(1, (er!$A$3:$A$75=$BG$2)*(er!$C$3:$C$75=Q17), 0)))*BE17,"")))} -> 333.9728 | BH17: =IF(A17="","",( IF(B17="Snapchat Rep", IF(A17="","",(P17-BF17)),-BF17))) -> -466560 | BI17: {=IFERROR(INDEX('Com&tax'!$F$2:$F$5, MATCH(1, ('Com&tax'!$A$2:$A$5=B17)*('Com&tax'!$B$2:$B$5=Y17), 0)),0)} -> 0.049 | BJ17: =IF(A17="","",( IFERROR((J17*(1-BE17))*BI17,0))) -> 129548.16 | BK17: {=IF(A17="","",( IFERROR((J17*(1-BE17))*BI17/INDEX(er!D:D, MATCH(Q17,er!C:C,0),1),0)))} -> 92.733114 | BL17: {=IFERROR(INDEX('Com&tax'!$G$2:$G$5, MATCH(1, ('Com&tax'!$A$2:$A$5=B17)*('Com&tax'!$B$2:$B$5=Y17), 0)),0)} -> 0.1575 | BM17: =IF(A17="","",( IFERROR((J17*(1-BE17))*BL17,0))) -> 416404.8 | BN17: {=IF(A17="","",( IFERROR((J17*(1-BE17))*BL17/INDEX(er!D:D, MATCH(Q17,er!C:C,0),1),0)))} -> 298.07072 | BO17: {=IFERROR(INDEX('Com&tax'!$H$2:$H$5, MATCH(1, ('Com&tax'!$A$2:$A$5=B17)*('Com&tax'!$B$2:$B$5=Y17), 0)),0)} -> 0.07 | BP17: =IF(A17="","",( IFERROR(J17*BO17,0))) -> 217728 | BQ17: {=IF(A17="","",( IFERROR(J17*BO17/INDEX(er!D:D, MATCH(Q17,er!C:C,0),1),0)))} -> 155.85397 | BR17: {=IFERROR(INDEX('Com&tax'!$F$2:$F$5, MATCH(1, ('Com&tax'!$A$2:$A$5=B17)*('Com&tax'!$D$2:$D$5=H17), 0)),0)} -> 0.049 | BS17: =IF(A17="","",( IFERROR((J17*(1-BE17))*BR17,0))) -> 129548.16 | BT17: {=IF(A17="","",( IFERROR((J17*(1-BE17))*BR17/INDEX(er!D:D, MATCH(Q17,er!C:C,0),1),0)))} -> 92.733114 | BU17: {=IFERROR(INDEX('Com&tax'!$G$2:$G$5, MATCH(1, ('Com&tax'!$A$2:$A$5=B17)*('Com&tax'!$D$2:$D$5=H17), 0)),0)} -> 0.1575 | BV17: =IF(A17="","",( IFERROR((J17*(1-BE17))*BU17,0))) -> 416404.8 | BW17: {=IF(A17="","",( IFERROR((J17*(1-BE17))*BU17/INDEX(er!D:D, MATCH(Q17,er!C:C,0),1),0)))} -> 298.07072 | BX17: {=IFERROR(INDEX('Com&tax'!$H$2:$H$5, MATCH(1, ('Com&tax'!$A$2:$A$5=B17)*('Com&tax'!$D$2:$D$5=H17), 0)),0)} -> 0.07 | BY17: =IF(A17="","",( IFERROR(J17*BX17,0))) -> 217728 | BZ17: {=IF(A17="","",( IFERROR(J17*BX17/INDEX(er!D:D, MATCH(Q17,er!C:C,0),1),0)))} -> 155.85397 | CA17: {=IF(A17="","",( IFERROR(1-((P17/ INDEX(er!$D$3:$D$75,MATCH(1, (er!$A$3:$A$75=$BG$2)*(er!$C$3:$C$75=Q17), 0)) / (J17/ INDEX(er!$D$3:$D$75,MATCH(1, (er!$A$3:$A$75=$BG$2)*(er!$C$3:$C$75=L17), 0))))),"")))} -> 0.39552496 | CB17: =IF(AB17="","",1-AD17/AB17) -> 0.395525 | CC17: =IF(AND(CA17="", CB17=""), "", CA17-CB17) -> -3.8580247e-08 | CD17: =BJ17+BM17-BS17-BV17 -> 0 | CE17: =BK17+BN17-BT17-BW17 -> 0 | CF17: =AJ17-CE17 -> 0 | CG17: =IF(OR(BE17="", AE17=""), "Miss", IF(ABS(AE17/100-AK17)<0.005, "OK", "Incorrect")) -> OK | CI17: OK | CK17: 0 | CL17: =(AI17+CK17)/INDEX(er!D:D,MATCH(AC17,er!C:C,0),1) -> 8.5898354e-05 | CN17: =CK17/INDEX(er!D:D,MATCH(AC17,er!C:C,0),1) -> 0
A18: T3163157 | B18: Twitter Rep | C18: IMS | D18: AR_Media Company_Hipódromo Argentino de Palermo S.A_AR00380263-X-Hipódromo Sala-Takeover-26 | G18: Argentina | H18: Aleph Argentina | I18: Argentina | J18: 3110400 | K18: 3110400 | L18: ARS | M18: 3110400 | N18: ARS | O18: 3110400 | P18: 1880159.2 | Q18: ARS | R18: Mexico | U18: 0 | V18: 2026-02 | W18: February/2026 | X18: IMS | Y18: Argentina | Z18: Mexico | AA18: ARS | AB18: 3110400 | AC18: ARS | AD18: 1880159 | AE18: 39.55 | AF18: OK | AG18: 0 | AH18: 0 | AI18: 0.12 | AJ18: 0 | AK18: 0.39552496 | AL18: OK | AM18: 10573735 | AO18: Miss | AP18: Miss | AR18: Miss | AT18: Miss | AU18: 3110400 | AV18: 2224 | AW18: Miss | AX18: 3110400 | AY18: 2226.49 | AZ18: ARS | BA18: 1880159 | BB18: OK | BC18: 0.12 | BD18: 0 | BE18: {=IFERROR(INDEX('Com&tax'!$E$2:$E$5, MATCH(1, ('Com&tax'!$A$2:$A$5=B18)*('Com&tax'!$B$2:$B$5=G18), 0)),"")} -> 0.15 | BF18: =IF(A18="","",( IFERROR(O18*BE18,""))) -> 466560 | BG18: {=IF(A18="","",( IFERROR((O18/ INDEX(er!$D$3:$D$75,MATCH(1, (er!$A$3:$A$75=$BG$2)*(er!$C$3:$C$75=Q18), 0)))*BE18,"")))} -> 333.9728 | BH18: =IF(A18="","",( IF(B18="Snapchat Rep", IF(A18="","",(P18-BF18)),-BF18))) -> -466560 | BI18: {=IFERROR(INDEX('Com&tax'!$F$2:$F$5, MATCH(1, ('Com&tax'!$A$2:$A$5=B18)*('Com&tax'!$B$2:$B$5=Y18), 0)),0)} -> 0.049 | BJ18: =IF(A18="","",( IFERROR((J18*(1-BE18))*BI18,0))) -> 129548.16 | BK18: {=IF(A18="","",( IFERROR((J18*(1-BE18))*BI18/INDEX(er!D:D, MATCH(Q18,er!C:C,0),1),0)))} -> 92.733114 | BL18: {=IFERROR(INDEX('Com&tax'!$G$2:$G$5, MATCH(1, ('Com&tax'!$A$2:$A$5=B18)*('Com&tax'!$B$2:$B$5=Y18), 0)),0)} -> 0.1575 | BM18: =IF(A18="","",( IFERROR((J18*(1-BE18))*BL18,0))) -> 416404.8 | BN18: {=IF(A18="","",( IFERROR((J18*(1-BE18))*BL18/INDEX(er!D:D, MATCH(Q18,er!C:C,0),1),0)))} -> 298.07072 | BO18: {=IFERROR(INDEX('Com&tax'!$H$2:$H$5, MATCH(1, ('Com&tax'!$A$2:$A$5=B18)*('Com&tax'!$B$2:$B$5=Y18), 0)),0)} -> 0.07 | BP18: =IF(A18="","",( IFERROR(J18*BO18,0))) -> 217728 | BQ18: {=IF(A18="","",( IFERROR(J18*BO18/INDEX(er!D:D, MATCH(Q18,er!C:C,0),1),0)))} -> 155.85397 | BR18: {=IFERROR(INDEX('Com&tax'!$F$2:$F$5, MATCH(1, ('Com&tax'!$A$2:$A$5=B18)*('Com&tax'!$D$2:$D$5=H18), 0)),0)} -> 0.049 | BS18: =IF(A18="","",( IFERROR((J18*(1-BE18))*BR18,0))) -> 129548.16 | BT18: {=IF(A18="","",( IFERROR((J18*(1-BE18))*BR18/INDEX(er!D:D, MATCH(Q18,er!C:C,0),1),0)))} -> 92.733114 | BU18: {=IFERROR(INDEX('Com&tax'!$G$2:$G$5, MATCH(1, ('Com&tax'!$A$2:$A$5=B18)*('Com&tax'!$D$2:$D$5=H18), 0)),0)} -> 0.1575 | BV18: =IF(A18="","",( IFERROR((J18*(1-BE18))*BU18,0))) -> 416404.8 | BW18: {=IF(A18="","",( IFERROR((J18*(1-BE18))*BU18/INDEX(er!D:D, MATCH(Q18,er!C:C,0),1),0)))} -> 298.07072 | BX18: {=IFERROR(INDEX('Com&tax'!$H$2:$H$5, MATCH(1, ('Com&tax'!$A$2:$A$5=B18)*('Com&tax'!$D$2:$D$5=H18), 0)),0)} -> 0.07 | BY18: =IF(A18="","",( IFERROR(J18*BX18,0))) -> 217728 | BZ18: {=IF(A18="","",( IFERROR(J18*BX18/INDEX(er!D:D, MATCH(Q18,er!C:C,0),1),0)))} -> 155.85397 | CA18: {=IF(A18="","",( IFERROR(1-((P18/ INDEX(er!$D$3:$D$75,MATCH(1, (er!$A$3:$A$75=$BG$2)*(er!$C$3:$C$75=Q18), 0)) / (J18/ INDEX(er!$D$3:$D$75,MATCH(1, (er!$A$3:$A$75=$BG$2)*(er!$C$3:$C$75=L18), 0))))),"")))} -> 0.39552496 | CB18: =IF(AB18="","",1-AD18/AB18) -> 0.395525 | CC18: =IF(AND(CA18="", CB18=""), "", CA18-CB18) -> -3.8580247e-08 | CD18: =BJ18+BM18-BS18-BV18 -> 0 | CE18: =BK18+BN18-BT18-BW18 -> 0 | CF18: =AJ18-CE18 -> 0 | CG18: =IF(OR(BE18="", AE18=""), "Miss", IF(ABS(AE18/100-AK18)<0.005, "OK", "Incorrect")) -> OK | CI18: OK | CK18: 0 | CL18: =(AI18+CK18)/INDEX(er!D:D,MATCH(AC18,er!C:C,0),1) -> 8.5898354e-05 | CN18: =CK18/INDEX(er!D:D,MATCH(AC18,er!C:C,0),1) -> 0
A19: T3163161 | B19: Twitter Billing | C19: IMS | D19: AR_Media Company_Mercado Libre Argentina_T3163161 - MLA | Double Dates 2026 | Takeovers - ORDEN N°1 | G19: Argentina | H19: Aleph Argentina | I19: Argentina | J19: 2304000 | K19: 2304000 | L19: ARS | M19: 2304000 | N19: ARS | O19: 2304000 | P19: 1520628.5 | Q19: ARS | R19: Mexico | U19: 0 | V19: 2026-02 | W19: February/2026 | X19: IMS | Y19: Argentina | Z19: Mexico | AA19: ARS | AB19: 2304000 | AC19: ARS | AD19: 1520686.1 | AE19: 34 | AF19: OK | AG19: 0 | AH19: 0 | AI19: -57.6 | AJ19: -0.04 | AK19: 0.340005 | AL19: OK | AM19: 10573724 | AO19: Miss | AP19: Miss | AR19: Miss | AT19: Miss | AU19: 2304000 | AV19: 1647 | AW19: Miss | AX19: 2304000 | AY19: 1649.25 | AZ19: ARS | BA19: 1520686.1 | BB19: OK | BC19: -57.6 | BD19: -0.04 | BE19: {=IFERROR(INDEX('Com&tax'!$E$2:$E$5, MATCH(1, ('Com&tax'!$A$2:$A$5=B19)*('Com&tax'!$B$2:$B$5=G19), 0)),"")} -> 0.15 | BF19: =IF(A19="","",( IFERROR(O19*BE19,""))) -> 345600 | BG19: {=IF(A19="","",( IFERROR((O19/ INDEX(er!$D$3:$D$75,MATCH(1, (er!$A$3:$A$75=$BG$2)*(er!$C$3:$C$75=Q19), 0)))*BE19,"")))} -> 247.38726 | BH19: =IF(A19="","",( IF(B19="Snapchat Rep", IF(A19="","",(P19-BF19)),-BF19))) -> -345600 | BI19: {=IFERROR(INDEX('Com&tax'!$F$2:$F$5, MATCH(1, ('Com&tax'!$A$2:$A$5=B19)*('Com&tax'!$B$2:$B$5=Y19), 0)),0)} -> 0.049 | BJ19: =IF(A19="","",( IFERROR((J19*(1-BE19))*BI19,0))) -> 95961.6 | BK19: {=IF(A19="","",( IFERROR((J19*(1-BE19))*BI19/INDEX(er!D:D, MATCH(Q19,er!C:C,0),1),0)))} -> 68.691195 | BL19: {=IFERROR(INDEX('Com&tax'!$G$2:$G$5, MATCH(1, ('Com&tax'!$A$2:$A$5=B19)*('Com&tax'!$B$2:$B$5=Y19), 0)),0)} -> 0.1575 | BM19: =IF(A19="","",( IFERROR((J19*(1-BE19))*BL19,0))) -> 308448 | BN19: {=IF(A19="","",( IFERROR((J19*(1-BE19))*BL19/INDEX(er!D:D, MATCH(Q19,er!C:C,0),1),0)))} -> 220.79313 | BO19: {=IFERROR(INDEX('Com&tax'!$H$2:$H$5, MATCH(1, ('Com&tax'!$A$2:$A$5=B19)*('Com&tax'!$B$2:$B$5=Y19), 0)),0)} -> 0 | BP19: =IF(A19="","",( IFERROR(J19*BO19,0))) -> 0 | BQ19: {=IF(A19="","",( IFERROR(J19*BO19/INDEX(er!D:D, MATCH(Q19,er!C:C,0),1),0)))} -> 0 | BR19: {=IFERROR(INDEX('Com&tax'!$F$2:$F$5, MATCH(1, ('Com&tax'!$A$2:$A$5=B19)*('Com&tax'!$D$2:$D$5=H19), 0)),0)} -> 0.049 | BS19: =IF(A19="","",( IFERROR((J19*(1-BE19))*BR19,0))) -> 95961.6 | BT19: {=IF(A19="","",( IFERROR((J19*(1-BE19))*BR19/INDEX(er!D:D, MATCH(Q19,er!C:C,0),1),0)))} -> 68.691195 | BU19: {=IFERROR(INDEX('Com&tax'!$G$2:$G$5, MATCH(1, ('Com&tax'!$A$2:$A$5=B19)*('Com&tax'!$D$2:$D$5=H19), 0)),0)} -> 0.1575 | BV19: =IF(A19="","",( IFERROR((J19*(1-BE19))*BU19,0))) -> 308448 | BW19: {=IF(A19="","",( IFERROR((J19*(1-BE19))*BU19/INDEX(er!D:D, MATCH(Q19,er!C:C,0),1),0)))} -> 220.79313 | BX19: {=IFERROR(INDEX('Com&tax'!$H$2:$H$5, MATCH(1, ('Com&tax'!$A$2:$A$5=B19)*('Com&tax'!$D$2:$D$5=H19), 0)),0)} -> 0 | BY19: =IF(A19="","",( IFERROR(J19*BX19,0))) -> 0 | BZ19: {=IF(A19="","",( IFERROR(J19*BX19/INDEX(er!D:D, MATCH(Q19,er!C:C,0),1),0)))} -> 0 | CA19: {=IF(A19="","",( IFERROR(1-((P19/ INDEX(er!$D$3:$D$75,MATCH(1, (er!$A$3:$A$75=$BG$2)*(er!$C$3:$C$75=Q19), 0)) / (J19/ INDEX(er!$D$3:$D$75,MATCH(1, (er!$A$3:$A$75=$BG$2)*(er!$C$3:$C$75=L19), 0))))),"")))} -> 0.340005 | CB19: =IF(AB19="","",1-AD19/AB19) -> 0.33998 | CC19: =IF(AND(CA19="", CB19=""), "", CA19-CB19) -> 2.5e-05 | CD19: =BJ19+BM19-BS19-BV19 -> 0 | CE19: =BK19+BN19-BT19-BW19 -> 0 | CF19: =AJ19-CE19 -> -0.04 | CG19: =IF(OR(BE19="", AE19=""), "Miss", IF(ABS(AE19/100-AK19)<0.005, "OK", "Incorrect")) -> OK | CI19: OK | CK19: 0 | CL19: =(AI19+CK19)/INDEX(er!D:D,MATCH(AC19,er!C:C,0),1) -> -0.04123121 | CN19: =CK19/INDEX(er!D:D,MATCH(AC19,er!C:C,0),1) -> 0
A20: T3184062 | B20: Twitter Rep | C20: IMS | D20: AR_Media Company_Play Digital Argentina_X | MODO | Promo Diarco | G20: Argentina | H20: Aleph Argentina | I20: Argentina | J20: 718276.95 | K20: 718276.95 | L20: ARS | M20: 718276.95 | N20: ARS | O20: 718276.95 | P20: 434180.49 | Q20: ARS | R20: Mexico | U20: 0 | V20: 2026-02 | W20: February/2026 | X20: IMS | Y20: Argentina | Z20: Mexico | AA20: ARS | AB20: 718276.95 | AC20: ARS | AD20: 434180.46 | AE20: 39.55 | AF20: OK | AG20: 0 | AH20: 0 | AI20: 0.03 | AJ20: 0 | AK20: 0.39552496 | AL20: OK | AM20: 10573725 | AO20: Miss | AP20: Miss | AR20: Miss | AT20: Miss | AU20: 718276.95 | AV20: 512 | AW20: Miss | AX20: 718276.95 | AY20: 514.16 | AZ20: ARS | BA20: 434180.46 | BB20: OK | BC20: 0.03 | BD20: 0 | BE20: {=IFERROR(INDEX('Com&tax'!$E$2:$E$5, MATCH(1, ('Com&tax'!$A$2:$A$5=B20)*('Com&tax'!$B$2:$B$5=G20), 0)),"")} -> 0.15 | BF20: =IF(A20="","",( IFERROR(O20*BE20,""))) -> 107741.54 | BG20: {=IF(A20="","",( IFERROR((O20/ INDEX(er!$D$3:$D$75,MATCH(1, (er!$A$3:$A$75=$BG$2)*(er!$C$3:$C$75=Q20), 0)))*BE20,"")))} -> 77.123509 | BH20: =IF(A20="","",( IF(B20="Snapchat Rep", IF(A20="","",(P20-BF20)),-BF20))) -> -107741.54 | BI20: {=IFERROR(INDEX('Com&tax'!$F$2:$F$5, MATCH(1, ('Com&tax'!$A$2:$A$5=B20)*('Com&tax'!$B$2:$B$5=Y20), 0)),0)} -> 0.049 | BJ20: =IF(A20="","",( IFERROR((J20*(1-BE20))*BI20,0))) -> 29916.235 | BK20: {=IF(A20="","",( IFERROR((J20*(1-BE20))*BI20/INDEX(er!D:D, MATCH(Q20,er!C:C,0),1),0)))} -> 21.414628 | BL20: {=IFERROR(INDEX('Com&tax'!$G$2:$G$5, MATCH(1, ('Com&tax'!$A$2:$A$5=B20)*('Com&tax'!$B$2:$B$5=Y20), 0)),0)} -> 0.1575 | BM20: =IF(A20="","",( IFERROR((J20*(1-BE20))*BL20,0))) -> 96159.327 | BN20: {=IF(A20="","",( IFERROR((J20*(1-BE20))*BL20/INDEX(er!D:D, MATCH(Q20,er!C:C,0),1),0)))} -> 68.832732 | BO20: {=IFERROR(INDEX('Com&tax'!$H$2:$H$5, MATCH(1, ('Com&tax'!$A$2:$A$5=B20)*('Com&tax'!$B$2:$B$5=Y20), 0)),0)} -> 0.07 | BP20: =IF(A20="","",( IFERROR(J20*BO20,0))) -> 50279.387 | BQ20: {=IF(A20="","",( IFERROR(J20*BO20/INDEX(er!D:D, MATCH(Q20,er!C:C,0),1),0)))} -> 35.990971 | BR20: {=IFERROR(INDEX('Com&tax'!$F$2:$F$5, MATCH(1, ('Com&tax'!$A$2:$A$5=B20)*('Com&tax'!$D$2:$D$5=H20), 0)),0)} -> 0.049 | BS20: =IF(A20="","",( IFERROR((J20*(1-BE20))*BR20,0))) -> 29916.235 | BT20: {=IF(A20="","",( IFERROR((J20*(1-BE20))*BR20/INDEX(er!D:D, MATCH(Q20,er!C:C,0),1),0)))} -> 21.414628 | BU20: {=IFERROR(INDEX('Com&tax'!$G$2:$G$5, MATCH(1, ('Com&tax'!$A$2:$A$5=B20)*('Com&tax'!$D$2:$D$5=H20), 0)),0)} -> 0.1575 | BV20: =IF(A20="","",( IFERROR((J20*(1-BE20))*BU20,0))) -> 96159.327 | BW20: {=IF(A20="","",( IFERROR((J20*(1-BE20))*BU20/INDEX(er!D:D, MATCH(Q20,er!C:C,0),1),0)))} -> 68.832732 | BX20: {=IFERROR(INDEX('Com&tax'!$H$2:$H$5, MATCH(1, ('Com&tax'!$A$2:$A$5=B20)*('Com&tax'!$D$2:$D$5=H20), 0)),0)} -> 0.07 | BY20: =IF(A20="","",( IFERROR(J20*BX20,0))) -> 50279.387 | BZ20: {=IF(A20="","",( IFERROR(J20*BX20/INDEX(er!D:D, MATCH(Q20,er!C:C,0),1),0)))} -> 35.990971 | CA20: {=IF(A20="","",( IFERROR(1-((P20/ INDEX(er!$D$3:$D$75,MATCH(1, (er!$A$3:$A$75=$BG$2)*(er!$C$3:$C$75=Q20), 0)) / (J20/ INDEX(er!$D$3:$D$75,MATCH(1, (er!$A$3:$A$75=$BG$2)*(er!$C$3:$C$75=L20), 0))))),"")))} -> 0.39552496 | CB20: =IF(AB20="","",1-AD20/AB20) -> 0.395525 | CC20: =IF(AND(CA20="", CB20=""), "", CA20-CB20) -> -4.1766619e-08 | CD20: =BJ20+BM20-BS20-BV20 -> 0 | CE20: =BK20+BN20-BT20-BW20 -> 0 | CF20: =AJ20-CE20 -> 0 | CG20: =IF(OR(BE20="", AE20=""), "Miss", IF(ABS(AE20/100-AK20)<0.005, "OK", "Incorrect")) -> OK | CI20: OK | CK20: 0 | CL20: =(AI20+CK20)/INDEX(er!D:D,MATCH(AC20,er!C:C,0),1) -> 2.1474588e-05 | CN20: =CK20/INDEX(er!D:D,MATCH(AC20,er!C:C,0),1) -> 0
A21: T3184279 | B21: Twitter Rep | C21: IMS | D21: AR_Media Company_USAL Argentina_X - Arg - USAL - Q42025 | G21: Argentina | H21: Aleph Argentina | I21: Argentina | J21: 1206718.5 | K21: 1206718.5 | L21: ARS | M21: 1206718.5 | N21: ARS | O21: 1206718.5 | P21: 729431.2 | Q21: ARS | R21: Mexico | U21: 0 | V21: 2026-02 | W21: February/2026 | X21: IMS | Y21: Argentina | Z21: Mexico | AA21: ARS | AB21: 1206718.5 | AC21: ARS | AD21: 729431.15 | AE21: 39.55 | AF21: OK | AG21: 0 | AH21: 0 | AI21: 0.05 | AJ21: 0 | AK21: 0.39552496 | AL21: OK | AM21: 10573652 | AO21: Miss | AP21: Miss | AR21: Miss | AT21: Miss | AU21: 1206718.5 | AV21: 862 | AW21: Miss | AX21: 1206718.5 | AY21: 863.79 | AZ21: ARS | BA21: 729431.15 | BB21: OK | BC21: 0.05 | BD21: 0 | BE21: {=IFERROR(INDEX('Com&tax'!$E$2:$E$5, MATCH(1, ('Com&tax'!$A$2:$A$5=B21)*('Com&tax'!$B$2:$B$5=G21), 0)),"")} -> 0.15 | BF21: =IF(A21="","",( IFERROR(O21*BE21,""))) -> 181007.77 | BG21: {=IF(A21="","",( IFERROR((O21/ INDEX(er!$D$3:$D$75,MATCH(1, (er!$A$3:$A$75=$BG$2)*(er!$C$3:$C$75=Q21), 0)))*BE21,"")))} -> 129.56891 | BH21: =IF(A21="","",( IF(B21="Snapchat Rep", IF(A21="","",(P21-BF21)),-BF21))) -> -181007.77 | BI21: {=IFERROR(INDEX('Com&tax'!$F$2:$F$5, MATCH(1, ('Com&tax'!$A$2:$A$5=B21)*('Com&tax'!$B$2:$B$5=Y21), 0)),0)} -> 0.049 | BJ21: =IF(A21="","",( IFERROR((J21*(1-BE21))*BI21,0))) -> 50259.825 | BK21: {=IF(A21="","",( IFERROR((J21*(1-BE21))*BI21/INDEX(er!D:D, MATCH(Q21,er!C:C,0),1),0)))} -> 35.976968 | BL21: {=IFERROR(INDEX('Com&tax'!$G$2:$G$5, MATCH(1, ('Com&tax'!$A$2:$A$5=B21)*('Com&tax'!$B$2:$B$5=Y21), 0)),0)} -> 0.1575 | BM21: =IF(A21="","",( IFERROR((J21*(1-BE21))*BL21,0))) -> 161549.44 | BN21: {=IF(A21="","",( IFERROR((J21*(1-BE21))*BL21/INDEX(er!D:D, MATCH(Q21,er!C:C,0),1),0)))} -> 115.64026 | BO21: {=IFERROR(INDEX('Com&tax'!$H$2:$H$5, MATCH(1, ('Com&tax'!$A$2:$A$5=B21)*('Com&tax'!$B$2:$B$5=Y21), 0)),0)} -> 0.07 | BP21: =IF(A21="","",( IFERROR(J21*BO21,0))) -> 84470.294 | BQ21: {=IF(A21="","",( IFERROR(J21*BO21/INDEX(er!D:D, MATCH(Q21,er!C:C,0),1),0)))} -> 60.465493 | BR21: {=IFERROR(INDEX('Com&tax'!$F$2:$F$5, MATCH(1, ('Com&tax'!$A$2:$A$5=B21)*('Com&tax'!$D$2:$D$5=H21), 0)),0)} -> 0.049 | BS21: =IF(A21="","",( IFERROR((J21*(1-BE21))*BR21,0))) -> 50259.825 | BT21: {=IF(A21="","",( IFERROR((J21*(1-BE21))*BR21/INDEX(er!D:D, MATCH(Q21,er!C:C,0),1),0)))} -> 35.976968 | BU21: {=IFERROR(INDEX('Com&tax'!$G$2:$G$5, MATCH(1, ('Com&tax'!$A$2:$A$5=B21)*('Com&tax'!$D$2:$D$5=H21), 0)),0)} -> 0.1575 | BV21: =IF(A21="","",( IFERROR((J21*(1-BE21))*BU21,0))) -> 161549.44 | BW21: {=IF(A21="","",( IFERROR((J21*(1-BE21))*BU21/INDEX(er!D:D, MATCH(Q21,er!C:C,0),1),0)))} -> 115.64026 | BX21: {=IFERROR(INDEX('Com&tax'!$H$2:$H$5, MATCH(1, ('Com&tax'!$A$2:$A$5=B21)*('Com&tax'!$D$2:$D$5=H21), 0)),0)} -> 0.07 | BY21: =IF(A21="","",( IFERROR(J21*BX21,0))) -> 84470.294 | BZ21: {=IF(A21="","",( IFERROR(J21*BX21/INDEX(er!D:D, MATCH(Q21,er!C:C,0),1),0)))} -> 60.465493 | CA21: {=IF(A21="","",( IFERROR(1-((P21/ INDEX(er!$D$3:$D$75,MATCH(1, (er!$A$3:$A$75=$BG$2)*(er!$C$3:$C$75=Q21), 0)) / (J21/ INDEX(er!$D$3:$D$75,MATCH(1, (er!$A$3:$A$75=$BG$2)*(er!$C$3:$C$75=L21), 0))))),"")))} -> 0.39552496 | CB21: =IF(AB21="","",1-AD21/AB21) -> 0.395525 | CC21: =IF(AND(CA21="", CB21=""), "", CA21-CB21) -> -4.1434685e-08 | CD21: =BJ21+BM21-BS21-BV21 -> 0 | CE21: =BK21+BN21-BT21-BW21 -> 0 | CF21: =AJ21-CE21 -> 0 | CG21: =IF(OR(BE21="", AE21=""), "Miss", IF(ABS(AE21/100-AK21)<0.005, "OK", "Incorrect")) -> OK | CI21: OK | CK21: 0 | CL21: =(AI21+CK21)/INDEX(er!D:D,MATCH(AC21,er!C:C,0),1) -> 3.5790981e-05 | CN21: =CK21/INDEX(er!D:D,MATCH(AC21,er!C:C,0),1) -> 0
A22: T3186988 | B22: Twitter Rep | C22: IMS | D22: AR_Media Company_Cinemark Argentina_X - Arg - Cinemark - Q42025 | G22: Argentina | H22: Aleph Argentina | I22: Argentina | J22: 2431431.1 | K22: 2431431.1 | L22: ARS | M22: 2431431.1 | N22: ARS | O22: 2431431.1 | P22: 1469739.4 | Q22: ARS | R22: Mexico | U22: 0 | V22: 2026-02 | W22: February/2026 | X22: IMS | Y22: Argentina | Z22: Mexico | AA22: ARS | AB22: 2431431.1 | AC22: ARS | AD22: 1469739.3 | AE22: 39.55 | AF22: OK | AG22: 0 | AH22: 0 | AI22: 0.1 | AJ22: 0 | AK22: 0.39552496 | AL22: OK | AM22: 10573662 | AO22: Miss | AP22: Miss | AR22: Miss | AT22: Miss | AU22: 2431431.1 | AV22: 1738 | AW22: Miss | AX22: 2431431.1 | AY22: 1740.47 | AZ22: ARS | BA22: 1469739.3 | BB22: OK | BC22: 0.09 | BD22: 0 | BE22: {=IFERROR(INDEX('Com&tax'!$E$2:$E$5, MATCH(1, ('Com&tax'!$A$2:$A$5=B22)*('Com&tax'!$B$2:$B$5=G22), 0)),"")} -> 0.15 | BF22: =IF(A22="","",( IFERROR(O22*BE22,""))) -> 364714.67 | BG22: {=IF(A22="","",( IFERROR((O22/ INDEX(er!$D$3:$D$75,MATCH(1, (er!$A$3:$A$75=$BG$2)*(er!$C$3:$C$75=Q22), 0)))*BE22,"")))} -> 261.06991 | BH22: =IF(A22="","",( IF(B22="Snapchat Rep", IF(A22="","",(P22-BF22)),-BF22))) -> -364714.67 | BI22: {=IFERROR(INDEX('Com&tax'!$F$2:$F$5, MATCH(1, ('Com&tax'!$A$2:$A$5=B22)*('Com&tax'!$B$2:$B$5=Y22), 0)),0)} -> 0.049 | BJ22: =IF(A22="","",( IFERROR((J22*(1-BE22))*BI22,0))) -> 101269.11 | BK22: {=IF(A22="","",( IFERROR((J22*(1-BE22))*BI22/INDEX(er!D:D, MATCH(Q22,er!C:C,0),1),0)))} -> 72.490412 | BL22: {=IFERROR(INDEX('Com&tax'!$G$2:$G$5, MATCH(1, ('Com&tax'!$A$2:$A$5=B22)*('Com&tax'!$B$2:$B$5=Y22), 0)),0)} -> 0.1575 | BM22: =IF(A22="","",( IFERROR((J22*(1-BE22))*BL22,0))) -> 325507.84 | BN22: {=IF(A22="","",( IFERROR((J22*(1-BE22))*BL22/INDEX(er!D:D, MATCH(Q22,er!C:C,0),1),0)))} -> 233.0049 | BO22: {=IFERROR(INDEX('Com&tax'!$H$2:$H$5, MATCH(1, ('Com&tax'!$A$2:$A$5=B22)*('Com&tax'!$B$2:$B$5=Y22), 0)),0)} -> 0.07 | BP22: =IF(A22="","",( IFERROR(J22*BO22,0))) -> 170200.18 | BQ22: {=IF(A22="","",( IFERROR(J22*BO22/INDEX(er!D:D, MATCH(Q22,er!C:C,0),1),0)))} -> 121.83263 | BR22: {=IFERROR(INDEX('Com&tax'!$F$2:$F$5, MATCH(1, ('Com&tax'!$A$2:$A$5=B22)*('Com&tax'!$D$2:$D$5=H22), 0)),0)} -> 0.049 | BS22: =IF(A22="","",( IFERROR((J22*(1-BE22))*BR22,0))) -> 101269.11 | BT22: {=IF(A22="","",( IFERROR((J22*(1-BE22))*BR22/INDEX(er!D:D, MATCH(Q22,er!C:C,0),1),0)))} -> 72.490412 | BU22: {=IFERROR(INDEX('Com&tax'!$G$2:$G$5, MATCH(1, ('Com&tax'!$A$2:$A$5=B22)*('Com&tax'!$D$2:$D$5=H22), 0)),0)} -> 0.1575 | BV22: =IF(A22="","",( IFERROR((J22*(1-BE22))*BU22,0))) -> 325507.84 | BW22: {=IF(A22="","",( IFERROR((J22*(1-BE22))*BU22/INDEX(er!D:D, MATCH(Q22,er!C:C,0),1),0)))} -> 233.0049 | BX22: {=IFERROR(INDEX('Com&tax'!$H$2:$H$5, MATCH(1, ('Com&tax'!$A$2:$A$5=B22)*('Com&tax'!$D$2:$D$5=H22), 0)),0)} -> 0.07 | BY22: =IF(A22="","",( IFERROR(J22*BX22,0))) -> 170200.18 | BZ22: {=IF(A22="","",( IFERROR(J22*BX22/INDEX(er!D:D, MATCH(Q22,er!C:C,0),1),0)))} -> 121.83263 | CA22: {=IF(A22="","",( IFERROR(1-((P22/ INDEX(er!$D$3:$D$75,MATCH(1, (er!$A$3:$A$75=$BG$2)*(er!$C$3:$C$75=Q22), 0)) / (J22/ INDEX(er!$D$3:$D$75,MATCH(1, (er!$A$3:$A$75=$BG$2)*(er!$C$3:$C$75=L22), 0))))),"")))} -> 0.39552496 | CB22: =IF(AB22="","",1-AD22/AB22) -> 0.395525 | CC22: =IF(AND(CA22="", CB22=""), "", CA22-CB22) -> -4.1128042e-08 | CD22: =BJ22+BM22-BS22-BV22 -> 0 | CE22: =BK22+BN22-BT22-BW22 -> 0 | CF22: =AJ22-CE22 -> 0 | CG22: =IF(OR(BE22="", AE22=""), "Miss", IF(ABS(AE22/100-AK22)<0.005, "OK", "Incorrect")) -> OK | CI22: OK | CK22: 0 | CL22: =(AI22+CK22)/INDEX(er!D:D,MATCH(AC22,er!C:C,0),1) -> 7.1581961e-05 | CN22: =CK22/INDEX(er!D:D,MATCH(AC22,er!C:C,0),1) -> 0
A23: T3203120 | B23: Twitter Billing | C23: IMS | D23: AR_Media Company_WARNER BROS. (SOUTH), ARGENTINA_T3203120 - Warner Argentina | La Novia - 25/01/2026 | G23: Argentina | H23: Aleph Argentina | I23: Argentina | J23: 4454635 | K23: 4454635 | L23: ARS | M23: 4454635 | N23: ARS | O23: 4454635 | P23: 2940036.9 | Q23: ARS | R23: Mexico | U23: 0 | V23: 2026-02 | W23: February/2026 | X23: IMS | Y23: Argentina | Z23: Mexico | AA23: ARS | AB23: 4454635 | AC23: ARS | AD23: 2940148.2 | AE23: 34 | AF23: OK | AG23: 0 | AH23: 0 | AI23: -111.37 | AJ23: -0.08 | AK23: 0.340005 | AL23: OK | AM23: 10573626 | AO23: Miss | AP23: Miss | AR23: Miss | AT23: Miss | AU23: 4454635 | AV23: 3187 | AW23: Miss | AX23: 4454635 | AY23: 3188.72 | AZ23: ARS | BA23: 2940148.2 | BB23: OK | BC23: -111.36 | BD23: -0.08 | BE23: {=IFERROR(INDEX('Com&tax'!$E$2:$E$5, MATCH(1, ('Com&tax'!$A$2:$A$5=B23)*('Com&tax'!$B$2:$B$5=G23), 0)),"")} -> 0.15 | BF23: =IF(A23="","",( IFERROR(O23*BE23,""))) -> 668195.26 | BG23: {=IF(A23="","",( IFERROR((O23/ INDEX(er!$D$3:$D$75,MATCH(1, (er!$A$3:$A$75=$BG$2)*(er!$C$3:$C$75=Q23), 0)))*BE23,"")))} -> 478.30727 | BH23: =IF(A23="","",( IF(B23="Snapchat Rep", IF(A23="","",(P23-BF23)),-BF23))) -> -668195.26 | BI23: {=IFERROR(INDEX('Com&tax'!$F$2:$F$5, MATCH(1, ('Com&tax'!$A$2:$A$5=B23)*('Com&tax'!$B$2:$B$5=Y23), 0)),0)} -> 0.049 | BJ23: =IF(A23="","",( IFERROR((J23*(1-BE23))*BI23,0))) -> 185535.55 | BK23: {=IF(A23="","",( IFERROR((J23*(1-BE23))*BI23/INDEX(er!D:D, MATCH(Q23,er!C:C,0),1),0)))} -> 132.80999 | BL23: {=IFERROR(INDEX('Com&tax'!$G$2:$G$5, MATCH(1, ('Com&tax'!$A$2:$A$5=B23)*('Com&tax'!$B$2:$B$5=Y23), 0)),0)} -> 0.1575 | BM23: =IF(A23="","",( IFERROR((J23*(1-BE23))*BL23,0))) -> 596364.27 | BN23: {=IF(A23="","",( IFERROR((J23*(1-BE23))*BL23/INDEX(er!D:D, MATCH(Q23,er!C:C,0),1),0)))} -> 426.88924 | BO23: {=IFERROR(INDEX('Com&tax'!$H$2:$H$5, MATCH(1, ('Com&tax'!$A$2:$A$5=B23)*('Com&tax'!$B$2:$B$5=Y23), 0)),0)} -> 0 | BP23: =IF(A23="","",( IFERROR(J23*BO23,0))) -> 0 | BQ23: {=IF(A23="","",( IFERROR(J23*BO23/INDEX(er!D:D, MATCH(Q23,er!C:C,0),1),0)))} -> 0 | BR23: {=IFERROR(INDEX('Com&tax'!$F$2:$F$5, MATCH(1, ('Com&tax'!$A$2:$A$5=B23)*('Com&tax'!$D$2:$D$5=H23), 0)),0)} -> 0.049 | BS23: =IF(A23="","",( IFERROR((J23*(1-BE23))*BR23,0))) -> 185535.55 | BT23: {=IF(A23="","",( IFERROR((J23*(1-BE23))*BR23/INDEX(er!D:D, MATCH(Q23,er!C:C,0),1),0)))} -> 132.80999 | BU23: {=IFERROR(INDEX('Com&tax'!$G$2:$G$5, MATCH(1, ('Com&tax'!$A$2:$A$5=B23)*('Com&tax'!$D$2:$D$5=H23), 0)),0)} -> 0.1575 | BV23: =IF(A23="","",( IFERROR((J23*(1-BE23))*BU23,0))) -> 596364.27 | BW23: {=IF(A23="","",( IFERROR((J23*(1-BE23))*BU23/INDEX(er!D:D, MATCH(Q23,er!C:C,0),1),0)))} -> 426.88924 | BX23: {=IFERROR(INDEX('Com&tax'!$H$2:$H$5, MATCH(1, ('Com&tax'!$A$2:$A$5=B23)*('Com&tax'!$D$2:$D$5=H23), 0)),0)} -> 0 | BY23: =IF(A23="","",( IFERROR(J23*BX23,0))) -> 0 | BZ23: {=IF(A23="","",( IFERROR(J23*BX23/INDEX(er!D:D, MATCH(Q23,er!C:C,0),1),0)))} -> 0 | CA23: {=IF(A23="","",( IFERROR(1-((P23/ INDEX(er!$D$3:$D$75,MATCH(1, (er!$A$3:$A$75=$BG$2)*(er!$C$3:$C$75=Q23), 0)) / (J23/ INDEX(er!$D$3:$D$75,MATCH(1, (er!$A$3:$A$75=$BG$2)*(er!$C$3:$C$75=L23), 0))))),"")))} -> 0.340005 | CB23: =IF(AB23="","",1-AD23/AB23) -> 0.33998 | CC23: =IF(AND(CA23="", CB23=""), "", CA23-CB23) -> 2.5000926e-05 | CD23: =BJ23+BM23-BS23-BV23 -> 0 | CE23: =BK23+BN23-BT23-BW23 -> 0 | CF23: =AJ23-CE23 -> -0.08 | CG23: =IF(OR(BE23="", AE23=""), "Miss", IF(ABS(AE23/100-AK23)<0.005, "OK", "Incorrect")) -> OK | CI23: OK | CK23: 0 | CL23: =(AI23+CK23)/INDEX(er!D:D,MATCH(AC23,er!C:C,0),1) -> -0.07972083 | CN23: =CK23/INDEX(er!D:D,MATCH(AC23,er!C:C,0),1) -> 0
A24: T3203811 | B24: Twitter Billing | C24: IMS | D24: AR_Media Company_Mercado Libre Argentina_T3203811 - MLA | Verano | Takeover- 6/Enero, 4/Feb - 07/12/2025 | G24: Argentina | H24: Aleph Argentina | I24: Argentina | J24: 2304000 | K24: 2304000 | L24: ARS | M24: 2304000 | N24: ARS | O24: 2304000 | P24: 1520628.5 | Q24: ARS | R24: Mexico | U24: 0 | V24: 2026-02 | W24: February/2026 | X24: IMS | Y24: Argentina | Z24: Mexico | AA24: ARS | AB24: 2304000 | AC24: ARS | AD24: 1520686.1 | AE24: 34 | AF24: OK | AG24: 0 | AH24: 0 | AI24: -57.6 | AJ24: -0.04 | AK24: 0.340005 | AL24: OK | AM24: 10573677 | AO24: Miss | AP24: Miss | AR24: Miss | AT24: Miss | AU24: 2304000 | AV24: 1647 | AW24: Miss | AX24: 2304000 | AY24: 1649.25 | AZ24: ARS | BA24: 1520686.1 | BB24: OK | BC24: -57.6 | BD24: -0.04 | BE24: {=IFERROR(INDEX('Com&tax'!$E$2:$E$5, MATCH(1, ('Com&tax'!$A$2:$A$5=B24)*('Com&tax'!$B$2:$B$5=G24), 0)),"")} -> 0.15 | BF24: =IF(A24="","",( IFERROR(O24*BE24,""))) -> 345600 | BG24: {=IF(A24="","",( IFERROR((O24/ INDEX(er!$D$3:$D$75,MATCH(1, (er!$A$3:$A$75=$BG$2)*(er!$C$3:$C$75=Q24), 0)))*BE24,"")))} -> 247.38726 | BH24: =IF(A24="","",( IF(B24="Snapchat Rep", IF(A24="","",(P24-BF24)),-BF24))) -> -345600 | BI24: {=IFERROR(INDEX('Com&tax'!$F$2:$F$5, MATCH(1, ('Com&tax'!$A$2:$A$5=B24)*('Com&tax'!$B$2:$B$5=Y24), 0)),0)} -> 0.049 | BJ24: =IF(A24="","",( IFERROR((J24*(1-BE24))*BI24,0))) -> 95961.6 | BK24: {=IF(A24="","",( IFERROR((J24*(1-BE24))*BI24/INDEX(er!D:D, MATCH(Q24,er!C:C,0),1),0)))} -> 68.691195 | BL24: {=IFERROR(INDEX('Com&tax'!$G$2:$G$5, MATCH(1, ('Com&tax'!$A$2:$A$5=B24)*('Com&tax'!$B$2:$B$5=Y24), 0)),0)} -> 0.1575 | BM24: =IF(A24="","",( IFERROR((J24*(1-BE24))*BL24,0))) -> 308448 | BN24: {=IF(A24="","",( IFERROR((J24*(1-BE24))*BL24/INDEX(er!D:D, MATCH(Q24,er!C:C,0),1),0)))} -> 220.79313 | BO24: {=IFERROR(INDEX('Com&tax'!$H$2:$H$5, MATCH(1, ('Com&tax'!$A$2:$A$5=B24)*('Com&tax'!$B$2:$B$5=Y24), 0)),0)} -> 0 | BP24: =IF(A24="","",( IFERROR(J24*BO24,0))) -> 0 | BQ24: {=IF(A24="","",( IFERROR(J24*BO24/INDEX(er!D:D, MATCH(Q24,er!C:C,0),1),0)))} -> 0 | BR24: {=IFERROR(INDEX('Com&tax'!$F$2:$F$5, MATCH(1, ('Com&tax'!$A$2:$A$5=B24)*('Com&tax'!$D$2:$D$5=H24), 0)),0)} -> 0.049 | BS24: =IF(A24="","",( IFERROR((J24*(1-BE24))*BR24,0))) -> 95961.6 | BT24: {=IF(A24="","",( IFERROR((J24*(1-BE24))*BR24/INDEX(er!D:D, MATCH(Q24,er!C:C,0),1),0)))} -> 68.691195 | BU24: {=IFERROR(INDEX('Com&tax'!$G$2:$G$5, MATCH(1, ('Com&tax'!$A$2:$A$5=B24)*('Com&tax'!$D$2:$D$5=H24), 0)),0)} -> 0.1575 | BV24: =IF(A24="","",( IFERROR((J24*(1-BE24))*BU24,0))) -> 308448 | BW24: {=IF(A24="","",( IFERROR((J24*(1-BE24))*BU24/INDEX(er!D:D, MATCH(Q24,er!C:C,0),1),0)))} -> 220.79313 | BX24: {=IFERROR(INDEX('Com&tax'!$H$2:$H$5, MATCH(1, ('Com&tax'!$A$2:$A$5=B24)*('Com&tax'!$D$2:$D$5=H24), 0)),0)} -> 0 | BY24: =IF(A24="","",( IFERROR(J24*BX24,0))) -> 0 | BZ24: {=IF(A24="","",( IFERROR(J24*BX24/INDEX(er!D:D, MATCH(Q24,er!C:C,0),1),0)))} -> 0 | CA24: {=IF(A24="","",( IFERROR(1-((P24/ INDEX(er!$D$3:$D$75,MATCH(1, (er!$A$3:$A$75=$BG$2)*(er!$C$3:$C$75=Q24), 0)) / (J24/ INDEX(er!$D$3:$D$75,MATCH(1, (er!$A$3:$A$75=$BG$2)*(er!$C$3:$C$75=L24), 0))))),"")))} -> 0.340005 | CB24: =IF(AB24="","",1-AD24/AB24) -> 0.33998 | CC24: =IF(AND(CA24="", CB24=""), "", CA24-CB24) -> 2.5e-05 | CD24: =BJ24+BM24-BS24-BV24 -> 0 | CE24: =BK24+BN24-BT24-BW24 -> 0 | CF24: =AJ24-CE24 -> -0.04 | CG24: =IF(OR(BE24="", AE24=""), "Miss", IF(ABS(AE24/100-AK24)<0.005, "OK", "Incorrect")) -> OK | CI24: OK | CK24: 0 | CL24: =(AI24+CK24)/INDEX(er!D:D,MATCH(AC24,er!C:C,0),1) -> -0.04123121 | CN24: =CK24/INDEX(er!D:D,MATCH(AC24,er!C:C,0),1) -> 0
A25: T3207502 | B25: Twitter Billing | C25: IMS | D25: AR_Media Company_WARNER BROS. (SOUTH), ARGENTINA_T3207502 - Warner Argentina | La Novia - 19/02/2026 | G25: Argentina | H25: Aleph Argentina | I25: Argentina | J25: 1192935.2 | K25: 1192935.2 | L25: ARS | M25: 1192935.2 | N25: ARS | O25: 1192935.2 | P25: 787331.25 | Q25: ARS | R25: Mexico | U25: 0 | V25: 2026-02 | W25: February/2026 | X25: IMS | Y25: Argentina | Z25: Mexico | AA25: ARS | AB25: 1192935.2 | AC25: ARS | AD25: 930489.44 | AE25: 22 | AF25: OK | AG25: 0 | AH25: 0 | AI25: -143158.19 | AJ25: -102.48 | AK25: 0.340005 | AL25: OK | AM25: 10573678 | AO25: Miss | AP25: Miss | AR25: Miss | AT25: Miss | AU25: 1192935.2 | AV25: 852 | AW25: Miss | AX25: 1192935.2 | AY25: 853.93 | AZ25: ARS | BA25: 930489.45 | BB25: OK | BC25: -143158.2 | BD25: -102.48 | BE25: {=IFERROR(INDEX('Com&tax'!$E$2:$E$5, MATCH(1, ('Com&tax'!$A$2:$A$5=B25)*('Com&tax'!$B$2:$B$5=G25), 0)),"")} -> 0.15 | BF25: =IF(A25="","",( IFERROR(O25*BE25,""))) -> 178940.28 | BG25: {=IF(A25="","",( IFERROR((O25/ INDEX(er!$D$3:$D$75,MATCH(1, (er!$A$3:$A$75=$BG$2)*(er!$C$3:$C$75=Q25), 0)))*BE25,"")))} -> 128.08896 | BH25: =IF(A25="","",( IF(B25="Snapchat Rep", IF(A25="","",(P25-BF25)),-BF25))) -> -178940.28 | BI25: {=IFERROR(INDEX('Com&tax'!$F$2:$F$5, MATCH(1, ('Com&tax'!$A$2:$A$5=B25)*('Com&tax'!$B$2:$B$5=Y25), 0)),0)} -> 0.049 | BJ25: =IF(A25="","",( IFERROR((J25*(1-BE25))*BI25,0))) -> 49685.75 | BK25: {=IF(A25="","",( IFERROR((J25*(1-BE25))*BI25/INDEX(er!D:D, MATCH(Q25,er!C:C,0),1),0)))} -> 35.566035 | BL25: {=IFERROR(INDEX('Com&tax'!$G$2:$G$5, MATCH(1, ('Com&tax'!$A$2:$A$5=B25)*('Com&tax'!$B$2:$B$5=Y25), 0)),0)} -> 0.1575 | BM25: =IF(A25="","",( IFERROR((J25*(1-BE25))*BL25,0))) -> 159704.2 | BN25: {=IF(A25="","",( IFERROR((J25*(1-BE25))*BL25/INDEX(er!D:D, MATCH(Q25,er!C:C,0),1),0)))} -> 114.3194 | BO25: {=IFERROR(INDEX('Com&tax'!$H$2:$H$5, MATCH(1, ('Com&tax'!$A$2:$A$5=B25)*('Com&tax'!$B$2:$B$5=Y25), 0)),0)} -> 0 | BP25: =IF(A25="","",( IFERROR(J25*BO25,0))) -> 0 | BQ25: {=IF(A25="","",( IFERROR(J25*BO25/INDEX(er!D:D, MATCH(Q25,er!C:C,0),1),0)))} -> 0 | BR25: {=IFERROR(INDEX('Com&tax'!$F$2:$F$5, MATCH(1, ('Com&tax'!$A$2:$A$5=B25)*('Com&tax'!$D$2:$D$5=H25), 0)),0)} -> 0.049 | BS25: =IF(A25="","",( IFERROR((J25*(1-BE25))*BR25,0))) -> 49685.75 | BT25: {=IF(A25="","",( IFERROR((J25*(1-BE25))*BR25/INDEX(er!D:D, MATCH(Q25,er!C:C,0),1),0)))} -> 35.566035 | BU25: {=IFERROR(INDEX('Com&tax'!$G$2:$G$5, MATCH(1, ('Com&tax'!$A$2:$A$5=B25)*('Com&tax'!$D$2:$D$5=H25), 0)),0)} -> 0.1575 | BV25: =IF(A25="","",( IFERROR((J25*(1-BE25))*BU25,0))) -> 159704.2 | BW25: {=IF(A25="","",( IFERROR((J25*(1-BE25))*BU25/INDEX(er!D:D, MATCH(Q25,er!C:C,0),1),0)))} -> 114.3194 | BX25: {=IFERROR(INDEX('Com&tax'!$H$2:$H$5, MATCH(1, ('Com&tax'!$A$2:$A$5=B25)*('Com&tax'!$D$2:$D$5=H25), 0)),0)} -> 0 | BY25: =IF(A25="","",( IFERROR(J25*BX25,0))) -> 0 | BZ25: {=IF(A25="","",( IFERROR(J25*BX25/INDEX(er!D:D, MATCH(Q25,er!C:C,0),1),0)))} -> 0 | CA25: {=IF(A25="","",( IFERROR(1-((P25/ INDEX(er!$D$3:$D$75,MATCH(1, (er!$A$3:$A$75=$BG$2)*(er!$C$3:$C$75=Q25), 0)) / (J25/ INDEX(er!$D$3:$D$75,MATCH(1, (er!$A$3:$A$75=$BG$2)*(er!$C$3:$C$75=L25), 0))))),"")))} -> 0.340005 | CB25: =IF(AB25="","",1-AD25/AB25) -> 0.22 | CC25: =IF(AND(CA25="", CB25=""), "", CA25-CB25) -> 0.120005 | CD25: =BJ25+BM25-BS25-BV25 -> 0 | CE25: =BK25+BN25-BT25-BW25 -> 0 | CF25: =AJ25-CE25 -> -102.48 | CG25: =IF(OR(BE25="", AE25=""), "Miss", IF(ABS(AE25/100-AK25)<0.005, "OK", "Incorrect")) -> Incorrect | CI25: OK. Twitter Comm. ERR | CK25: 209389.95 | CL25: =(AI25+CK25)/INDEX(er!D:D,MATCH(AC25,er!C:C,0),1) -> 47.409991 | CN25: =CK25/INDEX(er!D:D,MATCH(AC25,er!C:C,0),1) -> 149.88543
A26: T3209384 | B26: Twitter Rep | C26: IMS | D26: AR_Media Company_Play Digital Argentina_X | MODO | Cencosud 2026 | G26: Argentina | H26: Aleph Argentina | I26: Argentina | J26: 6210184.3 | K26: 6210184.3 | L26: ARS | M26: 6210184.3 | N26: ARS | O26: 6210184.3 | P26: 3753901.4 | Q26: ARS | R26: Mexico | U26: 0 | V26: 2026-02 | W26: February/2026 | X26: IMS | Y26: Argentina | Z26: Mexico | AA26: ARS | AB26: 6210184.3 | AC26: ARS | AD26: 3753901.2 | AE26: 39.55 | AF26: OK | AG26: 0 | AH26: 0 | AI26: 0.25 | AJ26: 0 | AK26: 0.39552496 | AL26: OK | AM26: 10573653 | AO26: Miss | AP26: Miss | AR26: Miss | AT26: Miss | AU26: 6210184.3 | AV26: 4443 | AW26: Miss | AX26: 6210184.3 | AY26: 4445.37 | AZ26: ARS | BA26: 3753901.2 | BB26: OK | BC26: 0.26 | BD26: 0 | BE26: {=IFERROR(INDEX('Com&tax'!$E$2:$E$5, MATCH(1, ('Com&tax'!$A$2:$A$5=B26)*('Com&tax'!$B$2:$B$5=G26), 0)),"")} -> 0.15 | BF26: =IF(A26="","",( IFERROR(O26*BE26,""))) -> 931527.65 | BG26: {=IF(A26="","",( IFERROR((O26/ INDEX(er!$D$3:$D$75,MATCH(1, (er!$A$3:$A$75=$BG$2)*(er!$C$3:$C$75=Q26), 0)))*BE26,"")))} -> 666.80576 | BH26: =IF(A26="","",( IF(B26="Snapchat Rep", IF(A26="","",(P26-BF26)),-BF26))) -> -931527.65 | BI26: {=IFERROR(INDEX('Com&tax'!$F$2:$F$5, MATCH(1, ('Com&tax'!$A$2:$A$5=B26)*('Com&tax'!$B$2:$B$5=Y26), 0)),0)} -> 0.049 | BJ26: =IF(A26="","",( IFERROR((J26*(1-BE26))*BI26,0))) -> 258654.18 | BK26: {=IF(A26="","",( IFERROR((J26*(1-BE26))*BI26/INDEX(er!D:D, MATCH(Q26,er!C:C,0),1),0)))} -> 185.14973 | BL26: {=IFERROR(INDEX('Com&tax'!$G$2:$G$5, MATCH(1, ('Com&tax'!$A$2:$A$5=B26)*('Com&tax'!$B$2:$B$5=Y26), 0)),0)} -> 0.1575 | BM26: =IF(A26="","",( IFERROR((J26*(1-BE26))*BL26,0))) -> 831388.43 | BN26: {=IF(A26="","",( IFERROR((J26*(1-BE26))*BL26/INDEX(er!D:D, MATCH(Q26,er!C:C,0),1),0)))} -> 595.12414 | BO26: {=IFERROR(INDEX('Com&tax'!$H$2:$H$5, MATCH(1, ('Com&tax'!$A$2:$A$5=B26)*('Com&tax'!$B$2:$B$5=Y26), 0)),0)} -> 0.07 | BP26: =IF(A26="","",( IFERROR(J26*BO26,0))) -> 434712.9 | BQ26: {=IF(A26="","",( IFERROR(J26*BO26/INDEX(er!D:D, MATCH(Q26,er!C:C,0),1),0)))} -> 311.17602 | BR26: {=IFERROR(INDEX('Com&tax'!$F$2:$F$5, MATCH(1, ('Com&tax'!$A$2:$A$5=B26)*('Com&tax'!$D$2:$D$5=H26), 0)),0)} -> 0.049 | BS26: =IF(A26="","",( IFERROR((J26*(1-BE26))*BR26,0))) -> 258654.18 | BT26: {=IF(A26="","",( IFERROR((J26*(1-BE26))*BR26/INDEX(er!D:D, MATCH(Q26,er!C:C,0),1),0)))} -> 185.14973 | BU26: {=IFERROR(INDEX('Com&tax'!$G$2:$G$5, MATCH(1, ('Com&tax'!$A$2:$A$5=B26)*('Com&tax'!$D$2:$D$5=H26), 0)),0)} -> 0.1575 | BV26: =IF(A26="","",( IFERROR((J26*(1-BE26))*BU26,0))) -> 831388.43 | BW26: {=IF(A26="","",( IFERROR((J26*(1-BE26))*BU26/INDEX(er!D:D, MATCH(Q26,er!C:C,0),1),0)))} -> 595.12414 | BX26: {=IFERROR(INDEX('Com&tax'!$H$2:$H$5, MATCH(1, ('Com&tax'!$A$2:$A$5=B26)*('Com&tax'!$D$2:$D$5=H26), 0)),0)} -> 0.07 | BY26: =IF(A26="","",( IFERROR(J26*BX26,0))) -> 434712.9 | BZ26: {=IF(A26="","",( IFERROR(J26*BX26/INDEX(er!D:D, MATCH(Q26,er!C:C,0),1),0)))} -> 311.17602 | CA26: {=IF(A26="","",( IFERROR(1-((P26/ INDEX(er!$D$3:$D$75,MATCH(1, (er!$A$3:$A$75=$BG$2)*(er!$C$3:$C$75=Q26), 0)) / (J26/ INDEX(er!$D$3:$D$75,MATCH(1, (er!$A$3:$A$75=$BG$2)*(er!$C$3:$C$75=L26), 0))))),"")))} -> 0.39552496 | CB26: =IF(AB26="","",1-AD26/AB26) -> 0.395525 | CC26: =IF(AND(CA26="", CB26=""), "", CA26-CB26) -> -4.0256454e-08 | CD26: =BJ26+BM26-BS26-BV26 -> 0 | CE26: =BK26+BN26-BT26-BW26 -> 0 | CF26: =AJ26-CE26 -> 0 | CG26: =IF(OR(BE26="", AE26=""), "Miss", IF(ABS(AE26/100-AK26)<0.005, "OK", "Incorrect")) -> OK | CI26: OK | CK26: 0 | CL26: =(AI26+CK26)/INDEX(er!D:D,MATCH(AC26,er!C:C,0),1) -> 0.0001789549 | CN26: =CK26/INDEX(er!D:D,MATCH(AC26,er!C:C,0),1) -> 0
A27: T3210360 | B27: Twitter Rep | C27: IMS | D27: AR_Media Company_Red Bull Argentina Argentina_X - Arg - Red Bull - Summer - Q1 2026 | G27: Argentina | H27: Aleph Argentina | I27: Argentina | J27: 5546437.7 | K27: 5546437.7 | L27: ARS | M27: 5546437.7 | N27: ARS | O27: 5546437.7 | P27: 3352683.1 | Q27: ARS | R27: Mexico | U27: 0 | V27: 2026-02 | W27: February/2026 | X27: IMS | Y27: Argentina | Z27: Mexico | AA27: ARS | AB27: 5546437.7 | AC27: ARS | AD27: 3352682.9 | AE27: 39.55 | AF27: OK | AG27: 0 | AH27: 0 | AI27: 0.22 | AJ27: 0 | AK27: 0.39552496 | AL27: OK | AM27: 10573679 | AO27: Miss | AP27: Miss | AR27: Miss | AT27: Miss | AU27: 5546437.7 | AV27: 3968 | AW27: Miss | AX27: 5546437.7 | AY27: 3970.25 | AZ27: ARS | BA27: 3352682.9 | BB27: OK | BC27: 0.22 | BD27: 0 | BE27: {=IFERROR(INDEX('Com&tax'!$E$2:$E$5, MATCH(1, ('Com&tax'!$A$2:$A$5=B27)*('Com&tax'!$B$2:$B$5=G27), 0)),"")} -> 0.15 | BF27: =IF(A27="","",( IFERROR(O27*BE27,""))) -> 831965.66 | BG27: {=IF(A27="","",( IFERROR((O27/ INDEX(er!$D$3:$D$75,MATCH(1, (er!$A$3:$A$75=$BG$2)*(er!$C$3:$C$75=Q27), 0)))*BE27,"")))} -> 595.53733 | BH27: =IF(A27="","",( IF(B27="Snapchat Rep", IF(A27="","",(P27-BF27)),-BF27))) -> -831965.66 | BI27: {=IFERROR(INDEX('Com&tax'!$F$2:$F$5, MATCH(1, ('Com&tax'!$A$2:$A$5=B27)*('Com&tax'!$B$2:$B$5=Y27), 0)),0)} -> 0.049 | BJ27: =IF(A27="","",( IFERROR((J27*(1-BE27))*BI27,0))) -> 231009.13 | BK27: {=IF(A27="","",( IFERROR((J27*(1-BE27))*BI27/INDEX(er!D:D, MATCH(Q27,er!C:C,0),1),0)))} -> 165.36087 | BL27: {=IFERROR(INDEX('Com&tax'!$G$2:$G$5, MATCH(1, ('Com&tax'!$A$2:$A$5=B27)*('Com&tax'!$B$2:$B$5=Y27), 0)),0)} -> 0.1575 | BM27: =IF(A27="","",( IFERROR((J27*(1-BE27))*BL27,0))) -> 742529.35 | BN27: {=IF(A27="","",( IFERROR((J27*(1-BE27))*BL27/INDEX(er!D:D, MATCH(Q27,er!C:C,0),1),0)))} -> 531.51707 | BO27: {=IFERROR(INDEX('Com&tax'!$H$2:$H$5, MATCH(1, ('Com&tax'!$A$2:$A$5=B27)*('Com&tax'!$B$2:$B$5=Y27), 0)),0)} -> 0.07 | BP27: =IF(A27="","",( IFERROR(J27*BO27,0))) -> 388250.64 | BQ27: {=IF(A27="","",( IFERROR(J27*BO27/INDEX(er!D:D, MATCH(Q27,er!C:C,0),1),0)))} -> 277.91742 | BR27: {=IFERROR(INDEX('Com&tax'!$F$2:$F$5, MATCH(1, ('Com&tax'!$A$2:$A$5=B27)*('Com&tax'!$D$2:$D$5=H27), 0)),0)} -> 0.049 | BS27: =IF(A27="","",( IFERROR((J27*(1-BE27))*BR27,0))) -> 231009.13 | BT27: {=IF(A27="","",( IFERROR((J27*(1-BE27))*BR27/INDEX(er!D:D, MATCH(Q27,er!C:C,0),1),0)))} -> 165.36087 | BU27: {=IFERROR(INDEX('Com&tax'!$G$2:$G$5, MATCH(1, ('Com&tax'!$A$2:$A$5=B27)*('Com&tax'!$D$2:$D$5=H27), 0)),0)} -> 0.1575 | BV27: =IF(A27="","",( IFERROR((J27*(1-BE27))*BU27,0))) -> 742529.35 | BW27: {=IF(A27="","",( IFERROR((J27*(1-BE27))*BU27/INDEX(er!D:D, MATCH(Q27,er!C:C,0),1),0)))} -> 531.51707 | BX27: {=IFERROR(INDEX('Com&tax'!$H$2:$H$5, MATCH(1, ('Com&tax'!$A$2:$A$5=B27)*('Com&tax'!$D$2:$D$5=H27), 0)),0)} -> 0.07 | BY27: =IF(A27="","",( IFERROR(J27*BX27,0))) -> 388250.64 | BZ27: {=IF(A27="","",( IFERROR(J27*BX27/INDEX(er!D:D, MATCH(Q27,er!C:C,0),1),0)))} -> 277.91742 | CA27: {=IF(A27="","",( IFERROR(1-((P27/ INDEX(er!$D$3:$D$75,MATCH(1, (er!$A$3:$A$75=$BG$2)*(er!$C$3:$C$75=Q27), 0)) / (J27/ INDEX(er!$D$3:$D$75,MATCH(1, (er!$A$3:$A$75=$BG$2)*(er!$C$3:$C$75=L27), 0))))),"")))} -> 0.39552496 | CB27: =IF(AB27="","",1-AD27/AB27) -> 0.395525 | CC27: =IF(AND(CA27="", CB27=""), "", CA27-CB27) -> -3.9665099e-08 | CD27: =BJ27+BM27-BS27-BV27 -> 0 | CE27: =BK27+BN27-BT27-BW27 -> 0 | CF27: =AJ27-CE27 -> 0 | CG27: =IF(OR(BE27="", AE27=""), "Miss", IF(ABS(AE27/100-AK27)<0.005, "OK", "Incorrect")) -> OK | CI27: OK | CK27: 0 | CL27: =(AI27+CK27)/INDEX(er!D:D,MATCH(AC27,er!C:C,0),1) -> 0.00015748031 | CN27: =CK27/INDEX(er!D:D,MATCH(AC27,er!C:C,0),1) -> 0
... A29: T3218190 | B29: Twitter Rep | C29: IMS | D29: AR_Media Company_Banco Santander Rio Argentina_X | Santander | Verano 2026 | G29: Argentina | H29: Aleph Argentina | I29: Argentina | J29: 9005104.1 | K29: 9005104.1 | L29: ARS | M29: 9005104.1 | N29: ARS | O29: 9005104.1 | P29: 5443360.7 | Q29: ARS | R29: Mexico | U29: 0 | V29: 2026-02 | W29: February/2026 | X29: IMS | Y29: Argentina | Z29: Mexico | AA29: ARS | AB29: 9005104.1 | AC29: ARS | AD29: 5443360.3 | AE29: 39.55 | AF29: OK | AG29: 0 | AH29: 0 | AI29: 0.37 | AJ29: 0 | AK29: 0.39552496 | AL29: OK | AM29: 10573717 | AO29: Miss | AP29: Miss | AR29: Miss | AT29: Miss | AU29: 9005104.1 | AV29: 6444 | AW29: Miss | AX29: 9005104.1 | AY29: 6446.03 | AZ29: ARS | BA29: 5443360.3 | BB29: OK | BC29: 0.36 | BD29: 0 | BE29: {=IFERROR(INDEX('Com&tax'!$E$2:$E$5, MATCH(1, ('Com&tax'!$A$2:$A$5=B29)*('Com&tax'!$B$2:$B$5=G29), 0)),"")} -> 0.15 | BF29: =IF(A29="","",( IFERROR(O29*BE29,""))) -> 1350765.6 | BG29: {=IF(A29="","",( IFERROR((O29/ INDEX(er!$D$3:$D$75,MATCH(1, (er!$A$3:$A$75=$BG$2)*(er!$C$3:$C$75=Q29), 0)))*BE29,"")))} -> 966.90452 | BH29: =IF(A29="","",( IF(B29="Snapchat Rep", IF(A29="","",(P29-BF29)),-BF29))) -> -1350765.6 | BI29: {=IFERROR(INDEX('Com&tax'!$F$2:$F$5, MATCH(1, ('Com&tax'!$A$2:$A$5=B29)*('Com&tax'!$B$2:$B$5=Y29), 0)),0)} -> 0.049 | BJ29: =IF(A29="","",( IFERROR((J29*(1-BE29))*BI29,0))) -> 375062.59 | BK29: {=IF(A29="","",( IFERROR((J29*(1-BE29))*BI29/INDEX(er!D:D, MATCH(Q29,er!C:C,0),1),0)))} -> 268.47716 | BL29: {=IFERROR(INDEX('Com&tax'!$G$2:$G$5, MATCH(1, ('Com&tax'!$A$2:$A$5=B29)*('Com&tax'!$B$2:$B$5=Y29), 0)),0)} -> 0.1575 | BM29: =IF(A29="","",( IFERROR((J29*(1-BE29))*BL29,0))) -> 1205558.3 | BN29: {=IF(A29="","",( IFERROR((J29*(1-BE29))*BL29/INDEX(er!D:D, MATCH(Q29,er!C:C,0),1),0)))} -> 862.96229 | BO29: {=IFERROR(INDEX('Com&tax'!$H$2:$H$5, MATCH(1, ('Com&tax'!$A$2:$A$5=B29)*('Com&tax'!$B$2:$B$5=Y29), 0)),0)} -> 0.07 | BP29: =IF(A29="","",( IFERROR(J29*BO29,0))) -> 630357.29 | BQ29: {=IF(A29="","",( IFERROR(J29*BO29/INDEX(er!D:D, MATCH(Q29,er!C:C,0),1),0)))} -> 451.22211 | BR29: {=IFERROR(INDEX('Com&tax'!$F$2:$F$5, MATCH(1, ('Com&tax'!$A$2:$A$5=B29)*('Com&tax'!$D$2:$D$5=H29), 0)),0)} -> 0.049 | BS29: =IF(A29="","",( IFERROR((J29*(1-BE29))*BR29,0))) -> 375062.59 | BT29: {=IF(A29="","",( IFERROR((J29*(1-BE29))*BR29/INDEX(er!D:D, MATCH(Q29,er!C:C,0),1),0)))} -> 268.47716 | BU29: {=IFERROR(INDEX('Com&tax'!$G$2:$G$5, MATCH(1, ('Com&tax'!$A$2:$A$5=B29)*('Com&tax'!$D$2:$D$5=H29), 0)),0)} -> 0.1575 | BV29: =IF(A29="","",( IFERROR((J29*(1-BE29))*BU29,0))) -> 1205558.3 | BW29: {=IF(A29="","",( IFERROR((J29*(1-BE29))*BU29/INDEX(er!D:D, MATCH(Q29,er!C:C,0),1),0)))} -> 862.96229 | BX29: {=IFERROR(INDEX('Com&tax'!$H$2:$H$5, MATCH(1, ('Com&tax'!$A$2:$A$5=B29)*('Com&tax'!$D$2:$D$5=H29), 0)),0)} -> 0.07 | BY29: =IF(A29="","",( IFERROR(J29*BX29,0))) -> 630357.29 | BZ29: {=IF(A29="","",( IFERROR(J29*BX29/INDEX(er!D:D, MATCH(Q29,er!C:C,0),1),0)))} -> 451.22211 | CA29: {=IF(A29="","",( IFERROR(1-((P29/ INDEX(er!$D$3:$D$75,MATCH(1, (er!$A$3:$A$75=$BG$2)*(er!$C$3:$C$75=Q29), 0)) / (J29/ INDEX(er!$D$3:$D$75,MATCH(1, (er!$A$3:$A$75=$BG$2)*(er!$C$3:$C$75=L29), 0))))),"")))} -> 0.39552496 | CB29: =IF(AB29="","",1-AD29/AB29) -> 0.395525 | CC29: =IF(AND(CA29="", CB29=""), "", CA29-CB29) -> -4.1087809e-08 | CD29: =BJ29+BM29-BS29-BV29 -> 0 | CE29: =BK29+BN29-BT29-BW29 -> 0 | CF29: =AJ29-CE29 -> 0 | CG29: =IF(OR(BE29="", AE29=""), "Miss", IF(ABS(AE29/100-AK29)<0.005, "OK", "Incorrect")) -> OK | CI29: OK | CK29: 0 | CL29: =(AI29+CK29)/INDEX(er!D:D,MATCH(AC29,er!C:C,0),1) -> 0.00026485326 | CN29: =CK29/INDEX(er!D:D,MATCH(AC29,er!C:C,0),1) -> 0
A30: T3218548 | B30: Twitter Rep | C30: IMS | D30: AR_Media Company_Telecom Argentina SA Argentina_AR00395703 | X | Personal | Flow - Lollapalooza - Mar 26 | E30: SO Exported to ERP | G30: Argentina | H30: Aleph Argentina | I30: Argentina | J30: 241926.19 | K30: 241926.19 | L30: ARS | M30: 241926.19 | N30: ARS | O30: 241926.19 | P30: 146238.34 | Q30: ARS | R30: Mexico | U30: 0 | V30: 2026-02 | W30: February/2026 | X30: IMS | Y30: Argentina | Z30: Mexico | AA30: ARS | AB30: 241926.19 | AC30: ARS | AD30: 188702.43 | AE30: 22 | AF30: OK | AG30: 0 | AH30: 0 | AI30: -42464.09 | AJ30: -30.4 | AK30: 0.39552497 | AL30: OK | AM30: 10573667 | AO30: Miss | AP30: Miss | AR30: Miss | AT30: Miss | AU30: 241926.19 | AV30: 171 | AW30: Miss | AX30: 241926.19 | AY30: 173.18 | AZ30: ARS | BA30: 188702.43 | BB30: OK | BC30: -42464.09 | BD30: -30.4 | BE30: {=IFERROR(INDEX('Com&tax'!$E$2:$E$5, MATCH(1, ('Com&tax'!$A$2:$A$5=B30)*('Com&tax'!$B$2:$B$5=G30), 0)),"")} -> 0.15 | BF30: =IF(A30="","",( IFERROR(O30*BE30,""))) -> 36288.929 | BG30: {=IF(A30="","",( IFERROR((O30/ INDEX(er!$D$3:$D$75,MATCH(1, (er!$A$3:$A$75=$BG$2)*(er!$C$3:$C$75=Q30), 0)))*BE30,"")))} -> 25.976327 | BH30: =IF(A30="","",( IF(B30="Snapchat Rep", IF(A30="","",(P30-BF30)),-BF30))) -> -36288.929 | BI30: {=IFERROR(INDEX('Com&tax'!$F$2:$F$5, MATCH(1, ('Com&tax'!$A$2:$A$5=B30)*('Com&tax'!$B$2:$B$5=Y30), 0)),0)} -> 0.049 | BJ30: =IF(A30="","",( IFERROR((J30*(1-BE30))*BI30,0))) -> 10076.226 | BK30: {=IF(A30="","",( IFERROR((J30*(1-BE30))*BI30/INDEX(er!D:D, MATCH(Q30,er!C:C,0),1),0)))} -> 7.2127601 | BL30: {=IFERROR(INDEX('Com&tax'!$G$2:$G$5, MATCH(1, ('Com&tax'!$A$2:$A$5=B30)*('Com&tax'!$B$2:$B$5=Y30), 0)),0)} -> 0.1575 | BM30: =IF(A30="","",( IFERROR((J30*(1-BE30))*BL30,0))) -> 32387.869 | BN30: {=IF(A30="","",( IFERROR((J30*(1-BE30))*BL30/INDEX(er!D:D, MATCH(Q30,er!C:C,0),1),0)))} -> 23.183872 | BO30: {=IFERROR(INDEX('Com&tax'!$H$2:$H$5, MATCH(1, ('Com&tax'!$A$2:$A$5=B30)*('Com&tax'!$B$2:$B$5=Y30), 0)),0)} -> 0.07 | BP30: =IF(A30="","",( IFERROR(J30*BO30,0))) -> 16934.833 | BQ30: {=IF(A30="","",( IFERROR(J30*BO30/INDEX(er!D:D, MATCH(Q30,er!C:C,0),1),0)))} -> 12.122286 | BR30: {=IFERROR(INDEX('Com&tax'!$F$2:$F$5, MATCH(1, ('Com&tax'!$A$2:$A$5=B30)*('Com&tax'!$D$2:$D$5=H30), 0)),0)} -> 0.049 | BS30: =IF(A30="","",( IFERROR((J30*(1-BE30))*BR30,0))) -> 10076.226 | BT30: {=IF(A30="","",( IFERROR((J30*(1-BE30))*BR30/INDEX(er!D:D, MATCH(Q30,er!C:C,0),1),0)))} -> 7.2127601 | BU30: {=IFERROR(INDEX('Com&tax'!$G$2:$G$5, MATCH(1, ('Com&tax'!$A$2:$A$5=B30)*('Com&tax'!$D$2:$D$5=H30), 0)),0)} -> 0.1575 | BV30: =IF(A30="","",( IFERROR((J30*(1-BE30))*BU30,0))) -> 32387.869 | BW30: {=IF(A30="","",( IFERROR((J30*(1-BE30))*BU30/INDEX(er!D:D, MATCH(Q30,er!C:C,0),1),0)))} -> 23.183872 | BX30: {=IFERROR(INDEX('Com&tax'!$H$2:$H$5, MATCH(1, ('Com&tax'!$A$2:$A$5=B30)*('Com&tax'!$D$2:$D$5=H30), 0)),0)} -> 0.07 | BY30: =IF(A30="","",( IFERROR(J30*BX30,0))) -> 16934.833 | BZ30: {=IF(A30="","",( IFERROR(J30*BX30/INDEX(er!D:D, MATCH(Q30,er!C:C,0),1),0)))} -> 12.122286 | CA30: {=IF(A30="","",( IFERROR(1-((P30/ INDEX(er!$D$3:$D$75,MATCH(1, (er!$A$3:$A$75=$BG$2)*(er!$C$3:$C$75=Q30), 0)) / (J30/ INDEX(er!$D$3:$D$75,MATCH(1, (er!$A$3:$A$75=$BG$2)*(er!$C$3:$C$75=L30), 0))))),"")))} -> 0.39552497 | CB30: =IF(AB30="","",1-AD30/AB30) -> 0.21999999 | CC30: =IF(AND(CA30="", CB30=""), "", CA30-CB30) -> 0.17552498 | CD30: =BJ30+BM30-BS30-BV30 -> 0 | CE30: =BK30+BN30-BT30-BW30 -> 0 | CF30: =AJ30-CE30 -> -30.4 | CG30: =IF(OR(BE30="", AE30=""), "Miss", IF(ABS(AE30/100-AK30)<0.005, "OK", "Incorrect")) -> Incorrect | CI30: OK. Twitter tax err. | CK30: 42464.094 | CL30: =(AI30+CK30)/INDEX(er!D:D,MATCH(AC30,er!C:C,0),1) -> 3.2210093e-06 | CN30: =CK30/INDEX(er!D:D,MATCH(AC30,er!C:C,0),1) -> 30.396632
A31: T3219252 | B31: Twitter Rep | C31: IMS | D31: AR_Media Company_YPF S.A. ARGENTINA_AR00396301-X-YPF-COMBUSTIBLES-VERANO-Dic/Ene 26 | G31: Argentina | H31: Aleph Argentina | I31: Argentina | J31: 1677857.2 | K31: 1677857.2 | L31: ARS | M31: 1677857.2 | N31: ARS | O31: 1677857.2 | P31: 1014222.8 | Q31: ARS | R31: Mexico | U31: 0 | V31: 2026-02 | W31: February/2026 | X31: IMS | Y31: Argentina | Z31: Mexico | AA31: ARS | AB31: 1677857.2 | AC31: ARS | AD31: 1014222.7 | AE31: 39.55 | AF31: OK | AG31: 0 | AH31: 0 | AI31: 0.06 | AJ31: 0 | AK31: 0.39552496 | AL31: OK | AM31: 10573736 | AO31: Miss | AP31: Miss | AR31: Miss | AT31: Miss | AU31: 1677857.2 | AV31: 1199 | AW31: Miss | AX31: 1677857.2 | AY31: 1201.04 | AZ31: ARS | BA31: 1014222.7 | BB31: OK | BC31: 0.06 | BD31: 0 | BE31: {=IFERROR(INDEX('Com&tax'!$E$2:$E$5, MATCH(1, ('Com&tax'!$A$2:$A$5=B31)*('Com&tax'!$B$2:$B$5=G31), 0)),"")} -> 0.15 | BF31: =IF(A31="","",( IFERROR(O31*BE31,""))) -> 251678.57 | BG31: {=IF(A31="","",( IFERROR((O31/ INDEX(er!$D$3:$D$75,MATCH(1, (er!$A$3:$A$75=$BG$2)*(er!$C$3:$C$75=Q31), 0)))*BE31,"")))} -> 180.15646 | BH31: =IF(A31="","",( IF(B31="Snapchat Rep", IF(A31="","",(P31-BF31)),-BF31))) -> -251678.57 | BI31: {=IFERROR(INDEX('Com&tax'!$F$2:$F$5, MATCH(1, ('Com&tax'!$A$2:$A$5=B31)*('Com&tax'!$B$2:$B$5=Y31), 0)),0)} -> 0.049 | BJ31: =IF(A31="","",( IFERROR((J31*(1-BE31))*BI31,0))) -> 69882.751 | BK31: {=IF(A31="","",( IFERROR((J31*(1-BE31))*BI31/INDEX(er!D:D, MATCH(Q31,er!C:C,0),1),0)))} -> 50.023444 | BL31: {=IFERROR(INDEX('Com&tax'!$G$2:$G$5, MATCH(1, ('Com&tax'!$A$2:$A$5=B31)*('Com&tax'!$B$2:$B$5=Y31), 0)),0)} -> 0.1575 | BM31: =IF(A31="","",( IFERROR((J31*(1-BE31))*BL31,0))) -> 224623.13 | BN31: {=IF(A31="","",( IFERROR((J31*(1-BE31))*BL31/INDEX(er!D:D, MATCH(Q31,er!C:C,0),1),0)))} -> 160.78964 | BO31: {=IFERROR(INDEX('Com&tax'!$H$2:$H$5, MATCH(1, ('Com&tax'!$A$2:$A$5=B31)*('Com&tax'!$B$2:$B$5=Y31), 0)),0)} -> 0.07 | BP31: =IF(A31="","",( IFERROR(J31*BO31,0))) -> 117450 | BQ31: {=IF(A31="","",( IFERROR(J31*BO31/INDEX(er!D:D, MATCH(Q31,er!C:C,0),1),0)))} -> 84.073014 | BR31: {=IFERROR(INDEX('Com&tax'!$F$2:$F$5, MATCH(1, ('Com&tax'!$A$2:$A$5=B31)*('Com&tax'!$D$2:$D$5=H31), 0)),0)} -> 0.049 | BS31: =IF(A31="","",( IFERROR((J31*(1-BE31))*BR31,0))) -> 69882.751 | BT31: {=IF(A31="","",( IFERROR((J31*(1-BE31))*BR31/INDEX(er!D:D, MATCH(Q31,er!C:C,0),1),0)))} -> 50.023444 | BU31: {=IFERROR(INDEX('Com&tax'!$G$2:$G$5, MATCH(1, ('Com&tax'!$A$2:$A$5=B31)*('Com&tax'!$D$2:$D$5=H31), 0)),0)} -> 0.1575 | BV31: =IF(A31="","",( IFERROR((J31*(1-BE31))*BU31,0))) -> 224623.13 | BW31: {=IF(A31="","",( IFERROR((J31*(1-BE31))*BU31/INDEX(er!D:D, MATCH(Q31,er!C:C,0),1),0)))} -> 160.78964 | BX31: {=IFERROR(INDEX('Com&tax'!$H$2:$H$5, MATCH(1, ('Com&tax'!$A$2:$A$5=B31)*('Com&tax'!$D$2:$D$5=H31), 0)),0)} -> 0.07 | BY31: =IF(A31="","",( IFERROR(J31*BX31,0))) -> 117450 | BZ31: {=IF(A31="","",( IFERROR(J31*BX31/INDEX(er!D:D, MATCH(Q31,er!C:C,0),1),0)))} -> 84.073014 | CA31: {=IF(A31="","",( IFERROR(1-((P31/ INDEX(er!$D$3:$D$75,MATCH(1, (er!$A$3:$A$75=$BG$2)*(er!$C$3:$C$75=Q31), 0)) / (J31/ INDEX(er!$D$3:$D$75,MATCH(1, (er!$A$3:$A$75=$BG$2)*(er!$C$3:$C$75=L31), 0))))),"")))} -> 0.39552496 | CB31: =IF(AB31="","",1-AD31/AB31) -> 0.395525 | CC31: =IF(AND(CA31="", CB31=""), "", CA31-CB31) -> -3.5759897e-08 | CD31: =BJ31+BM31-BS31-BV31 -> 0 | CE31: =BK31+BN31-BT31-BW31 -> 0 | CF31: =AJ31-CE31 -> 0 | CG31: =IF(OR(BE31="", AE31=""), "Miss", IF(ABS(AE31/100-AK31)<0.005, "OK", "Incorrect")) -> OK | CI31: OK | CK31: 0 | CL31: =(AI31+CK31)/INDEX(er!D:D,MATCH(AC31,er!C:C,0),1) -> 4.2949177e-05 | CN31: =CK31/INDEX(er!D:D,MATCH(AC31,er!C:C,0),1) -> 0
A32: T3219531 | B32: Twitter Billing | C32: IMS | D32: AR_Media Company_Mercado Libre Argentina_T3219531 - MLA | Campaña Verano - 28/12/2025 | G32: Argentina | H32: Aleph Argentina | I32: Argentina | J32: 1952420.4 | K32: 1952420.4 | L32: ARS | M32: 1952420.4 | N32: ARS | O32: 1952420.4 | P32: 1288587.7 | Q32: ARS | R32: Mexico | U32: 0 | V32: 2026-02 | W32: February/2026 | X32: IMS | Y32: Argentina | Z32: Mexico | AA32: ARS | AB32: 1952420.4 | AC32: ARS | AD32: 1288636.5 | AE32: 34 | AF32: OK | AG32: 0 | AH32: 0 | AI32: -48.81 | AJ32: -0.03 | AK32: 0.340005 | AL32: OK | AM32: 10573702 | AO32: Miss | AP32: Miss | AR32: Miss | AT32: Miss | AU32: 1952420.4 | AV32: 1396 | AW32: Miss | AX32: 1952420.4 | AY32: 1397.58 | AZ32: ARS | BA32: 1288636.5 | BB32: OK | BC32: -48.81 | BD32: -0.03 | BE32: {=IFERROR(INDEX('Com&tax'!$E$2:$E$5, MATCH(1, ('Com&tax'!$A$2:$A$5=B32)*('Com&tax'!$B$2:$B$5=G32), 0)),"")} -> 0.15 | BF32: =IF(A32="","",( IFERROR(O32*BE32,""))) -> 292863.07 | BG32: {=IF(A32="","",( IFERROR((O32/ INDEX(er!$D$3:$D$75,MATCH(1, (er!$A$3:$A$75=$BG$2)*(er!$C$3:$C$75=Q32), 0)))*BE32,"")))} -> 209.63713 | BH32: =IF(A32="","",( IF(B32="Snapchat Rep", IF(A32="","",(P32-BF32)),-BF32))) -> -292863.07 | BI32: {=IFERROR(INDEX('Com&tax'!$F$2:$F$5, MATCH(1, ('Com&tax'!$A$2:$A$5=B32)*('Com&tax'!$B$2:$B$5=Y32), 0)),0)} -> 0.049 | BJ32: =IF(A32="","",( IFERROR((J32*(1-BE32))*BI32,0))) -> 81318.311 | BK32: {=IF(A32="","",( IFERROR((J32*(1-BE32))*BI32/INDEX(er!D:D, MATCH(Q32,er!C:C,0),1),0)))} -> 58.209242 | BL32: {=IFERROR(INDEX('Com&tax'!$G$2:$G$5, MATCH(1, ('Com&tax'!$A$2:$A$5=B32)*('Com&tax'!$B$2:$B$5=Y32), 0)),0)} -> 0.1575 | BM32: =IF(A32="","",( IFERROR((J32*(1-BE32))*BL32,0))) -> 261380.29 | BN32: {=IF(A32="","",( IFERROR((J32*(1-BE32))*BL32/INDEX(er!D:D, MATCH(Q32,er!C:C,0),1),0)))} -> 187.10114 | BO32: {=IFERROR(INDEX('Com&tax'!$H$2:$H$5, MATCH(1, ('Com&tax'!$A$2:$A$5=B32)*('Com&tax'!$B$2:$B$5=Y32), 0)),0)} -> 0 | BP32: =IF(A32="","",( IFERROR(J32*BO32,0))) -> 0 | BQ32: {=IF(A32="","",( IFERROR(J32*BO32/INDEX(er!D:D, MATCH(Q32,er!C:C,0),1),0)))} -> 0 | BR32: {=IFERROR(INDEX('Com&tax'!$F$2:$F$5, MATCH(1, ('Com&tax'!$A$2:$A$5=B32)*('Com&tax'!$D$2:$D$5=H32), 0)),0)} -> 0.049 | BS32: =IF(A32="","",( IFERROR((J32*(1-BE32))*BR32,0))) -> 81318.311 | BT32: {=IF(A32="","",( IFERROR((J32*(1-BE32))*BR32/INDEX(er!D:D, MATCH(Q32,er!C:C,0),1),0)))} -> 58.209242 | BU32: {=IFERROR(INDEX('Com&tax'!$G$2:$G$5, MATCH(1, ('Com&tax'!$A$2:$A$5=B32)*('Com&tax'!$D$2:$D$5=H32), 0)),0)} -> 0.1575 | BV32: =IF(A32="","",( IFERROR((J32*(1-BE32))*BU32,0))) -> 261380.29 | BW32: {=IF(A32="","",( IFERROR((J32*(1-BE32))*BU32/INDEX(er!D:D, MATCH(Q32,er!C:C,0),1),0)))} -> 187.10114 | BX32: {=IFERROR(INDEX('Com&tax'!$H$2:$H$5, MATCH(1, ('Com&tax'!$A$2:$A$5=B32)*('Com&tax'!$D$2:$D$5=H32), 0)),0)} -> 0 | BY32: =IF(A32="","",( IFERROR(J32*BX32,0))) -> 0 | BZ32: {=IF(A32="","",( IFERROR(J32*BX32/INDEX(er!D:D, MATCH(Q32,er!C:C,0),1),0)))} -> 0 | CA32: {=IF(A32="","",( IFERROR(1-((P32/ INDEX(er!$D$3:$D$75,MATCH(1, (er!$A$3:$A$75=$BG$2)*(er!$C$3:$C$75=Q32), 0)) / (J32/ INDEX(er!$D$3:$D$75,MATCH(1, (er!$A$3:$A$75=$BG$2)*(er!$C$3:$C$75=L32), 0))))),"")))} -> 0.340005 | CB32: =IF(AB32="","",1-AD32/AB32) -> 0.33998 | CC32: =IF(AND(CA32="", CB32=""), "", CA32-CB32) -> 2.4999738e-05 | CD32: =BJ32+BM32-BS32-BV32 -> 0 | CE32: =BK32+BN32-BT32-BW32 -> 0 | CF32: =AJ32-CE32 -> -0.03 | CG32: =IF(OR(BE32="", AE32=""), "Miss", IF(ABS(AE32/100-AK32)<0.005, "OK", "Incorrect")) -> OK | CI32: OK | CK32: 0 | CL32: =(AI32+CK32)/INDEX(er!D:D,MATCH(AC32,er!C:C,0),1) -> -0.034939155 | CN32: =CK32/INDEX(er!D:D,MATCH(AC32,er!C:C,0),1) -> 0
A33: T3221498 | B33: Twitter Rep | C33: IMS | D33: AR_Media Company_CERVECERIA Y MALTERIA QUILMES SAICA Y G ARGENTINA_AR00396561-X-ABI ARG-SED DE BRAHMA VERANO-Ene-25 | G33: Argentina | H33: Aleph Argentina | I33: Argentina | J33: 9577518.7 | K33: 9577518.7 | L33: ARS | M33: 9577518.7 | N33: ARS | O33: 9577518.7 | P33: 5789371 | Q33: ARS | R33: Mexico | U33: 0 | V33: 2026-02 | W33: February/2026 | X33: IMS | Y33: Argentina | Z33: Mexico | AA33: ARS | AB33: 9577518.7 | AC33: ARS | AD33: 5789370.6 | AE33: 39.55 | AF33: OK | AG33: 0 | AH33: 0 | AI33: 0.39 | AJ33: 0 | AK33: 0.39552496 | AL33: OK | AM33: 10573692 | AO33: Miss | AP33: Miss | AR33: Miss | AT33: Miss | AU33: 9577518.7 | AV33: 6854 | AW33: Miss | AX33: 9577518.7 | AY33: 6855.78 | AZ33: ARS | BA33: 5789370.6 | BB33: OK | BC33: 0.39 | BD33: 0 | BE33: {=IFERROR(INDEX('Com&tax'!$E$2:$E$5, MATCH(1, ('Com&tax'!$A$2:$A$5=B33)*('Com&tax'!$B$2:$B$5=G33), 0)),"")} -> 0.15 | BF33: =IF(A33="","",( IFERROR(O33*BE33,""))) -> 1436627.8 | BG33: {=IF(A33="","",( IFERROR((O33/ INDEX(er!$D$3:$D$75,MATCH(1, (er!$A$3:$A$75=$BG$2)*(er!$C$3:$C$75=Q33), 0)))*BE33,"")))} -> 1028.3664 | BH33: =IF(A33="","",( IF(B33="Snapchat Rep", IF(A33="","",(P33-BF33)),-BF33))) -> -1436627.8 | BI33: {=IFERROR(INDEX('Com&tax'!$F$2:$F$5, MATCH(1, ('Com&tax'!$A$2:$A$5=B33)*('Com&tax'!$B$2:$B$5=Y33), 0)),0)} -> 0.049 | BJ33: =IF(A33="","",( IFERROR((J33*(1-BE33))*BI33,0))) -> 398903.65 | BK33: {=IF(A33="","",( IFERROR((J33*(1-BE33))*BI33/INDEX(er!D:D, MATCH(Q33,er!C:C,0),1),0)))} -> 285.54306 | BL33: {=IFERROR(INDEX('Com&tax'!$G$2:$G$5, MATCH(1, ('Com&tax'!$A$2:$A$5=B33)*('Com&tax'!$B$2:$B$5=Y33), 0)),0)} -> 0.1575 | BM33: =IF(A33="","",( IFERROR((J33*(1-BE33))*BL33,0))) -> 1282190.3 | BN33: {=IF(A33="","",( IFERROR((J33*(1-BE33))*BL33/INDEX(er!D:D, MATCH(Q33,er!C:C,0),1),0)))} -> 917.81697 | BO33: {=IFERROR(INDEX('Com&tax'!$H$2:$H$5, MATCH(1, ('Com&tax'!$A$2:$A$5=B33)*('Com&tax'!$B$2:$B$5=Y33), 0)),0)} -> 0.07 | BP33: =IF(A33="","",( IFERROR(J33*BO33,0))) -> 670426.31 | BQ33: {=IF(A33="","",( IFERROR(J33*BO33/INDEX(er!D:D, MATCH(Q33,er!C:C,0),1),0)))} -> 479.9043 | BR33: {=IFERROR(INDEX('Com&tax'!$F$2:$F$5, MATCH(1, ('Com&tax'!$A$2:$A$5=B33)*('Com&tax'!$D$2:$D$5=H33), 0)),0)} -> 0.049 | BS33: =IF(A33="","",( IFERROR((J33*(1-BE33))*BR33,0))) -> 398903.65 | BT33: {=IF(A33="","",( IFERROR((J33*(1-BE33))*BR33/INDEX(er!D:D, MATCH(Q33,er!C:C,0),1),0)))} -> 285.54306 | BU33: {=IFERROR(INDEX('Com&tax'!$G$2:$G$5, MATCH(1, ('Com&tax'!$A$2:$A$5=B33)*('Com&tax'!$D$2:$D$5=H33), 0)),0)} -> 0.1575 | BV33: =IF(A33="","",( IFERROR((J33*(1-BE33))*BU33,0))) -> 1282190.3 | BW33: {=IF(A33="","",( IFERROR((J33*(1-BE33))*BU33/INDEX(er!D:D, MATCH(Q33,er!C:C,0),1),0)))} -> 917.81697 | BX33: {=IFERROR(INDEX('Com&tax'!$H$2:$H$5, MATCH(1, ('Com&tax'!$A$2:$A$5=B33)*('Com&tax'!$D$2:$D$5=H33), 0)),0)} -> 0.07 | BY33: =IF(A33="","",( IFERROR(J33*BX33,0))) -> 670426.31 | BZ33: {=IF(A33="","",( IFERROR(J33*BX33/INDEX(er!D:D, MATCH(Q33,er!C:C,0),1),0)))} -> 479.9043 | CA33: {=IF(A33="","",( IFERROR(1-((P33/ INDEX(er!$D$3:$D$75,MATCH(1, (er!$A$3:$A$75=$BG$2)*(er!$C$3:$C$75=Q33), 0)) / (J33/ INDEX(er!$D$3:$D$75,MATCH(1, (er!$A$3:$A$75=$BG$2)*(er!$C$3:$C$75=L33), 0))))),"")))} -> 0.39552496 | CB33: =IF(AB33="","",1-AD33/AB33) -> 0.395525 | CC33: =IF(AND(CA33="", CB33=""), "", CA33-CB33) -> -4.0720359e-08 | CD33: =BJ33+BM33-BS33-BV33 -> 0 | CE33: =BK33+BN33-BT33-BW33 -> 0 | CF33: =AJ33-CE33 -> 0 | CG33: =IF(OR(BE33="", AE33=""), "Miss", IF(ABS(AE33/100-AK33)<0.005, "OK", "Incorrect")) -> OK | CI33: OK | CK33: 0 | CL33: =(AI33+CK33)/INDEX(er!D:D,MATCH(AC33,er!C:C,0),1) -> 0.00027916965 | CN33: =CK33/INDEX(er!D:D,MATCH(AC33,er!C:C,0),1) -> 0
A34: T3221499 | B34: Twitter Rep | C34: IMS | D34: AR_Media Company_CERVECERIA Y MALTERIA QUILMES SAICA Y G ARGENTINA_AR00396558-X-ABI ARG-SED DE BRAHMA CARNAVAL-Ene-26 | G34: Argentina | H34: Aleph Argentina | I34: Argentina | J34: 894756.91 | K34: 894756.91 | L34: ARS | M34: 894756.91 | N34: ARS | O34: 894756.91 | P34: 540858.22 | Q34: ARS | R34: Mexico | U34: 0 | V34: 2026-02 | W34: February/2026 | X34: IMS | Y34: Argentina | Z34: Mexico | AA34: ARS | AB34: 894756.91 | AC34: ARS | AD34: 540858.18 | AE34: 39.55 | AF34: OK | AG34: 0 | AH34: 0 | AI34: 0.04 | AJ34: 0 | AK34: 0.39552496 | AL34: OK | AM34: 10573693 | AO34: Miss | AP34: Miss | AR34: Miss | AT34: Miss | AU34: 894756.91 | AV34: 638 | AW34: Miss | AX34: 894756.91 | AY34: 640.48 | AZ34: ARS | BA34: 540858.19 | BB34: OK | BC34: 0.03 | BD34: 0 | BE34: {=IFERROR(INDEX('Com&tax'!$E$2:$E$5, MATCH(1, ('Com&tax'!$A$2:$A$5=B34)*('Com&tax'!$B$2:$B$5=G34), 0)),"")} -> 0.15 | BF34: =IF(A34="","",( IFERROR(O34*BE34,""))) -> 134213.54 | BG34: {=IF(A34="","",( IFERROR((O34/ INDEX(er!$D$3:$D$75,MATCH(1, (er!$A$3:$A$75=$BG$2)*(er!$C$3:$C$75=Q34), 0)))*BE34,"")))} -> 96.072682 | BH34: =IF(A34="","",( IF(B34="Snapchat Rep", IF(A34="","",(P34-BF34)),-BF34))) -> -134213.54 | BI34: {=IFERROR(INDEX('Com&tax'!$F$2:$F$5, MATCH(1, ('Com&tax'!$A$2:$A$5=B34)*('Com&tax'!$B$2:$B$5=Y34), 0)),0)} -> 0.049 | BJ34: =IF(A34="","",( IFERROR((J34*(1-BE34))*BI34,0))) -> 37266.625 | BK34: {=IF(A34="","",( IFERROR((J34*(1-BE34))*BI34/INDEX(er!D:D, MATCH(Q34,er!C:C,0),1),0)))} -> 26.676181 | BL34: {=IFERROR(INDEX('Com&tax'!$G$2:$G$5, MATCH(1, ('Com&tax'!$A$2:$A$5=B34)*('Com&tax'!$B$2:$B$5=Y34), 0)),0)} -> 0.1575 | BM34: =IF(A34="","",( IFERROR((J34*(1-BE34))*BL34,0))) -> 119785.58 | BN34: {=IF(A34="","",( IFERROR((J34*(1-BE34))*BL34/INDEX(er!D:D, MATCH(Q34,er!C:C,0),1),0)))} -> 85.744869 | BO34: {=IFERROR(INDEX('Com&tax'!$H$2:$H$5, MATCH(1, ('Com&tax'!$A$2:$A$5=B34)*('Com&tax'!$B$2:$B$5=Y34), 0)),0)} -> 0.07 | BP34: =IF(A34="","",( IFERROR(J34*BO34,0))) -> 62632.984 | BQ34: {=IF(A34="","",( IFERROR(J34*BO34/INDEX(er!D:D, MATCH(Q34,er!C:C,0),1),0)))} -> 44.833918 | BR34: {=IFERROR(INDEX('Com&tax'!$F$2:$F$5, MATCH(1, ('Com&tax'!$A$2:$A$5=B34)*('Com&tax'!$D$2:$D$5=H34), 0)),0)} -> 0.049 | BS34: =IF(A34="","",( IFERROR((J34*(1-BE34))*BR34,0))) -> 37266.625 | BT34: {=IF(A34="","",( IFERROR((J34*(1-BE34))*BR34/INDEX(er!D:D, MATCH(Q34,er!C:C,0),1),0)))} -> 26.676181 | BU34: {=IFERROR(INDEX('Com&tax'!$G$2:$G$5, MATCH(1, ('Com&tax'!$A$2:$A$5=B34)*('Com&tax'!$D$2:$D$5=H34), 0)),0)} -> 0.1575 | BV34: =IF(A34="","",( IFERROR((J34*(1-BE34))*BU34,0))) -> 119785.58 | BW34: {=IF(A34="","",( IFERROR((J34*(1-BE34))*BU34/INDEX(er!D:D, MATCH(Q34,er!C:C,0),1),0)))} -> 85.744869 | BX34: {=IFERROR(INDEX('Com&tax'!$H$2:$H$5, MATCH(1, ('Com&tax'!$A$2:$A$5=B34)*('Com&tax'!$D$2:$D$5=H34), 0)),0)} -> 0.07 | BY34: =IF(A34="","",( IFERROR(J34*BX34,0))) -> 62632.984 | BZ34: {=IF(A34="","",( IFERROR(J34*BX34/INDEX(er!D:D, MATCH(Q34,er!C:C,0),1),0)))} -> 44.833918 | CA34: {=IF(A34="","",( IFERROR(1-((P34/ INDEX(er!$D$3:$D$75,MATCH(1, (er!$A$3:$A$75=$BG$2)*(er!$C$3:$C$75=Q34), 0)) / (J34/ INDEX(er!$D$3:$D$75,MATCH(1, (er!$A$3:$A$75=$BG$2)*(er!$C$3:$C$75=L34), 0))))),"")))} -> 0.39552496 | CB34: =IF(AB34="","",1-AD34/AB34) -> 0.395525 | CC34: =IF(AND(CA34="", CB34=""), "", CA34-CB34) -> -4.470488e-08 | CD34: =BJ34+BM34-BS34-BV34 -> 0 | CE34: =BK34+BN34-BT34-BW34 -> 0 | CF34: =AJ34-CE34 -> 0 | CG34: =IF(OR(BE34="", AE34=""), "Miss", IF(ABS(AE34/100-AK34)<0.005, "OK", "Incorrect")) -> OK | CI34: OK | CK34: 0 | CL34: =(AI34+CK34)/INDEX(er!D:D,MATCH(AC34,er!C:C,0),1) -> 2.8632785e-05 | CN34: =CK34/INDEX(er!D:D,MATCH(AC34,er!C:C,0),1) -> 0
A35: T3221580 | B35: Twitter Billing | C35: IMS | D35: AR_Media Company_UIP Argentina_T3221580 - UIP Argentina | Hamnet - 01/01/2026 | G35: Argentina | H35: Aleph Argentina | I35: Argentina | J35: 1353203.4 | K35: 1353203.4 | L35: ARS | M35: 1353203.4 | N35: ARS | O35: 1353203.4 | P35: 893107.5 | Q35: ARS | R35: Mexico | U35: 0 | V35: 2026-02 | W35: February/2026 | X35: IMS | Y35: Argentina | Z35: Mexico | AA35: ARS | AB35: 1353203.4 | AC35: ARS | AD35: 893141.33 | AE35: 34 | AF35: OK | AG35: 0 | AH35: 0 | AI35: -33.83 | AJ35: -0.02 | AK35: 0.340005 | AL35: OK | AM35: 10573699 | AO35: Miss | AP35: Miss | AR35: Miss | AT35: Miss | AU35: 1353203.4 | AV35: 967 | AW35: Miss | AX35: 1353203.4 | AY35: 968.65 | AZ35: ARS | BA35: 893141.33 | BB35: OK | BC35: -33.83 | BD35: -0.02 | BE35: {=IFERROR(INDEX('Com&tax'!$E$2:$E$5, MATCH(1, ('Com&tax'!$A$2:$A$5=B35)*('Com&tax'!$B$2:$B$5=G35), 0)),"")} -> 0.15 | BF35: =IF(A35="","",( IFERROR(O35*BE35,""))) -> 202980.52 | BG35: {=IF(A35="","",( IFERROR((O35/ INDEX(er!$D$3:$D$75,MATCH(1, (er!$A$3:$A$75=$BG$2)*(er!$C$3:$C$75=Q35), 0)))*BE35,"")))} -> 145.29743 | BH35: =IF(A35="","",( IF(B35="Snapchat Rep", IF(A35="","",(P35-BF35)),-BF35))) -> -202980.52 | BI35: {=IFERROR(INDEX('Com&tax'!$F$2:$F$5, MATCH(1, ('Com&tax'!$A$2:$A$5=B35)*('Com&tax'!$B$2:$B$5=Y35), 0)),0)} -> 0.049 | BJ35: =IF(A35="","",( IFERROR((J35*(1-BE35))*BI35,0))) -> 56360.923 | BK35: {=IF(A35="","",( IFERROR((J35*(1-BE35))*BI35/INDEX(er!D:D, MATCH(Q35,er!C:C,0),1),0)))} -> 40.344254 | BL35: {=IFERROR(INDEX('Com&tax'!$G$2:$G$5, MATCH(1, ('Com&tax'!$A$2:$A$5=B35)*('Com&tax'!$B$2:$B$5=Y35), 0)),0)} -> 0.1575 | BM35: =IF(A35="","",( IFERROR((J35*(1-BE35))*BL35,0))) -> 181160.11 | BN35: {=IF(A35="","",( IFERROR((J35*(1-BE35))*BL35/INDEX(er!D:D, MATCH(Q35,er!C:C,0),1),0)))} -> 129.67796 | BO35: {=IFERROR(INDEX('Com&tax'!$H$2:$H$5, MATCH(1, ('Com&tax'!$A$2:$A$5=B35)*('Com&tax'!$B$2:$B$5=Y35), 0)),0)} -> 0 | BP35: =IF(A35="","",( IFERROR(J35*BO35,0))) -> 0 | BQ35: {=IF(A35="","",( IFERROR(J35*BO35/INDEX(er!D:D, MATCH(Q35,er!C:C,0),1),0)))} -> 0 | BR35: {=IFERROR(INDEX('Com&tax'!$F$2:$F$5, MATCH(1, ('Com&tax'!$A$2:$A$5=B35)*('Com&tax'!$D$2:$D$5=H35), 0)),0)} -> 0.049 | BS35: =IF(A35="","",( IFERROR((J35*(1-BE35))*BR35,0))) -> 56360.923 | BT35: {=IF(A35="","",( IFERROR((J35*(1-BE35))*BR35/INDEX(er!D:D, MATCH(Q35,er!C:C,0),1),0)))} -> 40.344254 | BU35: {=IFERROR(INDEX('Com&tax'!$G$2:$G$5, MATCH(1, ('Com&tax'!$A$2:$A$5=B35)*('Com&tax'!$D$2:$D$5=H35), 0)),0)} -> 0.1575 | BV35: =IF(A35="","",( IFERROR((J35*(1-BE35))*BU35,0))) -> 181160.11 | BW35: {=IF(A35="","",( IFERROR((J35*(1-BE35))*BU35/INDEX(er!D:D, MATCH(Q35,er!C:C,0),1),0)))} -> 129.67796 | BX35: {=IFERROR(INDEX('Com&tax'!$H$2:$H$5, MATCH(1, ('Com&tax'!$A$2:$A$5=B35)*('Com&tax'!$D$2:$D$5=H35), 0)),0)} -> 0 | BY35: =IF(A35="","",( IFERROR(J35*BX35,0))) -> 0 | BZ35: {=IF(A35="","",( IFERROR(J35*BX35/INDEX(er!D:D, MATCH(Q35,er!C:C,0),1),0)))} -> 0 | CA35: {=IF(A35="","",( IFERROR(1-((P35/ INDEX(er!$D$3:$D$75,MATCH(1, (er!$A$3:$A$75=$BG$2)*(er!$C$3:$C$75=Q35), 0)) / (J35/ INDEX(er!$D$3:$D$75,MATCH(1, (er!$A$3:$A$75=$BG$2)*(er!$C$3:$C$75=L35), 0))))),"")))} -> 0.340005 | CB35: =IF(AB35="","",1-AD35/AB35) -> 0.33998 | CC35: =IF(AND(CA35="", CB35=""), "", CA35-CB35) -> 2.4999936e-05 | CD35: =BJ35+BM35-BS35-BV35 -> 0 | CE35: =BK35+BN35-BT35-BW35 -> 0 | CF35: =AJ35-CE35 -> -0.02 | CG35: =IF(OR(BE35="", AE35=""), "Miss", IF(ABS(AE35/100-AK35)<0.005, "OK", "Incorrect")) -> OK | CI35: OK | CK35: 0 | CL35: =(AI35+CK35)/INDEX(er!D:D,MATCH(AC35,er!C:C,0),1) -> -0.024216178 | CN35: =CK35/INDEX(er!D:D,MATCH(AC35,er!C:C,0),1) -> 0
A36: T3221584 | B36: Twitter Rep | C36: IMS | D36: AR_Media Company_Play Digital Argentina_X | MODO | AO Performance | G36: Argentina | H36: Aleph Argentina | I36: Argentina | J36: 2414313 | K36: 2414313 | L36: ARS | M36: 2414313 | N36: ARS | O36: 2414313 | P36: 1459391.9 | Q36: ARS | R36: Mexico | U36: 0 | V36: 2026-02 | W36: February/2026 | X36: IMS | Y36: Argentina | Z36: Mexico | AA36: ARS | AB36: 2414313 | AC36: ARS | AD36: 1459391.8 | AE36: 39.55 | AF36: OK | AG36: 0 | AH36: 0 | AI36: 0.09 | AJ36: 0 | AK36: 0.39552496 | AL36: OK | AM36: 10573703 | AO36: Miss | AP36: Miss | AR36: Miss | AT36: Miss | AU36: 2414313 | AV36: 1726 | AW36: Miss | AX36: 2414313 | AY36: 1728.21 | AZ36: ARS | BA36: 1459391.8 | BB36: OK | BC36: 0.1 | BD36: 0 | BE36: {=IFERROR(INDEX('Com&tax'!$E$2:$E$5, MATCH(1, ('Com&tax'!$A$2:$A$5=B36)*('Com&tax'!$B$2:$B$5=G36), 0)),"")} -> 0.15 | BF36: =IF(A36="","",( IFERROR(O36*BE36,""))) -> 362146.95 | BG36: {=IF(A36="","",( IFERROR((O36/ INDEX(er!$D$3:$D$75,MATCH(1, (er!$A$3:$A$75=$BG$2)*(er!$C$3:$C$75=Q36), 0)))*BE36,"")))} -> 259.23189 | BH36: =IF(A36="","",( IF(B36="Snapchat Rep", IF(A36="","",(P36-BF36)),-BF36))) -> -362146.95 | BI36: {=IFERROR(INDEX('Com&tax'!$F$2:$F$5, MATCH(1, ('Com&tax'!$A$2:$A$5=B36)*('Com&tax'!$B$2:$B$5=Y36), 0)),0)} -> 0.049 | BJ36: =IF(A36="","",( IFERROR((J36*(1-BE36))*BI36,0))) -> 100556.14 | BK36: {=IF(A36="","",( IFERROR((J36*(1-BE36))*BI36/INDEX(er!D:D, MATCH(Q36,er!C:C,0),1),0)))} -> 71.980054 | BL36: {=IFERROR(INDEX('Com&tax'!$G$2:$G$5, MATCH(1, ('Com&tax'!$A$2:$A$5=B36)*('Com&tax'!$B$2:$B$5=Y36), 0)),0)} -> 0.1575 | BM36: =IF(A36="","",( IFERROR((J36*(1-BE36))*BL36,0))) -> 323216.15 | BN36: {=IF(A36="","",( IFERROR((J36*(1-BE36))*BL36/INDEX(er!D:D, MATCH(Q36,er!C:C,0),1),0)))} -> 231.36446 | BO36: {=IFERROR(INDEX('Com&tax'!$H$2:$H$5, MATCH(1, ('Com&tax'!$A$2:$A$5=B36)*('Com&tax'!$B$2:$B$5=Y36), 0)),0)} -> 0.07 | BP36: =IF(A36="","",( IFERROR(J36*BO36,0))) -> 169001.91 | BQ36: {=IF(A36="","",( IFERROR(J36*BO36/INDEX(er!D:D, MATCH(Q36,er!C:C,0),1),0)))} -> 120.97488 | BR36: {=IFERROR(INDEX('Com&tax'!$F$2:$F$5, MATCH(1, ('Com&tax'!$A$2:$A$5=B36)*('Com&tax'!$D$2:$D$5=H36), 0)),0)} -> 0.049 | BS36: =IF(A36="","",( IFERROR((J36*(1-BE36))*BR36,0))) -> 100556.14 | BT36: {=IF(A36="","",( IFERROR((J36*(1-BE36))*BR36/INDEX(er!D:D, MATCH(Q36,er!C:C,0),1),0)))} -> 71.980054 | BU36: {=IFERROR(INDEX('Com&tax'!$G$2:$G$5, MATCH(1, ('Com&tax'!$A$2:$A$5=B36)*('Com&tax'!$D$2:$D$5=H36), 0)),0)} -> 0.1575 | BV36: =IF(A36="","",( IFERROR((J36*(1-BE36))*BU36,0))) -> 323216.15 | BW36: {=IF(A36="","",( IFERROR((J36*(1-BE36))*BU36/INDEX(er!D:D, MATCH(Q36,er!C:C,0),1),0)))} -> 231.36446 | BX36: {=IFERROR(INDEX('Com&tax'!$H$2:$H$5, MATCH(1, ('Com&tax'!$A$2:$A$5=B36)*('Com&tax'!$D$2:$D$5=H36), 0)),0)} -> 0.07 | BY36: =IF(A36="","",( IFERROR(J36*BX36,0))) -> 169001.91 | BZ36: {=IF(A36="","",( IFERROR(J36*BX36/INDEX(er!D:D, MATCH(Q36,er!C:C,0),1),0)))} -> 120.97488 | CA36: {=IF(A36="","",( IFERROR(1-((P36/ INDEX(er!$D$3:$D$75,MATCH(1, (er!$A$3:$A$75=$BG$2)*(er!$C$3:$C$75=Q36), 0)) / (J36/ INDEX(er!$D$3:$D$75,MATCH(1, (er!$A$3:$A$75=$BG$2)*(er!$C$3:$C$75=L36), 0))))),"")))} -> 0.39552496 | CB36: =IF(AB36="","",1-AD36/AB36) -> 0.395525 | CC36: =IF(AND(CA36="", CB36=""), "", CA36-CB36) -> -3.7277686e-08 | CD36: =BJ36+BM36-BS36-BV36 -> 0 | CE36: =BK36+BN36-BT36-BW36 -> 0 | CF36: =AJ36-CE36 -> 0 | CG36: =IF(OR(BE36="", AE36=""), "Miss", IF(ABS(AE36/100-AK36)<0.005, "OK", "Incorrect")) -> OK | CI36: OK | CK36: 0 | CL36: =(AI36+CK36)/INDEX(er!D:D,MATCH(AC36,er!C:C,0),1) -> 6.4423765e-05 | CN36: =CK36/INDEX(er!D:D,MATCH(AC36,er!C:C,0),1) -> 0
A37: T3222030 | B37: Twitter Rep | C37: IMS | D37: AR_Media Company_Hipódromo Argentino de Palermo S.A_AR00397255-X-Hipódromo de Palemro-Beturf-AON 26 | G37: Argentina | H37: Aleph Argentina | I37: Argentina | J37: 3962972.3 | K37: 3962972.3 | L37: ARS | M37: 3962972.3 | N37: ARS | O37: 3962972.3 | P37: 2395517.9 | Q37: ARS | R37: Mexico | U37: 0 | V37: 2026-02 | W37: February/2026 | X37: IMS | Y37: Argentina | Z37: Mexico | AA37: ARS | AB37: 3962972.3 | AC37: ARS | AD37: 2395517.7 | AE37: 39.55 | AF37: OK | AG37: 0 | AH37: 0 | AI37: 0.16 | AJ37: 0 | AK37: 0.39552496 | AL37: OK | AM37: 10573647 | AO37: Miss | AP37: Miss | AR37: Miss | AT37: Miss | AU37: 3962972.3 | AV37: 2835 | AW37: Miss | AX37: 3962972.3 | AY37: 2836.77 | AZ37: ARS | BA37: 2395517.7 | BB37: OK | BC37: 0.15 | BD37: 0 | BE37: {=IFERROR(INDEX('Com&tax'!$E$2:$E$5, MATCH(1, ('Com&tax'!$A$2:$A$5=B37)*('Com&tax'!$B$2:$B$5=G37), 0)),"")} -> 0.15 | BF37: =IF(A37="","",( IFERROR(O37*BE37,""))) -> 594445.85 | BG37: {=IF(A37="","",( IFERROR((O37/ INDEX(er!$D$3:$D$75,MATCH(1, (er!$A$3:$A$75=$BG$2)*(er!$C$3:$C$75=Q37), 0)))*BE37,"")))} -> 425.516 | BH37: =IF(A37="","",( IF(B37="Snapchat Rep", IF(A37="","",(P37-BF37)),-BF37))) -> -594445.85 | BI37: {=IFERROR(INDEX('Com&tax'!$F$2:$F$5, MATCH(1, ('Com&tax'!$A$2:$A$5=B37)*('Com&tax'!$B$2:$B$5=Y37), 0)),0)} -> 0.049 | BJ37: =IF(A37="","",( IFERROR((J37*(1-BE37))*BI37,0))) -> 165057.8 | BK37: {=IF(A37="","",( IFERROR((J37*(1-BE37))*BI37/INDEX(er!D:D, MATCH(Q37,er!C:C,0),1),0)))} -> 118.15161 | BL37: {=IFERROR(INDEX('Com&tax'!$G$2:$G$5, MATCH(1, ('Com&tax'!$A$2:$A$5=B37)*('Com&tax'!$B$2:$B$5=Y37), 0)),0)} -> 0.1575 | BM37: =IF(A37="","",( IFERROR((J37*(1-BE37))*BL37,0))) -> 530542.92 | BN37: {=IF(A37="","",( IFERROR((J37*(1-BE37))*BL37/INDEX(er!D:D, MATCH(Q37,er!C:C,0),1),0)))} -> 379.77303 | BO37: {=IFERROR(INDEX('Com&tax'!$H$2:$H$5, MATCH(1, ('Com&tax'!$A$2:$A$5=B37)*('Com&tax'!$B$2:$B$5=Y37), 0)),0)} -> 0.07 | BP37: =IF(A37="","",( IFERROR(J37*BO37,0))) -> 277408.06 | BQ37: {=IF(A37="","",( IFERROR(J37*BO37/INDEX(er!D:D, MATCH(Q37,er!C:C,0),1),0)))} -> 198.57413 | BR37: {=IFERROR(INDEX('Com&tax'!$F$2:$F$5, MATCH(1, ('Com&tax'!$A$2:$A$5=B37)*('Com&tax'!$D$2:$D$5=H37), 0)),0)} -> 0.049 | BS37: =IF(A37="","",( IFERROR((J37*(1-BE37))*BR37,0))) -> 165057.8 | BT37: {=IF(A37="","",( IFERROR((J37*(1-BE37))*BR37/INDEX(er!D:D, MATCH(Q37,er!C:C,0),1),0)))} -> 118.15161 | BU37: {=IFERROR(INDEX('Com&tax'!$G$2:$G$5, MATCH(1, ('Com&tax'!$A$2:$A$5=B37)*('Com&tax'!$D$2:$D$5=H37), 0)),0)} -> 0.1575 | BV37: =IF(A37="","",( IFERROR((J37*(1-BE37))*BU37,0))) -> 530542.92 | BW37: {=IF(A37="","",( IFERROR((J37*(1-BE37))*BU37/INDEX(er!D:D, MATCH(Q37,er!C:C,0),1),0)))} -> 379.77303 | BX37: {=IFERROR(INDEX('Com&tax'!$H$2:$H$5, MATCH(1, ('Com&tax'!$A$2:$A$5=B37)*('Com&tax'!$D$2:$D$5=H37), 0)),0)} -> 0.07 | BY37: =IF(A37="","",( IFERROR(J37*BX37,0))) -> 277408.06 | BZ37: {=IF(A37="","",( IFERROR(J37*BX37/INDEX(er!D:D, MATCH(Q37,er!C:C,0),1),0)))} -> 198.57413 | CA37: {=IF(A37="","",( IFERROR(1-((P37/ INDEX(er!$D$3:$D$75,MATCH(1, (er!$A$3:$A$75=$BG$2)*(er!$C$3:$C$75=Q37), 0)) / (J37/ INDEX(er!$D$3:$D$75,MATCH(1, (er!$A$3:$A$75=$BG$2)*(er!$C$3:$C$75=L37), 0))))),"")))} -> 0.39552496 | CB37: =IF(AB37="","",1-AD37/AB37) -> 0.395525 | CC37: =IF(AND(CA37="", CB37=""), "", CA37-CB37) -> -4.0373736e-08 | CD37: =BJ37+BM37-BS37-BV37 -> 0 | CE37: =BK37+BN37-BT37-BW37 -> 0 | CF37: =AJ37-CE37 -> 0 | CG37: =IF(OR(BE37="", AE37=""), "Miss", IF(ABS(AE37/100-AK37)<0.005, "OK", "Incorrect")) -> OK | CI37: OK | CK37: 0 | CL37: =(AI37+CK37)/INDEX(er!D:D,MATCH(AC37,er!C:C,0),1) -> 0.00011453114 | CN37: =CK37/INDEX(er!D:D,MATCH(AC37,er!C:C,0),1) -> 0
A38: T3222032 | B38: Twitter Rep | C38: IMS | D38: AR_Media Company_Hipódromo Argentino de Palermo S.A_AR00397261-X-Hipódromo de Palermo-Betfun-AON 26 | G38: Argentina | H38: Aleph Argentina | I38: Argentina | J38: 893323.9 | K38: 893323.9 | L38: ARS | M38: 893323.9 | N38: ARS | O38: 893323.9 | P38: 539992 | Q38: ARS | R38: Mexico | U38: 0 | V38: 2026-02 | W38: February/2026 | X38: IMS | Y38: Argentina | Z38: Mexico | AA38: ARS | AB38: 893323.9 | AC38: ARS | AD38: 539991.97 | AE38: 39.55 | AF38: OK | AG38: 0 | AH38: 0 | AI38: 0.03 | AJ38: 0 | AK38: 0.39552496 | AL38: OK | AM38: 10573737 | AO38: Miss | AP38: Miss | AR38: Miss | AT38: Miss | AU38: 893323.9 | AV38: 637 | AW38: Miss | AX38: 893323.9 | AY38: 639.46 | AZ38: ARS | BA38: 539991.96 | BB38: OK | BC38: 0.04 | BD38: 0 | BE38: {=IFERROR(INDEX('Com&tax'!$E$2:$E$5, MATCH(1, ('Com&tax'!$A$2:$A$5=B38)*('Com&tax'!$B$2:$B$5=G38), 0)),"")} -> 0.15 | BF38: =IF(A38="","",( IFERROR(O38*BE38,""))) -> 133998.58 | BG38: {=IF(A38="","",( IFERROR((O38/ INDEX(er!$D$3:$D$75,MATCH(1, (er!$A$3:$A$75=$BG$2)*(er!$C$3:$C$75=Q38), 0)))*BE38,"")))} -> 95.918815 | BH38: =IF(A38="","",( IF(B38="Snapchat Rep", IF(A38="","",(P38-BF38)),-BF38))) -> -133998.58 | BI38: {=IFERROR(INDEX('Com&tax'!$F$2:$F$5, MATCH(1, ('Com&tax'!$A$2:$A$5=B38)*('Com&tax'!$B$2:$B$5=Y38), 0)),0)} -> 0.049 | BJ38: =IF(A38="","",( IFERROR((J38*(1-BE38))*BI38,0))) -> 37206.94 | BK38: {=IF(A38="","",( IFERROR((J38*(1-BE38))*BI38/INDEX(er!D:D, MATCH(Q38,er!C:C,0),1),0)))} -> 26.633458 | BL38: {=IFERROR(INDEX('Com&tax'!$G$2:$G$5, MATCH(1, ('Com&tax'!$A$2:$A$5=B38)*('Com&tax'!$B$2:$B$5=Y38), 0)),0)} -> 0.1575 | BM38: =IF(A38="","",( IFERROR((J38*(1-BE38))*BL38,0))) -> 119593.74 | BN38: {=IF(A38="","",( IFERROR((J38*(1-BE38))*BL38/INDEX(er!D:D, MATCH(Q38,er!C:C,0),1),0)))} -> 85.607543 | BO38: {=IFERROR(INDEX('Com&tax'!$H$2:$H$5, MATCH(1, ('Com&tax'!$A$2:$A$5=B38)*('Com&tax'!$B$2:$B$5=Y38), 0)),0)} -> 0.07 | BP38: =IF(A38="","",( IFERROR(J38*BO38,0))) -> 62532.673 | BQ38: {=IF(A38="","",( IFERROR(J38*BO38/INDEX(er!D:D, MATCH(Q38,er!C:C,0),1),0)))} -> 44.762114 | BR38: {=IFERROR(INDEX('Com&tax'!$F$2:$F$5, MATCH(1, ('Com&tax'!$A$2:$A$5=B38)*('Com&tax'!$D$2:$D$5=H38), 0)),0)} -> 0.049 | BS38: =IF(A38="","",( IFERROR((J38*(1-BE38))*BR38,0))) -> 37206.94 | BT38: {=IF(A38="","",( IFERROR((J38*(1-BE38))*BR38/INDEX(er!D:D, MATCH(Q38,er!C:C,0),1),0)))} -> 26.633458 | BU38: {=IFERROR(INDEX('Com&tax'!$G$2:$G$5, MATCH(1, ('Com&tax'!$A$2:$A$5=B38)*('Com&tax'!$D$2:$D$5=H38), 0)),0)} -> 0.1575 | BV38: =IF(A38="","",( IFERROR((J38*(1-BE38))*BU38,0))) -> 119593.74 | BW38: {=IF(A38="","",( IFERROR((J38*(1-BE38))*BU38/INDEX(er!D:D, MATCH(Q38,er!C:C,0),1),0)))} -> 85.607543 | BX38: {=IFERROR(INDEX('Com&tax'!$H$2:$H$5, MATCH(1, ('Com&tax'!$A$2:$A$5=B38)*('Com&tax'!$D$2:$D$5=H38), 0)),0)} -> 0.07 | BY38: =IF(A38="","",( IFERROR(J38*BX38,0))) -> 62532.673 | BZ38: {=IF(A38="","",( IFERROR(J38*BX38/INDEX(er!D:D, MATCH(Q38,er!C:C,0),1),0)))} -> 44.762114 | CA38: {=IF(A38="","",( IFERROR(1-((P38/ INDEX(er!$D$3:$D$75,MATCH(1, (er!$A$3:$A$75=$BG$2)*(er!$C$3:$C$75=Q38), 0)) / (J38/ INDEX(er!$D$3:$D$75,MATCH(1, (er!$A$3:$A$75=$BG$2)*(er!$C$3:$C$75=L38), 0))))),"")))} -> 0.39552496 | CB38: =IF(AB38="","",1-AD38/AB38) -> 0.39552499 | CC38: =IF(AND(CA38="", CB38=""), "", CA38-CB38) -> -3.3582444e-08 | CD38: =BJ38+BM38-BS38-BV38 -> 0 | CE38: =BK38+BN38-BT38-BW38 -> 0 | CF38: =AJ38-CE38 -> 0 | CG38: =IF(OR(BE38="", AE38=""), "Miss", IF(ABS(AE38/100-AK38)<0.005, "OK", "Incorrect")) -> OK | CI38: OK | CK38: 0 | CL38: =(AI38+CK38)/INDEX(er!D:D,MATCH(AC38,er!C:C,0),1) -> 2.1474588e-05 | CN38: =CK38/INDEX(er!D:D,MATCH(AC38,er!C:C,0),1) -> 0
A39: T3222033 | B39: Twitter Rep | C39: IMS | D39: AR_Media Company_Hipódromo Argentino de Palermo S.A_AR00397257-X-Hipódromo de Palermo-Sala-AON 26 | G39: Argentina | H39: Aleph Argentina | I39: Argentina | J39: 4055968.3 | K39: 4055968.3 | L39: ARS | M39: 4055968.3 | N39: ARS | O39: 4055968.3 | P39: 2451731.6 | Q39: ARS | R39: Mexico | U39: 0 | V39: 2026-02 | W39: February/2026 | X39: IMS | Y39: Argentina | Z39: Mexico | AA39: ARS | AB39: 4055968.3 | AC39: ARS | AD39: 2451731.4 | AE39: 39.55 | AF39: OK | AG39: 0 | AH39: 0 | AI39: 0.17 | AJ39: 0 | AK39: 0.39552496 | AL39: OK | AM39: 10573704 | AO39: Miss | AP39: Miss | AR39: Miss | AT39: Miss | AU39: 4055968.3 | AV39: 2901 | AW39: Miss | AX39: 4055968.3 | AY39: 2903.34 | AZ39: ARS | BA39: 2451731.5 | BB39: OK | BC39: 0.16 | BD39: 0 | BE39: {=IFERROR(INDEX('Com&tax'!$E$2:$E$5, MATCH(1, ('Com&tax'!$A$2:$A$5=B39)*('Com&tax'!$B$2:$B$5=G39), 0)),"")} -> 0.15 | BF39: =IF(A39="","",( IFERROR(O39*BE39,""))) -> 608395.25 | BG39: {=IF(A39="","",( IFERROR((O39/ INDEX(er!$D$3:$D$75,MATCH(1, (er!$A$3:$A$75=$BG$2)*(er!$C$3:$C$75=Q39), 0)))*BE39,"")))} -> 435.50125 | BH39: =IF(A39="","",( IF(B39="Snapchat Rep", IF(A39="","",(P39-BF39)),-BF39))) -> -608395.25 | BI39: {=IFERROR(INDEX('Com&tax'!$F$2:$F$5, MATCH(1, ('Com&tax'!$A$2:$A$5=B39)*('Com&tax'!$B$2:$B$5=Y39), 0)),0)} -> 0.049 | BJ39: =IF(A39="","",( IFERROR((J39*(1-BE39))*BI39,0))) -> 168931.08 | BK39: {=IF(A39="","",( IFERROR((J39*(1-BE39))*BI39/INDEX(er!D:D, MATCH(Q39,er!C:C,0),1),0)))} -> 120.92418 | BL39: {=IFERROR(INDEX('Com&tax'!$G$2:$G$5, MATCH(1, ('Com&tax'!$A$2:$A$5=B39)*('Com&tax'!$B$2:$B$5=Y39), 0)),0)} -> 0.1575 | BM39: =IF(A39="","",( IFERROR((J39*(1-BE39))*BL39,0))) -> 542992.76 | BN39: {=IF(A39="","",( IFERROR((J39*(1-BE39))*BL39/INDEX(er!D:D, MATCH(Q39,er!C:C,0),1),0)))} -> 388.68487 | BO39: {=IFERROR(INDEX('Com&tax'!$H$2:$H$5, MATCH(1, ('Com&tax'!$A$2:$A$5=B39)*('Com&tax'!$B$2:$B$5=Y39), 0)),0)} -> 0.07 | BP39: =IF(A39="","",( IFERROR(J39*BO39,0))) -> 283917.78 | BQ39: {=IF(A39="","",( IFERROR(J39*BO39/INDEX(er!D:D, MATCH(Q39,er!C:C,0),1),0)))} -> 203.23392 | BR39: {=IFERROR(INDEX('Com&tax'!$F$2:$F$5, MATCH(1, ('Com&tax'!$A$2:$A$5=B39)*('Com&tax'!$D$2:$D$5=H39), 0)),0)} -> 0.049 | BS39: =IF(A39="","",( IFERROR((J39*(1-BE39))*BR39,0))) -> 168931.08 | BT39: {=IF(A39="","",( IFERROR((J39*(1-BE39))*BR39/INDEX(er!D:D, MATCH(Q39,er!C:C,0),1),0)))} -> 120.92418 | BU39: {=IFERROR(INDEX('Com&tax'!$G$2:$G$5, MATCH(1, ('Com&tax'!$A$2:$A$5=B39)*('Com&tax'!$D$2:$D$5=H39), 0)),0)} -> 0.1575 | BV39: =IF(A39="","",( IFERROR((J39*(1-BE39))*BU39,0))) -> 542992.76 | BW39: {=IF(A39="","",( IFERROR((J39*(1-BE39))*BU39/INDEX(er!D:D, MATCH(Q39,er!C:C,0),1),0)))} -> 388.68487 | BX39: {=IFERROR(INDEX('Com&tax'!$H$2:$H$5, MATCH(1, ('Com&tax'!$A$2:$A$5=B39)*('Com&tax'!$D$2:$D$5=H39), 0)),0)} -> 0.07 | BY39: =IF(A39="","",( IFERROR(J39*BX39,0))) -> 283917.78 | BZ39: {=IF(A39="","",( IFERROR(J39*BX39/INDEX(er!D:D, MATCH(Q39,er!C:C,0),1),0)))} -> 203.23392 | CA39: {=IF(A39="","",( IFERROR(1-((P39/ INDEX(er!$D$3:$D$75,MATCH(1, (er!$A$3:$A$75=$BG$2)*(er!$C$3:$C$75=Q39), 0)) / (J39/ INDEX(er!$D$3:$D$75,MATCH(1, (er!$A$3:$A$75=$BG$2)*(er!$C$3:$C$75=L39), 0))))),"")))} -> 0.39552496 | CB39: =IF(AB39="","",1-AD39/AB39) -> 0.395525 | CC39: =IF(AND(CA39="", CB39=""), "", CA39-CB39) -> -4.1913542e-08 | CD39: =BJ39+BM39-BS39-BV39 -> 0 | CE39: =BK39+BN39-BT39-BW39 -> 0 | CF39: =AJ39-CE39 -> 0 | CG39: =IF(OR(BE39="", AE39=""), "Miss", IF(ABS(AE39/100-AK39)<0.005, "OK", "Incorrect")) -> OK | CI39: OK | CK39: 0 | CL39: =(AI39+CK39)/INDEX(er!D:D,MATCH(AC39,er!C:C,0),1) -> 0.00012168933 | CN39: =CK39/INDEX(er!D:D,MATCH(AC39,er!C:C,0),1) -> 0
A40: T3222060 | B40: Twitter Rep | C40: IMS | D40: AR_Media Company_Play Digital Argentina_X | MODO | ChangoMás | G40: Argentina | H40: Aleph Argentina | I40: Argentina | J40: 1699231.8 | K40: 1699231.8 | L40: ARS | M40: 1699231.8 | N40: ARS | O40: 1699231.8 | P40: 1027143.2 | Q40: ARS | R40: Mexico | U40: 0 | V40: 2026-02 | W40: February/2026 | X40: IMS | Y40: Argentina | Z40: Mexico | AA40: ARS | AB40: 1699231.8 | AC40: ARS | AD40: 1027143.1 | AE40: 39.55 | AF40: OK | AG40: 0 | AH40: 0 | AI40: 0.06 | AJ40: 0 | AK40: 0.39552496 | AL40: OK | AM40: 10573628 | AO40: Miss | AP40: Miss | AR40: Miss | AT40: Miss | AU40: 1699231.8 | AV40: 1214 | AW40: Miss | AX40: 1699231.8 | AY40: 1216.34 | AZ40: ARS | BA40: 1027143.1 | BB40: OK | BC40: 0.06 | BD40: 0 | BE40: {=IFERROR(INDEX('Com&tax'!$E$2:$E$5, MATCH(1, ('Com&tax'!$A$2:$A$5=B40)*('Com&tax'!$B$2:$B$5=G40), 0)),"")} -> 0.15 | BF40: =IF(A40="","",( IFERROR(O40*BE40,""))) -> 254884.77 | BG40: {=IF(A40="","",( IFERROR((O40/ INDEX(er!$D$3:$D$75,MATCH(1, (er!$A$3:$A$75=$BG$2)*(er!$C$3:$C$75=Q40), 0)))*BE40,"")))} -> 182.45151 | BH40: =IF(A40="","",( IF(B40="Snapchat Rep", IF(A40="","",(P40-BF40)),-BF40))) -> -254884.77 | BI40: {=IFERROR(INDEX('Com&tax'!$F$2:$F$5, MATCH(1, ('Com&tax'!$A$2:$A$5=B40)*('Com&tax'!$B$2:$B$5=Y40), 0)),0)} -> 0.049 | BJ40: =IF(A40="","",( IFERROR((J40*(1-BE40))*BI40,0))) -> 70773.003 | BK40: {=IF(A40="","",( IFERROR((J40*(1-BE40))*BI40/INDEX(er!D:D, MATCH(Q40,er!C:C,0),1),0)))} -> 50.660704 | BL40: {=IFERROR(INDEX('Com&tax'!$G$2:$G$5, MATCH(1, ('Com&tax'!$A$2:$A$5=B40)*('Com&tax'!$B$2:$B$5=Y40), 0)),0)} -> 0.1575 | BM40: =IF(A40="","",( IFERROR((J40*(1-BE40))*BL40,0))) -> 227484.65 | BN40: {=IF(A40="","",( IFERROR((J40*(1-BE40))*BL40/INDEX(er!D:D, MATCH(Q40,er!C:C,0),1),0)))} -> 162.83798 | BO40: {=IFERROR(INDEX('Com&tax'!$H$2:$H$5, MATCH(1, ('Com&tax'!$A$2:$A$5=B40)*('Com&tax'!$B$2:$B$5=Y40), 0)),0)} -> 0.07 | BP40: =IF(A40="","",( IFERROR(J40*BO40,0))) -> 118946.22 | BQ40: {=IF(A40="","",( IFERROR(J40*BO40/INDEX(er!D:D, MATCH(Q40,er!C:C,0),1),0)))} -> 85.14404 | BR40: {=IFERROR(INDEX('Com&tax'!$F$2:$F$5, MATCH(1, ('Com&tax'!$A$2:$A$5=B40)*('Com&tax'!$D$2:$D$5=H40), 0)),0)} -> 0.049 | BS40: =IF(A40="","",( IFERROR((J40*(1-BE40))*BR40,0))) -> 70773.003 | BT40: {=IF(A40="","",( IFERROR((J40*(1-BE40))*BR40/INDEX(er!D:D, MATCH(Q40,er!C:C,0),1),0)))} -> 50.660704 | BU40: {=IFERROR(INDEX('Com&tax'!$G$2:$G$5, MATCH(1, ('Com&tax'!$A$2:$A$5=B40)*('Com&tax'!$D$2:$D$5=H40), 0)),0)} -> 0.1575 | BV40: =IF(A40="","",( IFERROR((J40*(1-BE40))*BU40,0))) -> 227484.65 | BW40: {=IF(A40="","",( IFERROR((J40*(1-BE40))*BU40/INDEX(er!D:D, MATCH(Q40,er!C:C,0),1),0)))} -> 162.83798 | BX40: {=IFERROR(INDEX('Com&tax'!$H$2:$H$5, MATCH(1, ('Com&tax'!$A$2:$A$5=B40)*('Com&tax'!$D$2:$D$5=H40), 0)),0)} -> 0.07 | BY40: =IF(A40="","",( IFERROR(J40*BX40,0))) -> 118946.22 | BZ40: {=IF(A40="","",( IFERROR(J40*BX40/INDEX(er!D:D, MATCH(Q40,er!C:C,0),1),0)))} -> 85.14404 | CA40: {=IF(A40="","",( IFERROR(1-((P40/ INDEX(er!$D$3:$D$75,MATCH(1, (er!$A$3:$A$75=$BG$2)*(er!$C$3:$C$75=Q40), 0)) / (J40/ INDEX(er!$D$3:$D$75,MATCH(1, (er!$A$3:$A$75=$BG$2)*(er!$C$3:$C$75=L40), 0))))),"")))} -> 0.39552496 | CB40: =IF(AB40="","",1-AD40/AB40) -> 0.395525 | CC40: =IF(AND(CA40="", CB40=""), "", CA40-CB40) -> -3.5310074e-08 | CD40: =BJ40+BM40-BS40-BV40 -> 0 | CE40: =BK40+BN40-BT40-BW40 -> 0 | CF40: =AJ40-CE40 -> 0 | CG40: =IF(OR(BE40="", AE40=""), "Miss", IF(ABS(AE40/100-AK40)<0.005, "OK", "Incorrect")) -> OK | CI40: OK | CK40: 0 | CL40: =(AI40+CK40)/INDEX(er!D:D,MATCH(AC40,er!C:C,0),1) -> 4.2949177e-05 | CN40: =CK40/INDEX(er!D:D,MATCH(AC40,er!C:C,0),1) -> 0
A41: T3222574 | B41: Twitter Rep | C41: IMS | D41: AR_Media Company_Arcos Dorados Argentina Argentina_AR00397993 | X | MCD ARG | CF-LITTLE MC - Ene/Feb 2026 | G41: Argentina | H41: Aleph Argentina | I41: Argentina | J41: 4381827.8 | K41: 4381827.8 | L41: ARS | M41: 4381827.8 | N41: ARS | O41: 4381827.8 | P41: 2648705.5 | Q41: ARS | R41: Mexico | U41: 0 | V41: 2026-02 | W41: February/2026 | X41: IMS | Y41: Argentina | Z41: Mexico | AA41: ARS | AB41: 4381827.9 | AC41: ARS | AD41: 2648705.4 | AE41: 39.55 | AF41: OK | AG41: -0.1 | AH41: 0 | AI41: 0.12 | AJ41: 0 | AK41: 0.39552496 | AL41: OK | AM41: 10573648 | AN41: Do the Upsell OR Create New Opp | AO41: Miss | AP41: Miss | AR41: Miss | AT41: Miss | AU41: 4381827.8 | AV41: 3135 | AW41: Miss | AX41: 4381827.8 | AY41: 3136.6 | AZ41: ARS | BA41: 2648705.4 | BB41: OK | BC41: 0.12 | BD41: 0 | BE41: {=IFERROR(INDEX('Com&tax'!$E$2:$E$5, MATCH(1, ('Com&tax'!$A$2:$A$5=B41)*('Com&tax'!$B$2:$B$5=G41), 0)),"")} -> 0.15 | BF41: =IF(A41="","",( IFERROR(O41*BE41,""))) -> 657274.17 | BG41: {=IF(A41="","",( IFERROR((O41/ INDEX(er!$D$3:$D$75,MATCH(1, (er!$A$3:$A$75=$BG$2)*(er!$C$3:$C$75=Q41), 0)))*BE41,"")))} -> 470.48974 | BH41: =IF(A41="","",( IF(B41="Snapchat Rep", IF(A41="","",(P41-BF41)),-BF41))) -> -657274.17 | BI41: {=IFERROR(INDEX('Com&tax'!$F$2:$F$5, MATCH(1, ('Com&tax'!$A$2:$A$5=B41)*('Com&tax'!$B$2:$B$5=Y41), 0)),0)} -> 0.049 | BJ41: =IF(A41="","",( IFERROR((J41*(1-BE41))*BI41,0))) -> 182503.13 | BK41: {=IF(A41="","",( IFERROR((J41*(1-BE41))*BI41/INDEX(er!D:D, MATCH(Q41,er!C:C,0),1),0)))} -> 130.63932 | BL41: {=IFERROR(INDEX('Com&tax'!$G$2:$G$5, MATCH(1, ('Com&tax'!$A$2:$A$5=B41)*('Com&tax'!$B$2:$B$5=Y41), 0)),0)} -> 0.1575 | BM41: =IF(A41="","",( IFERROR((J41*(1-BE41))*BL41,0))) -> 586617.19 | BN41: {=IF(A41="","",( IFERROR((J41*(1-BE41))*BL41/INDEX(er!D:D, MATCH(Q41,er!C:C,0),1),0)))} -> 419.91209 | BO41: {=IFERROR(INDEX('Com&tax'!$H$2:$H$5, MATCH(1, ('Com&tax'!$A$2:$A$5=B41)*('Com&tax'!$B$2:$B$5=Y41), 0)),0)} -> 0.07 | BP41: =IF(A41="","",( IFERROR(J41*BO41,0))) -> 306727.94 | BQ41: {=IF(A41="","",( IFERROR(J41*BO41/INDEX(er!D:D, MATCH(Q41,er!C:C,0),1),0)))} -> 219.56188 | BR41: {=IFERROR(INDEX('Com&tax'!$F$2:$F$5, MATCH(1, ('Com&tax'!$A$2:$A$5=B41)*('Com&tax'!$D$2:$D$5=H41), 0)),0)} -> 0.049 | BS41: =IF(A41="","",( IFERROR((J41*(1-BE41))*BR41,0))) -> 182503.13 | BT41: {=IF(A41="","",( IFERROR((J41*(1-BE41))*BR41/INDEX(er!D:D, MATCH(Q41,er!C:C,0),1),0)))} -> 130.63932 | BU41: {=IFERROR(INDEX('Com&tax'!$G$2:$G$5, MATCH(1, ('Com&tax'!$A$2:$A$5=B41)*('Com&tax'!$D$2:$D$5=H41), 0)),0)} -> 0.1575 | BV41: =IF(A41="","",( IFERROR((J41*(1-BE41))*BU41,0))) -> 586617.19 | BW41: {=IF(A41="","",( IFERROR((J41*(1-BE41))*BU41/INDEX(er!D:D, MATCH(Q41,er!C:C,0),1),0)))} -> 419.91209 | BX41: {=IFERROR(INDEX('Com&tax'!$H$2:$H$5, MATCH(1, ('Com&tax'!$A$2:$A$5=B41)*('Com&tax'!$D$2:$D$5=H41), 0)),0)} -> 0.07 | BY41: =IF(A41="","",( IFERROR(J41*BX41,0))) -> 306727.94 | BZ41: {=IF(A41="","",( IFERROR(J41*BX41/INDEX(er!D:D, MATCH(Q41,er!C:C,0),1),0)))} -> 219.56188 | CA41: {=IF(A41="","",( IFERROR(1-((P41/ INDEX(er!$D$3:$D$75,MATCH(1, (er!$A$3:$A$75=$BG$2)*(er!$C$3:$C$75=Q41), 0)) / (J41/ INDEX(er!$D$3:$D$75,MATCH(1, (er!$A$3:$A$75=$BG$2)*(er!$C$3:$C$75=L41), 0))))),"")))} -> 0.39552496 | CB41: =IF(AB41="","",1-AD41/AB41) -> 0.395525 | CC41: =IF(AND(CA41="", CB41=""), "", CA41-CB41) -> -4.1180875e-08 | CD41: =BJ41+BM41-BS41-BV41 -> 0 | CE41: =BK41+BN41-BT41-BW41 -> 0 | CF41: =AJ41-CE41 -> 0 | CG41: =IF(OR(BE41="", AE41=""), "Miss", IF(ABS(AE41/100-AK41)<0.005, "OK", "Incorrect")) -> OK | CI41: OK | CK41: 0 | CL41: =(AI41+CK41)/INDEX(er!D:D,MATCH(AC41,er!C:C,0),1) -> 8.5898354e-05 | CN41: =CK41/INDEX(er!D:D,MATCH(AC41,er!C:C,0),1) -> 0
A42: T3222582 | B42: Twitter Rep | C42: IMS | D42: AR_Media Company_BANCO SUPERVIELLE ARGENTINA_X | Banco Supervielle | ENE 26 | G42: Argentina | H42: Aleph Argentina | I42: Argentina | J42: 4712962.4 | K42: 4712962.4 | L42: ARS | M42: 4712962.4 | N42: ARS | O42: 4712962.4 | P42: 2848868.1 | Q42: ARS | R42: Mexico | U42: 0 | V42: 2026-02 | W42: February/2026 | X42: IMS | Y42: Argentina | Z42: Mexico | AA42: ARS | AB42: 4712962.4 | AC42: ARS | AD42: 2848868 | AE42: 39.55 | AF42: OK | AG42: 0 | AH42: 0 | AI42: 0.19 | AJ42: 0 | AK42: 0.39552496 | AL42: OK | AM42: 10573620 | AO42: Miss | AP42: Miss | AR42: Miss | AT42: Miss | AU42: 4712962.4 | AV42: 3372 | AW42: Miss | AX42: 4712962.4 | AY42: 3373.63 | AZ42: ARS | BA42: 2848868 | BB42: OK | BC42: 0.2 | BD42: 0 | BE42: {=IFERROR(INDEX('Com&tax'!$E$2:$E$5, MATCH(1, ('Com&tax'!$A$2:$A$5=B42)*('Com&tax'!$B$2:$B$5=G42), 0)),"")} -> 0.15 | BF42: =IF(A42="","",( IFERROR(O42*BE42,""))) -> 706944.36 | BG42: {=IF(A42="","",( IFERROR((O42/ INDEX(er!$D$3:$D$75,MATCH(1, (er!$A$3:$A$75=$BG$2)*(er!$C$3:$C$75=Q42), 0)))*BE42,"")))} -> 506.04464 | BH42: =IF(A42="","",( IF(B42="Snapchat Rep", IF(A42="","",(P42-BF42)),-BF42))) -> -706944.36 | BI42: {=IFERROR(INDEX('Com&tax'!$F$2:$F$5, MATCH(1, ('Com&tax'!$A$2:$A$5=B42)*('Com&tax'!$B$2:$B$5=Y42), 0)),0)} -> 0.049 | BJ42: =IF(A42="","",( IFERROR((J42*(1-BE42))*BI42,0))) -> 196294.88 | BK42: {=IF(A42="","",( IFERROR((J42*(1-BE42))*BI42/INDEX(er!D:D, MATCH(Q42,er!C:C,0),1),0)))} -> 140.51173 | BL42: {=IFERROR(INDEX('Com&tax'!$G$2:$G$5, MATCH(1, ('Com&tax'!$A$2:$A$5=B42)*('Com&tax'!$B$2:$B$5=Y42), 0)),0)} -> 0.1575 | BM42: =IF(A42="","",( IFERROR((J42*(1-BE42))*BL42,0))) -> 630947.84 | BN42: {=IF(A42="","",( IFERROR((J42*(1-BE42))*BL42/INDEX(er!D:D, MATCH(Q42,er!C:C,0),1),0)))} -> 451.64484 | BO42: {=IFERROR(INDEX('Com&tax'!$H$2:$H$5, MATCH(1, ('Com&tax'!$A$2:$A$5=B42)*('Com&tax'!$B$2:$B$5=Y42), 0)),0)} -> 0.07 | BP42: =IF(A42="","",( IFERROR(J42*BO42,0))) -> 329907.37 | BQ42: {=IF(A42="","",( IFERROR(J42*BO42/INDEX(er!D:D, MATCH(Q42,er!C:C,0),1),0)))} -> 236.15417 | BR42: {=IFERROR(INDEX('Com&tax'!$F$2:$F$5, MATCH(1, ('Com&tax'!$A$2:$A$5=B42)*('Com&tax'!$D$2:$D$5=H42), 0)),0)} -> 0.049 | BS42: =IF(A42="","",( IFERROR((J42*(1-BE42))*BR42,0))) -> 196294.88 | BT42: {=IF(A42="","",( IFERROR((J42*(1-BE42))*BR42/INDEX(er!D:D, MATCH(Q42,er!C:C,0),1),0)))} -> 140.51173 | BU42: {=IFERROR(INDEX('Com&tax'!$G$2:$G$5, MATCH(1, ('Com&tax'!$A$2:$A$5=B42)*('Com&tax'!$D$2:$D$5=H42), 0)),0)} -> 0.1575 | BV42: =IF(A42="","",( IFERROR((J42*(1-BE42))*BU42,0))) -> 630947.84 | BW42: {=IF(A42="","",( IFERROR((J42*(1-BE42))*BU42/INDEX(er!D:D, MATCH(Q42,er!C:C,0),1),0)))} -> 451.64484 | BX42: {=IFERROR(INDEX('Com&tax'!$H$2:$H$5, MATCH(1, ('Com&tax'!$A$2:$A$5=B42)*('Com&tax'!$D$2:$D$5=H42), 0)),0)} -> 0.07 | BY42: =IF(A42="","",( IFERROR(J42*BX42,0))) -> 329907.37 | BZ42: {=IF(A42="","",( IFERROR(J42*BX42/INDEX(er!D:D, MATCH(Q42,er!C:C,0),1),0)))} -> 236.15417 | CA42: {=IF(A42="","",( IFERROR(1-((P42/ INDEX(er!$D$3:$D$75,MATCH(1, (er!$A$3:$A$75=$BG$2)*(er!$C$3:$C$75=Q42), 0)) / (J42/ INDEX(er!$D$3:$D$75,MATCH(1, (er!$A$3:$A$75=$BG$2)*(er!$C$3:$C$75=L42), 0))))),"")))} -> 0.39552496 | CB42: =IF(AB42="","",1-AD42/AB42) -> 0.395525 | CC42: =IF(AND(CA42="", CB42=""), "", CA42-CB42) -> -4.0314347e-08 | CD42: =BJ42+BM42-BS42-BV42 -> 0 | CE42: =BK42+BN42-BT42-BW42 -> 0 | CF42: =AJ42-CE42 -> 0 | CG42: =IF(OR(BE42="", AE42=""), "Miss", IF(ABS(AE42/100-AK42)<0.005, "OK", "Incorrect")) -> OK | CI42: OK | CK42: 0 | CL42: =(AI42+CK42)/INDEX(er!D:D,MATCH(AC42,er!C:C,0),1) -> 0.00013600573 | CN42: =CK42/INDEX(er!D:D,MATCH(AC42,er!C:C,0),1) -> 0
A43: T3222819 | B43: Twitter Rep | C43: IMS | D43: AR_Media Company_TARJETA NARANJA SA Argentina_AR00398214-X-ARG-Naranja X-Verano-Ene/Feb 26 | G43: Argentina | H43: Aleph Argentina | I43: Argentina | J43: 7779983.4 | K43: 7779983.4 | L43: ARS | M43: 7779983.4 | N43: ARS | O43: 7779983.4 | P43: 4702805.8 | Q43: ARS | R43: Mexico | U43: 0 | V43: 2026-02 | W43: February/2026 | X43: IMS | Y43: Argentina | Z43: Mexico | AA43: ARS | AB43: 7779983.4 | AC43: ARS | AD43: 4702805.5 | AE43: 39.55 | AF43: OK | AG43: 0 | AH43: 0 | AI43: 0.31 | AJ43: 0 | AK43: 0.39552496 | AL43: OK | AM43: 10573649 | AO43: Miss | AP43: Miss | AR43: Miss | AT43: Miss | AU43: 7779983.4 | AV43: 5567 | AW43: Miss | AX43: 7779983.4 | AY43: 5569.06 | AZ43: ARS | BA43: 4702805.5 | BB43: OK | BC43: 0.31 | BD43: 0 | BE43: {=IFERROR(INDEX('Com&tax'!$E$2:$E$5, MATCH(1, ('Com&tax'!$A$2:$A$5=B43)*('Com&tax'!$B$2:$B$5=G43), 0)),"")} -> 0.15 | BF43: =IF(A43="","",( IFERROR(O43*BE43,""))) -> 1166997.5 | BG43: {=IF(A43="","",( IFERROR((O43/ INDEX(er!$D$3:$D$75,MATCH(1, (er!$A$3:$A$75=$BG$2)*(er!$C$3:$C$75=Q43), 0)))*BE43,"")))} -> 835.35971 | BH43: =IF(A43="","",( IF(B43="Snapchat Rep", IF(A43="","",(P43-BF43)),-BF43))) -> -1166997.5 | BI43: {=IFERROR(INDEX('Com&tax'!$F$2:$F$5, MATCH(1, ('Com&tax'!$A$2:$A$5=B43)*('Com&tax'!$B$2:$B$5=Y43), 0)),0)} -> 0.049 | BJ43: =IF(A43="","",( IFERROR((J43*(1-BE43))*BI43,0))) -> 324036.31 | BK43: {=IF(A43="","",( IFERROR((J43*(1-BE43))*BI43/INDEX(er!D:D, MATCH(Q43,er!C:C,0),1),0)))} -> 231.95155 | BL43: {=IFERROR(INDEX('Com&tax'!$G$2:$G$5, MATCH(1, ('Com&tax'!$A$2:$A$5=B43)*('Com&tax'!$B$2:$B$5=Y43), 0)),0)} -> 0.1575 | BM43: =IF(A43="","",( IFERROR((J43*(1-BE43))*BL43,0))) -> 1041545.3 | BN43: {=IF(A43="","",( IFERROR((J43*(1-BE43))*BL43/INDEX(er!D:D, MATCH(Q43,er!C:C,0),1),0)))} -> 745.55854 | BO43: {=IFERROR(INDEX('Com&tax'!$H$2:$H$5, MATCH(1, ('Com&tax'!$A$2:$A$5=B43)*('Com&tax'!$B$2:$B$5=Y43), 0)),0)} -> 0.07 | BP43: =IF(A43="","",( IFERROR(J43*BO43,0))) -> 544598.84 | BQ43: {=IF(A43="","",( IFERROR(J43*BO43/INDEX(er!D:D, MATCH(Q43,er!C:C,0),1),0)))} -> 389.83453 | BR43: {=IFERROR(INDEX('Com&tax'!$F$2:$F$5, MATCH(1, ('Com&tax'!$A$2:$A$5=B43)*('Com&tax'!$D$2:$D$5=H43), 0)),0)} -> 0.049 | BS43: =IF(A43="","",( IFERROR((J43*(1-BE43))*BR43,0))) -> 324036.31 | BT43: {=IF(A43="","",( IFERROR((J43*(1-BE43))*BR43/INDEX(er!D:D, MATCH(Q43,er!C:C,0),1),0)))} -> 231.95155 | BU43: {=IFERROR(INDEX('Com&tax'!$G$2:$G$5, MATCH(1, ('Com&tax'!$A$2:$A$5=B43)*('Com&tax'!$D$2:$D$5=H43), 0)),0)} -> 0.1575 | BV43: =IF(A43="","",( IFERROR((J43*(1-BE43))*BU43,0))) -> 1041545.3 | BW43: {=IF(A43="","",( IFERROR((J43*(1-BE43))*BU43/INDEX(er!D:D, MATCH(Q43,er!C:C,0),1),0)))} -> 745.55854 | BX43: {=IFERROR(INDEX('Com&tax'!$H$2:$H$5, MATCH(1, ('Com&tax'!$A$2:$A$5=B43)*('Com&tax'!$D$2:$D$5=H43), 0)),0)} -> 0.07 | BY43: =IF(A43="","",( IFERROR(J43*BX43,0))) -> 544598.84 | BZ43: {=IF(A43="","",( IFERROR(J43*BX43/INDEX(er!D:D, MATCH(Q43,er!C:C,0),1),0)))} -> 389.83453 | CA43: {=IF(A43="","",( IFERROR(1-((P43/ INDEX(er!$D$3:$D$75,MATCH(1, (er!$A$3:$A$75=$BG$2)*(er!$C$3:$C$75=Q43), 0)) / (J43/ INDEX(er!$D$3:$D$75,MATCH(1, (er!$A$3:$A$75=$BG$2)*(er!$C$3:$C$75=L43), 0))))),"")))} -> 0.39552496 | CB43: =IF(AB43="","",1-AD43/AB43) -> 0.395525 | CC43: =IF(AND(CA43="", CB43=""), "", CA43-CB43) -> -3.9845843e-08 | CD43: =BJ43+BM43-BS43-BV43 -> 0 | CE43: =BK43+BN43-BT43-BW43 -> 0 | CF43: =AJ43-CE43 -> 0 | CG43: =IF(OR(BE43="", AE43=""), "Miss", IF(ABS(AE43/100-AK43)<0.005, "OK", "Incorrect")) -> OK | CI43: OK | CK43: 0 | CL43: =(AI43+CK43)/INDEX(er!D:D,MATCH(AC43,er!C:C,0),1) -> 0.00022190408 | CN43: =CK43/INDEX(er!D:D,MATCH(AC43,er!C:C,0),1) -> 0
A44: T3223536 | B44: Twitter Billing | C44: IMS | D44: AR_Media Company_Mercado Libre Argentina_T3223536 - MPA | Somos Francos | Takeovers- 6/Feb, 4/Mar | G44: Argentina | H44: Aleph Argentina | I44: Argentina | J44: 2937600 | K44: 2937600 | L44: ARS | M44: 2937600 | N44: ARS | O44: 2937600 | P44: 1938801.3 | Q44: ARS | R44: Mexico | U44: 0 | V44: 2026-02 | W44: February/2026 | X44: IMS | Y44: Argentina | Z44: Mexico | AA44: ARS | AB44: 2937600 | AC44: ARS | AD44: 1938874.8 | AE44: 34 | AF44: OK | AG44: 0 | AH44: 0 | AI44: -73.44 | AJ44: -0.05 | AK44: 0.340005 | AL44: OK | AM44: 10573672 | AO44: Miss | AP44: Miss | AR44: Miss | AT44: Miss | AU44: 2937600 | AV44: 2101 | AW44: Miss | AX44: 2937600 | AY44: 2102.79 | AZ44: ARS | BA44: 1938874.8 | BB44: OK | BC44: -73.44 | BD44: -0.05 | BE44: {=IFERROR(INDEX('Com&tax'!$E$2:$E$5, MATCH(1, ('Com&tax'!$A$2:$A$5=B44)*('Com&tax'!$B$2:$B$5=G44), 0)),"")} -> 0.15 | BF44: =IF(A44="","",( IFERROR(O44*BE44,""))) -> 440640 | BG44: {=IF(A44="","",( IFERROR((O44/ INDEX(er!$D$3:$D$75,MATCH(1, (er!$A$3:$A$75=$BG$2)*(er!$C$3:$C$75=Q44), 0)))*BE44,"")))} -> 315.41875 | BH44: =IF(A44="","",( IF(B44="Snapchat Rep", IF(A44="","",(P44-BF44)),-BF44))) -> -440640 | BI44: {=IFERROR(INDEX('Com&tax'!$F$2:$F$5, MATCH(1, ('Com&tax'!$A$2:$A$5=B44)*('Com&tax'!$B$2:$B$5=Y44), 0)),0)} -> 0.049 | BJ44: =IF(A44="","",( IFERROR((J44*(1-BE44))*BI44,0))) -> 122351.04 | BK44: {=IF(A44="","",( IFERROR((J44*(1-BE44))*BI44/INDEX(er!D:D, MATCH(Q44,er!C:C,0),1),0)))} -> 87.581274 | BL44: {=IFERROR(INDEX('Com&tax'!$G$2:$G$5, MATCH(1, ('Com&tax'!$A$2:$A$5=B44)*('Com&tax'!$B$2:$B$5=Y44), 0)),0)} -> 0.1575 | BM44: =IF(A44="","",( IFERROR((J44*(1-BE44))*BL44,0))) -> 393271.2 | BN44: {=IF(A44="","",( IFERROR((J44*(1-BE44))*BL44/INDEX(er!D:D, MATCH(Q44,er!C:C,0),1),0)))} -> 281.51124 | BO44: {=IFERROR(INDEX('Com&tax'!$H$2:$H$5, MATCH(1, ('Com&tax'!$A$2:$A$5=B44)*('Com&tax'!$B$2:$B$5=Y44), 0)),0)} -> 0 | BP44: =IF(A44="","",( IFERROR(J44*BO44,0))) -> 0 | BQ44: {=IF(A44="","",( IFERROR(J44*BO44/INDEX(er!D:D, MATCH(Q44,er!C:C,0),1),0)))} -> 0 | BR44: {=IFERROR(INDEX('Com&tax'!$F$2:$F$5, MATCH(1, ('Com&tax'!$A$2:$A$5=B44)*('Com&tax'!$D$2:$D$5=H44), 0)),0)} -> 0.049 | BS44: =IF(A44="","",( IFERROR((J44*(1-BE44))*BR44,0))) -> 122351.04 | BT44: {=IF(A44="","",( IFERROR((J44*(1-BE44))*BR44/INDEX(er!D:D, MATCH(Q44,er!C:C,0),1),0)))} -> 87.581274 | BU44: {=IFERROR(INDEX('Com&tax'!$G$2:$G$5, MATCH(1, ('Com&tax'!$A$2:$A$5=B44)*('Com&tax'!$D$2:$D$5=H44), 0)),0)} -> 0.1575 | BV44: =IF(A44="","",( IFERROR((J44*(1-BE44))*BU44,0))) -> 393271.2 | BW44: {=IF(A44="","",( IFERROR((J44*(1-BE44))*BU44/INDEX(er!D:D, MATCH(Q44,er!C:C,0),1),0)))} -> 281.51124 | BX44: {=IFERROR(INDEX('Com&tax'!$H$2:$H$5, MATCH(1, ('Com&tax'!$A$2:$A$5=B44)*('Com&tax'!$D$2:$D$5=H44), 0)),0)} -> 0 | BY44: =IF(A44="","",( IFERROR(J44*BX44,0))) -> 0 | BZ44: {=IF(A44="","",( IFERROR(J44*BX44/INDEX(er!D:D, MATCH(Q44,er!C:C,0),1),0)))} -> 0 | CA44: {=IF(A44="","",( IFERROR(1-((P44/ INDEX(er!$D$3:$D$75,MATCH(1, (er!$A$3:$A$75=$BG$2)*(er!$C$3:$C$75=Q44), 0)) / (J44/ INDEX(er!$D$3:$D$75,MATCH(1, (er!$A$3:$A$75=$BG$2)*(er!$C$3:$C$75=L44), 0))))),"")))} -> 0.340005 | CB44: =IF(AB44="","",1-AD44/AB44) -> 0.33998 | CC44: =IF(AND(CA44="", CB44=""), "", CA44-CB44) -> 2.5e-05 | CD44: =BJ44+BM44-BS44-BV44 -> 0 | CE44: =BK44+BN44-BT44-BW44 -> 0 | CF44: =AJ44-CE44 -> -0.05 | CG44: =IF(OR(BE44="", AE44=""), "Miss", IF(ABS(AE44/100-AK44)<0.005, "OK", "Incorrect")) -> OK | CI44: OK | CK44: 0 | CL44: =(AI44+CK44)/INDEX(er!D:D,MATCH(AC44,er!C:C,0),1) -> -0.052569792 | CN44: =CK44/INDEX(er!D:D,MATCH(AC44,er!C:C,0),1) -> 0
A45: T3224678 | B45: Twitter Rep | C45: IMS | D45: AR_Media Company_Assist Card Argentina Argentina_AR00398290 | X | Assist Card AR | 2026 | G45: Argentina | H45: Aleph Argentina | I45: Argentina | J45: 1651074.3 | K45: 1651074.3 | L45: ARS | M45: 1651074.3 | N45: ARS | O45: 1651074.3 | P45: 998033.19 | Q45: ARS | R45: Mexico | U45: 0 | V45: 2026-02 | W45: February/2026 | X45: IMS | Y45: Argentina | Z45: Mexico | AA45: ARS | AB45: 1651074.3 | AC45: ARS | AD45: 998033.13 | AE45: 39.55 | AF45: OK | AG45: 0 | AH45: 0 | AI45: 0.06 | AJ45: 0 | AK45: 0.39552496 | AL45: OK | AM45: 10573666 | AO45: Miss | AP45: Miss | AR45: Miss | AT45: Miss | AU45: 1651074.3 | AV45: 1180 | AW45: Miss | AX45: 1651074.3 | AY45: 1181.87 | AZ45: ARS | BA45: 998033.13 | BB45: OK | BC45: 0.06 | BD45: 0 | BE45: {=IFERROR(INDEX('Com&tax'!$E$2:$E$5, MATCH(1, ('Com&tax'!$A$2:$A$5=B45)*('Com&tax'!$B$2:$B$5=G45), 0)),"")} -> 0.15 | BF45: =IF(A45="","",( IFERROR(O45*BE45,""))) -> 247661.14 | BG45: {=IF(A45="","",( IFERROR((O45/ INDEX(er!$D$3:$D$75,MATCH(1, (er!$A$3:$A$75=$BG$2)*(er!$C$3:$C$75=Q45), 0)))*BE45,"")))} -> 177.2807 | BH45: =IF(A45="","",( IF(B45="Snapchat Rep", IF(A45="","",(P45-BF45)),-BF45))) -> -247661.14 | BI45: {=IFERROR(INDEX('Com&tax'!$F$2:$F$5, MATCH(1, ('Com&tax'!$A$2:$A$5=B45)*('Com&tax'!$B$2:$B$5=Y45), 0)),0)} -> 0.049 | BJ45: =IF(A45="","",( IFERROR((J45*(1-BE45))*BI45,0))) -> 68767.244 | BK45: {=IF(A45="","",( IFERROR((J45*(1-BE45))*BI45/INDEX(er!D:D, MATCH(Q45,er!C:C,0),1),0)))} -> 49.224942 | BL45: {=IFERROR(INDEX('Com&tax'!$G$2:$G$5, MATCH(1, ('Com&tax'!$A$2:$A$5=B45)*('Com&tax'!$B$2:$B$5=Y45), 0)),0)} -> 0.1575 | BM45: =IF(A45="","",( IFERROR((J45*(1-BE45))*BL45,0))) -> 221037.57 | BN45: {=IF(A45="","",( IFERROR((J45*(1-BE45))*BL45/INDEX(er!D:D, MATCH(Q45,er!C:C,0),1),0)))} -> 158.22303 | BO45: {=IFERROR(INDEX('Com&tax'!$H$2:$H$5, MATCH(1, ('Com&tax'!$A$2:$A$5=B45)*('Com&tax'!$B$2:$B$5=Y45), 0)),0)} -> 0.07 | BP45: =IF(A45="","",( IFERROR(J45*BO45,0))) -> 115575.2 | BQ45: {=IF(A45="","",( IFERROR(J45*BO45/INDEX(er!D:D, MATCH(Q45,er!C:C,0),1),0)))} -> 82.730995 | BR45: {=IFERROR(INDEX('Com&tax'!$F$2:$F$5, MATCH(1, ('Com&tax'!$A$2:$A$5=B45)*('Com&tax'!$D$2:$D$5=H45), 0)),0)} -> 0.049 | BS45: =IF(A45="","",( IFERROR((J45*(1-BE45))*BR45,0))) -> 68767.244 | BT45: {=IF(A45="","",( IFERROR((J45*(1-BE45))*BR45/INDEX(er!D:D, MATCH(Q45,er!C:C,0),1),0)))} -> 49.224942 | BU45: {=IFERROR(INDEX('Com&tax'!$G$2:$G$5, MATCH(1, ('Com&tax'!$A$2:$A$5=B45)*('Com&tax'!$D$2:$D$5=H45), 0)),0)} -> 0.1575 | BV45: =IF(A45="","",( IFERROR((J45*(1-BE45))*BU45,0))) -> 221037.57 | BW45: {=IF(A45="","",( IFERROR((J45*(1-BE45))*BU45/INDEX(er!D:D, MATCH(Q45,er!C:C,0),1),0)))} -> 158.22303 | BX45: {=IFERROR(INDEX('Com&tax'!$H$2:$H$5, MATCH(1, ('Com&tax'!$A$2:$A$5=B45)*('Com&tax'!$D$2:$D$5=H45), 0)),0)} -> 0.07 | BY45: =IF(A45="","",( IFERROR(J45*BX45,0))) -> 115575.2 | BZ45: {=IF(A45="","",( IFERROR(J45*BX45/INDEX(er!D:D, MATCH(Q45,er!C:C,0),1),0)))} -> 82.730995 | CA45: {=IF(A45="","",( IFERROR(1-((P45/ INDEX(er!$D$3:$D$75,MATCH(1, (er!$A$3:$A$75=$BG$2)*(er!$C$3:$C$75=Q45), 0)) / (J45/ INDEX(er!$D$3:$D$75,MATCH(1, (er!$A$3:$A$75=$BG$2)*(er!$C$3:$C$75=L45), 0))))),"")))} -> 0.39552496 | CB45: =IF(AB45="","",1-AD45/AB45) -> 0.395525 | CC45: =IF(AND(CA45="", CB45=""), "", CA45-CB45) -> -3.6339976e-08 | CD45: =BJ45+BM45-BS45-BV45 -> 0 | CE45: =BK45+BN45-BT45-BW45 -> 0 | CF45: =AJ45-CE45 -> 0 | CG45: =IF(OR(BE45="", AE45=""), "Miss", IF(ABS(AE45/100-AK45)<0.005, "OK", "Incorrect")) -> OK | CI45: OK | CK45: 0 | CL45: =(AI45+CK45)/INDEX(er!D:D,MATCH(AC45,er!C:C,0),1) -> 4.2949177e-05 | CN45: =CK45/INDEX(er!D:D,MATCH(AC45,er!C:C,0),1) -> 0
A46: T3224761 | B46: Twitter Rep | C46: IMS | D46: AR_Media Company_Telecom Argentina SA Argentina_AR00398495 | X | PERSONAL | Ecosistema parte 2 | Ene-Feb 2026 | E46: SO Exported to ERP | G46: Argentina | H46: Aleph Argentina | I46: Argentina | J46: 7514153.1 | K46: 7514153.1 | L46: ARS | M46: 7514153.1 | N46: ARS | O46: 7514153.1 | P46: 4542118 | Q46: ARS | R46: Mexico | U46: 0 | V46: 2026-02 | W46: February/2026 | X46: IMS | Y46: Argentina | Z46: Mexico | AA46: ARS | AB46: 7514153.1 | AC46: ARS | AD46: 4542117.7 | AE46: 39.55 | AF46: OK | AG46: 0 | AH46: 0 | AI46: 0.3 | AJ46: 0 | AK46: 0.39552496 | AL46: OK | AM46: 10573630 | AO46: Miss | AP46: Miss | AR46: Miss | AT46: Miss | AU46: 7514153.1 | AV46: 5377 | AW46: Miss | AX46: 7514153.1 | AY46: 5378.78 | AZ46: ARS | BA46: 4542117.7 | BB46: OK | BC46: 0.3 | BD46: 0 | BE46: {=IFERROR(INDEX('Com&tax'!$E$2:$E$5, MATCH(1, ('Com&tax'!$A$2:$A$5=B46)*('Com&tax'!$B$2:$B$5=G46), 0)),"")} -> 0.15 | BF46: =IF(A46="","",( IFERROR(O46*BE46,""))) -> 1127123 | BG46: {=IF(A46="","",( IFERROR((O46/ INDEX(er!$D$3:$D$75,MATCH(1, (er!$A$3:$A$75=$BG$2)*(er!$C$3:$C$75=Q46), 0)))*BE46,"")))} -> 806.81673 | BH46: =IF(A46="","",( IF(B46="Snapchat Rep", IF(A46="","",(P46-BF46)),-BF46))) -> -1127123 | BI46: {=IFERROR(INDEX('Com&tax'!$F$2:$F$5, MATCH(1, ('Com&tax'!$A$2:$A$5=B46)*('Com&tax'!$B$2:$B$5=Y46), 0)),0)} -> 0.049 | BJ46: =IF(A46="","",( IFERROR((J46*(1-BE46))*BI46,0))) -> 312964.48 | BK46: {=IF(A46="","",( IFERROR((J46*(1-BE46))*BI46/INDEX(er!D:D, MATCH(Q46,er!C:C,0),1),0)))} -> 224.02611 | BL46: {=IFERROR(INDEX('Com&tax'!$G$2:$G$5, MATCH(1, ('Com&tax'!$A$2:$A$5=B46)*('Com&tax'!$B$2:$B$5=Y46), 0)),0)} -> 0.1575 | BM46: =IF(A46="","",( IFERROR((J46*(1-BE46))*BL46,0))) -> 1005957.3 | BN46: {=IF(A46="","",( IFERROR((J46*(1-BE46))*BL46/INDEX(er!D:D, MATCH(Q46,er!C:C,0),1),0)))} -> 720.08393 | BO46: {=IFERROR(INDEX('Com&tax'!$H$2:$H$5, MATCH(1, ('Com&tax'!$A$2:$A$5=B46)*('Com&tax'!$B$2:$B$5=Y46), 0)),0)} -> 0.07 | BP46: =IF(A46="","",( IFERROR(J46*BO46,0))) -> 525990.72 | BQ46: {=IF(A46="","",( IFERROR(J46*BO46/INDEX(er!D:D, MATCH(Q46,er!C:C,0),1),0)))} -> 376.51447 | BR46: {=IFERROR(INDEX('Com&tax'!$F$2:$F$5, MATCH(1, ('Com&tax'!$A$2:$A$5=B46)*('Com&tax'!$D$2:$D$5=H46), 0)),0)} -> 0.049 | BS46: =IF(A46="","",( IFERROR((J46*(1-BE46))*BR46,0))) -> 312964.48 | BT46: {=IF(A46="","",( IFERROR((J46*(1-BE46))*BR46/INDEX(er!D:D, MATCH(Q46,er!C:C,0),1),0)))} -> 224.02611 | BU46: {=IFERROR(INDEX('Com&tax'!$G$2:$G$5, MATCH(1, ('Com&tax'!$A$2:$A$5=B46)*('Com&tax'!$D$2:$D$5=H46), 0)),0)} -> 0.1575 | BV46: =IF(A46="","",( IFERROR((J46*(1-BE46))*BU46,0))) -> 1005957.3 | BW46: {=IF(A46="","",( IFERROR((J46*(1-BE46))*BU46/INDEX(er!D:D, MATCH(Q46,er!C:C,0),1),0)))} -> 720.08393 | BX46: {=IFERROR(INDEX('Com&tax'!$H$2:$H$5, MATCH(1, ('Com&tax'!$A$2:$A$5=B46)*('Com&tax'!$D$2:$D$5=H46), 0)),0)} -> 0.07 | BY46: =IF(A46="","",( IFERROR(J46*BX46,0))) -> 525990.72 | BZ46: {=IF(A46="","",( IFERROR(J46*BX46/INDEX(er!D:D, MATCH(Q46,er!C:C,0),1),0)))} -> 376.51447 | CA46: {=IF(A46="","",( IFERROR(1-((P46/ INDEX(er!$D$3:$D$75,MATCH(1, (er!$A$3:$A$75=$BG$2)*(er!$C$3:$C$75=Q46), 0)) / (J46/ INDEX(er!$D$3:$D$75,MATCH(1, (er!$A$3:$A$75=$BG$2)*(er!$C$3:$C$75=L46), 0))))),"")))} -> 0.39552496 | CB46: =IF(AB46="","",1-AD46/AB46) -> 0.395525 | CC46: =IF(AND(CA46="", CB46=""), "", CA46-CB46) -> -3.9924659e-08 | CD46: =BJ46+BM46-BS46-BV46 -> 0 | CE46: =BK46+BN46-BT46-BW46 -> 0 | CF46: =AJ46-CE46 -> 0 | CG46: =IF(OR(BE46="", AE46=""), "Miss", IF(ABS(AE46/100-AK46)<0.005, "OK", "Incorrect")) -> OK | CI46: OK | CK46: 0 | CL46: =(AI46+CK46)/INDEX(er!D:D,MATCH(AC46,er!C:C,0),1) -> 0.00021474588 | CN46: =CK46/INDEX(er!D:D,MATCH(AC46,er!C:C,0),1) -> 0
A47: T3225314 | B47: Twitter Rep | C47: IMS | D47: AR_Media Company_BANCO DE LA PROVINCIA DE BUENOS AIRES Argentina_X | Bapro | ENE 26 | G47: Argentina | H47: Aleph Argentina | I47: Argentina | J47: 7991501.8 | K47: 7991501.8 | L47: ARS | M47: 7991501.8 | N47: ARS | O47: 7991501.8 | P47: 4830663.4 | Q47: ARS | R47: Mexico | U47: 0 | V47: 2026-02 | W47: February/2026 | X47: IMS | Y47: Argentina | Z47: Mexico | AA47: ARS | AB47: 7991501.8 | AC47: ARS | AD47: 4830663 | AE47: 39.55 | AF47: OK | AG47: 0 | AH47: 0 | AI47: 0.34 | AJ47: 0 | AK47: 0.39552496 | AL47: OK | AM47: 10573696 | AO47: Miss | AP47: Miss | AR47: Miss | AT47: Miss | AU47: 7991501.8 | AV47: 5718 | AW47: Miss | AX47: 7991501.8 | AY47: 5720.47 | AZ47: ARS | BA47: 4830663.1 | BB47: OK | BC47: 0.32 | BD47: 0 | BE47: {=IFERROR(INDEX('Com&tax'!$E$2:$E$5, MATCH(1, ('Com&tax'!$A$2:$A$5=B47)*('Com&tax'!$B$2:$B$5=G47), 0)),"")} -> 0.15 | BF47: =IF(A47="","",( IFERROR(O47*BE47,""))) -> 1198725.3 | BG47: {=IF(A47="","",( IFERROR((O47/ INDEX(er!$D$3:$D$75,MATCH(1, (er!$A$3:$A$75=$BG$2)*(er!$C$3:$C$75=Q47), 0)))*BE47,"")))} -> 858.07106 | BH47: =IF(A47="","",( IF(B47="Snapchat Rep", IF(A47="","",(P47-BF47)),-BF47))) -> -1198725.3 | BI47: {=IFERROR(INDEX('Com&tax'!$F$2:$F$5, MATCH(1, ('Com&tax'!$A$2:$A$5=B47)*('Com&tax'!$B$2:$B$5=Y47), 0)),0)} -> 0.049 | BJ47: =IF(A47="","",( IFERROR((J47*(1-BE47))*BI47,0))) -> 332846.05 | BK47: {=IF(A47="","",( IFERROR((J47*(1-BE47))*BI47/INDEX(er!D:D, MATCH(Q47,er!C:C,0),1),0)))} -> 238.25773 | BL47: {=IFERROR(INDEX('Com&tax'!$G$2:$G$5, MATCH(1, ('Com&tax'!$A$2:$A$5=B47)*('Com&tax'!$B$2:$B$5=Y47), 0)),0)} -> 0.1575 | BM47: =IF(A47="","",( IFERROR((J47*(1-BE47))*BL47,0))) -> 1069862.3 | BN47: {=IF(A47="","",( IFERROR((J47*(1-BE47))*BL47/INDEX(er!D:D, MATCH(Q47,er!C:C,0),1),0)))} -> 765.82842 | BO47: {=IFERROR(INDEX('Com&tax'!$H$2:$H$5, MATCH(1, ('Com&tax'!$A$2:$A$5=B47)*('Com&tax'!$B$2:$B$5=Y47), 0)),0)} -> 0.07 | BP47: =IF(A47="","",( IFERROR(J47*BO47,0))) -> 559405.13 | BQ47: {=IF(A47="","",( IFERROR(J47*BO47/INDEX(er!D:D, MATCH(Q47,er!C:C,0),1),0)))} -> 400.43316 | BR47: {=IFERROR(INDEX('Com&tax'!$F$2:$F$5, MATCH(1, ('Com&tax'!$A$2:$A$5=B47)*('Com&tax'!$D$2:$D$5=H47), 0)),0)} -> 0.049 | BS47: =IF(A47="","",( IFERROR((J47*(1-BE47))*BR47,0))) -> 332846.05 | BT47: {=IF(A47="","",( IFERROR((J47*(1-BE47))*BR47/INDEX(er!D:D, MATCH(Q47,er!C:C,0),1),0)))} -> 238.25773 | BU47: {=IFERROR(INDEX('Com&tax'!$G$2:$G$5, MATCH(1, ('Com&tax'!$A$2:$A$5=B47)*('Com&tax'!$D$2:$D$5=H47), 0)),0)} -> 0.1575 | BV47: =IF(A47="","",( IFERROR((J47*(1-BE47))*BU47,0))) -> 1069862.3 | BW47: {=IF(A47="","",( IFERROR((J47*(1-BE47))*BU47/INDEX(er!D:D, MATCH(Q47,er!C:C,0),1),0)))} -> 765.82842 | BX47: {=IFERROR(INDEX('Com&tax'!$H$2:$H$5, MATCH(1, ('Com&tax'!$A$2:$A$5=B47)*('Com&tax'!$D$2:$D$5=H47), 0)),0)} -> 0.07 | BY47: =IF(A47="","",( IFERROR(J47*BX47,0))) -> 559405.13 | BZ47: {=IF(A47="","",( IFERROR(J47*BX47/INDEX(er!D:D, MATCH(Q47,er!C:C,0),1),0)))} -> 400.43316 | CA47: {=IF(A47="","",( IFERROR(1-((P47/ INDEX(er!$D$3:$D$75,MATCH(1, (er!$A$3:$A$75=$BG$2)*(er!$C$3:$C$75=Q47), 0)) / (J47/ INDEX(er!$D$3:$D$75,MATCH(1, (er!$A$3:$A$75=$BG$2)*(er!$C$3:$C$75=L47), 0))))),"")))} -> 0.39552496 | CB47: =IF(AB47="","",1-AD47/AB47) -> 0.395525 | CC47: =IF(AND(CA47="", CB47=""), "", CA47-CB47) -> -4.2545195e-08 | CD47: =BJ47+BM47-BS47-BV47 -> 0 | CE47: =BK47+BN47-BT47-BW47 -> 0 | CF47: =AJ47-CE47 -> 0 | CG47: =IF(OR(BE47="", AE47=""), "Miss", IF(ABS(AE47/100-AK47)<0.005, "OK", "Incorrect")) -> OK | CI47: OK | CK47: 0 | CL47: =(AI47+CK47)/INDEX(er!D:D,MATCH(AC47,er!C:C,0),1) -> 0.00024337867 | CN47: =CK47/INDEX(er!D:D,MATCH(AC47,er!C:C,0),1) -> 0
A48: T3225345 | B48: Twitter Billing | C48: IMS | D48: AR_Media Company_Mercado Libre Argentina_T3225345 - MLA | LPF | video - 19/01/2026 | G48: Argentina | H48: Aleph Argentina | I48: Argentina | J48: 8088113.9 | K48: 8088113.9 | L48: ARS | M48: 8088113.9 | N48: ARS | O48: 8088113.9 | P48: 5338114.7 | Q48: ARS | R48: Mexico | U48: 0 | V48: 2026-02 | W48: February/2026 | X48: IMS | Y48: Argentina | Z48: Mexico | AA48: ARS | AB48: 8088113.9 | AC48: ARS | AD48: 5338316.9 | AE48: 34 | AF48: OK | AG48: 0 | AH48: 0 | AI48: -202.2 | AJ48: -0.14 | AK48: 0.340005 | AL48: OK | AM48: 10573632 | AO48: Miss | AP48: Miss | AR48: Miss | AT48: Miss | AU48: 8088113.9 | AV48: 5788 | AW48: Miss | AX48: 8088113.9 | AY48: 5789.63 | AZ48: ARS | BA48: 5338316.9 | BB48: OK | BC48: -202.2 | BD48: -0.14 | BE48: {=IFERROR(INDEX('Com&tax'!$E$2:$E$5, MATCH(1, ('Com&tax'!$A$2:$A$5=B48)*('Com&tax'!$B$2:$B$5=G48), 0)),"")} -> 0.15 | BF48: =IF(A48="","",( IFERROR(O48*BE48,""))) -> 1213217.1 | BG48: {=IF(A48="","",( IFERROR((O48/ INDEX(er!$D$3:$D$75,MATCH(1, (er!$A$3:$A$75=$BG$2)*(er!$C$3:$C$75=Q48), 0)))*BE48,"")))} -> 868.44459 | BH48: =IF(A48="","",( IF(B48="Snapchat Rep", IF(A48="","",(P48-BF48)),-BF48))) -> -1213217.1 | BI48: {=IFERROR(INDEX('Com&tax'!$F$2:$F$5, MATCH(1, ('Com&tax'!$A$2:$A$5=B48)*('Com&tax'!$B$2:$B$5=Y48), 0)),0)} -> 0.049 | BJ48: =IF(A48="","",( IFERROR((J48*(1-BE48))*BI48,0))) -> 336869.94 | BK48: {=IF(A48="","",( IFERROR((J48*(1-BE48))*BI48/INDEX(er!D:D, MATCH(Q48,er!C:C,0),1),0)))} -> 241.13811 | BL48: {=IFERROR(INDEX('Com&tax'!$G$2:$G$5, MATCH(1, ('Com&tax'!$A$2:$A$5=B48)*('Com&tax'!$B$2:$B$5=Y48), 0)),0)} -> 0.1575 | BM48: =IF(A48="","",( IFERROR((J48*(1-BE48))*BL48,0))) -> 1082796.2 | BN48: {=IF(A48="","",( IFERROR((J48*(1-BE48))*BL48/INDEX(er!D:D, MATCH(Q48,er!C:C,0),1),0)))} -> 775.08679 | BO48: {=IFERROR(INDEX('Com&tax'!$H$2:$H$5, MATCH(1, ('Com&tax'!$A$2:$A$5=B48)*('Com&tax'!$B$2:$B$5=Y48), 0)),0)} -> 0 | BP48: =IF(A48="","",( IFERROR(J48*BO48,0))) -> 0 | BQ48: {=IF(A48="","",( IFERROR(J48*BO48/INDEX(er!D:D, MATCH(Q48,er!C:C,0),1),0)))} -> 0 | BR48: {=IFERROR(INDEX('Com&tax'!$F$2:$F$5, MATCH(1, ('Com&tax'!$A$2:$A$5=B48)*('Com&tax'!$D$2:$D$5=H48), 0)),0)} -> 0.049 | BS48: =IF(A48="","",( IFERROR((J48*(1-BE48))*BR48,0))) -> 336869.94 | BT48: {=IF(A48="","",( IFERROR((J48*(1-BE48))*BR48/INDEX(er!D:D, MATCH(Q48,er!C:C,0),1),0)))} -> 241.13811 | BU48: {=IFERROR(INDEX('Com&tax'!$G$2:$G$5, MATCH(1, ('Com&tax'!$A$2:$A$5=B48)*('Com&tax'!$D$2:$D$5=H48), 0)),0)} -> 0.1575 | BV48: =IF(A48="","",( IFERROR((J48*(1-BE48))*BU48,0))) -> 1082796.2 | BW48: {=IF(A48="","",( IFERROR((J48*(1-BE48))*BU48/INDEX(er!D:D, MATCH(Q48,er!C:C,0),1),0)))} -> 775.08679 | BX48: {=IFERROR(INDEX('Com&tax'!$H$2:$H$5, MATCH(1, ('Com&tax'!$A$2:$A$5=B48)*('Com&tax'!$D$2:$D$5=H48), 0)),0)} -> 0 | BY48: =IF(A48="","",( IFERROR(J48*BX48,0))) -> 0 | BZ48: {=IF(A48="","",( IFERROR(J48*BX48/INDEX(er!D:D, MATCH(Q48,er!C:C,0),1),0)))} -> 0 | CA48: {=IF(A48="","",( IFERROR(1-((P48/ INDEX(er!$D$3:$D$75,MATCH(1, (er!$A$3:$A$75=$BG$2)*(er!$C$3:$C$75=Q48), 0)) / (J48/ INDEX(er!$D$3:$D$75,MATCH(1, (er!$A$3:$A$75=$BG$2)*(er!$C$3:$C$75=L48), 0))))),"")))} -> 0.340005 | CB48: =IF(AB48="","",1-AD48/AB48) -> 0.33998 | CC48: =IF(AND(CA48="", CB48=""), "", CA48-CB48) -> 2.4999648e-05 | CD48: =BJ48+BM48-BS48-BV48 -> 0 | CE48: =BK48+BN48-BT48-BW48 -> 0 | CF48: =AJ48-CE48 -> -0.14 | CG48: =IF(OR(BE48="", AE48=""), "Miss", IF(ABS(AE48/100-AK48)<0.005, "OK", "Incorrect")) -> OK | CI48: OK | CK48: 0 | CL48: =(AI48+CK48)/INDEX(er!D:D,MATCH(AC48,er!C:C,0),1) -> -0.14473873 | CN48: =CK48/INDEX(er!D:D,MATCH(AC48,er!C:C,0),1) -> 0
A49: T3225691 | B49: Twitter Billing | C49: IMS | D49: AR_Media Company_Mercado Libre Argentina_T3225691 - MPA | Somos Francos - 26/01/2026 | G49: Argentina | H49: Aleph Argentina | I49: Argentina | J49: 4701458.8 | K49: 4701458.8 | L49: ARS | M49: 4701458.8 | N49: ARS | O49: 4701458.8 | P49: 3102939.3 | Q49: ARS | R49: Mexico | U49: 0 | V49: 2026-02 | W49: February/2026 | X49: IMS | Y49: Argentina | Z49: Mexico | AA49: ARS | AB49: 4701458.8 | AC49: ARS | AD49: 3103056.8 | AE49: 34 | AF49: OK | AG49: 0 | AH49: 0 | AI49: -117.54 | AJ49: -0.08 | AK49: 0.340005 | AL49: OK | AM49: 10573671 | AO49: Miss | AP49: Miss | AR49: Miss | AT49: Miss | AU49: 4701458.8 | AV49: 3363 | AW49: Miss | AX49: 4701458.8 | AY49: 3365.4 | AZ49: ARS | BA49: 3103056.8 | BB49: OK | BC49: -117.54 | BD49: -0.08 | BE49: {=IFERROR(INDEX('Com&tax'!$E$2:$E$5, MATCH(1, ('Com&tax'!$A$2:$A$5=B49)*('Com&tax'!$B$2:$B$5=G49), 0)),"")} -> 0.15 | BF49: =IF(A49="","",( IFERROR(O49*BE49,""))) -> 705218.82 | BG49: {=IF(A49="","",( IFERROR((O49/ INDEX(er!$D$3:$D$75,MATCH(1, (er!$A$3:$A$75=$BG$2)*(er!$C$3:$C$75=Q49), 0)))*BE49,"")))} -> 504.80946 | BH49: =IF(A49="","",( IF(B49="Snapchat Rep", IF(A49="","",(P49-BF49)),-BF49))) -> -705218.82 | BI49: {=IFERROR(INDEX('Com&tax'!$F$2:$F$5, MATCH(1, ('Com&tax'!$A$2:$A$5=B49)*('Com&tax'!$B$2:$B$5=Y49), 0)),0)} -> 0.049 | BJ49: =IF(A49="","",( IFERROR((J49*(1-BE49))*BI49,0))) -> 195815.76 | BK49: {=IF(A49="","",( IFERROR((J49*(1-BE49))*BI49/INDEX(er!D:D, MATCH(Q49,er!C:C,0),1),0)))} -> 140.16876 | BL49: {=IFERROR(INDEX('Com&tax'!$G$2:$G$5, MATCH(1, ('Com&tax'!$A$2:$A$5=B49)*('Com&tax'!$B$2:$B$5=Y49), 0)),0)} -> 0.1575 | BM49: =IF(A49="","",( IFERROR((J49*(1-BE49))*BL49,0))) -> 629407.8 | BN49: {=IF(A49="","",( IFERROR((J49*(1-BE49))*BL49/INDEX(er!D:D, MATCH(Q49,er!C:C,0),1),0)))} -> 450.54244 | BO49: {=IFERROR(INDEX('Com&tax'!$H$2:$H$5, MATCH(1, ('Com&tax'!$A$2:$A$5=B49)*('Com&tax'!$B$2:$B$5=Y49), 0)),0)} -> 0 | BP49: =IF(A49="","",( IFERROR(J49*BO49,0))) -> 0 | BQ49: {=IF(A49="","",( IFERROR(J49*BO49/INDEX(er!D:D, MATCH(Q49,er!C:C,0),1),0)))} -> 0 | BR49: {=IFERROR(INDEX('Com&tax'!$F$2:$F$5, MATCH(1, ('Com&tax'!$A$2:$A$5=B49)*('Com&tax'!$D$2:$D$5=H49), 0)),0)} -> 0.049 | BS49: =IF(A49="","",( IFERROR((J49*(1-BE49))*BR49,0))) -> 195815.76 | BT49: {=IF(A49="","",( IFERROR((J49*(1-BE49))*BR49/INDEX(er!D:D, MATCH(Q49,er!C:C,0),1),0)))} -> 140.16876 | BU49: {=IFERROR(INDEX('Com&tax'!$G$2:$G$5, MATCH(1, ('Com&tax'!$A$2:$A$5=B49)*('Com&tax'!$D$2:$D$5=H49), 0)),0)} -> 0.1575 | BV49: =IF(A49="","",( IFERROR((J49*(1-BE49))*BU49,0))) -> 629407.8 | BW49: {=IF(A49="","",( IFERROR((J49*(1-BE49))*BU49/INDEX(er!D:D, MATCH(Q49,er!C:C,0),1),0)))} -> 450.54244 | BX49: {=IFERROR(INDEX('Com&tax'!$H$2:$H$5, MATCH(1, ('Com&tax'!$A$2:$A$5=B49)*('Com&tax'!$D$2:$D$5=H49), 0)),0)} -> 0 | BY49: =IF(A49="","",( IFERROR(J49*BX49,0))) -> 0 | BZ49: {=IF(A49="","",( IFERROR(J49*BX49/INDEX(er!D:D, MATCH(Q49,er!C:C,0),1),0)))} -> 0 | CA49: {=IF(A49="","",( IFERROR(1-((P49/ INDEX(er!$D$3:$D$75,MATCH(1, (er!$A$3:$A$75=$BG$2)*(er!$C$3:$C$75=Q49), 0)) / (J49/ INDEX(er!$D$3:$D$75,MATCH(1, (er!$A$3:$A$75=$BG$2)*(er!$C$3:$C$75=L49), 0))))),"")))} -> 0.340005 | CB49: =IF(AB49="","",1-AD49/AB49) -> 0.33998 | CC49: =IF(AND(CA49="", CB49=""), "", CA49-CB49) -> 2.5000751e-05 | CD49: =BJ49+BM49-BS49-BV49 -> 0 | CE49: =BK49+BN49-BT49-BW49 -> 0 | CF49: =AJ49-CE49 -> -0.08 | CG49: =IF(OR(BE49="", AE49=""), "Miss", IF(ABS(AE49/100-AK49)<0.005, "OK", "Incorrect")) -> OK | CI49: OK | CK49: 0 | CL49: =(AI49+CK49)/INDEX(er!D:D,MATCH(AC49,er!C:C,0),1) -> -0.084137437 | CN49: =CK49/INDEX(er!D:D,MATCH(AC49,er!C:C,0),1) -> 0
A50: T3227274 | B50: Twitter Billing | C50: IMS | D50: AR_Media Company_Mercado Libre Argentina_T3227274 - MLA | Fecha Doble 2/2 - 15/01/2026 | G50: Argentina | H50: Aleph Argentina | I50: Argentina | J50: 1745729.2 | K50: 1745729.2 | L50: ARS | M50: 1745729.2 | N50: ARS | O50: 1745729.2 | P50: 1152172.5 | Q50: ARS | R50: Mexico | U50: 0 | V50: 2026-02 | W50: February/2026 | X50: IMS | Y50: Argentina | Z50: Mexico | AA50: ARS | AB50: 1745729.2 | AC50: ARS | AD50: 1152216.2 | AE50: 34 | AF50: OK | AG50: 0 | AH50: 0 | AI50: -43.64 | AJ50: -0.03 | AK50: 0.340005 | AL50: OK | AM50: 10573639 | AO50: Miss | AP50: Miss | AR50: Miss | AT50: Miss | AU50: 1745729.2 | AV50: 1248 | AW50: Miss | AX50: 1745729.2 | AY50: 1249.63 | AZ50: ARS | BA50: 1152216.2 | BB50: OK | BC50: -43.64 | BD50: -0.03 | BE50: {=IFERROR(INDEX('Com&tax'!$E$2:$E$5, MATCH(1, ('Com&tax'!$A$2:$A$5=B50)*('Com&tax'!$B$2:$B$5=G50), 0)),"")} -> 0.15 | BF50: =IF(A50="","",( IFERROR(O50*BE50,""))) -> 261859.37 | BG50: {=IF(A50="","",( IFERROR((O50/ INDEX(er!$D$3:$D$75,MATCH(1, (er!$A$3:$A$75=$BG$2)*(er!$C$3:$C$75=Q50), 0)))*BE50,"")))} -> 187.44408 | BH50: =IF(A50="","",( IF(B50="Snapchat Rep", IF(A50="","",(P50-BF50)),-BF50))) -> -261859.37 | BI50: {=IFERROR(INDEX('Com&tax'!$F$2:$F$5, MATCH(1, ('Com&tax'!$A$2:$A$5=B50)*('Com&tax'!$B$2:$B$5=Y50), 0)),0)} -> 0.049 | BJ50: =IF(A50="","",( IFERROR((J50*(1-BE50))*BI50,0))) -> 72709.62 | BK50: {=IF(A50="","",( IFERROR((J50*(1-BE50))*BI50/INDEX(er!D:D, MATCH(Q50,er!C:C,0),1),0)))} -> 52.046972 | BL50: {=IFERROR(INDEX('Com&tax'!$G$2:$G$5, MATCH(1, ('Com&tax'!$A$2:$A$5=B50)*('Com&tax'!$B$2:$B$5=Y50), 0)),0)} -> 0.1575 | BM50: =IF(A50="","",( IFERROR((J50*(1-BE50))*BL50,0))) -> 233709.49 | BN50: {=IF(A50="","",( IFERROR((J50*(1-BE50))*BL50/INDEX(er!D:D, MATCH(Q50,er!C:C,0),1),0)))} -> 167.29384 | BO50: {=IFERROR(INDEX('Com&tax'!$H$2:$H$5, MATCH(1, ('Com&tax'!$A$2:$A$5=B50)*('Com&tax'!$B$2:$B$5=Y50), 0)),0)} -> 0 | BP50: =IF(A50="","",( IFERROR(J50*BO50,0))) -> 0 | BQ50: {=IF(A50="","",( IFERROR(J50*BO50/INDEX(er!D:D, MATCH(Q50,er!C:C,0),1),0)))} -> 0 | BR50: {=IFERROR(INDEX('Com&tax'!$F$2:$F$5, MATCH(1, ('Com&tax'!$A$2:$A$5=B50)*('Com&tax'!$D$2:$D$5=H50), 0)),0)} -> 0.049 | BS50: =IF(A50="","",( IFERROR((J50*(1-BE50))*BR50,0))) -> 72709.62 | BT50: {=IF(A50="","",( IFERROR((J50*(1-BE50))*BR50/INDEX(er!D:D, MATCH(Q50,er!C:C,0),1),0)))} -> 52.046972 | BU50: {=IFERROR(INDEX('Com&tax'!$G$2:$G$5, MATCH(1, ('Com&tax'!$A$2:$A$5=B50)*('Com&tax'!$D$2:$D$5=H50), 0)),0)} -> 0.1575 | BV50: =IF(A50="","",( IFERROR((J50*(1-BE50))*BU50,0))) -> 233709.49 | BW50: {=IF(A50="","",( IFERROR((J50*(1-BE50))*BU50/INDEX(er!D:D, MATCH(Q50,er!C:C,0),1),0)))} -> 167.29384 | BX50: {=IFERROR(INDEX('Com&tax'!$H$2:$H$5, MATCH(1, ('Com&tax'!$A$2:$A$5=B50)*('Com&tax'!$D$2:$D$5=H50), 0)),0)} -> 0 | BY50: =IF(A50="","",( IFERROR(J50*BX50,0))) -> 0 | BZ50: {=IF(A50="","",( IFERROR(J50*BX50/INDEX(er!D:D, MATCH(Q50,er!C:C,0),1),0)))} -> 0 | CA50: {=IF(A50="","",( IFERROR(1-((P50/ INDEX(er!$D$3:$D$75,MATCH(1, (er!$A$3:$A$75=$BG$2)*(er!$C$3:$C$75=Q50), 0)) / (J50/ INDEX(er!$D$3:$D$75,MATCH(1, (er!$A$3:$A$75=$BG$2)*(er!$C$3:$C$75=L50), 0))))),"")))} -> 0.340005 | CB50: =IF(AB50="","",1-AD50/AB50) -> 0.33998 | CC50: =IF(AND(CA50="", CB50=""), "", CA50-CB50) -> 2.499815e-05 | CD50: =BJ50+BM50-BS50-BV50 -> 0 | CE50: =BK50+BN50-BT50-BW50 -> 0 | CF50: =AJ50-CE50 -> -0.03 | CG50: =IF(OR(BE50="", AE50=""), "Miss", IF(ABS(AE50/100-AK50)<0.005, "OK", "Incorrect")) -> OK | CI50: OK | CK50: 0 | CL50: =(AI50+CK50)/INDEX(er!D:D,MATCH(AC50,er!C:C,0),1) -> -0.031238368 | CN50: =CK50/INDEX(er!D:D,MATCH(AC50,er!C:C,0),1) -> 0
A51: T3231502 | B51: Twitter Rep | C51: IMS | D51: AR_Media Company_FAST FOOD SUDAMERICANA ARGENTINA_X | Burger King - Cosquin Rock '26 | G51: Argentina | H51: Aleph Argentina | I51: Argentina | J51: 92012.77 | K51: 92012.77 | L51: ARS | M51: 92012.77 | N51: ARS | O51: 92012.77 | P51: 55619.42 | Q51: ARS | R51: Mexico | U51: 0 | V51: 2026-02 | W51: February/2026 | X51: IMS | Y51: Argentina | Z51: Mexico | AA51: ARS | AB51: 92012.77 | AC51: ARS | AD51: 55619.42 | AE51: 39.55 | AF51: OK | AG51: 0 | AH51: 0 | AI51: 0 | AJ51: 0 | AK51: 0.39552499 | AL51: OK | AM51: 10573641 | AN51: Manually insert Revenue,Manually insert Cogs | AO51: Miss | AP51: Miss | AR51: Miss | AT51: Miss | AU51: 92012.77 | AV51: 64 | AW51: Miss | AX51: 92012.77 | AY51: 65.86 | AZ51: ARS | BA51: 55619.42 | BB51: OK | BC51: 0 | BD51: 0 | BE51: {=IFERROR(INDEX('Com&tax'!$E$2:$E$5, MATCH(1, ('Com&tax'!$A$2:$A$5=B51)*('Com&tax'!$B$2:$B$5=G51), 0)),"")} -> 0.15 | BF51: =IF(A51="","",( IFERROR(O51*BE51,""))) -> 13801.916 | BG51: {=IF(A51="","",( IFERROR((O51/ INDEX(er!$D$3:$D$75,MATCH(1, (er!$A$3:$A$75=$BG$2)*(er!$C$3:$C$75=Q51), 0)))*BE51,"")))} -> 9.8796818 | BH51: =IF(A51="","",( IF(B51="Snapchat Rep", IF(A51="","",(P51-BF51)),-BF51))) -> -13801.916 | BI51: {=IFERROR(INDEX('Com&tax'!$F$2:$F$5, MATCH(1, ('Com&tax'!$A$2:$A$5=B51)*('Com&tax'!$B$2:$B$5=Y51), 0)),0)} -> 0.049 | BJ51: =IF(A51="","",( IFERROR((J51*(1-BE51))*BI51,0))) -> 3832.3319 | BK51: {=IF(A51="","",( IFERROR((J51*(1-BE51))*BI51/INDEX(er!D:D, MATCH(Q51,er!C:C,0),1),0)))} -> 2.7432583 | BL51: {=IFERROR(INDEX('Com&tax'!$G$2:$G$5, MATCH(1, ('Com&tax'!$A$2:$A$5=B51)*('Com&tax'!$B$2:$B$5=Y51), 0)),0)} -> 0.1575 | BM51: =IF(A51="","",( IFERROR((J51*(1-BE51))*BL51,0))) -> 12318.21 | BN51: {=IF(A51="","",( IFERROR((J51*(1-BE51))*BL51/INDEX(er!D:D, MATCH(Q51,er!C:C,0),1),0)))} -> 8.817616 | BO51: {=IFERROR(INDEX('Com&tax'!$H$2:$H$5, MATCH(1, ('Com&tax'!$A$2:$A$5=B51)*('Com&tax'!$B$2:$B$5=Y51), 0)),0)} -> 0.07 | BP51: =IF(A51="","",( IFERROR(J51*BO51,0))) -> 6440.8939 | BQ51: {=IF(A51="","",( IFERROR(J51*BO51/INDEX(er!D:D, MATCH(Q51,er!C:C,0),1),0)))} -> 4.6105182 | BR51: {=IFERROR(INDEX('Com&tax'!$F$2:$F$5, MATCH(1, ('Com&tax'!$A$2:$A$5=B51)*('Com&tax'!$D$2:$D$5=H51), 0)),0)} -> 0.049 | BS51: =IF(A51="","",( IFERROR((J51*(1-BE51))*BR51,0))) -> 3832.3319 | BT51: {=IF(A51="","",( IFERROR((J51*(1-BE51))*BR51/INDEX(er!D:D, MATCH(Q51,er!C:C,0),1),0)))} -> 2.7432583 | BU51: {=IFERROR(INDEX('Com&tax'!$G$2:$G$5, MATCH(1, ('Com&tax'!$A$2:$A$5=B51)*('Com&tax'!$D$2:$D$5=H51), 0)),0)} -> 0.1575 | BV51: =IF(A51="","",( IFERROR((J51*(1-BE51))*BU51,0))) -> 12318.21 | BW51: {=IF(A51="","",( IFERROR((J51*(1-BE51))*BU51/INDEX(er!D:D, MATCH(Q51,er!C:C,0),1),0)))} -> 8.817616 | BX51: {=IFERROR(INDEX('Com&tax'!$H$2:$H$5, MATCH(1, ('Com&tax'!$A$2:$A$5=B51)*('Com&tax'!$D$2:$D$5=H51), 0)),0)} -> 0.07 | BY51: =IF(A51="","",( IFERROR(J51*BX51,0))) -> 6440.8939 | BZ51: {=IF(A51="","",( IFERROR(J51*BX51/INDEX(er!D:D, MATCH(Q51,er!C:C,0),1),0)))} -> 4.6105182 | CA51: {=IF(A51="","",( IFERROR(1-((P51/ INDEX(er!$D$3:$D$75,MATCH(1, (er!$A$3:$A$75=$BG$2)*(er!$C$3:$C$75=Q51), 0)) / (J51/ INDEX(er!$D$3:$D$75,MATCH(1, (er!$A$3:$A$75=$BG$2)*(er!$C$3:$C$75=L51), 0))))),"")))} -> 0.39552499 | CB51: =IF(AB51="","",1-AD51/AB51) -> 0.39552499 | CC51: =IF(AND(CA51="", CB51=""), "", CA51-CB51) -> 1.110223e-16 | CD51: =BJ51+BM51-BS51-BV51 -> 0 | CE51: =BK51+BN51-BT51-BW51 -> 0 | CF51: =AJ51-CE51 -> 0 | CG51: =IF(OR(BE51="", AE51=""), "Miss", IF(ABS(AE51/100-AK51)<0.005, "OK", "Incorrect")) -> OK | CI51: OK | CK51: 0 | CL51: =(AI51+CK51)/INDEX(er!D:D,MATCH(AC51,er!C:C,0),1) -> 0 | CN51: =CK51/INDEX(er!D:D,MATCH(AC51,er!C:C,0),1) -> 0
A52: T3231647 | B52: Twitter Rep | C52: IMS | D52: AR_Media Company_Play Digital Argentina_AR00400737 X | MODO | Promo COTO | G52: Argentina | H52: Aleph Argentina | I52: Argentina | J52: 4109965 | K52: 4109965 | L52: ARS | M52: 4109965 | N52: ARS | O52: 4109965 | P52: 2484371.2 | Q52: ARS | R52: Mexico | U52: 0 | V52: 2026-02 | W52: February/2026 | X52: IMS | Y52: Argentina | Z52: Mexico | AA52: ARS | AB52: 4109965 | AC52: ARS | AD52: 2484371.1 | AE52: 39.55 | AF52: OK | AG52: 0 | AH52: 0 | AI52: 0.17 | AJ52: 0 | AK52: 0.39552496 | AL52: OK | AM52: 10573633 | AO52: Miss | AP52: Miss | AR52: Miss | AT52: Miss | AU52: 4109965 | AV52: 2940 | AW52: Miss | AX52: 4109965 | AY52: 2941.99 | AZ52: ARS | BA52: 2484371.1 | BB52: OK | BC52: 0.17 | BD52: 0 | BE52: {=IFERROR(INDEX('Com&tax'!$E$2:$E$5, MATCH(1, ('Com&tax'!$A$2:$A$5=B52)*('Com&tax'!$B$2:$B$5=G52), 0)),"")} -> 0.15 | BF52: =IF(A52="","",( IFERROR(O52*BE52,""))) -> 616494.75 | BG52: {=IF(A52="","",( IFERROR((O52/ INDEX(er!$D$3:$D$75,MATCH(1, (er!$A$3:$A$75=$BG$2)*(er!$C$3:$C$75=Q52), 0)))*BE52,"")))} -> 441.29903 | BH52: =IF(A52="","",( IF(B52="Snapchat Rep", IF(A52="","",(P52-BF52)),-BF52))) -> -616494.75 | BI52: {=IFERROR(INDEX('Com&tax'!$F$2:$F$5, MATCH(1, ('Com&tax'!$A$2:$A$5=B52)*('Com&tax'!$B$2:$B$5=Y52), 0)),0)} -> 0.049 | BJ52: =IF(A52="","",( IFERROR((J52*(1-BE52))*BI52,0))) -> 171180.04 | BK52: {=IF(A52="","",( IFERROR((J52*(1-BE52))*BI52/INDEX(er!D:D, MATCH(Q52,er!C:C,0),1),0)))} -> 122.53403 | BL52: {=IFERROR(INDEX('Com&tax'!$G$2:$G$5, MATCH(1, ('Com&tax'!$A$2:$A$5=B52)*('Com&tax'!$B$2:$B$5=Y52), 0)),0)} -> 0.1575 | BM52: =IF(A52="","",( IFERROR((J52*(1-BE52))*BL52,0))) -> 550221.56 | BN52: {=IF(A52="","",( IFERROR((J52*(1-BE52))*BL52/INDEX(er!D:D, MATCH(Q52,er!C:C,0),1),0)))} -> 393.85939 | BO52: {=IFERROR(INDEX('Com&tax'!$H$2:$H$5, MATCH(1, ('Com&tax'!$A$2:$A$5=B52)*('Com&tax'!$B$2:$B$5=Y52), 0)),0)} -> 0.07 | BP52: =IF(A52="","",( IFERROR(J52*BO52,0))) -> 287697.55 | BQ52: {=IF(A52="","",( IFERROR(J52*BO52/INDEX(er!D:D, MATCH(Q52,er!C:C,0),1),0)))} -> 205.93955 | BR52: {=IFERROR(INDEX('Com&tax'!$F$2:$F$5, MATCH(1, ('Com&tax'!$A$2:$A$5=B52)*('Com&tax'!$D$2:$D$5=H52), 0)),0)} -> 0.049 | BS52: =IF(A52="","",( IFERROR((J52*(1-BE52))*BR52,0))) -> 171180.04 | BT52: {=IF(A52="","",( IFERROR((J52*(1-BE52))*BR52/INDEX(er!D:D, MATCH(Q52,er!C:C,0),1),0)))} -> 122.53403 | BU52: {=IFERROR(INDEX('Com&tax'!$G$2:$G$5, MATCH(1, ('Com&tax'!$A$2:$A$5=B52)*('Com&tax'!$D$2:$D$5=H52), 0)),0)} -> 0.1575 | BV52: =IF(A52="","",( IFERROR((J52*(1-BE52))*BU52,0))) -> 550221.56 | BW52: {=IF(A52="","",( IFERROR((J52*(1-BE52))*BU52/INDEX(er!D:D, MATCH(Q52,er!C:C,0),1),0)))} -> 393.85939 | BX52: {=IFERROR(INDEX('Com&tax'!$H$2:$H$5, MATCH(1, ('Com&tax'!$A$2:$A$5=B52)*('Com&tax'!$D$2:$D$5=H52), 0)),0)} -> 0.07 | BY52: =IF(A52="","",( IFERROR(J52*BX52,0))) -> 287697.55 | BZ52: {=IF(A52="","",( IFERROR(J52*BX52/INDEX(er!D:D, MATCH(Q52,er!C:C,0),1),0)))} -> 205.93955 | CA52: {=IF(A52="","",( IFERROR(1-((P52/ INDEX(er!$D$3:$D$75,MATCH(1, (er!$A$3:$A$75=$BG$2)*(er!$C$3:$C$75=Q52), 0)) / (J52/ INDEX(er!$D$3:$D$75,MATCH(1, (er!$A$3:$A$75=$BG$2)*(er!$C$3:$C$75=L52), 0))))),"")))} -> 0.39552496 | CB52: =IF(AB52="","",1-AD52/AB52) -> 0.395525 | CC52: =IF(AND(CA52="", CB52=""), "", CA52-CB52) -> -4.1362883e-08 | CD52: =BJ52+BM52-BS52-BV52 -> 0 | CE52: =BK52+BN52-BT52-BW52 -> 0 | CF52: =AJ52-CE52 -> 0 | CG52: =IF(OR(BE52="", AE52=""), "Miss", IF(ABS(AE52/100-AK52)<0.005, "OK", "Incorrect")) -> OK | CI52: OK | CK52: 0 | CL52: =(AI52+CK52)/INDEX(er!D:D,MATCH(AC52,er!C:C,0),1) -> 0.00012168933 | CN52: =CK52/INDEX(er!D:D,MATCH(AC52,er!C:C,0),1) -> 0
A53: T3231673 | B53: Twitter Rep | C53: IMS | D53: AR_Media Company_Bayer Argentina_X - Arg - FieldView - Año 2026 | G53: Argentina | H53: Aleph Argentina | I53: Argentina | J53: 798524.61 | K53: 798524.61 | L53: ARS | M53: 798524.61 | N53: ARS | O53: 798524.61 | P53: 482688.2 | Q53: ARS | R53: Mexico | U53: 0 | V53: 2026-02 | W53: February/2026 | X53: IMS | Y53: Argentina | Z53: Mexico | AA53: ARS | AB53: 798524.61 | AC53: ARS | AD53: 482688.16 | AE53: 39.55 | AF53: OK | AG53: 0 | AH53: 0 | AI53: 0.04 | AJ53: 0 | AK53: 0.39552495 | AL53: OK | AM53: 10573655 | AO53: Miss | AP53: Miss | AR53: Miss | AT53: Miss | AU53: 798524.61 | AV53: 570 | AW53: Miss | AX53: 798524.61 | AY53: 571.6 | AZ53: ARS | BA53: 482688.16 | BB53: OK | BC53: 0.04 | BD53: 0 | BE53: {=IFERROR(INDEX('Com&tax'!$E$2:$E$5, MATCH(1, ('Com&tax'!$A$2:$A$5=B53)*('Com&tax'!$B$2:$B$5=G53), 0)),"")} -> 0.15 | BF53: =IF(A53="","",( IFERROR(O53*BE53,""))) -> 119778.69 | BG53: {=IF(A53="","",( IFERROR((O53/ INDEX(er!$D$3:$D$75,MATCH(1, (er!$A$3:$A$75=$BG$2)*(er!$C$3:$C$75=Q53), 0)))*BE53,"")))} -> 85.739937 | BH53: =IF(A53="","",( IF(B53="Snapchat Rep", IF(A53="","",(P53-BF53)),-BF53))) -> -119778.69 | BI53: {=IFERROR(INDEX('Com&tax'!$F$2:$F$5, MATCH(1, ('Com&tax'!$A$2:$A$5=B53)*('Com&tax'!$B$2:$B$5=Y53), 0)),0)} -> 0.049 | BJ53: =IF(A53="","",( IFERROR((J53*(1-BE53))*BI53,0))) -> 33258.55 | BK53: {=IF(A53="","",( IFERROR((J53*(1-BE53))*BI53/INDEX(er!D:D, MATCH(Q53,er!C:C,0),1),0)))} -> 23.807122 | BL53: {=IFERROR(INDEX('Com&tax'!$G$2:$G$5, MATCH(1, ('Com&tax'!$A$2:$A$5=B53)*('Com&tax'!$B$2:$B$5=Y53), 0)),0)} -> 0.1575 | BM53: =IF(A53="","",( IFERROR((J53*(1-BE53))*BL53,0))) -> 106902.48 | BN53: {=IF(A53="","",( IFERROR((J53*(1-BE53))*BL53/INDEX(er!D:D, MATCH(Q53,er!C:C,0),1),0)))} -> 76.522893 | BO53: {=IFERROR(INDEX('Com&tax'!$H$2:$H$5, MATCH(1, ('Com&tax'!$A$2:$A$5=B53)*('Com&tax'!$B$2:$B$5=Y53), 0)),0)} -> 0.07 | BP53: =IF(A53="","",( IFERROR(J53*BO53,0))) -> 55896.723 | BQ53: {=IF(A53="","",( IFERROR(J53*BO53/INDEX(er!D:D, MATCH(Q53,er!C:C,0),1),0)))} -> 40.01197 | BR53: {=IFERROR(INDEX('Com&tax'!$F$2:$F$5, MATCH(1, ('Com&tax'!$A$2:$A$5=B53)*('Com&tax'!$D$2:$D$5=H53), 0)),0)} -> 0.049 | BS53: =IF(A53="","",( IFERROR((J53*(1-BE53))*BR53,0))) -> 33258.55 | BT53: {=IF(A53="","",( IFERROR((J53*(1-BE53))*BR53/INDEX(er!D:D, MATCH(Q53,er!C:C,0),1),0)))} -> 23.807122 | BU53: {=IFERROR(INDEX('Com&tax'!$G$2:$G$5, MATCH(1, ('Com&tax'!$A$2:$A$5=B53)*('Com&tax'!$D$2:$D$5=H53), 0)),0)} -> 0.1575 | BV53: =IF(A53="","",( IFERROR((J53*(1-BE53))*BU53,0))) -> 106902.48 | BW53: {=IF(A53="","",( IFERROR((J53*(1-BE53))*BU53/INDEX(er!D:D, MATCH(Q53,er!C:C,0),1),0)))} -> 76.522893 | BX53: {=IFERROR(INDEX('Com&tax'!$H$2:$H$5, MATCH(1, ('Com&tax'!$A$2:$A$5=B53)*('Com&tax'!$D$2:$D$5=H53), 0)),0)} -> 0.07 | BY53: =IF(A53="","",( IFERROR(J53*BX53,0))) -> 55896.723 | BZ53: {=IF(A53="","",( IFERROR(J53*BX53/INDEX(er!D:D, MATCH(Q53,er!C:C,0),1),0)))} -> 40.01197 | CA53: {=IF(A53="","",( IFERROR(1-((P53/ INDEX(er!$D$3:$D$75,MATCH(1, (er!$A$3:$A$75=$BG$2)*(er!$C$3:$C$75=Q53), 0)) / (J53/ INDEX(er!$D$3:$D$75,MATCH(1, (er!$A$3:$A$75=$BG$2)*(er!$C$3:$C$75=L53), 0))))),"")))} -> 0.39552495 | CB53: =IF(AB53="","",1-AD53/AB53) -> 0.395525 | CC53: =IF(AND(CA53="", CB53=""), "", CA53-CB53) -> -5.0092382e-08 | CD53: =BJ53+BM53-BS53-BV53 -> 0 | CE53: =BK53+BN53-BT53-BW53 -> 0 | CF53: =AJ53-CE53 -> 0 | CG53: =IF(OR(BE53="", AE53=""), "Miss", IF(ABS(AE53/100-AK53)<0.005, "OK", "Incorrect")) -> OK | CI53: OK | CK53: 0 | CL53: =(AI53+CK53)/INDEX(er!D:D,MATCH(AC53,er!C:C,0),1) -> 2.8632785e-05 | CN53: =CK53/INDEX(er!D:D,MATCH(AC53,er!C:C,0),1) -> 0
A54: T3233788 | B54: Twitter Rep | C54: IMS | D54: AR_Media Company_Honda Motor de Argentina_X | Arg | Honda | Q1 2026 | G54: Argentina | H54: Aleph Argentina | I54: Argentina | J54: 2028302 | K54: 2028302 | L54: ARS | M54: 2028302 | N54: ARS | O54: 2028302 | P54: 1226058 | Q54: ARS | R54: Mexico | U54: 0 | V54: 2026-02 | W54: February/2026 | X54: IMS | Y54: Argentina | Z54: Mexico | AA54: ARS | AB54: 2028302 | AC54: ARS | AD54: 1226057.9 | AE54: 39.55 | AF54: OK | AG54: 0 | AH54: 0 | AI54: 0.09 | AJ54: 0 | AK54: 0.39552496 | AL54: OK | AM54: 10573642 | AO54: Miss | AP54: Miss | AR54: Miss | AT54: Miss | AU54: 2028302 | AV54: 1450 | AW54: Miss | AX54: 2028302 | AY54: 1451.9 | AZ54: ARS | BA54: 1226057.9 | BB54: OK | BC54: 0.08 | BD54: 0 | BE54: {=IFERROR(INDEX('Com&tax'!$E$2:$E$5, MATCH(1, ('Com&tax'!$A$2:$A$5=B54)*('Com&tax'!$B$2:$B$5=G54), 0)),"")} -> 0.15 | BF54: =IF(A54="","",( IFERROR(O54*BE54,""))) -> 304245.31 | BG54: {=IF(A54="","",( IFERROR((O54/ INDEX(er!$D$3:$D$75,MATCH(1, (er!$A$3:$A$75=$BG$2)*(er!$C$3:$C$75=Q54), 0)))*BE54,"")))} -> 217.78476 | BH54: =IF(A54="","",( IF(B54="Snapchat Rep", IF(A54="","",(P54-BF54)),-BF54))) -> -304245.31 | BI54: {=IFERROR(INDEX('Com&tax'!$F$2:$F$5, MATCH(1, ('Com&tax'!$A$2:$A$5=B54)*('Com&tax'!$B$2:$B$5=Y54), 0)),0)} -> 0.049 | BJ54: =IF(A54="","",( IFERROR((J54*(1-BE54))*BI54,0))) -> 84478.78 | BK54: {=IF(A54="","",( IFERROR((J54*(1-BE54))*BI54/INDEX(er!D:D, MATCH(Q54,er!C:C,0),1),0)))} -> 60.471568 | BL54: {=IFERROR(INDEX('Com&tax'!$G$2:$G$5, MATCH(1, ('Com&tax'!$A$2:$A$5=B54)*('Com&tax'!$B$2:$B$5=Y54), 0)),0)} -> 0.1575 | BM54: =IF(A54="","",( IFERROR((J54*(1-BE54))*BL54,0))) -> 271538.94 | BN54: {=IF(A54="","",( IFERROR((J54*(1-BE54))*BL54/INDEX(er!D:D, MATCH(Q54,er!C:C,0),1),0)))} -> 194.3729 | BO54: {=IFERROR(INDEX('Com&tax'!$H$2:$H$5, MATCH(1, ('Com&tax'!$A$2:$A$5=B54)*('Com&tax'!$B$2:$B$5=Y54), 0)),0)} -> 0.07 | BP54: =IF(A54="","",( IFERROR(J54*BO54,0))) -> 141981.14 | BQ54: {=IF(A54="","",( IFERROR(J54*BO54/INDEX(er!D:D, MATCH(Q54,er!C:C,0),1),0)))} -> 101.63289 | BR54: {=IFERROR(INDEX('Com&tax'!$F$2:$F$5, MATCH(1, ('Com&tax'!$A$2:$A$5=B54)*('Com&tax'!$D$2:$D$5=H54), 0)),0)} -> 0.049 | BS54: =IF(A54="","",( IFERROR((J54*(1-BE54))*BR54,0))) -> 84478.78 | BT54: {=IF(A54="","",( IFERROR((J54*(1-BE54))*BR54/INDEX(er!D:D, MATCH(Q54,er!C:C,0),1),0)))} -> 60.471568 | BU54: {=IFERROR(INDEX('Com&tax'!$G$2:$G$5, MATCH(1, ('Com&tax'!$A$2:$A$5=B54)*('Com&tax'!$D$2:$D$5=H54), 0)),0)} -> 0.1575 | BV54: =IF(A54="","",( IFERROR((J54*(1-BE54))*BU54,0))) -> 271538.94 | BW54: {=IF(A54="","",( IFERROR((J54*(1-BE54))*BU54/INDEX(er!D:D, MATCH(Q54,er!C:C,0),1),0)))} -> 194.3729 | BX54: {=IFERROR(INDEX('Com&tax'!$H$2:$H$5, MATCH(1, ('Com&tax'!$A$2:$A$5=B54)*('Com&tax'!$D$2:$D$5=H54), 0)),0)} -> 0.07 | BY54: =IF(A54="","",( IFERROR(J54*BX54,0))) -> 141981.14 | BZ54: {=IF(A54="","",( IFERROR(J54*BX54/INDEX(er!D:D, MATCH(Q54,er!C:C,0),1),0)))} -> 101.63289 | CA54: {=IF(A54="","",( IFERROR(1-((P54/ INDEX(er!$D$3:$D$75,MATCH(1, (er!$A$3:$A$75=$BG$2)*(er!$C$3:$C$75=Q54), 0)) / (J54/ INDEX(er!$D$3:$D$75,MATCH(1, (er!$A$3:$A$75=$BG$2)*(er!$C$3:$C$75=L54), 0))))),"")))} -> 0.39552496 | CB54: =IF(AB54="","",1-AD54/AB54) -> 0.395525 | CC54: =IF(AND(CA54="", CB54=""), "", CA54-CB54) -> -4.437209e-08 | CD54: =BJ54+BM54-BS54-BV54 -> 0 | CE54: =BK54+BN54-BT54-BW54 -> 0 | CF54: =AJ54-CE54 -> 0 | CG54: =IF(OR(BE54="", AE54=""), "Miss", IF(ABS(AE54/100-AK54)<0.005, "OK", "Incorrect")) -> OK | CI54: OK | CK54: 0 | CL54: =(AI54+CK54)/INDEX(er!D:D,MATCH(AC54,er!C:C,0),1) -> 6.4423765e-05 | CN54: =CK54/INDEX(er!D:D,MATCH(AC54,er!C:C,0),1) -> 0
A55: T3235652 | B55: Twitter Rep | C55: IMS | D55: AR_Media Company_YPF S.A. ARGENTINA_AR00401632-X-YPF-COMBUSTIBLES-BENEFICIO BNA+MODO-Ene 26 | G55: Argentina | H55: Aleph Argentina | I55: Argentina | J55: 1419697 | K55: 1419697 | L55: ARS | M55: 1419697 | N55: ARS | O55: 1419697 | P55: 858171.42 | Q55: ARS | R55: Mexico | U55: 0 | V55: 2026-02 | W55: February/2026 | X55: IMS | Y55: Argentina | Z55: Mexico | AA55: ARS | AB55: 1419697 | AC55: ARS | AD55: 858171.36 | AE55: 39.55 | AF55: OK | AG55: 0 | AH55: 0 | AI55: 0.06 | AJ55: 0 | AK55: 0.39552496 | AL55: OK | AM55: 10573643 | AO55: Miss | AP55: Miss | AR55: Miss | AT55: Miss | AU55: 1419697 | AV55: 1014 | AW55: Miss | AX55: 1419697 | AY55: 1016.25 | AZ55: ARS | BA55: 858171.37 | BB55: OK | BC55: 0.05 | BD55: 0 | BE55: {=IFERROR(INDEX('Com&tax'!$E$2:$E$5, MATCH(1, ('Com&tax'!$A$2:$A$5=B55)*('Com&tax'!$B$2:$B$5=G55), 0)),"")} -> 0.15 | BF55: =IF(A55="","",( IFERROR(O55*BE55,""))) -> 212954.55 | BG55: {=IF(A55="","",( IFERROR((O55/ INDEX(er!$D$3:$D$75,MATCH(1, (er!$A$3:$A$75=$BG$2)*(er!$C$3:$C$75=Q55), 0)))*BE55,"")))} -> 152.43705 | BH55: =IF(A55="","",( IF(B55="Snapchat Rep", IF(A55="","",(P55-BF55)),-BF55))) -> -212954.55 | BI55: {=IFERROR(INDEX('Com&tax'!$F$2:$F$5, MATCH(1, ('Com&tax'!$A$2:$A$5=B55)*('Com&tax'!$B$2:$B$5=Y55), 0)),0)} -> 0.049 | BJ55: =IF(A55="","",( IFERROR((J55*(1-BE55))*BI55,0))) -> 59130.381 | BK55: {=IF(A55="","",( IFERROR((J55*(1-BE55))*BI55/INDEX(er!D:D, MATCH(Q55,er!C:C,0),1),0)))} -> 42.326687 | BL55: {=IFERROR(INDEX('Com&tax'!$G$2:$G$5, MATCH(1, ('Com&tax'!$A$2:$A$5=B55)*('Com&tax'!$B$2:$B$5=Y55), 0)),0)} -> 0.1575 | BM55: =IF(A55="","",( IFERROR((J55*(1-BE55))*BL55,0))) -> 190061.94 | BN55: {=IF(A55="","",( IFERROR((J55*(1-BE55))*BL55/INDEX(er!D:D, MATCH(Q55,er!C:C,0),1),0)))} -> 136.05006 | BO55: {=IFERROR(INDEX('Com&tax'!$H$2:$H$5, MATCH(1, ('Com&tax'!$A$2:$A$5=B55)*('Com&tax'!$B$2:$B$5=Y55), 0)),0)} -> 0.07 | BP55: =IF(A55="","",( IFERROR(J55*BO55,0))) -> 99378.792 | BQ55: {=IF(A55="","",( IFERROR(J55*BO55/INDEX(er!D:D, MATCH(Q55,er!C:C,0),1),0)))} -> 71.137289 | BR55: {=IFERROR(INDEX('Com&tax'!$F$2:$F$5, MATCH(1, ('Com&tax'!$A$2:$A$5=B55)*('Com&tax'!$D$2:$D$5=H55), 0)),0)} -> 0.049 | BS55: =IF(A55="","",( IFERROR((J55*(1-BE55))*BR55,0))) -> 59130.381 | BT55: {=IF(A55="","",( IFERROR((J55*(1-BE55))*BR55/INDEX(er!D:D, MATCH(Q55,er!C:C,0),1),0)))} -> 42.326687 | BU55: {=IFERROR(INDEX('Com&tax'!$G$2:$G$5, MATCH(1, ('Com&tax'!$A$2:$A$5=B55)*('Com&tax'!$D$2:$D$5=H55), 0)),0)} -> 0.1575 | BV55: =IF(A55="","",( IFERROR((J55*(1-BE55))*BU55,0))) -> 190061.94 | BW55: {=IF(A55="","",( IFERROR((J55*(1-BE55))*BU55/INDEX(er!D:D, MATCH(Q55,er!C:C,0),1),0)))} -> 136.05006 | BX55: {=IFERROR(INDEX('Com&tax'!$H$2:$H$5, MATCH(1, ('Com&tax'!$A$2:$A$5=B55)*('Com&tax'!$D$2:$D$5=H55), 0)),0)} -> 0.07 | BY55: =IF(A55="","",( IFERROR(J55*BX55,0))) -> 99378.792 | BZ55: {=IF(A55="","",( IFERROR(J55*BX55/INDEX(er!D:D, MATCH(Q55,er!C:C,0),1),0)))} -> 71.137289 | CA55: {=IF(A55="","",( IFERROR(1-((P55/ INDEX(er!$D$3:$D$75,MATCH(1, (er!$A$3:$A$75=$BG$2)*(er!$C$3:$C$75=Q55), 0)) / (J55/ INDEX(er!$D$3:$D$75,MATCH(1, (er!$A$3:$A$75=$BG$2)*(er!$C$3:$C$75=L55), 0))))),"")))} -> 0.39552496 | CB55: =IF(AB55="","",1-AD55/AB55) -> 0.395525 | CC55: =IF(AND(CA55="", CB55=""), "", CA55-CB55) -> -4.2262538e-08 | CD55: =BJ55+BM55-BS55-BV55 -> 0 | CE55: =BK55+BN55-BT55-BW55 -> 0 | CF55: =AJ55-CE55 -> 0 | CG55: =IF(OR(BE55="", AE55=""), "Miss", IF(ABS(AE55/100-AK55)<0.005, "OK", "Incorrect")) -> OK | CI55: OK | CK55: 0 | CL55: =(AI55+CK55)/INDEX(er!D:D,MATCH(AC55,er!C:C,0),1) -> 4.2949177e-05 | CN55: =CK55/INDEX(er!D:D,MATCH(AC55,er!C:C,0),1) -> 0
A56: T3235657 | B56: Twitter Rep | C56: IMS | D56: AR_Media Company_Hipódromo Argentino de Palermo S.A_AR00402568-X-Betfun-Takeover-Feb 26-CF | G56: Argentina | H56: Aleph Argentina | I56: Argentina | J56: 3110400 | K56: 3110400 | L56: ARS | M56: 3110400 | N56: ARS | O56: 3110400 | P56: 1880159.2 | Q56: ARS | R56: Mexico | U56: 0 | V56: 2026-02 | W56: February/2026 | X56: IMS | Y56: Argentina | Z56: Mexico | AA56: ARS | AB56: 3110400 | AC56: ARS | AD56: 1880159 | AE56: 39.55 | AF56: OK | AG56: 0 | AH56: 0 | AI56: 0.12 | AJ56: 0 | AK56: 0.39552496 | AL56: OK | AM56: 10573622 | AO56: Miss | AP56: Miss | AR56: Miss | AT56: Miss | AU56: 3110400 | AV56: 2224 | AW56: Miss | AX56: 3110400 | AY56: 2226.49 | AZ56: ARS | BA56: 1880159 | BB56: OK | BC56: 0.12 | BD56: 0 | BE56: {=IFERROR(INDEX('Com&tax'!$E$2:$E$5, MATCH(1, ('Com&tax'!$A$2:$A$5=B56)*('Com&tax'!$B$2:$B$5=G56), 0)),"")} -> 0.15 | BF56: =IF(A56="","",( IFERROR(O56*BE56,""))) -> 466560 | BG56: {=IF(A56="","",( IFERROR((O56/ INDEX(er!$D$3:$D$75,MATCH(1, (er!$A$3:$A$75=$BG$2)*(er!$C$3:$C$75=Q56), 0)))*BE56,"")))} -> 333.9728 | BH56: =IF(A56="","",( IF(B56="Snapchat Rep", IF(A56="","",(P56-BF56)),-BF56))) -> -466560 | BI56: {=IFERROR(INDEX('Com&tax'!$F$2:$F$5, MATCH(1, ('Com&tax'!$A$2:$A$5=B56)*('Com&tax'!$B$2:$B$5=Y56), 0)),0)} -> 0.049 | BJ56: =IF(A56="","",( IFERROR((J56*(1-BE56))*BI56,0))) -> 129548.16 | BK56: {=IF(A56="","",( IFERROR((J56*(1-BE56))*BI56/INDEX(er!D:D, MATCH(Q56,er!C:C,0),1),0)))} -> 92.733114 | BL56: {=IFERROR(INDEX('Com&tax'!$G$2:$G$5, MATCH(1, ('Com&tax'!$A$2:$A$5=B56)*('Com&tax'!$B$2:$B$5=Y56), 0)),0)} -> 0.1575 | BM56: =IF(A56="","",( IFERROR((J56*(1-BE56))*BL56,0))) -> 416404.8 | BN56: {=IF(A56="","",( IFERROR((J56*(1-BE56))*BL56/INDEX(er!D:D, MATCH(Q56,er!C:C,0),1),0)))} -> 298.07072 | BO56: {=IFERROR(INDEX('Com&tax'!$H$2:$H$5, MATCH(1, ('Com&tax'!$A$2:$A$5=B56)*('Com&tax'!$B$2:$B$5=Y56), 0)),0)} -> 0.07 | BP56: =IF(A56="","",( IFERROR(J56*BO56,0))) -> 217728 | BQ56: {=IF(A56="","",( IFERROR(J56*BO56/INDEX(er!D:D, MATCH(Q56,er!C:C,0),1),0)))} -> 155.85397 | BR56: {=IFERROR(INDEX('Com&tax'!$F$2:$F$5, MATCH(1, ('Com&tax'!$A$2:$A$5=B56)*('Com&tax'!$D$2:$D$5=H56), 0)),0)} -> 0.049 | BS56: =IF(A56="","",( IFERROR((J56*(1-BE56))*BR56,0))) -> 129548.16 | BT56: {=IF(A56="","",( IFERROR((J56*(1-BE56))*BR56/INDEX(er!D:D, MATCH(Q56,er!C:C,0),1),0)))} -> 92.733114 | BU56: {=IFERROR(INDEX('Com&tax'!$G$2:$G$5, MATCH(1, ('Com&tax'!$A$2:$A$5=B56)*('Com&tax'!$D$2:$D$5=H56), 0)),0)} -> 0.1575 | BV56: =IF(A56="","",( IFERROR((J56*(1-BE56))*BU56,0))) -> 416404.8 | BW56: {=IF(A56="","",( IFERROR((J56*(1-BE56))*BU56/INDEX(er!D:D, MATCH(Q56,er!C:C,0),1),0)))} -> 298.07072 | BX56: {=IFERROR(INDEX('Com&tax'!$H$2:$H$5, MATCH(1, ('Com&tax'!$A$2:$A$5=B56)*('Com&tax'!$D$2:$D$5=H56), 0)),0)} -> 0.07 | BY56: =IF(A56="","",( IFERROR(J56*BX56,0))) -> 217728 | BZ56: {=IF(A56="","",( IFERROR(J56*BX56/INDEX(er!D:D, MATCH(Q56,er!C:C,0),1),0)))} -> 155.85397 | CA56: {=IF(A56="","",( IFERROR(1-((P56/ INDEX(er!$D$3:$D$75,MATCH(1, (er!$A$3:$A$75=$BG$2)*(er!$C$3:$C$75=Q56), 0)) / (J56/ INDEX(er!$D$3:$D$75,MATCH(1, (er!$A$3:$A$75=$BG$2)*(er!$C$3:$C$75=L56), 0))))),"")))} -> 0.39552496 | CB56: =IF(AB56="","",1-AD56/AB56) -> 0.395525 | CC56: =IF(AND(CA56="", CB56=""), "", CA56-CB56) -> -3.8580247e-08 | CD56: =BJ56+BM56-BS56-BV56 -> 0 | CE56: =BK56+BN56-BT56-BW56 -> 0 | CF56: =AJ56-CE56 -> 0 | CG56: =IF(OR(BE56="", AE56=""), "Miss", IF(ABS(AE56/100-AK56)<0.005, "OK", "Incorrect")) -> OK | CI56: OK | CK56: 0 | CL56: =(AI56+CK56)/INDEX(er!D:D,MATCH(AC56,er!C:C,0),1) -> 8.5898354e-05 | CN56: =CK56/INDEX(er!D:D,MATCH(AC56,er!C:C,0),1) -> 0
A57: T3237872 | B57: Twitter Rep | C57: IMS | D57: AR_Media Company_Bodog Malta_AR00402659-X ARG-Bodog Brasil-Q1/Q2-26 | G57: Argentina | H57: Aleph Argentina | I57: Argentina | J57: 12942.5 | K57: 12942.5 | L57: ARS | M57: 8.35 | N57: USD | O57: 8.35 | P57: 5.5 | Q57: USD | R57: Mexico | U57: 0 | V57: 2026-02 | W57: February/2026 | X57: IMS | Y57: Malta | Z57: Mexico | AA57: USD | AB57: 8.35 | AC57: USD | AD57: 7.1 | AE57: 15 | AF57: OK | AG57: 0 | AH57: 0 | AI57: -1.6 | AJ57: -1.6 | AK57: 0.40633572 | AL57: OK | AM57: 10572898 | AO57: Miss | AP57: Miss | AR57: Miss | AT57: Miss | AU57: 8.35 | AV57: 6 | AW57: Miss | AX57: 8.35 | AY57: 8.35 | AZ57: USD | BA57: 7.1 | BB57: OK | BC57: -1.6 | BD57: -1.6 | BE57: {=IFERROR(INDEX('Com&tax'!$E$2:$E$5, MATCH(1, ('Com&tax'!$A$2:$A$5=B57)*('Com&tax'!$B$2:$B$5=G57), 0)),"")} -> 0.15 | BF57: =IF(A57="","",( IFERROR(O57*BE57,""))) -> 1.2525 | BG57: {=IF(A57="","",( IFERROR((O57/ INDEX(er!$D$3:$D$75,MATCH(1, (er!$A$3:$A$75=$BG$2)*(er!$C$3:$C$75=Q57), 0)))*BE57,"")))} -> 1.2525 | BH57: =IF(A57="","",( IF(B57="Snapchat Rep", IF(A57="","",(P57-BF57)),-BF57))) -> -1.2525 | BI57: {=IFERROR(INDEX('Com&tax'!$F$2:$F$5, MATCH(1, ('Com&tax'!$A$2:$A$5=B57)*('Com&tax'!$B$2:$B$5=Y57), 0)),0)} -> 0 | BJ57: =IF(A57="","",( IFERROR((J57*(1-BE57))*BI57,0))) -> 0 | BK57: {=IF(A57="","",( IFERROR((J57*(1-BE57))*BI57/INDEX(er!D:D, MATCH(Q57,er!C:C,0),1),0)))} -> 0 | BL57: {=IFERROR(INDEX('Com&tax'!$G$2:$G$5, MATCH(1, ('Com&tax'!$A$2:$A$5=B57)*('Com&tax'!$B$2:$B$5=Y57), 0)),0)} -> 0 | BM57: =IF(A57="","",( IFERROR((J57*(1-BE57))*BL57,0))) -> 0 | BN57: {=IF(A57="","",( IFERROR((J57*(1-BE57))*BL57/INDEX(er!D:D, MATCH(Q57,er!C:C,0),1),0)))} -> 0 | BO57: {=IFERROR(INDEX('Com&tax'!$H$2:$H$5, MATCH(1, ('Com&tax'!$A$2:$A$5=B57)*('Com&tax'!$B$2:$B$5=Y57), 0)),0)} -> 0 | BP57: =IF(A57="","",( IFERROR(J57*BO57,0))) -> 0 | BQ57: {=IF(A57="","",( IFERROR(J57*BO57/INDEX(er!D:D, MATCH(Q57,er!C:C,0),1),0)))} -> 0 | BR57: {=IFERROR(INDEX('Com&tax'!$F$2:$F$5, MATCH(1, ('Com&tax'!$A$2:$A$5=B57)*('Com&tax'!$D$2:$D$5=H57), 0)),0)} -> 0.049 | BS57: =IF(A57="","",( IFERROR((J57*(1-BE57))*BR57,0))) -> 539.05512 | BT57: {=IF(A57="","",( IFERROR((J57*(1-BE57))*BR57/INDEX(er!D:D, MATCH(Q57,er!C:C,0),1),0)))} -> 539.05512 | BU57: {=IFERROR(INDEX('Com&tax'!$G$2:$G$5, MATCH(1, ('Com&tax'!$A$2:$A$5=B57)*('Com&tax'!$D$2:$D$5=H57), 0)),0)} -> 0.1575 | BV57: =IF(A57="","",( IFERROR((J57*(1-BE57))*BU57,0))) -> 1732.6772 | BW57: {=IF(A57="","",( IFERROR((J57*(1-BE57))*BU57/INDEX(er!D:D, MATCH(Q57,er!C:C,0),1),0)))} -> 1732.6772 | BX57: {=IFERROR(INDEX('Com&tax'!$H$2:$H$5, MATCH(1, ('Com&tax'!$A$2:$A$5=B57)*('Com&tax'!$D$2:$D$5=H57), 0)),0)} -> 0.07 | BY57: =IF(A57="","",( IFERROR(J57*BX57,0))) -> 905.975 | BZ57: {=IF(A57="","",( IFERROR(J57*BX57/INDEX(er!D:D, MATCH(Q57,er!C:C,0),1),0)))} -> 905.975 | CA57: {=IF(A57="","",( IFERROR(1-((P57/ INDEX(er!$D$3:$D$75,MATCH(1, (er!$A$3:$A$75=$BG$2)*(er!$C$3:$C$75=Q57), 0)) / (J57/ INDEX(er!$D$3:$D$75,MATCH(1, (er!$A$3:$A$75=$BG$2)*(er!$C$3:$C$75=L57), 0))))),"")))} -> 0.40633572 | CB57: =IF(AB57="","",1-AD57/AB57) -> 0.1497006 | CC57: =IF(AND(CA57="", CB57=""), "", CA57-CB57) -> 0.25663512 | CD57: =BJ57+BM57-BS57-BV57 -> -2271.7323 | CE57: =BK57+BN57-BT57-BW57 -> -2271.7323 | CF57: =AJ57-CE57 -> 2270.1323 | CG57: =IF(OR(BE57="", AE57=""), "Miss", IF(ABS(AE57/100-AK57)<0.005, "OK", "Incorrect")) -> Incorrect | CI57: OK. Diff. Bill. / Adv. Country | CK57: 0 | CL57: =(AI57+CK57)/INDEX(er!D:D,MATCH(AC57,er!C:C,0),1) -> -1.6 | CN57: =CK57/INDEX(er!D:D,MATCH(AC57,er!C:C,0),1) -> 0
A58: T3237874 | B58: Twitter Rep | C58: IMS | D58: AR_Media Company_Bodog Malta_AR00402658-X ARG-Bodog México-Q1/Q2-26 | G58: Argentina | H58: Aleph Argentina | I58: Argentina | J58: 2669100 | K58: 2669100 | L58: ARS | M58: 1722 | N58: USD | O58: 1722 | P58: 1134.32 | Q58: USD | R58: Mexico | U58: 0 | V58: 2026-02 | W58: February/2026 | X58: IMS | Y58: Malta | Z58: Mexico | AA58: USD | AB58: 1722 | AC58: USD | AD58: 1463.7 | AE58: 15 | AF58: OK | AG58: 0 | AH58: 0 | AI58: -329.38 | AJ58: -329.38 | AK58: 0.40629986 | AL58: OK | AM58: 10572880 | AO58: Miss | AP58: Miss | AR58: Miss | AT58: Miss | AU58: 1722 | AV58: 1720 | AW58: Miss | AX58: 1722 | AY58: 1722 | AZ58: USD | BA58: 1463.7 | BB58: OK | BC58: -329.38 | BD58: -329.38 | BE58: {=IFERROR(INDEX('Com&tax'!$E$2:$E$5, MATCH(1, ('Com&tax'!$A$2:$A$5=B58)*('Com&tax'!$B$2:$B$5=G58), 0)),"")} -> 0.15 | BF58: =IF(A58="","",( IFERROR(O58*BE58,""))) -> 258.3 | BG58: {=IF(A58="","",( IFERROR((O58/ INDEX(er!$D$3:$D$75,MATCH(1, (er!$A$3:$A$75=$BG$2)*(er!$C$3:$C$75=Q58), 0)))*BE58,"")))} -> 258.3 | BH58: =IF(A58="","",( IF(B58="Snapchat Rep", IF(A58="","",(P58-BF58)),-BF58))) -> -258.3 | BI58: {=IFERROR(INDEX('Com&tax'!$F$2:$F$5, MATCH(1, ('Com&tax'!$A$2:$A$5=B58)*('Com&tax'!$B$2:$B$5=Y58), 0)),0)} -> 0 | BJ58: =IF(A58="","",( IFERROR((J58*(1-BE58))*BI58,0))) -> 0 | BK58: {=IF(A58="","",( IFERROR((J58*(1-BE58))*BI58/INDEX(er!D:D, MATCH(Q58,er!C:C,0),1),0)))} -> 0 | BL58: {=IFERROR(INDEX('Com&tax'!$G$2:$G$5, MATCH(1, ('Com&tax'!$A$2:$A$5=B58)*('Com&tax'!$B$2:$B$5=Y58), 0)),0)} -> 0 | BM58: =IF(A58="","",( IFERROR((J58*(1-BE58))*BL58,0))) -> 0 | BN58: {=IF(A58="","",( IFERROR((J58*(1-BE58))*BL58/INDEX(er!D:D, MATCH(Q58,er!C:C,0),1),0)))} -> 0 | BO58: {=IFERROR(INDEX('Com&tax'!$H$2:$H$5, MATCH(1, ('Com&tax'!$A$2:$A$5=B58)*('Com&tax'!$B$2:$B$5=Y58), 0)),0)} -> 0 | BP58: =IF(A58="","",( IFERROR(J58*BO58,0))) -> 0 | BQ58: {=IF(A58="","",( IFERROR(J58*BO58/INDEX(er!D:D, MATCH(Q58,er!C:C,0),1),0)))} -> 0 | BR58: {=IFERROR(INDEX('Com&tax'!$F$2:$F$5, MATCH(1, ('Com&tax'!$A$2:$A$5=B58)*('Com&tax'!$D$2:$D$5=H58), 0)),0)} -> 0.049 | BS58: =IF(A58="","",( IFERROR((J58*(1-BE58))*BR58,0))) -> 111168.01 | BT58: {=IF(A58="","",( IFERROR((J58*(1-BE58))*BR58/INDEX(er!D:D, MATCH(Q58,er!C:C,0),1),0)))} -> 111168.01 | BU58: {=IFERROR(INDEX('Com&tax'!$G$2:$G$5, MATCH(1, ('Com&tax'!$A$2:$A$5=B58)*('Com&tax'!$D$2:$D$5=H58), 0)),0)} -> 0.1575 | BV58: =IF(A58="","",( IFERROR((J58*(1-BE58))*BU58,0))) -> 357325.76 | BW58: {=IF(A58="","",( IFERROR((J58*(1-BE58))*BU58/INDEX(er!D:D, MATCH(Q58,er!C:C,0),1),0)))} -> 357325.76 | BX58: {=IFERROR(INDEX('Com&tax'!$H$2:$H$5, MATCH(1, ('Com&tax'!$A$2:$A$5=B58)*('Com&tax'!$D$2:$D$5=H58), 0)),0)} -> 0.07 | BY58: =IF(A58="","",( IFERROR(J58*BX58,0))) -> 186837 | BZ58: {=IF(A58="","",( IFERROR(J58*BX58/INDEX(er!D:D, MATCH(Q58,er!C:C,0),1),0)))} -> 186837 | CA58: {=IF(A58="","",( IFERROR(1-((P58/ INDEX(er!$D$3:$D$75,MATCH(1, (er!$A$3:$A$75=$BG$2)*(er!$C$3:$C$75=Q58), 0)) / (J58/ INDEX(er!$D$3:$D$75,MATCH(1, (er!$A$3:$A$75=$BG$2)*(er!$C$3:$C$75=L58), 0))))),"")))} -> 0.40629986 | CB58: =IF(AB58="","",1-AD58/AB58) -> 0.15 | CC58: =IF(AND(CA58="", CB58=""), "", CA58-CB58) -> 0.25629986 | CD58: =BJ58+BM58-BS58-BV58 -> -468493.78 | CE58: =BK58+BN58-BT58-BW58 -> -468493.78 | CF58: =AJ58-CE58 -> 468164.4 | CG58: =IF(OR(BE58="", AE58=""), "Miss", IF(ABS(AE58/100-AK58)<0.005, "OK", "Incorrect")) -> Incorrect | CI58: OK. Diff. Bill. / Adv. Country | CK58: 0 | CL58: =(AI58+CK58)/INDEX(er!D:D,MATCH(AC58,er!C:C,0),1) -> -329.38 | CN58: =CK58/INDEX(er!D:D,MATCH(AC58,er!C:C,0),1) -> 0
A59: T3237879 | B59: Twitter Rep | C59: IMS | D59: AR_Media Company_CIA INDUSTRIAL CERVECERA S A_AR00402663-CCU-Schneider Remix Limón-Feb 26 | G59: Argentina | H59: Aleph Argentina | I59: Argentina | J59: 5000000 | K59: 5000000 | L59: ARS | M59: 5000000 | N59: ARS | O59: 5000000 | P59: 3022375.2 | Q59: ARS | R59: Mexico | U59: 0 | V59: 2026-02 | W59: February/2026 | X59: IMS | Y59: Argentina | Z59: Mexico | AA59: ARS | AB59: 5000000 | AC59: ARS | AD59: 3022375 | AE59: 39.55 | AF59: OK | AG59: 0 | AH59: 0 | AI59: 0.2 | AJ59: 0 | AK59: 0.39552496 | AL59: OK | AM59: 10573631 | AO59: Miss | AP59: Miss | AR59: Miss | AT59: Miss | AU59: 5000000 | AV59: 3577 | AW59: Miss | AX59: 5000000 | AY59: 3579.1 | AZ59: ARS | BA59: 3022375 | BB59: OK | BC59: 0.2 | BD59: 0 | BE59: {=IFERROR(INDEX('Com&tax'!$E$2:$E$5, MATCH(1, ('Com&tax'!$A$2:$A$5=B59)*('Com&tax'!$B$2:$B$5=G59), 0)),"")} -> 0.15 | BF59: =IF(A59="","",( IFERROR(O59*BE59,""))) -> 750000 | BG59: {=IF(A59="","",( IFERROR((O59/ INDEX(er!$D$3:$D$75,MATCH(1, (er!$A$3:$A$75=$BG$2)*(er!$C$3:$C$75=Q59), 0)))*BE59,"")))} -> 536.86471 | BH59: =IF(A59="","",( IF(B59="Snapchat Rep", IF(A59="","",(P59-BF59)),-BF59))) -> -750000 | BI59: {=IFERROR(INDEX('Com&tax'!$F$2:$F$5, MATCH(1, ('Com&tax'!$A$2:$A$5=B59)*('Com&tax'!$B$2:$B$5=Y59), 0)),0)} -> 0.049 | BJ59: =IF(A59="","",( IFERROR((J59*(1-BE59))*BI59,0))) -> 208250 | BK59: {=IF(A59="","",( IFERROR((J59*(1-BE59))*BI59/INDEX(er!D:D, MATCH(Q59,er!C:C,0),1),0)))} -> 149.06943 | BL59: {=IFERROR(INDEX('Com&tax'!$G$2:$G$5, MATCH(1, ('Com&tax'!$A$2:$A$5=B59)*('Com&tax'!$B$2:$B$5=Y59), 0)),0)} -> 0.1575 | BM59: =IF(A59="","",( IFERROR((J59*(1-BE59))*BL59,0))) -> 669375 | BN59: {=IF(A59="","",( IFERROR((J59*(1-BE59))*BL59/INDEX(er!D:D, MATCH(Q59,er!C:C,0),1),0)))} -> 479.15175 | BO59: {=IFERROR(INDEX('Com&tax'!$H$2:$H$5, MATCH(1, ('Com&tax'!$A$2:$A$5=B59)*('Com&tax'!$B$2:$B$5=Y59), 0)),0)} -> 0.07 | BP59: =IF(A59="","",( IFERROR(J59*BO59,0))) -> 350000 | BQ59: {=IF(A59="","",( IFERROR(J59*BO59/INDEX(er!D:D, MATCH(Q59,er!C:C,0),1),0)))} -> 250.53686 | BR59: {=IFERROR(INDEX('Com&tax'!$F$2:$F$5, MATCH(1, ('Com&tax'!$A$2:$A$5=B59)*('Com&tax'!$D$2:$D$5=H59), 0)),0)} -> 0.049 | BS59: =IF(A59="","",( IFERROR((J59*(1-BE59))*BR59,0))) -> 208250 | BT59: {=IF(A59="","",( IFERROR((J59*(1-BE59))*BR59/INDEX(er!D:D, MATCH(Q59,er!C:C,0),1),0)))} -> 149.06943 | BU59: {=IFERROR(INDEX('Com&tax'!$G$2:$G$5, MATCH(1, ('Com&tax'!$A$2:$A$5=B59)*('Com&tax'!$D$2:$D$5=H59), 0)),0)} -> 0.1575 | BV59: =IF(A59="","",( IFERROR((J59*(1-BE59))*BU59,0))) -> 669375 | BW59: {=IF(A59="","",( IFERROR((J59*(1-BE59))*BU59/INDEX(er!D:D, MATCH(Q59,er!C:C,0),1),0)))} -> 479.15175 | BX59: {=IFERROR(INDEX('Com&tax'!$H$2:$H$5, MATCH(1, ('Com&tax'!$A$2:$A$5=B59)*('Com&tax'!$D$2:$D$5=H59), 0)),0)} -> 0.07 | BY59: =IF(A59="","",( IFERROR(J59*BX59,0))) -> 350000 | BZ59: {=IF(A59="","",( IFERROR(J59*BX59/INDEX(er!D:D, MATCH(Q59,er!C:C,0),1),0)))} -> 250.53686 | CA59: {=IF(A59="","",( IFERROR(1-((P59/ INDEX(er!$D$3:$D$75,MATCH(1, (er!$A$3:$A$75=$BG$2)*(er!$C$3:$C$75=Q59), 0)) / (J59/ INDEX(er!$D$3:$D$75,MATCH(1, (er!$A$3:$A$75=$BG$2)*(er!$C$3:$C$75=L59), 0))))),"")))} -> 0.39552496 | CB59: =IF(AB59="","",1-AD59/AB59) -> 0.395525 | CC59: =IF(AND(CA59="", CB59=""), "", CA59-CB59) -> -4e-08 | CD59: =BJ59+BM59-BS59-BV59 -> 0 | CE59: =BK59+BN59-BT59-BW59 -> 0 | CF59: =AJ59-CE59 -> 0 | CG59: =IF(OR(BE59="", AE59=""), "Miss", IF(ABS(AE59/100-AK59)<0.005, "OK", "Incorrect")) -> OK | CI59: OK | CK59: 0 | CL59: =(AI59+CK59)/INDEX(er!D:D,MATCH(AC59,er!C:C,0),1) -> 0.00014316392 | CN59: =CK59/INDEX(er!D:D,MATCH(AC59,er!C:C,0),1) -> 0
A60: T3238173 | B60: Twitter Rep | C60: IMS | D60: AR_Media Company_Telecom Argentina SA Argentina_AR00403015 | X | FLOW | Contenidos - LLQLL - Reserva - Feb 26 | E60: SO Exported to ERP | G60: Argentina | H60: Aleph Argentina | I60: Argentina | J60: 4884766 | K60: 4884766 | L60: ARS | M60: 4884766 | N60: ARS | O60: 4884766 | P60: 2952719.1 | Q60: ARS | R60: Mexico | U60: 0 | V60: 2026-02 | W60: February/2026 | X60: IMS | Y60: Argentina | Z60: Mexico | AA60: ARS | AB60: 4884766 | AC60: ARS | AD60: 2952718.9 | AE60: 39.55 | AF60: OK | AG60: 0 | AH60: 0 | AI60: 0.19 | AJ60: 0 | AK60: 0.39552496 | AL60: OK | AM60: 10573673 | AO60: Miss | AP60: Miss | AR60: Miss | AT60: Miss | AU60: 4884766 | AV60: 3495 | AW60: Miss | AX60: 4884766 | AY60: 3496.61 | AZ60: ARS | BA60: 2952718.9 | BB60: OK | BC60: 0.19 | BD60: 0 | BE60: {=IFERROR(INDEX('Com&tax'!$E$2:$E$5, MATCH(1, ('Com&tax'!$A$2:$A$5=B60)*('Com&tax'!$B$2:$B$5=G60), 0)),"")} -> 0.15 | BF60: =IF(A60="","",( IFERROR(O60*BE60,""))) -> 732714.9 | BG60: {=IF(A60="","",( IFERROR((O60/ INDEX(er!$D$3:$D$75,MATCH(1, (er!$A$3:$A$75=$BG$2)*(er!$C$3:$C$75=Q60), 0)))*BE60,"")))} -> 524.4917 | BH60: =IF(A60="","",( IF(B60="Snapchat Rep", IF(A60="","",(P60-BF60)),-BF60))) -> -732714.9 | BI60: {=IFERROR(INDEX('Com&tax'!$F$2:$F$5, MATCH(1, ('Com&tax'!$A$2:$A$5=B60)*('Com&tax'!$B$2:$B$5=Y60), 0)),0)} -> 0.049 | BJ60: =IF(A60="","",( IFERROR((J60*(1-BE60))*BI60,0))) -> 203450.5 | BK60: {=IF(A60="","",( IFERROR((J60*(1-BE60))*BI60/INDEX(er!D:D, MATCH(Q60,er!C:C,0),1),0)))} -> 145.63386 | BL60: {=IFERROR(INDEX('Com&tax'!$G$2:$G$5, MATCH(1, ('Com&tax'!$A$2:$A$5=B60)*('Com&tax'!$B$2:$B$5=Y60), 0)),0)} -> 0.1575 | BM60: =IF(A60="","",( IFERROR((J60*(1-BE60))*BL60,0))) -> 653948.05 | BN60: {=IF(A60="","",( IFERROR((J60*(1-BE60))*BL60/INDEX(er!D:D, MATCH(Q60,er!C:C,0),1),0)))} -> 468.10884 | BO60: {=IFERROR(INDEX('Com&tax'!$H$2:$H$5, MATCH(1, ('Com&tax'!$A$2:$A$5=B60)*('Com&tax'!$B$2:$B$5=Y60), 0)),0)} -> 0.07 | BP60: =IF(A60="","",( IFERROR(J60*BO60,0))) -> 341933.62 | BQ60: {=IF(A60="","",( IFERROR(J60*BO60/INDEX(er!D:D, MATCH(Q60,er!C:C,0),1),0)))} -> 244.76279 | BR60: {=IFERROR(INDEX('Com&tax'!$F$2:$F$5, MATCH(1, ('Com&tax'!$A$2:$A$5=B60)*('Com&tax'!$D$2:$D$5=H60), 0)),0)} -> 0.049 | BS60: =IF(A60="","",( IFERROR((J60*(1-BE60))*BR60,0))) -> 203450.5 | BT60: {=IF(A60="","",( IFERROR((J60*(1-BE60))*BR60/INDEX(er!D:D, MATCH(Q60,er!C:C,0),1),0)))} -> 145.63386 | BU60: {=IFERROR(INDEX('Com&tax'!$G$2:$G$5, MATCH(1, ('Com&tax'!$A$2:$A$5=B60)*('Com&tax'!$D$2:$D$5=H60), 0)),0)} -> 0.1575 | BV60: =IF(A60="","",( IFERROR((J60*(1-BE60))*BU60,0))) -> 653948.05 | BW60: {=IF(A60="","",( IFERROR((J60*(1-BE60))*BU60/INDEX(er!D:D, MATCH(Q60,er!C:C,0),1),0)))} -> 468.10884 | BX60: {=IFERROR(INDEX('Com&tax'!$H$2:$H$5, MATCH(1, ('Com&tax'!$A$2:$A$5=B60)*('Com&tax'!$D$2:$D$5=H60), 0)),0)} -> 0.07 | BY60: =IF(A60="","",( IFERROR(J60*BX60,0))) -> 341933.62 | BZ60: {=IF(A60="","",( IFERROR(J60*BX60/INDEX(er!D:D, MATCH(Q60,er!C:C,0),1),0)))} -> 244.76279 | CA60: {=IF(A60="","",( IFERROR(1-((P60/ INDEX(er!$D$3:$D$75,MATCH(1, (er!$A$3:$A$75=$BG$2)*(er!$C$3:$C$75=Q60), 0)) / (J60/ INDEX(er!$D$3:$D$75,MATCH(1, (er!$A$3:$A$75=$BG$2)*(er!$C$3:$C$75=L60), 0))))),"")))} -> 0.39552496 | CB60: =IF(AB60="","",1-AD60/AB60) -> 0.395525 | CC60: =IF(AND(CA60="", CB60=""), "", CA60-CB60) -> -3.8896439e-08 | CD60: =BJ60+BM60-BS60-BV60 -> 0 | CE60: =BK60+BN60-BT60-BW60 -> 0 | CF60: =AJ60-CE60 -> 0 | CG60: =IF(OR(BE60="", AE60=""), "Miss", IF(ABS(AE60/100-AK60)<0.005, "OK", "Incorrect")) -> OK | CI60: OK | CK60: 0 | CL60: =(AI60+CK60)/INDEX(er!D:D,MATCH(AC60,er!C:C,0),1) -> 0.00013600573 | CN60: =CK60/INDEX(er!D:D,MATCH(AC60,er!C:C,0),1) -> 0
