Workbook

Sheet Pivot
B3: Etiquetas de fila | C3: Cuenta de Advertiser id | D3: Suma de Net amount (USD)
B4: OK | C4: 26 | D4: 89751.57 | E4: =+D4/D$7 -> 0.99704713
B5: n/a | C5: 1 | D5: 0.05 | E5: =+D5/D$7 -> 5.5544829e-07
B6: Less rev/cogs than partner report | C6: 1 | D6: 265.76 | E6: =+D6/D$7 -> 0.0029523188
B7: Total general | C7: 28 | D7: 90017.38

Sheet Summary
N1: More rev/cogs than partner report
B2: Criteo report | G2: Salesforce
A3: concatenate | B3: Advertiser ID | C3: Advertiser name | D3: Currency | E3: Suma de Net amount | F3: Net amount (USD) | G3: Status | H3: Cost | I3: Purchase Currency | J3: Revenue | K3: Billing currency | L3: Dif Report - SF | M3: DIF USD | N3: Comments | O3: COGS USD | P3: REV USD | Q3: MG
A4: =+B4&"-"&"February" -> 31764-February | B4: 31764 | C4: Sony Store PE | D4: USD | E4: 288.47 | F4: =E4/INDEX('ex rate'!C:C,MATCH(D4,'ex rate'!A:A,0),1) -> 288.47 | G4: =VLOOKUP(A4,Salesforce!$A:$L,12,0) -> Under Review | H4: =IFERROR(SUMIF(Salesforce!$A:$A,Summary!A4,Salesforce!$AN:$AN),0) -> 288.47 | I4: =VLOOKUP(A4,Salesforce!$A:$Z,26,0) -> USD | J4: =IFERROR(SUMIFS(Salesforce!$AM:$AM,Salesforce!$A:$A,Summary!A4,Salesforce!J:J,"<>"&"Supply Deal"),0) -> 288.47 | K4: =VLOOKUP(A4,Salesforce!$A:$Z,25,0) -> USD | L4: =+E4-H4 -> 0 | M4: =+L4/VLOOKUP(I4,'ex rate'!A:C,3,0) -> 0 | N4: OK | O4: =+E4/+VLOOKUP(D4,'ex rate'!A:C,3,0) -> 288.47 | P4: =J4/INDEX('ex rate'!C:C,MATCH(K4,'ex rate'!A:A,0),1) -> 288.47 | Q4: =(P4-O4)/P4 -> 0
A5: =+B5&"-"&"February" -> 98889-February | B5: 98889 | C5: Arajet PE | D5: USD | E5: 1497.88 | F5: =E5/INDEX('ex rate'!C:C,MATCH(D5,'ex rate'!A:A,0),1) -> 1497.88 | G5: =VLOOKUP(A5,Salesforce!$A:$L,12,0) -> Under Review | H5: =IFERROR(SUMIF(Salesforce!$A:$A,Summary!A5,Salesforce!$AN:$AN),0) -> 1497.88 | I5: =VLOOKUP(A5,Salesforce!$A:$Z,26,0) -> USD | J5: =IFERROR(SUMIFS(Salesforce!$AM:$AM,Salesforce!$A:$A,Summary!A5,Salesforce!J:J,"<>"&"Supply Deal"),0) -> 1497.88 | K5: =VLOOKUP(A5,Salesforce!$A:$Z,25,0) -> USD | L5: =+E5-H5 -> 0 | M5: =+L5/VLOOKUP(I5,'ex rate'!A:C,3,0) -> 0 | N5: OK | O5: =+E5/+VLOOKUP(D5,'ex rate'!A:C,3,0) -> 1497.88 | P5: =J5/INDEX('ex rate'!C:C,MATCH(K5,'ex rate'!A:A,0),1) -> 1497.88 | Q5: =(P5-O5)/P5 -> 0
A6: =+B6&"-"&"February" -> 114667-February | B6: 114667 | C6: UCSUR PE | D6: USD | E6: 16105.49 | F6: =E6/INDEX('ex rate'!C:C,MATCH(D6,'ex rate'!A:A,0),1) -> 16105.49 | G6: =VLOOKUP(A6,Salesforce!$A:$L,12,0) -> Under Review | H6: =IFERROR(SUMIF(Salesforce!$A:$A,Summary!A6,Salesforce!$AN:$AN),0) -> 16105.49 | I6: =VLOOKUP(A6,Salesforce!$A:$Z,26,0) -> USD | J6: =IFERROR(SUMIFS(Salesforce!$AM:$AM,Salesforce!$A:$A,Summary!A6,Salesforce!J:J,"<>"&"Supply Deal"),0) -> 16105.49 | K6: =VLOOKUP(A6,Salesforce!$A:$Z,25,0) -> USD | L6: =+E6-H6 -> 0 | M6: =+L6/VLOOKUP(I6,'ex rate'!A:C,3,0) -> 0 | N6: OK | O6: =+E6/+VLOOKUP(D6,'ex rate'!A:C,3,0) -> 16105.49 | P6: =J6/INDEX('ex rate'!C:C,MATCH(K6,'ex rate'!A:A,0),1) -> 16105.49 | Q6: =(P6-O6)/P6 -> 0
A7: =+B7&"-"&"February" -> 115210-February | B7: 115210 | C7: TIENDAS MASS PE | D7: USD | E7: 4027.45 | F7: =E7/INDEX('ex rate'!C:C,MATCH(D7,'ex rate'!A:A,0),1) -> 4027.45 | G7: =VLOOKUP(A7,Salesforce!$A:$L,12,0) -> Under Review | H7: =IFERROR(SUMIF(Salesforce!$A:$A,Summary!A7,Salesforce!$AN:$AN),0) -> 4027.45 | I7: =VLOOKUP(A7,Salesforce!$A:$Z,26,0) -> USD | J7: =IFERROR(SUMIFS(Salesforce!$AM:$AM,Salesforce!$A:$A,Summary!A7,Salesforce!J:J,"<>"&"Supply Deal"),0) -> 4027.45 | K7: =VLOOKUP(A7,Salesforce!$A:$Z,25,0) -> USD | L7: =+E7-H7 -> 0 | M7: =+L7/VLOOKUP(I7,'ex rate'!A:C,3,0) -> 0 | N7: OK | O7: =+E7/+VLOOKUP(D7,'ex rate'!A:C,3,0) -> 4027.45 | P7: =J7/INDEX('ex rate'!C:C,MATCH(K7,'ex rate'!A:A,0),1) -> 4027.45 | Q7: =(P7-O7)/P7 -> 0
A8: =+B8&"-"&"February" -> 116497-February | B8: 116497 | C8: PC FACTORY PE | D8: USD | E8: 1999.95 | F8: =E8/INDEX('ex rate'!C:C,MATCH(D8,'ex rate'!A:A,0),1) -> 1999.95 | G8: =VLOOKUP(A8,Salesforce!$A:$L,12,0) -> Under Review | H8: =IFERROR(SUMIF(Salesforce!$A:$A,Summary!A8,Salesforce!$AN:$AN),0) -> 1999.95 | I8: =VLOOKUP(A8,Salesforce!$A:$Z,26,0) -> USD | J8: =IFERROR(SUMIFS(Salesforce!$AM:$AM,Salesforce!$A:$A,Summary!A8,Salesforce!J:J,"<>"&"Supply Deal"),0) -> 1999.95 | K8: =VLOOKUP(A8,Salesforce!$A:$Z,25,0) -> USD | L8: =+E8-H8 -> 0 | M8: =+L8/VLOOKUP(I8,'ex rate'!A:C,3,0) -> 0 | N8: OK | O8: =+E8/+VLOOKUP(D8,'ex rate'!A:C,3,0) -> 1999.95 | P8: =J8/INDEX('ex rate'!C:C,MATCH(K8,'ex rate'!A:A,0),1) -> 1999.95 | Q8: =(P8-O8)/P8 -> 0
A9: =+B9&"-"&"February" -> 116982-February | B9: 116982 | C9: Financiera Oh PE | D9: USD | E9: 2398.79 | F9: =E9/INDEX('ex rate'!C:C,MATCH(D9,'ex rate'!A:A,0),1) -> 2398.79 | G9: =VLOOKUP(A9,Salesforce!$A:$L,12,0) -> Under Review | H9: =IFERROR(SUMIF(Salesforce!$A:$A,Summary!A9,Salesforce!$AN:$AN),0) -> 2398.79 | I9: =VLOOKUP(A9,Salesforce!$A:$Z,26,0) -> USD | J9: =IFERROR(SUMIFS(Salesforce!$AM:$AM,Salesforce!$A:$A,Summary!A9,Salesforce!J:J,"<>"&"Supply Deal"),0) -> 2398.79 | K9: =VLOOKUP(A9,Salesforce!$A:$Z,25,0) -> USD | L9: =+E9-H9 -> 0 | M9: =+L9/VLOOKUP(I9,'ex rate'!A:C,3,0) -> 0 | N9: OK | O9: =+E9/+VLOOKUP(D9,'ex rate'!A:C,3,0) -> 2398.79 | P9: =J9/INDEX('ex rate'!C:C,MATCH(K9,'ex rate'!A:A,0),1) -> 2398.79 | Q9: =(P9-O9)/P9 -> 0
A10: =+B10&"-"&"February" -> 117067-February | B10: 117067 | C10: APUESTA TOTAL PE | D10: USD | E10: 5184.83 | F10: =E10/INDEX('ex rate'!C:C,MATCH(D10,'ex rate'!A:A,0),1) -> 5184.83 | G10: =VLOOKUP(A10,Salesforce!$A:$L,12,0) -> Under Review | H10: =IFERROR(SUMIF(Salesforce!$A:$A,Summary!A10,Salesforce!$AN:$AN),0) -> 5184.83 | I10: =VLOOKUP(A10,Salesforce!$A:$Z,26,0) -> USD | J10: =IFERROR(SUMIFS(Salesforce!$AM:$AM,Salesforce!$A:$A,Summary!A10,Salesforce!J:J,"<>"&"Supply Deal"),0) -> 5184.83 | K10: =VLOOKUP(A10,Salesforce!$A:$Z,25,0) -> USD | L10: =+E10-H10 -> 0 | M10: =+L10/VLOOKUP(I10,'ex rate'!A:C,3,0) -> 0 | N10: OK | O10: =+E10/+VLOOKUP(D10,'ex rate'!A:C,3,0) -> 5184.83 | P10: =J10/INDEX('ex rate'!C:C,MATCH(K10,'ex rate'!A:A,0),1) -> 5184.83 | Q10: =(P10-O10)/P10 -> 0
A11: =+B11&"-"&"February" -> 118854-February | B11: 118854 | C11: Oncosalud PE | D11: USD | E11: 912.96 | F11: =E11/INDEX('ex rate'!C:C,MATCH(D11,'ex rate'!A:A,0),1) -> 912.96 | G11: =VLOOKUP(A11,Salesforce!$A:$L,12,0) -> Under Review | H11: =IFERROR(SUMIF(Salesforce!$A:$A,Summary!A11,Salesforce!$AN:$AN),0) -> 912.96 | I11: =VLOOKUP(A11,Salesforce!$A:$Z,26,0) -> USD | J11: =IFERROR(SUMIFS(Salesforce!$AM:$AM,Salesforce!$A:$A,Summary!A11,Salesforce!J:J,"<>"&"Supply Deal"),0) -> 912.96 | K11: =VLOOKUP(A11,Salesforce!$A:$Z,25,0) -> USD | L11: =+E11-H11 -> 0 | M11: =+L11/VLOOKUP(I11,'ex rate'!A:C,3,0) -> 0 | N11: OK | O11: =+E11/+VLOOKUP(D11,'ex rate'!A:C,3,0) -> 912.96 | P11: =J11/INDEX('ex rate'!C:C,MATCH(K11,'ex rate'!A:A,0),1) -> 912.96 | Q11: =(P11-O11)/P11 -> 0
A12: =+B12&"-"&"February" -> 119907-February | B12: 119907 | C12: SISE PE | D12: USD | E12: 8000 | F12: =E12/INDEX('ex rate'!C:C,MATCH(D12,'ex rate'!A:A,0),1) -> 8000 | G12: =VLOOKUP(A12,Salesforce!$A:$L,12,0) -> Under Review | H12: =IFERROR(SUMIF(Salesforce!$A:$A,Summary!A12,Salesforce!$AN:$AN),0) -> 8000 | I12: =VLOOKUP(A12,Salesforce!$A:$Z,26,0) -> USD | J12: =IFERROR(SUMIFS(Salesforce!$AM:$AM,Salesforce!$A:$A,Summary!A12,Salesforce!J:J,"<>"&"Supply Deal"),0) -> 8000 | K12: =VLOOKUP(A12,Salesforce!$A:$Z,25,0) -> USD | L12: =+E12-H12 -> 0 | M12: =+L12/VLOOKUP(I12,'ex rate'!A:C,3,0) -> 0 | N12: OK | O12: =+E12/+VLOOKUP(D12,'ex rate'!A:C,3,0) -> 8000 | P12: =J12/INDEX('ex rate'!C:C,MATCH(K12,'ex rate'!A:A,0),1) -> 8000 | Q12: =(P12-O12)/P12 -> 0
A13: =+B13&"-"&"February" -> 29652-February | B13: 29652 | C13: Interbank PE | D13: USD | E13: 998.79 | F13: =E13/INDEX('ex rate'!C:C,MATCH(D13,'ex rate'!A:A,0),1) -> 998.79 | G13: =VLOOKUP(A13,Salesforce!$A:$L,12,0) -> Under Review | H13: =IFERROR(SUMIF(Salesforce!$A:$A,Summary!A13,Salesforce!$AN:$AN),0) -> 998.79 | I13: =VLOOKUP(A13,Salesforce!$A:$Z,26,0) -> USD | J13: =IFERROR(SUMIFS(Salesforce!$AM:$AM,Salesforce!$A:$A,Summary!A13,Salesforce!J:J,"<>"&"Supply Deal"),0) -> 998.79 | K13: =VLOOKUP(A13,Salesforce!$A:$Z,25,0) -> USD | L13: =+E13-H13 -> 0 | M13: =+L13/VLOOKUP(I13,'ex rate'!A:C,3,0) -> 0 | N13: OK | O13: =+E13/+VLOOKUP(D13,'ex rate'!A:C,3,0) -> 998.79 | P13: =J13/INDEX('ex rate'!C:C,MATCH(K13,'ex rate'!A:A,0),1) -> 998.79 | Q13: =(P13-O13)/P13 -> 0
A14: =+B14&"-"&"February" -> 39798-February | B14: 39798 | C14: Promart PE | D14: USD | E14: 1173.05 | F14: =E14/INDEX('ex rate'!C:C,MATCH(D14,'ex rate'!A:A,0),1) -> 1173.05 | G14: =VLOOKUP(A14,Salesforce!$A:$L,12,0) -> Under Review | H14: =IFERROR(SUMIF(Salesforce!$A:$A,Summary!A14,Salesforce!$AN:$AN),0) -> 1173.05 | I14: =VLOOKUP(A14,Salesforce!$A:$Z,26,0) -> USD | J14: =IFERROR(SUMIFS(Salesforce!$AM:$AM,Salesforce!$A:$A,Summary!A14,Salesforce!J:J,"<>"&"Supply Deal"),0) -> 1173.05 | K14: =VLOOKUP(A14,Salesforce!$A:$Z,25,0) -> USD | L14: =+E14-H14 -> 0 | M14: =+L14/VLOOKUP(I14,'ex rate'!A:C,3,0) -> 0 | N14: OK | O14: =+E14/+VLOOKUP(D14,'ex rate'!A:C,3,0) -> 1173.05 | P14: =J14/INDEX('ex rate'!C:C,MATCH(K14,'ex rate'!A:A,0),1) -> 1173.05 | Q14: =(P14-O14)/P14 -> 0
A15: =+B15&"-"&"February" -> 41643-February | B15: 41643 | C15: Oechsle PE | D15: USD | E15: 2771.71 | F15: =E15/INDEX('ex rate'!C:C,MATCH(D15,'ex rate'!A:A,0),1) -> 2771.71 | G15: =VLOOKUP(A15,Salesforce!$A:$L,12,0) -> Under Review | H15: =IFERROR(SUMIF(Salesforce!$A:$A,Summary!A15,Salesforce!$AN:$AN),0) -> 2771.71 | I15: =VLOOKUP(A15,Salesforce!$A:$Z,26,0) -> USD | J15: =IFERROR(SUMIFS(Salesforce!$AM:$AM,Salesforce!$A:$A,Summary!A15,Salesforce!J:J,"<>"&"Supply Deal"),0) -> 2771.71 | K15: =VLOOKUP(A15,Salesforce!$A:$Z,25,0) -> USD | L15: =+E15-H15 -> 0 | M15: =+L15/VLOOKUP(I15,'ex rate'!A:C,3,0) -> 0 | N15: OK | O15: =+E15/+VLOOKUP(D15,'ex rate'!A:C,3,0) -> 2771.71 | P15: =J15/INDEX('ex rate'!C:C,MATCH(K15,'ex rate'!A:A,0),1) -> 2771.71 | Q15: =(P15-O15)/P15 -> 0
... A31: =+B31&"-"&"February" -> 120764-February | B31: 120764 | C31: Natura PE | D31: USD | E31: 265.76 | F31: =E31/INDEX('ex rate'!C:C,MATCH(D31,'ex rate'!A:A,0),1) -> 265.76 | G31: =VLOOKUP(A31,Salesforce!$A:$L,12,0) -> Under Review | H31: =IFERROR(SUMIF(Salesforce!$A:$A,Summary!A31,Salesforce!$AN:$AN),0) -> 225.896 | I31: =VLOOKUP(A31,Salesforce!$A:$Z,26,0) -> USD | J31: =IFERROR(SUMIFS(Salesforce!$AM:$AM,Salesforce!$A:$A,Summary!A31,Salesforce!J:J,"<>"&"Supply Deal"),0) -> 265.76 | K31: =VLOOKUP(A31,Salesforce!$A:$Z,25,0) -> USD | L31: =+E31-H31 -> 39.864 | M31: =+L31/VLOOKUP(I31,'ex rate'!A:C,3,0) -> 39.864 | N31: Less rev/cogs than partner report | O31: =+E31/+VLOOKUP(D31,'ex rate'!A:C,3,0) -> 265.76 | P31: =J31/INDEX('ex rate'!C:C,MATCH(K31,'ex rate'!A:A,0),1) -> 265.76 | Q31: =(P31-O31)/P31 -> 0

Sheet DEALS
A3: Salesforce Project Number | B3: Trade Deal | C3: Type of Line | D3: Suma de Net Budget Delivered (Billing Currency)
A4: 00240205 | C4: Standard | D4: 3699.53
A5: 00240223 | C5: Standard | D5: 2986.68
A6: 00246193 | C6: Standard | D6: 4773.92
A7: 00265916 | C7: Standard | D7: 1998.87
A8: 00270878 | C8: Standard | D8: 1800
A9: 00289572 | C9: Standard | D9: 16105.49
A10: 00295095 | C10: Standard | D10: 1999.95
A11: 00314444 | C11: Standard | D11: 912.96
A12: 00324209 | C12: Standard | D12: 9029.13
A13: 00324625 | C13: Standard | D13: 1027.45
A14: 00326928 | C14: Standard | D14: 999.97
A15: 00323897 | C15: Standard | D15: 8000
... A33: 00328627 | C33: Standard | D33: 7953137.5
A34: Total general | D34: 8041089.1

Sheet Salesforce
A1: 1 | B1: =+A1+1 -> 2 | C1: =+B1+1 -> 3 | D1: =+C1+1 -> 4 | E1: =+D1+1 -> 5 | F1: =+E1+1 -> 6 | G1: =+F1+1 -> 7 | H1: =+G1+1 -> 8 | I1: =+H1+1 -> 9 | ... BP1: =+BO1+1 -> 68
A2: Publisher PO ID | B2: Year | C2: Line Month | D2: Posting Period | E2: Finance Date | F2: Salesforce Project Number | G2: Line ID | H2: Project : Opportunity : Aleph Campaign ID | I2: Line Product Number | J2: Type of Line | K2: Status | L2: Order Line Status | M2: Company Name (Know as + Country) | N2: Company To Invoice Legal Name | O2: Vendor | P2: Product Business Unit | Q2: Reporting Country | R2: Billing Country | S2: Delivery Country | T2: Billing Entity | U2: Purchase Country | V2: Product | W2: Sales UOM | X2: Purchase UOM | Y2: Billing Currency | Z2: Purchase Currency | AA2: Publisher PO ID | AB2: Qualified Sales Quantity | AC2: Qualified Purchase Quantity | AD2: Gross Discounted | AE2: Gross Sales Price | AF2: Net Sales Price | AG2: Gross Purchase Price | AH2: Net Purchase Price | AI2: Client Discount | AJ2: Agency Commission | AK2: Delivered Sales Quantity | AL2: Delivered Purchase Quantity | AM2: Net Budget Delivered (Billing Currency) | AN2: Net Cost Delivered (Buying Currency) | AO2: Net Cost Delivered w/o Tax (Buying Curr) | AP2: Activation Exchange Rate | AQ2: Total Net Budget (Delivered) (converted) | AR2: Total Net Cost (Delivered) (converted) | AS2: Margin Delivered (Billing Currency) | AT2: Margin Amount (Delivered) | AU2: Margin Amount (Delivered) (converted) | AV2: Margin % (Delivered) | AW2: Sales Order Number | AX2: SO Status | AY2: Purchase Order Number | AZ2: PO Status | BA2: Invoice Description | BB2: Line Description | BC2: Purchase Entity | BD2: Billing Exchange Rate | BE2: Project Name | BF2: Company to invoice | BG2: Company To Invoice Tax Id | BH2: Sales Manager | BI2: Trade Deal | BJ2: Branding/Performance | BK2: Sales Channel | BL2: End Date | BM2: Project : Company to invoice : Payment condition | BN2: Branding/Performance | BO2: Sales Channel | BP2: Status | BQ2: Rev. Act. FX / Closing FX | BR2: COGS Act. FX / Closing FX | BS2: SO STATUS | BT2: PO STATUS
A3: =+AA3&"-"&C3 -> 73548-February | B3: 2026 | C3: February | D3: February/2026 | E3: 28/2/2026 | F3: 00270878 | G3: 802Uj00000ILwke | H3: PE00322629 | I3: 0004188108 | J3: Standard | K3: Activated | L3: Under Review | M3: JOINNUS SAC Peru | N3: JOINNUS SAC | O3: CRITEO CORP. United States of America | P3: Criteo | Q3: Peru | S3: GLOBAL | T3: Aleph Peru | U3: Mexico | V3: Dynamic Ads | W3: Auction / Budget | X3: Auction / Budget | Y3: USD | Z3: USD | AA3: 73548 | AB3: 1800 | AC3: 1800 | AD3: 1 | AE3: 1 | AF3: 1 | AG3: 0.91 | AH3: 1 | AI3: 0 | AK3: 1800 | AL3: 1800 | AM3: 1800 | AN3: 1800 | AO3: 1800 | AQ3: 18459.69 | AR3: 1800 | AS3: 0 | AT3: 0 | AU3: 0 | AV3: 0 | AW3: SOIPE-000006663 | AX3: SO Exported to ERP | AY3: POIME-000025299 | AZ3: PO Exported to ERP | BC3: Aleph Mexico | BD3: 1 | BE3: PE_JOINNUS_CRITEO_MAYO 2025 | BF3: JOINNUS SAC Peru | BG3: 20555387785 | BH3: Rodrigo Aldecoa | BJ3: Client Performance Driven (ROI) | BK3: Traditional (Local Team) | BL3: 28/2/2026 | BM3: 30 days | BP3: =INDEX(Summary!N:N,MATCH(A3,Summary!A:A,0),1) -> OK | BQ3: =AM3/INDEX('ex rate'!C:C,MATCH(Y3,'ex rate'!A:A,0),1) -> 1800 | BR3: =AO3/INDEX('ex rate'!C:C,MATCH(Z3,'ex rate'!A:A,0),1) -> 1800 | BS3: SO READY TO EXPORT | BT3: PO READY TO EXPORT
A4: =+AA4&"-"&C4 -> 116497-February | B4: 2026 | C4: February | D4: February/2026 | E4: 28/2/2026 | F4: 00295095 | G4: 802Uj00000IM33I | H4: PE00357033 | I4: 0004185982 | J4: Standard | K4: Activated | L4: Under Review | M4: PC Factory CHILE | N4: Media Analytics S.A.C. | O4: CRITEO CORP. United States of America | P4: Criteo | Q4: Peru | S4: GLOBAL | T4: Aleph Peru | U4: Mexico | V4: Dynamic Ads | W4: Auction / Budget | X4: Auction / Budget | Y4: USD | Z4: USD | AA4: 116497 | AB4: 1999.95 | AC4: 1999.95 | AD4: 1 | AE4: 1 | AF4: 1 | AG4: 0.85 | AH4: 1 | AI4: 0 | AK4: 1999.95 | AL4: 1999.95 | AM4: 1999.95 | AN4: 1999.95 | AO4: 1999.95 | AQ4: 15499.96 | AR4: 1999.95 | AS4: 0 | AT4: 0 | AU4: 0 | AV4: 0 | AW4: SOIPE-000008334 | AX4: SO Exported to ERP | AY4: POIME-000027193 | AZ4: PO Exported to ERP | BC4: Aleph Mexico | BD4: 1 | BE4: PE_CRITEO_PC FACTORY JULIO 2025 | BF4: Media Analytics Perú | BG4: 20606271744 | BH4: Rodrigo Aldecoa | BJ4: Client Performance Driven (ROI) | BK4: Traditional (Local Team) | BL4: 28/2/2026 | BM4: 30 days | BP4: =INDEX(Summary!N:N,MATCH(A4,Summary!A:A,0),1) -> OK | BQ4: =AM4/INDEX('ex rate'!C:C,MATCH(Y4,'ex rate'!A:A,0),1) -> 1999.95 | BR4: =AO4/INDEX('ex rate'!C:C,MATCH(Z4,'ex rate'!A:A,0),1) -> 1999.95 | BS4: SO READY TO EXPORT | BT4: PO READY TO EXPORT
A5: =+AA5&"-"&C5 -> 118854-February | B5: 2026 | C5: February | D5: February/2026 | E5: 28/2/2026 | F5: 00314444 | G5: 802Uj00000O9ALb | H5: PE00386377 | I5: 0004721846 | J5: Standard | K5: Activated | L5: Under Review | M5: ONCOSALUD S.A.C. | N5: Media Analytics S.A.C. | O5: CRITEO CORP. United States of America | P5: Criteo | Q5: Peru | S5: GLOBAL | T5: Aleph Peru | U5: Mexico | V5: Dynamic Ads | W5: Auction / Budget | X5: Auction / Budget | Y5: USD | Z5: USD | AA5: 118854 | AB5: 912.96 | AC5: 912.96 | AD5: 1 | AE5: 1 | AF5: 1 | AG5: 0.85 | AH5: 1 | AI5: 0 | AK5: 912.96 | AL5: 912.96 | AM5: 912.96 | AN5: 912.96 | AO5: 912.96 | AQ5: 3499.99 | AR5: 912.96 | AS5: 0 | AT5: 0 | AU5: 0 | AV5: 0 | AW5: SOIPE-000009862 | AX5: SO Exported to ERP | AY5: POIME-000030616 | AZ5: PO Exported to ERP | BC5: Aleph Mexico | BD5: 1 | BE5: Criteo_NOV25_Oncosalud PE | BF5: Media Analytics Perú | BG5: 20606271744 | BH5: Rodrigo Aldecoa | BJ5: Client Performance Driven (ROI) | BK5: Traditional (Local Team) | BL5: 28/2/2026 | BM5: 30 days | BP5: =INDEX(Summary!N:N,MATCH(A5,Summary!A:A,0),1) -> OK | BQ5: =AM5/INDEX('ex rate'!C:C,MATCH(Y5,'ex rate'!A:A,0),1) -> 912.96 | BR5: =AO5/INDEX('ex rate'!C:C,MATCH(Z5,'ex rate'!A:A,0),1) -> 912.96 | BS5: SO READY TO EXPORT | BT5: PO READY TO EXPORT
A6: =+AA6&"-"&C6 -> 115210-February | B6: 2026 | C6: February | D6: February/2026 | E6: 28/2/2026 | F6: 00324625 | G6: 802Uj00000PmHY2 | H6: PE00399888 | I6: 0004890443 | J6: Standard | K6: Activated | L6: Under Review | M6: COMPAÑIA HARD DISCOUNT S.A.C. | N6: COMPAÑIA HARD DISCOUNT S.A.C. | O6: CRITEO CORP. United States of America | P6: Criteo | Q6: Peru | S6: GLOBAL | T6: Aleph Peru | U6: Mexico | V6: Dynamic Ads | W6: Auction / Budget | X6: Auction / Budget | Y6: USD | Z6: USD | AA6: 115210 | AB6: 1027.45 | AC6: 1027.45 | AD6: 1 | AE6: 1 | AF6: 1 | AG6: 0.91 | AH6: 1 | AI6: 0 | AK6: 1027.45 | AL6: 1027.45 | AM6: 1027.45 | AN6: 1027.45 | AO6: 1027.45 | AQ6: 6000.1 | AR6: 1027.45 | AS6: 0 | AT6: 0 | AU6: 0 | AV6: 0 | AW6: SOIPE-000010175 | AX6: SO Exported to ERP | AY6: POIME-000032235 | AZ6: PO Exported to ERP | BC6: Aleph Mexico | BD6: 1 | BE6: PE_CRITEO_TIENDAS MASS_ENE 2026 | BF6: COMPAÑIA HARD DISCOUNT S.A.C. | BG6: 20608280333 | BH6: Rodrigo Aldecoa | BJ6: Client Performance Driven (ROI) | BK6: Traditional (Local Team) | BL6: 28/2/2026 | BM6: 30 days | BP6: =INDEX(Summary!N:N,MATCH(A6,Summary!A:A,0),1) -> OK | BQ6: =AM6/INDEX('ex rate'!C:C,MATCH(Y6,'ex rate'!A:A,0),1) -> 1027.45 | BR6: =AO6/INDEX('ex rate'!C:C,MATCH(Z6,'ex rate'!A:A,0),1) -> 1027.45 | BS6: SO READY TO EXPORT | BT6: PO READY TO EXPORT
A7: =+AA7&"-"&C7 -> 44368-February | B7: 2026 | C7: February | D7: February/2026 | E7: 28/2/2026 | F7: 00324209 | G7: 802Uj00000PrZr9 | H7: PE00398904 | I7: 0004892401 | J7: Standard | K7: Activated | L7: Under Review | M7: BCP Peru | N7: QUAL MEDIA S.A.C. | O7: CRITEO CORP. United States of America | P7: Criteo | Q7: Peru | S7: GLOBAL | T7: Aleph Peru | U7: Mexico | V7: Dynamic Ads | W7: Auction / Budget | X7: Auction / Budget | Y7: USD | Z7: USD | AA7: 44368 | AB7: 9029.13 | AC7: 9029.13 | AD7: 1 | AE7: 1 | AF7: 1 | AG7: 0.85 | AH7: 1 | AI7: 0 | AK7: 9029.13 | AL7: 9029.13 | AM7: 9029.13 | AN7: 9029.13 | AO7: 9029.13 | AQ7: 10968.49 | AR7: 9029.13 | AS7: 0 | AT7: 0 | AU7: 0 | AV7: 0 | AW7: SOIPE-000010171 | AX7: SO Exported to ERP | AY7: POIME-000032243 | AZ7: PO Exported to ERP | BC7: Aleph Mexico | BD7: 1 | BE7: PE - CRITEO - OMD - BCP - ENE - 2026 | BF7: QUAL MEDIA S.A.C., Peru | BG7: 20509867560 | BH7: Rodrigo Aldecoa | BJ7: Brand Objectives | BK7: Traditional (Local Team) | BL7: 28/2/2026 | BM7: 75 days | BP7: =INDEX(Summary!N:N,MATCH(A7,Summary!A:A,0),1) -> OK | BQ7: =AM7/INDEX('ex rate'!C:C,MATCH(Y7,'ex rate'!A:A,0),1) -> 9029.13 | BR7: =AO7/INDEX('ex rate'!C:C,MATCH(Z7,'ex rate'!A:A,0),1) -> 9029.13 | BS7: SO READY TO EXPORT | BT7: PO READY TO EXPORT
A8: =+AA8&"-"&C8 -> 120258-February | B8: 2026 | C8: February | D8: February/2026 | E8: 28/2/2026 | F8: 00326088 | G8: 802Um00000DRqRF | H8: PE00401676 | I8: 0004908031 | J8: Standard | K8: Activated | L8: Under Review | M8: Pepsico Perú | N8: QUAL MEDIA S.A.C. | O8: CRITEO CORP. United States of America | P8: Criteo | Q8: Peru | S8: GLOBAL | T8: Aleph Peru | U8: Mexico | V8: Dynamic Ads | W8: Auction / Budget | X8: Auction / Budget | Y8: USD | Z8: USD | AA8: 120258 | AB8: 2500 | AC8: 2500 | AD8: 1 | AE8: 1 | AF8: 1 | AG8: 0.85 | AH8: 1 | AI8: 0 | AK8: 2500 | AL8: 2500 | AM8: 2500 | AN8: 2500 | AO8: 2500 | AQ8: 2500 | AR8: 2500 | AS8: 0 | AT8: 0 | AU8: 0 | AV8: 0 | AW8: SOIPE-000010268 | AX8: SO Exported to ERP | AY8: POIME-000032884 | AZ8: PO Exported to ERP | BC8: Aleph Mexico | BD8: 1 | BE8: PE - CRITEO - OMD - PEPSICO - FEB & MAR - 2026 | BF8: QUAL MEDIA S.A.C., Peru | BG8: 20509867560 | BH8: Rodrigo Aldecoa | BJ8: Brand Objectives | BK8: Traditional (Local Team) | BL8: 28/2/2026 | BM8: 75 days | BP8: =INDEX(Summary!N:N,MATCH(A8,Summary!A:A,0),1) -> OK | BQ8: =AM8/INDEX('ex rate'!C:C,MATCH(Y8,'ex rate'!A:A,0),1) -> 2500 | BR8: =AO8/INDEX('ex rate'!C:C,MATCH(Z8,'ex rate'!A:A,0),1) -> 2500 | BS8: SO READY TO EXPORT | BT8: PO READY TO EXPORT
A9: =+AA9&"-"&C9 -> 110594-February | B9: 2026 | C9: February | D9: February/2026 | E9: 28/2/2026 | F9: 00326928 | G9: 802Um00000DePtm | H9: PE00403309 | I9: 0004917062 | J9: Standard | K9: Activated | L9: Under Review | M9: DIVEMOTOR Perú | N9: Media Analytics S.A.C. | O9: CRITEO CORP. United States of America | P9: Criteo | Q9: Peru | S9: GLOBAL | T9: Aleph Peru | U9: Mexico | V9: Dynamic Ads | W9: Auction / Budget | X9: Auction / Budget | Y9: USD | Z9: USD | AA9: 110594 | AB9: 999.97 | AC9: 999.97 | AD9: 1 | AE9: 1 | AF9: 1 | AG9: 0.85 | AH9: 1 | AI9: 0 | AK9: 999.97 | AL9: 999.97 | AM9: 999.97 | AN9: 999.97 | AO9: 999.97 | AQ9: 1999.97 | AR9: 999.97 | AS9: 0 | AT9: 0 | AU9: 0 | AV9: 0 | AW9: SOIPE-000010176 | AX9: SO Exported to ERP | AY9: POIME-000032240 | AZ9: PO Exported to ERP | BC9: Aleph Mexico | BD9: 1 | BE9: PE_CRITEO_DIVEMOTOR ENE 2026 | BF9: Media Analytics Perú | BG9: 20606271744 | BH9: Rodrigo Aldecoa | BJ9: Client Performance Driven (ROI) | BK9: Traditional (Local Team) | BL9: 28/2/2026 | BM9: 30 days | BP9: =INDEX(Summary!N:N,MATCH(A9,Summary!A:A,0),1) -> OK | BQ9: =AM9/INDEX('ex rate'!C:C,MATCH(Y9,'ex rate'!A:A,0),1) -> 999.97 | BR9: =AO9/INDEX('ex rate'!C:C,MATCH(Z9,'ex rate'!A:A,0),1) -> 999.97 | BS9: SO READY TO EXPORT | BT9: PO READY TO EXPORT
A10: =+AA10&"-"&C10 -> 63589-February | B10: 2026 | C10: February | D10: February/2026 | E10: 28/2/2026 | F10: 00327579 | G10: 802Um00000Dlouj | H10: PE00392766 | I10: 0004938057 | J10: Standard | K10: Activated | L10: Under Review | M10: ESTILOS S.R.L. Peru | N10: ESTILOS S.R.L. | O10: CRITEO CORP. United States of America | P10: Criteo | Q10: Peru | S10: GLOBAL | T10: Aleph Peru | U10: Mexico | V10: Dynamic Ads | W10: Auction / Budget | X10: Auction / Budget | Y10: USD | Z10: USD | AA10: 63589 | AB10: 2991.08 | AC10: 2991.08 | AD10: 1 | AE10: 1 | AF10: 1 | AG10: 0.85 | AH10: 1 | AI10: 0 | AK10: 2991.08 | AL10: 2991.08 | AM10: 2991.08 | AN10: 2991.08 | AO10: 2991.08 | AQ10: 2991.08 | AR10: 2991.08 | AS10: 0 | AT10: 0 | AU10: 0 | AV10: 0 | AW10: SOIPE-000010270 | AX10: SO Exported to ERP | AY10: POIME-000032891 | AZ10: PO Exported to ERP | BC10: Aleph Mexico | BD10: 1 | BE10: PE_CRITEO_ESTILOS_FEB 2026 PIPE | BF10: ESTILOS S.R.L. Peru | BG10: 20100199158 | BH10: Rodrigo Aldecoa | BJ10: Client Performance Driven (ROI) | BK10: Traditional (Local Team) | BL10: 28/2/2026 | BM10: 30 days | BP10: =INDEX(Summary!N:N,MATCH(A10,Summary!A:A,0),1) -> OK | BQ10: =AM10/INDEX('ex rate'!C:C,MATCH(Y10,'ex rate'!A:A,0),1) -> 2991.08 | BR10: =AO10/INDEX('ex rate'!C:C,MATCH(Z10,'ex rate'!A:A,0),1) -> 2991.08 | BS10: SO READY TO EXPORT | BT10: PO READY TO EXPORT
A11: =+AA11&"-"&C11 -> 116982-February | B11: 2026 | C11: February | D11: February/2026 | E11: 28/2/2026 | F11: 00327580 | G11: 802Um00000Dlp61 | H11: PE00392769 | I11: 0004938058 | J11: Standard | K11: Activated | L11: Under Review | M11: Financiera Oh SA Perú | N11: Financiera Oh SA | O11: CRITEO CORP. United States of America | P11: Criteo | Q11: Peru | S11: GLOBAL | T11: Aleph Peru | U11: Mexico | V11: Dynamic Ads | W11: Auction / Budget | X11: Auction / Budget | Y11: USD | Z11: USD | AA11: 116982 | AB11: 2398.79 | AC11: 2398.79 | AD11: 1 | AE11: 1 | AF11: 1 | AG11: 0.85 | AH11: 1 | AI11: 0 | AK11: 2398.79 | AL11: 2398.79 | AM11: 2398.79 | AN11: 2398.79 | AO11: 2398.79 | AQ11: 2398.79 | AR11: 2398.79 | AS11: 0 | AT11: 0 | AU11: 0 | AV11: 0 | AW11: SOIPE-000010269 | AX11: SO Exported to ERP | AY11: POIME-000032895 | AZ11: PO Exported to ERP | BC11: Aleph Mexico | BD11: 1 | BE11: CRITEO_PE_FINANCIERA OH-FEB-2026 | BF11: Financiera Oh SA Perú | BG11: 20522291201 | BH11: Rodrigo Aldecoa | BJ11: Brand Objectives | BK11: Traditional (Local Team) | BL11: 28/2/2026 | BM11: 30 days | BP11: =INDEX(Summary!N:N,MATCH(A11,Summary!A:A,0),1) -> OK | BQ11: =AM11/INDEX('ex rate'!C:C,MATCH(Y11,'ex rate'!A:A,0),1) -> 2398.79 | BR11: =AO11/INDEX('ex rate'!C:C,MATCH(Z11,'ex rate'!A:A,0),1) -> 2398.79 | BS11: SO READY TO EXPORT | BT11: PO READY TO EXPORT
A12: =+AA12&"-"&C12 -> 94854-February | B12: 2026 | C12: February | D12: February/2026 | E12: 28/2/2026 | F12: 00327581 | G12: 802Um00000DlpFh | H12: PE00392772 | I12: 0004938061 | J12: Standard | K12: Activated | L12: Under Review | M12: IMPORTACIONES HIRAOKA S.A.C | N12: IMPORTACIONES HIRAOKA S.A.C | O12: CRITEO CORP. United States of America | P12: Criteo | Q12: Peru | S12: GLOBAL | T12: Aleph Peru | U12: Mexico | V12: Dynamic Ads | W12: Auction / Budget | X12: Auction / Budget | Y12: USD | Z12: USD | AA12: 94854 | AB12: 2019.13 | AC12: 2019.13 | AD12: 1 | AE12: 1 | AF12: 1 | AG12: 0.85 | AH12: 1 | AI12: 0 | AK12: 2019.13 | AL12: 2019.13 | AM12: 2019.13 | AN12: 2019.13 | AO12: 2019.13 | AQ12: 2019.13 | AR12: 2019.13 | AS12: 0 | AT12: 0 | AU12: 0 | AV12: 0 | AW12: SOIPE-000010266 | AX12: SO Exported to ERP | AY12: POIME-000032893 | AZ12: PO Exported to ERP | BC12: Aleph Mexico | BD12: 1 | BE12: Criteo_FEB.2026_Hiraoka | BF12: IMPORTACIONES HIRAOKA S.A.C | BG12: 20100016681 | BH12: Rodrigo Aldecoa | BJ12: Client Performance Driven (ROI) | BK12: Traditional (Local Team) | BL12: 28/2/2026 | BM12: 30 days | BP12: =INDEX(Summary!N:N,MATCH(A12,Summary!A:A,0),1) -> OK | BQ12: =AM12/INDEX('ex rate'!C:C,MATCH(Y12,'ex rate'!A:A,0),1) -> 2019.13 | BR12: =AO12/INDEX('ex rate'!C:C,MATCH(Z12,'ex rate'!A:A,0),1) -> 2019.13 | BS12: SO READY TO EXPORT | BT12: PO READY TO EXPORT
A13: =+AA13&"-"&C13 -> 29652-February | B13: 2026 | C13: February | D13: February/2026 | E13: 28/2/2026 | F13: 00327582 | G13: 802Um00000DlpXR | H13: PE00392775 | I13: 0004938062 | J13: Standard | K13: Activated | L13: Under Review | M13: BANCO INTERNACIONAL DEL PERU (Interbank) | N13: BANCO INTERNACIONAL DEL PERU (Interbank) | O13: CRITEO CORP. United States of America | P13: Criteo | Q13: Peru | S13: GLOBAL | T13: Aleph Peru | U13: Mexico | V13: Dynamic Ads | W13: Auction / Budget | X13: Auction / Budget | Y13: USD | Z13: USD | AA13: 29652 | AB13: 998.79 | AC13: 998.79 | AD13: 1 | AE13: 1 | AF13: 1 | AG13: 0.85 | AH13: 1 | AI13: 0 | AK13: 998.79 | AL13: 998.79 | AM13: 998.79 | AN13: 998.79 | AO13: 998.79 | AQ13: 998.79 | AR13: 998.79 | AS13: 0 | AT13: 0 | AU13: 0 | AV13: 0 | AW13: SOIPE-000010265 | AX13: SO Exported to ERP | AY13: POIME-000032897 | AZ13: PO Exported to ERP | BC13: Aleph Mexico | BD13: 1 | BE13: PE_CRITEO_INTERBANK_FEB 2026 PIPE | BF13: BANCO INTERNACIONAL DEL PERU (Interbank) | BG13: 20100053455 | BH13: Rodrigo Aldecoa | BJ13: Client Performance Driven (ROI) | BK13: Traditional (Local Team) | BL13: 28/2/2026 | BM13: 30 days | BP13: =INDEX(Summary!N:N,MATCH(A13,Summary!A:A,0),1) -> OK | BQ13: =AM13/INDEX('ex rate'!C:C,MATCH(Y13,'ex rate'!A:A,0),1) -> 998.79 | BR13: =AO13/INDEX('ex rate'!C:C,MATCH(Z13,'ex rate'!A:A,0),1) -> 998.79 | BS13: SO READY TO EXPORT | BT13: PO READY TO EXPORT
A14: =+AA14&"-"&C14 -> 39798-February | B14: 2026 | C14: February | D14: February/2026 | E14: 28/2/2026 | F14: 00327584 | G14: 802Um00000DlqQH | H14: PE00392790 | I14: 0004938065 | J14: Standard | K14: Activated | L14: Under Review | M14: HOMECENTERS PERUANOS S.A. | N14: HOMECENTERS PERUANOS S.A. | O14: CRITEO CORP. United States of America | P14: Criteo | Q14: Peru | S14: GLOBAL | T14: Aleph Peru | U14: Mexico | V14: Dynamic Ads | W14: Auction / Budget | X14: Auction / Budget | Y14: USD | Z14: USD | AA14: 39798 | AB14: 993 | AC14: 993 | AD14: 1 | AE14: 1 | AF14: 1 | AG14: 0.85 | AH14: 1 | AI14: 0 | AK14: 993 | AL14: 993 | AM14: 993 | AN14: 993 | AO14: 993 | AQ14: 993 | AR14: 993 | AS14: 0 | AT14: 0 | AU14: 0 | AV14: 0 | AW14: SOIPE-000010277 | AX14: SO Exported to ERP | AY14: POIME-000032898 | AZ14: PO Exported to ERP | BC14: Aleph Mexico | BD14: 1 | BE14: PE_CRITEO_PROMART_2026_FE PIPE | BF14: HOMECENTERS PERUANOS S.A. | BG14: 20536557858 | BH14: Rodrigo Aldecoa | BJ14: Client Performance Driven (ROI) | BK14: Traditional (Local Team) | BL14: 28/2/2026 | BM14: 30 days | BP14: =INDEX(Summary!N:N,MATCH(A14,Summary!A:A,0),1) -> OK | BQ14: =AM14/INDEX('ex rate'!C:C,MATCH(Y14,'ex rate'!A:A,0),1) -> 993 | BR14: =AO14/INDEX('ex rate'!C:C,MATCH(Z14,'ex rate'!A:A,0),1) -> 993 | BS14: SO READY TO EXPORT | BT14: PO READY TO EXPORT
... A22: =+AA22&"-"&C22 -> 39798-February | B22: 2026 | C22: February | D22: February/2026 | E22: 28/2/2026 | F22: 00331503 | G22: 802Um00000EfsM9 | H22: PE00409589 | I22: 0004988972 | J22: Standard | K22: Activated | L22: Under Review | M22: HOMECENTERS PERUANOS S.A. | N22: HOMECENTERS PERUANOS S.A. | O22: CRITEO CORP. United States of America | P22: Criteo | Q22: Peru | S22: GLOBAL | T22: Aleph Peru | U22: Mexico | V22: Dynamic Ads | W22: Auction / Budget | X22: Auction / Budget | Y22: USD | Z22: USD | AA22: 39798 | AB22: 180.05 | AC22: 180.05 | AD22: 1 | AE22: 1 | AF22: 1 | AG22: 0.91 | AH22: 1 | AI22: 0 | AK22: 180.05 | AL22: 180.05 | AM22: 180.05 | AN22: 180.05 | AO22: 180.05 | AQ22: 180.05 | AR22: 180.05 | AS22: 0 | AT22: 0 | AU22: 0 | AV22: 0 | AW22: SOIPE-000010272 | AX22: SO Exported to ERP | AY22: POIME-000032934 | AZ22: PO Exported to ERP | BC22: Aleph Mexico | BD22: 1 | BE22: PE_CRITEO_PROMART_2026_FEB 2 | BF22: HOMECENTERS PERUANOS S.A. | BG22: 20536557858 | BH22: Rodrigo Aldecoa | BJ22: Client Performance Driven (ROI) | BK22: Traditional (Local Team) | BL22: 28/2/2026 | BM22: 30 days | BP22: =INDEX(Summary!N:N,MATCH(A22,Summary!A:A,0),1) -> OK | BQ22: =AM22/INDEX('ex rate'!C:C,MATCH(Y22,'ex rate'!A:A,0),1) -> 180.05 | BR22: =AO22/INDEX('ex rate'!C:C,MATCH(Z22,'ex rate'!A:A,0),1) -> 180.05 | BS22: SO READY TO EXPORT | BT22: PO READY TO EXPORT
A23: =+AA23&"-"&C23 -> 120764-February | B23: 2026 | C23: February | D23: March/2026 | E23: 31/3/2026 | F23: 00332895 | G23: 802Um00000EvhRZ | H23: PE00410816 | I23: 0005002605 | J23: Standard | K23: Pending Changes Approval Needed | L23: Under Review | M23: NATURA COSMETICOS S.A. Peru | N23: Especialidades Digitales Internacionales SAC | O23: CRITEO CORP. United States of America | P23: Criteo | Q23: Peru | S23: GLOBAL | T23: Aleph Peru | U23: Mexico | V23: Dynamic Ads | W23: Auction / Budget | X23: Auction / Budget | Y23: USD | Z23: USD | AA23: 120764 | AB23: 265.76 | AC23: 265.76 | AD23: 1 | AE23: 1 | AF23: 1 | AG23: 0.85 | AH23: 0.85 | AI23: 0 | AK23: 265.76 | AL23: 265.76 | AM23: 265.76 | AN23: 225.896 | AO23: 225.9 | AQ23: 265.76 | AR23: 225.896 | AS23: 39.864 | AT23: 39.864 | AU23: 39.864 | AV23: 0.15 | BC23: Aleph Mexico | BD23: 1 | BE23: PE - CRITEO - HAVAS - NATURA - FEB y MAR - 2026 | BF23: Especialidades Digitales Internacionales PERU | BG23: 20600995031 | BH23: Rodrigo Aldecoa | BJ23: Client Performance Driven (ROI) | BK23: Traditional (Local Team) | BL23: 28/2/2026 | BM23: 60 days | BP23: =INDEX(Summary!N:N,MATCH(A23,Summary!A:A,0),1) -> Less rev/cogs than partner report | BQ23: =AM23/INDEX('ex rate'!C:C,MATCH(Y23,'ex rate'!A:A,0),1) -> 265.76 | BR23: =AO23/INDEX('ex rate'!C:C,MATCH(Z23,'ex rate'!A:A,0),1) -> 225.9
A24: =+AA24&"-"&C24 -> 98889-February | B24: 2026 | C24: February | D24: February/2026 | E24: 28/2/2026 | F24: 00331315 | G24: 802Um00000EfEF8 | H24: AR00408210 | I24: 0004987349 | J24: Standard | K24: Activated | L24: Under Review | M24: Arajet Dominican Republic | N24: Arajet S.A. | O24: CRITEO CORP. United States of America | P24: Criteo | Q24: Argentina | S24: GLOBAL | T24: Aleph Spain | U24: Mexico | V24: Dynamic Ads | W24: Auction / Budget | X24: Auction / Budget | Y24: USD | Z24: USD | AA24: 98889 | AB24: 1497.88 | AC24: 1497.88 | AD24: 1 | AE24: 1 | AF24: 1 | AG24: 0.91 | AH24: 1 | AI24: 0 | AK24: 1497.88 | AL24: 1497.88 | AM24: 1497.88 | AN24: 1497.88 | AO24: 1497.88 | AQ24: 1497.88 | AR24: 1497.88 | AS24: 0 | AT24: 0 | AU24: 0 | AV24: 0 | AW24: SOIES-000001011 | AX24: SO Exported to ERP | AY24: POIME-000032930 | AZ24: PO Exported to ERP | BC24: Aleph Mexico | BD24: 1 | BE24: AR_CRITEO_ARAJET_FEB_2026 | BF24: Arajet Dominican Republic | BG24: 131094376 | BH24: Maria Candela Lirio | BJ24: Client Performance Driven (ROI) | BK24: Traditional (Local Team) | BL24: 28/2/2026 | BM24: 60 days | BP24: =INDEX(Summary!N:N,MATCH(A24,Summary!A:A,0),1) -> OK | BQ24: =AM24/INDEX('ex rate'!C:C,MATCH(Y24,'ex rate'!A:A,0),1) -> 1497.88 | BR24: =AO24/INDEX('ex rate'!C:C,MATCH(Z24,'ex rate'!A:A,0),1) -> 1497.88 | BS24: SO READY TO EXPORT | BT24: PO READY TO EXPORT
A25: =+AA25&"-"&C25 -> 99591-February | B25: 2026 | C25: February | D25: February/2026 | E25: 28/2/2026 | F25: 00265916 | G25: 802Uj00000ILzgz | H25: PE00314814 | I25: 0004184060 | J25: Standard | K25: Activated | L25: Under Review | M25: AP LATAM HOLDINGS, LLC United States of America | N25: AP LATAM HOLDINGS, LLC | O25: CRITEO CORP. United States of America | P25: Criteo | Q25: Peru | S25: GLOBAL | T25: Aleph USA | U25: Mexico | V25: Dynamic Ads | W25: Auction / Budget | X25: Auction / Budget | Y25: USD | Z25: USD | AA25: 99591 | AB25: 1998.87 | AC25: 1998.87 | AD25: 1 | AE25: 1 | AF25: 1 | AG25: 0.91 | AH25: 1 | AI25: 0 | AK25: 1998.87 | AL25: 1998.87 | AM25: 1998.87 | AN25: 1998.87 | AO25: 1998.87 | AQ25: 20501.04 | AR25: 1998.87 | AS25: 0 | AT25: 0 | AU25: 0 | AV25: 0 | AW25: SOIUS-000002116 | AX25: SO Exported to ERP | AY25: POIME-000021070 | AZ25: PO Exported to ERP | BC25: Aleph Mexico | BD25: 1 | BE25: PE_USMP_CRITEO_MAYO 2025 | BF25: AP LATAM HOLDINGS, LLC United States of America | BG25: 815181325 | BH25: Andrea Burga | BJ25: Client Performance Driven (ROI) | BK25: Traditional (Local Team) | BL25: 28/2/2026 | BM25: 30 days | BP25: =INDEX(Summary!N:N,MATCH(A25,Summary!A:A,0),1) -> OK | BQ25: =AM25/INDEX('ex rate'!C:C,MATCH(Y25,'ex rate'!A:A,0),1) -> 1998.87 | BR25: =AO25/INDEX('ex rate'!C:C,MATCH(Z25,'ex rate'!A:A,0),1) -> 1998.87 | BS25: SO READY TO EXPORT | BT25: PO READY TO EXPORT
A26: =+AA26&"-"&C26 -> 114667-February | B26: 2026 | C26: February | D26: February/2026 | E26: 28/2/2026 | F26: 00289572 | G26: 802Uj00000IM3Hb | H26: PE00349925 | I26: 0004186494 | J26: Standard | K26: Activated | L26: Under Review | M26: UNIVERSIDAD CIENTIFICA DEL SUR S.A.C. | N26: QUAL MEDIA S.A.C. | O26: CRITEO CORP. United States of America | P26: Criteo | Q26: Peru | S26: GLOBAL | T26: Aleph Peru | U26: Mexico | V26: Dynamic Ads | W26: Auction / Budget | X26: Auction / Budget | Y26: USD | Z26: USD | AA26: 114667 | AB26: 16105.49 | AC26: 16105.49 | AD26: 1 | AE26: 1 | AF26: 1 | AG26: 0.85 | AH26: 1 | AI26: 0 | AK26: 16105.49 | AL26: 16105.49 | AM26: 16105.49 | AN26: 16105.49 | AO26: 16105.49 | AQ26: 78847.45 | AR26: 16105.49 | AS26: 0 | AT26: 0 | AU26: 0 | AV26: 0 | AW26: SOIPE-000007234 | AX26: SO Exported to ERP | AY26: POIME-000026121 | AZ26: PO Exported to ERP | BC26: Aleph Mexico | BD26: 1 | BE26: PE_CRITEO_UCSUR_JUNIO 2025 | BF26: QUAL MEDIA S.A.C., Peru | BG26: 20509867560 | BH26: Andrea Burga | BJ26: Client Performance Driven (ROI) | BK26: Traditional (Local Team) | BL26: 28/2/2026 | BM26: 75 days | BP26: =INDEX(Summary!N:N,MATCH(A26,Summary!A:A,0),1) -> OK | BQ26: =AM26/INDEX('ex rate'!C:C,MATCH(Y26,'ex rate'!A:A,0),1) -> 16105.49 | BR26: =AO26/INDEX('ex rate'!C:C,MATCH(Z26,'ex rate'!A:A,0),1) -> 16105.49 | BS26: SO READY TO EXPORT | BT26: PO READY TO EXPORT
A27: =+AA27&"-"&C27 -> 74346-February | B27: 2026 | C27: February | D27: February/2026 | E27: 28/2/2026 | F27: 00240205 | G27: 802Uj00000IM4K0 | H27: PE00276252 | I27: 0004188518 | J27: Standard | K27: Activated | L27: Under Review | M27: EL PACIFICO VIDA CIA DE SEGUROS Y REASEGUROS S.A. | N27: QUAL MEDIA S.A.C. | O27: CRITEO CORP. United States of America | P27: Criteo | Q27: Peru | S27: GLOBAL | T27: Aleph Peru | U27: Mexico | V27: Dynamic Ads | W27: Auction / Budget | X27: Auction / Budget | Y27: USD | Z27: USD | AA27: 74346 | AB27: 3699.53 | AC27: 3699.53 | AD27: 1 | AE27: 1 | AF27: 1 | AG27: 0.91 | AH27: 1 | AI27: 0 | AK27: 3699.53 | AL27: 3699.53 | AM27: 3699.53 | AN27: 3699.53 | AO27: 3699.53 | AQ27: 55543.41 | AR27: 3699.53 | AS27: 0 | AT27: 0 | AU27: 0 | AV27: 0 | AW27: SOIPE-000003644 | AX27: SO Exported to ERP | AY27: POIME-000016807 | AZ27: PO Exported to ERP | BC27: Aleph Mexico | BD27: 1 | BE27: PE_CRITEO_PACIFICO SEGUROS_2025_MAYO | BF27: QUAL MEDIA S.A.C., Peru | BG27: 20509867560 | BH27: Andrea Burga | BJ27: Client Performance Driven (ROI) | BK27: Traditional (Local Team) | BL27: 28/2/2026 | BM27: 75 days | BP27: =INDEX(Summary!N:N,MATCH(A27,Summary!A:A,0),1) -> OK | BQ27: =AM27/INDEX('ex rate'!C:C,MATCH(Y27,'ex rate'!A:A,0),1) -> 3699.53 | BR27: =AO27/INDEX('ex rate'!C:C,MATCH(Z27,'ex rate'!A:A,0),1) -> 3699.53 | BS27: SO READY TO EXPORT | BT27: PO READY TO EXPORT
A28: =+AA28&"-"&C28 -> 107799-February | B28: 2026 | C28: February | D28: February/2026 | E28: 28/2/2026 | F28: 00246193 | G28: 802Uj00000Jcyfu | H28: PE00287203 | I28: 0004248624 | J28: Standard | K28: Activated | L28: Under Review | M28: CONFEDERACION DE DESARROLLADORES INMOBILIARIOS DEL PERU- CODIPPeru | N28: CONFEDERACION DE DESARROLLADORES INMOBILIARIOS DEL PERU- CODIP | O28: CRITEO CORP. United States of America | P28: Criteo | Q28: Peru | S28: GLOBAL | T28: Aleph Peru | U28: Mexico | V28: Dynamic Ads | W28: Auction / Budget | X28: Auction / Budget | Y28: USD | Z28: USD | AA28: 107799 | AB28: 4773.92 | AC28: 4773.92 | AD28: 1 | AE28: 1 | AF28: 1 | AG28: 0.91 | AH28: 1 | AI28: 0 | AK28: 4773.92 | AL28: 4773.92 | AM28: 4773.92 | AN28: 4773.92 | AO28: 4773.92 | AQ28: 44372.9 | AR28: 4773.92 | AS28: 0 | AT28: 0 | AU28: 0 | AV28: 0 | AW28: SOIPE-000003676 | AX28: SO Exported to ERP | AY28: POIME-000019588 | AZ28: PO Exported to ERP | BB28: Factura Mayo | BC28: Aleph Mexico | BD28: 1 | BE28: PE_ASEI NEXO_CRITEO_ABRIL MAYO 2025 | BF28: CONFEDERACION DE DESARROLLADORES INMOBILIARIOS DEL PERU- CODIPPeru | BG28: 20552213832 | BH28: Andrea Burga | BJ28: Client Performance Driven (ROI) | BK28: Traditional (Local Team) | BL28: 28/2/2026 | BM28: 30 days | BP28: =INDEX(Summary!N:N,MATCH(A28,Summary!A:A,0),1) -> OK | BQ28: =AM28/INDEX('ex rate'!C:C,MATCH(Y28,'ex rate'!A:A,0),1) -> 4773.92 | BR28: =AO28/INDEX('ex rate'!C:C,MATCH(Z28,'ex rate'!A:A,0),1) -> 4773.92 | BS28: SO READY TO EXPORT | BT28: PO READY TO EXPORT
A29: =+AA29&"-"&C29 -> 103986-February | B29: 2026 | C29: February | D29: February/2026 | E29: 28/2/2026 | F29: 00240223 | G29: 802Uj00000OKEiZ | H29: PE00277713 | I29: 0004746208 | J29: Standard | K29: Activated | L29: Under Review | M29: NESSUS HOTELES PERU S.A. | N29: NESSUS HOTELES PERU S.A. | O29: CRITEO CORP. United States of America | P29: Criteo | Q29: Peru | S29: GLOBAL | T29: Aleph Peru | U29: Mexico | V29: Dynamic Ads | W29: Auction / Budget | X29: Auction / Budget | Y29: USD | Z29: USD | AA29: 103986 | AB29: 2986.68 | AC29: 2986.68 | AD29: 1 | AE29: 1 | AF29: 1 | AG29: 0.91 | AH29: 1 | AI29: 0 | AK29: 2986.68 | AL29: 2986.68 | AM29: 2986.68 | AN29: 2986.68 | AO29: 2986.68 | AQ29: 25322.44 | AR29: 2986.68 | AS29: 0 | AT29: 0 | AU29: 0 | AV29: 0 | AW29: SOIPE-000003641 | AX29: SO Exported to ERP | AY29: POIME-000018208 | AZ29: PO Exported to ERP | BC29: Aleph Mexico | BD29: 1 | BE29: PE_CRITEO_CASA ANDINA_2025_MAYO | BF29: NESSUS HOTELES PERU S.A. | BG29: 20505670443 | BH29: Andrea Burga | BJ29: Client Performance Driven (ROI) | BK29: Traditional (Local Team) | BL29: 28/2/2026 | BM29: 30 days | BP29: =INDEX(Summary!N:N,MATCH(A29,Summary!A:A,0),1) -> OK | BQ29: =AM29/INDEX('ex rate'!C:C,MATCH(Y29,'ex rate'!A:A,0),1) -> 2986.68 | BR29: =AO29/INDEX('ex rate'!C:C,MATCH(Z29,'ex rate'!A:A,0),1) -> 2986.68 | BS29: SO READY TO EXPORT | BT29: PO READY TO EXPORT
A30: =+AA30&"-"&C30 -> 119907-February | B30: 2026 | C30: February | D30: February/2026 | E30: 28/2/2026 | F30: 00323897 | G30: 802Um00000Djl0J | H30: PE00398043 | I30: 0004930416 | J30: Standard | K30: Activated | L30: Under Review | M30: SISE | N30: MEDIAWISE S.A.C | O30: CRITEO CORP. United States of America | P30: Criteo | Q30: Peru | S30: GLOBAL | T30: Aleph Peru | U30: Mexico | V30: Dynamic Ads | W30: Auction / Budget | X30: Auction / Budget | Y30: USD | Z30: USD | AA30: 119907 | AB30: 8000 | AC30: 8000 | AD30: 1 | AE30: 1 | AF30: 1 | AG30: 0.91 | AH30: 1 | AI30: 0 | AK30: 8000 | AL30: 8000 | AM30: 8000 | AN30: 8000 | AO30: 8000 | AQ30: 16823.87 | AR30: 8000 | AS30: 0 | AT30: 0 | AU30: 0 | AV30: 0 | AW30: SOIPE-000010173 | AX30: SO Exported to ERP | AY30: POIME-000032214 | AZ30: PO Exported to ERP | BC30: Aleph Mexico | BD30: 1 | BE30: PE_SISE_CRITEO_ENE_26 | BF30: MEDIAWISE S.A.C, Peru | BG30: 20550082722 | BH30: Andrea Burga | BJ30: Client Performance Driven (ROI) | BK30: Traditional (Local Team) | BL30: 28/2/2026 | BM30: 60 days | BP30: =INDEX(Summary!N:N,MATCH(A30,Summary!A:A,0),1) -> OK | BQ30: =AM30/INDEX('ex rate'!C:C,MATCH(Y30,'ex rate'!A:A,0),1) -> 8000 | BR30: =AO30/INDEX('ex rate'!C:C,MATCH(Z30,'ex rate'!A:A,0),1) -> 8000 | BS30: SO READY TO EXPORT | BT30: PO READY TO EXPORT
A31: =+AA31&"-"&C31 -> 31764-February | B31: 2026 | C31: February | D31: February/2026 | E31: 28/2/2026 | F31: 00327517 | G31: 802Um00000DkpJO | H31: CO00391696 | I31: 0004932626 | J31: Standard | K31: Activated | L31: Under Review | M31: SONY LATIN AMERICA INC. United States of America | N31: Group M Worldwide LLC DBA EssenceMediacom Miami | O31: CRITEO CORP. United States of America | P31: Criteo | Q31: Colombia | S31: GLOBAL | T31: Aleph USA | U31: Mexico | V31: Dynamic Ads | W31: Auction / Budget | X31: Auction / Budget | Y31: USD | Z31: USD | AA31: 31764 | AB31: 288.47 | AC31: 288.47 | AD31: 1 | AE31: 1 | AF31: 1 | AG31: 0.91 | AH31: 1 | AI31: 0 | AK31: 288.47 | AL31: 288.47 | AM31: 288.47 | AN31: 288.47 | AO31: 288.47 | AQ31: 288.47 | AR31: 288.47 | AS31: 0 | AT31: 0 | AU31: 0 | AV31: 0 | AW31: SOIUS-000002996 | AX31: SO Exported to ERP | AY31: POIME-000032887 | AZ31: PO Exported to ERP | BC31: Aleph Mexico | BD31: 1 | BE31: COL_CRITEO_MEDIACOM MIAMI_SONY ALON_FEBRERO 2026 | BF31: Group M Worldwide LLC DBA EssenceMediacom Miami | BG31: 204031493 | BH31: Paola Reina | BJ31: Client Performance Driven (ROI) | BK31: Traditional (Local Team) | BL31: 28/2/2026 | BM31: 30 days | BP31: =INDEX(Summary!N:N,MATCH(A31,Summary!A:A,0),1) -> OK | BQ31: =AM31/INDEX('ex rate'!C:C,MATCH(Y31,'ex rate'!A:A,0),1) -> 288.47 | BR31: =AO31/INDEX('ex rate'!C:C,MATCH(Z31,'ex rate'!A:A,0),1) -> 288.47 | BS31: SO READY TO EXPORT | BT31: PO READY TO EXPORT
A32: =+AA32&"-"&C32 -> 120332-February | B32: 2026 | C32: February | D32: February/2026 | E32: 28/2/2026 | F32: 00328627 | G32: 802Um00000E0KBZ | H32: CO00373095 | I32: 0004953815 | J32: Standard | K32: Activated | L32: Under Review | M32: Cueros Velez Colombia | N32: SISTEMAS COLOMBIA S A S | O32: CRITEO CORP. United States of America | P32: Criteo | Q32: Colombia | S32: GLOBAL | T32: Aleph Colombia | U32: Mexico | V32: Dynamic Ads | W32: Auction / Budget | X32: Auction / Budget | Y32: COP | Z32: USD | AA32: 120332 | AB32: 2065.75 | AC32: 2065.75 | AD32: 1 | AE32: 1 | AF32: 1 | AG32: 0.85 | AH32: 1 | AI32: 0 | AK32: 2065.75 | AL32: 2065.75 | AM32: 7953137.5 | AN32: 2065.75 | AO32: 2065.75 | AP32: 3850 | AQ32: 2065.75 | AR32: 2065.75 | AS32: 172903.27 | AT32: 0 | AU32: 0 | AV32: 0 | AW32: SOICO-000004001 | AX32: SO Exported to ERP | AY32: POIME-000032902 | AZ32: PO Exported to ERP | BC32: Aleph Mexico | BD32: 3766.3 | BE32: COL_CRITEO_ADBID_VELEZ PE_FEBRERO 2026 | BF32: SISTEMAS COLOMBIA COLOMBIA | BG32: 9002185787 | BH32: Paola Reina | BJ32: Client Performance Driven (ROI) | BK32: Traditional (Local Team) | BL32: 28/2/2026 | BM32: 60 days | BP32: =INDEX(Summary!N:N,MATCH(A32,Summary!A:A,0),1) -> OK | BQ32: =AM32/INDEX('ex rate'!C:C,MATCH(Y32,'ex rate'!A:A,0),1) -> 2111.658 | BR32: =AO32/INDEX('ex rate'!C:C,MATCH(Z32,'ex rate'!A:A,0),1) -> 2065.75 | BS32: SO READY TO EXPORT | BT32: PO READY TO EXPORT
A33: =+AA33&"-"&C33 -> 115741-February | B33: 2026 | C33: February | D33: February/2026 | E33: 28/2/2026 | F33: 00331315 | G33: 802Um00000EfEF3 | H33: AR00408210 | I33: 0004987344 | J33: Standard | K33: Activated | L33: Under Review | M33: Arajet Dominican Republic | N33: Arajet S.A. | O33: CRITEO CORP. United States of America | P33: Criteo | Q33: Argentina | S33: GLOBAL | T33: Aleph Spain | U33: Mexico | V33: Dynamic Ads | W33: Auction / Budget | X33: Auction / Budget | Y33: USD | Z33: USD | AA33: 115741 | AB33: 5499.38 | AC33: 5499.38 | AD33: 1 | AE33: 1 | AF33: 1 | AG33: 0.91 | AH33: 1 | AI33: 0 | AK33: 5499.38 | AL33: 5499.38 | AM33: 5499.38 | AN33: 5499.38 | AO33: 5499.38 | AQ33: 5499.38 | AR33: 5499.38 | AS33: 0 | AT33: 0 | AU33: 0 | AV33: 0 | AW33: SOIES-000001011 | AX33: SO Exported to ERP | AY33: POIME-000032930 | AZ33: PO Exported to ERP | BC33: Aleph Mexico | BD33: 1 | BE33: AR_CRITEO_ARAJET_FEB_2026 | BF33: Arajet Dominican Republic | BG33: 131094376 | BH33: Maria Candela Lirio | BJ33: Client Performance Driven (ROI) | BK33: Traditional (Local Team) | BL33: 28/2/2026 | BM33: 60 days | BP33: =INDEX(Summary!N:N,MATCH(A33,Summary!A:A,0),1) -> #N/A | BQ33: =AM33/INDEX('ex rate'!C:C,MATCH(Y33,'ex rate'!A:A,0),1) -> 5499.38 | BR33: =AO33/INDEX('ex rate'!C:C,MATCH(Z33,'ex rate'!A:A,0),1) -> 5499.38 | BS33: SO READY TO EXPORT | BT33: PO READY TO EXPORT
A34: =+AA34&"-"&C34 -> 98890-February | B34: 2026 | C34: February | D34: February/2026 | E34: 28/2/2026 | F34: 00331315 | G34: 802Um00000EfEF4 | H34: AR00408210 | I34: 0004987345 | J34: Standard | K34: Activated | L34: Under Review | M34: Arajet Dominican Republic | N34: Arajet S.A. | O34: CRITEO CORP. United States of America | P34: Criteo | Q34: Argentina | S34: GLOBAL | T34: Aleph Spain | U34: Mexico | V34: Dynamic Ads | W34: Auction / Budget | X34: Auction / Budget | Y34: USD | Z34: USD | AA34: 98890 | AB34: 5000 | AC34: 5000 | AD34: 1 | AE34: 1 | AF34: 1 | AG34: 0.91 | AH34: 1 | AI34: 0 | AK34: 5000 | AL34: 5000 | AM34: 5000 | AN34: 5000 | AO34: 5000 | AQ34: 5000 | AR34: 5000 | AS34: 0 | AT34: 0 | AU34: 0 | AV34: 0 | AW34: SOIES-000001011 | AX34: SO Exported to ERP | AY34: POIME-000032930 | AZ34: PO Exported to ERP | BC34: Aleph Mexico | BD34: 1 | BE34: AR_CRITEO_ARAJET_FEB_2026 | BF34: Arajet Dominican Republic | BG34: 131094376 | BH34: Maria Candela Lirio | BJ34: Client Performance Driven (ROI) | BK34: Traditional (Local Team) | BL34: 28/2/2026 | BM34: 60 days | BP34: =INDEX(Summary!N:N,MATCH(A34,Summary!A:A,0),1) -> #N/A | BQ34: =AM34/INDEX('ex rate'!C:C,MATCH(Y34,'ex rate'!A:A,0),1) -> 5000 | BR34: =AO34/INDEX('ex rate'!C:C,MATCH(Z34,'ex rate'!A:A,0),1) -> 5000 | BS34: SO READY TO EXPORT | BT34: PO READY TO EXPORT
A35: =+AA35&"-"&C35 -> 98888-February | B35: 2026 | C35: February | D35: February/2026 | E35: 28/2/2026 | F35: 00331315 | G35: 802Um00000EfEF5 | H35: AR00408210 | I35: 0004987346 | J35: Standard | K35: Activated | L35: Under Review | M35: Arajet Dominican Republic | N35: Arajet S.A. | O35: CRITEO CORP. United States of America | P35: Criteo | Q35: Argentina | S35: GLOBAL | T35: Aleph Spain | U35: Mexico | V35: Dynamic Ads | W35: Auction / Budget | X35: Auction / Budget | Y35: USD | Z35: USD | AA35: 98888 | AB35: 2988.6 | AC35: 2988.6 | AD35: 1 | AE35: 1 | AF35: 1 | AG35: 0.91 | AH35: 1 | AI35: 0 | AK35: 2988.6 | AL35: 2988.6 | AM35: 2988.6 | AN35: 2988.6 | AO35: 2988.6 | AQ35: 2988.6 | AR35: 2988.6 | AS35: 0 | AT35: 0 | AU35: 0 | AV35: 0 | AW35: SOIES-000001011 | AX35: SO Exported to ERP | AY35: POIME-000032930 | AZ35: PO Exported to ERP | BC35: Aleph Mexico | BD35: 1 | BE35: AR_CRITEO_ARAJET_FEB_2026 | BF35: Arajet Dominican Republic | BG35: 131094376 | BH35: Maria Candela Lirio | BJ35: Client Performance Driven (ROI) | BK35: Traditional (Local Team) | BL35: 28/2/2026 | BM35: 60 days | BP35: =INDEX(Summary!N:N,MATCH(A35,Summary!A:A,0),1) -> #N/A | BQ35: =AM35/INDEX('ex rate'!C:C,MATCH(Y35,'ex rate'!A:A,0),1) -> 2988.6 | BR35: =AO35/INDEX('ex rate'!C:C,MATCH(Z35,'ex rate'!A:A,0),1) -> 2988.6 | BS35: SO READY TO EXPORT | BT35: PO READY TO EXPORT
A36: =+AA36&"-"&C36 -> 118620-February | B36: 2026 | C36: February | D36: February/2026 | E36: 28/2/2026 | F36: 00331315 | G36: 802Um00000EfEF6 | H36: AR00408210 | I36: 0004987347 | J36: Standard | K36: Activated | L36: Under Review | M36: Arajet Dominican Republic | N36: Arajet S.A. | O36: CRITEO CORP. United States of America | P36: Criteo | Q36: Argentina | S36: GLOBAL | T36: Aleph Spain | U36: Mexico | V36: Dynamic Ads | W36: Auction / Budget | X36: Auction / Budget | Y36: USD | Z36: USD | AA36: 118620 | AB36: 3000 | AC36: 3000 | AD36: 1 | AE36: 1 | AF36: 1 | AG36: 0.85 | AH36: 1 | AI36: 0 | AK36: 3000 | AL36: 3000 | AM36: 3000 | AN36: 3000 | AO36: 3000 | AQ36: 3000 | AR36: 3000 | AS36: 0 | AT36: 0 | AU36: 0 | AV36: 0 | AW36: SOIES-000001011 | AX36: SO Exported to ERP | AY36: POIME-000032930 | AZ36: PO Exported to ERP | BC36: Aleph Mexico | BD36: 1 | BE36: AR_CRITEO_ARAJET_FEB_2026 | BF36: Arajet Dominican Republic | BG36: 131094376 | BH36: Maria Candela Lirio | BJ36: Client Performance Driven (ROI) | BK36: Traditional (Local Team) | BL36: 28/2/2026 | BM36: 60 days | BP36: =INDEX(Summary!N:N,MATCH(A36,Summary!A:A,0),1) -> #N/A | BQ36: =AM36/INDEX('ex rate'!C:C,MATCH(Y36,'ex rate'!A:A,0),1) -> 3000 | BR36: =AO36/INDEX('ex rate'!C:C,MATCH(Z36,'ex rate'!A:A,0),1) -> 3000 | BS36: SO READY TO EXPORT | BT36: PO READY TO EXPORT
A37: =+AA37&"-"&C37 -> 101280-February | B37: 2026 | C37: February | D37: February/2026 | E37: 28/2/2026 | F37: 00331315 | G37: 802Um00000EfEF7 | H37: AR00408210 | I37: 0004987348 | J37: Standard | K37: Activated | L37: Under Review | M37: Arajet Dominican Republic | N37: Arajet S.A. | O37: CRITEO CORP. United States of America | P37: Criteo | Q37: Argentina | S37: GLOBAL | T37: Aleph Spain | U37: Mexico | V37: Dynamic Ads | W37: Auction / Budget | X37: Auction / Budget | Y37: USD | Z37: USD | AA37: 101280 | AB37: 3000 | AC37: 3000 | AD37: 1 | AE37: 1 | AF37: 1 | AG37: 0.91 | AH37: 1 | AI37: 0 | AK37: 3000 | AL37: 3000 | AM37: 3000 | AN37: 3000 | AO37: 3000 | AQ37: 3000 | AR37: 3000 | AS37: 0 | AT37: 0 | AU37: 0 | AV37: 0 | AW37: SOIES-000001011 | AX37: SO Exported to ERP | AY37: POIME-000032930 | AZ37: PO Exported to ERP | BC37: Aleph Mexico | BD37: 1 | BE37: AR_CRITEO_ARAJET_FEB_2026 | BF37: Arajet Dominican Republic | BG37: 131094376 | BH37: Maria Candela Lirio | BJ37: Client Performance Driven (ROI) | BK37: Traditional (Local Team) | BL37: 28/2/2026 | BM37: 60 days | BP37: =INDEX(Summary!N:N,MATCH(A37,Summary!A:A,0),1) -> #N/A | BQ37: =AM37/INDEX('ex rate'!C:C,MATCH(Y37,'ex rate'!A:A,0),1) -> 3000 | BR37: =AO37/INDEX('ex rate'!C:C,MATCH(Z37,'ex rate'!A:A,0),1) -> 3000 | BS37: SO READY TO EXPORT | BT37: PO READY TO EXPORT
A38: =+AA38&"-"&C38 -> 118622-February | B38: 2026 | C38: February | D38: February/2026 | E38: 28/2/2026 | F38: 00331315 | G38: 802Um00000EfEF9 | H38: AR00408210 | I38: 0004987350 | J38: Standard | K38: Activated | L38: Under Review | M38: Arajet Dominican Republic | N38: Arajet S.A. | O38: CRITEO CORP. United States of America | P38: Criteo | Q38: Argentina | S38: GLOBAL | T38: Aleph Spain | U38: Mexico | V38: Dynamic Ads | W38: Auction / Budget | X38: Auction / Budget | Y38: USD | Z38: USD | AA38: 118622 | AB38: 4000 | AC38: 4000 | AD38: 1 | AE38: 1 | AF38: 1 | AG38: 0.85 | AH38: 1 | AI38: 0 | AK38: 4000 | AL38: 4000 | AM38: 4000 | AN38: 4000 | AO38: 4000 | AQ38: 4000 | AR38: 4000 | AS38: 0 | AT38: 0 | AU38: 0 | AV38: 0 | AW38: SOIES-000001011 | AX38: SO Exported to ERP | AY38: POIME-000032930 | AZ38: PO Exported to ERP | BC38: Aleph Mexico | BD38: 1 | BE38: AR_CRITEO_ARAJET_FEB_2026 | BF38: Arajet Dominican Republic | BG38: 131094376 | BH38: Maria Candela Lirio | BJ38: Client Performance Driven (ROI) | BK38: Traditional (Local Team) | BL38: 28/2/2026 | BM38: 60 days | BP38: =INDEX(Summary!N:N,MATCH(A38,Summary!A:A,0),1) -> #N/A | BQ38: =AM38/INDEX('ex rate'!C:C,MATCH(Y38,'ex rate'!A:A,0),1) -> 4000 | BR38: =AO38/INDEX('ex rate'!C:C,MATCH(Z38,'ex rate'!A:A,0),1) -> 4000 | BS38: SO READY TO EXPORT | BT38: PO READY TO EXPORT
A39: =+AA39&"-"&C39 -> 110436-February | B39: 2026 | C39: February | D39: February/2026 | E39: 28/2/2026 | F39: 00331315 | G39: 802Um00000EfEFA | H39: AR00408210 | I39: 0004987351 | J39: Standard | K39: Activated | L39: Under Review | M39: Arajet Dominican Republic | N39: Arajet S.A. | O39: CRITEO CORP. United States of America | P39: Criteo | Q39: Argentina | S39: GLOBAL | T39: Aleph Spain | U39: Mexico | V39: Dynamic Ads | W39: Auction / Budget | X39: Auction / Budget | Y39: USD | Z39: USD | AA39: 110436 | AB39: 6000 | AC39: 6000 | AD39: 1 | AE39: 1 | AF39: 1 | AG39: 0.85 | AH39: 1 | AI39: 0 | AK39: 6000 | AL39: 6000 | AM39: 6000 | AN39: 6000 | AO39: 6000 | AQ39: 6000 | AR39: 6000 | AS39: 0 | AT39: 0 | AU39: 0 | AV39: 0 | AW39: SOIES-000001011 | AX39: SO Exported to ERP | AY39: POIME-000032930 | AZ39: PO Exported to ERP | BC39: Aleph Mexico | BD39: 1 | BE39: AR_CRITEO_ARAJET_FEB_2026 | BF39: Arajet Dominican Republic | BG39: 131094376 | BH39: Maria Candela Lirio | BJ39: Client Performance Driven (ROI) | BK39: Traditional (Local Team) | BL39: 28/2/2026 | BM39: 60 days | BP39: =INDEX(Summary!N:N,MATCH(A39,Summary!A:A,0),1) -> #N/A | BQ39: =AM39/INDEX('ex rate'!C:C,MATCH(Y39,'ex rate'!A:A,0),1) -> 6000 | BR39: =AO39/INDEX('ex rate'!C:C,MATCH(Z39,'ex rate'!A:A,0),1) -> 6000 | BS39: SO READY TO EXPORT | BT39: PO READY TO EXPORT
A40: =+AA40&"-"&C40 -> 31762-February | B40: 2026 | C40: February | D40: February/2026 | E40: 28/2/2026 | F40: 00327517 | G40: 802Um00000DkpJN | H40: CO00391696 | I40: 0004932625 | J40: Standard | K40: Activated | L40: Under Review | M40: SONY LATIN AMERICA INC. United States of America | N40: Group M Worldwide LLC DBA EssenceMediacom Miami | O40: CRITEO CORP. United States of America | P40: Criteo | Q40: Colombia | S40: GLOBAL | T40: Aleph USA | U40: Mexico | V40: Dynamic Ads | W40: Auction / Budget | X40: Auction / Budget | Y40: USD | Z40: USD | AA40: 31762 | AB40: 296.01 | AC40: 296.01 | AD40: 1 | AE40: 1 | AF40: 1 | AG40: 0.91 | AH40: 1 | AI40: 0 | AK40: 296.01 | AL40: 296.01 | AM40: 296.01 | AN40: 296.01 | AO40: 296.01 | AQ40: 296.01 | AR40: 296.01 | AS40: 0 | AT40: 0 | AU40: 0 | AV40: 0 | AW40: SOIUS-000002996 | AX40: SO Exported to ERP | AY40: POIME-000032887 | AZ40: PO Exported to ERP | BC40: Aleph Mexico | BD40: 1 | BE40: COL_CRITEO_MEDIACOM MIAMI_SONY ALON_FEBRERO 2026 | BF40: Group M Worldwide LLC DBA EssenceMediacom Miami | BG40: 204031493 | BH40: Paola Reina | BJ40: Client Performance Driven (ROI) | BK40: Traditional (Local Team) | BL40: 28/2/2026 | BM40: 30 days | BP40: =INDEX(Summary!N:N,MATCH(A40,Summary!A:A,0),1) -> #N/A | BQ40: =AM40/INDEX('ex rate'!C:C,MATCH(Y40,'ex rate'!A:A,0),1) -> 296.01 | BR40: =AO40/INDEX('ex rate'!C:C,MATCH(Z40,'ex rate'!A:A,0),1) -> 296.01 | BS40: SO READY TO EXPORT | BT40: PO READY TO EXPORT
A41: =+AA41&"-"&C41 -> 31763-February | B41: 2026 | C41: February | D41: February/2026 | E41: 28/2/2026 | F41: 00327517 | G41: 802Um00000DkpJP | H41: CO00391696 | I41: 0004932627 | J41: Standard | K41: Activated | L41: Under Review | M41: SONY LATIN AMERICA INC. United States of America | N41: Group M Worldwide LLC DBA EssenceMediacom Miami | O41: CRITEO CORP. United States of America | P41: Criteo | Q41: Colombia | S41: GLOBAL | T41: Aleph USA | U41: Mexico | V41: Dynamic Ads | W41: Auction / Budget | X41: Auction / Budget | Y41: USD | Z41: USD | AA41: 31763 | AB41: 253.33 | AC41: 253.33 | AD41: 1 | AE41: 1 | AF41: 1 | AG41: 0.91 | AH41: 1 | AI41: 0 | AK41: 253.33 | AL41: 253.33 | AM41: 253.33 | AN41: 253.33 | AO41: 253.33 | AQ41: 253.33 | AR41: 253.33 | AS41: 0 | AT41: 0 | AU41: 0 | AV41: 0 | AW41: SOIUS-000002996 | AX41: SO Exported to ERP | AY41: POIME-000032887 | AZ41: PO Exported to ERP | BC41: Aleph Mexico | BD41: 1 | BE41: COL_CRITEO_MEDIACOM MIAMI_SONY ALON_FEBRERO 2026 | BF41: Group M Worldwide LLC DBA EssenceMediacom Miami | BG41: 204031493 | BH41: Paola Reina | BJ41: Client Performance Driven (ROI) | BK41: Traditional (Local Team) | BL41: 28/2/2026 | BM41: 30 days | BP41: =INDEX(Summary!N:N,MATCH(A41,Summary!A:A,0),1) -> #N/A | BQ41: =AM41/INDEX('ex rate'!C:C,MATCH(Y41,'ex rate'!A:A,0),1) -> 253.33 | BR41: =AO41/INDEX('ex rate'!C:C,MATCH(Z41,'ex rate'!A:A,0),1) -> 253.33 | BS41: SO READY TO EXPORT | BT41: PO READY TO EXPORT
A42: =+AA42&"-"&C42 -> 36112-February | B42: 2026 | C42: February | D42: February/2026 | E42: 28/2/2026 | F42: 00327517 | G42: 802Um00000DkpJQ | H42: CO00391696 | I42: 0004932628 | J42: Standard | K42: Activated | L42: Under Review | M42: SONY LATIN AMERICA INC. United States of America | N42: Group M Worldwide LLC DBA EssenceMediacom Miami | O42: CRITEO CORP. United States of America | P42: Criteo | Q42: Colombia | S42: GLOBAL | T42: Aleph USA | U42: Mexico | V42: Dynamic Ads | W42: Auction / Budget | X42: Auction / Budget | Y42: USD | Z42: USD | AA42: 36112 | AB42: 300.73 | AC42: 300.73 | AD42: 1 | AE42: 1 | AF42: 1 | AG42: 0.91 | AH42: 1 | AI42: 0 | AK42: 300.73 | AL42: 300.73 | AM42: 300.73 | AN42: 300.73 | AO42: 300.73 | AQ42: 300.73 | AR42: 300.73 | AS42: 0 | AT42: 0 | AU42: 0 | AV42: 0 | AW42: SOIUS-000002996 | AX42: SO Exported to ERP | AY42: POIME-000032887 | AZ42: PO Exported to ERP | BC42: Aleph Mexico | BD42: 1 | BE42: COL_CRITEO_MEDIACOM MIAMI_SONY ALON_FEBRERO 2026 | BF42: Group M Worldwide LLC DBA EssenceMediacom Miami | BG42: 204031493 | BH42: Paola Reina | BJ42: Client Performance Driven (ROI) | BK42: Traditional (Local Team) | BL42: 28/2/2026 | BM42: 30 days | BP42: =INDEX(Summary!N:N,MATCH(A42,Summary!A:A,0),1) -> #N/A | BQ42: =AM42/INDEX('ex rate'!C:C,MATCH(Y42,'ex rate'!A:A,0),1) -> 300.73 | BR42: =AO42/INDEX('ex rate'!C:C,MATCH(Z42,'ex rate'!A:A,0),1) -> 300.73 | BS42: SO READY TO EXPORT | BT42: PO READY TO EXPORT
A43: =+AA43&"-"&C43 -> 31276-February | B43: 2026 | C43: February | D43: February/2026 | E43: 28/2/2026 | F43: 00327517 | G43: 802Um00000DkpJR | H43: CO00391696 | I43: 0004932629 | J43: Standard | K43: Activated | L43: Under Review | M43: SONY LATIN AMERICA INC. United States of America | N43: Group M Worldwide LLC DBA EssenceMediacom Miami | O43: CRITEO CORP. United States of America | P43: Criteo | Q43: Colombia | S43: GLOBAL | T43: Aleph USA | U43: Mexico | V43: Dynamic Ads | W43: Auction / Budget | X43: Auction / Budget | Y43: USD | Z43: USD | AA43: 31276 | AB43: 1816.55 | AC43: 1816.55 | AD43: 1 | AE43: 1 | AF43: 1 | AG43: 0.91 | AH43: 1 | AI43: 0 | AK43: 1816.55 | AL43: 1816.55 | AM43: 1816.55 | AN43: 1816.55 | AO43: 1816.55 | AQ43: 1816.55 | AR43: 1816.55 | AS43: 0 | AT43: 0 | AU43: 0 | AV43: 0 | AW43: SOIUS-000002996 | AX43: SO Exported to ERP | AY43: POIME-000032887 | AZ43: PO Exported to ERP | BC43: Aleph Mexico | BD43: 1 | BE43: COL_CRITEO_MEDIACOM MIAMI_SONY ALON_FEBRERO 2026 | BF43: Group M Worldwide LLC DBA EssenceMediacom Miami | BG43: 204031493 | BH43: Paola Reina | BJ43: Client Performance Driven (ROI) | BK43: Traditional (Local Team) | BL43: 28/2/2026 | BM43: 30 days | BP43: =INDEX(Summary!N:N,MATCH(A43,Summary!A:A,0),1) -> #N/A | BQ43: =AM43/INDEX('ex rate'!C:C,MATCH(Y43,'ex rate'!A:A,0),1) -> 1816.55 | BR43: =AO43/INDEX('ex rate'!C:C,MATCH(Z43,'ex rate'!A:A,0),1) -> 1816.55 | BS43: SO READY TO EXPORT | BT43: PO READY TO EXPORT

Sheet SF_Direct
A1: Publisher PO ID | B1: Year | C1: Line Month | D1: Posting Period | E1: Finance Date | F1: Salesforce Project Number | G1: Line ID | H1: Project : Opportunity : Aleph Campaign ID | I1: Line Product Number | J1: Type of Line | K1: Status | L1: Order Line Status | M1: Company Name (Know as + Country) | N1: Company To Invoice Legal Name | O1: Vendor | P1: Product Business Unit | Q1: Reporting Country | R1: Billing Country | S1: Delivery Country | T1: Billing Entity | U1: Purchase Country | V1: Product | W1: Sales UOM | X1: Purchase UOM | Y1: Billing Currency | Z1: Purchase Currency | AA1: Publisher PO ID | AB1: Qualified Sales Quantity | AC1: Qualified Purchase Quantity | AD1: Gross Discounted | AE1: Gross Sales Price | AF1: Net Sales Price | AG1: Gross Purchase Price | AH1: Net Purchase Price | AI1: Client Discount | AJ1: Agency Commission | AK1: Delivered Sales Quantity | AL1: Delivered Purchase Quantity | AM1: Net Budget Delivered (Billing Currency) | AN1: Net Cost Delivered (Buying Currency) | AO1: Net Cost Delivered w/o Tax (Buying Curr) | AP1: Activation Exchange Rate | AQ1: Total Net Budget (Delivered) (converted) | AR1: Total Net Cost (Delivered) (converted) | AS1: Margin Delivered (Billing Currency) | AT1: Margin Amount (Delivered) | AU1: Margin Amount (Delivered) (converted) | AV1: Margin % (Delivered) | AW1: Sales Order Number | AX1: SO Status | AY1: Purchase Order Number | AZ1: PO Status | BA1: Invoice Description | BB1: Line Description | BC1: Purchase Entity | BD1: Billing Exchange Rate | BE1: Project Name | BF1: Company to invoice | BG1: Company To Invoice Tax Id | BH1: Sales Manager | BI1: Trade Deal | BJ1: Branding/Performance | BK1: Sales Channel | BL1: End Date | BM1: Project : Company to invoice : Payment condition | BN1: Branding/Performance | BO1: Sales Channel | BP1: Status | BQ1: Rev. Act. FX / Closing FX | BR1: COGS Act. FX / Closing FX | BT1: SO STATUS | BU1: PO STATUS
A2: =+AA2&"-"&C2 -> 115957-February | B2: 2026 | C2: February | D2: February/2026 | E2: 28/2/2026 | F2: 00303820 | G2: 802Um00000EjgCj | H2: AR00372251 | I2: 0004993495 | J2: Standard | K2: Activated | L2: Under Review | M2: Arajet Dominican Republic | N2: Criteo MEA FZ-LLC | O2: CRITEO CORP. United States of America | P2: Criteo Direct | Q2: Argentina | S2: GLOBAL | T2: Aleph Rep Dominicana | U2: Mexico | V2: Dynamic Ads | W2: Auction / Budget | X2: Auction / Budget | Y2: USD | Z2: USD | AA2: 115957 | AB2: 1389.89 | AC2: 1389.89 | AD2: 1 | AE2: 1 | AF2: 1 | AG2: 1 | AH2: 1 | AI2: 0 | AK2: 1389.89 | AL2: 1389.89 | AM2: 1389.89 | AN2: 1389.89 | AO2: 1389.89 | AQ2: 8376.11 | AR2: 1389.89 | AS2: 166.7868 | AT2: 166.7868 | AU2: 166.7868 | AV2: 0.12 | BC2: Aleph Mexico | BD2: 1 | BE2: BR_CRITEO_ARAJET_AGO_2025 | BF2: Criteo | BG2: 100220759300003 | BH2: Diana Campos | BJ2: Client Performance Driven (ROI) | BK2: Traditional (Local Team) | BL2: 28/2/2026 | BM2: Prepaid | BP2: #N/A | BQ2: 1499.95 | BR2: 1499.95
A3: =+AA3&"-"&C3 -> 111236-February | B3: 2026 | C3: February | D3: February/2026 | E3: 28/2/2026 | F3: 00301813 | G3: 802Uj00000OKBcd | H3: PE00369584 | I3: 0004746267 | J3: Standard | K3: Activated | L3: Under Review | M3: FARMACIAS SIMAN HONDURAS | N3: Criteo MEA FZ-LLC | O3: CRITEO CORP. United States of America | P3: Criteo Direct | Q3: Peru | S3: GLOBAL | T3: Aleph Peru | U3: Mexico | V3: Dynamic Ads | W3: Auction / Budget | X3: Auction / Budget | Y3: USD | Z3: USD | AA3: 111236 | AB3: 1533.98 | AC3: 1533.98 | AD3: 1 | AE3: 1 | AF3: 1 | AG3: 1 | AH3: 1 | AI3: 0 | AK3: 1533.98 | AL3: 1533.98 | AM3: 1533.98 | AN3: 1533.98 | AO3: 1533.98 | AQ3: 16030.74 | AR3: 1533.98 | AS3: 184.0776 | AT3: 184.0776 | AU3: 184.0776 | AV3: 0.12 | BC3: Aleph Mexico | BD3: 1 | BE3: NI_CRITEO_FARMACOSTO_AGOST_2025 | BF3: Criteo | BG3: 100220759300003 | BH3: Rodrigo Aldecoa | BJ3: Client Performance Driven (ROI) | BK3: Traditional (Local Team) | BL3: 28/2/2026 | BM3: Prepaid | BP3: #N/A | BQ3: 2503.04 | BR3: 2503.04
A4: =+AA4&"-"&C4 -> 111235-February | B4: 2026 | C4: February | D4: February/2026 | E4: 28/2/2026 | F4: 00301814 | G4: 802Uj00000OKFpu | H4: PE00369587 | I4: 0004746240 | J4: Standard | K4: Activated | L4: Under Review | M4: FARMACIAS SIMAN HONDURAS | N4: Criteo MEA FZ-LLC | O4: CRITEO CORP. United States of America | P4: Criteo Direct | Q4: Peru | S4: GLOBAL | T4: Aleph Peru | U4: Mexico | V4: Dynamic Ads | W4: Auction / Budget | X4: Auction / Budget | Y4: USD | Z4: USD | AA4: 111235 | AB4: 2530.7 | AC4: 2530.7 | AD4: 1 | AE4: 1 | AF4: 1 | AG4: 1 | AH4: 1 | AI4: 0 | AK4: 2530.7 | AL4: 2530.7 | AM4: 2530.7 | AN4: 2530.7 | AO4: 2530.7 | AQ4: 29896.19 | AR4: 2530.7 | AS4: 303.684 | AT4: 303.684 | AU4: 303.684 | AV4: 0.12 | BC4: Aleph Mexico | BD4: 1 | BE4: GT_CRITEO_FARMACOSTO_AGOST_2025 | BF4: Criteo | BG4: 100220759300003 | BH4: Rodrigo Aldecoa | BJ4: Client Performance Driven (ROI) | BK4: Traditional (Local Team) | BL4: 28/2/2026 | BM4: Prepaid | BP4: #N/A | BQ4: 7043.68 | BR4: 7043.68
A5: =+AA5&"-"&C5 -> 86037-February | B5: 2026 | C5: February | D5: February/2026 | E5: 28/2/2026 | F5: 00301812 | G5: 802Uj00000OKGKY | H5: PE00369580 | I5: 0004746284 | J5: Standard | K5: Activated | L5: Under Review | M5: FARMACIAS SIMAN HONDURAS | N5: Criteo MEA FZ-LLC | O5: CRITEO CORP. United States of America | P5: Criteo Direct | Q5: Peru | S5: GLOBAL | T5: Aleph Peru | U5: Mexico | V5: Dynamic Ads | W5: Auction / Budget | X5: Auction / Budget | Y5: USD | Z5: USD | AA5: 86037 | AB5: 7036.65 | AC5: 7036.65 | AD5: 1 | AE5: 1 | AF5: 1 | AG5: 1 | AH5: 1 | AI5: 0 | AK5: 7036.65 | AL5: 7036.65 | AM5: 7036.65 | AN5: 7036.65 | AO5: 7036.65 | AQ5: 54077.64 | AR5: 7036.65 | AS5: 844.398 | AT5: 844.398 | AU5: 844.398 | AV5: 0.12 | BC5: Aleph Mexico | BD5: 1 | BE5: HN_CRITEO_FARMACIASIMAN_AGOST_2025 | BF5: Criteo | BG5: 100220759300003 | BH5: Rodrigo Aldecoa | BJ5: Client Performance Driven (ROI) | BK5: Traditional (Local Team) | BL5: 28/2/2026 | BM5: Prepaid

Sheet ex rate
A1: Shared
B2: EOM | C2: 46081
A3: Currency | B3: Country | C3: 46054
A4: USD | B4: United States | C4: 1
A5: EUR | B5: Eurozone | C5: 0.84709869
A6: ARS | B6: Argentina | C6: 1397
A7: BRL | B7: Brazil | C7: 5.1495
A8: CLP | B8: Chile | C8: 861.19
A9: MXN | B9: Mexico | C9: 17.2563
A10: UYU | B10: Uruguay | C10: 38.402
A11: GBP | B11: United Kingdom | C11: 0.73995343
A12: COP | B12: Colombia | C12: 3766.3
A13: PEN | B13: Peru | C13: 3.361
A14: GTQ | B14: Guatemala | C14: 7.66476
... A81: USD | B81: El Salvador | C81: 1

Sheet Criteo Report
A1: Off.Doc.Number | B1: Document Type | C1: Document date | D1: Bill Start | E1: Bill To | F1: Bill Type | G1: Bill Status | H1: Advertiser Country | I1: Advertiser ID | J1: Advertiser name | K1: Reversal Reason | L1: Criteo company code | M1: Criteo company | N1: BP | O1: BP Name | P1: Brand Name | Q1: BP Country | R1: Currency | S1: Gross amount | T1: Net amount | U1: Tax amount
A2: B13ZZ12602005743 | B2: IN | C2: 46081 | D2: 46054 | E2: 46081 | F2: Invoice | G2: INVOICED | H2: PE | I2: 31764 | J2: Sony Store PE | L2: 13 | M2: Criteo Corp | N2: 2100001461 | O2: Aleph CO | P2: IMM Internet Media México, S. de R.L. de C.V. | Q2: MX | R2: USD | S2: 288.47 | T2: 288.47 | U2: 0
A3: B13ZZ12602005743 | B3: IN | C3: 46081 | D3: 46056 | E3: 46081 | F3: Invoice | G3: INVOICED | H3: PE | I3: 120332 | J3: Velez PE | L3: 13 | M3: Criteo Corp | N3: 2100001461 | O3: Aleph CO | P3: IMM Internet Media México, S. de R.L. de C.V. | Q3: MX | R3: USD | S3: 2065.75 | T3: 2065.75 | U3: 0
A4: B13ZZ12602005745 | B4: IN | C4: 46081 | D4: 46054 | E4: 46081 | F4: Invoice | G4: INVOICED | H4: PE | I4: 98889 | J4: Arajet PE | L4: 13 | M4: Criteo Corp | N4: 2100001966 | O4: Aleph AR | P4: IMM Internet Media México, S. de R.L. de C.V. | Q4: MX | R4: USD | S4: 1497.88 | T4: 1497.88 | U4: 0
A5: B13ZZ12602005746 | B5: IN | C5: 46081 | D5: 46054 | E5: 46081 | F5: Invoice | G5: INVOICED | H5: PE | I5: 110594 | J5: DIVEMOTOR PE | L5: 13 | M5: Criteo Corp | N5: 2100001899 | O5: Aleph PE | P5: IMM Internet Media México, S. de R.L. de C.V. | Q5: MX | R5: USD | S5: 999.97 | T5: 999.97 | U5: 0
A6: B13ZZ12602005746 | B6: IN | C6: 46081 | D6: 46054 | E6: 46081 | F6: Invoice | G6: INVOICED | H6: PE | I6: 107799 | J6: Nexo Inmobiliario PE | L6: 13 | M6: Criteo Corp | N6: 2100001899 | O6: Aleph PE | P6: IMM Internet Media México, S. de R.L. de C.V. | Q6: MX | R6: USD | S6: 4773.92 | T6: 4773.92 | U6: 0
A7: B13ZZ12602005746 | B7: IN | C7: 46081 | D7: 46073 | E7: 46081 | F7: Invoice | G7: INVOICED | H7: PE | I7: 107434 | J7: BANCO BBVA PERU | L7: 13 | M7: Criteo Corp | N7: 2100001899 | O7: Aleph PE | P7: IMM Internet Media México, S. de R.L. de C.V. | Q7: MX | R7: USD | S7: 848.2 | T7: 848.2 | U7: 0
A8: B13ZZ12602005746 | B8: IN | C8: 46081 | D8: 46065 | E8: 46079 | F8: Invoice | G8: INVOICED | H8: PE | I8: 106852 | J8: MAKRO PE | L8: 13 | M8: Criteo Corp | N8: 2100001899 | O8: Aleph PE | P8: IMM Internet Media México, S. de R.L. de C.V. | Q8: MX | R8: USD | S8: 2000 | T8: 2000 | U8: 0
A9: B13ZZ12602005746 | B9: IN | C9: 46081 | D9: 46054 | E9: 46081 | F9: Invoice | G9: INVOICED | H9: PE | I9: 114667 | J9: UCSUR PE | L9: 13 | M9: Criteo Corp | N9: 2100001899 | O9: Aleph PE | P9: IMM Internet Media México, S. de R.L. de C.V. | Q9: MX | R9: USD | S9: 16105.49 | T9: 16105.49 | U9: 0
A10: B13ZZ12602005746 | B10: IN | C10: 46081 | D10: 46054 | E10: 46081 | F10: Invoice | G10: INVOICED | H10: PE | I10: 115210 | J10: TIENDAS MASS PE | L10: 13 | M10: Criteo Corp | N10: 2100001899 | O10: Aleph PE | P10: IMM Internet Media México, S. de R.L. de C.V. | Q10: MX | R10: USD | S10: 4027.45 | T10: 4027.45 | U10: 0
A11: B13ZZ12602005746 | B11: IN | C11: 46081 | D11: 46054 | E11: 46081 | F11: Invoice | G11: INVOICED | H11: PE | I11: 116497 | J11: PC FACTORY PE | L11: 13 | M11: Criteo Corp | N11: 2100001899 | O11: Aleph PE | P11: IMM Internet Media México, S. de R.L. de C.V. | Q11: MX | R11: USD | S11: 1999.95 | T11: 1999.95 | U11: 0
A12: B13ZZ12602005746 | B12: IN | C12: 46081 | D12: 46054 | E12: 46081 | F12: Invoice | G12: INVOICED | H12: PE | I12: 103986 | J12: Casa Andina PE | L12: 13 | M12: Criteo Corp | N12: 2100001899 | O12: Aleph PE | P12: IMM Internet Media México, S. de R.L. de C.V. | Q12: MX | R12: USD | S12: 2986.68 | T12: 2986.68 | U12: 0
A13: B13ZZ12602005746 | B13: IN | C13: 46081 | D13: 46054 | E13: 46081 | F13: Invoice | G13: INVOICED | H13: PE | I13: 116982 | J13: Financiera Oh PE | L13: 13 | M13: Criteo Corp | N13: 2100001899 | O13: Aleph PE | P13: IMM Internet Media México, S. de R.L. de C.V. | Q13: MX | R13: USD | S13: 2398.79 | T13: 2398.79 | U13: 0
... A29: B13ZZ12602005746 | B29: IN | C29: 46081 | D29: 46054 | E29: 46081 | F29: Invoice | G29: INVOICED | H29: PE | I29: 44368 | J29: BCP PE | L29: 13 | M29: Criteo Corp | N29: 2100001899 | O29: Aleph PE | P29: IMM Internet Media México, S. de R.L. de C.V. | Q29: MX | R29: USD | S29: 9029.13 | T29: 9029.13 | U29: 0

Sheet Criteo Direct Report
A1: Off.Doc.Number | B1: Document Type | C1: Document date | D1: Bill Start | E1: Bill To | F1: Bill Type | G1: Bill Status | H1: Advertiser Country | I1: Advertiser ID | J1: Advertiser name | K1: Reversal Reason | L1: Criteo company code | M1: Criteo company | N1: BP | O1: BP Name | P1: Brand Name | Q1: BP Country | R1: Currency | S1: Gross amount | T1: Net amount | U1: Tax amount
A2: B13HN12602005657 | B2: IN | C2: 46081 | D2: 46054 | E2: 46081 | F2: Invoice | G2: INVOICED | H2: HN | I2: 86037 | J2: Farmacia Siman HN | L2: 13 | M2: Criteo Corp | N2: 1100019323 | O2: Súper Farmacia Simán S. A. | P2: IMM Internet Media México, S. de R.L. de C.V. | Q2: HN | R2: USD | S2: 7036.65 | T2: 7036.65 | U2: 0
A3: B20BR12602000864 | B3: IN | C3: 46081 | D3: 46054 | E3: 46078 | F3: Invoice | G3: INVOICED | H3: BR | I3: 115957 | J3: Arajet BR | L3: 20 | M3: Criteo do Brasil | N3: 1100024541 | O3: ARAJET S.A. | P3: IMM Internet Media México, S. de R.L. de C.V. | Q3: BR | R3: BRL | S3: 7257.09 | T3: 7257.09 | U3: 0
A4: B13NI12602004917 | B4: IN | C4: 46081 | D4: 46054 | E4: 46081 | F4: Invoice | G4: INVOICED | H4: NI | I4: 111236 | J4: Farma Costo NI | L4: 13 | M4: Criteo Corp | N4: 1100021480 | O4: Inversiones Madison Nicaragua S.A | P4: IMM Internet Media México, S. de R.L. de C.V. | Q4: NI | R4: USD | S4: 1533.98 | T4: 1533.98 | U4: 0
A5: B13GT12602004918 | B5: IN | C5: 46081 | D5: 46054 | E5: 46081 | F5: Invoice | G5: INVOICED | H5: GT | I5: 111235 | J5: Farma Costo GT | L5: 13 | M5: Criteo Corp | N5: 1100021481 | O5: INVERSIONES MADISON SOCIEDAD ANONIMA | P5: IMM Internet Media México, S. de R.L. de C.V. | Q5: GT | R5: USD | S5: 2530.7 | T5: 2530.7 | U5: 0

Sheet Pivot Criteo report
A1: Advertiser ID | B1: Advertiser name | C1: Currency | D1: Suma de Net amount
A2: 31764 | B2: Sony Store PE | C2: USD | D2: 288.47
A3: 98889 | B3: Arajet PE | C3: USD | D3: 1497.88
A4: 114667 | B4: UCSUR PE | C4: USD | D4: 16105.49
A5: 115210 | B5: TIENDAS MASS PE | C5: USD | D5: 4027.45
A6: 116497 | B6: PC FACTORY PE | C6: USD | D6: 1999.95
A7: 116982 | B7: Financiera Oh PE | C7: USD | D7: 2398.79
A8: 117067 | B8: APUESTA TOTAL PE | C8: USD | D8: 5184.83
A9: 118854 | B9: Oncosalud PE | C9: USD | D9: 912.96
A10: 119907 | B10: SISE PE | C10: USD | D10: 8000
A11: 29652 | B11: Interbank PE | C11: USD | D11: 998.79
A12: 39798 | B12: Promart PE | C12: USD | D12: 1173.05
A13: 41643 | B13: Oechsle PE | C13: USD | D13: 2771.71
... A29: 120764 | B29: Natura PE | C29: USD | D29: 265.76
A30: Total general | D30: 90017.38

Sheet ERP
A1: Posting type | B1: Date | C1: Customer name | D1: Customer account | E1: Vendor name | F1: Vendor account | G1: Description | H1: SO / PO | I1: Ledger account | J1: Journal number | K1: Voucher | L1: Document date | M1: Ledger account2 | N1: Main account | O1: Account name | P1: Currency | Q1: Amount in transaction currency | R1: Amount | S1: Amount in reporting currency | T1: Posting layer | U1: Created by | V1: ENTITY | W1: ACCOUNT | X1: BU
A2: Sales - packing slip revenue | B2: 46081 | G2: SOICO-000004001, 4K1WUL1GXX | H2: SOICO-000004001 | I2: 4101011200-Criteo-ALL-ICOL-COL-Rep | J2: GJT080755 | K2: PS006476 | L2: 46081 | M2: 4101011200-Criteo-ALL-ICOL-COL-Rep | N2: 4101011200 | O2: Representation | P2: COP | Q2: -7953137.5 | R2: -7953137.5 | S2: -2117.09 | T2: Current | U2: daniela.alonso | V2: ICOL | W2: REV | X2: CRITEO
A3: Purchase expenditure, un-invoiced | B3: 46081 | G3: POIME-000032936, 0AWJPBBCLJ | H3: POIME-000032936 | I3: 5101011200-Criteo-ALL-IPER-PER-Rep | J3: GJT380839 | K3: PR070789 | L3: 46081 | M3: 5101011200-Criteo-ALL-IPER-PER-Rep | N3: 5101011200 | O3: Representation | P3: USD | Q3: 379.94 | R3: 6556.36 | S3: 379.94 | T3: Current | U3: Admin | V3: IMEX | W3: COGS | X3: CRITEO
A4: Purchase expenditure, un-invoiced | B4: 46081 | G4: POIME-000032934, 0AWJPBBCLJ | H4: POIME-000032934 | I4: 5101011200-Criteo-ALL-IPER-PER-Rep | J4: GJT380837 | K4: PR070787 | L4: 46081 | M4: 5101011200-Criteo-ALL-IPER-PER-Rep | N4: 5101011200 | O4: Representation | P4: USD | Q4: 180.05 | R4: 3107 | S4: 180.05 | T4: Current | U4: Admin | V4: IMEX | W4: COGS | X4: CRITEO
A5: Purchase expenditure, un-invoiced | B5: 46081 | G5: POIME-000032930, 0AWJPBBCLJ | H5: POIME-000032930 | I5: 5101011200-Criteo-ALL-IESP-ARG-Rep | J5: GJT380833 | K5: PR070783 | L5: 46081 | M5: 5101011200-Criteo-ALL-IESP-ARG-Rep | N5: 5101011200 | O5: Representation | P5: USD | Q5: 30985.86 | R5: 534701.3 | S5: 30985.86 | T5: Current | U5: Admin | V5: IMEX | W5: COGS | X5: CRITEO
A6: Purchase expenditure, un-invoiced | B6: 46081 | G6: POIME-000032928, 0AWJPBBCLJ | H6: POIME-000032928 | I6: 5101011200-Criteo-ALL-IPER-PER-Rep | J6: GJT380831 | K6: PR070781 | L6: 46081 | M6: 5101011200-Criteo-ALL-IPER-PER-Rep | N6: 5101011200 | O6: Representation | P6: USD | Q6: 5184.83 | R6: 89470.98 | S6: 5184.83 | T6: Current | U6: Admin | V6: IMEX | W6: COGS | X6: CRITEO
A7: Purchase expenditure, un-invoiced | B7: 46081 | G7: POIME-000032919, 0AWJPBBCLJ | H7: POIME-000032919 | I7: 5101011200-Criteo-ALL-IPER-PER-Rep | J7: GJT380822 | K7: PR070772 | L7: 46081 | M7: 5101011200-Criteo-ALL-IPER-PER-Rep | N7: 5101011200 | O7: Representation | P7: USD | Q7: 6300 | R7: 108714.69 | S7: 6300 | T7: Current | U7: Admin | V7: IMEX | W7: COGS | X7: CRITEO
A8: Purchase expenditure, un-invoiced | B8: 46081 | G8: POIME-000032918, 0AWJPBBCLJ | H8: POIME-000032918 | I8: 5101011200-Criteo-ALL-IPER-PER-Rep | J8: GJT380821 | K8: PR070771 | L8: 46081 | M8: 5101011200-Criteo-ALL-IPER-PER-Rep | N8: 5101011200 | O8: Representation | P8: USD | Q8: 848.2 | R8: 14636.79 | S8: 848.2 | T8: Current | U8: Admin | V8: IMEX | W8: COGS | X8: CRITEO
A9: Purchase expenditure, un-invoiced | B9: 46081 | G9: POIME-000032917, 0AWJPBBCLJ | H9: POIME-000032917 | I9: 5101011200-Criteo-ALL-IPER-PER-Rep | J9: GJT380820 | K9: PR070770 | L9: 46081 | M9: 5101011200-Criteo-ALL-IPER-PER-Rep | N9: 5101011200 | O9: Representation | P9: USD | Q9: 2771.71 | R9: 47829.46 | S9: 2771.71 | T9: Current | U9: Admin | V9: IMEX | W9: COGS | X9: CRITEO
A10: Purchase expenditure, un-invoiced | B10: 46081 | G10: POIME-000032905, 0AWJPBBCLJ | H10: POIME-000032905 | I10: 5101011200-Criteo-ALL-IPER-PER-Rep | J10: GJT380808 | K10: PR070758 | L10: 46081 | M10: 5101011200-Criteo-ALL-IPER-PER-Rep | N10: 5101011200 | O10: Representation | P10: USD | Q10: 2000 | R10: 34512.6 | S10: 2000 | T10: Current | U10: Admin | V10: IMEX | W10: COGS | X10: CRITEO
A11: Purchase expenditure, un-invoiced | B11: 46081 | G11: POIME-000032904, 0AWJPBBCLJ | H11: POIME-000032904 | I11: 5101011200-Criteo-ALL-IPER-PER-Rep | J11: GJT380807 | K11: PR070757 | L11: 46081 | M11: 5101011200-Criteo-ALL-IPER-PER-Rep | N11: 5101011200 | O11: Representation | P11: USD | Q11: 3000 | R11: 51768.9 | S11: 3000 | T11: Current | U11: Admin | V11: IMEX | W11: COGS | X11: CRITEO
A12: Purchase expenditure, un-invoiced | B12: 46081 | G12: POIME-000032902, 0AWJPBBCLJ | H12: POIME-000032902 | I12: 5101011200-Criteo-ALL-ICOL-COL-Rep | J12: GJT380805 | K12: PR070755 | L12: 46081 | M12: 5101011200-Criteo-ALL-ICOL-COL-Rep | N12: 5101011200 | O12: Representation | P12: USD | Q12: 2065.75 | R12: 35647.2 | S12: 2065.75 | T12: Current | U12: Admin | V12: IMEX | W12: COGS | X12: CRITEO
A13: Purchase expenditure, un-invoiced | B13: 46081 | G13: POIME-000032898, 0AWJPBBCLJ | H13: POIME-000032898 | I13: 5101011200-Criteo-ALL-IPER-PER-Rep | J13: GJT380801 | K13: PR070751 | L13: 46081 | M13: 5101011200-Criteo-ALL-IPER-PER-Rep | N13: 5101011200 | O13: Representation | P13: USD | Q13: 993 | R13: 17135.51 | S13: 993 | T13: Current | U13: Admin | V13: IMEX | W13: COGS | X13: CRITEO
... A56: Sales - packing slip revenue | B56: 46081 | G56: SOIPE-000003641, 20505670443 | H56: SOIPE-000003641 | I56: 4101011200-Criteo-ALL-IPER-PER-Rep | J56: GJT171633 | K56: PS014972 | L56: 46081 | M56: 4101011200-Criteo-ALL-IPER-PER-Rep | N56: 4101011200 | O56: Representation | P56: USD | Q56: -2986.68 | R56: -10038.23 | S56: -2986.68 | T56: Current | U56: daniela.alonso | V56: IPER | W56: REV | X56: CRITEO
A57: Sales order revenue | B57: 46079 | C57: Media Analytics S.A.C. | D57: 20606271744 | G57: SOIPE-000008334, 20606271744, Media Analytics S.A.C. | H57: SOIPE-000008334 | I57: 4101011200-Criteo-ALL-IPER-PER-Rep | J57: GJT169926 | K57: CI00011265 | L57: 46079 | M57: 4101011200-Criteo-ALL-IPER-PER-Rep | N57: 4101011200 | O57: Representation | P57: USD | Q57: -2000 | R57: -6726 | S57: -2000 | T57: Current | U57: ext_vanessa.ortiz | V57: IPER | W57: REV | X57: CRITEO
A58: Sales order revenue | B58: 46079 | C58: Media Analytics S.A.C. | D58: 20606271744 | G58: SOIPE-000008334, 20606271744, Media Analytics S.A.C. | H58: SOIPE-000008334 | I58: 4101011200-Criteo-ALL-IPER-PER-Rep | J58: GJT169926 | K58: CI00011265 | L58: 46079 | M58: 4101011200-Criteo-ALL-IPER-PER-Rep | N58: 4101011200 | O58: Representation | P58: USD | Q58: 0 | R58: -70 | S58: 0 | T58: Current | U58: ext_vanessa.ortiz | V58: IPER | W58: REV | X58: CRITEO
A59: Sales - packing slip revenue | B59: 46079 | C59: Media Analytics S.A.C. | D59: 20606271744 | G59: SOIPE-000008334, 20606271744, Media Analytics S.A.C. | H59: SOIPE-000008334 | I59: 4101011200-Criteo-ALL-IPER-PER-Rep | J59: GJT169926 | K59: CI00011265 | L59: 46079 | M59: 4101011200-Criteo-ALL-IPER-PER-Rep | N59: 4101011200 | O59: Representation | P59: USD | Q59: 2000 | R59: 6796 | S59: 2000 | T59: Current | U59: ext_vanessa.ortiz | V59: IPER | W59: REV | X59: CRITEO
A60: Sales order revenue | B60: 46079 | C60: Media Analytics S.A.C. | D60: 20606271744 | G60: SOIPE-000009862, 20606271744, Media Analytics S.A.C. | H60: SOIPE-000009862 | I60: 4101011200-Criteo-ALL-IPER-PER-Rep | J60: GJT169924 | K60: CI00011263 | L60: 46079 | M60: 4101011200-Criteo-ALL-IPER-PER-Rep | N60: 4101011200 | O60: Representation | P60: USD | Q60: -1179.23 | R60: -3965.75 | S60: -1179.23 | T60: Current | U60: ext_vanessa.ortiz | V60: IPER | W60: REV | X60: CRITEO
A61: Sales order revenue | B61: 46079 | C61: Media Analytics S.A.C. | D61: 20606271744 | G61: SOIPE-000009862, 20606271744, Media Analytics S.A.C. | H61: SOIPE-000009862 | I61: 4101011200-Criteo-ALL-IPER-PER-Rep | J61: GJT169924 | K61: CI00011263 | L61: 46079 | M61: 4101011200-Criteo-ALL-IPER-PER-Rep | N61: 4101011200 | O61: Representation | P61: USD | Q61: 0 | R61: -7.08 | S61: 0 | T61: Current | U61: ext_vanessa.ortiz | V61: IPER | W61: REV | X61: CRITEO
A62: Sales - packing slip revenue | B62: 46079 | C62: Media Analytics S.A.C. | D62: 20606271744 | G62: SOIPE-000009862, 20606271744, Media Analytics S.A.C. | H62: SOIPE-000009862 | I62: 4101011200-Criteo-ALL-IPER-PER-Rep | J62: GJT169924 | K62: CI00011263 | L62: 46079 | M62: 4101011200-Criteo-ALL-IPER-PER-Rep | N62: 4101011200 | O62: Representation | P62: USD | Q62: 1179.23 | R62: 3972.83 | S62: 1179.23 | T62: Current | U62: ext_vanessa.ortiz | V62: IPER | W62: REV | X62: CRITEO
A63: Sales order revenue | B63: 46079 | C63: CONFEDERACION DE DESARROLLADORES INMOBILIARIOS DEL PERU- CODIP | D63: VRK905HFAA | G63: SOIPE-000003676, VRK905HFAA, CONFEDERACION DE DESARROLLADORES INMOBILIARIOS DEL PERU- CODIP | H63: SOIPE-000003676 | I63: 4101011200-Criteo--IPER-PER-Rep | J63: GJT169910 | K63: CI00011254 | L63: 46079 | M63: 4101011200-Criteo--IPER-PER-Rep | N63: 4101011200 | O63: Representation | P63: USD | Q63: -4699.94 | R63: -15805.9 | S63: -4699.94 | T63: Current | U63: roman.villanueva | V63: IPER | W63: REV | X63: CRITEO
A64: Sales - packing slip revenue | B64: 46079 | C64: CONFEDERACION DE DESARROLLADORES INMOBILIARIOS DEL PERU- CODIP | D64: VRK905HFAA | G64: SOIPE-000003676, VRK905HFAA, CONFEDERACION DE DESARROLLADORES INMOBILIARIOS DEL PERU- CODIP | H64: SOIPE-000003676 | I64: 4101011200-Criteo--IPER-PER-Rep | J64: GJT169910 | K64: CI00011254 | L64: 46079 | M64: 4101011200-Criteo--IPER-PER-Rep | N64: 4101011200 | O64: Representation | P64: USD | Q64: 4699.94 | R64: 15805.9 | S64: 4699.94 | T64: Current | U64: roman.villanueva | V64: IPER | W64: REV | X64: CRITEO
A65: Sales order revenue | B65: 46079 | C65: CONFEDERACION DE DESARROLLADORES INMOBILIARIOS DEL PERU- CODIP | D65: VRK905HFAA | G65: SOIPE-000003676, VRK905HFAA, CONFEDERACION DE DESARROLLADORES INMOBILIARIOS DEL PERU- CODIP | H65: SOIPE-000003676 | I65: 4101011200-Criteo--IPER-PER-Rep | J65: GJT169909 | K65: CI00011253 | L65: 46079 | M65: 4101011200-Criteo--IPER-PER-Rep | N65: 4101011200 | O65: Representation | P65: USD | Q65: -4571.33 | R65: -15373.38 | S65: -4571.33 | T65: Current | U65: roman.villanueva | V65: IPER | W65: REV | X65: CRITEO
A66: Sales - packing slip revenue | B66: 46079 | C66: CONFEDERACION DE DESARROLLADORES INMOBILIARIOS DEL PERU- CODIP | D66: VRK905HFAA | G66: SOIPE-000003676, VRK905HFAA, CONFEDERACION DE DESARROLLADORES INMOBILIARIOS DEL PERU- CODIP | H66: SOIPE-000003676 | I66: 4101011200-Criteo--IPER-PER-Rep | J66: GJT169909 | K66: CI00011253 | L66: 46079 | M66: 4101011200-Criteo--IPER-PER-Rep | N66: 4101011200 | O66: Representation | P66: USD | Q66: 4571.33 | R66: 15373.38 | S66: 4571.33 | T66: Current | U66: roman.villanueva | V66: IPER | W66: REV | X66: CRITEO
A67: Sales order revenue | B67: 46079 | C67: CONFEDERACION DE DESARROLLADORES INMOBILIARIOS DEL PERU- CODIP | D67: VRK905HFAA | G67: SOIPE-000003676, VRK905HFAA, CONFEDERACION DE DESARROLLADORES INMOBILIARIOS DEL PERU- CODIP | H67: SOIPE-000003676 | I67: 4101011200-Criteo--IPER-PER-Rep | J67: GJT169908 | K67: CI00011252 | L67: 46079 | M67: 4101011200-Criteo--IPER-PER-Rep | N67: 4101011200 | O67: Representation | P67: USD | Q67: 12.11 | R67: 40.73 | S67: 12.11 | T67: Current | U67: roman.villanueva | V67: IPER | W67: REV | X67: CRITEO
A68: Sales - packing slip revenue | B68: 46079 | C68: CONFEDERACION DE DESARROLLADORES INMOBILIARIOS DEL PERU- CODIP | D68: VRK905HFAA | G68: SOIPE-000003676, VRK905HFAA, CONFEDERACION DE DESARROLLADORES INMOBILIARIOS DEL PERU- CODIP | H68: SOIPE-000003676 | I68: 4101011200-Criteo--IPER-PER-Rep | J68: GJT169908 | K68: CI00011252 | L68: 46079 | M68: 4101011200-Criteo--IPER-PER-Rep | N68: 4101011200 | O68: Representation | P68: USD | Q68: -12.11 | R68: -40.73 | S68: -12.11 | T68: Current | U68: roman.villanueva | V68: IPER | W68: REV | X68: CRITEO
... A72: Sales - packing slip revenue | B72: 46079 | C72: CONFEDERACION DE DESARROLLADORES INMOBILIARIOS DEL PERU- CODIP | D72: VRK905HFAA | G72: SOIPE-000003676, VRK905HFAA, CONFEDERACION DE DESARROLLADORES INMOBILIARIOS DEL PERU- CODIP | H72: SOIPE-000003676 | I72: 4101011200-Criteo--IPER-PER-Rep | J72: GJT169905 | K72: CC00001499 | L72: 46079 | M72: 4101011200-Criteo--IPER-PER-Rep | N72: 4101011200 | O72: Representation | P72: USD | Q72: -4571.33 | R72: -15373.38 | S72: -4571.33 | T72: Current | U72: roman.villanueva | V72: IPER | W72: REV | X72: CRITEO
A73: Sales - packing slip revenue | B73: 46079 | G73: SOIPE-000003676, VRK905HFAA | H73: SOIPE-000003676 | I73: 4101011200-Criteo--IPER-PER-Rep | J73: GJT169904 | K73: PS014821 | L73: 46079 | M73: 4101011200-Criteo--IPER-PER-Rep | N73: 4101011200 | O73: Representation | P73: USD | Q73: 0 | R73: 0 | S73: 0 | T73: Current | U73: roman.villanueva | V73: IPER | W73: REV | X73: CRITEO
A74: Sales order revenue | B74: 46078 | C74: MEDIAWISE S.A.C | D74: 20550082722 | G74: SOIPE-000007234, 20509867560, MEDIAWISE S.A.C | H74: SOIPE-000007234 | I74: 4101011200-Criteo-ALL-IPER-PER-Rep | J74: GJT169842 | K74: CI00011249 | L74: 46078 | M74: 4101011200-Criteo-ALL-IPER-PER-Rep | N74: 4101011200 | O74: Representation | P74: USD | Q74: -19100.01 | R74: -64233.33 | S74: -19100.01 | T74: Current | U74: ext_vanessa.ortiz | V74: IPER | W74: REV | X74: CRITEO
A75: Sales order revenue | B75: 46078 | C75: MEDIAWISE S.A.C | D75: 20550082722 | G75: SOIPE-000007234, 20509867560, MEDIAWISE S.A.C | H75: SOIPE-000007234 | I75: 4101011200-Criteo-ALL-IPER-PER-Rep | J75: GJT169842 | K75: CI00011249 | L75: 46078 | M75: 4101011200-Criteo-ALL-IPER-PER-Rep | N75: 4101011200 | O75: Representation | P75: USD | Q75: 0 | R75: -114.6 | S75: 0 | T75: Current | U75: ext_vanessa.ortiz | V75: IPER | W75: REV | X75: CRITEO
A76: Sales - packing slip revenue | B76: 46078 | C76: MEDIAWISE S.A.C | D76: 20550082722 | G76: SOIPE-000007234, 20509867560, MEDIAWISE S.A.C | H76: SOIPE-000007234 | I76: 4101011200-Criteo-ALL-IPER-PER-Rep | J76: GJT169842 | K76: CI00011249 | L76: 46078 | M76: 4101011200-Criteo-ALL-IPER-PER-Rep | N76: 4101011200 | O76: Representation | P76: USD | Q76: 19100.01 | R76: 64347.93 | S76: 19100.01 | T76: Current | U76: ext_vanessa.ortiz | V76: IPER | W76: REV | X76: CRITEO
A77: Sales order revenue | B77: 46065 | C77: JOINNUS SAC | D77: 7YFI1MY30V | G77: SOIPE-000006663, 7YFI1MY30V, JOINNUS SAC | H77: SOIPE-000006663 | I77: 4101011200-Criteo-ALL-IPER-PER-Rep | J77: GJT168879 | K77: CI00011161 | L77: 46065 | M77: 4101011200-Criteo-ALL-IPER-PER-Rep | N77: 4101011200 | O77: Representation | P77: USD | Q77: -1800 | R77: -6053.4 | S77: -1800 | T77: Current | U77: roman.villanueva | V77: IPER | W77: REV | X77: CRITEO
A78: Sales order revenue | B78: 46065 | C78: JOINNUS SAC | D78: 7YFI1MY30V | G78: SOIPE-000006663, 7YFI1MY30V, JOINNUS SAC | H78: SOIPE-000006663 | I78: 4101011200-Criteo-ALL-IPER-PER-Rep | J78: GJT168879 | K78: CI00011161 | L78: 46065 | M78: 4101011200-Criteo-ALL-IPER-PER-Rep | N78: 4101011200 | O78: Representation | P78: USD | Q78: 0 | R78: 14.4 | S78: 0 | T78: Current | U78: roman.villanueva | V78: IPER | W78: REV | X78: CRITEO
A79: Sales - packing slip revenue | B79: 46065 | C79: JOINNUS SAC | D79: 7YFI1MY30V | G79: SOIPE-000006663, 7YFI1MY30V, JOINNUS SAC | H79: SOIPE-000006663 | I79: 4101011200-Criteo-ALL-IPER-PER-Rep | J79: GJT168879 | K79: CI00011161 | L79: 46065 | M79: 4101011200-Criteo-ALL-IPER-PER-Rep | N79: 4101011200 | O79: Representation | P79: USD | Q79: 1800 | R79: 6039 | S79: 1800 | T79: Current | U79: roman.villanueva | V79: IPER | W79: REV | X79: CRITEO
A80: Sales order revenue | B80: 46065 | C80: CONFEDERACION DE DESARROLLADORES INMOBILIARIOS DEL PERU- CODIP | D80: VRK905HFAA | G80: SOIPE-000003676, VRK905HFAA, CONFEDERACION DE DESARROLLADORES INMOBILIARIOS DEL PERU- CODIP | H80: SOIPE-000003676 | I80: 4101011200-Criteo-ALL-IPER-PER-Rep | J80: GJT168878 | K80: CI00011160 | L80: 46065 | M80: 4101011200-Criteo-ALL-IPER-PER-Rep | N80: 4101011200 | O80: Representation | P80: USD | Q80: -4699.94 | R80: -15805.9 | S80: -4699.94 | T80: Current | U80: roman.villanueva | V80: IPER | W80: REV | X80: CRITEO
A81: Sales order revenue | B81: 46065 | C81: CONFEDERACION DE DESARROLLADORES INMOBILIARIOS DEL PERU- CODIP | D81: VRK905HFAA | G81: SOIPE-000003676, VRK905HFAA, CONFEDERACION DE DESARROLLADORES INMOBILIARIOS DEL PERU- CODIP | H81: SOIPE-000003676 | I81: 4101011200-Criteo-ALL-IPER-PER-Rep | J81: GJT168878 | K81: CI00011160 | L81: 46065 | M81: 4101011200-Criteo-ALL-IPER-PER-Rep | N81: 4101011200 | O81: Representation | P81: USD | Q81: 0 | R81: 37.6 | S81: 0 | T81: Current | U81: roman.villanueva | V81: IPER | W81: REV | X81: CRITEO
A82: Sales - packing slip revenue | B82: 46065 | C82: CONFEDERACION DE DESARROLLADORES INMOBILIARIOS DEL PERU- CODIP | D82: VRK905HFAA | G82: SOIPE-000003676, VRK905HFAA, CONFEDERACION DE DESARROLLADORES INMOBILIARIOS DEL PERU- CODIP | H82: SOIPE-000003676 | I82: 4101011200-Criteo-ALL-IPER-PER-Rep | J82: GJT168878 | K82: CI00011160 | L82: 46065 | M82: 4101011200-Criteo-ALL-IPER-PER-Rep | N82: 4101011200 | O82: Representation | P82: USD | Q82: 4699.94 | R82: 15768.3 | S82: 4699.94 | T82: Current | U82: roman.villanueva | V82: IPER | W82: REV | X82: CRITEO
A83: Sales order revenue | B83: 46065 | C83: NESSUS HOTELES PERU SA | D83: 20505670443 | G83: SOIPE-000003641, 20505670443, NESSUS HOTELES PERU SA | H83: SOIPE-000003641 | I83: 4101011200-Criteo-ALL-IPER-PER-Rep | J83: GJT168876 | K83: CI00011158 | L83: 46065 | M83: 4101011200-Criteo-ALL-IPER-PER-Rep | N83: 4101011200 | O83: Representation | P83: USD | Q83: -2996.87 | R83: -10078.47 | S83: -2996.87 | T83: Current | U83: roman.villanueva | V83: IPER | W83: REV | X83: CRITEO
A84: Sales order revenue | B84: 46065 | C84: NESSUS HOTELES PERU SA | D84: 20505670443 | G84: SOIPE-000003641, 20505670443, NESSUS HOTELES PERU SA | H84: SOIPE-000003641 | I84: 4101011200-Criteo-ALL-IPER-PER-Rep | J84: GJT168876 | K84: CI00011158 | L84: 46065 | M84: 4101011200-Criteo-ALL-IPER-PER-Rep | N84: 4101011200 | O84: Representation | P84: USD | Q84: 0 | R84: 23.97 | S84: 0 | T84: Current | U84: roman.villanueva | V84: IPER | W84: REV | X84: CRITEO
A85: Sales - packing slip revenue | B85: 46065 | C85: NESSUS HOTELES PERU SA | D85: 20505670443 | G85: SOIPE-000003641, 20505670443, NESSUS HOTELES PERU SA | H85: SOIPE-000003641 | I85: 4101011200-Criteo-ALL-IPER-PER-Rep | J85: GJT168876 | K85: CI00011158 | L85: 46065 | M85: 4101011200-Criteo-ALL-IPER-PER-Rep | N85: 4101011200 | O85: Representation | P85: USD | Q85: 2996.87 | R85: 10054.5 | S85: 2996.87 | T85: Current | U85: roman.villanueva | V85: IPER | W85: REV | X85: CRITEO
... A91: Sales - packing slip revenue | B91: 46057 | C91: MEDIAWISE S.A.C | D91: 20550082722 | G91: SOIPE-000007234, 20509867560, MEDIAWISE S.A.C | H91: SOIPE-000007234 | I91: 4101011200-Criteo-ALL-IPER-PER-Rep | J91: GJT167265 | K91: CI00011054 | L91: 46057 | M91: 4101011200-Criteo-ALL-IPER-PER-Rep | N91: 4101011200 | O91: Representation | P91: USD | Q91: 12057.38 | R91: 40609.26 | S91: 12057.38 | T91: Current | U91: ext_vanessa.ortiz | V91: IPER | W91: REV | X91: CRITEO
A92: Sales - packing slip revenue | B92: 46081 | G92: SOIES-000001011, 132407865 | H92: SOIES-000001011 | I92: 4101011200-Criteo-ALL-IESP-ARG-Rep | J92: GJT057009 | K92: PS002010 | L92: 46081 | M92: 4101011200-Criteo-ALL-IESP-ARG-Rep | N92: 4101011200 | O92: Representation | P92: USD | Q92: -30985.86 | R92: -26248.08 | S92: -30985.86 | T92: Current | U92: daniela.alonso | V92: IESP | W92: REV | X92: CRITEO
A93: Sales - packing slip revenue | B93: 46081 | G93: SOIUS-000002996, M15000002947 | H93: SOIUS-000002996 | I93: 4101011200-Criteo-ALL-IUSA-COL-Rep | J93: GJT074456 | K93: PS005445 | L93: 46081 | M93: 4101011200-Criteo-ALL-IUSA-COL-Rep | N93: 4101011200 | O93: Representation | P93: USD | Q93: -2955.09 | R93: -2955.09 | S93: -2955.09 | T93: Current | U93: daniela.alonso | V93: IUSA | W93: REV | X93: CRITEO
A94: Sales - packing slip revenue | B94: 46081 | G94: SOIUS-000002116, NDG0RNDCWW | H94: SOIUS-000002116 | I94: 4101011200-Criteo-ALL-IUSA-PER-Rep | J94: GJT074448 | K94: PS005437 | L94: 46081 | M94: 4101011200-Criteo-ALL-IUSA-PER-Rep | N94: 4101011200 | O94: Representation | P94: USD | Q94: -1998.87 | R94: -1998.87 | S94: -1998.87 | T94: Current | U94: daniela.alonso | V94: IUSA | W94: REV | X94: CRITEO
A95: Sales order revenue | B95: 46063 | C95: AP LATAM HOLDINGS, LLC | D95: NDG0RNDCWW | G95: SOIUS-000002116, NDG0RNDCWW, AP LATAM HOLDINGS, LLC | H95: SOIUS-000002116 | I95: 4101011200-Criteo-ALL-IUSA-PER-Rep | J95: GJT072614 | K95: IUSA_CI_00004598 | L95: 46063 | M95: 4101011200-Criteo-ALL-IUSA-PER-Rep | N95: 4101011200 | O95: Representation | P95: USD | Q95: -1999.76 | R95: -1999.76 | S95: -1999.76 | T95: Current | U95: antonio.ynurrigarro | V95: IUSA | W95: REV | X95: CRITEO
A96: Sales - packing slip revenue | B96: 46063 | C96: AP LATAM HOLDINGS, LLC | D96: NDG0RNDCWW | G96: SOIUS-000002116, NDG0RNDCWW, AP LATAM HOLDINGS, LLC | H96: SOIUS-000002116 | I96: 4101011200-Criteo-ALL-IUSA-PER-Rep | J96: GJT072614 | K96: IUSA_CI_00004598 | L96: 46063 | M96: 4101011200-Criteo-ALL-IUSA-PER-Rep | N96: 4101011200 | O96: Representation | P96: USD | Q96: 1999.76 | R96: 1999.76 | S96: 1999.76 | T96: Current | U96: antonio.ynurrigarro | V96: IUSA | W96: REV | X96: CRITEO

Sheet SAP
A1: Company Code | B1: Posting Date | C1: Customer | D1: Name of Customer | E1: Sales Document | F1: Purchasing Document | G1: G/L Account | H1: WBS Element | I1: Transaction Currency | J1: Amount in Transaction Currency | K1: Company Code Currency | L1: Amount in Company Code Currency | M1: Amount in Global Currency | N1: Assignment Reference | O1: Journal Entry | P1: Journal Entry Type | Q1: Posting Key | R1: Tax Code | S1: Clearing Journal Entry | T1: Profit Center | U1: Segment | V1: Journal Entry Item Text | W1: Number of Items | X1: Creation Date Time (UTC) | Y1: Journal Entry Created By | Z1: Functional Area

Sheet ERP VS SF
B1: ERP | C1: CRM AD | E1: CRM PREV_M | F1: ∆ | K1: ERP | L1: CRM AD | N1: CRM PREV_M | O1: ∆
A2: SOICO-000004001 | B2: =SUMIF(ERP!H:H,A2,ERP!Q:Q)+SUMIF(SAP!E:E,A2,SAP!J:J) -> -7953137.5 | C2: =SUMIF(Salesforce!AW:AW,A2,Salesforce!AM:AM) -> 7953137.5 | E2: =SUMIF(CRM_PREV_M!AV:AV,A2,CRM_PREV_M!AL:AL) -> 0 | F2: =B2+C2+E2+D2 -> 0 | J2: POIME-000032936 | K2: =SUMIF(ERP!H:H,J2,ERP!Q:Q) -> 379.94 | L2: =SUMIFS(Salesforce!AO:AO,Salesforce!AY:AY,J2) -> 379.94 | N2: =SUMIF(CRM_PREV_M!AX:AX,J2,CRM_PREV_M!AN:AN) -> 0 | O2: =K2-L2-N2-M2 -> 0
A3: SOIPE-000010278 | B3: =SUMIF(ERP!H:H,A3,ERP!Q:Q)+SUMIF(SAP!E:E,A3,SAP!J:J) -> -3000 | C3: =SUMIF(Salesforce!AW:AW,A3,Salesforce!AM:AM) -> 3000 | E3: =SUMIF(CRM_PREV_M!AV:AV,A3,CRM_PREV_M!AL:AL) -> 0 | F3: =B3+C3+E3+D3 -> 0 | J3: POIME-000032934 | K3: =SUMIF(ERP!H:H,J3,ERP!Q:Q) -> 180.05 | L3: =SUMIFS(Salesforce!AO:AO,Salesforce!AY:AY,J3) -> 180.05 | N3: =SUMIF(CRM_PREV_M!AX:AX,J3,CRM_PREV_M!AN:AN) -> 0 | O3: =K3-L3-N3-M3 -> 0
A4: SOIPE-000010277 | B4: =SUMIF(ERP!H:H,A4,ERP!Q:Q)+SUMIF(SAP!E:E,A4,SAP!J:J) -> -993 | C4: =SUMIF(Salesforce!AW:AW,A4,Salesforce!AM:AM) -> 993 | E4: =SUMIF(CRM_PREV_M!AV:AV,A4,CRM_PREV_M!AL:AL) -> 0 | F4: =B4+C4+E4+D4 -> 0 | J4: POIME-000032930 | K4: =SUMIF(ERP!H:H,J4,ERP!Q:Q) -> 30985.86 | L4: =SUMIFS(Salesforce!AO:AO,Salesforce!AY:AY,J4) -> 30985.86 | N4: =SUMIF(CRM_PREV_M!AX:AX,J4,CRM_PREV_M!AN:AN) -> 0 | O4: =K4-L4-N4-M4 -> 0
A5: SOIPE-000010276 | B5: =SUMIF(ERP!H:H,A5,ERP!Q:Q)+SUMIF(SAP!E:E,A5,SAP!J:J) -> -6300 | C5: =SUMIF(Salesforce!AW:AW,A5,Salesforce!AM:AM) -> 6300 | E5: =SUMIF(CRM_PREV_M!AV:AV,A5,CRM_PREV_M!AL:AL) -> 0 | F5: =B5+C5+E5+D5 -> 0 | J5: POIME-000032928 | K5: =SUMIF(ERP!H:H,J5,ERP!Q:Q) -> 5184.83 | L5: =SUMIFS(Salesforce!AO:AO,Salesforce!AY:AY,J5) -> 5184.83 | N5: =SUMIF(CRM_PREV_M!AX:AX,J5,CRM_PREV_M!AN:AN) -> 0 | O5: =K5-L5-N5-M5 -> 0
A6: SOIPE-000010275 | B6: =SUMIF(ERP!H:H,A6,ERP!Q:Q)+SUMIF(SAP!E:E,A6,SAP!J:J) -> -2771.71 | C6: =SUMIF(Salesforce!AW:AW,A6,Salesforce!AM:AM) -> 2771.71 | E6: =SUMIF(CRM_PREV_M!AV:AV,A6,CRM_PREV_M!AL:AL) -> 0 | F6: =B6+C6+E6+D6 -> 0 | J6: POIME-000032919 | K6: =SUMIF(ERP!H:H,J6,ERP!Q:Q) -> 6300 | L6: =SUMIFS(Salesforce!AO:AO,Salesforce!AY:AY,J6) -> 6300 | N6: =SUMIF(CRM_PREV_M!AX:AX,J6,CRM_PREV_M!AN:AN) -> 0 | O6: =K6-L6-N6-M6 -> 0
A7: SOIPE-000010274 | B7: =SUMIF(ERP!H:H,A7,ERP!Q:Q)+SUMIF(SAP!E:E,A7,SAP!J:J) -> -848.2 | C7: =SUMIF(Salesforce!AW:AW,A7,Salesforce!AM:AM) -> 848.2 | E7: =SUMIF(CRM_PREV_M!AV:AV,A7,CRM_PREV_M!AL:AL) -> 0 | F7: =B7+C7+E7+D7 -> 0 | J7: POIME-000032918 | K7: =SUMIF(ERP!H:H,J7,ERP!Q:Q) -> 848.2 | L7: =SUMIFS(Salesforce!AO:AO,Salesforce!AY:AY,J7) -> 848.2 | N7: =SUMIF(CRM_PREV_M!AX:AX,J7,CRM_PREV_M!AN:AN) -> 0 | O7: =K7-L7-N7-M7 -> 0
A8: SOIPE-000010273 | B8: =SUMIF(ERP!H:H,A8,ERP!Q:Q)+SUMIF(SAP!E:E,A8,SAP!J:J) -> -5184.83 | C8: =SUMIF(Salesforce!AW:AW,A8,Salesforce!AM:AM) -> 5184.83 | E8: =SUMIF(CRM_PREV_M!AV:AV,A8,CRM_PREV_M!AL:AL) -> 0 | F8: =B8+C8+E8+D8 -> 0 | J8: POIME-000032917 | K8: =SUMIF(ERP!H:H,J8,ERP!Q:Q) -> 2771.71 | L8: =SUMIFS(Salesforce!AO:AO,Salesforce!AY:AY,J8) -> 2771.71 | N8: =SUMIF(CRM_PREV_M!AX:AX,J8,CRM_PREV_M!AN:AN) -> 0 | O8: =K8-L8-N8-M8 -> 0
A9: SOIPE-000010272 | B9: =SUMIF(ERP!H:H,A9,ERP!Q:Q)+SUMIF(SAP!E:E,A9,SAP!J:J) -> -180.05 | C9: =SUMIF(Salesforce!AW:AW,A9,Salesforce!AM:AM) -> 180.05 | E9: =SUMIF(CRM_PREV_M!AV:AV,A9,CRM_PREV_M!AL:AL) -> 0 | F9: =B9+C9+E9+D9 -> 0 | J9: POIME-000032905 | K9: =SUMIF(ERP!H:H,J9,ERP!Q:Q) -> 2000 | L9: =SUMIFS(Salesforce!AO:AO,Salesforce!AY:AY,J9) -> 2000 | N9: =SUMIF(CRM_PREV_M!AX:AX,J9,CRM_PREV_M!AN:AN) -> 0 | O9: =K9-L9-N9-M9 -> 0
A10: SOIPE-000010271 | B10: =SUMIF(ERP!H:H,A10,ERP!Q:Q)+SUMIF(SAP!E:E,A10,SAP!J:J) -> -379.94 | C10: =SUMIF(Salesforce!AW:AW,A10,Salesforce!AM:AM) -> 379.94 | E10: =SUMIF(CRM_PREV_M!AV:AV,A10,CRM_PREV_M!AL:AL) -> 0 | F10: =B10+C10+E10+D10 -> 0 | J10: POIME-000032904 | K10: =SUMIF(ERP!H:H,J10,ERP!Q:Q) -> 3000 | L10: =SUMIFS(Salesforce!AO:AO,Salesforce!AY:AY,J10) -> 3000 | N10: =SUMIF(CRM_PREV_M!AX:AX,J10,CRM_PREV_M!AN:AN) -> 0 | O10: =K10-L10-N10-M10 -> 0
A11: SOIPE-000010270 | B11: =SUMIF(ERP!H:H,A11,ERP!Q:Q)+SUMIF(SAP!E:E,A11,SAP!J:J) -> -2991.08 | C11: =SUMIF(Salesforce!AW:AW,A11,Salesforce!AM:AM) -> 2991.08 | E11: =SUMIF(CRM_PREV_M!AV:AV,A11,CRM_PREV_M!AL:AL) -> 0 | F11: =B11+C11+E11+D11 -> 0 | J11: POIME-000032902 | K11: =SUMIF(ERP!H:H,J11,ERP!Q:Q) -> 2065.75 | L11: =SUMIFS(Salesforce!AO:AO,Salesforce!AY:AY,J11) -> 2065.75 | N11: =SUMIF(CRM_PREV_M!AX:AX,J11,CRM_PREV_M!AN:AN) -> 0 | O11: =K11-L11-N11-M11 -> 0
A12: SOIPE-000010269 | B12: =SUMIF(ERP!H:H,A12,ERP!Q:Q)+SUMIF(SAP!E:E,A12,SAP!J:J) -> -2398.79 | C12: =SUMIF(Salesforce!AW:AW,A12,Salesforce!AM:AM) -> 2398.79 | E12: =SUMIF(CRM_PREV_M!AV:AV,A12,CRM_PREV_M!AL:AL) -> 0 | F12: =B12+C12+E12+D12 -> 0 | J12: POIME-000032898 | K12: =SUMIF(ERP!H:H,J12,ERP!Q:Q) -> 993 | L12: =SUMIFS(Salesforce!AO:AO,Salesforce!AY:AY,J12) -> 993 | N12: =SUMIF(CRM_PREV_M!AX:AX,J12,CRM_PREV_M!AN:AN) -> 0 | O12: =K12-L12-N12-M12 -> 0
A13: SOIPE-000010268 | B13: =SUMIF(ERP!H:H,A13,ERP!Q:Q)+SUMIF(SAP!E:E,A13,SAP!J:J) -> -2500 | C13: =SUMIF(Salesforce!AW:AW,A13,Salesforce!AM:AM) -> 2500 | E13: =SUMIF(CRM_PREV_M!AV:AV,A13,CRM_PREV_M!AL:AL) -> 0 | F13: =B13+C13+E13+D13 -> 0 | J13: POIME-000032897 | K13: =SUMIF(ERP!H:H,J13,ERP!Q:Q) -> 998.79 | L13: =SUMIFS(Salesforce!AO:AO,Salesforce!AY:AY,J13) -> 998.79 | N13: =SUMIF(CRM_PREV_M!AX:AX,J13,CRM_PREV_M!AN:AN) -> 0 | O13: =K13-L13-N13-M13 -> 0
... A30: SOIPE-000008334 | B30: =SUMIF(ERP!H:H,A30,ERP!Q:Q)+SUMIF(SAP!E:E,A30,SAP!J:J) -> -1999.95 | C30: =SUMIF(Salesforce!AW:AW,A30,Salesforce!AM:AM) -> 1999.95 | E30: =SUMIF(CRM_PREV_M!AV:AV,A30,CRM_PREV_M!AL:AL) -> 0 | F30: =B30+C30+E30+D30 -> 2.2737368e-13 | J30: POIME-000016807 | K30: =SUMIF(ERP!H:H,J30,ERP!Q:Q) -> 3699.53 | L30: =SUMIFS(Salesforce!AO:AO,Salesforce!AY:AY,J30) -> 3699.53 | N30: =SUMIF(CRM_PREV_M!AX:AX,J30,CRM_PREV_M!AN:AN) -> 0 | O30: =K30-L30-N30-M30 -> 0
A31: SOIPE-000009862 | B31: =SUMIF(ERP!H:H,A31,ERP!Q:Q)+SUMIF(SAP!E:E,A31,SAP!J:J) -> -912.96 | C31: =SUMIF(Salesforce!AW:AW,A31,Salesforce!AM:AM) -> 912.96 | E31: =SUMIF(CRM_PREV_M!AV:AV,A31,CRM_PREV_M!AL:AL) -> 0 | F31: =B31+C31+E31+D31 -> 0
A32: SOIPE-000009862 | B32: =SUMIF(ERP!H:H,A32,ERP!Q:Q)+SUMIF(SAP!E:E,A32,SAP!J:J) -> -912.96 | C32: =SUMIF(Salesforce!AW:AW,A32,Salesforce!AM:AM) -> 912.96 | E32: =SUMIF(CRM_PREV_M!AV:AV,A32,CRM_PREV_M!AL:AL) -> 0 | F32: =B32+C32+E32+D32 -> 0
A33: SOIPE-000009862 | B33: =SUMIF(ERP!H:H,A33,ERP!Q:Q)+SUMIF(SAP!E:E,A33,SAP!J:J) -> -912.96 | C33: =SUMIF(Salesforce!AW:AW,A33,Salesforce!AM:AM) -> 912.96 | E33: =SUMIF(CRM_PREV_M!AV:AV,A33,CRM_PREV_M!AL:AL) -> 0 | F33: =B33+C33+E33+D33 -> 0
A34: SOIPE-000003676 | B34: =SUMIF(ERP!H:H,A34,ERP!Q:Q)+SUMIF(SAP!E:E,A34,SAP!J:J) -> -4773.92 | C34: =SUMIF(Salesforce!AW:AW,A34,Salesforce!AM:AM) -> 4773.92 | E34: =SUMIF(CRM_PREV_M!AV:AV,A34,CRM_PREV_M!AL:AL) -> 0 | F34: =B34+C34+E34+D34 -> -9.094947e-13
A35: SOIPE-000003676 | B35: =SUMIF(ERP!H:H,A35,ERP!Q:Q)+SUMIF(SAP!E:E,A35,SAP!J:J) -> -4773.92 | C35: =SUMIF(Salesforce!AW:AW,A35,Salesforce!AM:AM) -> 4773.92 | E35: =SUMIF(CRM_PREV_M!AV:AV,A35,CRM_PREV_M!AL:AL) -> 0 | F35: =B35+C35+E35+D35 -> -9.094947e-13
A36: SOIPE-000003676 | B36: =SUMIF(ERP!H:H,A36,ERP!Q:Q)+SUMIF(SAP!E:E,A36,SAP!J:J) -> -4773.92 | C36: =SUMIF(Salesforce!AW:AW,A36,Salesforce!AM:AM) -> 4773.92 | E36: =SUMIF(CRM_PREV_M!AV:AV,A36,CRM_PREV_M!AL:AL) -> 0 | F36: =B36+C36+E36+D36 -> -9.094947e-13
A37: SOIPE-000003676 | B37: =SUMIF(ERP!H:H,A37,ERP!Q:Q)+SUMIF(SAP!E:E,A37,SAP!J:J) -> -4773.92 | C37: =SUMIF(Salesforce!AW:AW,A37,Salesforce!AM:AM) -> 4773.92 | E37: =SUMIF(CRM_PREV_M!AV:AV,A37,CRM_PREV_M!AL:AL) -> 0 | F37: =B37+C37+E37+D37 -> -9.094947e-13
A38: SOIPE-000003676 | B38: =SUMIF(ERP!H:H,A38,ERP!Q:Q)+SUMIF(SAP!E:E,A38,SAP!J:J) -> -4773.92 | C38: =SUMIF(Salesforce!AW:AW,A38,Salesforce!AM:AM) -> 4773.92 | E38: =SUMIF(CRM_PREV_M!AV:AV,A38,CRM_PREV_M!AL:AL) -> 0 | F38: =B38+C38+E38+D38 -> -9.094947e-13
A39: SOIPE-000003676 | B39: =SUMIF(ERP!H:H,A39,ERP!Q:Q)+SUMIF(SAP!E:E,A39,SAP!J:J) -> -4773.92 | C39: =SUMIF(Salesforce!AW:AW,A39,Salesforce!AM:AM) -> 4773.92 | E39: =SUMIF(CRM_PREV_M!AV:AV,A39,CRM_PREV_M!AL:AL) -> 0 | F39: =B39+C39+E39+D39 -> -9.094947e-13
A40: SOIPE-000003676 | B40: =SUMIF(ERP!H:H,A40,ERP!Q:Q)+SUMIF(SAP!E:E,A40,SAP!J:J) -> -4773.92 | C40: =SUMIF(Salesforce!AW:AW,A40,Salesforce!AM:AM) -> 4773.92 | E40: =SUMIF(CRM_PREV_M!AV:AV,A40,CRM_PREV_M!AL:AL) -> 0 | F40: =B40+C40+E40+D40 -> -9.094947e-13
A41: SOIPE-000003676 | B41: =SUMIF(ERP!H:H,A41,ERP!Q:Q)+SUMIF(SAP!E:E,A41,SAP!J:J) -> -4773.92 | C41: =SUMIF(Salesforce!AW:AW,A41,Salesforce!AM:AM) -> 4773.92 | E41: =SUMIF(CRM_PREV_M!AV:AV,A41,CRM_PREV_M!AL:AL) -> 0 | F41: =B41+C41+E41+D41 -> -9.094947e-13
A42: SOIPE-000003676 | B42: =SUMIF(ERP!H:H,A42,ERP!Q:Q)+SUMIF(SAP!E:E,A42,SAP!J:J) -> -4773.92 | C42: =SUMIF(Salesforce!AW:AW,A42,Salesforce!AM:AM) -> 4773.92 | E42: =SUMIF(CRM_PREV_M!AV:AV,A42,CRM_PREV_M!AL:AL) -> 0 | F42: =B42+C42+E42+D42 -> -9.094947e-13
... A67: SOIUS-000002116 | B67: =SUMIF(ERP!H:H,A67,ERP!Q:Q)+SUMIF(SAP!E:E,A67,SAP!J:J) -> -1998.87 | C67: =SUMIF(Salesforce!AW:AW,A67,Salesforce!AM:AM) -> 1998.87 | E67: =SUMIF(CRM_PREV_M!AV:AV,A67,CRM_PREV_M!AL:AL) -> 0 | F67: =B67+C67+E67+D67 -> -2.2737368e-13

Sheet CRM_PREV_M
A1: Year | B1: Line Month | C1: Posting Period | D1: Finance Date | E1: Salesforce Project Number | F1: Line ID | G1: Project : Opportunity : Aleph Campaign ID | H1: Line Product Number | I1: Type of Line | J1: Status | K1: Order Line Status | L1: Company Name (Know as + Country) | M1: Company To Invoice Legal Name | N1: Vendor | O1: Product Business Unit | P1: Reporting Country | Q1: Billing Country | R1: Delivery Country | S1: Billing Entity | T1: Purchase Country | U1: Product | V1: Sales UOM | W1: Purchase UOM | X1: Billing Currency | Y1: Purchase Currency | Z1: Publisher PO ID | AA1: Qualified Sales Quantity | AB1: Qualified Purchase Quantity | AC1: Gross Discounted | AD1: Gross Sales Price | AE1: Net Sales Price | AF1: Gross Purchase Price | AG1: Net Purchase Price | AH1: Client Discount | AI1: Agency Commission | AJ1: Delivered Sales Quantity | AK1: Delivered Purchase Quantity | AL1: Net Budget Delivered (Billing Currency) | AM1: Net Cost Delivered (Buying Currency) | AN1: Net Cost Delivered w/o Tax (Buying Curr) | AO1: Activation Exchange Rate | AP1: Total Net Budget (Delivered) (converted) | AQ1: Total Net Cost (Delivered) (converted) | AR1: Margin Delivered (Billing Currency) | AS1: Margin Amount (Delivered) | AT1: Margin Amount (Delivered) (converted) | AU1: Margin % (Delivered) | AV1: Sales Order Number | AW1: SO Status | AX1: Purchase Order Number | AY1: PO Status | AZ1: Invoice Description | BA1: Line Description | BB1: Purchase Entity | BC1: Billing Exchange Rate | BD1: Project Name | BE1: Company to invoice | BF1: Company To Invoice Tax Id | BG1: Sales Manager | BH1: Trade Deal | BI1: Branding/Performance | BJ1: Sales Channel | BK1: End Date | BL1: Project : Company to invoice : Payment condition | BM1: Rev. Act. FX / Closing FX

Sheet Billing_Rev
A4: Billing Entity | B4: Type of Line | C4: Sales Order Number | D4: Company To Invoice Tax Id | E4: Company To Invoice Legal Name | F4: Salesforce Project Number | G4: Project Name | H4: Billing Currency | I4: Billing Exchange Rate | J4: Suma de Net Budget Delivered (Billing Currency)
A5: Aleph USA | B5: Standard | C5: SOIUS-000002116 | D5: 815181325 | E5: AP LATAM HOLDINGS, LLC | F5: 00265916 | G5: PE_USMP_CRITEO_MAYO 2025 | H5: USD | I5: 1 | J5: 1998.87
A6: Aleph USA | B6: Standard | C6: SOIUS-000002996 | D6: 204031493 | E6: Group M Worldwide LLC DBA EssenceMediacom Miami | F6: 00327517 | G6: COL_CRITEO_MEDIACOM MIAMI_SONY ALON_FEBRERO 2026 | H6: USD | I6: 1 | J6: 288.47
A7: Aleph Peru | B7: Standard | C7: SOIPE-000007234 | D7: 20509867560 | E7: QUAL MEDIA S.A.C. | F7: 00289572 | G7: PE_CRITEO_UCSUR_JUNIO 2025 | H7: USD | I7: 1 | J7: 16105.49
A8: Aleph Peru | B8: Standard | C8: SOIPE-000006663 | D8: 20555387785 | E8: JOINNUS SAC | F8: 00270878 | G8: PE_JOINNUS_CRITEO_MAYO 2025 | H8: USD | I8: 1 | J8: 1800
A9: Aleph Peru | B9: Standard | C9: SOIPE-000008334 | D9: 20606271744 | E9: Media Analytics S.A.C. | F9: 00295095 | G9: PE_CRITEO_PC FACTORY JULIO 2025 | H9: USD | I9: 1 | J9: 1999.95
A10: Aleph Peru | B10: Standard | C10: SOIPE-000003644 | D10: 20509867560 | E10: QUAL MEDIA S.A.C. | F10: 00240205 | G10: PE_CRITEO_PACIFICO SEGUROS_2025_MAYO | H10: USD | I10: 1 | J10: 3699.53
A11: Aleph Peru | B11: Standard | C11: SOIPE-000003676 | D11: 20552213832 | E11: CONFEDERACION DE DESARROLLADORES INMOBILIARIOS DEL PERU- CODIP | F11: 00246193 | G11: PE_ASEI NEXO_CRITEO_ABRIL MAYO 2025 | H11: USD | I11: 1 | J11: 4773.92
A12: Aleph Peru | B12: Standard | C12: SOIPE-000003641 | D12: 20505670443 | E12: NESSUS HOTELES PERU S.A. | F12: 00240223 | G12: PE_CRITEO_CASA ANDINA_2025_MAYO | H12: USD | I12: 1 | J12: 2986.68
A13: Aleph Peru | B13: Standard | C13: SOIPE-000009862 | D13: 20606271744 | E13: Media Analytics S.A.C. | F13: 00314444 | G13: Criteo_NOV25_Oncosalud PE | H13: USD | I13: 1 | J13: 912.96
A14: Aleph Peru | B14: Standard | C14: SOIPE-000010171 | D14: 20509867560 | E14: QUAL MEDIA S.A.C. | F14: 00324209 | G14: PE - CRITEO - OMD - BCP - ENE - 2026 | H14: USD | I14: 1 | J14: 9029.13
A15: Aleph Peru | B15: Standard | C15: SOIPE-000010175 | D15: 20608280333 | E15: COMPAÑIA HARD DISCOUNT S.A.C. | F15: 00324625 | G15: PE_CRITEO_TIENDAS MASS_ENE 2026 | H15: USD | I15: 1 | J15: 1027.45
A16: Aleph Peru | B16: Standard | C16: SOIPE-000010176 | D16: 20606271744 | E16: Media Analytics S.A.C. | F16: 00326928 | G16: PE_CRITEO_DIVEMOTOR ENE 2026 | H16: USD | I16: 1 | J16: 999.97
... A34: Aleph Spain | B34: Standard | C34: SOIES-000001011 | D34: 131094376 | E34: Arajet S.A. | F34: 00331315 | G34: AR_CRITEO_ARAJET_FEB_2026 | H34: USD | I34: 1 | J34: 1497.88

Sheet Interco
H1: Advertisement cost- Criteo - 2026-02 | L1: Advertisement fee- Criteo - Dec2025 | P1: INT COGS CRITEO FEB26
C2: Order Line Status | D2: (Todas) | H2: MEXICO
C3: Type of Line | D3: Standard
C5: Purchase Entity | D5: Billing Entity | E5: Product Business Unit | F5: Suma de Rev. Act. FX / Closing FX | G5: Suma de COGS Act. FX / Closing FX | H5: Comm. | I5: Net COGS | J5: Net Revenue | K5: Margin | L5: SF | M5: IO | N5: PO | P5: Supply Deal
C6: Aleph Mexico | D6: Aleph Peru | E6: Criteo | F6: 84166.36 | G6: 84126.5 | H6: 0.12 | I6: =G6*(1-H6) -> 74031.32 | J6: =F6-I6 -> 10135.04 | K6: =J6/F6 -> 0.12041676 | M6: SOIME-000003598 | N6: POIPE-000001099 | O6: CRE1-GRW-SAL-LOCL-CT
C7: Aleph Mexico | D7: Aleph Colombia | E7: Criteo | F7: 2111.658 | G7: 2065.75
C8: Aleph Mexico | D8: Aleph USA | E8: Criteo | F8: 2287.34 | G8: 2287.34
C9: Aleph Mexico | D9: Aleph Spain | E9: Criteo | F9: 1497.88 | G9: 1497.88
C10: Total general | F10: 90063.238 | G10: 89977.47
